Workbook

Sheet FINACHIAL REPORT
A1: RWVCA REPORT DATE ….........
A2: RWANDA WOOD VALUE CHAIN ASSOCIATION
A4: ICPCs NAME | B4: TVA IN | C4: MSF IN | D4: MS REGIS | E4: MS CONTR | F4: TVA+MSF | G4: FR NOT INVOICED | H4: MOMO | I4: PAID ON BANK | J4: CASH
A5: GISOZI | B5: =GISOZI!F37 -> 0 | C5: =GISOZI!G37 -> 0 | D5: =GISOZI!C43 -> 0 | E5: =GISOZI!C44 -> 0 | F5: =SUM(B5:C5) -> 0 | G5: =GISOZI!C41 -> 0 | H5: =GISOZI!C39 -> 0 | I5: =GISOZI!C42 -> 0 | J5: =GISOZI!C40 -> 0
A6: GAHANGA | B6: =GAHANGA!F37 -> 0 | C6: =GAHANGA!G37 -> 0 | D6: =GAHANGA!C43 -> 0 | E6: =GAHANGA!C44 -> 0 | F6: =SUM(B6:C6) -> 0 | G6: =GAHANGA!C41 -> 0 | H6: =GAHANGA!C39 -> 0 | I6: =GAHANGA!C42 -> 0 | J6: =GAHANGA!C40 -> 0
A7: KIMIROMKO | B7: =KIMIRONKO!F37 -> 0 | C7: =KIMIRONKO!G37 -> 0 | D7: =KIMIRONKO!C43 -> 0 | E7: =KIMIRONKO!C44 -> 0 | F7: =SUM(B7:C7) -> 0 | G7: =KIMIRONKO!C41 -> 0 | H7: =KIMIRONKO!C39 -> 0 | I7: =KIMIRONKO!C42 -> 0 | J7: =KIMIRONKO!C40 -> 0
A8: BISHENYI | B8: =BISHENYI!F37 -> 0 | C8: =BISHENYI!G37 -> 0 | D8: =BISHENYI!C43 -> 0 | E8: =BISHENYI!C44 -> 0 | F8: =SUM(B8:C8) -> 0 | G8: =BISHENYI!C41 -> 0 | H8: =BISHENYI!C39 -> 0 | I8: =BISHENYI!C42 -> 0 | J8: =BISHENYI!C40 -> 0
A9: RWAMAGANA | B9: =RWAMAGANA!F37 -> 12360231 | C9: =RWAMAGANA!G37 -> 1363010 | D9: =RWAMAGANA!C43 -> 50000 | E9: =RWAMAGANA!C44 -> 100000 | F9: =SUM(B9:C9) -> 13723241 | G9: =RWAMAGANA!C41 -> 0 | H9: =RWAMAGANA!C39 -> 13723241 | I9: =RWAMAGANA!C42 -> 0 | J9: =RWAMAGANA!C40 -> 0
A10: BUGESERA | B10: =BUGESERA!F37 -> 0 | C10: =BUGESERA!G37 -> 0 | D10: =BUGESERA!C43 -> 0 | E10: =BUGESERA!C44 -> 0 | F10: =SUM(B10:C10) -> 0 | G10: =BUGESERA!C41 -> 0 | H10: =BUGESERA!C39 -> 0 | I10: =BUGESERA!C42 -> 0 | J10: =BUGESERA!C40 -> 0
A11: MUHANGA | B11: =MUHANGA!F37 -> 0 | C11: =MUHANGA!G37 -> 0 | D11: =MUHANGA!C43 -> 0 | E11: =MUHANGA!C44 -> 0 | F11: =SUM(B11:C11) -> 0 | G11: =MUHANGA!C41 -> 0 | H11: =MUHANGA!C39 -> 0 | I11: =MUHANGA!C42 -> 0 | J11: =MUHANGA!C40 -> 0
A12: RUHANGO | B12: =RUHANGO!F37 -> 0 | C12: =RUHANGO!G37 -> 0 | D12: =RUHANGO!C43 -> 0 | E12: =RUHANGO!C44 -> 0 | F12: =SUM(B12:C12) -> 0 | G12: =RUHANGO!C41 -> 0 | H12: =RUHANGO!C39 -> 0 | I12: =RUHANGO!C42 -> 0 | J12: =RUHANGO!C40 -> 0
A13: HUYE | B13: =HUYE!F37 -> 251206.78 | C13: =HUYE!G37 -> 33000 | D13: =HUYE!C43 -> 0 | E13: =HUYE!C44 -> 0 | F13: =SUM(B13:C13) -> 284206.78 | G13: =HUYE!C41 -> 0 | H13: =HUYE!C39 -> 0 | I13: =HUYE!C42 -> 0 | J13: =HUYE!C40 -> 0
A14: RUSIZI | B14: =RUSIZI!F37 -> 0 | C14: =RUSIZI!G37 -> 0 | D14: =RUSIZI!C43 -> 0 | E14: =RUSIZI!C44 -> 0 | F14: =SUM(B14:C14) -> 0 | G14: =RUSIZI!C41 -> 0 | H14: =RUSIZI!C39 -> 0 | I14: =RUSIZI!C42 -> 0 | J14: =RUSIZI!C40 -> 0
A15: NYAMASHEKE | B15: =NYAMASHEKE!F37 -> 0 | C15: =NYAMASHEKE!G37 -> 0 | D15: =NYAMASHEKE!C43 -> 0 | E15: =NYAMASHEKE!C44 -> 0 | F15: =SUM(B15:C15) -> 0 | G15: =NYAMASHEKE!C41 -> 0 | H15: =NYAMASHEKE!C39 -> 0 | I15: =NYAMASHEKE!C42 -> 0 | J15: =NYAMASHEKE!C40 -> 0
A16: KARONGI | B16: =KARONGI!F37 -> 0 | C16: =KARONGI!G37 -> 0 | D16: =KARONGI!C43 -> 0 | E16: =KARONGI!C44 -> 0 | F16: =SUM(B16:C16) -> 0 | G16: =KARONGI!C41 -> 0 | H16: =KARONGI!C39 -> 0 | I16: =KARONGI!C42 -> 0 | J16: =KARONGI!C40 -> 0
A17: RUBAVU | B17: =RUBAVU!F37 -> 0 | C17: =RUBAVU!G37 -> 0 | D17: =RUBAVU!C43 -> 0 | E17: =RUBAVU!C44 -> 0 | F17: =SUM(B17:C17) -> 0 | G17: =RUBAVU!C41 -> 0 | H17: =RUBAVU!C39 -> 0 | I17: =RUBAVU!C42 -> 0 | J17: =RUBAVU!C40 -> 0
A18: MUSANZE | B18: =MUSANZE!F37 -> 0 | C18: =MUSANZE!G37 -> 0 | D18: =MUSANZE!C43 -> 0 | E18: =MUSANZE!C44 -> 0 | F18: =SUM(B18:C18) -> 0 | G18: =MUSANZE!C41 -> 0 | H18: =MUSANZE!C39 -> 0 | I18: =MUSANZE!C42 -> 0 | J18: =MUSANZE!C40 -> 0
A19: KAYONZA | B19: =KAYONZA!F37 -> 0 | C19: =KAYONZA!G37 -> 0 | D19: =KAYONZA!C43 -> 0 | E19: =KAYONZA!C44 -> 0 | F19: =SUM(B19:C19) -> 0 | G19: =KAYONZA!C41 -> 0 | H19: =KAYONZA!C39 -> 0 | I19: =KAYONZA!C42 -> 0 | J19: =KAYONZA!C40 -> 0
A20: NYAGATARE | B20: =NYAGATARE!F37 -> 0 | C20: =NYAGATARE!G37 -> 0 | D20: =NYAGATARE!C43 -> 0 | E20: =NYAGATARE!C44 -> 0 | F20: =SUM(B20:C20) -> 0 | G20: =NYAGATARE!C41 -> 0 | H20: =NYAGATARE!C39 -> 0 | I20: =NYAGATARE!C42 -> 0 | J20: =NYAGATARE!C40 -> 0
A21: KIREHE | B21: =KIREHE!F37 -> 0 | C21: =KIREHE!G37 -> 0 | D21: =KIREHE!C43 -> 0 | E21: =KIREHE!C44 -> 0 | F21: =SUM(B21:C21) -> 0 | G21: =KIREHE!C41 -> 0 | H21: =KIREHE!C39 -> 0 | I21: =KIREHE!C42 -> 0 | J21: =KIREHE!C40 -> 0
A22: NYANZA | B22: =NYANZA!F37 -> 0 | C22: =NYANZA!G37 -> 0 | D22: =NYANZA!C43 -> 0 | E22: =NYANZA!C44 -> 0 | F22: =SUM(B22:C22) -> 0 | G22: =NYANZA!C41 -> 0 | H22: =NYANZA!C39 -> 0 | I22: =NYANZA!C42 -> 0 | J22: =NYANZA!C40 -> 0
A23: NYARUGENGE | B23: =NYARUGENGE!F37 -> 0 | C23: =NYARUGENGE!G37 -> 0 | D23: =NYARUGENGE!C43 -> 0 | E23: =NYARUGENGE!C44 -> 0 | F23: =SUM(B23:C23) -> 0 | G23: =NYARUGENGE!C41 -> 0 | H23: =NYARUGENGE!C39 -> 0 | I23: =NYARUGENGE!C42 -> 0 | J23: =NYARUGENGE!C40 -> 0
A24: GATSIBO | B24: =GATSIBO!F37 -> 0 | C24: =GATSIBO!G37 -> 0 | D24: =GATSIBO!C43 -> 0 | E24: =GATSIBO!C44 -> 0 | F24: =SUM(B24:C24) -> 0 | G24: =GATSIBO!C41 -> 0 | H24: =GATSIBO!C39 -> 0 | I24: =GATSIBO!C42 -> 0 | J24: =GATSIBO!C40 -> 0
A25: GASHYUSHYA | B25: =GASHYUSHYA!F37 -> 0 | C25: =GASHYUSHYA!G37 -> 0 | D25: =GASHYUSHYA!C43 -> 0 | E25: =GASHYUSHYA!C44 -> 0 | F25: =SUM(B25:C25) -> 0 | G25: =GASHYUSHYA!C41 -> 0 | H25: =GASHYUSHYA!C39 -> 0 | I25: =GASHYUSHYA!C42 -> 0 | J25: =GASHYUSHYA!C40 -> 0
F26: =SUM(B26:C26) -> 0
F27: =SUM(B27:C27) -> 0
F28: =SUM(B28:C28) -> 0
B29: =SUM(B5:B28) -> 12611438 | C29: =SUM(C5:C28) -> 1396010 | D29: =SUM(D5:D28) -> 50000 | E29: =SUM(E5:E28) -> 100000 | F29: =SUM(F5:F28) -> 14007448 | G29: =SUM(G5:G28) -> 0 | H29: =SUM(H5:H28) -> 13723241 | I29: =SUM(I5:I28) -> 0 | J29: =SUM(J5:J28) -> 0
E30: REPORT DESCRIPTION
A31: REPORT SUMMARY
A32: VAT+MSF | C32: =SUM(B29+C29) -> 14007448
A33: VAT+MSF+FR NOT INVOCED | C33: =SUM(F29,G29) -> 14007448
A34: MOMO+CASH+BANK+FR NOT INVOICED | C34: =SUM(H29,J29,I29+G29) -> 13723241
A35: MS REGIST+MS CONTRIB | C35: =SUM(D29:E29) -> 150000
A36: TOTAL INCOME INVOICED+MSF&MS REGIST | C36: =SUM(H29+I29+J29+C35) -> 13873241 | E36: COORDINATOR NAME: Chantal NIYIGENA
A37: TOTAL INCOME | C37: =NYANZA!C45+KIREHE!C45+NYAGATARE!C45+KAYONZA!C45+MUSANZE!C45+MUSANZE!C45+RUBAVU!C45+KARONGI!C45+NYAMASHEKE!C45+RUSIZI!C45+HUYE!C45+RUHANGO!C45+MUHANGA!C45+BUGESERA!C45+RWAMAGANA!C45+NYARUGENGE!C45+BISHENYI!C45+GAHANGA!C45+KIMIRONKO!C45+GISOZI!C45+GATSIBO!C45+GASHYUSHYA!C45 -> 13873241
A38: RWANDA WOOD VALUE CHAIN ASSOCIATION

Sheet Sheet17

Sheet Sheet18

Sheet Sheet19

Sheet Sheet20

Sheet Sheet21

Sheet Sheet22

Sheet Sheet23

Sheet Sheet24

Sheet Sheet25

Sheet Sheet26

Sheet Sheet27

Sheet Sheet28

Sheet Sheet29

Sheet GASHYUSHYA
A1: QUANTITY REPORT
A3: MONTHS REPORT OF NOVEMBER 2025
A5: NAME OF TIMBER | B5: No OF TIMBER | C5: PRICE OF TIMBER | E5: TOTAL COST | F5: TVA | G5: MSF | H5: TVA+MSF
A6: PINUS NINI | E6: =PRODUCT(B6*C6) -> 0 | F6: =PRODUCT(E6*18)/118 -> 0 | G6: =PRODUCT(B6*50) -> 0 | H6: =SUM(F6:G6) -> 0
A7: PINUS NTOYA | E7: =PRODUCT(B7*C7) -> 0 | F7: =PRODUCT(E7*18)/118 -> 0 | G7: =PRODUCT(B7*50) -> 0 | H7: =SUM(F7:G7) -> 0
A8: PINUS | E8: =PRODUCT(B8*C8) -> 0 | F8: =PRODUCT(E8*18)/118 -> 0 | G8: =PRODUCT(B8*50) -> 0 | H8: =SUM(F8:G8) -> 0
A9: MADIRIYE NINI | E9: =PRODUCT(B9*C9) -> 0 | F9: =PRODUCT(E9*18)/118 -> 0 | G9: =PRODUCT(B9*30) -> 0 | H9: =SUM(F9:G9) -> 0
A10: MADIRIYE NTOYA | E10: =PRODUCT(B10*C10) -> 0 | F10: =PRODUCT(E10*18)/118 -> 0 | G10: =PRODUCT(B10*30) -> 0 | H10: =SUM(F10:G10) -> 0
A11: MADRIEN | E11: =PRODUCT(B11*C11) -> 0 | F11: =PRODUCT(E11*18)/118 -> 0 | G11: =PRODUCT(B11*30) -> 0 | H11: =SUM(F11:G11) -> 0
A12: MADRIEN | E12: =PRODUCT(B12*C12) -> 0 | F12: =PRODUCT(E12*18)/118 -> 0 | G12: =PRODUCT(B12*30) -> 0 | H12: =SUM(F12:G12) -> 0
A13: PLANCHE | E13: =PRODUCT(B13*C13) -> 0 | F13: =PRODUCT(E13*18)/118 -> 0 | G13: =PRODUCT(B13*20) -> 0 | H13: =SUM(F13:G13) -> 0
A14: PLANCHE | E14: =PRODUCT(B14*C14) -> 0 | F14: =PRODUCT(E14*18)/118 -> 0 | G14: =PRODUCT(B14*20) -> 0 | H14: =SUM(F14:G14) -> 0
A15: Other Timber for Difference Price
A16: NAME OF TIMBER | B16: No OF TIMBER | C16: P/U | D16: MSF | E16: TOTAL COST | F16: VAT | G16: MSF | H16: VTA+MST
A17: IBIPANDE | E17: =PRODUCT(B17*C17) -> 0 | F17: =PRODUCT(E17*18)/118 -> 0 | G17: =PRODUCT(B17*D17) -> 0 | H17: =SUM(F17:G17) -> 0
A18: IBIPANDE | E18: =PRODUCT(B18*C18) -> 0 | F18: =PRODUCT(E18*18)/118 -> 0 | G18: =PRODUCT(B18*D18) -> 0 | H18: =SUM(F18:G18) -> 0
A19: UMUSAVE | E19: =PRODUCT(B19*C19) -> 0 | F19: =PRODUCT(E19*18)/118 -> 0 | G19: =PRODUCT(B19*D19) -> 0 | H19: =SUM(F19:G19) -> 0
A20: UMUSAVE | E20: =PRODUCT(B20*C20) -> 0 | F20: =PRODUCT(E20*18)/118 -> 0 | G20: =PRODUCT(B20*D20) -> 0 | H20: =SUM(F20:G20) -> 0
A21: OTHER | E21: =PRODUCT(B21*C21) -> 0 | F21: =PRODUCT(E21*18)/118 -> 0 | G21: =PRODUCT(B21*D21) -> 0 | H21: =SUM(F21:G21) -> 0
A22: OTHER | E22: =PRODUCT(B22*C22) -> 0 | F22: =PRODUCT(E22*18)/118 -> 0 | G22: =PRODUCT(B22*D22) -> 0 | H22: =SUM(F22:G22) -> 0
A23: OTHER | E23: =PRODUCT(B23*C23) -> 0 | F23: =PRODUCT(E23*18)/118 -> 0 | G23: =PRODUCT(B23*D23) -> 0 | H23: =SUM(F23:G23) -> 0
A24: OTHER | E24: =PRODUCT(B24*C24) -> 0 | F24: =PRODUCT(E24*18)/118 -> 0 | G24: =PRODUCT(B24*D24) -> 0 | H24: =SUM(F24:G24) -> 0
A25: OTHER | E25: =PRODUCT(B25*C25) -> 0 | F25: =PRODUCT(E25*18)/118 -> 0 | G25: =PRODUCT(B25*D25) -> 0 | H25: =SUM(F25:G25) -> 0
A26: OTHER | E26: =PRODUCT(B26*C26) -> 0 | F26: =PRODUCT(E26*18)/118 -> 0 | G26: =PRODUCT(B26*D26) -> 0 | H26: =SUM(F26:G26) -> 0
A27: OTHER | E27: =PRODUCT(B27*C27) -> 0 | F27: =PRODUCT(E27*18)/118 -> 0 | G27: =PRODUCT(B27*D27) -> 0 | H27: =SUM(F27:G27) -> 0
A28: OTHER | E28: =PRODUCT(B28*C28) -> 0 | F28: =PRODUCT(E28*18)/118 -> 0 | G28: =PRODUCT(B28*D28) -> 0 | H28: =SUM(F28:G28) -> 0
... A36: OTHER | E36: =PRODUCT(B36*C36) -> 0 | F36: =PRODUCT(E36*18)/118 -> 0 | G36: =PRODUCT(B36*D36) -> 0 | H36: =SUM(F36:G36) -> 0
A37: TOTALY | E37: =SUM(E5:E36) -> 0 | F37: =SUM(F5:F36) -> 0 | G37: =SUM(G5:G36) -> 0 | H37: =SUM(H5:H36) -> 0
A38: SUMMARY | C38: RWF | E38: NAME | G38: Phone | H38: RWF
A39: TOTAL RWF PAID ON MOMO PAY
A40: TOTAL RWF PAID ON CASH
A41: AMOUNT NOT INVOICED
A42: TOTAL RWF DEPPOSITED ON BANK
A43: MEMBERSHIP FEES REGISTRETION
A44: MEMBERSHIP FEES CONTRIBUTION
A45: TOTAL INCOME | C45: =SUM(C39+C40+C41+C42+C43+C44) -> 0
A46: TIMBER SUMMARY
A48: REPORT SUMMARY | C48: TIMBER TYPE | E48: NUMBER OF QUANTITY
C49: INTURUSU | E49: =SUM(B9:B12) -> 0
C50: PINUS | E50: =SUM(B6:B8) -> 0
C51: PALNCHE | E51: =SUM(B13:B14) -> 0
C52: IBIPANDE | E52: =SUM(B17:B18) -> 0
C53: UMUSAVE | E53: =SUM(B19:B20) -> 0
C54: OTHER TYPE OF TIMBER | E54: =B29 -> 0
C55: OTHER TYPE OF TIMBER | E55: =B30 -> 0
C56: OTHER TYPE OF TIMBER | E56: =B31 -> 0
C57: OTHER TYPE OF TIMBER | E57: =B32 -> 0
C58: OTHER TYPE OF TIMBER | E58: =B33 -> 0
C59: OTHER TYPE OF TIMBER | E59: =B34 -> 0
C60: OTHER TYPE OF TIMBER | E60: =B35 -> 0
C61: OTHER TYPE OF TIMBER | E61: =B36 -> 0
C62: TOTAL TIMBER | E62: =SUM(E49:H61) -> 0

Sheet Sheet30

Sheet Sheet31

Sheet Sheet32

Sheet Sheet33

Sheet Sheet34

Sheet Sheet35

Sheet NGOMA
A1: QUANTITY REPORT
A3: MONTHS REPORT OF NOVEMBER 2025
A5: NAME OF TIMBER | B5: No OF TIMBER | C5: PRICE OF TIMBER | E5: TOTAL COST | F5: TVA | G5: MSF | H5: TVA+MSF
A6: PINUS NINI | E6: =PRODUCT(B6*C6) -> 0 | F6: =PRODUCT(E6*18)/118 -> 0 | G6: =PRODUCT(B6*50) -> 0 | H6: =SUM(F6:G6) -> 0
A7: PINUS NTOYA | E7: =PRODUCT(B7*C7) -> 0 | F7: =PRODUCT(E7*18)/118 -> 0 | G7: =PRODUCT(B7*50) -> 0 | H7: =SUM(F7:G7) -> 0
A8: PINUS | E8: =PRODUCT(B8*C8) -> 0 | F8: =PRODUCT(E8*18)/118 -> 0 | G8: =PRODUCT(B8*50) -> 0 | H8: =SUM(F8:G8) -> 0
A9: MADIRIYE NINI | E9: =PRODUCT(B9*C9) -> 0 | F9: =PRODUCT(E9*18)/118 -> 0 | G9: =PRODUCT(B9*30) -> 0 | H9: =SUM(F9:G9) -> 0
A10: MADIRIYE NTOYA | E10: =PRODUCT(B10*C10) -> 0 | F10: =PRODUCT(E10*18)/118 -> 0 | G10: =PRODUCT(B10*30) -> 0 | H10: =SUM(F10:G10) -> 0
A11: MADRIEN | E11: =PRODUCT(B11*C11) -> 0 | F11: =PRODUCT(E11*18)/118 -> 0 | G11: =PRODUCT(B11*30) -> 0 | H11: =SUM(F11:G11) -> 0
A12: MADRIEN | E12: =PRODUCT(B12*C12) -> 0 | F12: =PRODUCT(E12*18)/118 -> 0 | G12: =PRODUCT(B12*30) -> 0 | H12: =SUM(F12:G12) -> 0
A13: PLANCHE | E13: =PRODUCT(B13*C13) -> 0 | F13: =PRODUCT(E13*18)/118 -> 0 | G13: =PRODUCT(B13*20) -> 0 | H13: =SUM(F13:G13) -> 0
A14: PLANCHE | E14: =PRODUCT(B14*C14) -> 0 | F14: =PRODUCT(E14*18)/118 -> 0 | G14: =PRODUCT(B14*20) -> 0 | H14: =SUM(F14:G14) -> 0
A15: Other Timber for Difference Price
A16: NAME OF TIMBER | B16: No OF TIMBER | C16: P/U | D16: MSF | E16: TOTAL COST | F16: VAT | G16: MSF | H16: VTA+MST
A17: IBIPANDE | E17: =PRODUCT(B17*C17) -> 0 | F17: =PRODUCT(E17*18)/118 -> 0 | G17: =PRODUCT(B17*D17) -> 0 | H17: =SUM(F17:G17) -> 0
A18: IBIPANDE | E18: =PRODUCT(B18*C18) -> 0 | F18: =PRODUCT(E18*18)/118 -> 0 | G18: =PRODUCT(B18*D18) -> 0 | H18: =SUM(F18:G18) -> 0
A19: UMUSAVE | E19: =PRODUCT(B19*C19) -> 0 | F19: =PRODUCT(E19*18)/118 -> 0 | G19: =PRODUCT(B19*D19) -> 0 | H19: =SUM(F19:G19) -> 0
A20: UMUSAVE | E20: =PRODUCT(B20*C20) -> 0 | F20: =PRODUCT(E20*18)/118 -> 0 | G20: =PRODUCT(B20*D20) -> 0 | H20: =SUM(F20:G20) -> 0
A21: OTHER | E21: =PRODUCT(B21*C21) -> 0 | F21: =PRODUCT(E21*18)/118 -> 0 | G21: =PRODUCT(B21*D21) -> 0 | H21: =SUM(F21:G21) -> 0
A22: OTHER | E22: =PRODUCT(B22*C22) -> 0 | F22: =PRODUCT(E22*18)/118 -> 0 | G22: =PRODUCT(B22*D22) -> 0 | H22: =SUM(F22:G22) -> 0
A23: OTHER | E23: =PRODUCT(B23*C23) -> 0 | F23: =PRODUCT(E23*18)/118 -> 0 | G23: =PRODUCT(B23*D23) -> 0 | H23: =SUM(F23:G23) -> 0
A24: OTHER | E24: =PRODUCT(B24*C24) -> 0 | F24: =PRODUCT(E24*18)/118 -> 0 | G24: =PRODUCT(B24*D24) -> 0 | H24: =SUM(F24:G24) -> 0
A25: OTHER | E25: =PRODUCT(B25*C25) -> 0 | F25: =PRODUCT(E25*18)/118 -> 0 | G25: =PRODUCT(B25*D25) -> 0 | H25: =SUM(F25:G25) -> 0
A26: OTHER | E26: =PRODUCT(B26*C26) -> 0 | F26: =PRODUCT(E26*18)/118 -> 0 | G26: =PRODUCT(B26*D26) -> 0 | H26: =SUM(F26:G26) -> 0
A27: OTHER | E27: =PRODUCT(B27*C27) -> 0 | F27: =PRODUCT(E27*18)/118 -> 0 | G27: =PRODUCT(B27*D27) -> 0 | H27: =SUM(F27:G27) -> 0
A28: OTHER | E28: =PRODUCT(B28*C28) -> 0 | F28: =PRODUCT(E28*18)/118 -> 0 | G28: =PRODUCT(B28*D28) -> 0 | H28: =SUM(F28:G28) -> 0
... A36: OTHER | E36: =PRODUCT(B36*C36) -> 0 | F36: =PRODUCT(E36*18)/118 -> 0 | G36: =PRODUCT(B36*D36) -> 0 | H36: =SUM(F36:G36) -> 0
A37: TOTALY | E37: =SUM(E5:E36) -> 0 | F37: =SUM(F5:F36) -> 0 | G37: =SUM(G5:G36) -> 0 | H37: =SUM(H5:H36) -> 0
A38: SUMMARY | C38: RWF | E38: NAME | G38: Phone | H38: RWF
A39: TOTAL RWF PAID ON MOMO PAY
A40: TOTAL RWF PAID ON CASH
A41: AMOUNT NOT INVOICED
A42: TOTAL RWF DEPPOSITED ON BANK
A43: MEMBERSHIP FEES REGISTRETION
A44: MEMBERSHIP FEES CONTRIBUTION
A45: TOTAL INCOME | C45: =SUM(C39+C40+C41+C42+C43+C44) -> 0
A46: TIMBER SUMMARY
A48: REPORT SUMMARY | C48: TIMBER TYPE | E48: NUMBER OF QUANTITY
C49: INTURUSU | E49: =SUM(B9:B12) -> 0
C50: PINUS | E50: =SUM(B6:B8) -> 0
C51: PALNCHE | E51: =SUM(B13:B14) -> 0
C52: IBIPANDE | E52: =SUM(B17:B18) -> 0
C53: UMUSAVE | E53: =SUM(B19:B20) -> 0
C54: OTHER TYPE OF TIMBER | E54: =B29 -> 0
C55: OTHER TYPE OF TIMBER | E55: =B30 -> 0
C56: OTHER TYPE OF TIMBER | E56: =B31 -> 0
C57: OTHER TYPE OF TIMBER | E57: =B32 -> 0
C58: OTHER TYPE OF TIMBER | E58: =B33 -> 0
C59: OTHER TYPE OF TIMBER | E59: =B34 -> 0
C60: OTHER TYPE OF TIMBER | E60: =B35 -> 0
C61: OTHER TYPE OF TIMBER | E61: =B36 -> 0
C62: TOTAL TIMBER | E62: =SUM(E49:H61) -> 0

Sheet GISAGARA
A1: QUANTITY REPORT
A3: MONTHS REPORT OF NOVEMBER 2025
A5: NAME OF TIMBER | B5: No OF TIMBER | C5: PRICE OF TIMBER | E5: TOTAL COST | F5: TVA | G5: MSF | H5: TVA+MSF
A6: PINUS NINI | E6: =PRODUCT(B6*C6) -> 0 | F6: =PRODUCT(E6*18)/118 -> 0 | G6: =PRODUCT(B6*50) -> 0 | H6: =SUM(F6:G6) -> 0
A7: PINUS NTOYA | E7: =PRODUCT(B7*C7) -> 0 | F7: =PRODUCT(E7*18)/118 -> 0 | G7: =PRODUCT(B7*50) -> 0 | H7: =SUM(F7:G7) -> 0
A8: PINUS | E8: =PRODUCT(B8*C8) -> 0 | F8: =PRODUCT(E8*18)/118 -> 0 | G8: =PRODUCT(B8*50) -> 0 | H8: =SUM(F8:G8) -> 0
A9: MADIRIYE NINI | E9: =PRODUCT(B9*C9) -> 0 | F9: =PRODUCT(E9*18)/118 -> 0 | G9: =PRODUCT(B9*30) -> 0 | H9: =SUM(F9:G9) -> 0
A10: MADIRIYE NTOYA | E10: =PRODUCT(B10*C10) -> 0 | F10: =PRODUCT(E10*18)/118 -> 0 | G10: =PRODUCT(B10*30) -> 0 | H10: =SUM(F10:G10) -> 0
A11: MADRIEN | E11: =PRODUCT(B11*C11) -> 0 | F11: =PRODUCT(E11*18)/118 -> 0 | G11: =PRODUCT(B11*30) -> 0 | H11: =SUM(F11:G11) -> 0
A12: MADRIEN | E12: =PRODUCT(B12*C12) -> 0 | F12: =PRODUCT(E12*18)/118 -> 0 | G12: =PRODUCT(B12*30) -> 0 | H12: =SUM(F12:G12) -> 0
A13: PLANCHE | E13: =PRODUCT(B13*C13) -> 0 | F13: =PRODUCT(E13*18)/118 -> 0 | G13: =PRODUCT(B13*20) -> 0 | H13: =SUM(F13:G13) -> 0
A14: PLANCHE | E14: =PRODUCT(B14*C14) -> 0 | F14: =PRODUCT(E14*18)/118 -> 0 | G14: =PRODUCT(B14*20) -> 0 | H14: =SUM(F14:G14) -> 0
A15: Other Timber for Difference Price
A16: NAME OF TIMBER | B16: No OF TIMBER | C16: P/U | D16: MSF | E16: TOTAL COST | F16: VAT | G16: MSF | H16: VTA+MST
A17: IBIPANDE | E17: =PRODUCT(B17*C17) -> 0 | F17: =PRODUCT(E17*18)/118 -> 0 | G17: =PRODUCT(B17*D17) -> 0 | H17: =SUM(F17:G17) -> 0
A18: IBIPANDE | E18: =PRODUCT(B18*C18) -> 0 | F18: =PRODUCT(E18*18)/118 -> 0 | G18: =PRODUCT(B18*D18) -> 0 | H18: =SUM(F18:G18) -> 0
A19: UMUSAVE | E19: =PRODUCT(B19*C19) -> 0 | F19: =PRODUCT(E19*18)/118 -> 0 | G19: =PRODUCT(B19*D19) -> 0 | H19: =SUM(F19:G19) -> 0
A20: UMUSAVE | E20: =PRODUCT(B20*C20) -> 0 | F20: =PRODUCT(E20*18)/118 -> 0 | G20: =PRODUCT(B20*D20) -> 0 | H20: =SUM(F20:G20) -> 0
A21: OTHER | E21: =PRODUCT(B21*C21) -> 0 | F21: =PRODUCT(E21*18)/118 -> 0 | G21: =PRODUCT(B21*D21) -> 0 | H21: =SUM(F21:G21) -> 0
A22: OTHER | E22: =PRODUCT(B22*C22) -> 0 | F22: =PRODUCT(E22*18)/118 -> 0 | G22: =PRODUCT(B22*D22) -> 0 | H22: =SUM(F22:G22) -> 0
A23: OTHER | E23: =PRODUCT(B23*C23) -> 0 | F23: =PRODUCT(E23*18)/118 -> 0 | G23: =PRODUCT(B23*D23) -> 0 | H23: =SUM(F23:G23) -> 0
A24: OTHER | E24: =PRODUCT(B24*C24) -> 0 | F24: =PRODUCT(E24*18)/118 -> 0 | G24: =PRODUCT(B24*D24) -> 0 | H24: =SUM(F24:G24) -> 0
A25: OTHER | E25: =PRODUCT(B25*C25) -> 0 | F25: =PRODUCT(E25*18)/118 -> 0 | G25: =PRODUCT(B25*D25) -> 0 | H25: =SUM(F25:G25) -> 0
A26: OTHER | E26: =PRODUCT(B26*C26) -> 0 | F26: =PRODUCT(E26*18)/118 -> 0 | G26: =PRODUCT(B26*D26) -> 0 | H26: =SUM(F26:G26) -> 0
A27: OTHER | E27: =PRODUCT(B27*C27) -> 0 | F27: =PRODUCT(E27*18)/118 -> 0 | G27: =PRODUCT(B27*D27) -> 0 | H27: =SUM(F27:G27) -> 0
A28: OTHER | E28: =PRODUCT(B28*C28) -> 0 | F28: =PRODUCT(E28*18)/118 -> 0 | G28: =PRODUCT(B28*D28) -> 0 | H28: =SUM(F28:G28) -> 0
... A36: OTHER | E36: =PRODUCT(B36*C36) -> 0 | F36: =PRODUCT(E36*18)/118 -> 0 | G36: =PRODUCT(B36*D36) -> 0 | H36: =SUM(F36:G36) -> 0
A37: TOTALY | E37: =SUM(E5:E36) -> 0 | F37: =SUM(F5:F36) -> 0 | G37: =SUM(G5:G36) -> 0 | H37: =SUM(H5:H36) -> 0
A38: SUMMARY | C38: RWF | E38: NAME | G38: Phone | H38: RWF
A39: TOTAL RWF PAID ON MOMO PAY
A40: TOTAL RWF PAID ON CASH
A41: AMOUNT NOT INVOICED
A42: TOTAL RWF DEPPOSITED ON BANK
A43: MEMBERSHIP FEES REGISTRETION
A44: MEMBERSHIP FEES CONTRIBUTION
A45: TOTAL INCOME | C45: =SUM(C39+C40+C41+C42+C43+C44) -> 0
A46: TIMBER SUMMARY
A48: REPORT SUMMARY | C48: TIMBER TYPE | E48: NUMBER OF QUANTITY
C49: INTURUSU | E49: =SUM(B9:B12) -> 0
C50: PINUS | E50: =SUM(B6:B8) -> 0
C51: PALNCHE | E51: =SUM(B13:B14) -> 0
C52: IBIPANDE | E52: =SUM(B17:B18) -> 0
C53: UMUSAVE | E53: =SUM(B19:B20) -> 0
C54: OTHER TYPE OF TIMBER | E54: =B29 -> 0
C55: OTHER TYPE OF TIMBER | E55: =B30 -> 0
C56: OTHER TYPE OF TIMBER | E56: =B31 -> 0
C57: OTHER TYPE OF TIMBER | E57: =B32 -> 0
C58: OTHER TYPE OF TIMBER | E58: =B33 -> 0
C59: OTHER TYPE OF TIMBER | E59: =B34 -> 0
C60: OTHER TYPE OF TIMBER | E60: =B35 -> 0
C61: OTHER TYPE OF TIMBER | E61: =B36 -> 0
C62: TOTAL TIMBER | E62: =SUM(E49:H61) -> 0

Sheet NYAMAGABE
A1: QUANTITY REPORT
A3: MONTHS REPORT OF MARCH 2026
A5: NAME OF TIMBER | B5: No OF TIMBER | C5: PRICE OF TIMBER | E5: TOTAL COST | F5: TVA | G5: MSF | H5: TVA+MSF
A6: PINUS NINI | E6: =PRODUCT(B6*C6) -> 0 | F6: =PRODUCT(E6*18)/118 -> 0 | G6: =PRODUCT(B6*50) -> 0 | H6: =SUM(F6:G6) -> 0
A7: PINUS NTOYA | E7: =PRODUCT(B7*C7) -> 0 | F7: =PRODUCT(E7*18)/118 -> 0 | G7: =PRODUCT(B7*50) -> 0 | H7: =SUM(F7:G7) -> 0
A8: PINUS | B8: 180 | C8: 8260 | E8: =PRODUCT(B8*C8) -> 1486800 | F8: =PRODUCT(E8*18)/118 -> 226800 | G8: =PRODUCT(B8*50) -> 9000 | H8: =SUM(F8:G8) -> 235800
A9: MADIRIYE NINI | E9: =PRODUCT(B9*C9) -> 0 | F9: =PRODUCT(E9*18)/118 -> 0 | G9: =PRODUCT(B9*30) -> 0 | H9: =SUM(F9:G9) -> 0
A10: MADIRIYE NTOYA | B10: 2000 | C10: 2360 | E10: =PRODUCT(B10*C10) -> 4720000 | F10: =PRODUCT(E10*18)/118 -> 720000 | G10: =PRODUCT(B10*30) -> 60000 | H10: =SUM(F10:G10) -> 780000
A11: MADRIEN | E11: =PRODUCT(B11*C11) -> 0 | F11: =PRODUCT(E11*18)/118 -> 0 | G11: =PRODUCT(B11*30) -> 0 | H11: =SUM(F11:G11) -> 0
A12: MADRIEN | E12: =PRODUCT(B12*C12) -> 0 | F12: =PRODUCT(E12*18)/118 -> 0 | G12: =PRODUCT(B12*30) -> 0 | H12: =SUM(F12:G12) -> 0
A13: PLANCHE | E13: =PRODUCT(B13*C13) -> 0 | F13: =PRODUCT(E13*18)/118 -> 0 | G13: =PRODUCT(B13*20) -> 0 | H13: =SUM(F13:G13) -> 0
A14: PLANCHE | E14: =PRODUCT(B14*C14) -> 0 | F14: =PRODUCT(E14*18)/118 -> 0 | G14: =PRODUCT(B14*20) -> 0 | H14: =SUM(F14:G14) -> 0
A15: Other Timber for Difference Price
A16: NAME OF TIMBER | B16: No OF TIMBER | C16: P/U | D16: MSF | E16: TOTAL COST | F16: VAT | G16: MSF | H16: VTA+MST
A17: DECHETS | B17: 16 | C17: 10000 | D17: 1500 | E17: =PRODUCT(B17*C17) -> 160000 | F17: =PRODUCT(E17*18)/118 -> 24406.78 | G17: =PRODUCT(B17*D17) -> 24000 | H17: =SUM(F17:G17) -> 48406.78
A18: IBIPANDE | E18: =PRODUCT(B18*C18) -> 0 | F18: =PRODUCT(E18*18)/118 -> 0 | G18: =PRODUCT(B18*D18) -> 0 | H18: =SUM(F18:G18) -> 0
A19: UMUSAVE | E19: =PRODUCT(B19*C19) -> 0 | F19: =PRODUCT(E19*18)/118 -> 0 | G19: =PRODUCT(B19*D19) -> 0 | H19: =SUM(F19:G19) -> 0
A20: UMUSAVE | E20: =PRODUCT(B20*C20) -> 0 | F20: =PRODUCT(E20*18)/118 -> 0 | G20: =PRODUCT(B20*D20) -> 0 | H20: =SUM(F20:G20) -> 0
A21: OTHER | E21: =PRODUCT(B21*C21) -> 0 | F21: =PRODUCT(E21*18)/118 -> 0 | G21: =PRODUCT(B21*D21) -> 0 | H21: =SUM(F21:G21) -> 0
A22: OTHER | E22: =PRODUCT(B22*C22) -> 0 | F22: =PRODUCT(E22*18)/118 -> 0 | G22: =PRODUCT(B22*D22) -> 0 | H22: =SUM(F22:G22) -> 0
A23: OTHER | E23: =PRODUCT(B23*C23) -> 0 | F23: =PRODUCT(E23*18)/118 -> 0 | G23: =PRODUCT(B23*D23) -> 0 | H23: =SUM(F23:G23) -> 0
A24: OTHER | E24: =PRODUCT(B24*C24) -> 0 | F24: =PRODUCT(E24*18)/118 -> 0 | G24: =PRODUCT(B24*D24) -> 0 | H24: =SUM(F24:G24) -> 0
A25: OTHER | E25: =PRODUCT(B25*C25) -> 0 | F25: =PRODUCT(E25*18)/118 -> 0 | G25: =PRODUCT(B25*D25) -> 0 | H25: =SUM(F25:G25) -> 0
A26: OTHER | E26: =PRODUCT(B26*C26) -> 0 | F26: =PRODUCT(E26*18)/118 -> 0 | G26: =PRODUCT(B26*D26) -> 0 | H26: =SUM(F26:G26) -> 0
A27: OTHER | E27: =PRODUCT(B27*C27) -> 0 | F27: =PRODUCT(E27*18)/118 -> 0 | G27: =PRODUCT(B27*D27) -> 0 | H27: =SUM(F27:G27) -> 0
A28: OTHER | E28: =PRODUCT(B28*C28) -> 0 | F28: =PRODUCT(E28*18)/118 -> 0 | G28: =PRODUCT(B28*D28) -> 0 | H28: =SUM(F28:G28) -> 0
A29: OTHER | E29: =PRODUCT(B29*C29) -> 0 | F29: =PRODUCT(E29*18)/118 -> 0 | G29: =PRODUCT(B29*D29) -> 0 | H29: =SUM(F29:G29) -> 0
... A36: OTHER | E36: =PRODUCT(B36*C36) -> 0 | F36: =PRODUCT(E36*18)/118 -> 0 | G36: =PRODUCT(B36*D36) -> 0 | H36: =SUM(F36:G36) -> 0
A37: TOTALY | E37: =SUM(E5:E36) -> 6366800 | F37: =SUM(F5:F36) -> 971206.78 | G37: =SUM(G5:G36) -> 93000 | H37: =SUM(H5:H36) -> 1064206.8
A38: SUMMARY | C38: RWF | E38: NAME | G38: Phone | H38: RWF
A39: TOTAL RWF PAID ON MOMO PAY
A40: TOTAL RWF PAID ON CASH | C40: 54207
A41: AMOUNT NOT INVOICED
A42: TOTAL RWF DEPPOSITED ON BANK
A43: MEMBERSHIP FEES REGISTRETION
A44: MEMBERSHIP FEES CONTRIBUTION
A45: TOTAL INCOME | C45: =SUM(C39+C40+C41+C42+C43+C44) -> 54207
A46: TIMBER SUMMARY
A48: REPORT SUMMARY | C48: TIMBER TYPE | E48: NUMBER OF QUANTITY
C49: INTURUSU | E49: =SUM(B9:B12) -> 2000
C50: PINUS | E50: =SUM(B6:B8) -> 180
C51: PALNCHE | E51: =SUM(B13:B14) -> 0
C52: IBIPANDE | E52: =SUM(B17:B18) -> 16
C53: UMUSAVE | E53: =SUM(B19:B20) -> 0
C54: OTHER TYPE OF TIMBER | E54: =B29 -> 0
C55: OTHER TYPE OF TIMBER | E55: =B30 -> 0
C56: OTHER TYPE OF TIMBER | E56: =B31 -> 0
C57: OTHER TYPE OF TIMBER | E57: =B32 -> 0
C58: OTHER TYPE OF TIMBER | E58: =B33 -> 0
C59: OTHER TYPE OF TIMBER | E59: =B34 -> 0
C60: OTHER TYPE OF TIMBER | E60: =B35 -> 0
C61: OTHER TYPE OF TIMBER | E61: =B36 -> 0
C62: TOTAL TIMBER | E62: =SUM(E49:H61) -> 2196

Sheet NGORORERO
A1: QUANTITY REPORT
A3: MONTHS REPORT OF NOVEMBER 2025
A5: NAME OF TIMBER | B5: No OF TIMBER | C5: PRICE OF TIMBER | E5: TOTAL COST | F5: TVA | G5: MSF | H5: TVA+MSF
A6: PINUS NINI | E6: =PRODUCT(B6*C6) -> 0 | F6: =PRODUCT(E6*18)/118 -> 0 | G6: =PRODUCT(B6*50) -> 0 | H6: =SUM(F6:G6) -> 0
A7: PINUS NTOYA | E7: =PRODUCT(B7*C7) -> 0 | F7: =PRODUCT(E7*18)/118 -> 0 | G7: =PRODUCT(B7*50) -> 0 | H7: =SUM(F7:G7) -> 0
A8: PINUS | E8: =PRODUCT(B8*C8) -> 0 | F8: =PRODUCT(E8*18)/118 -> 0 | G8: =PRODUCT(B8*50) -> 0 | H8: =SUM(F8:G8) -> 0
A9: MADIRIYE NINI | E9: =PRODUCT(B9*C9) -> 0 | F9: =PRODUCT(E9*18)/118 -> 0 | G9: =PRODUCT(B9*30) -> 0 | H9: =SUM(F9:G9) -> 0
A10: MADIRIYE NTOYA | E10: =PRODUCT(B10*C10) -> 0 | F10: =PRODUCT(E10*18)/118 -> 0 | G10: =PRODUCT(B10*30) -> 0 | H10: =SUM(F10:G10) -> 0
A11: MADRIEN | E11: =PRODUCT(B11*C11) -> 0 | F11: =PRODUCT(E11*18)/118 -> 0 | G11: =PRODUCT(B11*30) -> 0 | H11: =SUM(F11:G11) -> 0
A12: MADRIEN | E12: =PRODUCT(B12*C12) -> 0 | F12: =PRODUCT(E12*18)/118 -> 0 | G12: =PRODUCT(B12*30) -> 0 | H12: =SUM(F12:G12) -> 0
A13: PLANCHE | E13: =PRODUCT(B13*C13) -> 0 | F13: =PRODUCT(E13*18)/118 -> 0 | G13: =PRODUCT(B13*20) -> 0 | H13: =SUM(F13:G13) -> 0
A14: PLANCHE | E14: =PRODUCT(B14*C14) -> 0 | F14: =PRODUCT(E14*18)/118 -> 0 | G14: =PRODUCT(B14*20) -> 0 | H14: =SUM(F14:G14) -> 0
A15: Other Timber for Difference Price
A16: NAME OF TIMBER | B16: No OF TIMBER | C16: P/U | D16: MSF | E16: TOTAL COST | F16: VAT | G16: MSF | H16: VTA+MST
A17: IBIPANDE | E17: =PRODUCT(B17*C17) -> 0 | F17: =PRODUCT(E17*18)/118 -> 0 | G17: =PRODUCT(B17*D17) -> 0 | H17: =SUM(F17:G17) -> 0
A18: IBIPANDE | E18: =PRODUCT(B18*C18) -> 0 | F18: =PRODUCT(E18*18)/118 -> 0 | G18: =PRODUCT(B18*D18) -> 0 | H18: =SUM(F18:G18) -> 0
A19: UMUSAVE | E19: =PRODUCT(B19*C19) -> 0 | F19: =PRODUCT(E19*18)/118 -> 0 | G19: =PRODUCT(B19*D19) -> 0 | H19: =SUM(F19:G19) -> 0
A20: UMUSAVE | E20: =PRODUCT(B20*C20) -> 0 | F20: =PRODUCT(E20*18)/118 -> 0 | G20: =PRODUCT(B20*D20) -> 0 | H20: =SUM(F20:G20) -> 0
A21: OTHER | E21: =PRODUCT(B21*C21) -> 0 | F21: =PRODUCT(E21*18)/118 -> 0 | G21: =PRODUCT(B21*D21) -> 0 | H21: =SUM(F21:G21) -> 0
A22: OTHER | E22: =PRODUCT(B22*C22) -> 0 | F22: =PRODUCT(E22*18)/118 -> 0 | G22: =PRODUCT(B22*D22) -> 0 | H22: =SUM(F22:G22) -> 0
A23: OTHER | E23: =PRODUCT(B23*C23) -> 0 | F23: =PRODUCT(E23*18)/118 -> 0 | G23: =PRODUCT(B23*D23) -> 0 | H23: =SUM(F23:G23) -> 0
A24: OTHER | E24: =PRODUCT(B24*C24) -> 0 | F24: =PRODUCT(E24*18)/118 -> 0 | G24: =PRODUCT(B24*D24) -> 0 | H24: =SUM(F24:G24) -> 0
A25: OTHER | E25: =PRODUCT(B25*C25) -> 0 | F25: =PRODUCT(E25*18)/118 -> 0 | G25: =PRODUCT(B25*D25) -> 0 | H25: =SUM(F25:G25) -> 0
A26: OTHER | E26: =PRODUCT(B26*C26) -> 0 | F26: =PRODUCT(E26*18)/118 -> 0 | G26: =PRODUCT(B26*D26) -> 0 | H26: =SUM(F26:G26) -> 0
A27: OTHER | E27: =PRODUCT(B27*C27) -> 0 | F27: =PRODUCT(E27*18)/118 -> 0 | G27: =PRODUCT(B27*D27) -> 0 | H27: =SUM(F27:G27) -> 0
A28: OTHER | E28: =PRODUCT(B28*C28) -> 0 | F28: =PRODUCT(E28*18)/118 -> 0 | G28: =PRODUCT(B28*D28) -> 0 | H28: =SUM(F28:G28) -> 0
... A36: OTHER | E36: =PRODUCT(B36*C36) -> 0 | F36: =PRODUCT(E36*18)/118 -> 0 | G36: =PRODUCT(B36*D36) -> 0 | H36: =SUM(F36:G36) -> 0
A37: TOTALY | E37: =SUM(E5:E36) -> 0 | F37: =SUM(F5:F36) -> 0 | G37: =SUM(G5:G36) -> 0 | H37: =SUM(H5:H36) -> 0
A38: SUMMARY | C38: RWF | E38: NAME | G38: Phone | H38: RWF
A39: TOTAL RWF PAID ON MOMO PAY
A40: TOTAL RWF PAID ON CASH
A41: AMOUNT NOT INVOICED
A42: TOTAL RWF DEPPOSITED ON BANK
A43: MEMBERSHIP FEES REGISTRETION
A44: MEMBERSHIP FEES CONTRIBUTION
A45: TOTAL INCOME | C45: =SUM(C39+C40+C41+C42+C43+C44) -> 0
A46: TIMBER SUMMARY
A48: REPORT SUMMARY | C48: TIMBER TYPE | E48: NUMBER OF QUANTITY
C49: INTURUSU | E49: =SUM(B9:B12) -> 0
C50: PINUS | E50: =SUM(B6:B8) -> 0
C51: PALNCHE | E51: =SUM(B13:B14) -> 0
C52: IBIPANDE | E52: =SUM(B17:B18) -> 0
C53: UMUSAVE | E53: =SUM(B19:B20) -> 0
C54: OTHER TYPE OF TIMBER | E54: =B29 -> 0
C55: OTHER TYPE OF TIMBER | E55: =B30 -> 0
C56: OTHER TYPE OF TIMBER | E56: =B31 -> 0
C57: OTHER TYPE OF TIMBER | E57: =B32 -> 0
C58: OTHER TYPE OF TIMBER | E58: =B33 -> 0
C59: OTHER TYPE OF TIMBER | E59: =B34 -> 0
C60: OTHER TYPE OF TIMBER | E60: =B35 -> 0
C61: OTHER TYPE OF TIMBER | E61: =B36 -> 0
C62: TOTAL TIMBER | E62: =SUM(E49:H61) -> 0

Sheet GISOZI
A1: QUANTITY REPORT
A3: MONTHS REPORT OF NOVEMBER 2025
A5: NAME OF TIMBER | B5: No OF TIMBER | C5: PRICE OF TIMBER | E5: TOTAL COST | F5: TVA | G5: MSF | H5: TVA+MSF
A6: PINUS NINI | E6: =PRODUCT(B6*C6) -> 0 | F6: =PRODUCT(E6*18)/118 -> 0 | G6: =PRODUCT(B6*50) -> 0 | H6: =SUM(F6:G6) -> 0
A7: PINUS NTOYA | E7: =PRODUCT(B7*C7) -> 0 | F7: =PRODUCT(E7*18)/118 -> 0 | G7: =PRODUCT(B7*50) -> 0 | H7: =SUM(F7:G7) -> 0
A8: PINUS | E8: =PRODUCT(B8*C8) -> 0 | F8: =PRODUCT(E8*18)/118 -> 0 | G8: =PRODUCT(B8*50) -> 0 | H8: =SUM(F8:G8) -> 0
A9: MADIRIYE NINI | E9: =PRODUCT(B9*C9) -> 0 | F9: =PRODUCT(E9*18)/118 -> 0 | G9: =PRODUCT(B9*30) -> 0 | H9: =SUM(F9:G9) -> 0
A10: MADIRIYE NTOYA | E10: =PRODUCT(B10*C10) -> 0 | F10: =PRODUCT(E10*18)/118 -> 0 | G10: =PRODUCT(B10*30) -> 0 | H10: =SUM(F10:G10) -> 0
A11: MADRIEN | E11: =PRODUCT(B11*C11) -> 0 | F11: =PRODUCT(E11*18)/118 -> 0 | G11: =PRODUCT(B11*30) -> 0 | H11: =SUM(F11:G11) -> 0
A12: MADRIEN | E12: =PRODUCT(B12*C12) -> 0 | F12: =PRODUCT(E12*18)/118 -> 0 | G12: =PRODUCT(B12*30) -> 0 | H12: =SUM(F12:G12) -> 0
A13: PLANCHE | E13: =PRODUCT(B13*C13) -> 0 | F13: =PRODUCT(E13*18)/118 -> 0 | G13: =PRODUCT(B13*20) -> 0 | H13: =SUM(F13:G13) -> 0
A14: PLANCHE | E14: =PRODUCT(B14*C14) -> 0 | F14: =PRODUCT(E14*18)/118 -> 0 | G14: =PRODUCT(B14*20) -> 0 | H14: =SUM(F14:G14) -> 0
A15: Other Timber for Difference Price
A16: NAME OF TIMBER | B16: No OF TIMBER | C16: P/U | D16: MSF | E16: TOTAL COST | F16: VAT | G16: MSF | H16: VTA+MST
A17: IBIPANDE | E17: =PRODUCT(B17*C17) -> 0 | F17: =PRODUCT(E17*18)/118 -> 0 | G17: =PRODUCT(B17*D17) -> 0 | H17: =SUM(F17:G17) -> 0
A18: IBIPANDE | E18: =PRODUCT(B18*C18) -> 0 | F18: =PRODUCT(E18*18)/118 -> 0 | G18: =PRODUCT(B18*D18) -> 0 | H18: =SUM(F18:G18) -> 0
A19: UMUSAVE | E19: =PRODUCT(B19*C19) -> 0 | F19: =PRODUCT(E19*18)/118 -> 0 | G19: =PRODUCT(B19*D19) -> 0 | H19: =SUM(F19:G19) -> 0
A20: UMUSAVE | E20: =PRODUCT(B20*C20) -> 0 | F20: =PRODUCT(E20*18)/118 -> 0 | G20: =PRODUCT(B20*D20) -> 0 | H20: =SUM(F20:G20) -> 0
A21: OTHER | E21: =PRODUCT(B21*C21) -> 0 | F21: =PRODUCT(E21*18)/118 -> 0 | G21: =PRODUCT(B21*D21) -> 0 | H21: =SUM(F21:G21) -> 0
A22: OTHER | E22: =PRODUCT(B22*C22) -> 0 | F22: =PRODUCT(E22*18)/118 -> 0 | G22: =PRODUCT(B22*D22) -> 0 | H22: =SUM(F22:G22) -> 0
A23: OTHER | E23: =PRODUCT(B23*C23) -> 0 | F23: =PRODUCT(E23*18)/118 -> 0 | G23: =PRODUCT(B23*D23) -> 0 | H23: =SUM(F23:G23) -> 0
A24: OTHER | E24: =PRODUCT(B24*C24) -> 0 | F24: =PRODUCT(E24*18)/118 -> 0 | G24: =PRODUCT(B24*D24) -> 0 | H24: =SUM(F24:G24) -> 0
A25: OTHER | E25: =PRODUCT(B25*C25) -> 0 | F25: =PRODUCT(E25*18)/118 -> 0 | G25: =PRODUCT(B25*D25) -> 0 | H25: =SUM(F25:G25) -> 0
A26: OTHER | E26: =PRODUCT(B26*C26) -> 0 | F26: =PRODUCT(E26*18)/118 -> 0 | G26: =PRODUCT(B26*D26) -> 0 | H26: =SUM(F26:G26) -> 0
A27: OTHER | E27: =PRODUCT(B27*C27) -> 0 | F27: =PRODUCT(E27*18)/118 -> 0 | G27: =PRODUCT(B27*D27) -> 0 | H27: =SUM(F27:G27) -> 0
A28: OTHER | E28: =PRODUCT(B28*C28) -> 0 | F28: =PRODUCT(E28*18)/118 -> 0 | G28: =PRODUCT(B28*D28) -> 0 | H28: =SUM(F28:G28) -> 0
... A36: OTHER | E36: =PRODUCT(B36*C36) -> 0 | F36: =PRODUCT(E36*18)/118 -> 0 | G36: =PRODUCT(B36*D36) -> 0 | H36: =SUM(F36:G36) -> 0
A37: TOTALY | E37: =SUM(E5:E36) -> 0 | F37: =SUM(F5:F36) -> 0 | G37: =SUM(G5:G36) -> 0 | H37: =SUM(H5:H36) -> 0
A38: SUMMARY | C38: RWF | E38: NAME | G38: Phone | H38: RWF
A39: TOTAL RWF PAID ON MOMO PAY
A40: TOTAL RWF PAID ON CASH
A41: AMOUNT NOT INVOICED
A42: TOTAL RWF DEPPOSITED ON BANK
A43: MEMBERSHIP FEES REGISTRETION
A44: MEMBERSHIP FEES CONTRIBUTION
A45: TOTAL INCOME | C45: =SUM(C39+C40+C41+C42+C43+C44) -> 0
A46: TIMBER SUMMARY
A48: REPORT SUMMARY | C48: TIMBER TYPE | E48: NUMBER OF QUANTITY
C49: INTURUSU | E49: =SUM(B9:B12) -> 0
C50: PINUS | E50: =SUM(B6:B8) -> 0
C51: PALNCHE | E51: =SUM(B13:B14) -> 0
C52: IBIPANDE | E52: =SUM(B17:B18) -> 0
C53: UMUSAVE | E53: =SUM(B19:B20) -> 0
C54: OTHER | E54: =B29 -> 0
C55: OTHER | E55: =B30 -> 0
C56: OTHER | E56: =B31 -> 0
C57: OTHER | E57: =B32 -> 0
C58: OTHER | E58: =B33 -> 0
C59: OTHER | E59: =B34 -> 0
C60: OTHER | E60: =B35 -> 0
C61: OTHER | E61: =B36 -> 0
C62: TOTAL TIMBER | E62: =SUM(E49:H61) -> 0

Sheet BISHENYI
A1: QUANTITY REPORT
A3: MONTHS REPORT OF NOVEMBER 2025
A5: NAME OF TIMBER | B5: No OF TIMBER | C5: PRICE OF TIMBER | E5: TOTAL COST | F5: TVA | G5: MSF | H5: TVA+MSF
A6: PINUS NINI | E6: =PRODUCT(B6*C6) -> 0 | F6: =PRODUCT(E6*18)/118 -> 0 | G6: =PRODUCT(B6*50) -> 0 | H6: =SUM(F6:G6) -> 0
A7: PINUS NTOYA | E7: =PRODUCT(B7*C7) -> 0 | F7: =PRODUCT(E7*18)/118 -> 0 | G7: =PRODUCT(B7*50) -> 0 | H7: =SUM(F7:G7) -> 0
A8: PINUS | E8: =PRODUCT(B8*C8) -> 0 | F8: =PRODUCT(E8*18)/118 -> 0 | G8: =PRODUCT(B8*50) -> 0 | H8: =SUM(F8:G8) -> 0
A9: MADIRIYE NINI | E9: =PRODUCT(B9*C9) -> 0 | F9: =PRODUCT(E9*18)/118 -> 0 | G9: =PRODUCT(B9*30) -> 0 | H9: =SUM(F9:G9) -> 0
A10: MADIRIYE NTOYA | C10: 2124 | E10: =PRODUCT(B10*C10) -> 0 | F10: =PRODUCT(E10*18)/118 -> 0 | G10: =PRODUCT(B10*30) -> 0 | H10: =SUM(F10:G10) -> 0
A11: MADRIEN | E11: =PRODUCT(B11*C11) -> 0 | F11: =PRODUCT(E11*18)/118 -> 0 | G11: =PRODUCT(B11*30) -> 0 | H11: =SUM(F11:G11) -> 0
A12: MADRIEN | E12: =PRODUCT(B12*C12) -> 0 | F12: =PRODUCT(E12*18)/118 -> 0 | G12: =PRODUCT(B12*30) -> 0 | H12: =SUM(F12:G12) -> 0
A13: PLANCHE | E13: =PRODUCT(B13*C13) -> 0 | F13: =PRODUCT(E13*18)/118 -> 0 | G13: =PRODUCT(B13*20) -> 0 | H13: =SUM(F13:G13) -> 0
A14: PLANCHE | E14: =PRODUCT(B14*C14) -> 0 | F14: =PRODUCT(E14*18)/118 -> 0 | G14: =PRODUCT(B14*20) -> 0 | H14: =SUM(F14:G14) -> 0
A15: Other Timber for Difference Price
A16: NAME OF TIMBER | B16: No OF TIMBER | C16: P/U | D16: MSF | E16: TOTAL COST | F16: VAT | G16: MSF | H16: VTA+MST
A17: IBIPANDE | E17: =PRODUCT(B17*C17) -> 0 | F17: =PRODUCT(E17*18)/118 -> 0 | G17: =PRODUCT(B17*D17) -> 0 | H17: =SUM(F17:G17) -> 0
A18: IBIPANDE | E18: =PRODUCT(B18*C18) -> 0 | F18: =PRODUCT(E18*18)/118 -> 0 | G18: =PRODUCT(B18*D18) -> 0 | H18: =SUM(F18:G18) -> 0
A19: UMUSAVE | E19: =PRODUCT(B19*C19) -> 0 | F19: =PRODUCT(E19*18)/118 -> 0 | G19: =PRODUCT(B19*D19) -> 0 | H19: =SUM(F19:G19) -> 0
A20: UMUSAVE | E20: =PRODUCT(B20*C20) -> 0 | F20: =PRODUCT(E20*18)/118 -> 0 | G20: =PRODUCT(B20*D20) -> 0 | H20: =SUM(F20:G20) -> 0
A21: OTHER | E21: =PRODUCT(B21*C21) -> 0 | F21: =PRODUCT(E21*18)/118 -> 0 | G21: =PRODUCT(B21*D21) -> 0 | H21: =SUM(F21:G21) -> 0
A22: OTHER | E22: =PRODUCT(B22*C22) -> 0 | F22: =PRODUCT(E22*18)/118 -> 0 | G22: =PRODUCT(B22*D22) -> 0 | H22: =SUM(F22:G22) -> 0
A23: OTHER | E23: =PRODUCT(B23*C23) -> 0 | F23: =PRODUCT(E23*18)/118 -> 0 | G23: =PRODUCT(B23*D23) -> 0 | H23: =SUM(F23:G23) -> 0
A24: OTHER | E24: =PRODUCT(B24*C24) -> 0 | F24: =PRODUCT(E24*18)/118 -> 0 | G24: =PRODUCT(B24*D24) -> 0 | H24: =SUM(F24:G24) -> 0
A25: OTHER | E25: =PRODUCT(B25*C25) -> 0 | F25: =PRODUCT(E25*18)/118 -> 0 | G25: =PRODUCT(B25*D25) -> 0 | H25: =SUM(F25:G25) -> 0
A26: OTHER | E26: =PRODUCT(B26*C26) -> 0 | F26: =PRODUCT(E26*18)/118 -> 0 | G26: =PRODUCT(B26*D26) -> 0 | H26: =SUM(F26:G26) -> 0
A27: OTHER | E27: =PRODUCT(B27*C27) -> 0 | F27: =PRODUCT(E27*18)/118 -> 0 | G27: =PRODUCT(B27*D27) -> 0 | H27: =SUM(F27:G27) -> 0
A28: OTHER | E28: =PRODUCT(B28*C28) -> 0 | F28: =PRODUCT(E28*18)/118 -> 0 | G28: =PRODUCT(B28*D28) -> 0 | H28: =SUM(F28:G28) -> 0
... A36: OTHER | E36: =PRODUCT(B36*C36) -> 0 | F36: =PRODUCT(E36*18)/118 -> 0 | G36: =PRODUCT(B36*D36) -> 0 | H36: =SUM(F36:G36) -> 0
A37: TOTALY | E37: =SUM(E5:E36) -> 0 | F37: =SUM(F5:F36) -> 0 | G37: =SUM(G5:G36) -> 0 | H37: =SUM(H5:H36) -> 0
A38: SUMMARY | C38: RWF | E38: NAME | G38: Phone | H38: RWF
A39: TOTAL RWF PAID ON MOMO PAY
A40: TOTAL RWF PAID ON CASH
A41: AMOUNT NOT INVOICED
A42: TOTAL RWF DEPPOSITED ON BANK
A43: MEMBERSHIP FEES REGISTRETION
A44: MEMBERSHIP FEES CONTRIBUTION
A45: TOTAL INCOME | C45: =SUM(C39+C40+C41+C42+C43+C44) -> 0
A46: TIMBER SUMMARY
A48: REPORT SUMMARY | C48: TIMBER TYPE | E48: NUMBER OF QUANTITY
C49: INTURUSU | E49: =SUM(B9:B12) -> 0
C50: PINUS | E50: =SUM(B6:B8) -> 0
C51: PALNCHE | E51: =SUM(B13:B14) -> 0
C52: IBIPANDE | E52: =SUM(B17:B18) -> 0
C53: UMUSAVE | E53: =SUM(B19:B20) -> 0
C54: OTHER | E54: =B29 -> 0
C55: OTHER | E55: =B30 -> 0
C56: OTHER | E56: =B31 -> 0
C57: OTHER | E57: =B32 -> 0
C58: OTHER | E58: =B33 -> 0
C59: OTHER | E59: =B34 -> 0
C60: OTHER | E60: =B35 -> 0
C61: OTHER | E61: =B36 -> 0
C62: TOTAL TIMBER | E62: =SUM(E49:H61) -> 0

Sheet RWAMAGANA
A1: QUANTITY REPORT
A3: QUARTERLY REPORT FROM 01/01/2026 TO 31/03/2026
A5: NAME OF TIMBER | B5: No OF TIMBER | C5: PRICE OF TIMBER | E5: TOTAL COST | F5: TVA | G5: MSF | H5: TVA+MSF
A6: PINUS NINI | E6: =PRODUCT(B6*C6) -> 0 | F6: =PRODUCT(E6*18)/118 -> 0 | G6: =PRODUCT(B6*50) -> 0 | H6: =SUM(F6:G6) -> 0
A7: PINUS NTOYA | E7: =PRODUCT(B7*C7) -> 0 | F7: =PRODUCT(E7*18)/118 -> 0 | G7: =PRODUCT(B7*50) -> 0 | H7: =SUM(F7:G7) -> 0
A8: PINUS | B8: 620 | C8: 5900 | E8: =PRODUCT(B8*C8) -> 3658000 | F8: =PRODUCT(E8*18)/118 -> 558000 | G8: =PRODUCT(B8*50) -> 31000 | H8: =SUM(F8:G8) -> 589000
A9: MADIRIYE NINI | E9: =PRODUCT(B9*C9) -> 0 | F9: =PRODUCT(E9*18)/118 -> 0 | G9: =PRODUCT(B9*30) -> 0 | H9: =SUM(F9:G9) -> 0
A10: MADIRIYE NTOYA | B10: 34693 | C10: 2124 | E10: =PRODUCT(B10*C10) -> 73687932 | F10: =PRODUCT(E10*18)/118 -> 11240532 | G10: =PRODUCT(B10*30) -> 1040790 | H10: =SUM(F10:G10) -> 12281322
A11: MADRIEN | E11: =PRODUCT(B11*C11) -> 0 | F11: =PRODUCT(E11*18)/118 -> 0 | G11: =PRODUCT(B11*30) -> 0 | H11: =SUM(F11:G11) -> 0
A12: MADRIEN | E12: =PRODUCT(B12*C12) -> 0 | F12: =PRODUCT(E12*18)/118 -> 0 | G12: =PRODUCT(B12*30) -> 0 | H12: =SUM(F12:G12) -> 0
A13: PLANCHE | B13: 1837 | C13: 1357 | E13: =PRODUCT(B13*C13) -> 2492809 | F13: =PRODUCT(E13*18)/118 -> 380259 | G13: =PRODUCT(B13*20) -> 36740 | H13: =SUM(F13:G13) -> 416999
A14: PLANCHE | E14: =PRODUCT(B14*C14) -> 0 | F14: =PRODUCT(E14*18)/118 -> 0 | G14: =PRODUCT(B14*20) -> 0 | H14: =SUM(F14:G14) -> 0
A15: Other Timber for Difference Price
A16: NAME OF TIMBER | B16: No OF TIMBER | C16: P/U | D16: MSF | E16: TOTAL COST | F16: VAT | G16: MSF | H16: VTA+MST
A17: GEREVERIA | B17: 1008 | C17: 1180 | D17: 30 | E17: =PRODUCT(B17*C17) -> 1189440 | F17: =PRODUCT(E17*18)/118 -> 181440 | G17: =PRODUCT(B17*D17) -> 30240 | H17: =SUM(F17:G17) -> 211680
A18: GEREVERIA | B18: 944 | D18: 210 | E18: =PRODUCT(B18*C18) -> 0 | F18: =PRODUCT(E18*18)/118 -> 0 | G18: =PRODUCT(B18*D18) -> 198240 | H18: =SUM(F18:G18) -> 198240
A19: GEREVERIA | B19: 130 | D19: 200 | E19: =PRODUCT(B19*C19) -> 0 | F19: =PRODUCT(E19*18)/118 -> 0 | G19: =PRODUCT(B19*D19) -> 26000 | H19: =SUM(F19:G19) -> 26000
A20: UMUSAVE | E20: =PRODUCT(B20*C20) -> 0 | F20: =PRODUCT(E20*18)/118 -> 0 | G20: =PRODUCT(B20*D20) -> 0 | H20: =SUM(F20:G20) -> 0
A21: OTHER | E21: =PRODUCT(B21*C21) -> 0 | F21: =PRODUCT(E21*18)/118 -> 0 | G21: =PRODUCT(B21*D21) -> 0 | H21: =SUM(F21:G21) -> 0
A22: OTHER | E22: =PRODUCT(B22*C22) -> 0 | F22: =PRODUCT(E22*18)/118 -> 0 | G22: =PRODUCT(B22*D22) -> 0 | H22: =SUM(F22:G22) -> 0
A23: OTHER | E23: =PRODUCT(B23*C23) -> 0 | F23: =PRODUCT(E23*18)/118 -> 0 | G23: =PRODUCT(B23*D23) -> 0 | H23: =SUM(F23:G23) -> 0
A24: OTHER | E24: =PRODUCT(B24*C24) -> 0 | F24: =PRODUCT(E24*18)/118 -> 0 | G24: =PRODUCT(B24*D24) -> 0 | H24: =SUM(F24:G24) -> 0
A25: OTHER | E25: =PRODUCT(B25*C25) -> 0 | F25: =PRODUCT(E25*18)/118 -> 0 | G25: =PRODUCT(B25*D25) -> 0 | H25: =SUM(F25:G25) -> 0
A26: OTHER | E26: =PRODUCT(B26*C26) -> 0 | F26: =PRODUCT(E26*18)/118 -> 0 | G26: =PRODUCT(B26*D26) -> 0 | H26: =SUM(F26:G26) -> 0
A27: OTHER | E27: =PRODUCT(B27*C27) -> 0 | F27: =PRODUCT(E27*18)/118 -> 0 | G27: =PRODUCT(B27*D27) -> 0 | H27: =SUM(F27:G27) -> 0
A28: OTHER | E28: =PRODUCT(B28*C28) -> 0 | F28: =PRODUCT(E28*18)/118 -> 0 | G28: =PRODUCT(B28*D28) -> 0 | H28: =SUM(F28:G28) -> 0
A29: OTHER | E29: =PRODUCT(B29*C29) -> 0 | F29: =PRODUCT(E29*18)/118 -> 0 | G29: =PRODUCT(B29*D29) -> 0 | H29: =SUM(F29:G29) -> 0
A30: OTHER | E30: =PRODUCT(B30*C30) -> 0 | F30: =PRODUCT(E30*18)/118 -> 0 | G30: =PRODUCT(B30*D30) -> 0 | H30: =SUM(F30:G30) -> 0
A31: OTHER | E31: =PRODUCT(B31*C31) -> 0 | F31: =PRODUCT(E31*18)/118 -> 0 | G31: =PRODUCT(B31*D31) -> 0 | H31: =SUM(F31:G31) -> 0
... A34: OTHER | E34: =PRODUCT(B34*C34) -> 0 | F34: =PRODUCT(E34*18)/118 -> 0 | G34: =PRODUCT(B34*D34) -> 0 | H34: =SUM(F34:G34) -> 0
A35: OTHER | D35: 30 | E35: =PRODUCT(B35*C35) -> 0 | F35: =PRODUCT(E35*18)/118 -> 0 | G35: =PRODUCT(B35*D35) -> 0 | H35: =SUM(F35:G35) -> 0
A36: OTHER | E36: =PRODUCT(B36*C36) -> 0 | F36: =PRODUCT(E36*18)/118 -> 0 | G36: =PRODUCT(B36*D36) -> 0 | H36: =SUM(F36:G36) -> 0
A37: TOTALY | E37: =SUM(E5:E36) -> 81028181 | F37: =SUM(F5:F36) -> 12360231 | G37: =SUM(G5:G36) -> 1363010 | H37: =SUM(H5:H36) -> 13723241
A38: SUMMARY | C38: RWF | E38: NAME | G38: Phone | H38: RWF
A39: TOTAL RWF PAID ON MOMO PAY | C39: 13723241
A40: TOTAL RWF PAID ON CASH
A41: AMOUNT NOT INVOICED
A42: TOTAL RWF DEPPOSITED ON BANK
A43: MEMBERSHIP FEES REGISTRETION | C43: 50000
A44: MEMBERSHIP FEES CONTRIBUTION | C44: 100000
A45: TOTAL INCOME | C45: =SUM(C39+C40+C41+C42+C43+C44) -> 13873241
A46: TIMBER SUMMARY
A48: REPORT SUMMARY | C48: TIMBER TYPE | E48: NUMBER OF QUANTITY
C49: INTURUSU | E49: =SUM(B9:B12) -> 34693
C50: PINUS | E50: =SUM(B6:B8) -> 620
C51: PALNCHE | E51: =SUM(B13:B14) -> 1837
C52: IBIPANDE | E52: =SUM(B17:B18) -> 1952
C53: UMUSAVE | E53: =SUM(B19:B20) -> 130
C54: OTHER | E54: =B29 -> 0
C55: OTHER | E55: =B30 -> 0
C56: OTHER | E56: =B31 -> 0
C57: OTHER | E57: =B32 -> 0
C58: OTHER | E58: =B33 -> 0
C59: OTHER | E59: =B34 -> 0
C60: OTHER | E60: =B35 -> 0
C61: OTHER | E61: =B36 -> 0
C62: TOTAL TIMBER | E62: =SUM(E49:H61) -> 39232

Sheet KIMIRONKO
A1: QUANTITY REPORT
A3: MONTHS REPORT OF NOVEMBER 2025
A5: NAME OF TIMBER | B5: No OF TIMBER | C5: PRICE OF TIMBER | E5: TOTAL COST | F5: TVA | G5: MSF | H5: TVA+MSF
A6: PINUS NINI | E6: =PRODUCT(B6*C6) -> 0 | F6: =PRODUCT(E6*18)/118 -> 0 | G6: =PRODUCT(B6*50) -> 0 | H6: =SUM(F6:G6) -> 0
A7: PINUS NTOYA | E7: =PRODUCT(B7*C7) -> 0 | F7: =PRODUCT(E7*18)/118 -> 0 | G7: =PRODUCT(B7*50) -> 0 | H7: =SUM(F7:G7) -> 0
A8: PINUS | E8: =PRODUCT(B8*C8) -> 0 | F8: =PRODUCT(E8*18)/118 -> 0 | G8: =PRODUCT(B8*50) -> 0 | H8: =SUM(F8:G8) -> 0
A9: MADIRIYE NINI | E9: =PRODUCT(B9*C9) -> 0 | F9: =PRODUCT(E9*18)/118 -> 0 | G9: =PRODUCT(B9*30) -> 0 | H9: =SUM(F9:G9) -> 0
A10: MADIRIYE NTOYA | E10: =PRODUCT(B10*C10) -> 0 | F10: =PRODUCT(E10*18)/118 -> 0 | G10: =PRODUCT(B10*30) -> 0 | H10: =SUM(F10:G10) -> 0
A11: MADRIEN | E11: =PRODUCT(B11*C11) -> 0 | F11: =PRODUCT(E11*18)/118 -> 0 | G11: =PRODUCT(B11*30) -> 0 | H11: =SUM(F11:G11) -> 0
A12: MADRIEN | E12: =PRODUCT(B12*C12) -> 0 | F12: =PRODUCT(E12*18)/118 -> 0 | G12: =PRODUCT(B12*30) -> 0 | H12: =SUM(F12:G12) -> 0
A13: PLANCHE | E13: =PRODUCT(B13*C13) -> 0 | F13: =PRODUCT(E13*18)/118 -> 0 | G13: =PRODUCT(B13*20) -> 0 | H13: =SUM(F13:G13) -> 0
A14: PLANCHE | E14: =PRODUCT(B14*C14) -> 0 | F14: =PRODUCT(E14*18)/118 -> 0 | G14: =PRODUCT(B14*20) -> 0 | H14: =SUM(F14:G14) -> 0
A15: Other Timber for Difference Price
A16: NAME OF TIMBER | B16: No OF TIMBER | C16: P/U | D16: MSF | E16: TOTAL COST | F16: VAT | G16: MSF | H16: VTA+MST
A17: IBIPANDE | E17: =PRODUCT(B17*C17) -> 0 | F17: =PRODUCT(E17*18)/118 -> 0 | G17: =PRODUCT(B17*D17) -> 0 | H17: =SUM(F17:G17) -> 0
A18: IBIPANDE | E18: =PRODUCT(B18*C18) -> 0 | F18: =PRODUCT(E18*18)/118 -> 0 | G18: =PRODUCT(B18*D18) -> 0 | H18: =SUM(F18:G18) -> 0
A19: UMUSAVE | E19: =PRODUCT(B19*C19) -> 0 | F19: =PRODUCT(E19*18)/118 -> 0 | G19: =PRODUCT(B19*D19) -> 0 | H19: =SUM(F19:G19) -> 0
A20: UMUSAVE | E20: =PRODUCT(B20*C20) -> 0 | F20: =PRODUCT(E20*18)/118 -> 0 | G20: =PRODUCT(B20*D20) -> 0 | H20: =SUM(F20:G20) -> 0
A21: OTHER | E21: =PRODUCT(B21*C21) -> 0 | F21: =PRODUCT(E21*18)/118 -> 0 | G21: =PRODUCT(B21*D21) -> 0 | H21: =SUM(F21:G21) -> 0
A22: OTHER | E22: =PRODUCT(B22*C22) -> 0 | F22: =PRODUCT(E22*18)/118 -> 0 | G22: =PRODUCT(B22*D22) -> 0 | H22: =SUM(F22:G22) -> 0
A23: OTHER | E23: =PRODUCT(B23*C23) -> 0 | F23: =PRODUCT(E23*18)/118 -> 0 | G23: =PRODUCT(B23*D23) -> 0 | H23: =SUM(F23:G23) -> 0
A24: OTHER | E24: =PRODUCT(B24*C24) -> 0 | F24: =PRODUCT(E24*18)/118 -> 0 | G24: =PRODUCT(B24*D24) -> 0 | H24: =SUM(F24:G24) -> 0
A25: OTHER | E25: =PRODUCT(B25*C25) -> 0 | F25: =PRODUCT(E25*18)/118 -> 0 | G25: =PRODUCT(B25*D25) -> 0 | H25: =SUM(F25:G25) -> 0
A26: OTHER | E26: =PRODUCT(B26*C26) -> 0 | F26: =PRODUCT(E26*18)/118 -> 0 | G26: =PRODUCT(B26*D26) -> 0 | H26: =SUM(F26:G26) -> 0
A27: OTHER | E27: =PRODUCT(B27*C27) -> 0 | F27: =PRODUCT(E27*18)/118 -> 0 | G27: =PRODUCT(B27*D27) -> 0 | H27: =SUM(F27:G27) -> 0
A28: OTHER | E28: =PRODUCT(B28*C28) -> 0 | F28: =PRODUCT(E28*18)/118 -> 0 | G28: =PRODUCT(B28*D28) -> 0 | H28: =SUM(F28:G28) -> 0
... A36: OTHER | E36: =PRODUCT(B36*C36) -> 0 | F36: =PRODUCT(E36*18)/118 -> 0 | G36: =PRODUCT(B36*D36) -> 0 | H36: =SUM(F36:G36) -> 0
A37: TOTALY | E37: =SUM(E5:E36) -> 0 | F37: =SUM(F5:F36) -> 0 | G37: =SUM(G5:G36) -> 0 | H37: =SUM(H5:H36) -> 0
A38: SUMMARY | C38: RWF | E38: NAME | G38: Phone | H38: RWF
A39: TOTAL RWF PAID ON MOMO PAY
A40: TOTAL RWF PAID ON CASH
A41: AMOUNT NOT INVOICED
A42: TOTAL RWF DEPPOSITED ON BANK
A43: MEMBERSHIP FEES REGISTRETION
A44: MEMBERSHIP FEES CONTRIBUTION
A45: TOTAL INCOME | C45: =SUM(C39+C40+C41+C42+C43+C44) -> 0
A46: TIMBER SUMMARY
A48: REPORT SUMMARY | C48: TIMBER TYPE | E48: NUMBER OF QUANTITY
C49: INTURUSU | E49: =SUM(B9:B12) -> 0
C50: PINUS | E50: =SUM(B6:B8) -> 0
C51: PALNCHE | E51: =SUM(B13:B14) -> 0
C52: IBIPANDE | E52: =SUM(B17:B18) -> 0
C53: UMUSAVE | E53: =SUM(B19:B20) -> 0
C54: OTHER | E54: =B29 -> 0
C55: OTHER | E55: =B30 -> 0
C56: OTHER | E56: =B31 -> 0
C57: OTHER | E57: =B32 -> 0
C58: OTHER | E58: =B33 -> 0
C59: OTHER | E59: =B34 -> 0
C60: OTHER | E60: =B35 -> 0
C61: OTHER | E61: =B36 -> 0
C62: TOTAL TIMBER | E62: =SUM(E49:H61) -> 0

Sheet GAHANGA
A1: QUANTITY REPORT
A3: MONTHS REPORT OF NOVEMBER 2025
A5: NAME OF TIMBER | B5: No OF TIMBER | C5: PRICE OF TIMBER | E5: TOTAL COST | F5: TVA | G5: MSF | H5: TVA+MSF
A6: PINUS NINI | E6: =PRODUCT(B6*C6) -> 0 | F6: =PRODUCT(E6*18)/118 -> 0 | G6: =PRODUCT(B6*50) -> 0 | H6: =SUM(F6:G6) -> 0
A7: PINUS NTOYA | E7: =PRODUCT(B7*C7) -> 0 | F7: =PRODUCT(E7*18)/118 -> 0 | G7: =PRODUCT(B7*50) -> 0 | H7: =SUM(F7:G7) -> 0
A8: PINUS | E8: =PRODUCT(B8*C8) -> 0 | F8: =PRODUCT(E8*18)/118 -> 0 | G8: =PRODUCT(B8*50) -> 0 | H8: =SUM(F8:G8) -> 0
A9: MADIRIYE NINI | E9: =PRODUCT(B9*C9) -> 0 | F9: =PRODUCT(E9*18)/118 -> 0 | G9: =PRODUCT(B9*30) -> 0 | H9: =SUM(F9:G9) -> 0
A10: MADIRIYE NTOYA | E10: =PRODUCT(B10*C10) -> 0 | F10: =PRODUCT(E10*18)/118 -> 0 | G10: =PRODUCT(B10*30) -> 0 | H10: =SUM(F10:G10) -> 0
A11: MADRIEN | E11: =PRODUCT(B11*C11) -> 0 | F11: =PRODUCT(E11*18)/118 -> 0 | G11: =PRODUCT(B11*30) -> 0 | H11: =SUM(F11:G11) -> 0
A12: MADRIEN | E12: =PRODUCT(B12*C12) -> 0 | F12: =PRODUCT(E12*18)/118 -> 0 | G12: =PRODUCT(B12*30) -> 0 | H12: =SUM(F12:G12) -> 0
A13: PLANCHE | E13: =PRODUCT(B13*C13) -> 0 | F13: =PRODUCT(E13*18)/118 -> 0 | G13: =PRODUCT(B13*20) -> 0 | H13: =SUM(F13:G13) -> 0
A14: PLANCHE | E14: =PRODUCT(B14*C14) -> 0 | F14: =PRODUCT(E14*18)/118 -> 0 | G14: =PRODUCT(B14*20) -> 0 | H14: =SUM(F14:G14) -> 0
A15: Other Timber for Difference Price
A16: NAME OF TIMBER | B16: No OF TIMBER | C16: P/U | D16: MSF | E16: TOTAL COST | F16: VAT | G16: MSF | H16: VTA+MST
A17: IBIPANDE | D17: 30 | E17: =PRODUCT(B17*C17) -> 0 | F17: =PRODUCT(E17*18)/118 -> 0 | G17: =PRODUCT(B17*D17) -> 0 | H17: =SUM(F17:G17) -> 0
A18: IBIPANDE | E18: =PRODUCT(B18*C18) -> 0 | F18: =PRODUCT(E18*18)/118 -> 0 | G18: =PRODUCT(B18*D18) -> 0 | H18: =SUM(F18:G18) -> 0
A19: UMUSAVE | E19: =PRODUCT(B19*C19) -> 0 | F19: =PRODUCT(E19*18)/118 -> 0 | G19: =PRODUCT(B19*D19) -> 0 | H19: =SUM(F19:G19) -> 0
A20: UMUSAVE | E20: =PRODUCT(B20*C20) -> 0 | F20: =PRODUCT(E20*18)/118 -> 0 | G20: =PRODUCT(B20*D20) -> 0 | H20: =SUM(F20:G20) -> 0
A21: OTHER | E21: =PRODUCT(B21*C21) -> 0 | F21: =PRODUCT(E21*18)/118 -> 0 | G21: =PRODUCT(B21*D21) -> 0 | H21: =SUM(F21:G21) -> 0
A22: OTHER | E22: =PRODUCT(B22*C22) -> 0 | F22: =PRODUCT(E22*18)/118 -> 0 | G22: =PRODUCT(B22*D22) -> 0 | H22: =SUM(F22:G22) -> 0
A23: OTHER | E23: =PRODUCT(B23*C23) -> 0 | F23: =PRODUCT(E23*18)/118 -> 0 | G23: =PRODUCT(B23*D23) -> 0 | H23: =SUM(F23:G23) -> 0
A24: OTHER | E24: =PRODUCT(B24*C24) -> 0 | F24: =PRODUCT(E24*18)/118 -> 0 | G24: =PRODUCT(B24*D24) -> 0 | H24: =SUM(F24:G24) -> 0
A25: OTHER | E25: =PRODUCT(B25*C25) -> 0 | F25: =PRODUCT(E25*18)/118 -> 0 | G25: =PRODUCT(B25*D25) -> 0 | H25: =SUM(F25:G25) -> 0
A26: OTHER | E26: =PRODUCT(B26*C26) -> 0 | F26: =PRODUCT(E26*18)/118 -> 0 | G26: =PRODUCT(B26*D26) -> 0 | H26: =SUM(F26:G26) -> 0
A27: OTHER | E27: =PRODUCT(B27*C27) -> 0 | F27: =PRODUCT(E27*18)/118 -> 0 | G27: =PRODUCT(B27*D27) -> 0 | H27: =SUM(F27:G27) -> 0
A28: OTHER | E28: =PRODUCT(B28*C28) -> 0 | F28: =PRODUCT(E28*18)/118 -> 0 | G28: =PRODUCT(B28*D28) -> 0 | H28: =SUM(F28:G28) -> 0
A29: OTHER | E29: =PRODUCT(B29*C29) -> 0 | F29: =PRODUCT(E29*18)/118 -> 0 | G29: =PRODUCT(B29*D29) -> 0 | H29: =SUM(F29:G29) -> 0
... A34: OTHER | E34: =PRODUCT(B34*C34) -> 0 | F34: =PRODUCT(E34*18)/118 -> 0 | G34: =PRODUCT(B34*D34) -> 0 | H34: =SUM(F34:G34) -> 0
A35: OTHER | D35: 30 | E35: =PRODUCT(B35*C35) -> 0 | F35: =PRODUCT(E35*18)/118 -> 0 | G35: =PRODUCT(B35*D35) -> 0 | H35: =SUM(F35:G35) -> 0
A36: OTHER | E36: =PRODUCT(B36*C36) -> 0 | F36: =PRODUCT(E36*18)/118 -> 0 | G36: =PRODUCT(B36*D36) -> 0 | H36: =SUM(F36:G36) -> 0
A37: TOTALY | E37: =SUM(E5:E36) -> 0 | F37: =SUM(F5:F36) -> 0 | G37: =SUM(G5:G36) -> 0 | H37: =SUM(H5:H36) -> 0
A38: SUMMARY | C38: RWF | E38: NAME | G38: Phone | H38: RWF
A39: TOTAL RWF PAID ON MOMO PAY
A40: TOTAL RWF PAID ON CASH
A41: AMOUNT NOT INVOICED
A42: TOTAL RWF DEPPOSITED ON BANK
A43: MEMBERSHIP FEES REGISTRETION
A44: MEMBERSHIP FEES CONTRIBUTION
A45: TOTAL INCOME | C45: =SUM(C39+C40+C41+C42+C43+C44) -> 0
A46: TIMBER SUMMARY
A48: REPORT SUMMARY | C48: TIMBER TYPE | E48: NUMBER OF QUANTITY
C49: INTURUSU | E49: =SUM(B9:B12) -> 0
C50: PINUS | E50: =SUM(B6:B8) -> 0
C51: PALNCHE | E51: =SUM(B13:B14) -> 0
C52: IBIPANDE | E52: =SUM(B17:B18) -> 0
C53: UMUSAVE | E53: =SUM(B19:B20) -> 0
C54: OTHER | E54: =B29 -> 0
C55: OTHER | E55: =B30 -> 0
C56: OTHER | E56: =B31 -> 0
C57: OTHER | E57: =B32 -> 0
C58: OTHER | E58: =B33 -> 0
C59: OTHER | E59: =B34 -> 0
C60: OTHER | E60: =B35 -> 0
C61: OTHER | E61: =B36 -> 0
C62: TOTAL TIMBER | E62: =SUM(E49:H61) -> 0

Sheet BUGESERA
A1: QUANTITY REPORT
A3: MONTHS REPORT OF NOVEMBER 2025
A5: NAME OF TIMBER | B5: No OF TIMBER | C5: PRICE OF TIMBER | E5: TOTAL COST | F5: TVA | G5: MSF | H5: TVA+MSF
A6: PINUS NINI | E6: =PRODUCT(B6*C6) -> 0 | F6: =PRODUCT(E6*18)/118 -> 0 | G6: =PRODUCT(B6*50) -> 0 | H6: =SUM(F6:G6) -> 0
A7: PINUS NTOYA | E7: =PRODUCT(B7*C7) -> 0 | F7: =PRODUCT(E7*18)/118 -> 0 | G7: =PRODUCT(B7*50) -> 0 | H7: =SUM(F7:G7) -> 0
A8: PINUS | E8: =PRODUCT(B8*C8) -> 0 | F8: =PRODUCT(E8*18)/118 -> 0 | G8: =PRODUCT(B8*50) -> 0 | H8: =SUM(F8:G8) -> 0
A9: MADIRIYE NINI | E9: =PRODUCT(B9*C9) -> 0 | F9: =PRODUCT(E9*18)/118 -> 0 | G9: =PRODUCT(B9*30) -> 0 | H9: =SUM(F9:G9) -> 0
A10: MADIRIYE NTOYA | E10: =PRODUCT(B10*C10) -> 0 | F10: =PRODUCT(E10*18)/118 -> 0 | G10: =PRODUCT(B10*30) -> 0 | H10: =SUM(F10:G10) -> 0
A11: MADRIEN | E11: =PRODUCT(B11*C11) -> 0 | F11: =PRODUCT(E11*18)/118 -> 0 | G11: =PRODUCT(B11*30) -> 0 | H11: =SUM(F11:G11) -> 0
A12: MADRIEN | E12: =PRODUCT(B12*C12) -> 0 | F12: =PRODUCT(E12*18)/118 -> 0 | G12: =PRODUCT(B12*30) -> 0 | H12: =SUM(F12:G12) -> 0
A13: PLANCHE | E13: =PRODUCT(B13*C13) -> 0 | F13: =PRODUCT(E13*18)/118 -> 0 | G13: =PRODUCT(B13*20) -> 0 | H13: =SUM(F13:G13) -> 0
A14: PLANCHE | E14: =PRODUCT(B14*C14) -> 0 | F14: =PRODUCT(E14*18)/118 -> 0 | G14: =PRODUCT(B14*20) -> 0 | H14: =SUM(F14:G14) -> 0
A15: Other Timber for Difference Price
A16: NAME OF TIMBER | B16: No OF TIMBER | C16: P/U | D16: MSF | E16: TOTAL COST | F16: VAT | G16: MSF | H16: VTA+MST
A17: IBIPANDE | E17: =PRODUCT(B17*C17) -> 0 | F17: =PRODUCT(E17*18)/118 -> 0 | G17: =PRODUCT(B17*D17) -> 0 | H17: =SUM(F17:G17) -> 0
A18: IBIPANDE | E18: =PRODUCT(B18*C18) -> 0 | F18: =PRODUCT(E18*18)/118 -> 0 | G18: =PRODUCT(B18*D18) -> 0 | H18: =SUM(F18:G18) -> 0
A19: UMUSAVE | E19: =PRODUCT(B19*C19) -> 0 | F19: =PRODUCT(E19*18)/118 -> 0 | G19: =PRODUCT(B19*D19) -> 0 | H19: =SUM(F19:G19) -> 0
A20: UMUSAVE | E20: =PRODUCT(B20*C20) -> 0 | F20: =PRODUCT(E20*18)/118 -> 0 | G20: =PRODUCT(B20*D20) -> 0 | H20: =SUM(F20:G20) -> 0
A21: OTHER | E21: =PRODUCT(B21*C21) -> 0 | F21: =PRODUCT(E21*18)/118 -> 0 | G21: =PRODUCT(B21*D21) -> 0 | H21: =SUM(F21:G21) -> 0
A22: OTHER | E22: =PRODUCT(B22*C22) -> 0 | F22: =PRODUCT(E22*18)/118 -> 0 | G22: =PRODUCT(B22*D22) -> 0 | H22: =SUM(F22:G22) -> 0
A23: OTHER | E23: =PRODUCT(B23*C23) -> 0 | F23: =PRODUCT(E23*18)/118 -> 0 | G23: =PRODUCT(B23*D23) -> 0 | H23: =SUM(F23:G23) -> 0
A24: OTHER | E24: =PRODUCT(B24*C24) -> 0 | F24: =PRODUCT(E24*18)/118 -> 0 | G24: =PRODUCT(B24*D24) -> 0 | H24: =SUM(F24:G24) -> 0
A25: OTHER | E25: =PRODUCT(B25*C25) -> 0 | F25: =PRODUCT(E25*18)/118 -> 0 | G25: =PRODUCT(B25*D25) -> 0 | H25: =SUM(F25:G25) -> 0
A26: OTHER | E26: =PRODUCT(B26*C26) -> 0 | F26: =PRODUCT(E26*18)/118 -> 0 | G26: =PRODUCT(B26*D26) -> 0 | H26: =SUM(F26:G26) -> 0
A27: OTHER | E27: =PRODUCT(B27*C27) -> 0 | F27: =PRODUCT(E27*18)/118 -> 0 | G27: =PRODUCT(B27*D27) -> 0 | H27: =SUM(F27:G27) -> 0
A28: OTHER | E28: =PRODUCT(B28*C28) -> 0 | F28: =PRODUCT(E28*18)/118 -> 0 | G28: =PRODUCT(B28*D28) -> 0 | H28: =SUM(F28:G28) -> 0
... A36: OTHER | E36: =PRODUCT(B36*C36) -> 0 | F36: =PRODUCT(E36*18)/118 -> 0 | G36: =PRODUCT(B36*D36) -> 0 | H36: =SUM(F36:G36) -> 0
A37: TOTALY | E37: =SUM(E5:E36) -> 0 | F37: =SUM(F5:F36) -> 0 | G37: =SUM(G5:G36) -> 0 | H37: =SUM(H5:H36) -> 0
A38: SUMMARY | C38: RWF | E38: NAME | G38: Phone | H38: RWF
A39: TOTAL RWF PAID ON MOMO PAY
A40: TOTAL RWF PAID ON CASH
A41: AMOUNT NOT INVOICED
A42: TOTAL RWF DEPPOSITED ON BANK
A43: MEMBERSHIP FEES REGISTRETION
A44: MEMBERSHIP FEES CONTRIBUTION
A45: TOTAL INCOME | C45: =SUM(C39+C40+C41+C42+C43+C44) -> 0
A46: TIMBER SUMMARY
A48: REPORT SUMMARY | C48: TIMBER TYPE | E48: NUMBER OF QUANTITY
C49: INTURUSU | E49: =SUM(B9:B12) -> 0
C50: PINUS | E50: =SUM(B6:B8) -> 0
C51: PALNCHE | E51: =SUM(B13:B14) -> 0
C52: IBIPANDE | E52: =SUM(B17:B18) -> 0
C53: UMUSAVE | E53: =SUM(B19:B20) -> 0
C54: OTHER | E54: =B29 -> 0
C55: OTHER | E55: =B30 -> 0
C56: OTHER | E56: =B31 -> 0
C57: OTHER | E57: =B32 -> 0
C58: OTHER | E58: =B33 -> 0
C59: OTHER | E59: =B34 -> 0
C60: OTHER | E60: =B35 -> 0
C61: OTHER | E61: =B36 -> 0
C62: TOTAL TIMBER | E62: =SUM(E49:H61) -> 0

Sheet NYARUGENGE
A1: QUANTITY REPORT
A3: MONTHS REPORT OF NOVEMBER 2025
A5: NAME OF TIMBER | B5: No OF TIMBER | C5: PRICE OF TIMBER | E5: TOTAL COST | F5: TVA | G5: MSF | H5: TVA+MSF
A6: PINUS NINI | E6: =PRODUCT(B6*C6) -> 0 | F6: =PRODUCT(E6*18)/118 -> 0 | G6: =PRODUCT(B6*50) -> 0 | H6: =SUM(F6:G6) -> 0
A7: PINUS NTOYA | E7: =PRODUCT(B7*C7) -> 0 | F7: =PRODUCT(E7*18)/118 -> 0 | G7: =PRODUCT(B7*50) -> 0 | H7: =SUM(F7:G7) -> 0
A8: PINUS | E8: =PRODUCT(B8*C8) -> 0 | F8: =PRODUCT(E8*18)/118 -> 0 | G8: =PRODUCT(B8*50) -> 0 | H8: =SUM(F8:G8) -> 0
A9: MADIRIYE NINI | E9: =PRODUCT(B9*C9) -> 0 | F9: =PRODUCT(E9*18)/118 -> 0 | G9: =PRODUCT(B9*30) -> 0 | H9: =SUM(F9:G9) -> 0
A10: MADIRIYE NTOYA | E10: =PRODUCT(B10*C10) -> 0 | F10: =PRODUCT(E10*18)/118 -> 0 | G10: =PRODUCT(B10*30) -> 0 | H10: =SUM(F10:G10) -> 0
A11: MADRIEN | E11: =PRODUCT(B11*C11) -> 0 | F11: =PRODUCT(E11*18)/118 -> 0 | G11: =PRODUCT(B11*30) -> 0 | H11: =SUM(F11:G11) -> 0
A12: MADRIEN | E12: =PRODUCT(B12*C12) -> 0 | F12: =PRODUCT(E12*18)/118 -> 0 | G12: =PRODUCT(B12*30) -> 0 | H12: =SUM(F12:G12) -> 0
A13: PLANCHE | E13: =PRODUCT(B13*C13) -> 0 | F13: =PRODUCT(E13*18)/118 -> 0 | G13: =PRODUCT(B13*20) -> 0 | H13: =SUM(F13:G13) -> 0
A14: PLANCHE | E14: =PRODUCT(B14*C14) -> 0 | F14: =PRODUCT(E14*18)/118 -> 0 | G14: =PRODUCT(B14*20) -> 0 | H14: =SUM(F14:G14) -> 0
A15: Other Timber for Difference Price
A16: NAME OF TIMBER | B16: No OF TIMBER | C16: P/U | D16: MSF | E16: TOTAL COST | F16: VAT | G16: MSF | H16: VTA+MST
A17: IBIPANDE | E17: =PRODUCT(B17*C17) -> 0 | F17: =PRODUCT(E17*18)/118 -> 0 | G17: =PRODUCT(B17*D17) -> 0 | H17: =SUM(F17:G17) -> 0
A18: IBIPANDE | E18: =PRODUCT(B18*C18) -> 0 | F18: =PRODUCT(E18*18)/118 -> 0 | G18: =PRODUCT(B18*D18) -> 0 | H18: =SUM(F18:G18) -> 0
A19: UMUSAVE | E19: =PRODUCT(B19*C19) -> 0 | F19: =PRODUCT(E19*18)/118 -> 0 | G19: =PRODUCT(B19*D19) -> 0 | H19: =SUM(F19:G19) -> 0
A20: UMUSAVE | E20: =PRODUCT(B20*C20) -> 0 | F20: =PRODUCT(E20*18)/118 -> 0 | G20: =PRODUCT(B20*D20) -> 0 | H20: =SUM(F20:G20) -> 0
A21: OTHER | E21: =PRODUCT(B21*C21) -> 0 | F21: =PRODUCT(E21*18)/118 -> 0 | G21: =PRODUCT(B21*D21) -> 0 | H21: =SUM(F21:G21) -> 0
A22: OTHER | E22: =PRODUCT(B22*C22) -> 0 | F22: =PRODUCT(E22*18)/118 -> 0 | G22: =PRODUCT(B22*D22) -> 0 | H22: =SUM(F22:G22) -> 0
A23: OTHER | E23: =PRODUCT(B23*C23) -> 0 | F23: =PRODUCT(E23*18)/118 -> 0 | G23: =PRODUCT(B23*D23) -> 0 | H23: =SUM(F23:G23) -> 0
A24: OTHER | E24: =PRODUCT(B24*C24) -> 0 | F24: =PRODUCT(E24*18)/118 -> 0 | G24: =PRODUCT(B24*D24) -> 0 | H24: =SUM(F24:G24) -> 0
A25: OTHER | E25: =PRODUCT(B25*C25) -> 0 | F25: =PRODUCT(E25*18)/118 -> 0 | G25: =PRODUCT(B25*D25) -> 0 | H25: =SUM(F25:G25) -> 0
A26: OTHER | E26: =PRODUCT(B26*C26) -> 0 | F26: =PRODUCT(E26*18)/118 -> 0 | G26: =PRODUCT(B26*D26) -> 0 | H26: =SUM(F26:G26) -> 0
A27: OTHER | E27: =PRODUCT(B27*C27) -> 0 | F27: =PRODUCT(E27*18)/118 -> 0 | G27: =PRODUCT(B27*D27) -> 0 | H27: =SUM(F27:G27) -> 0
A28: OTHER | E28: =PRODUCT(B28*C28) -> 0 | F28: =PRODUCT(E28*18)/118 -> 0 | G28: =PRODUCT(B28*D28) -> 0 | H28: =SUM(F28:G28) -> 0
... A36: OTHER | E36: =PRODUCT(B36*C36) -> 0 | F36: =PRODUCT(E36*18)/118 -> 0 | G36: =PRODUCT(B36*D36) -> 0 | H36: =SUM(F36:G36) -> 0
A37: TOTALY | E37: =SUM(E5:E36) -> 0 | F37: =SUM(F5:F36) -> 0 | G37: =SUM(G5:G36) -> 0 | H37: =SUM(H5:H36) -> 0
A38: SUMMARY | C38: RWF | E38: NAME | G38: Phone | H38: RWF
A39: TOTAL RWF PAID ON MOMO PAY
A40: TOTAL RWF PAID ON CASH
A41: AMOUNT NOT INVOICED
A42: TOTAL RWF DEPPOSITED ON BANK
A43: MEMBERSHIP FEES REGISTRETION
A44: MEMBERSHIP FEES CONTRIBUTION
A45: TOTAL INCOME | C45: =SUM(C39+C40+C41+C42+C43+C44) -> 0
A46: TIMBER SUMMARY
A48: REPORT SUMMARY | C48: TIMBER TYPE | E48: NUMBER OF QUANTITY
C49: INTURUSU | E49: =SUM(B9:B12) -> 0
C50: PINUS | E50: =SUM(B6:B8) -> 0
C51: PALNCHE | E51: =SUM(B13:B14) -> 0
C52: IBIPANDE | E52: =SUM(B17:B18) -> 0
C53: UMUSAVE | E53: =SUM(B19:B20) -> 0
C54: OTHER | E54: =B29 -> 0
C55: OTHER | E55: =B30 -> 0
C56: OTHER | E56: =B31 -> 0
C57: OTHER | E57: =B32 -> 0
C58: OTHER | E58: =B33 -> 0
C59: OTHER | E59: =B34 -> 0
C60: OTHER | E60: =B35 -> 0
C61: OTHER | E61: =B36 -> 0
C62: TOTAL TIMBER | E62: =SUM(E49:H61) -> 0

Sheet MUHANGA
A1: QUANTITY REPORT
A3: MONTHS REPORT OF NOVEMBER 2025
A5: NAME OF TIMBER | B5: No OF TIMBER | C5: PRICE OF TIMBER | E5: TOTAL COST | F5: TVA | G5: MSF | H5: TVA+MSF
A6: PINUS NINI | E6: =PRODUCT(B6*C6) -> 0 | F6: =PRODUCT(E6*18)/118 -> 0 | G6: =PRODUCT(B6*50) -> 0 | H6: =SUM(F6:G6) -> 0
A7: PINUS NTOYA | E7: =PRODUCT(B7*C7) -> 0 | F7: =PRODUCT(E7*18)/118 -> 0 | G7: =PRODUCT(B7*50) -> 0 | H7: =SUM(F7:G7) -> 0
A8: PINUS | E8: =PRODUCT(B8*C8) -> 0 | F8: =PRODUCT(E8*18)/118 -> 0 | G8: =PRODUCT(B8*50) -> 0 | H8: =SUM(F8:G8) -> 0
A9: MADIRIYE NINI | E9: =PRODUCT(B9*C9) -> 0 | F9: =PRODUCT(E9*18)/118 -> 0 | G9: =PRODUCT(B9*30) -> 0 | H9: =SUM(F9:G9) -> 0
A10: MADIRIYE NTOYA | E10: =PRODUCT(B10*C10) -> 0 | F10: =PRODUCT(E10*18)/118 -> 0 | G10: =PRODUCT(B10*30) -> 0 | H10: =SUM(F10:G10) -> 0
A11: MADRIEN | E11: =PRODUCT(B11*C11) -> 0 | F11: =PRODUCT(E11*18)/118 -> 0 | G11: =PRODUCT(B11*30) -> 0 | H11: =SUM(F11:G11) -> 0
A12: MADRIEN | E12: =PRODUCT(B12*C12) -> 0 | F12: =PRODUCT(E12*18)/118 -> 0 | G12: =PRODUCT(B12*30) -> 0 | H12: =SUM(F12:G12) -> 0
A13: PLANCHE | E13: =PRODUCT(B13*C13) -> 0 | F13: =PRODUCT(E13*18)/118 -> 0 | G13: =PRODUCT(B13*20) -> 0 | H13: =SUM(F13:G13) -> 0
A14: PLANCHE | E14: =PRODUCT(B14*C14) -> 0 | F14: =PRODUCT(E14*18)/118 -> 0 | G14: =PRODUCT(B14*20) -> 0 | H14: =SUM(F14:G14) -> 0
A15: Other Timber for Difference Price
A16: NAME OF TIMBER | B16: No OF TIMBER | C16: P/U | D16: MSF | E16: TOTAL COST | F16: VAT | G16: MSF | H16: VTA+MST
A17: IBIPANDE | E17: =PRODUCT(B17*C17) -> 0 | F17: =PRODUCT(E17*18)/118 -> 0 | G17: =PRODUCT(B17*D17) -> 0 | H17: =SUM(F17:G17) -> 0
A18: IBIPANDE | E18: =PRODUCT(B18*C18) -> 0 | F18: =PRODUCT(E18*18)/118 -> 0 | G18: =PRODUCT(B18*D18) -> 0 | H18: =SUM(F18:G18) -> 0
A19: UMUSAVE | E19: =PRODUCT(B19*C19) -> 0 | F19: =PRODUCT(E19*18)/118 -> 0 | G19: =PRODUCT(B19*D19) -> 0 | H19: =SUM(F19:G19) -> 0
A20: UMUSAVE | E20: =PRODUCT(B20*C20) -> 0 | F20: =PRODUCT(E20*18)/118 -> 0 | G20: =PRODUCT(B20*D20) -> 0 | H20: =SUM(F20:G20) -> 0
A21: OTHER | E21: =PRODUCT(B21*C21) -> 0 | F21: =PRODUCT(E21*18)/118 -> 0 | G21: =PRODUCT(B21*D21) -> 0 | H21: =SUM(F21:G21) -> 0
A22: OTHER | E22: =PRODUCT(B22*C22) -> 0 | F22: =PRODUCT(E22*18)/118 -> 0 | G22: =PRODUCT(B22*D22) -> 0 | H22: =SUM(F22:G22) -> 0
A23: OTHER | E23: =PRODUCT(B23*C23) -> 0 | F23: =PRODUCT(E23*18)/118 -> 0 | G23: =PRODUCT(B23*D23) -> 0 | H23: =SUM(F23:G23) -> 0
A24: OTHER | E24: =PRODUCT(B24*C24) -> 0 | F24: =PRODUCT(E24*18)/118 -> 0 | G24: =PRODUCT(B24*D24) -> 0 | H24: =SUM(F24:G24) -> 0
A25: OTHER | E25: =PRODUCT(B25*C25) -> 0 | F25: =PRODUCT(E25*18)/118 -> 0 | G25: =PRODUCT(B25*D25) -> 0 | H25: =SUM(F25:G25) -> 0
A26: OTHER | E26: =PRODUCT(B26*C26) -> 0 | F26: =PRODUCT(E26*18)/118 -> 0 | G26: =PRODUCT(B26*D26) -> 0 | H26: =SUM(F26:G26) -> 0
A27: OTHER | E27: =PRODUCT(B27*C27) -> 0 | F27: =PRODUCT(E27*18)/118 -> 0 | G27: =PRODUCT(B27*D27) -> 0 | H27: =SUM(F27:G27) -> 0
A28: OTHER | E28: =PRODUCT(B28*C28) -> 0 | F28: =PRODUCT(E28*18)/118 -> 0 | G28: =PRODUCT(B28*D28) -> 0 | H28: =SUM(F28:G28) -> 0
... A36: OTHER | E36: =PRODUCT(B36*C36) -> 0 | F36: =PRODUCT(E36*18)/118 -> 0 | G36: =PRODUCT(B36*D36) -> 0 | H36: =SUM(F36:G36) -> 0
A37: TOTALY | E37: =SUM(E5:E36) -> 0 | F37: =SUM(F5:F36) -> 0 | G37: =SUM(G5:G36) -> 0 | H37: =SUM(H5:H36) -> 0
A38: SUMMARY | C38: RWF | E38: NAME | G38: Phone | H38: RWF
A39: TOTAL RWF PAID ON MOMO PAY
A40: TOTAL RWF PAID ON CASH
A41: AMOUNT NOT INVOICED
A42: TOTAL RWF DEPPOSITED ON BANK
A43: MEMBERSHIP FEES REGISTRETION
A44: MEMBERSHIP FEES CONTRIBUTION
A45: TOTAL INCOME | C45: =SUM(C39+C40+C41+C42+C43+C44) -> 0
A46: TIMBER SUMMARY
A48: REPORT SUMMARY | C48: TIMBER TYPE | E48: NUMBER OF QUANTITY
C49: INTURUSU | E49: =SUM(B9:B12) -> 0
C50: PINUS | E50: =SUM(B6:B8) -> 0
C51: PALNCHE | E51: =SUM(B13:B14) -> 0
C52: IBIPANDE | E52: =SUM(B17:B18) -> 0
C53: UMUSAVE | E53: =SUM(B19:B20) -> 0
C54: OTHER | E54: =B29 -> 0
C55: OTHER | E55: =B30 -> 0
C56: OTHER | E56: =B31 -> 0
C57: OTHER | E57: =B32 -> 0
C58: OTHER | E58: =B33 -> 0
C59: OTHER | E59: =B34 -> 0
C60: OTHER | E60: =B35 -> 0
C61: OTHER | E61: =B36 -> 0
C62: TOTAL TIMBER | E62: =SUM(E49:H61) -> 0

Sheet HUYE
A1: QUANTITY REPORT
A3: NYAMAGABE MONTHS REPORT OF MARCH 2026
A5: NAME OF TIMBER | B5: No OF TIMBER | C5: PRICE OF TIMBER | E5: TOTAL COST | F5: TVA | G5: MSF | H5: TVA+MSF
A6: PINUS | C6: 9440 | E6: =PRODUCT(B6*C6) -> 0 | F6: =PRODUCT(E6*18)/118 -> 0 | G6: =PRODUCT(B6*50) -> 0 | H6: =SUM(F6:G6) -> 0
A7: PINUS NTOYA | B7: 180 | C7: 8260 | E7: =PRODUCT(B7*C7) -> 1486800 | F7: =PRODUCT(E7*18)/118 -> 226800 | G7: =PRODUCT(B7*50) -> 9000 | H7: =SUM(F7:G7) -> 235800
A8: IBIPANDE PINUS | C8: 2360 | E8: =PRODUCT(B8*C8) -> 0 | F8: =PRODUCT(E8*18)/118 -> 0 | G8: =PRODUCT(B8*50) -> 0 | H8: =SUM(F8:G8) -> 0
A9: MADIRIYE NINI | C9: 4130 | E9: =PRODUCT(B9*C9) -> 0 | F9: =PRODUCT(E9*18)/118 -> 0 | G9: =PRODUCT(B9*30) -> 0 | H9: =SUM(F9:G9) -> 0
A10: MADIRIYE NTOYA | C10: 2360 | E10: =PRODUCT(B10*C10) -> 0 | F10: =PRODUCT(E10*18)/118 -> 0 | G10: =PRODUCT(B10*30) -> 0 | H10: =SUM(F10:G10) -> 0
A11: MADRIEN | C11: 4300 | E11: =PRODUCT(B11*C11) -> 0 | F11: =PRODUCT(E11*18)/118 -> 0 | G11: =PRODUCT(B11*30) -> 0 | H11: =SUM(F11:G11) -> 0
A12: MADRIEN | E12: =PRODUCT(B12*C12) -> 0 | F12: =PRODUCT(E12*18)/118 -> 0 | G12: =PRODUCT(B12*30) -> 0 | H12: =SUM(F12:G12) -> 0
A13: GEREVERIYA | C13: 1180 | E13: =PRODUCT(B13*C13) -> 0 | F13: =PRODUCT(E13*18)/118 -> 0 | G13: =PRODUCT(B13*20) -> 0 | H13: =SUM(F13:G13) -> 0
A14: PLANCHE | E14: =PRODUCT(B14*C14) -> 0 | F14: =PRODUCT(E14*18)/118 -> 0 | G14: =PRODUCT(B14*20) -> 0 | H14: =SUM(F14:G14) -> 0
A15: Other Timber for Difference Price
A16: NAME OF TIMBER | B16: No OF TIMBER | C16: P/U | D16: MSF | E16: TOTAL COST | F16: VAT | G16: MSF | H16: VTA+MST
A17: DECHETS | B17: 16 | C17: 10000 | D17: 1500 | E17: =PRODUCT(B17*C17) -> 160000 | F17: =PRODUCT(E17*18)/118 -> 24406.78 | G17: =PRODUCT(B17*D17) -> 24000 | H17: =SUM(F17:G17) -> 48406.78
A18: DECHETS | E18: =PRODUCT(B18*C18) -> 0 | F18: =PRODUCT(E18*18)/118 -> 0 | G18: =PRODUCT(B18*D18) -> 0 | H18: =SUM(F18:G18) -> 0
A19: UMUSAVE | E19: =PRODUCT(B19*C19) -> 0 | F19: =PRODUCT(E19*18)/118 -> 0 | G19: =PRODUCT(B19*D19) -> 0 | H19: =SUM(F19:G19) -> 0
A20: UMUSAVE | E20: =PRODUCT(B20*C20) -> 0 | F20: =PRODUCT(E20*18)/118 -> 0 | G20: =PRODUCT(B20*D20) -> 0 | H20: =SUM(F20:G20) -> 0
A21: OTHER | E21: =PRODUCT(B21*C21) -> 0 | F21: =PRODUCT(E21*18)/118 -> 0 | G21: =PRODUCT(B21*D21) -> 0 | H21: =SUM(F21:G21) -> 0
A22: OTHER | E22: =PRODUCT(B22*C22) -> 0 | F22: =PRODUCT(E22*18)/118 -> 0 | G22: =PRODUCT(B22*D22) -> 0 | H22: =SUM(F22:G22) -> 0
A23: OTHER | E23: =PRODUCT(B23*C23) -> 0 | F23: =PRODUCT(E23*18)/118 -> 0 | G23: =PRODUCT(B23*D23) -> 0 | H23: =SUM(F23:G23) -> 0
A24: OTHER | E24: =PRODUCT(B24*C24) -> 0 | F24: =PRODUCT(E24*18)/118 -> 0 | G24: =PRODUCT(B24*D24) -> 0 | H24: =SUM(F24:G24) -> 0
A25: OTHER | E25: =PRODUCT(B25*C25) -> 0 | F25: =PRODUCT(E25*18)/118 -> 0 | G25: =PRODUCT(B25*D25) -> 0 | H25: =SUM(F25:G25) -> 0
A26: OTHER | E26: =PRODUCT(B26*C26) -> 0 | F26: =PRODUCT(E26*18)/118 -> 0 | G26: =PRODUCT(B26*D26) -> 0 | H26: =SUM(F26:G26) -> 0
A27: OTHER | E27: =PRODUCT(B27*C27) -> 0 | F27: =PRODUCT(E27*18)/118 -> 0 | G27: =PRODUCT(B27*D27) -> 0 | H27: =SUM(F27:G27) -> 0
A28: OTHER | E28: =PRODUCT(B28*C28) -> 0 | F28: =PRODUCT(E28*18)/118 -> 0 | G28: =PRODUCT(B28*D28) -> 0 | H28: =SUM(F28:G28) -> 0
A29: OTHER | E29: =PRODUCT(B29*C29) -> 0 | F29: =PRODUCT(E29*18)/118 -> 0 | G29: =PRODUCT(B29*D29) -> 0 | H29: =SUM(F29:G29) -> 0
... A36: OTHER | E36: =PRODUCT(B36*C36) -> 0 | F36: =PRODUCT(E36*18)/118 -> 0 | G36: =PRODUCT(B36*D36) -> 0 | H36: =SUM(F36:G36) -> 0
A37: TOTALY | E37: =SUM(E5:E36) -> 1646800 | F37: =SUM(F5:F36) -> 251206.78 | G37: =SUM(G5:G36) -> 33000 | H37: =SUM(H5:H36) -> 284206.78
A38: SUMMARY | C38: RWF | E38: NAME | G38: Phone | H38: RWF
A39: TOTAL RWF PAID ON MOMO PAY
A40: TOTAL RWF PAID ON CASH
A41: AMOUNT NOT INVOICED
A42: TOTAL RWF DEPPOSITED ON BANK
A43: MEMBERSHIP FEES REGISTRETION
A44: MEMBERSHIP FEES CONTRIBUTION
A45: TOTAL INCOME | C45: =SUM(C39+C40+C41+C42+C43+C44) -> 0
A46: TIMBER SUMMARY
A48: REPORT SUMMARY | C48: TIMBER TYPE | E48: NUMBER OF QUANTITY
C49: INTURUSU | E49: =SUM(B9:B12) -> 0
C50: PINUS | E50: =SUM(B6:B8) -> 180
C51: PALNCHE | E51: =SUM(B13:B14) -> 0
C52: IBIPANDE | E52: =SUM(B17:B18) -> 16
C53: UMUSAVE | E53: =SUM(B19:B20) -> 0
C54: OTHER | E54: =B29 -> 0
C55: OTHER | E55: =B30 -> 0
C56: OTHER | E56: =B31 -> 0
C57: OTHER | E57: =B32 -> 0
C58: OTHER | E58: =B33 -> 0
C59: OTHER | E59: =B34 -> 0
C60: OTHER | E60: =B35 -> 0
C61: OTHER | E61: =B36 -> 0
C62: TOTAL TIMBER | E62: =SUM(E49:H61) -> 196

Sheet Sheet1

Sheet Sheet2

Sheet Sheet3

Sheet Sheet4

Sheet Sheet5

Sheet Sheet6

Sheet Sheet7

Sheet Sheet8

Sheet Sheet9

Sheet Sheet10

Sheet Sheet11

Sheet Sheet12

Sheet Sheet13

Sheet Sheet14

Sheet Sheet15

Sheet Sheet16

Sheet NYAMASHEKE
A1: QUANTITY REPORT
A3: MONTHS REPORT OF NOVEMBER 2025
A5: NAME OF TIMBER | B5: No OF TIMBER | C5: PRICE OF TIMBER | E5: TOTAL COST | F5: TVA | G5: MSF | H5: TVA+MSF
A6: PINUS NINI | E6: =PRODUCT(B6*C6) -> 0 | F6: =PRODUCT(E6*18)/118 -> 0 | G6: =PRODUCT(B6*50) -> 0 | H6: =SUM(F6:G6) -> 0
A7: PINUS NTOYA | E7: =PRODUCT(B7*C7) -> 0 | F7: =PRODUCT(E7*18)/118 -> 0 | G7: =PRODUCT(B7*50) -> 0 | H7: =SUM(F7:G7) -> 0
A8: PINUS | E8: =PRODUCT(B8*C8) -> 0 | F8: =PRODUCT(E8*18)/118 -> 0 | G8: =PRODUCT(B8*50) -> 0 | H8: =SUM(F8:G8) -> 0
A9: MADIRIYE NINI | E9: =PRODUCT(B9*C9) -> 0 | F9: =PRODUCT(E9*18)/118 -> 0 | G9: =PRODUCT(B9*30) -> 0 | H9: =SUM(F9:G9) -> 0
A10: MADIRIYE NTOYA | E10: =PRODUCT(B10*C10) -> 0 | F10: =PRODUCT(E10*18)/118 -> 0 | G10: =PRODUCT(B10*30) -> 0 | H10: =SUM(F10:G10) -> 0
A11: MADRIEN | E11: =PRODUCT(B11*C11) -> 0 | F11: =PRODUCT(E11*18)/118 -> 0 | G11: =PRODUCT(B11*30) -> 0 | H11: =SUM(F11:G11) -> 0
A12: MADRIEN | E12: =PRODUCT(B12*C12) -> 0 | F12: =PRODUCT(E12*18)/118 -> 0 | G12: =PRODUCT(B12*30) -> 0 | H12: =SUM(F12:G12) -> 0
A13: PLANCHE | E13: =PRODUCT(B13*C13) -> 0 | F13: =PRODUCT(E13*18)/118 -> 0 | G13: =PRODUCT(B13*20) -> 0 | H13: =SUM(F13:G13) -> 0
A14: PLANCHE | E14: =PRODUCT(B14*C14) -> 0 | F14: =PRODUCT(E14*18)/118 -> 0 | G14: =PRODUCT(B14*20) -> 0 | H14: =SUM(F14:G14) -> 0
A15: Other Timber for Difference Price
A16: NAME OF TIMBER | B16: No OF TIMBER | C16: P/U | D16: MSF | E16: TOTAL COST | F16: VAT | G16: MSF | H16: VTA+MST
A17: IBIPANDE | E17: =PRODUCT(B17*C17) -> 0 | F17: =PRODUCT(E17*18)/118 -> 0 | G17: =PRODUCT(B17*D17) -> 0 | H17: =SUM(F17:G17) -> 0
A18: IBIPANDE | E18: =PRODUCT(B18*C18) -> 0 | F18: =PRODUCT(E18*18)/118 -> 0 | G18: =PRODUCT(B18*D18) -> 0 | H18: =SUM(F18:G18) -> 0
A19: UMUSAVE | E19: =PRODUCT(B19*C19) -> 0 | F19: =PRODUCT(E19*18)/118 -> 0 | G19: =PRODUCT(B19*D19) -> 0 | H19: =SUM(F19:G19) -> 0
A20: UMUSAVE | E20: =PRODUCT(B20*C20) -> 0 | F20: =PRODUCT(E20*18)/118 -> 0 | G20: =PRODUCT(B20*D20) -> 0 | H20: =SUM(F20:G20) -> 0
A21: OTHER | E21: =PRODUCT(B21*C21) -> 0 | F21: =PRODUCT(E21*18)/118 -> 0 | G21: =PRODUCT(B21*D21) -> 0 | H21: =SUM(F21:G21) -> 0
A22: OTHER | E22: =PRODUCT(B22*C22) -> 0 | F22: =PRODUCT(E22*18)/118 -> 0 | G22: =PRODUCT(B22*D22) -> 0 | H22: =SUM(F22:G22) -> 0
A23: OTHER | E23: =PRODUCT(B23*C23) -> 0 | F23: =PRODUCT(E23*18)/118 -> 0 | G23: =PRODUCT(B23*D23) -> 0 | H23: =SUM(F23:G23) -> 0
A24: OTHER | E24: =PRODUCT(B24*C24) -> 0 | F24: =PRODUCT(E24*18)/118 -> 0 | G24: =PRODUCT(B24*D24) -> 0 | H24: =SUM(F24:G24) -> 0
A25: OTHER | E25: =PRODUCT(B25*C25) -> 0 | F25: =PRODUCT(E25*18)/118 -> 0 | G25: =PRODUCT(B25*D25) -> 0 | H25: =SUM(F25:G25) -> 0
A26: OTHER | E26: =PRODUCT(B26*C26) -> 0 | F26: =PRODUCT(E26*18)/118 -> 0 | G26: =PRODUCT(B26*D26) -> 0 | H26: =SUM(F26:G26) -> 0
A27: OTHER | E27: =PRODUCT(B27*C27) -> 0 | F27: =PRODUCT(E27*18)/118 -> 0 | G27: =PRODUCT(B27*D27) -> 0 | H27: =SUM(F27:G27) -> 0
A28: OTHER | E28: =PRODUCT(B28*C28) -> 0 | F28: =PRODUCT(E28*18)/118 -> 0 | G28: =PRODUCT(B28*D28) -> 0 | H28: =SUM(F28:G28) -> 0
... A36: OTHER | E36: =PRODUCT(B36*C36) -> 0 | F36: =PRODUCT(E36*18)/118 -> 0 | G36: =PRODUCT(B36*D36) -> 0 | H36: =SUM(F36:G36) -> 0
A37: TOTALY | E37: =SUM(E5:E36) -> 0 | F37: =SUM(F5:F36) -> 0 | G37: =SUM(G5:G36) -> 0 | H37: =SUM(H5:H36) -> 0
A38: SUMMARY | C38: RWF | E38: NAME | G38: Phone | H38: RWF
A39: TOTAL RWF PAID ON MOMO PAY
A40: TOTAL RWF PAID ON CASH
A41: AMOUNT NOT INVOICED
A42: TOTAL RWF DEPPOSITED ON BANK
A43: MEMBERSHIP FEES REGISTRETION
A44: MEMBERSHIP FEES CONTRIBUTION
A45: TOTAL INCOME | C45: =SUM(C39+C40+C41+C42+C43+C44) -> 0
A46: TIMBER SUMMARY
A48: REPORT SUMMARY | C48: TIMBER TYPE | E48: NUMBER OF QUANTITY
C49: INTURUSU | E49: =SUM(B9:B12) -> 0
C50: PINUS | E50: =SUM(B6:B8) -> 0
C51: PALNCHE | E51: =SUM(B13:B14) -> 0
C52: IBIPANDE | E52: =SUM(B17:B18) -> 0
C53: UMUSAVE | E53: =SUM(B19:B20) -> 0
C54: OTHER | E54: =B29 -> 0
C55: OTHER | E55: =B30 -> 0
C56: OTHER | E56: =B31 -> 0
C57: OTHER | E57: =B32 -> 0
C58: OTHER | E58: =B33 -> 0
C59: OTHER | E59: =B34 -> 0
C60: OTHER | E60: =B35 -> 0
C61: OTHER | E61: =B36 -> 0
C62: TOTAL TIMBER | E62: =SUM(E49:H61) -> 0

Sheet KAYONZA
A1: QUANTITY REPORT
A3: MONTHS REPORT OF NOVEMBER 2025
A5: NAME OF TIMBER | B5: No OF TIMBER | C5: PRICE OF TIMBER | E5: TOTAL COST | F5: TVA | G5: MSF | H5: TVA+MSF
A6: PINUS NINI | E6: =PRODUCT(B6*C6) -> 0 | F6: =PRODUCT(E6*18)/118 -> 0 | G6: =PRODUCT(B6*50) -> 0 | H6: =SUM(F6:G6) -> 0
A7: PINUS NTOYA | E7: =PRODUCT(B7*C7) -> 0 | F7: =PRODUCT(E7*18)/118 -> 0 | G7: =PRODUCT(B7*50) -> 0 | H7: =SUM(F7:G7) -> 0
A8: PINUS | E8: =PRODUCT(B8*C8) -> 0 | F8: =PRODUCT(E8*18)/118 -> 0 | G8: =PRODUCT(B8*50) -> 0 | H8: =SUM(F8:G8) -> 0
A9: MADIRIYE NINI | E9: =PRODUCT(B9*C9) -> 0 | F9: =PRODUCT(E9*18)/118 -> 0 | G9: =PRODUCT(B9*30) -> 0 | H9: =SUM(F9:G9) -> 0
A10: MADIRIYE NTOYA | E10: =PRODUCT(B10*C10) -> 0 | F10: =PRODUCT(E10*18)/118 -> 0 | G10: =PRODUCT(B10*30) -> 0 | H10: =SUM(F10:G10) -> 0
A11: MADRIEN | E11: =PRODUCT(B11*C11) -> 0 | F11: =PRODUCT(E11*18)/118 -> 0 | G11: =PRODUCT(B11*30) -> 0 | H11: =SUM(F11:G11) -> 0
A12: MADRIEN | E12: =PRODUCT(B12*C12) -> 0 | F12: =PRODUCT(E12*18)/118 -> 0 | G12: =PRODUCT(B12*30) -> 0 | H12: =SUM(F12:G12) -> 0
A13: PLANCHE | E13: =PRODUCT(B13*C13) -> 0 | F13: =PRODUCT(E13*18)/118 -> 0 | G13: =PRODUCT(B13*20) -> 0 | H13: =SUM(F13:G13) -> 0
A14: PLANCHE | E14: =PRODUCT(B14*C14) -> 0 | F14: =PRODUCT(E14*18)/118 -> 0 | G14: =PRODUCT(B14*20) -> 0 | H14: =SUM(F14:G14) -> 0
A15: Other Timber for Difference Price
A16: NAME OF TIMBER | B16: No OF TIMBER | C16: P/U | D16: MSF | E16: TOTAL COST | F16: VAT | G16: MSF | H16: VTA+MST
A17: IBIPANDE | E17: =PRODUCT(B17*C17) -> 0 | F17: =PRODUCT(E17*18)/118 -> 0 | G17: =PRODUCT(B17*D17) -> 0 | H17: =SUM(F17:G17) -> 0
A18: IBIPANDE | E18: =PRODUCT(B18*C18) -> 0 | F18: =PRODUCT(E18*18)/118 -> 0 | G18: =PRODUCT(B18*D18) -> 0 | H18: =SUM(F18:G18) -> 0
A19: UMUSAVE | E19: =PRODUCT(B19*C19) -> 0 | F19: =PRODUCT(E19*18)/118 -> 0 | G19: =PRODUCT(B19*D19) -> 0 | H19: =SUM(F19:G19) -> 0
A20: UMUSAVE | E20: =PRODUCT(B20*C20) -> 0 | F20: =PRODUCT(E20*18)/118 -> 0 | G20: =PRODUCT(B20*D20) -> 0 | H20: =SUM(F20:G20) -> 0
A21: OTHER | E21: =PRODUCT(B21*C21) -> 0 | F21: =PRODUCT(E21*18)/118 -> 0 | G21: =PRODUCT(B21*D21) -> 0 | H21: =SUM(F21:G21) -> 0
A22: OTHER | E22: =PRODUCT(B22*C22) -> 0 | F22: =PRODUCT(E22*18)/118 -> 0 | G22: =PRODUCT(B22*D22) -> 0 | H22: =SUM(F22:G22) -> 0
A23: OTHER | E23: =PRODUCT(B23*C23) -> 0 | F23: =PRODUCT(E23*18)/118 -> 0 | G23: =PRODUCT(B23*D23) -> 0 | H23: =SUM(F23:G23) -> 0
A24: OTHER | E24: =PRODUCT(B24*C24) -> 0 | F24: =PRODUCT(E24*18)/118 -> 0 | G24: =PRODUCT(B24*D24) -> 0 | H24: =SUM(F24:G24) -> 0
A25: OTHER | E25: =PRODUCT(B25*C25) -> 0 | F25: =PRODUCT(E25*18)/118 -> 0 | G25: =PRODUCT(B25*D25) -> 0 | H25: =SUM(F25:G25) -> 0
A26: OTHER | E26: =PRODUCT(B26*C26) -> 0 | F26: =PRODUCT(E26*18)/118 -> 0 | G26: =PRODUCT(B26*D26) -> 0 | H26: =SUM(F26:G26) -> 0
A27: OTHER | E27: =PRODUCT(B27*C27) -> 0 | F27: =PRODUCT(E27*18)/118 -> 0 | G27: =PRODUCT(B27*D27) -> 0 | H27: =SUM(F27:G27) -> 0
A28: OTHER | E28: =PRODUCT(B28*C28) -> 0 | F28: =PRODUCT(E28*18)/118 -> 0 | G28: =PRODUCT(B28*D28) -> 0 | H28: =SUM(F28:G28) -> 0
... A36: OTHER | E36: =PRODUCT(B36*C36) -> 0 | F36: =PRODUCT(E36*18)/118 -> 0 | G36: =PRODUCT(B36*D36) -> 0 | H36: =SUM(F36:G36) -> 0
A37: TOTALY | E37: =SUM(E5:E36) -> 0 | F37: =SUM(F5:F36) -> 0 | G37: =SUM(G5:G36) -> 0 | H37: =SUM(H5:H36) -> 0
A38: SUMMARY | C38: RWF | E38: NAME | G38: Phone | H38: RWF
A39: TOTAL RWF PAID ON MOMO PAY
A40: TOTAL RWF PAID ON CASH
A41: AMOUNT NOT INVOICED
A42: TOTAL RWF DEPPOSITED ON BANK
A43: MEMBERSHIP FEES REGISTRETION
A44: MEMBERSHIP FEES CONTRIBUTION
A45: TOTAL INCOME | C45: =SUM(C39+C40+C41+C42+C43+C44) -> 0
A46: TIMBER SUMMARY
A48: REPORT SUMMARY | C48: TIMBER TYPE | E48: NUMBER OF QUANTITY
C49: INTURUSU | E49: =SUM(B9:B12) -> 0
C50: PINUS | E50: =SUM(B6:B8) -> 0
C51: PALNCHE | E51: =SUM(B13:B14) -> 0
C52: IBIPANDE | E52: =SUM(B17:B18) -> 0
C53: UMUSAVE | E53: =SUM(B19:B20) -> 0
C54: OTHER | E54: =B29 -> 0
C55: OTHER | E55: =B30 -> 0
C56: OTHER | E56: =B31 -> 0
C57: OTHER | E57: =B32 -> 0
C58: OTHER | E58: =B33 -> 0
C59: OTHER | E59: =B34 -> 0
C60: OTHER | E60: =B35 -> 0
C61: OTHER | E61: =B36 -> 0
C62: TOTAL TIMBER | E62: =SUM(E49:H61) -> 0

Sheet RUHANGO
A1: QUANTITY REPORT
A3: MONTHS REPORT OF NOVEMBER 2025
A5: NAME OF TIMBER | B5: No OF TIMBER | C5: PRICE OF TIMBER | E5: TOTAL COST | F5: TVA | G5: MSF | H5: TVA+MSF
A6: PINUS NINI | E6: =PRODUCT(B6*C6) -> 0 | F6: =PRODUCT(E6*18)/118 -> 0 | G6: =PRODUCT(B6*50) -> 0 | H6: =SUM(F6:G6) -> 0
A7: PINUS NTOYA | E7: =PRODUCT(B7*C7) -> 0 | F7: =PRODUCT(E7*18)/118 -> 0 | G7: =PRODUCT(B7*50) -> 0 | H7: =SUM(F7:G7) -> 0
A8: PINUS | E8: =PRODUCT(B8*C8) -> 0 | F8: =PRODUCT(E8*18)/118 -> 0 | G8: =PRODUCT(B8*50) -> 0 | H8: =SUM(F8:G8) -> 0
A9: MADIRIYE NINI | E9: =PRODUCT(B9*C9) -> 0 | F9: =PRODUCT(E9*18)/118 -> 0 | G9: =PRODUCT(B9*30) -> 0 | H9: =SUM(F9:G9) -> 0
A10: MADIRIYE NTOYA | E10: =PRODUCT(B10*C10) -> 0 | F10: =PRODUCT(E10*18)/118 -> 0 | G10: =PRODUCT(B10*30) -> 0 | H10: =SUM(F10:G10) -> 0
A11: MADRIEN | E11: =PRODUCT(B11*C11) -> 0 | F11: =PRODUCT(E11*18)/118 -> 0 | G11: =PRODUCT(B11*30) -> 0 | H11: =SUM(F11:G11) -> 0
A12: MADRIEN | E12: =PRODUCT(B12*C12) -> 0 | F12: =PRODUCT(E12*18)/118 -> 0 | G12: =PRODUCT(B12*30) -> 0 | H12: =SUM(F12:G12) -> 0
A13: PLANCHE | E13: =PRODUCT(B13*C13) -> 0 | F13: =PRODUCT(E13*18)/118 -> 0 | G13: =PRODUCT(B13*20) -> 0 | H13: =SUM(F13:G13) -> 0
A14: PLANCHE | E14: =PRODUCT(B14*C14) -> 0 | F14: =PRODUCT(E14*18)/118 -> 0 | G14: =PRODUCT(B14*20) -> 0 | H14: =SUM(F14:G14) -> 0
A15: Other Timber for Difference Price
A16: NAME OF TIMBER | B16: No OF TIMBER | C16: P/U | D16: MSF | E16: TOTAL COST | F16: VAT | G16: MSF | H16: VTA+MST
A17: IBIPANDE | E17: =PRODUCT(B17*C17) -> 0 | F17: =PRODUCT(E17*18)/118 -> 0 | G17: =PRODUCT(B17*D17) -> 0 | H17: =SUM(F17:G17) -> 0
A18: IBIPANDE | E18: =PRODUCT(B18*C18) -> 0 | F18: =PRODUCT(E18*18)/118 -> 0 | G18: =PRODUCT(B18*D18) -> 0 | H18: =SUM(F18:G18) -> 0
A19: UMUSAVE | E19: =PRODUCT(B19*C19) -> 0 | F19: =PRODUCT(E19*18)/118 -> 0 | G19: =PRODUCT(B19*D19) -> 0 | H19: =SUM(F19:G19) -> 0
A20: UMUSAVE | E20: =PRODUCT(B20*C20) -> 0 | F20: =PRODUCT(E20*18)/118 -> 0 | G20: =PRODUCT(B20*D20) -> 0 | H20: =SUM(F20:G20) -> 0
A21: OTHER | E21: =PRODUCT(B21*C21) -> 0 | F21: =PRODUCT(E21*18)/118 -> 0 | G21: =PRODUCT(B21*D21) -> 0 | H21: =SUM(F21:G21) -> 0
A22: OTHER | E22: =PRODUCT(B22*C22) -> 0 | F22: =PRODUCT(E22*18)/118 -> 0 | G22: =PRODUCT(B22*D22) -> 0 | H22: =SUM(F22:G22) -> 0
A23: OTHER | E23: =PRODUCT(B23*C23) -> 0 | F23: =PRODUCT(E23*18)/118 -> 0 | G23: =PRODUCT(B23*D23) -> 0 | H23: =SUM(F23:G23) -> 0
A24: OTHER | E24: =PRODUCT(B24*C24) -> 0 | F24: =PRODUCT(E24*18)/118 -> 0 | G24: =PRODUCT(B24*D24) -> 0 | H24: =SUM(F24:G24) -> 0
A25: OTHER | E25: =PRODUCT(B25*C25) -> 0 | F25: =PRODUCT(E25*18)/118 -> 0 | G25: =PRODUCT(B25*D25) -> 0 | H25: =SUM(F25:G25) -> 0
A26: OTHER | E26: =PRODUCT(B26*C26) -> 0 | F26: =PRODUCT(E26*18)/118 -> 0 | G26: =PRODUCT(B26*D26) -> 0 | H26: =SUM(F26:G26) -> 0
A27: OTHER | E27: =PRODUCT(B27*C27) -> 0 | F27: =PRODUCT(E27*18)/118 -> 0 | G27: =PRODUCT(B27*D27) -> 0 | H27: =SUM(F27:G27) -> 0
A28: OTHER | E28: =PRODUCT(B28*C28) -> 0 | F28: =PRODUCT(E28*18)/118 -> 0 | G28: =PRODUCT(B28*D28) -> 0 | H28: =SUM(F28:G28) -> 0
... A36: OTHER | E36: =PRODUCT(B36*C36) -> 0 | F36: =PRODUCT(E36*18)/118 -> 0 | G36: =PRODUCT(B36*D36) -> 0 | H36: =SUM(F36:G36) -> 0
A37: TOTALY | E37: =SUM(E5:E36) -> 0 | F37: =SUM(F5:F36) -> 0 | G37: =SUM(G5:G36) -> 0 | H37: =SUM(H5:H36) -> 0
A38: SUMMARY | C38: RWF | E38: NAME | G38: Phone | H38: RWF
A39: TOTAL RWF PAID ON MOMO PAY
A40: TOTAL RWF PAID ON CASH
A41: AMOUNT NOT INVOICED
A42: TOTAL RWF DEPPOSITED ON BANK
A43: MEMBERSHIP FEES REGISTRETION
A44: MEMBERSHIP FEES CONTRIBUTION
A45: TOTAL INCOME | C45: =SUM(C39+C40+C41+C42+C43+C44) -> 0
A46: TIMBER SUMMARY
A48: REPORT SUMMARY | C48: TIMBER TYPE | E48: NUMBER OF QUANTITY
C49: INTURUSU | E49: =SUM(B9:B12) -> 0
C50: PINUS | E50: =SUM(B6:B8) -> 0
C51: PALNCHE | E51: =SUM(B13:B14) -> 0
C52: IBIPANDE | E52: =SUM(B17:B18) -> 0
C53: UMUSAVE | E53: =SUM(B19:B20) -> 0
C54: OTHER | E54: =B29 -> 0
C55: OTHER | E55: =B30 -> 0
C56: OTHER | E56: =B31 -> 0
C57: OTHER | E57: =B32 -> 0
C58: OTHER | E58: =B33 -> 0
C59: OTHER | E59: =B34 -> 0
C60: OTHER | E60: =B35 -> 0
C61: OTHER | E61: =B36 -> 0
C62: TOTAL TIMBER | E62: =SUM(E49:H61) -> 0

Sheet KARONGI
A1: QUANTITY REPORT
A3: MONTHS REPORT OF NOVEMBER 2025
A5: NAME OF TIMBER | B5: No OF TIMBER | C5: PRICE OF TIMBER | E5: TOTAL COST | F5: TVA | G5: MSF | H5: TVA+MSF
A6: PINUS NINI | E6: =PRODUCT(B6*C6) -> 0 | F6: =PRODUCT(E6*18)/118 -> 0 | G6: =PRODUCT(B6*50) -> 0 | H6: =SUM(F6:G6) -> 0
A7: PINUS NTOYA | E7: =PRODUCT(B7*C7) -> 0 | F7: =PRODUCT(E7*18)/118 -> 0 | G7: =PRODUCT(B7*50) -> 0 | H7: =SUM(F7:G7) -> 0
A8: PINUS | E8: =PRODUCT(B8*C8) -> 0 | F8: =PRODUCT(E8*18)/118 -> 0 | G8: =PRODUCT(B8*50) -> 0 | H8: =SUM(F8:G8) -> 0
A9: MADIRIYE NINI | E9: =PRODUCT(B9*C9) -> 0 | F9: =PRODUCT(E9*18)/118 -> 0 | G9: =PRODUCT(B9*30) -> 0 | H9: =SUM(F9:G9) -> 0
A10: MADIRIYE NTOYA | E10: =PRODUCT(B10*C10) -> 0 | F10: =PRODUCT(E10*18)/118 -> 0 | G10: =PRODUCT(B10*30) -> 0 | H10: =SUM(F10:G10) -> 0
A11: MADRIEN | E11: =PRODUCT(B11*C11) -> 0 | F11: =PRODUCT(E11*18)/118 -> 0 | G11: =PRODUCT(B11*30) -> 0 | H11: =SUM(F11:G11) -> 0
A12: MADRIEN | E12: =PRODUCT(B12*C12) -> 0 | F12: =PRODUCT(E12*18)/118 -> 0 | G12: =PRODUCT(B12*30) -> 0 | H12: =SUM(F12:G12) -> 0
A13: PLANCHE | E13: =PRODUCT(B13*C13) -> 0 | F13: =PRODUCT(E13*18)/118 -> 0 | G13: =PRODUCT(B13*20) -> 0 | H13: =SUM(F13:G13) -> 0
A14: PLANCHE | E14: =PRODUCT(B14*C14) -> 0 | F14: =PRODUCT(E14*18)/118 -> 0 | G14: =PRODUCT(B14*20) -> 0 | H14: =SUM(F14:G14) -> 0
A15: Other Timber for Difference Price
A16: NAME OF TIMBER | B16: No OF TIMBER | C16: P/U | D16: MSF | E16: TOTAL COST | F16: VAT | G16: MSF | H16: VTA+MST
A17: IBIPANDE | E17: =PRODUCT(B17*C17) -> 0 | F17: =PRODUCT(E17*18)/118 -> 0 | G17: =PRODUCT(B17*D17) -> 0 | H17: =SUM(F17:G17) -> 0
A18: IBIPANDE | E18: =PRODUCT(B18*C18) -> 0 | F18: =PRODUCT(E18*18)/118 -> 0 | G18: =PRODUCT(B18*D18) -> 0 | H18: =SUM(F18:G18) -> 0
A19: UMUSAVE | E19: =PRODUCT(B19*C19) -> 0 | F19: =PRODUCT(E19*18)/118 -> 0 | G19: =PRODUCT(B19*D19) -> 0 | H19: =SUM(F19:G19) -> 0
A20: UMUSAVE | E20: =PRODUCT(B20*C20) -> 0 | F20: =PRODUCT(E20*18)/118 -> 0 | G20: =PRODUCT(B20*D20) -> 0 | H20: =SUM(F20:G20) -> 0
A21: OTHER | E21: =PRODUCT(B21*C21) -> 0 | F21: =PRODUCT(E21*18)/118 -> 0 | G21: =PRODUCT(B21*D21) -> 0 | H21: =SUM(F21:G21) -> 0
A22: OTHER | E22: =PRODUCT(B22*C22) -> 0 | F22: =PRODUCT(E22*18)/118 -> 0 | G22: =PRODUCT(B22*D22) -> 0 | H22: =SUM(F22:G22) -> 0
A23: OTHER | E23: =PRODUCT(B23*C23) -> 0 | F23: =PRODUCT(E23*18)/118 -> 0 | G23: =PRODUCT(B23*D23) -> 0 | H23: =SUM(F23:G23) -> 0
A24: OTHER | E24: =PRODUCT(B24*C24) -> 0 | F24: =PRODUCT(E24*18)/118 -> 0 | G24: =PRODUCT(B24*D24) -> 0 | H24: =SUM(F24:G24) -> 0
A25: OTHER | E25: =PRODUCT(B25*C25) -> 0 | F25: =PRODUCT(E25*18)/118 -> 0 | G25: =PRODUCT(B25*D25) -> 0 | H25: =SUM(F25:G25) -> 0
A26: OTHER | E26: =PRODUCT(B26*C26) -> 0 | F26: =PRODUCT(E26*18)/118 -> 0 | G26: =PRODUCT(B26*D26) -> 0 | H26: =SUM(F26:G26) -> 0
A27: OTHER | E27: =PRODUCT(B27*C27) -> 0 | F27: =PRODUCT(E27*18)/118 -> 0 | G27: =PRODUCT(B27*D27) -> 0 | H27: =SUM(F27:G27) -> 0
A28: OTHER | E28: =PRODUCT(B28*C28) -> 0 | F28: =PRODUCT(E28*18)/118 -> 0 | G28: =PRODUCT(B28*D28) -> 0 | H28: =SUM(F28:G28) -> 0
... A36: OTHER | E36: =PRODUCT(B36*C36) -> 0 | F36: =PRODUCT(E36*18)/118 -> 0 | G36: =PRODUCT(B36*D36) -> 0 | H36: =SUM(F36:G36) -> 0
A37: TOTALY | E37: =SUM(E5:E36) -> 0 | F37: =SUM(F5:F36) -> 0 | G37: =SUM(G5:G36) -> 0 | H37: =SUM(H5:H36) -> 0
A38: SUMMARY | C38: RWF | E38: NAME | G38: Phone | H38: RWF
A39: TOTAL RWF PAID ON MOMO PAY
A40: TOTAL RWF PAID ON CASH
A41: AMOUNT NOT INVOICED
A42: TOTAL RWF DEPPOSITED ON BANK
A43: MEMBERSHIP FEES REGISTRETION
A44: MEMBERSHIP FEES CONTRIBUTION
A45: TOTAL INCOME | C45: =SUM(C39+C40+C41+C42+C43+C44) -> 0
A46: TIMBER SUMMARY
A48: REPORT SUMMARY | C48: TIMBER TYPE | E48: NUMBER OF QUANTITY
C49: INTURUSU | E49: =SUM(B9:B12) -> 0
C50: PINUS | E50: =SUM(B6:B8) -> 0
C51: PALNCHE | E51: =SUM(B13:B14) -> 0
C52: IBIPANDE | E52: =SUM(B17:B18) -> 0
C53: UMUSAVE | E53: =SUM(B19:B20) -> 0
C54: OTHER | E54: =B29 -> 0
C55: OTHER | E55: =B30 -> 0
C56: OTHER | E56: =B31 -> 0
C57: OTHER | E57: =B32 -> 0
C58: OTHER | E58: =B33 -> 0
C59: OTHER | E59: =B34 -> 0
C60: OTHER | E60: =B35 -> 0
C61: OTHER | E61: =B36 -> 0
C62: TOTAL TIMBER | E62: =SUM(E49:H61) -> 0

Sheet RUSIZI
A1: QUANTITY REPORT
A3: MONTHS REPORT OF NOVEMBER 2025
A5: NAME OF TIMBER | B5: No OF TIMBER | C5: PRICE OF TIMBER | E5: TOTAL COST | F5: TVA | G5: MSF | H5: TVA+MSF
A6: PINUS NINI | E6: =PRODUCT(B6*C6) -> 0 | F6: =PRODUCT(E6*18)/118 -> 0 | G6: =PRODUCT(B6*50) -> 0 | H6: =SUM(F6:G6) -> 0
A7: PINUS NTOYA | E7: =PRODUCT(B7*C7) -> 0 | F7: =PRODUCT(E7*18)/118 -> 0 | G7: =PRODUCT(B7*50) -> 0 | H7: =SUM(F7:G7) -> 0
A8: PINUS | E8: =PRODUCT(B8*C8) -> 0 | F8: =PRODUCT(E8*18)/118 -> 0 | G8: =PRODUCT(B8*50) -> 0 | H8: =SUM(F8:G8) -> 0
A9: MADIRIYE NINI | E9: =PRODUCT(B9*C9) -> 0 | F9: =PRODUCT(E9*18)/118 -> 0 | G9: =PRODUCT(B9*30) -> 0 | H9: =SUM(F9:G9) -> 0
A10: MADIRIYE NTOYA | E10: =PRODUCT(B10*C10) -> 0 | F10: =PRODUCT(E10*18)/118 -> 0 | G10: =PRODUCT(B10*30) -> 0 | H10: =SUM(F10:G10) -> 0
A11: MADRIEN | E11: =PRODUCT(B11*C11) -> 0 | F11: =PRODUCT(E11*18)/118 -> 0 | G11: =PRODUCT(B11*30) -> 0 | H11: =SUM(F11:G11) -> 0
A12: MADRIEN | E12: =PRODUCT(B12*C12) -> 0 | F12: =PRODUCT(E12*18)/118 -> 0 | G12: =PRODUCT(B12*30) -> 0 | H12: =SUM(F12:G12) -> 0
A13: PLANCHE | E13: =PRODUCT(B13*C13) -> 0 | F13: =PRODUCT(E13*18)/118 -> 0 | G13: =PRODUCT(B13*20) -> 0 | H13: =SUM(F13:G13) -> 0
A14: PLANCHE | E14: =PRODUCT(B14*C14) -> 0 | F14: =PRODUCT(E14*18)/118 -> 0 | G14: =PRODUCT(B14*20) -> 0 | H14: =SUM(F14:G14) -> 0
A15: Other Timber for Difference Price
A16: NAME OF TIMBER | B16: No OF TIMBER | C16: P/U | D16: MSF | E16: TOTAL COST | F16: VAT | G16: MSF | H16: VTA+MST
A17: IBIPANDE | E17: =PRODUCT(B17*C17) -> 0 | F17: =PRODUCT(E17*18)/118 -> 0 | G17: =PRODUCT(B17*D17) -> 0 | H17: =SUM(F17:G17) -> 0
A18: IBIPANDE | E18: =PRODUCT(B18*C18) -> 0 | F18: =PRODUCT(E18*18)/118 -> 0 | G18: =PRODUCT(B18*D18) -> 0 | H18: =SUM(F18:G18) -> 0
A19: UMUSAVE | E19: =PRODUCT(B19*C19) -> 0 | F19: =PRODUCT(E19*18)/118 -> 0 | G19: =PRODUCT(B19*D19) -> 0 | H19: =SUM(F19:G19) -> 0
A20: UMUSAVE | E20: =PRODUCT(B20*C20) -> 0 | F20: =PRODUCT(E20*18)/118 -> 0 | G20: =PRODUCT(B20*D20) -> 0 | H20: =SUM(F20:G20) -> 0
A21: OTHER | E21: =PRODUCT(B21*C21) -> 0 | F21: =PRODUCT(E21*18)/118 -> 0 | G21: =PRODUCT(B21*D21) -> 0 | H21: =SUM(F21:G21) -> 0
A22: OTHER | E22: =PRODUCT(B22*C22) -> 0 | F22: =PRODUCT(E22*18)/118 -> 0 | G22: =PRODUCT(B22*D22) -> 0 | H22: =SUM(F22:G22) -> 0
A23: OTHER | E23: =PRODUCT(B23*C23) -> 0 | F23: =PRODUCT(E23*18)/118 -> 0 | G23: =PRODUCT(B23*D23) -> 0 | H23: =SUM(F23:G23) -> 0
A24: OTHER | E24: =PRODUCT(B24*C24) -> 0 | F24: =PRODUCT(E24*18)/118 -> 0 | G24: =PRODUCT(B24*D24) -> 0 | H24: =SUM(F24:G24) -> 0
A25: OTHER | E25: =PRODUCT(B25*C25) -> 0 | F25: =PRODUCT(E25*18)/118 -> 0 | G25: =PRODUCT(B25*D25) -> 0 | H25: =SUM(F25:G25) -> 0
A26: OTHER | E26: =PRODUCT(B26*C26) -> 0 | F26: =PRODUCT(E26*18)/118 -> 0 | G26: =PRODUCT(B26*D26) -> 0 | H26: =SUM(F26:G26) -> 0
A27: OTHER | E27: =PRODUCT(B27*C27) -> 0 | F27: =PRODUCT(E27*18)/118 -> 0 | G27: =PRODUCT(B27*D27) -> 0 | H27: =SUM(F27:G27) -> 0
A28: OTHER | E28: =PRODUCT(B28*C28) -> 0 | F28: =PRODUCT(E28*18)/118 -> 0 | G28: =PRODUCT(B28*D28) -> 0 | H28: =SUM(F28:G28) -> 0
... A36: OTHER | E36: =PRODUCT(B36*C36) -> 0 | F36: =PRODUCT(E36*18)/118 -> 0 | G36: =PRODUCT(B36*D36) -> 0 | H36: =SUM(F36:G36) -> 0
A37: TOTALY | E37: =SUM(E5:E36) -> 0 | F37: =SUM(F5:F36) -> 0 | G37: =SUM(G5:G36) -> 0 | H37: =SUM(H5:H36) -> 0
A38: SUMMARY | C38: RWF | E38: NAME | G38: Phone | H38: RWF
A39: TOTAL RWF PAID ON MOMO PAY
A40: TOTAL RWF PAID ON CASH
A41: AMOUNT NOT INVOICED
A42: TOTAL RWF DEPPOSITED ON BANK
A43: MEMBERSHIP FEES REGISTRETION
A44: MEMBERSHIP FEES CONTRIBUTION
A45: TOTAL INCOME | C45: =SUM(C39+C40+C41+C42+C43+C44) -> 0
A46: TIMBER SUMMARY
A48: REPORT SUMMARY | C48: TIMBER TYPE | E48: NUMBER OF QUANTITY
C49: INTURUSU | E49: =SUM(B9:B12) -> 0
C50: PINUS | E50: =SUM(B6:B8) -> 0
C51: PALNCHE | E51: =SUM(B13:B14) -> 0
C52: IBIPANDE | E52: =SUM(B17:B18) -> 0
C53: UMUSAVE | E53: =SUM(B19:B20) -> 0
C54: OTHER | E54: =B29 -> 0
C55: OTHER | E55: =B30 -> 0
C56: OTHER | E56: =B31 -> 0
C57: OTHER | E57: =B32 -> 0
C58: OTHER | E58: =B33 -> 0
C59: OTHER | E59: =B34 -> 0
C60: OTHER | E60: =B35 -> 0
C61: OTHER | E61: =B36 -> 0
C62: TOTAL TIMBER | E62: =SUM(E49:H61) -> 0

Sheet RUBAVU
A1: QUANTITY REPORT
A3: MONTHS REPORT OF NOVEMBER 2025
A5: NAME OF TIMBER | B5: No OF TIMBER | C5: PRICE OF TIMBER | E5: TOTAL COST | F5: TVA | G5: MSF | H5: TVA+MSF
A6: PINUS NINI | E6: =PRODUCT(B6*C6) -> 0 | F6: =PRODUCT(E6*18)/118 -> 0 | G6: =PRODUCT(B6*50) -> 0 | H6: =SUM(F6:G6) -> 0
A7: PINUS NTOYA | E7: =PRODUCT(B7*C7) -> 0 | F7: =PRODUCT(E7*18)/118 -> 0 | G7: =PRODUCT(B7*50) -> 0 | H7: =SUM(F7:G7) -> 0
A8: PINUS | E8: =PRODUCT(B8*C8) -> 0 | F8: =PRODUCT(E8*18)/118 -> 0 | G8: =PRODUCT(B8*50) -> 0 | H8: =SUM(F8:G8) -> 0
A9: MADIRIYE NINI | E9: =PRODUCT(B9*C9) -> 0 | F9: =PRODUCT(E9*18)/118 -> 0 | G9: =PRODUCT(B9*30) -> 0 | H9: =SUM(F9:G9) -> 0
A10: MADIRIYE NTOYA | E10: =PRODUCT(B10*C10) -> 0 | F10: =PRODUCT(E10*18)/118 -> 0 | G10: =PRODUCT(B10*30) -> 0 | H10: =SUM(F10:G10) -> 0
A11: MADRIEN | E11: =PRODUCT(B11*C11) -> 0 | F11: =PRODUCT(E11*18)/118 -> 0 | G11: =PRODUCT(B11*30) -> 0 | H11: =SUM(F11:G11) -> 0
A12: MADRIEN | E12: =PRODUCT(B12*C12) -> 0 | F12: =PRODUCT(E12*18)/118 -> 0 | G12: =PRODUCT(B12*30) -> 0 | H12: =SUM(F12:G12) -> 0
A13: PLANCHE | E13: =PRODUCT(B13*C13) -> 0 | F13: =PRODUCT(E13*18)/118 -> 0 | G13: =PRODUCT(B13*20) -> 0 | H13: =SUM(F13:G13) -> 0
A14: PLANCHE | E14: =PRODUCT(B14*C14) -> 0 | F14: =PRODUCT(E14*18)/118 -> 0 | G14: =PRODUCT(B14*20) -> 0 | H14: =SUM(F14:G14) -> 0
A15: Other Timber for Difference Price
A16: NAME OF TIMBER | B16: No OF TIMBER | C16: P/U | D16: MSF | E16: TOTAL COST | F16: VAT | G16: MSF | H16: VTA+MST
A17: IBIPANDE | E17: =PRODUCT(B17*C17) -> 0 | F17: =PRODUCT(E17*18)/118 -> 0 | G17: =PRODUCT(B17*D17) -> 0 | H17: =SUM(F17:G17) -> 0
A18: IBIPANDE | E18: =PRODUCT(B18*C18) -> 0 | F18: =PRODUCT(E18*18)/118 -> 0 | G18: =PRODUCT(B18*D18) -> 0 | H18: =SUM(F18:G18) -> 0
A19: UMUSAVE | E19: =PRODUCT(B19*C19) -> 0 | F19: =PRODUCT(E19*18)/118 -> 0 | G19: =PRODUCT(B19*D19) -> 0 | H19: =SUM(F19:G19) -> 0
A20: UMUSAVE | E20: =PRODUCT(B20*C20) -> 0 | F20: =PRODUCT(E20*18)/118 -> 0 | G20: =PRODUCT(B20*D20) -> 0 | H20: =SUM(F20:G20) -> 0
A21: OTHER | E21: =PRODUCT(B21*C21) -> 0 | F21: =PRODUCT(E21*18)/118 -> 0 | G21: =PRODUCT(B21*D21) -> 0 | H21: =SUM(F21:G21) -> 0
A22: OTHER | E22: =PRODUCT(B22*C22) -> 0 | F22: =PRODUCT(E22*18)/118 -> 0 | G22: =PRODUCT(B22*D22) -> 0 | H22: =SUM(F22:G22) -> 0
A23: OTHER | E23: =PRODUCT(B23*C23) -> 0 | F23: =PRODUCT(E23*18)/118 -> 0 | G23: =PRODUCT(B23*D23) -> 0 | H23: =SUM(F23:G23) -> 0
A24: OTHER | E24: =PRODUCT(B24*C24) -> 0 | F24: =PRODUCT(E24*18)/118 -> 0 | G24: =PRODUCT(B24*D24) -> 0 | H24: =SUM(F24:G24) -> 0
A25: OTHER | E25: =PRODUCT(B25*C25) -> 0 | F25: =PRODUCT(E25*18)/118 -> 0 | G25: =PRODUCT(B25*D25) -> 0 | H25: =SUM(F25:G25) -> 0
A26: OTHER | E26: =PRODUCT(B26*C26) -> 0 | F26: =PRODUCT(E26*18)/118 -> 0 | G26: =PRODUCT(B26*D26) -> 0 | H26: =SUM(F26:G26) -> 0
A27: OTHER | E27: =PRODUCT(B27*C27) -> 0 | F27: =PRODUCT(E27*18)/118 -> 0 | G27: =PRODUCT(B27*D27) -> 0 | H27: =SUM(F27:G27) -> 0
A28: OTHER | E28: =PRODUCT(B28*C28) -> 0 | F28: =PRODUCT(E28*18)/118 -> 0 | G28: =PRODUCT(B28*D28) -> 0 | H28: =SUM(F28:G28) -> 0
... A36: OTHER | E36: =PRODUCT(B36*C36) -> 0 | F36: =PRODUCT(E36*18)/118 -> 0 | G36: =PRODUCT(B36*D36) -> 0 | H36: =SUM(F36:G36) -> 0
A37: TOTALY | E37: =SUM(E5:E36) -> 0 | F37: =SUM(F5:F36) -> 0 | G37: =SUM(G5:G36) -> 0 | H37: =SUM(H5:H36) -> 0
A38: SUMMARY | C38: RWF | E38: NAME | G38: Phone | H38: RWF
A39: TOTAL RWF PAID ON MOMO PAY
A40: TOTAL RWF PAID ON CASH
A41: AMOUNT NOT INVOICED
A42: TOTAL RWF DEPPOSITED ON BANK
A43: MEMBERSHIP FEES REGISTRETION
A44: MEMBERSHIP FEES CONTRIBUTION
A45: TOTAL INCOME | C45: =SUM(C39+C40+C41+C42+C43+C44) -> 0
A46: TIMBER SUMMARY
A48: REPORT SUMMARY | C48: TIMBER TYPE | E48: NUMBER OF QUANTITY
C49: INTURUSU | E49: =SUM(B9:B12) -> 0
C50: PINUS | E50: =SUM(B6:B8) -> 0
C51: PALNCHE | E51: =SUM(B13:B14) -> 0
C52: IBIPANDE | E52: =SUM(B17:B18) -> 0
C53: UMUSAVE | E53: =SUM(B19:B20) -> 0
C54: OTHER | E54: =B29 -> 0
C55: OTHER | E55: =B30 -> 0
C56: OTHER | E56: =B31 -> 0
C57: OTHER | E57: =B32 -> 0
C58: OTHER | E58: =B33 -> 0
C59: OTHER | E59: =B34 -> 0
C60: OTHER | E60: =B35 -> 0
C61: OTHER | E61: =B36 -> 0
C62: TOTAL TIMBER | E62: =SUM(E49:H61) -> 0

Sheet MUSANZE
A1: QUANTITY REPORT
A3: MONTHS REPORT OF NOVEMBER 2025
A5: NAME OF TIMBER | B5: No OF TIMBER | C5: PRICE OF TIMBER | E5: TOTAL COST | F5: TVA | G5: MSF | H5: TVA+MSF
A6: PINUS NINI | E6: =PRODUCT(B6*C6) -> 0 | F6: =PRODUCT(E6*18)/118 -> 0 | G6: =PRODUCT(B6*50) -> 0 | H6: =SUM(F6:G6) -> 0
A7: PINUS NTOYA | E7: =PRODUCT(B7*C7) -> 0 | F7: =PRODUCT(E7*18)/118 -> 0 | G7: =PRODUCT(B7*50) -> 0 | H7: =SUM(F7:G7) -> 0
A8: PINUS | E8: =PRODUCT(B8*C8) -> 0 | F8: =PRODUCT(E8*18)/118 -> 0 | G8: =PRODUCT(B8*50) -> 0 | H8: =SUM(F8:G8) -> 0
A9: MADIRIYE NINI | E9: =PRODUCT(B9*C9) -> 0 | F9: =PRODUCT(E9*18)/118 -> 0 | G9: =PRODUCT(B9*30) -> 0 | H9: =SUM(F9:G9) -> 0
A10: MADIRIYE NTOYA | E10: =PRODUCT(B10*C10) -> 0 | F10: =PRODUCT(E10*18)/118 -> 0 | G10: =PRODUCT(B10*30) -> 0 | H10: =SUM(F10:G10) -> 0
A11: MADRIEN | E11: =PRODUCT(B11*C11) -> 0 | F11: =PRODUCT(E11*18)/118 -> 0 | G11: =PRODUCT(B11*30) -> 0 | H11: =SUM(F11:G11) -> 0
A12: MADRIEN | E12: =PRODUCT(B12*C12) -> 0 | F12: =PRODUCT(E12*18)/118 -> 0 | G12: =PRODUCT(B12*30) -> 0 | H12: =SUM(F12:G12) -> 0
A13: PLANCHE | E13: =PRODUCT(B13*C13) -> 0 | F13: =PRODUCT(E13*18)/118 -> 0 | G13: =PRODUCT(B13*20) -> 0 | H13: =SUM(F13:G13) -> 0
A14: PLANCHE | E14: =PRODUCT(B14*C14) -> 0 | F14: =PRODUCT(E14*18)/118 -> 0 | G14: =PRODUCT(B14*20) -> 0 | H14: =SUM(F14:G14) -> 0
A15: Other Timber for Difference Price
A16: NAME OF TIMBER | B16: No OF TIMBER | C16: P/U | D16: MSF | E16: TOTAL COST | F16: VAT | G16: MSF | H16: VTA+MST
A17: IBIPANDE | E17: =PRODUCT(B17*C17) -> 0 | F17: =PRODUCT(E17*18)/118 -> 0 | G17: =PRODUCT(B17*D17) -> 0 | H17: =SUM(F17:G17) -> 0
A18: IBIPANDE | E18: =PRODUCT(B18*C18) -> 0 | F18: =PRODUCT(E18*18)/118 -> 0 | G18: =PRODUCT(B18*D18) -> 0 | H18: =SUM(F18:G18) -> 0
A19: UMUSAVE | E19: =PRODUCT(B19*C19) -> 0 | F19: =PRODUCT(E19*18)/118 -> 0 | G19: =PRODUCT(B19*D19) -> 0 | H19: =SUM(F19:G19) -> 0
A20: UMUSAVE | E20: =PRODUCT(B20*C20) -> 0 | F20: =PRODUCT(E20*18)/118 -> 0 | G20: =PRODUCT(B20*D20) -> 0 | H20: =SUM(F20:G20) -> 0
A21: OTHER | E21: =PRODUCT(B21*C21) -> 0 | F21: =PRODUCT(E21*18)/118 -> 0 | G21: =PRODUCT(B21*D21) -> 0 | H21: =SUM(F21:G21) -> 0
A22: OTHER | E22: =PRODUCT(B22*C22) -> 0 | F22: =PRODUCT(E22*18)/118 -> 0 | G22: =PRODUCT(B22*D22) -> 0 | H22: =SUM(F22:G22) -> 0
A23: OTHER | E23: =PRODUCT(B23*C23) -> 0 | F23: =PRODUCT(E23*18)/118 -> 0 | G23: =PRODUCT(B23*D23) -> 0 | H23: =SUM(F23:G23) -> 0
A24: OTHER | E24: =PRODUCT(B24*C24) -> 0 | F24: =PRODUCT(E24*18)/118 -> 0 | G24: =PRODUCT(B24*D24) -> 0 | H24: =SUM(F24:G24) -> 0
A25: OTHER | E25: =PRODUCT(B25*C25) -> 0 | F25: =PRODUCT(E25*18)/118 -> 0 | G25: =PRODUCT(B25*D25) -> 0 | H25: =SUM(F25:G25) -> 0
A26: OTHER | E26: =PRODUCT(B26*C26) -> 0 | F26: =PRODUCT(E26*18)/118 -> 0 | G26: =PRODUCT(B26*D26) -> 0 | H26: =SUM(F26:G26) -> 0
A27: OTHER | E27: =PRODUCT(B27*C27) -> 0 | F27: =PRODUCT(E27*18)/118 -> 0 | G27: =PRODUCT(B27*D27) -> 0 | H27: =SUM(F27:G27) -> 0
A28: OTHER | E28: =PRODUCT(B28*C28) -> 0 | F28: =PRODUCT(E28*18)/118 -> 0 | G28: =PRODUCT(B28*D28) -> 0 | H28: =SUM(F28:G28) -> 0
... A36: OTHER | E36: =PRODUCT(B36*C36) -> 0 | F36: =PRODUCT(E36*18)/118 -> 0 | G36: =PRODUCT(B36*D36) -> 0 | H36: =SUM(F36:G36) -> 0
A37: TOTALY | E37: =SUM(E5:E36) -> 0 | F37: =SUM(F5:F36) -> 0 | G37: =SUM(G5:G36) -> 0 | H37: =SUM(H5:H36) -> 0
A38: SUMMARY | C38: RWF | E38: NAME | G38: Phone | H38: RWF
A39: TOTAL RWF PAID ON MOMO PAY
A40: TOTAL RWF PAID ON CASH
A41: AMOUNT NOT INVOICED
A42: TOTAL RWF DEPPOSITED ON BANK
A43: MEMBERSHIP FEES REGISTRETION
A44: MEMBERSHIP FEES CONTRIBUTION
A45: TOTAL INCOME | C45: =SUM(C39+C40+C41+C42+C43+C44) -> 0
A46: TIMBER SUMMARY
A48: REPORT SUMMARY | C48: TIMBER TYPE | E48: NUMBER OF QUANTITY
C49: INTURUSU | E49: =SUM(B9:B12) -> 0
C50: PINUS | E50: =SUM(B6:B8) -> 0
C51: PALNCHE | E51: =SUM(B13:B14) -> 0
C52: IBIPANDE | E52: =SUM(B17:B18) -> 0
C53: UMUSAVE | E53: =SUM(B19:B20) -> 0
C54: OTHER | E54: =B29 -> 0
C55: OTHER | E55: =B30 -> 0
C56: OTHER | E56: =B31 -> 0
C57: OTHER | E57: =B32 -> 0
C58: OTHER | E58: =B33 -> 0
C59: OTHER | E59: =B34 -> 0
C60: OTHER | E60: =B35 -> 0
C61: OTHER | E61: =B36 -> 0
C62: TOTAL TIMBER | E62: =SUM(E49:H61) -> 0

Sheet NYAGATARE
A1: QUANTITY REPORT
A3: MONTHS REPORT OF NOVEMBER 2025
A5: NAME OF TIMBER | B5: No OF TIMBER | C5: PRICE OF TIMBER | E5: TOTAL COST | F5: TVA | G5: MSF | H5: TVA+MSF
A6: PINUS NINI | E6: =PRODUCT(B6*C6) -> 0 | F6: =PRODUCT(E6*18)/118 -> 0 | G6: =PRODUCT(B6*50) -> 0 | H6: =SUM(F6:G6) -> 0
A7: PINUS NTOYA | E7: =PRODUCT(B7*C7) -> 0 | F7: =PRODUCT(E7*18)/118 -> 0 | G7: =PRODUCT(B7*50) -> 0 | H7: =SUM(F7:G7) -> 0
A8: PINUS | E8: =PRODUCT(B8*C8) -> 0 | F8: =PRODUCT(E8*18)/118 -> 0 | G8: =PRODUCT(B8*50) -> 0 | H8: =SUM(F8:G8) -> 0
A9: MADIRIYE NINI | E9: =PRODUCT(B9*C9) -> 0 | F9: =PRODUCT(E9*18)/118 -> 0 | G9: =PRODUCT(B9*30) -> 0 | H9: =SUM(F9:G9) -> 0
A10: MADIRIYE NTOYA | E10: =PRODUCT(B10*C10) -> 0 | F10: =PRODUCT(E10*18)/118 -> 0 | G10: =PRODUCT(B10*30) -> 0 | H10: =SUM(F10:G10) -> 0
A11: MADRIEN | E11: =PRODUCT(B11*C11) -> 0 | F11: =PRODUCT(E11*18)/118 -> 0 | G11: =PRODUCT(B11*30) -> 0 | H11: =SUM(F11:G11) -> 0
A12: MADRIEN | E12: =PRODUCT(B12*C12) -> 0 | F12: =PRODUCT(E12*18)/118 -> 0 | G12: =PRODUCT(B12*30) -> 0 | H12: =SUM(F12:G12) -> 0
A13: PLANCHE | E13: =PRODUCT(B13*C13) -> 0 | F13: =PRODUCT(E13*18)/118 -> 0 | G13: =PRODUCT(B13*20) -> 0 | H13: =SUM(F13:G13) -> 0
A14: PLANCHE | E14: =PRODUCT(B14*C14) -> 0 | F14: =PRODUCT(E14*18)/118 -> 0 | G14: =PRODUCT(B14*20) -> 0 | H14: =SUM(F14:G14) -> 0
A15: Other Timber for Difference Price
A16: NAME OF TIMBER | B16: No OF TIMBER | C16: P/U | D16: MSF | E16: TOTAL COST | F16: VAT | G16: MSF | H16: VTA+MST
A17: IBIPANDE | E17: =PRODUCT(B17*C17) -> 0 | F17: =PRODUCT(E17*18)/118 -> 0 | G17: =PRODUCT(B17*D17) -> 0 | H17: =SUM(F17:G17) -> 0
A18: IBIPANDE | E18: =PRODUCT(B18*C18) -> 0 | F18: =PRODUCT(E18*18)/118 -> 0 | G18: =PRODUCT(B18*D18) -> 0 | H18: =SUM(F18:G18) -> 0
A19: UMUSAVE | E19: =PRODUCT(B19*C19) -> 0 | F19: =PRODUCT(E19*18)/118 -> 0 | G19: =PRODUCT(B19*D19) -> 0 | H19: =SUM(F19:G19) -> 0
A20: UMUSAVE | E20: =PRODUCT(B20*C20) -> 0 | F20: =PRODUCT(E20*18)/118 -> 0 | G20: =PRODUCT(B20*D20) -> 0 | H20: =SUM(F20:G20) -> 0
A21: OTHER | E21: =PRODUCT(B21*C21) -> 0 | F21: =PRODUCT(E21*18)/118 -> 0 | G21: =PRODUCT(B21*D21) -> 0 | H21: =SUM(F21:G21) -> 0
A22: OTHER | E22: =PRODUCT(B22*C22) -> 0 | F22: =PRODUCT(E22*18)/118 -> 0 | G22: =PRODUCT(B22*D22) -> 0 | H22: =SUM(F22:G22) -> 0
A23: OTHER | E23: =PRODUCT(B23*C23) -> 0 | F23: =PRODUCT(E23*18)/118 -> 0 | G23: =PRODUCT(B23*D23) -> 0 | H23: =SUM(F23:G23) -> 0
A24: OTHER | E24: =PRODUCT(B24*C24) -> 0 | F24: =PRODUCT(E24*18)/118 -> 0 | G24: =PRODUCT(B24*D24) -> 0 | H24: =SUM(F24:G24) -> 0
A25: OTHER | E25: =PRODUCT(B25*C25) -> 0 | F25: =PRODUCT(E25*18)/118 -> 0 | G25: =PRODUCT(B25*D25) -> 0 | H25: =SUM(F25:G25) -> 0
A26: OTHER | E26: =PRODUCT(B26*C26) -> 0 | F26: =PRODUCT(E26*18)/118 -> 0 | G26: =PRODUCT(B26*D26) -> 0 | H26: =SUM(F26:G26) -> 0
A27: OTHER | E27: =PRODUCT(B27*C27) -> 0 | F27: =PRODUCT(E27*18)/118 -> 0 | G27: =PRODUCT(B27*D27) -> 0 | H27: =SUM(F27:G27) -> 0
A28: OTHER | E28: =PRODUCT(B28*C28) -> 0 | F28: =PRODUCT(E28*18)/118 -> 0 | G28: =PRODUCT(B28*D28) -> 0 | H28: =SUM(F28:G28) -> 0
... A36: OTHER | E36: =PRODUCT(B36*C36) -> 0 | F36: =PRODUCT(E36*18)/118 -> 0 | G36: =PRODUCT(B36*D36) -> 0 | H36: =SUM(F36:G36) -> 0
A37: TOTALY | E37: =SUM(E5:E36) -> 0 | F37: =SUM(F5:F36) -> 0 | G37: =SUM(G5:G36) -> 0 | H37: =SUM(H5:H36) -> 0
A38: SUMMARY | C38: RWF | E38: NAME | G38: Phone | H38: RWF
A39: TOTAL RWF PAID ON MOMO PAY
A40: TOTAL RWF PAID ON CASH
A41: AMOUNT NOT INVOICED
A42: TOTAL RWF DEPPOSITED ON BANK
A43: MEMBERSHIP FEES REGISTRETION
A44: MEMBERSHIP FEES CONTRIBUTION
A45: TOTAL INCOME | C45: =SUM(C39+C40+C41+C42+C43+C44) -> 0
A46: TIMBER SUMMARY
A48: REPORT SUMMARY | C48: TIMBER TYPE | E48: NUMBER OF QUANTITY
C49: INTURUSU | E49: =SUM(B9:B12) -> 0
C50: PINUS | E50: =SUM(B6:B8) -> 0
C51: PALNCHE | E51: =SUM(B13:B14) -> 0
C52: IBIPANDE | E52: =SUM(B17:B18) -> 0
C53: UMUSAVE | E53: =SUM(B19:B20) -> 0
C54: OTHER | E54: =B29 -> 0
C55: OTHER | E55: =B30 -> 0
C56: OTHER | E56: =B31 -> 0
C57: OTHER | E57: =B32 -> 0
C58: OTHER | E58: =B33 -> 0
C59: OTHER | E59: =B34 -> 0
C60: OTHER | E60: =B35 -> 0
C61: OTHER | E61: =B36 -> 0
C62: TOTAL TIMBER | E62: =SUM(E49:H61) -> 0

Sheet KIREHE
A1: QUANTITY REPORT
A3: MONTHS REPORT OF NOVEMBER 2025
A5: NAME OF TIMBER | B5: No OF TIMBER | C5: PRICE OF TIMBER | E5: TOTAL COST | F5: TVA | G5: MSF | H5: TVA+MSF
A6: PINUS NINI | E6: =PRODUCT(B6*C6) -> 0 | F6: =PRODUCT(E6*18)/118 -> 0 | G6: =PRODUCT(B6*50) -> 0 | H6: =SUM(F6:G6) -> 0
A7: PINUS NTOYA | E7: =PRODUCT(B7*C7) -> 0 | F7: =PRODUCT(E7*18)/118 -> 0 | G7: =PRODUCT(B7*50) -> 0 | H7: =SUM(F7:G7) -> 0
A8: PINUS | E8: =PRODUCT(B8*C8) -> 0 | F8: =PRODUCT(E8*18)/118 -> 0 | G8: =PRODUCT(B8*50) -> 0 | H8: =SUM(F8:G8) -> 0
A9: MADIRIYE NINI | E9: =PRODUCT(B9*C9) -> 0 | F9: =PRODUCT(E9*18)/118 -> 0 | G9: =PRODUCT(B9*30) -> 0 | H9: =SUM(F9:G9) -> 0
A10: MADIRIYE NTOYA | E10: =PRODUCT(B10*C10) -> 0 | F10: =PRODUCT(E10*18)/118 -> 0 | G10: =PRODUCT(B10*30) -> 0 | H10: =SUM(F10:G10) -> 0
A11: MADRIEN | E11: =PRODUCT(B11*C11) -> 0 | F11: =PRODUCT(E11*18)/118 -> 0 | G11: =PRODUCT(B11*30) -> 0 | H11: =SUM(F11:G11) -> 0
A12: MADRIEN | E12: =PRODUCT(B12*C12) -> 0 | F12: =PRODUCT(E12*18)/118 -> 0 | G12: =PRODUCT(B12*30) -> 0 | H12: =SUM(F12:G12) -> 0
A13: PLANCHE | E13: =PRODUCT(B13*C13) -> 0 | F13: =PRODUCT(E13*18)/118 -> 0 | G13: =PRODUCT(B13*20) -> 0 | H13: =SUM(F13:G13) -> 0
A14: PLANCHE | E14: =PRODUCT(B14*C14) -> 0 | F14: =PRODUCT(E14*18)/118 -> 0 | G14: =PRODUCT(B14*20) -> 0 | H14: =SUM(F14:G14) -> 0
A15: Other Timber for Difference Price
A16: NAME OF TIMBER | B16: No OF TIMBER | C16: P/U | D16: MSF | E16: TOTAL COST | F16: VAT | G16: MSF | H16: VTA+MST
A17: IBIPANDE | E17: =PRODUCT(B17*C17) -> 0 | F17: =PRODUCT(E17*18)/118 -> 0 | G17: =PRODUCT(B17*D17) -> 0 | H17: =SUM(F17:G17) -> 0
A18: IBIPANDE | E18: =PRODUCT(B18*C18) -> 0 | F18: =PRODUCT(E18*18)/118 -> 0 | G18: =PRODUCT(B18*D18) -> 0 | H18: =SUM(F18:G18) -> 0
A19: UMUSAVE | E19: =PRODUCT(B19*C19) -> 0 | F19: =PRODUCT(E19*18)/118 -> 0 | G19: =PRODUCT(B19*D19) -> 0 | H19: =SUM(F19:G19) -> 0
A20: UMUSAVE | E20: =PRODUCT(B20*C20) -> 0 | F20: =PRODUCT(E20*18)/118 -> 0 | G20: =PRODUCT(B20*D20) -> 0 | H20: =SUM(F20:G20) -> 0
A21: OTHER | E21: =PRODUCT(B21*C21) -> 0 | F21: =PRODUCT(E21*18)/118 -> 0 | G21: =PRODUCT(B21*D21) -> 0 | H21: =SUM(F21:G21) -> 0
A22: OTHER | E22: =PRODUCT(B22*C22) -> 0 | F22: =PRODUCT(E22*18)/118 -> 0 | G22: =PRODUCT(B22*D22) -> 0 | H22: =SUM(F22:G22) -> 0
A23: OTHER | E23: =PRODUCT(B23*C23) -> 0 | F23: =PRODUCT(E23*18)/118 -> 0 | G23: =PRODUCT(B23*D23) -> 0 | H23: =SUM(F23:G23) -> 0
A24: OTHER | E24: =PRODUCT(B24*C24) -> 0 | F24: =PRODUCT(E24*18)/118 -> 0 | G24: =PRODUCT(B24*D24) -> 0 | H24: =SUM(F24:G24) -> 0
A25: OTHER | E25: =PRODUCT(B25*C25) -> 0 | F25: =PRODUCT(E25*18)/118 -> 0 | G25: =PRODUCT(B25*D25) -> 0 | H25: =SUM(F25:G25) -> 0
A26: OTHER | E26: =PRODUCT(B26*C26) -> 0 | F26: =PRODUCT(E26*18)/118 -> 0 | G26: =PRODUCT(B26*D26) -> 0 | H26: =SUM(F26:G26) -> 0
A27: OTHER | E27: =PRODUCT(B27*C27) -> 0 | F27: =PRODUCT(E27*18)/118 -> 0 | G27: =PRODUCT(B27*D27) -> 0 | H27: =SUM(F27:G27) -> 0
A28: OTHER | E28: =PRODUCT(B28*C28) -> 0 | F28: =PRODUCT(E28*18)/118 -> 0 | G28: =PRODUCT(B28*D28) -> 0 | H28: =SUM(F28:G28) -> 0
... A36: OTHER | E36: =PRODUCT(B36*C36) -> 0 | F36: =PRODUCT(E36*18)/118 -> 0 | G36: =PRODUCT(B36*D36) -> 0 | H36: =SUM(F36:G36) -> 0
A37: TOTALY | E37: =SUM(E5:E36) -> 0 | F37: =SUM(F5:F36) -> 0 | G37: =SUM(G5:G36) -> 0 | H37: =SUM(H5:H36) -> 0
A38: SUMMARY | C38: RWF | E38: NAME | G38: Phone | H38: RWF
A39: TOTAL RWF PAID ON MOMO PAY
A40: TOTAL RWF PAID ON CASH
A41: AMOUNT NOT INVOICED
A42: TOTAL RWF DEPPOSITED ON BANK
A43: MEMBERSHIP FEES REGISTRETION
A44: MEMBERSHIP FEES CONTRIBUTION
A45: TOTAL INCOME | C45: =SUM(C39+C40+C41+C42+C43+C44) -> 0
A46: TIMBER SUMMARY
A48: REPORT SUMMARY | C48: TIMBER TYPE | E48: NUMBER OF QUANTITY
C49: INTURUSU | E49: =SUM(B9:B12) -> 0
C50: PINUS | E50: =SUM(B6:B8) -> 0
C51: PALNCHE | E51: =SUM(B13:B14) -> 0
C52: IBIPANDE | E52: =SUM(B17:B18) -> 0
C53: UMUSAVE | E53: =SUM(B19:B20) -> 0
C54: OTHER | E54: =B29 -> 0
C55: OTHER | E55: =B30 -> 0
C56: OTHER | E56: =B31 -> 0
C57: OTHER | E57: =B32 -> 0
C58: OTHER | E58: =B33 -> 0
C59: OTHER | E59: =B34 -> 0
C60: OTHER | E60: =B35 -> 0
C61: OTHER | E61: =B36 -> 0
C62: TOTAL TIMBER | E62: =SUM(E49:H61) -> 0

Sheet NYANZA
A1: QUANTITY REPORT
A3: MONTHS REPORT OF NOVEMBER 2025
A5: NAME OF TIMBER | B5: No OF TIMBER | C5: PRICE OF TIMBER | E5: TOTAL COST | F5: TVA | G5: MSF | H5: TVA+MSF
A6: PINUS NINI | E6: =PRODUCT(B6*C6) -> 0 | F6: =PRODUCT(E6*18)/118 -> 0 | G6: =PRODUCT(B6*50) -> 0 | H6: =SUM(F6:G6) -> 0
A7: PINUS NTOYA | E7: =PRODUCT(B7*C7) -> 0 | F7: =PRODUCT(E7*18)/118 -> 0 | G7: =PRODUCT(B7*50) -> 0 | H7: =SUM(F7:G7) -> 0
A8: PINUS | E8: =PRODUCT(B8*C8) -> 0 | F8: =PRODUCT(E8*18)/118 -> 0 | G8: =PRODUCT(B8*50) -> 0 | H8: =SUM(F8:G8) -> 0
A9: MADIRIYE NINI | E9: =PRODUCT(B9*C9) -> 0 | F9: =PRODUCT(E9*18)/118 -> 0 | G9: =PRODUCT(B9*30) -> 0 | H9: =SUM(F9:G9) -> 0
A10: MADIRIYE NTOYA | E10: =PRODUCT(B10*C10) -> 0 | F10: =PRODUCT(E10*18)/118 -> 0 | G10: =PRODUCT(B10*30) -> 0 | H10: =SUM(F10:G10) -> 0
A11: MADRIEN | E11: =PRODUCT(B11*C11) -> 0 | F11: =PRODUCT(E11*18)/118 -> 0 | G11: =PRODUCT(B11*30) -> 0 | H11: =SUM(F11:G11) -> 0
A12: MADRIEN | E12: =PRODUCT(B12*C12) -> 0 | F12: =PRODUCT(E12*18)/118 -> 0 | G12: =PRODUCT(B12*30) -> 0 | H12: =SUM(F12:G12) -> 0
A13: PLANCHE | E13: =PRODUCT(B13*C13) -> 0 | F13: =PRODUCT(E13*18)/118 -> 0 | G13: =PRODUCT(B13*20) -> 0 | H13: =SUM(F13:G13) -> 0
A14: PLANCHE | E14: =PRODUCT(B14*C14) -> 0 | F14: =PRODUCT(E14*18)/118 -> 0 | G14: =PRODUCT(B14*20) -> 0 | H14: =SUM(F14:G14) -> 0
A15: Other Timber for Difference Price
A16: NAME OF TIMBER | B16: No OF TIMBER | C16: P/U | D16: MSF | E16: TOTAL COST | F16: VAT | G16: MSF | H16: VTA+MST
A17: IBIPANDE | E17: =PRODUCT(B17*C17) -> 0 | F17: =PRODUCT(E17*18)/118 -> 0 | G17: =PRODUCT(B17*D17) -> 0 | H17: =SUM(F17:G17) -> 0
A18: IBIPANDE | E18: =PRODUCT(B18*C18) -> 0 | F18: =PRODUCT(E18*18)/118 -> 0 | G18: =PRODUCT(B18*D18) -> 0 | H18: =SUM(F18:G18) -> 0
A19: UMUSAVE | E19: =PRODUCT(B19*C19) -> 0 | F19: =PRODUCT(E19*18)/118 -> 0 | G19: =PRODUCT(B19*D19) -> 0 | H19: =SUM(F19:G19) -> 0
A20: UMUSAVE | E20: =PRODUCT(B20*C20) -> 0 | F20: =PRODUCT(E20*18)/118 -> 0 | G20: =PRODUCT(B20*D20) -> 0 | H20: =SUM(F20:G20) -> 0
A21: OTHER | E21: =PRODUCT(B21*C21) -> 0 | F21: =PRODUCT(E21*18)/118 -> 0 | G21: =PRODUCT(B21*D21) -> 0 | H21: =SUM(F21:G21) -> 0
A22: OTHER | E22: =PRODUCT(B22*C22) -> 0 | F22: =PRODUCT(E22*18)/118 -> 0 | G22: =PRODUCT(B22*D22) -> 0 | H22: =SUM(F22:G22) -> 0
A23: OTHER | E23: =PRODUCT(B23*C23) -> 0 | F23: =PRODUCT(E23*18)/118 -> 0 | G23: =PRODUCT(B23*D23) -> 0 | H23: =SUM(F23:G23) -> 0
A24: OTHER | E24: =PRODUCT(B24*C24) -> 0 | F24: =PRODUCT(E24*18)/118 -> 0 | G24: =PRODUCT(B24*D24) -> 0 | H24: =SUM(F24:G24) -> 0
A25: OTHER | E25: =PRODUCT(B25*C25) -> 0 | F25: =PRODUCT(E25*18)/118 -> 0 | G25: =PRODUCT(B25*D25) -> 0 | H25: =SUM(F25:G25) -> 0
A26: OTHER | E26: =PRODUCT(B26*C26) -> 0 | F26: =PRODUCT(E26*18)/118 -> 0 | G26: =PRODUCT(B26*D26) -> 0 | H26: =SUM(F26:G26) -> 0
A27: OTHER | E27: =PRODUCT(B27*C27) -> 0 | F27: =PRODUCT(E27*18)/118 -> 0 | G27: =PRODUCT(B27*D27) -> 0 | H27: =SUM(F27:G27) -> 0
A28: OTHER | E28: =PRODUCT(B28*C28) -> 0 | F28: =PRODUCT(E28*18)/118 -> 0 | G28: =PRODUCT(B28*D28) -> 0 | H28: =SUM(F28:G28) -> 0
... A36: OTHER | E36: =PRODUCT(B36*C36) -> 0 | F36: =PRODUCT(E36*18)/118 -> 0 | G36: =PRODUCT(B36*D36) -> 0 | H36: =SUM(F36:G36) -> 0
A37: TOTALY | E37: =SUM(E5:E36) -> 0 | F37: =SUM(F5:F36) -> 0 | G37: =SUM(G5:G36) -> 0 | H37: =SUM(H5:H36) -> 0
A38: SUMMARY | C38: RWF | E38: NAME | G38: Phone | H38: RWF
A39: TOTAL RWF PAID ON MOMO PAY
A40: TOTAL RWF PAID ON CASH
A41: AMOUNT NOT INVOICED
A42: TOTAL RWF DEPPOSITED ON BANK
A43: MEMBERSHIP FEES REGISTRETION
A44: MEMBERSHIP FEES CONTRIBUTION
A45: TOTAL INCOME | C45: =SUM(C39+C40+C41+C42+C43+C44) -> 0
A46: TIMBER SUMMARY
A48: REPORT SUMMARY | C48: TIMBER TYPE | E48: NUMBER OF QUANTITY
C49: INTURUSU | E49: =SUM(B9:B12) -> 0
C50: PINUS | E50: =SUM(B6:B8) -> 0
C51: PALNCHE | E51: =SUM(B13:B14) -> 0
C52: IBIPANDE | E52: =SUM(B17:B18) -> 0
C53: UMUSAVE | E53: =SUM(B19:B20) -> 0
C54: OTHER | E54: =B29 -> 0
C55: OTHER | E55: =B30 -> 0
C56: OTHER | E56: =B31 -> 0
C57: OTHER | E57: =B32 -> 0
C58: OTHER | E58: =B33 -> 0
C59: OTHER | E59: =B34 -> 0
C60: OTHER | E60: =B35 -> 0
C61: OTHER | E61: =B36 -> 0
C62: TOTAL TIMBER | E62: =SUM(E49:H61) -> 0

Sheet GATSIBO
A1: QUANTITY REPORT
A3: MONTHS REPORT OF NOVEMBER 2025
A5: NAME OF TIMBER | B5: No OF TIMBER | C5: PRICE OF TIMBER | E5: TOTAL COST | F5: TVA | G5: MSF | H5: TVA+MSF
A6: PINUS NINI | E6: =PRODUCT(B6*C6) -> 0 | F6: =PRODUCT(E6*18)/118 -> 0 | G6: =PRODUCT(B6*50) -> 0 | H6: =SUM(F6:G6) -> 0
A7: PINUS NTOYA | E7: =PRODUCT(B7*C7) -> 0 | F7: =PRODUCT(E7*18)/118 -> 0 | G7: =PRODUCT(B7*50) -> 0 | H7: =SUM(F7:G7) -> 0
A8: PINUS | E8: =PRODUCT(B8*C8) -> 0 | F8: =PRODUCT(E8*18)/118 -> 0 | G8: =PRODUCT(B8*50) -> 0 | H8: =SUM(F8:G8) -> 0
A9: MADIRIYE NINI | E9: =PRODUCT(B9*C9) -> 0 | F9: =PRODUCT(E9*18)/118 -> 0 | G9: =PRODUCT(B9*30) -> 0 | H9: =SUM(F9:G9) -> 0
A10: MADIRIYE NTOYA | E10: =PRODUCT(B10*C10) -> 0 | F10: =PRODUCT(E10*18)/118 -> 0 | G10: =PRODUCT(B10*30) -> 0 | H10: =SUM(F10:G10) -> 0
A11: MADRIEN | E11: =PRODUCT(B11*C11) -> 0 | F11: =PRODUCT(E11*18)/118 -> 0 | G11: =PRODUCT(B11*30) -> 0 | H11: =SUM(F11:G11) -> 0
A12: MADRIEN | E12: =PRODUCT(B12*C12) -> 0 | F12: =PRODUCT(E12*18)/118 -> 0 | G12: =PRODUCT(B12*30) -> 0 | H12: =SUM(F12:G12) -> 0
A13: PLANCHE | E13: =PRODUCT(B13*C13) -> 0 | F13: =PRODUCT(E13*18)/118 -> 0 | G13: =PRODUCT(B13*20) -> 0 | H13: =SUM(F13:G13) -> 0
A14: PLANCHE | E14: =PRODUCT(B14*C14) -> 0 | F14: =PRODUCT(E14*18)/118 -> 0 | G14: =PRODUCT(B14*20) -> 0 | H14: =SUM(F14:G14) -> 0
A15: Other Timber for Difference Price
A16: NAME OF TIMBER | B16: No OF TIMBER | C16: P/U | D16: MSF | E16: TOTAL COST | F16: VAT | G16: MSF | H16: VTA+MST
A17: IBIPANDE | E17: =PRODUCT(B17*C17) -> 0 | F17: =PRODUCT(E17*18)/118 -> 0 | G17: =PRODUCT(B17*D17) -> 0 | H17: =SUM(F17:G17) -> 0
A18: IBIPANDE | E18: =PRODUCT(B18*C18) -> 0 | F18: =PRODUCT(E18*18)/118 -> 0 | G18: =PRODUCT(B18*D18) -> 0 | H18: =SUM(F18:G18) -> 0
A19: UMUSAVE | E19: =PRODUCT(B19*C19) -> 0 | F19: =PRODUCT(E19*18)/118 -> 0 | G19: =PRODUCT(B19*D19) -> 0 | H19: =SUM(F19:G19) -> 0
A20: UMUSAVE | E20: =PRODUCT(B20*C20) -> 0 | F20: =PRODUCT(E20*18)/118 -> 0 | G20: =PRODUCT(B20*D20) -> 0 | H20: =SUM(F20:G20) -> 0
A21: OTHER | E21: =PRODUCT(B21*C21) -> 0 | F21: =PRODUCT(E21*18)/118 -> 0 | G21: =PRODUCT(B21*D21) -> 0 | H21: =SUM(F21:G21) -> 0
A22: OTHER | E22: =PRODUCT(B22*C22) -> 0 | F22: =PRODUCT(E22*18)/118 -> 0 | G22: =PRODUCT(B22*D22) -> 0 | H22: =SUM(F22:G22) -> 0
A23: OTHER | E23: =PRODUCT(B23*C23) -> 0 | F23: =PRODUCT(E23*18)/118 -> 0 | G23: =PRODUCT(B23*D23) -> 0 | H23: =SUM(F23:G23) -> 0
A24: OTHER | E24: =PRODUCT(B24*C24) -> 0 | F24: =PRODUCT(E24*18)/118 -> 0 | G24: =PRODUCT(B24*D24) -> 0 | H24: =SUM(F24:G24) -> 0
A25: OTHER | E25: =PRODUCT(B25*C25) -> 0 | F25: =PRODUCT(E25*18)/118 -> 0 | G25: =PRODUCT(B25*D25) -> 0 | H25: =SUM(F25:G25) -> 0
A26: OTHER | E26: =PRODUCT(B26*C26) -> 0 | F26: =PRODUCT(E26*18)/118 -> 0 | G26: =PRODUCT(B26*D26) -> 0 | H26: =SUM(F26:G26) -> 0
A27: OTHER | E27: =PRODUCT(B27*C27) -> 0 | F27: =PRODUCT(E27*18)/118 -> 0 | G27: =PRODUCT(B27*D27) -> 0 | H27: =SUM(F27:G27) -> 0
A28: OTHER | E28: =PRODUCT(B28*C28) -> 0 | F28: =PRODUCT(E28*18)/118 -> 0 | G28: =PRODUCT(B28*D28) -> 0 | H28: =SUM(F28:G28) -> 0
... A36: OTHER | E36: =PRODUCT(B36*C36) -> 0 | F36: =PRODUCT(E36*18)/118 -> 0 | G36: =PRODUCT(B36*D36) -> 0 | H36: =SUM(F36:G36) -> 0
A37: TOTALY | E37: =SUM(E5:E36) -> 0 | F37: =SUM(F5:F36) -> 0 | G37: =SUM(G5:G36) -> 0 | H37: =SUM(H5:H36) -> 0
A38: SUMMARY | C38: RWF | E38: NAME | G38: Phone | H38: RWF
A39: TOTAL RWF PAID ON MOMO PAY
A40: TOTAL RWF PAID ON CASH
A41: AMOUNT NOT INVOICED
A42: TOTAL RWF DEPPOSITED ON BANK
A43: MEMBERSHIP FEES REGISTRETION
A44: MEMBERSHIP FEES CONTRIBUTION
A45: TOTAL INCOME | C45: =SUM(C39+C40+C41+C42+C43+C44) -> 0
A46: TIMBER SUMMARY
A48: REPORT SUMMARY | C48: TIMBER TYPE | E48: NUMBER OF QUANTITY
C49: INTURUSU | E49: =SUM(B9:B12) -> 0
C50: PINUS | E50: =SUM(B6:B8) -> 0
C51: PALNCHE | E51: =SUM(B13:B14) -> 0
C52: IBIPANDE | E52: =SUM(B17:B18) -> 0
C53: UMUSAVE | E53: =SUM(B19:B20) -> 0
C54: OTHER | E54: =B29 -> 0
C55: OTHER | E55: =B30 -> 0
C56: OTHER | E56: =B31 -> 0
C57: OTHER | E57: =B32 -> 0
C58: OTHER | E58: =B33 -> 0
C59: OTHER | E59: =B34 -> 0
C60: OTHER | E60: =B35 -> 0
C61: OTHER | E61: =B36 -> 0
C62: TOTAL TIMBER | E62: =SUM(E49:H61) -> 0

Sheet ALL TIMBER SUMMARY
A1: TIMBER SUMMARY
A3: TIMBER TYPE | D3: NUMBER OF QUANTITY
A4: INTURUSU | D4: =NYANZA!E49+KIREHE!E49+NYAGATARE!E49+KAYONZA!E49+MUSANZE!E49+MUSANZE!E49+RUBAVU!E49+KARONGI!E49+NYAMASHEKE!E49+RUSIZI!E49+HUYE!E49+RUHANGO!E49+MUHANGA!E49+BUGESERA!E49+RWAMAGANA!E49+NYARUGENGE!E49+BISHENYI!E49+GAHANGA!E49+KIMIRONKO!E49+GISOZI!E49+GATSIBO!E49+GASHYUSHYA!E49 -> 34693
A5: PINUS | D5: =NYANZA!E50+KIREHE!E50+NYAGATARE!E50+KAYONZA!E50+MUSANZE!E50+MUSANZE!E50+RUBAVU!E50+KARONGI!E50+NYAMASHEKE!E50+RUSIZI!E50+HUYE!E50+RUHANGO!E50+MUHANGA!E50+BUGESERA!E50+RWAMAGANA!E50+NYARUGENGE!E50+BISHENYI!E50+GAHANGA!E50+KIMIRONKO!E50+GISOZI!E50+GATSIBO!E50+GASHYUSHYA!E50 -> 800
A6: PLANCHE | D6: =NYANZA!E51+KIREHE!E51+NYAGATARE!E51+KAYONZA!E51+MUSANZE!E51+MUSANZE!E51+RUBAVU!E51+KARONGI!E51+NYAMASHEKE!E51+RUSIZI!E51+HUYE!E51+RUHANGO!E51+MUHANGA!E51+BUGESERA!E51+RWAMAGANA!E51+NYARUGENGE!E51+BISHENYI!E51+GAHANGA!E51+KIMIRONKO!E51+GISOZI!E51+GATSIBO!E51+GASHYUSHYA!E51 -> 1837
A7: IBIPANDE | D7: =NYANZA!E52+KIREHE!E52+NYAGATARE!E52+KAYONZA!E52+MUSANZE!E52+MUSANZE!E52+RUBAVU!E52+KARONGI!E52+NYAMASHEKE!E52+RUSIZI!E52+HUYE!E52+RUHANGO!E52+MUHANGA!E52+BUGESERA!E52+RWAMAGANA!E52+NYARUGENGE!E52+BISHENYI!E52+GAHANGA!E52+KIMIRONKO!E52+GISOZI!E52+GATSIBO!E52+GASHYUSHYA!E52 -> 1968
A8: UMUSAVE | D8: =NYANZA!E53+KIREHE!E53+NYAGATARE!E53+KAYONZA!E53+MUSANZE!E53+MUSANZE!E53+RUBAVU!E53+KARONGI!E53+NYAMASHEKE!E53+RUSIZI!E53+HUYE!E53+RUHANGO!E53+MUHANGA!E53+BUGESERA!E53+RWAMAGANA!E53+NYARUGENGE!E53+BISHENYI!E53+GAHANGA!E53+KIMIRONKO!E53+GISOZI!E53+GATSIBO!E53+GASHYUSHYA!E53 -> 130
A9: OTHER TYPE OF TIMBER | D9: =NYANZA!E54+KIREHE!E54+NYAGATARE!E54+KAYONZA!E54+MUSANZE!E54+MUSANZE!E54+RUBAVU!E54+KARONGI!E54+NYAMASHEKE!E54+RUSIZI!E54+HUYE!E54+RUHANGO!E54+MUHANGA!E54+BUGESERA!E54+RWAMAGANA!E54+NYARUGENGE!E54+BISHENYI!E54+GAHANGA!E54+KIMIRONKO!E54+GISOZI!E54+GATSIBO!E54+GASHYUSHYA!E54 -> 0
A10: OTHER TYPE OF TIMBER | D10: =NYANZA!E55+KIREHE!E55+NYAGATARE!E55+KAYONZA!E55+MUSANZE!E55+MUSANZE!E55+RUBAVU!E55+KARONGI!E55+NYAMASHEKE!E55+RUSIZI!E55+HUYE!E55+RUHANGO!E55+MUHANGA!E55+BUGESERA!E55+RWAMAGANA!E55+NYARUGENGE!E55+BISHENYI!E55+GAHANGA!E55+KIMIRONKO!E55+GISOZI!E55+GATSIBO!E55+GASHYUSHYA!E55 -> 0
A11: OTHER TYPE OF TIMBER | D11: =NYANZA!E56+KIREHE!E56+NYAGATARE!E56+KAYONZA!E56+MUSANZE!E56+MUSANZE!E56+RUBAVU!E56+KARONGI!E56+NYAMASHEKE!E56+RUSIZI!E56+HUYE!E56+RUHANGO!E56+MUHANGA!E56+BUGESERA!E56+RWAMAGANA!E56+NYARUGENGE!E56+BISHENYI!E56+GAHANGA!E56+KIMIRONKO!E56+GISOZI!E56+GATSIBO!E56+GASHYUSHYA!E56 -> 0
A12: OTHER TYPE OF TIMBER | D12: =NYANZA!E57+KIREHE!E57+NYAGATARE!E57+KAYONZA!E57+MUSANZE!E57+MUSANZE!E57+RUBAVU!E57+KARONGI!E57+NYAMASHEKE!E57+RUSIZI!E57+HUYE!E57+RUHANGO!E57+MUHANGA!E57+BUGESERA!E57+RWAMAGANA!E57+NYARUGENGE!E57+BISHENYI!E57+GAHANGA!E57+KIMIRONKO!E57+GISOZI!E57+GATSIBO!E57+GASHYUSHYA!E57 -> 0
A13: OTHER TYPE OF TIMBER | D13: =NYANZA!E58+KIREHE!E58+NYAGATARE!E58+KAYONZA!E58+MUSANZE!E58+MUSANZE!E58+RUBAVU!E58+KARONGI!E58+NYAMASHEKE!E58+RUSIZI!E58+HUYE!E58+RUHANGO!E58+MUHANGA!E58+BUGESERA!E58+RWAMAGANA!E58+NYARUGENGE!E58+BISHENYI!E58+GAHANGA!E58+KIMIRONKO!E58+GISOZI!E58+GATSIBO!E58+GASHYUSHYA!E58 -> 0
A14: OTHER TYPE OF TIMBER | D14: =NYANZA!E59+KIREHE!E59+NYAGATARE!E59+KAYONZA!E59+MUSANZE!E59+MUSANZE!E59+RUBAVU!E59+KARONGI!E59+NYAMASHEKE!E59+RUSIZI!E59+HUYE!E59+RUHANGO!E59+MUHANGA!E59+BUGESERA!E59+RWAMAGANA!E59+NYARUGENGE!E59+BISHENYI!E59+GAHANGA!E59+KIMIRONKO!E59+GISOZI!E59+GATSIBO!E59+GASHYUSHYA!E59 -> 0
A15: OTHER TYPE OF TIMBER | D15: =NYANZA!E60+KIREHE!E60+NYAGATARE!E60+KAYONZA!E60+MUSANZE!E60+MUSANZE!E60+RUBAVU!E60+KARONGI!E60+NYAMASHEKE!E60+RUSIZI!E60+HUYE!E60+RUHANGO!E60+MUHANGA!E60+BUGESERA!E60+RWAMAGANA!E60+NYARUGENGE!E60+BISHENYI!E60+GAHANGA!E60+KIMIRONKO!E60+GISOZI!E60+GATSIBO!E60+GASHYUSHYA!E60 -> 0
A16: OTHER TYPE OF TIMBER | D16: =NYANZA!E61+KIREHE!E61+NYAGATARE!E61+KAYONZA!E61+MUSANZE!E61+MUSANZE!E61+RUBAVU!E61+KARONGI!E61+NYAMASHEKE!E61+RUSIZI!E61+HUYE!E61+RUHANGO!E61+MUHANGA!E61+BUGESERA!E61+RWAMAGANA!E61+NYARUGENGE!E61+BISHENYI!E61+GAHANGA!E61+KIMIRONKO!E61+GISOZI!E61+GATSIBO!E61+GASHYUSHYA!E61 -> 0
A17: TOTAL TIMBER | D17: =SUM(D4:D16) -> 39428
