Workbook

Sheet FINACHIAL REPORT
A1: RWVCA REPORT DATE ….........
A2: RWANDA WOOD VALUE CHAIN ASSOCIATION
A4: ICPCs NAME | B4: TVA IN | C4: MSF IN | D4: MS REGIS | E4: MS CONTR | F4: TVA+MSF | G4: FR NOT INVOICED | H4: MOMO | I4: PAID ON BANK | J4: CASH
A5: GISOZI | B5: =GISOZI!F37 -> 43011052 | C5: =GISOZI!G37 -> 3496975 | D5: =GISOZI!C43 -> 0 | E5: =GISOZI!C44 -> 0 | F5: =SUM(B5:C5) -> 46508027 | G5: =GISOZI!C41 -> 0 | H5: =GISOZI!C39 -> 46511291 | I5: =GISOZI!C42 -> 0 | J5: =GISOZI!C40 -> 0
A6: GAHANGA | B6: =GAHANGA!F37 -> 9050781.7 | C6: =GAHANGA!G37 -> 798440 | D6: =GAHANGA!C43 -> 0 | E6: =GAHANGA!C44 -> 0 | F6: =SUM(B6:C6) -> 9849221.7 | G6: =GAHANGA!C41 -> 0 | H6: =GAHANGA!C39 -> 9846122 | I6: =GAHANGA!C42 -> 0 | J6: =GAHANGA!C40 -> 0
A7: KIMIROMKO | B7: =KIMIRONKO!F37 -> 7669729.2 | C7: =KIMIRONKO!G37 -> 686820 | D7: =KIMIRONKO!C43 -> 0 | E7: =KIMIRONKO!C44 -> 0 | F7: =SUM(B7:C7) -> 8356549.2 | G7: =KIMIRONKO!C41 -> 0 | H7: =KIMIRONKO!C39 -> 0 | I7: =KIMIRONKO!C42 -> 0 | J7: =KIMIRONKO!C40 -> 0
A8: BISHENYI | B8: =BISHENYI!F37 -> 9938790 | C8: =BISHENYI!G37 -> 822220 | D8: =BISHENYI!C43 -> 0 | E8: =BISHENYI!C44 -> 0 | F8: =SUM(B8:C8) -> 10761010 | G8: =BISHENYI!C41 -> 0 | H8: =BISHENYI!C39 -> 10761010 | I8: =BISHENYI!C42 -> 0 | J8: =BISHENYI!C40 -> 0
A9: RWAMAGANA | B9: =RWAMAGANA!F37 -> 3853980 | C9: =RWAMAGANA!G37 -> 456010 | D9: =RWAMAGANA!C43 -> 0 | E9: =RWAMAGANA!C44 -> 0 | F9: =SUM(B9:C9) -> 4309990 | G9: =RWAMAGANA!C41 -> 0 | H9: =RWAMAGANA!C39 -> 4309990 | I9: =RWAMAGANA!C42 -> 0 | J9: =RWAMAGANA!C40 -> 0
A10: BUGESERA | B10: =BUGESERA!F37 -> 12888063 | C10: =BUGESERA!G37 -> 1192520 | D10: =BUGESERA!C43 -> 0 | E10: =BUGESERA!C44 -> 0 | F10: =SUM(B10:C10) -> 14080583 | G10: =BUGESERA!C41 -> 0 | H10: =BUGESERA!C39 -> 13878073 | I10: =BUGESERA!C42 -> 0 | J10: =BUGESERA!C40 -> 202510
A11: MUHANGA | B11: =MUHANGA!F37 -> 4724841.4 | C11: =MUHANGA!G37 -> 403250 | D11: =MUHANGA!C43 -> 0 | E11: =MUHANGA!C44 -> 0 | F11: =SUM(B11:C11) -> 5128091.4 | G11: =MUHANGA!C41 -> 0 | H11: =MUHANGA!C39 -> 5128091 | I11: =MUHANGA!C42 -> 0 | J11: =MUHANGA!C40 -> 0
A12: RUHANGO | B12: =RUHANGO!F37 -> 501864.41 | C12: =RUHANGO!G37 -> 206850 | D12: =RUHANGO!C43 -> 0 | E12: =RUHANGO!C44 -> 0 | F12: =SUM(B12:C12) -> 708714.41 | G12: =RUHANGO!C41 -> 0 | H12: =RUHANGO!C39 -> 708714 | I12: =RUHANGO!C42 -> 0 | J12: =RUHANGO!C40 -> 0
A13: HUYE | B13: =HUYE!F37 -> 3698455.4 | C13: =HUYE!G37 -> 417190 | D13: =HUYE!C43 -> 0 | E13: =HUYE!C44 -> 0 | F13: =SUM(B13:C13) -> 4115645.4 | G13: =HUYE!C41 -> 0 | H13: =HUYE!C39 -> 4051363 | I13: =HUYE!C42 -> 0 | J13: =HUYE!C40 -> 64282
A14: RUSIZI | B14: =RUSIZI!F37 -> 2099176.8 | C14: =RUSIZI!G37 -> 470800 | D14: =RUSIZI!C43 -> 0 | E14: =RUSIZI!C44 -> 0 | F14: =SUM(B14:C14) -> 2569976.8 | G14: =RUSIZI!C41 -> 0 | H14: =RUSIZI!C39 -> 2569977 | I14: =RUSIZI!C42 -> 0 | J14: =RUSIZI!C40 -> 0
A15: NYAMAGABE | B15: =NYAMAGABE!F37 -> 221400 | C15: =NYAMAGABE!G37 -> 26250 | D15: =NYAMAGABE!C43 -> 0 | E15: =NYAMAGABE!C44 -> 0 | F15: =SUM(B15:C15) -> 247650 | G15: =NYAMAGABE!C41 -> 0 | H15: =NYAMAGABE!C39 -> 247650 | I15: =NYAMAGABE!C42 -> 0 | J15: =NYAMAGABE!C40 -> 0
A16: KARONGI | B16: =KARONGI!F37 -> 1639954.4 | C16: =KARONGI!G37 -> 212400 | D16: =KARONGI!C43 -> 0 | E16: =KARONGI!C44 -> 0 | F16: =SUM(B16:C16) -> 1852354.4 | G16: =KARONGI!C41 -> 0 | H16: =KARONGI!C39 -> 1852254 | I16: =KARONGI!C42 -> 0 | J16: =KARONGI!C40 -> 0
A17: RUBAVU | B17: =RUBAVU!F37 -> 4851126 | C17: =RUBAVU!G37 -> 487130 | D17: =RUBAVU!C43 -> 0 | E17: =RUBAVU!C44 -> 0 | F17: =SUM(B17:C17) -> 5338256 | G17: =RUBAVU!C41 -> 0 | H17: =RUBAVU!C39 -> 4838256 | I17: =RUBAVU!C42 -> 500000 | J17: =RUBAVU!C40 -> 0
A18: MUSANZE | B18: =MUSANZE!F37 -> 2904333.6 | C18: =MUSANZE!G37 -> 337566 | D18: =MUSANZE!C43 -> 0 | E18: =MUSANZE!C44 -> 0 | F18: =SUM(B18:C18) -> 3241899.6 | G18: =MUSANZE!C41 -> 0 | H18: =MUSANZE!C39 -> 2093880 | I18: =MUSANZE!C42 -> 0 | J18: =MUSANZE!C40 -> 1148020
A19: KAYONZA | B19: =KAYONZA!F37 -> 3121470 | C19: =KAYONZA!G37 -> 315740 | D19: =KAYONZA!C43 -> 0 | E19: =KAYONZA!C44 -> 0 | F19: =SUM(B19:C19) -> 3437210 | G19: =KAYONZA!C41 -> 0 | H19: =KAYONZA!C39 -> 3437210 | I19: =KAYONZA!C42 -> 0 | J19: =KAYONZA!C40 -> 0
A20: NYAGATARE | B20: =NYAGATARE!F37 -> 1055972.7 | C20: =NYAGATARE!G37 -> 397650 | D20: =NYAGATARE!C43 -> 0 | E20: =NYAGATARE!C44 -> 0 | F20: =SUM(B20:C20) -> 1453622.7 | G20: =NYAGATARE!C41 -> 0 | H20: =NYAGATARE!C39 -> 1521032 | I20: =NYAGATARE!C42 -> 0 | J20: =NYAGATARE!C40 -> 0
A21: KIREHE | B21: =KIREHE!F37 -> 1757244.7 | C21: =KIREHE!G37 -> 344284 | D21: =KIREHE!C43 -> 0 | E21: =KIREHE!C44 -> 0 | F21: =SUM(B21:C21) -> 2101528.7 | G21: =KIREHE!C41 -> 0 | H21: =KIREHE!C39 -> 2101529 | I21: =KIREHE!C42 -> 0 | J21: =KIREHE!C40 -> 0
A22: NYANZA | B22: =NYANZA!F37 -> 517118.64 | C22: =NYANZA!G37 -> 201850 | D22: =NYANZA!C43 -> 0 | E22: =NYANZA!C44 -> 0 | F22: =SUM(B22:C22) -> 718968.64 | G22: =NYANZA!C41 -> 0 | H22: =NYANZA!C39 -> 718369 | I22: =NYANZA!C42 -> 0 | J22: =NYANZA!C40 -> 0
A23: NYARUGENGE | B23: =NYARUGENGE!F37 -> 4839858 | C23: =NYARUGENGE!G37 -> 439010 | D23: =NYARUGENGE!C43 -> 0 | E23: =NYARUGENGE!C44 -> 300000 | F23: =SUM(B23:C23) -> 5278868 | G23: =NYARUGENGE!C41 -> 0 | H23: =NYARUGENGE!C39 -> 5278868 | I23: =NYARUGENGE!C42 -> 0 | J23: =NYARUGENGE!C40 -> 0
A24: GATSIBO | B24: =GATSIBO!F37 -> 593550 | C24: =GATSIBO!G37 -> 221600 | D24: =GATSIBO!C43 -> 0 | E24: =GATSIBO!C44 -> 0 | F24: =SUM(B24:C24) -> 815150 | G24: =GATSIBO!C41 -> 53100 | H24: =GATSIBO!C39 -> 815150 | I24: =GATSIBO!C42 -> 0 | J24: =GATSIBO!C40 -> 0
A25: GASHYUSHYA | B25: =GASHYUSHYA!F37 -> 3407283 | C25: =GASHYUSHYA!G37 -> 380300 | D25: =GASHYUSHYA!C43 -> 0 | E25: =GASHYUSHYA!C44 -> 0 | F25: =SUM(B25:C25) -> 3787583 | G25: =GASHYUSHYA!C41 -> 0 | H25: =GASHYUSHYA!C39 -> 3787583 | I25: =GASHYUSHYA!C42 -> 0 | J25: =GASHYUSHYA!C40 -> 0
A26: RUTSIRO | B26: =RUTSIRO!F37 -> 0 | C26: =RUTSIRO!G37 -> 0 | D26: =RUTSIRO!C43 -> 0 | E26: =RUTSIRO!C44 -> 0 | F26: =SUM(B26:C26) -> 0 | G26: =RUTSIRO!C41 -> 0 | H26: =RUTSIRO!C39 -> 0 | I26: =RUTSIRO!C42 -> 0 | J26: =RUTSIRO!C40 -> 0
A27: NGORORERO | B27: =NGORORERO!F37 -> 12813.559 | C27: =NGORORERO!G37 -> 2100 | D27: =NGORORERO!C43 -> 0 | E27: =NGORORERO!C44 -> 0 | F27: =SUM(B27:C27) -> 14913.559 | G27: =NGORORERO!C41 -> 0 | H27: =NGORORERO!C39 -> 14914 | I27: =NGORORERO!C42 -> 0 | J27: =NGORORERO!C40 -> 0
B28: =THIRTH!F37 -> 0 | C28: =THIRTH!G37 -> 0 | D28: =THIRTH!C43 -> 0 | E28: =THIRTH!C44 -> 0 | F28: =SUM(B28:C28) -> 0 | G28: =THIRTH!C41 -> 0 | H28: =THIRTH!C39 -> 0 | I28: =THIRTH!C42 -> 0 | J28: =THIRTH!C40 -> 0
B29: =SUM(B5:B28) -> 1.2235886e+08 | C29: =SUM(C5:C28) -> 12316955 | D29: =SUM(D5:D28) -> 0 | E29: =SUM(E5:E28) -> 300000 | F29: =SUM(F5:F28) -> 1.3467581e+08 | G29: =SUM(G5:G28) -> 53100 | H29: =SUM(H5:H28) -> 124471326 | I29: =SUM(I5:I28) -> 500000 | J29: =SUM(J5:J28) -> 1414812
E30: REPORT DESCRIPTION
A31: REPORT SUMMARY
A32: VAT+MSF | C32: =SUM(B29+C29) -> 1.3467581e+08
A33: VAT+MSF+FR NOT INVOCED | C33: =SUM(F29,G29) -> 1.3472891e+08
A34: MOMO+CASH+BANK+FR NOT INVOICED | C34: =SUM(H29,J29,I29+G29) -> 126439238
A35: MS REGIST+MS CONTRIB | C35: =SUM(D29:E29) -> 300000
A36: TOTAL INCOME INVOICED+MSF&MS REGIST | C36: =SUM(H29+I29+J29+C35) -> 126686138 | E36: COORDINATOR NAME: Chantal NIYIGENA
A37: TOTAL INCOME | C37: =NYANZA!C45+KIREHE!C45+NYAGATARE!C45+KAYONZA!C45+MUSANZE!C45+MUSANZE!C45+RUBAVU!C45+KARONGI!C45+NYAMAGABE!C45+RUSIZI!C45+HUYE!C45+RUHANGO!C45+MUHANGA!C45+BUGESERA!C45+RWAMAGANA!C45+NYARUGENGE!C45+BISHENYI!C45+GAHANGA!C45+KIMIRONKO!C45+GISOZI!C45+GATSIBO!C45+GASHYUSHYA!C45 -> 129966224
A38: RWANDA WOOD VALUE CHAIN ASSOCIATION

Sheet GISOZI
A1: QUANTITY REPORT
A3: MONTHS REPORT OF APRIL 2026
A5: NAME OF TIMBER | B5: No OF TIMBER | C5: PRICE OF TIMBER | E5: TOTAL COST | F5: TVA | G5: MSF | H5: TVA+MSF
A6: PINUS NINI | B6: 614 | C6: 10620 | E6: =PRODUCT(B6*C6) -> 6520680 | F6: =PRODUCT(E6*18)/118 -> 994680 | G6: =PRODUCT(B6*50) -> 30700 | H6: =SUM(F6:G6) -> 1025380
A7: PINUS | B7: 5592 | C7: 8000 | E7: =PRODUCT(B7*C7) -> 44736000 | F7: =PRODUCT(E7*18)/118 -> 6824135.6 | G7: =PRODUCT(B7*50) -> 279600 | H7: =SUM(F7:G7) -> 7103735.6
A8: PINUS NTOYA | B8: 136 | C8: 6000 | E8: =PRODUCT(B8*C8) -> 816000 | F8: =PRODUCT(E8*18)/118 -> 124474.58 | G8: =PRODUCT(B8*50) -> 6800 | H8: =SUM(F8:G8) -> 131274.58
A9: MADIRIYE NINI | B9: 819 | C9: 3776 | E9: =PRODUCT(B9*C9) -> 3092544 | F9: =PRODUCT(E9*18)/118 -> 471744 | G9: =PRODUCT(B9*30) -> 24570 | H9: =SUM(F9:G9) -> 496314
A10: MADIRIYE NTOYA | B10: 10782 | C10: 2000 | E10: =PRODUCT(B10*C10) -> 21564000 | F10: =PRODUCT(E10*18)/118 -> 3289423.7 | G10: =PRODUCT(B10*30) -> 323460 | H10: =SUM(F10:G10) -> 3612883.7
A11: MADRIEN | B11: 1050 | C11: 3000 | E11: =PRODUCT(B11*C11) -> 3150000 | F11: =PRODUCT(E11*18)/118 -> 480508.47 | G11: =PRODUCT(B11*30) -> 31500 | H11: =SUM(F11:G11) -> 512008.47
A12: MADRIEN | B12: 87655 | C12: 2124 | E12: =PRODUCT(B12*C12) -> 186179220 | F12: =PRODUCT(E12*18)/118 -> 28400220 | G12: =PRODUCT(B12*30) -> 2629650 | H12: =SUM(F12:G12) -> 31029870
A13: PLANCHE | B13: 700 | C13: 1357 | E13: =PRODUCT(B13*C13) -> 949900 | F13: =PRODUCT(E13*18)/118 -> 144900 | G13: =PRODUCT(B13*20) -> 14000 | H13: =SUM(F13:G13) -> 158900
A14: MUNYONGORO | B14: 396 | C14: 3000 | E14: =PRODUCT(B14*C14) -> 1188000 | F14: =PRODUCT(E14*18)/118 -> 181220.34 | G14: =PRODUCT(B14*20) -> 7920 | H14: =SUM(F14:G14) -> 189140.34
A15: Other Timber for Difference Price
A16: NAME OF TIMBER | B16: No OF TIMBER | C16: P/U | D16: MSF | E16: TOTAL COST | F16: VAT | G16: MSF | H16: VTA+MST
A17: PINUS | C17: 10000 | D17: 50 | E17: =PRODUCT(B17*C17) -> 0 | F17: =PRODUCT(E17*18)/118 -> 0 | G17: =PRODUCT(B17*D17) -> 0 | H17: =SUM(F17:G17) -> 0
A18: MUNYONGORO | C18: 2360 | D18: 20 | E18: =PRODUCT(B18*C18) -> 0 | F18: =PRODUCT(E18*18)/118 -> 0 | G18: =PRODUCT(B18*D18) -> 0 | H18: =SUM(F18:G18) -> 0
A19: MADRIEN | B19: 720 | C19: 2600 | D19: 30 | E19: =PRODUCT(B19*C19) -> 1872000 | F19: =PRODUCT(E19*18)/118 -> 285559.32 | G19: =PRODUCT(B19*D19) -> 21600 | H19: =SUM(F19:G19) -> 307159.32
A20: PINUS NTOYA | B20: 900 | C20: 4720 | D20: 50 | E20: =PRODUCT(B20*C20) -> 4248000 | F20: =PRODUCT(E20*18)/118 -> 648000 | G20: =PRODUCT(B20*D20) -> 45000 | H20: =SUM(F20:G20) -> 693000
A21: IBIPANDE BY'INTURUSU | E21: =PRODUCT(B21*C21) -> 0 | F21: =PRODUCT(E21*18)/118 -> 0 | G21: =PRODUCT(B21*D21) -> 0 | H21: =SUM(F21:G21) -> 0
A22: IBIPANDE BYA PINUS | B22: 1007 | C22: 2000 | D22: 25 | E22: =PRODUCT(B22*C22) -> 2014000 | F22: =PRODUCT(E22*18)/118 -> 307220.34 | G22: =PRODUCT(B22*D22) -> 25175 | H22: =SUM(F22:G22) -> 332395.34
A23: PINUS | B23: 1020 | C23: 5000 | D23: 50 | E23: =PRODUCT(B23*C23) -> 5100000 | F23: =PRODUCT(E23*18)/118 -> 777966.1 | G23: =PRODUCT(B23*D23) -> 51000 | H23: =SUM(F23:G23) -> 828966.1
A24: PLANCHE ZA PINUS | B24: 300 | C24: 1770 | D24: 20 | E24: =PRODUCT(B24*C24) -> 531000 | F24: =PRODUCT(E24*18)/118 -> 81000 | G24: =PRODUCT(B24*D24) -> 6000 | H24: =SUM(F24:G24) -> 87000
A25: SIPURE | C25: 18000 | D25: 50 | E25: =PRODUCT(B25*C25) -> 0 | F25: =PRODUCT(E25*18)/118 -> 0 | G25: =PRODUCT(B25*D25) -> 0 | H25: =SUM(F25:G25) -> 0
A26: INTURUSU NTOYA | C26: 2500 | D26: 30 | E26: =PRODUCT(B26*C26) -> 0 | F26: =PRODUCT(E26*18)/118 -> 0 | G26: =PRODUCT(B26*D26) -> 0 | H26: =SUM(F26:G26) -> 0
A27: MUNYONGORO | C27: 3000 | D27: 20 | E27: =PRODUCT(B27*C27) -> 0 | F27: =PRODUCT(E27*18)/118 -> 0 | G27: =PRODUCT(B27*D27) -> 0 | H27: =SUM(F27:G27) -> 0
A28: MADRIEN | C28: 3000 | D28: 30 | E28: =PRODUCT(B28*C28) -> 0 | F28: =PRODUCT(E28*18)/118 -> 0 | G28: =PRODUCT(B28*D28) -> 0 | H28: =SUM(F28:G28) -> 0
A29: SIPURE | C29: 12036 | D29: 50 | E29: =PRODUCT(B29*C29) -> 0 | F29: =PRODUCT(E29*18)/118 -> 0 | G29: =PRODUCT(B29*D29) -> 0 | H29: =SUM(F29:G29) -> 0
A30: DESCHET | C30: 10000 | E30: =PRODUCT(B30*C30) -> 0 | F30: =PRODUCT(E30*18)/118 -> 0 | G30: =PRODUCT(B30*D30) -> 0 | H30: =SUM(F30:G30) -> 0
A31: DESCHET | D31: 5000 | E31: =PRODUCT(B31*C31) -> 0 | F31: =PRODUCT(E31*18)/118 -> 0 | G31: =PRODUCT(B31*D31) -> 0 | H31: =SUM(F31:G31) -> 0
A32: OTHER | E32: =PRODUCT(B32*C32) -> 0 | F32: =PRODUCT(E32*18)/118 -> 0 | G32: =PRODUCT(B32*D32) -> 0 | H32: =SUM(F32:G32) -> 0
A33: OTHER | E33: =PRODUCT(B33*C33) -> 0 | F33: =PRODUCT(E33*18)/118 -> 0 | G33: =PRODUCT(B33*D33) -> 0 | H33: =SUM(F33:G33) -> 0
A34: OTHER | E34: =PRODUCT(B34*C34) -> 0 | F34: =PRODUCT(E34*18)/118 -> 0 | G34: =PRODUCT(B34*D34) -> 0 | H34: =SUM(F34:G34) -> 0
A35: OTHER | E35: =PRODUCT(B35*C35) -> 0 | F35: =PRODUCT(E35*18)/118 -> 0 | G35: =PRODUCT(B35*D35) -> 0 | H35: =SUM(F35:G35) -> 0
A36: OTHER | E36: =PRODUCT(B36*C36) -> 0 | F36: =PRODUCT(E36*18)/118 -> 0 | G36: =PRODUCT(B36*D36) -> 0 | H36: =SUM(F36:G36) -> 0
A37: TOTALY | E37: =SUM(E5:E36) -> 281961344 | F37: =SUM(F5:F36) -> 43011052 | G37: =SUM(G5:G36) -> 3496975 | H37: =SUM(H5:H36) -> 46508027
A38: SUMMARY | C38: RWF | E38: NAME | G38: Phone | H38: RWF
A39: TOTAL RWF PAID ON MOMO PAY | C39: 46511291
A40: TOTAL RWF PAID ON CASH
A41: AMOUNT NOT INVOICED
A42: TOTAL RWF DEPPOSITED ON BANK
A43: MEMBERSHIP FEES REGISTRETION
A44: MEMBERSHIP FEES CONTRIBUTION
A45: TOTAL INCOME | C45: =SUM(C39+C40+C41+C42+C43+C44) -> 46511291
A46: TIMBER SUMMARY
A48: REPORT SUMMARY | C48: TIMBER TYPE | E48: NUMBER OF QUANTITY
C49: INTURUSU | E49: =SUM(B9:B12) -> 100306
C50: PINUS | E50: =SUM(B6:B8) -> 6342
C51: PALNCHE | E51: =SUM(B13:B14) -> 1096
C52: IBIPANDE | E52: =SUM(B17:B18) -> 0
C53: UMUSAVE | E53: =SUM(B19:B20) -> 1620
C54: OTHER | E54: =B29 -> 0
C55: OTHER | E55: =B30 -> 0
C56: OTHER | E56: =B31 -> 0
C57: OTHER | E57: =B32 -> 0
C58: OTHER | E58: =B33 -> 0
C59: OTHER | E59: =B34 -> 0
C60: OTHER | E60: =B35 -> 0
C61: OTHER | E61: =B36 -> 0
C62: TOTAL TIMBER | E62: =SUM(E49:H61) -> 109364

Sheet BISHENYI
A1: QUANTITY REPORT
A3: MONTHS REPORT OF APRIL 2026
A5: NAME OF TIMBER | B5: No OF TIMBER | C5: PRICE OF TIMBER | E5: TOTAL COST | F5: TVA | G5: MSF | H5: TVA+MSF
A6: PINUS NINI | E6: =PRODUCT(B6*C6) -> 0 | F6: =PRODUCT(E6*18)/118 -> 0 | G6: =PRODUCT(B6*50) -> 0 | H6: =SUM(F6:G6) -> 0
A7: PINUS NTOYA | B7: 155 | C7: 7670 | E7: =PRODUCT(B7*C7) -> 1188850 | F7: =PRODUCT(E7*18)/118 -> 181350 | G7: =PRODUCT(B7*50) -> 7750 | H7: =SUM(F7:G7) -> 189100
A8: PINUS | E8: =PRODUCT(B8*C8) -> 0 | F8: =PRODUCT(E8*18)/118 -> 0 | G8: =PRODUCT(B8*50) -> 0 | H8: =SUM(F8:G8) -> 0
A9: MADIRIYE NINI | E9: =PRODUCT(B9*C9) -> 0 | F9: =PRODUCT(E9*18)/118 -> 0 | G9: =PRODUCT(B9*30) -> 0 | H9: =SUM(F9:G9) -> 0
A10: MADIRIYE NTOYA | B10: 25349 | C10: 2360 | E10: =PRODUCT(B10*C10) -> 59823640 | F10: =PRODUCT(E10*18)/118 -> 9125640 | G10: =PRODUCT(B10*30) -> 760470 | H10: =SUM(F10:G10) -> 9886110
A11: MADRIEN | E11: =PRODUCT(B11*C11) -> 0 | F11: =PRODUCT(E11*18)/118 -> 0 | G11: =PRODUCT(B11*30) -> 0 | H11: =SUM(F11:G11) -> 0
A12: MADRIEN | E12: =PRODUCT(B12*C12) -> 0 | F12: =PRODUCT(E12*18)/118 -> 0 | G12: =PRODUCT(B12*30) -> 0 | H12: =SUM(F12:G12) -> 0
A13: PLANCHE | B13: 2700 | C13: 1534 | E13: =PRODUCT(B13*C13) -> 4141800 | F13: =PRODUCT(E13*18)/118 -> 631800 | G13: =PRODUCT(B13*20) -> 54000 | H13: =SUM(F13:G13) -> 685800
A14: PLANCHE | E14: =PRODUCT(B14*C14) -> 0 | F14: =PRODUCT(E14*18)/118 -> 0 | G14: =PRODUCT(B14*20) -> 0 | H14: =SUM(F14:G14) -> 0
A15: Other Timber for Difference Price
A16: NAME OF TIMBER | B16: No OF TIMBER | C16: P/U | D16: MSF | E16: TOTAL COST | F16: VAT | G16: MSF | H16: VTA+MST
A17: IBIPANDE BYA PINUS | C17: 2000 | D17: 50 | E17: =PRODUCT(B17*C17) -> 0 | F17: =PRODUCT(E17*18)/118 -> 0 | G17: =PRODUCT(B17*D17) -> 0 | H17: =SUM(F17:G17) -> 0
A18: IBIPANDE | E18: =PRODUCT(B18*C18) -> 0 | F18: =PRODUCT(E18*18)/118 -> 0 | G18: =PRODUCT(B18*D18) -> 0 | H18: =SUM(F18:G18) -> 0
A19: UMUSAVE | E19: =PRODUCT(B19*C19) -> 0 | F19: =PRODUCT(E19*18)/118 -> 0 | G19: =PRODUCT(B19*D19) -> 0 | H19: =SUM(F19:G19) -> 0
A20: UMUSAVE | E20: =PRODUCT(B20*C20) -> 0 | F20: =PRODUCT(E20*18)/118 -> 0 | G20: =PRODUCT(B20*D20) -> 0 | H20: =SUM(F20:G20) -> 0
A21: OTHER | E21: =PRODUCT(B21*C21) -> 0 | F21: =PRODUCT(E21*18)/118 -> 0 | G21: =PRODUCT(B21*D21) -> 0 | H21: =SUM(F21:G21) -> 0
A22: OTHER | E22: =PRODUCT(B22*C22) -> 0 | F22: =PRODUCT(E22*18)/118 -> 0 | G22: =PRODUCT(B22*D22) -> 0 | H22: =SUM(F22:G22) -> 0
A23: OTHER | E23: =PRODUCT(B23*C23) -> 0 | F23: =PRODUCT(E23*18)/118 -> 0 | G23: =PRODUCT(B23*D23) -> 0 | H23: =SUM(F23:G23) -> 0
A24: OTHER | E24: =PRODUCT(B24*C24) -> 0 | F24: =PRODUCT(E24*18)/118 -> 0 | G24: =PRODUCT(B24*D24) -> 0 | H24: =SUM(F24:G24) -> 0
A25: OTHER | E25: =PRODUCT(B25*C25) -> 0 | F25: =PRODUCT(E25*18)/118 -> 0 | G25: =PRODUCT(B25*D25) -> 0 | H25: =SUM(F25:G25) -> 0
A26: OTHER | E26: =PRODUCT(B26*C26) -> 0 | F26: =PRODUCT(E26*18)/118 -> 0 | G26: =PRODUCT(B26*D26) -> 0 | H26: =SUM(F26:G26) -> 0
A27: OTHER | E27: =PRODUCT(B27*C27) -> 0 | F27: =PRODUCT(E27*18)/118 -> 0 | G27: =PRODUCT(B27*D27) -> 0 | H27: =SUM(F27:G27) -> 0
A28: OTHER | E28: =PRODUCT(B28*C28) -> 0 | F28: =PRODUCT(E28*18)/118 -> 0 | G28: =PRODUCT(B28*D28) -> 0 | H28: =SUM(F28:G28) -> 0
A29: OTHER | E29: =PRODUCT(B29*C29) -> 0 | F29: =PRODUCT(E29*18)/118 -> 0 | G29: =PRODUCT(B29*D29) -> 0 | H29: =SUM(F29:G29) -> 0
... A36: OTHER | E36: =PRODUCT(B36*C36) -> 0 | F36: =PRODUCT(E36*18)/118 -> 0 | G36: =PRODUCT(B36*D36) -> 0 | H36: =SUM(F36:G36) -> 0
A37: TOTALY | E37: =SUM(E5:E36) -> 65154290 | F37: =SUM(F5:F36) -> 9938790 | G37: =SUM(G5:G36) -> 822220 | H37: =SUM(H5:H36) -> 10761010
A38: SUMMARY | C38: RWF | E38: NAME | G38: Phone | H38: RWF
A39: TOTAL RWF PAID ON MOMO PAY | C39: 10761010
A40: TOTAL RWF PAID ON CASH
A41: AMOUNT NOT INVOICED
A42: TOTAL RWF DEPPOSITED ON BANK
A43: MEMBERSHIP FEES REGISTRETION
A44: MEMBERSHIP FEES CONTRIBUTION
A45: TOTAL INCOME | C45: =SUM(C39+C40+C41+C42+C43+C44) -> 10761010
A46: TIMBER SUMMARY
A48: REPORT SUMMARY | C48: TIMBER TYPE | E48: NUMBER OF QUANTITY
C49: INTURUSU | E49: =SUM(B9:B12) -> 25349
C50: PINUS | E50: =SUM(B6:B8) -> 155
C51: PALNCHE | E51: =SUM(B13:B14) -> 2700
C52: IBIPANDE | E52: =SUM(B17:B18) -> 0
C53: UMUSAVE | E53: =SUM(B19:B20) -> 0
C54: OTHER | E54: =B29 -> 0
C55: OTHER | E55: =B30 -> 0
C56: OTHER | E56: =B31 -> 0
C57: OTHER | E57: =B32 -> 0
C58: OTHER | E58: =B33 -> 0
C59: OTHER | E59: =B34 -> 0
C60: OTHER | E60: =B35 -> 0
C61: OTHER | E61: =B36 -> 0
C62: TOTAL TIMBER | E62: =SUM(E49:H61) -> 28204

Sheet RWAMAGANA
A1: QUANTITY REPORT
A3: MONTHS REPORT OF APRIL 2026
A5: NAME OF TIMBER | B5: No OF TIMBER | C5: PRICE OF TIMBER | E5: TOTAL COST | F5: TVA | G5: MSF | H5: TVA+MSF
A6: PINUS NINI | E6: =PRODUCT(B6*C6) -> 0 | F6: =PRODUCT(E6*18)/118 -> 0 | G6: =PRODUCT(B6*50) -> 0 | H6: =SUM(F6:G6) -> 0
A7: PINUS NTOYA | E7: =PRODUCT(B7*C7) -> 0 | F7: =PRODUCT(E7*18)/118 -> 0 | G7: =PRODUCT(B7*50) -> 0 | H7: =SUM(F7:G7) -> 0
A8: PINUS | B8: 330 | C8: 5900 | E8: =PRODUCT(B8*C8) -> 1947000 | F8: =PRODUCT(E8*18)/118 -> 297000 | G8: =PRODUCT(B8*50) -> 16500 | H8: =SUM(F8:G8) -> 313500
A9: MADIRIYE NINI | E9: =PRODUCT(B9*C9) -> 0 | F9: =PRODUCT(E9*18)/118 -> 0 | G9: =PRODUCT(B9*30) -> 0 | H9: =SUM(F9:G9) -> 0
A10: MADIRIYE NTOYA | B10: 10695 | C10: 2124 | E10: =PRODUCT(B10*C10) -> 22716180 | F10: =PRODUCT(E10*18)/118 -> 3465180 | G10: =PRODUCT(B10*30) -> 320850 | H10: =SUM(F10:G10) -> 3786030
A11: MADRIEN | E11: =PRODUCT(B11*C11) -> 0 | F11: =PRODUCT(E11*18)/118 -> 0 | G11: =PRODUCT(B11*30) -> 0 | H11: =SUM(F11:G11) -> 0
A12: MADRIEN | E12: =PRODUCT(B12*C12) -> 0 | F12: =PRODUCT(E12*18)/118 -> 0 | G12: =PRODUCT(B12*30) -> 0 | H12: =SUM(F12:G12) -> 0
A13: PLANCHE | B13: 400 | C13: 1357 | E13: =PRODUCT(B13*C13) -> 542800 | F13: =PRODUCT(E13*18)/118 -> 82800 | G13: =PRODUCT(B13*20) -> 8000 | H13: =SUM(F13:G13) -> 90800
A14: PLANCHE | E14: =PRODUCT(B14*C14) -> 0 | F14: =PRODUCT(E14*18)/118 -> 0 | G14: =PRODUCT(B14*20) -> 0 | H14: =SUM(F14:G14) -> 0
A15: Other Timber for Difference Price
A16: NAME OF TIMBER | B16: No OF TIMBER | C16: P/U | D16: MSF | E16: TOTAL COST | F16: VAT | G16: MSF | H16: VTA+MST
A17: IBIPANDE | B17: 50 | C17: 1180 | D17: 30 | E17: =PRODUCT(B17*C17) -> 59000 | F17: =PRODUCT(E17*18)/118 -> 9000 | G17: =PRODUCT(B17*D17) -> 1500 | H17: =SUM(F17:G17) -> 10500
A18: IBIPANDE | B18: 331 | D18: 210 | E18: =PRODUCT(B18*C18) -> 0 | F18: =PRODUCT(E18*18)/118 -> 0 | G18: =PRODUCT(B18*D18) -> 69510 | H18: =SUM(F18:G18) -> 69510
A19: PINUS | B19: 793 | D19: 50 | E19: =PRODUCT(B19*C19) -> 0 | F19: =PRODUCT(E19*18)/118 -> 0 | G19: =PRODUCT(B19*D19) -> 39650 | H19: =SUM(F19:G19) -> 39650
A20: UMUSAVE | E20: =PRODUCT(B20*C20) -> 0 | F20: =PRODUCT(E20*18)/118 -> 0 | G20: =PRODUCT(B20*D20) -> 0 | H20: =SUM(F20:G20) -> 0
A21: OTHER | E21: =PRODUCT(B21*C21) -> 0 | F21: =PRODUCT(E21*18)/118 -> 0 | G21: =PRODUCT(B21*D21) -> 0 | H21: =SUM(F21:G21) -> 0
A22: OTHER | E22: =PRODUCT(B22*C22) -> 0 | F22: =PRODUCT(E22*18)/118 -> 0 | G22: =PRODUCT(B22*D22) -> 0 | H22: =SUM(F22:G22) -> 0
A23: OTHER | E23: =PRODUCT(B23*C23) -> 0 | F23: =PRODUCT(E23*18)/118 -> 0 | G23: =PRODUCT(B23*D23) -> 0 | H23: =SUM(F23:G23) -> 0
A24: OTHER | E24: =PRODUCT(B24*C24) -> 0 | F24: =PRODUCT(E24*18)/118 -> 0 | G24: =PRODUCT(B24*D24) -> 0 | H24: =SUM(F24:G24) -> 0
A25: OTHER | E25: =PRODUCT(B25*C25) -> 0 | F25: =PRODUCT(E25*18)/118 -> 0 | G25: =PRODUCT(B25*D25) -> 0 | H25: =SUM(F25:G25) -> 0
A26: OTHER | E26: =PRODUCT(B26*C26) -> 0 | F26: =PRODUCT(E26*18)/118 -> 0 | G26: =PRODUCT(B26*D26) -> 0 | H26: =SUM(F26:G26) -> 0
A27: OTHER | E27: =PRODUCT(B27*C27) -> 0 | F27: =PRODUCT(E27*18)/118 -> 0 | G27: =PRODUCT(B27*D27) -> 0 | H27: =SUM(F27:G27) -> 0
A28: OTHER | E28: =PRODUCT(B28*C28) -> 0 | F28: =PRODUCT(E28*18)/118 -> 0 | G28: =PRODUCT(B28*D28) -> 0 | H28: =SUM(F28:G28) -> 0
A29: OTHER | E29: =PRODUCT(B29*C29) -> 0 | F29: =PRODUCT(E29*18)/118 -> 0 | G29: =PRODUCT(B29*D29) -> 0 | H29: =SUM(F29:G29) -> 0
A30: OTHER | E30: =PRODUCT(B30*C30) -> 0 | F30: =PRODUCT(E30*18)/118 -> 0 | G30: =PRODUCT(B30*D30) -> 0 | H30: =SUM(F30:G30) -> 0
A31: OTHER | E31: =PRODUCT(B31*C31) -> 0 | F31: =PRODUCT(E31*18)/118 -> 0 | G31: =PRODUCT(B31*D31) -> 0 | H31: =SUM(F31:G31) -> 0
... A34: OTHER | E34: =PRODUCT(B34*C34) -> 0 | F34: =PRODUCT(E34*18)/118 -> 0 | G34: =PRODUCT(B34*D34) -> 0 | H34: =SUM(F34:G34) -> 0
A35: OTHER | D35: 30 | E35: =PRODUCT(B35*C35) -> 0 | F35: =PRODUCT(E35*18)/118 -> 0 | G35: =PRODUCT(B35*D35) -> 0 | H35: =SUM(F35:G35) -> 0
A36: OTHER | E36: =PRODUCT(B36*C36) -> 0 | F36: =PRODUCT(E36*18)/118 -> 0 | G36: =PRODUCT(B36*D36) -> 0 | H36: =SUM(F36:G36) -> 0
A37: TOTALY | E37: =SUM(E5:E36) -> 25264980 | F37: =SUM(F5:F36) -> 3853980 | G37: =SUM(G5:G36) -> 456010 | H37: =SUM(H5:H36) -> 4309990
A38: SUMMARY | C38: RWF | E38: NAME | G38: Phone | H38: RWF
A39: TOTAL RWF PAID ON MOMO PAY | C39: 4309990
A40: TOTAL RWF PAID ON CASH
A41: AMOUNT NOT INVOICED
A42: TOTAL RWF DEPPOSITED ON BANK
A43: MEMBERSHIP FEES REGISTRETION
A44: MEMBERSHIP FEES CONTRIBUTION
A45: TOTAL INCOME | C45: =SUM(C39+C40+C41+C42+C43+C44) -> 4309990
A46: TIMBER SUMMARY
A48: REPORT SUMMARY | C48: TIMBER TYPE | E48: NUMBER OF QUANTITY
C49: INTURUSU | E49: =SUM(B9:B12) -> 10695
C50: PINUS | E50: =SUM(B6:B8) -> 330
C51: PALNCHE | E51: =SUM(B13:B14) -> 400
C52: IBIPANDE | E52: =SUM(B17:B18) -> 381
C53: UMUSAVE | E53: =SUM(B19:B20) -> 793
C54: OTHER | E54: =B29 -> 0
C55: OTHER | E55: =B30 -> 0
C56: OTHER | E56: =B31 -> 0
C57: OTHER | E57: =B32 -> 0
C58: OTHER | E58: =B33 -> 0
C59: OTHER | E59: =B34 -> 0
C60: OTHER | E60: =B35 -> 0
C61: OTHER | E61: =B36 -> 0
C62: TOTAL TIMBER | E62: =SUM(E49:H61) -> 12599

Sheet KIMIRONKO
A1: QUANTITY&FINACHIAL REPORT
A3: WEEK REPORT FROM APRIL 2026
A5: NAME OF TIMBER | B5: No OF TIMBER | C5: PRICE OF TIMBER | E5: TOTAL COST | F5: TVA | G5: MSF | H5: TVA+MSF
A6: PINUS NINI | E6: =PRODUCT(B6*C6) -> 0 | F6: =PRODUCT(E6*18)/118 -> 0 | G6: =PRODUCT(B6*50) -> 0 | H6: =SUM(F6:G6) -> 0
A7: PINUS NTOYA | E7: =PRODUCT(B7*C7) -> 0 | F7: =PRODUCT(E7*18)/118 -> 0 | G7: =PRODUCT(B7*50) -> 0 | H7: =SUM(F7:G7) -> 0
A8: PINUS | B8: 230 | C8: 7670 | E8: =PRODUCT(B8*C8) -> 1764100 | F8: =PRODUCT(E8*18)/118 -> 269100 | G8: =PRODUCT(B8*50) -> 11500 | H8: =SUM(F8:G8) -> 280600
A9: MADIRIYE NINI | B9: 930 | C9: 3000 | E9: =PRODUCT(B9*C9) -> 2790000 | F9: =PRODUCT(E9*18)/118 -> 425593.22 | G9: =PRODUCT(B9*30) -> 27900 | H9: =SUM(F9:G9) -> 453493.22
A10: MADIRIYE NTOYA | B10: 20314 | C10: 2124 | E10: =PRODUCT(B10*C10) -> 43146936 | F10: =PRODUCT(E10*18)/118 -> 6581736 | G10: =PRODUCT(B10*30) -> 609420 | H10: =SUM(F10:G10) -> 7191156
A11: MADRIEN | E11: =PRODUCT(B11*C11) -> 0 | F11: =PRODUCT(E11*18)/118 -> 0 | G11: =PRODUCT(B11*30) -> 0 | H11: =SUM(F11:G11) -> 0
A12: MADRIEN | C12: 2124 | E12: =PRODUCT(B12*C12) -> 0 | F12: =PRODUCT(E12*18)/118 -> 0 | G12: =PRODUCT(B12*30) -> 0 | H12: =SUM(F12:G12) -> 0
A13: PLANCHE | B13: 1900 | C13: 1357 | E13: =PRODUCT(B13*C13) -> 2578300 | F13: =PRODUCT(E13*18)/118 -> 393300 | G13: =PRODUCT(B13*20) -> 38000 | H13: =SUM(F13:G13) -> 431300
A14: PLANCHE | E14: =PRODUCT(B14*C14) -> 0 | F14: =PRODUCT(E14*18)/118 -> 0 | G14: =PRODUCT(B14*20) -> 0 | H14: =SUM(F14:G14) -> 0
A15: Other Timber for Difference Price
A16: NAME OF TIMBER | B16: No OF TIMBER | C16: P/U | D16: MSF | E16: TOTAL COST | F16: VAT | G16: MSF | H16: VTA+MST
A17: IBIPANDE | E17: =PRODUCT(B17*C17) -> 0 | F17: =PRODUCT(E17*18)/118 -> 0 | G17: =PRODUCT(B17*D17) -> 0 | H17: =SUM(F17:G17) -> 0
A18: IBIPANDE | E18: =PRODUCT(B18*C18) -> 0 | F18: =PRODUCT(E18*18)/118 -> 0 | G18: =PRODUCT(B18*D18) -> 0 | H18: =SUM(F18:G18) -> 0
A19: UMUSAVE | E19: =PRODUCT(B19*C19) -> 0 | F19: =PRODUCT(E19*18)/118 -> 0 | G19: =PRODUCT(B19*D19) -> 0 | H19: =SUM(F19:G19) -> 0
A20: UMUSAVE | E20: =PRODUCT(B20*C20) -> 0 | F20: =PRODUCT(E20*18)/118 -> 0 | G20: =PRODUCT(B20*D20) -> 0 | H20: =SUM(F20:G20) -> 0
A21: OTHER | E21: =PRODUCT(B21*C21) -> 0 | F21: =PRODUCT(E21*18)/118 -> 0 | G21: =PRODUCT(B21*D21) -> 0 | H21: =SUM(F21:G21) -> 0
A22: OTHER | E22: =PRODUCT(B22*C22) -> 0 | F22: =PRODUCT(E22*18)/118 -> 0 | G22: =PRODUCT(B22*D22) -> 0 | H22: =SUM(F22:G22) -> 0
A23: OTHER | E23: =PRODUCT(B23*C23) -> 0 | F23: =PRODUCT(E23*18)/118 -> 0 | G23: =PRODUCT(B23*D23) -> 0 | H23: =SUM(F23:G23) -> 0
A24: OTHER | E24: =PRODUCT(B24*C24) -> 0 | F24: =PRODUCT(E24*18)/118 -> 0 | G24: =PRODUCT(B24*D24) -> 0 | H24: =SUM(F24:G24) -> 0
A25: OTHER | E25: =PRODUCT(B25*C25) -> 0 | F25: =PRODUCT(E25*18)/118 -> 0 | G25: =PRODUCT(B25*D25) -> 0 | H25: =SUM(F25:G25) -> 0
A26: OTHER | E26: =PRODUCT(B26*C26) -> 0 | F26: =PRODUCT(E26*18)/118 -> 0 | G26: =PRODUCT(B26*D26) -> 0 | H26: =SUM(F26:G26) -> 0
A27: OTHER | E27: =PRODUCT(B27*C27) -> 0 | F27: =PRODUCT(E27*18)/118 -> 0 | G27: =PRODUCT(B27*D27) -> 0 | H27: =SUM(F27:G27) -> 0
A28: OTHER | E28: =PRODUCT(B28*C28) -> 0 | F28: =PRODUCT(E28*18)/118 -> 0 | G28: =PRODUCT(B28*D28) -> 0 | H28: =SUM(F28:G28) -> 0
... A36: OTHER | E36: =PRODUCT(B36*C36) -> 0 | F36: =PRODUCT(E36*18)/118 -> 0 | G36: =PRODUCT(B36*D36) -> 0 | H36: =SUM(F36:G36) -> 0
A37: TOTALY | E37: =SUM(E5:E36) -> 50279336 | F37: =SUM(F5:F36) -> 7669729.2 | G37: =SUM(G5:G36) -> 686820 | H37: =SUM(H5:H36) -> 8356549.2
A38: SUMMARY | C38: RWF | E38: NAME | G38: Phone | H38: RWF
A39: TOTAL RWF PAID ON MOMO PAY
A40: TOTAL RWF PAID ON CASH
A41: AMOUNT NOT INVOICED
A42: TOTAL RWF DEPPOSITED ON BANK
A43: MEMBERSHIP FEES REGISTRETION
A44: MEMBERSHIP FEES CONTRIBUTION
A45: TOTAL INCOME | C45: =SUM(C39+C40+C41+C42+C43+C44) -> 0
A46: TIMBER SUMMARY
A48: REPORT SUMMARY | C48: TIMBER TYPE | E48: NUMBER OF QUANTITY
C49: INTURUSU | E49: =SUM(B9:B12) -> 21244
C50: PINUS | E50: =SUM(B6:B8) -> 230
C51: PALNCHE | E51: =SUM(B13:B14) -> 1900
C52: IBIPANDE | E52: =SUM(B17:B18) -> 0
C53: UMUSAVE | E53: =SUM(B19:B20) -> 0
C54: OTHER | E54: =B29 -> 0
C55: OTHER | E55: =B30 -> 0
C56: OTHER | E56: =B31 -> 0
C57: OTHER | E57: =B32 -> 0
C58: OTHER | E58: =B33 -> 0
C59: OTHER | E59: =B34 -> 0
C60: OTHER | E60: =B35 -> 0
C61: OTHER | E61: =B36 -> 0
C62: TOTAL TIMBER | E62: =SUM(E49:H61) -> 23374

Sheet GAHANGA
A1: QUANTITY REPORT
A3: MONTHS REPORT OF APRIL 2026
A5: NAME OF TIMBER | B5: No OF TIMBER | C5: PRICE OF TIMBER | E5: TOTAL COST | F5: TVA | G5: MSF | H5: TVA+MSF
A6: PINUS NINI | E6: =PRODUCT(B6*C6) -> 0 | F6: =PRODUCT(E6*18)/118 -> 0 | G6: =PRODUCT(B6*50) -> 0 | H6: =SUM(F6:G6) -> 0
A7: PINUS NTOYA | B7: 625 | C7: 7670 | E7: =PRODUCT(B7*C7) -> 4793750 | F7: =PRODUCT(E7*18)/118 -> 731250 | G7: =PRODUCT(B7*50) -> 31250 | H7: =SUM(F7:G7) -> 762500
A8: PINUS | E8: =PRODUCT(B8*C8) -> 0 | F8: =PRODUCT(E8*18)/118 -> 0 | G8: =PRODUCT(B8*50) -> 0 | H8: =SUM(F8:G8) -> 0
A9: MADIRIYE NINI | B9: 200 | C9: 3500 | E9: =PRODUCT(B9*C9) -> 700000 | F9: =PRODUCT(E9*18)/118 -> 106779.66 | G9: =PRODUCT(B9*30) -> 6000 | H9: =SUM(F9:G9) -> 112779.66
A10: MADIRIYE NTOYA | B10: 24773 | C10: 2124 | E10: =PRODUCT(B10*C10) -> 52617852 | F10: =PRODUCT(E10*18)/118 -> 8026452 | G10: =PRODUCT(B10*30) -> 743190 | H10: =SUM(F10:G10) -> 8769642
A11: MADRIEN | E11: =PRODUCT(B11*C11) -> 0 | F11: =PRODUCT(E11*18)/118 -> 0 | G11: =PRODUCT(B11*30) -> 0 | H11: =SUM(F11:G11) -> 0
A12: MADRIEN | E12: =PRODUCT(B12*C12) -> 0 | F12: =PRODUCT(E12*18)/118 -> 0 | G12: =PRODUCT(B12*30) -> 0 | H12: =SUM(F12:G12) -> 0
A13: PLANCHE | B13: 900 | C13: 1357 | E13: =PRODUCT(B13*C13) -> 1221300 | F13: =PRODUCT(E13*18)/118 -> 186300 | G13: =PRODUCT(B13*20) -> 18000 | H13: =SUM(F13:G13) -> 204300
A14: PLANCHE | E14: =PRODUCT(B14*C14) -> 0 | F14: =PRODUCT(E14*18)/118 -> 0 | G14: =PRODUCT(B14*20) -> 0 | H14: =SUM(F14:G14) -> 0
A15: Other Timber for Difference Price
A16: NAME OF TIMBER | B16: No OF TIMBER | C16: P/U | D16: MSF | E16: TOTAL COST | F16: VAT | G16: MSF | H16: VTA+MST
A17: IBIPANDE | D17: 30 | E17: =PRODUCT(B17*C17) -> 0 | F17: =PRODUCT(E17*18)/118 -> 0 | G17: =PRODUCT(B17*D17) -> 0 | H17: =SUM(F17:G17) -> 0
A18: IBIPANDE | E18: =PRODUCT(B18*C18) -> 0 | F18: =PRODUCT(E18*18)/118 -> 0 | G18: =PRODUCT(B18*D18) -> 0 | H18: =SUM(F18:G18) -> 0
A19: UMUSAVE | E19: =PRODUCT(B19*C19) -> 0 | F19: =PRODUCT(E19*18)/118 -> 0 | G19: =PRODUCT(B19*D19) -> 0 | H19: =SUM(F19:G19) -> 0
A20: UMUSAVE | E20: =PRODUCT(B20*C20) -> 0 | F20: =PRODUCT(E20*18)/118 -> 0 | G20: =PRODUCT(B20*D20) -> 0 | H20: =SUM(F20:G20) -> 0
A21: OTHER | E21: =PRODUCT(B21*C21) -> 0 | F21: =PRODUCT(E21*18)/118 -> 0 | G21: =PRODUCT(B21*D21) -> 0 | H21: =SUM(F21:G21) -> 0
A22: OTHER | E22: =PRODUCT(B22*C22) -> 0 | F22: =PRODUCT(E22*18)/118 -> 0 | G22: =PRODUCT(B22*D22) -> 0 | H22: =SUM(F22:G22) -> 0
A23: OTHER | E23: =PRODUCT(B23*C23) -> 0 | F23: =PRODUCT(E23*18)/118 -> 0 | G23: =PRODUCT(B23*D23) -> 0 | H23: =SUM(F23:G23) -> 0
A24: OTHER | E24: =PRODUCT(B24*C24) -> 0 | F24: =PRODUCT(E24*18)/118 -> 0 | G24: =PRODUCT(B24*D24) -> 0 | H24: =SUM(F24:G24) -> 0
A25: OTHER | E25: =PRODUCT(B25*C25) -> 0 | F25: =PRODUCT(E25*18)/118 -> 0 | G25: =PRODUCT(B25*D25) -> 0 | H25: =SUM(F25:G25) -> 0
A26: OTHER | E26: =PRODUCT(B26*C26) -> 0 | F26: =PRODUCT(E26*18)/118 -> 0 | G26: =PRODUCT(B26*D26) -> 0 | H26: =SUM(F26:G26) -> 0
A27: OTHER | E27: =PRODUCT(B27*C27) -> 0 | F27: =PRODUCT(E27*18)/118 -> 0 | G27: =PRODUCT(B27*D27) -> 0 | H27: =SUM(F27:G27) -> 0
A28: OTHER | E28: =PRODUCT(B28*C28) -> 0 | F28: =PRODUCT(E28*18)/118 -> 0 | G28: =PRODUCT(B28*D28) -> 0 | H28: =SUM(F28:G28) -> 0
A29: OTHER | E29: =PRODUCT(B29*C29) -> 0 | F29: =PRODUCT(E29*18)/118 -> 0 | G29: =PRODUCT(B29*D29) -> 0 | H29: =SUM(F29:G29) -> 0
... A34: OTHER | E34: =PRODUCT(B34*C34) -> 0 | F34: =PRODUCT(E34*18)/118 -> 0 | G34: =PRODUCT(B34*D34) -> 0 | H34: =SUM(F34:G34) -> 0
A35: OTHER | D35: 30 | E35: =PRODUCT(B35*C35) -> 0 | F35: =PRODUCT(E35*18)/118 -> 0 | G35: =PRODUCT(B35*D35) -> 0 | H35: =SUM(F35:G35) -> 0
A36: OTHER | E36: =PRODUCT(B36*C36) -> 0 | F36: =PRODUCT(E36*18)/118 -> 0 | G36: =PRODUCT(B36*D36) -> 0 | H36: =SUM(F36:G36) -> 0
A37: TOTALY | E37: =SUM(E5:E36) -> 59332902 | F37: =SUM(F5:F36) -> 9050781.7 | G37: =SUM(G5:G36) -> 798440 | H37: =SUM(H5:H36) -> 9849221.7
A38: SUMMARY | C38: RWF | E38: NAME | G38: Phone | H38: RWF
A39: TOTAL RWF PAID ON MOMO PAY | C39: 9846122
A40: TOTAL RWF PAID ON CASH
A41: AMOUNT NOT INVOICED
A42: TOTAL RWF DEPPOSITED ON BANK
A43: MEMBERSHIP FEES REGISTRETION
A44: MEMBERSHIP FEES CONTRIBUTION
A45: TOTAL INCOME | C45: =SUM(C39+C40+C41+C42+C43+C44) -> 9846122
A46: TIMBER SUMMARY
A48: REPORT SUMMARY | C48: TIMBER TYPE | E48: NUMBER OF QUANTITY
C49: INTURUSU | E49: =SUM(B9:B12) -> 24973
C50: PINUS | E50: =SUM(B6:B8) -> 625
C51: PALNCHE | E51: =SUM(B13:B14) -> 900
C52: IBIPANDE | E52: =SUM(B17:B18) -> 0
C53: UMUSAVE | E53: =SUM(B19:B20) -> 0
C54: OTHER | E54: =B29 -> 0
C55: OTHER | E55: =B30 -> 0
C56: OTHER | E56: =B31 -> 0
C57: OTHER | E57: =B32 -> 0
C58: OTHER | E58: =B33 -> 0
C59: OTHER | E59: =B34 -> 0
C60: OTHER | E60: =B35 -> 0
C61: OTHER | E61: =B36 -> 0
C62: TOTAL TIMBER | E62: =SUM(E49:H61) -> 26498

Sheet BUGESERA
A1: QUANTITY REPORT
A3: MONTHS REPORT OF APRIL 2026
A5: NAME OF TIMBER | B5: No OF TIMBER | C5: PRICE OF TIMBER | E5: TOTAL COST | F5: TVA | G5: MSF | H5: TVA+MSF
A6: PINUS NINI | C6: 7670 | E6: =PRODUCT(B6*C6) -> 0 | F6: =PRODUCT(E6*18)/118 -> 0 | G6: =PRODUCT(B6*50) -> 0 | H6: =SUM(F6:G6) -> 0
A7: PINUS NTOYA | B7: 83 | C7: 4720 | E7: =PRODUCT(B7*C7) -> 391760 | F7: =PRODUCT(E7*18)/118 -> 59760 | G7: =PRODUCT(B7*50) -> 4150 | H7: =SUM(F7:G7) -> 63910
A8: PINUS | E8: =PRODUCT(B8*C8) -> 0 | F8: =PRODUCT(E8*18)/118 -> 0 | G8: =PRODUCT(B8*50) -> 0 | H8: =SUM(F8:G8) -> 0
A9: MADIRIYE NINI | E9: =PRODUCT(B9*C9) -> 0 | F9: =PRODUCT(E9*18)/118 -> 0 | G9: =PRODUCT(B9*30) -> 0 | H9: =SUM(F9:G9) -> 0
A10: MADIRIYE NTOYA | B10: 35561 | C10: 2124 | E10: =PRODUCT(B10*C10) -> 75531564 | F10: =PRODUCT(E10*18)/118 -> 11521764 | G10: =PRODUCT(B10*30) -> 1066830 | H10: =SUM(F10:G10) -> 12588594
A11: MADRIEN | E11: =PRODUCT(B11*C11) -> 0 | F11: =PRODUCT(E11*18)/118 -> 0 | G11: =PRODUCT(B11*30) -> 0 | H11: =SUM(F11:G11) -> 0
A12: MADRIEN | E12: =PRODUCT(B12*C12) -> 0 | F12: =PRODUCT(E12*18)/118 -> 0 | G12: =PRODUCT(B12*30) -> 0 | H12: =SUM(F12:G12) -> 0
A13: PLANCHE | B13: 4997 | C13: 1357 | E13: =PRODUCT(B13*C13) -> 6780929 | F13: =PRODUCT(E13*18)/118 -> 1034379 | G13: =PRODUCT(B13*20) -> 99940 | H13: =SUM(F13:G13) -> 1134319
A14: PLANCHE | E14: =PRODUCT(B14*C14) -> 0 | F14: =PRODUCT(E14*18)/118 -> 0 | G14: =PRODUCT(B14*20) -> 0 | H14: =SUM(F14:G14) -> 0
A15: Other Timber for Difference Price
A16: NAME OF TIMBER | B16: No OF TIMBER | C16: P/U | D16: MSF | E16: TOTAL COST | F16: VAT | G16: MSF | H16: VTA+MST
A17: IBIPANDE | C17: 2006 | D17: 25 | E17: =PRODUCT(B17*C17) -> 0 | F17: =PRODUCT(E17*18)/118 -> 0 | G17: =PRODUCT(B17*D17) -> 0 | H17: =SUM(F17:G17) -> 0
A18: INTURUSU NINI | B18: 540 | C18: 3304 | D18: 40 | E18: =PRODUCT(B18*C18) -> 1784160 | F18: =PRODUCT(E18*18)/118 -> 272160 | G18: =PRODUCT(B18*D18) -> 21600 | H18: =SUM(F18:G18) -> 293760
A19: UMUSAVE | C19: 2360 | D19: 30 | E19: =PRODUCT(B19*C19) -> 0 | F19: =PRODUCT(E19*18)/118 -> 0 | G19: =PRODUCT(B19*D19) -> 0 | H19: =SUM(F19:G19) -> 0
A20: UMUSAVE | E20: =PRODUCT(B20*C20) -> 0 | F20: =PRODUCT(E20*18)/118 -> 0 | G20: =PRODUCT(B20*D20) -> 0 | H20: =SUM(F20:G20) -> 0
A21: OTHER | E21: =PRODUCT(B21*C21) -> 0 | F21: =PRODUCT(E21*18)/118 -> 0 | G21: =PRODUCT(B21*D21) -> 0 | H21: =SUM(F21:G21) -> 0
A22: OTHER | E22: =PRODUCT(B22*C22) -> 0 | F22: =PRODUCT(E22*18)/118 -> 0 | G22: =PRODUCT(B22*D22) -> 0 | H22: =SUM(F22:G22) -> 0
A23: OTHER | E23: =PRODUCT(B23*C23) -> 0 | F23: =PRODUCT(E23*18)/118 -> 0 | G23: =PRODUCT(B23*D23) -> 0 | H23: =SUM(F23:G23) -> 0
A24: OTHER | E24: =PRODUCT(B24*C24) -> 0 | F24: =PRODUCT(E24*18)/118 -> 0 | G24: =PRODUCT(B24*D24) -> 0 | H24: =SUM(F24:G24) -> 0
A25: OTHER | E25: =PRODUCT(B25*C25) -> 0 | F25: =PRODUCT(E25*18)/118 -> 0 | G25: =PRODUCT(B25*D25) -> 0 | H25: =SUM(F25:G25) -> 0
A26: OTHER | E26: =PRODUCT(B26*C26) -> 0 | F26: =PRODUCT(E26*18)/118 -> 0 | G26: =PRODUCT(B26*D26) -> 0 | H26: =SUM(F26:G26) -> 0
A27: OTHER | E27: =PRODUCT(B27*C27) -> 0 | F27: =PRODUCT(E27*18)/118 -> 0 | G27: =PRODUCT(B27*D27) -> 0 | H27: =SUM(F27:G27) -> 0
A28: OTHER | E28: =PRODUCT(B28*C28) -> 0 | F28: =PRODUCT(E28*18)/118 -> 0 | G28: =PRODUCT(B28*D28) -> 0 | H28: =SUM(F28:G28) -> 0
A29: OTHER | E29: =PRODUCT(B29*C29) -> 0 | F29: =PRODUCT(E29*18)/118 -> 0 | G29: =PRODUCT(B29*D29) -> 0 | H29: =SUM(F29:G29) -> 0
A30: OTHER | E30: =PRODUCT(B30*C30) -> 0 | F30: =PRODUCT(E30*18)/118 -> 0 | G30: =PRODUCT(B30*D30) -> 0 | H30: =SUM(F30:G30) -> 0
A31: OTHER | E31: =PRODUCT(B31*C31) -> 0 | F31: =PRODUCT(E31*18)/118 -> 0 | G31: =PRODUCT(B31*D31) -> 0 | H31: =SUM(F31:G31) -> 0
... A36: OTHER | E36: =PRODUCT(B36*C36) -> 0 | F36: =PRODUCT(E36*18)/118 -> 0 | G36: =PRODUCT(B36*D36) -> 0 | H36: =SUM(F36:G36) -> 0
A37: TOTALY | E37: =SUM(E5:E36) -> 84488413 | F37: =SUM(F5:F36) -> 12888063 | G37: =SUM(G5:G36) -> 1192520 | H37: =SUM(H5:H36) -> 14080583
A38: SUMMARY | C38: RWF | E38: NAME | G38: Phone | H38: RWF
A39: TOTAL RWF PAID ON MOMO PAY | C39: 13878073
A40: TOTAL RWF PAID ON CASH | C40: 202510
A41: AMOUNT NOT INVOICED
A42: TOTAL RWF DEPPOSITED ON BANK
A43: MEMBERSHIP FEES REGISTRETION
A44: MEMBERSHIP FEES CONTRIBUTION
A45: TOTAL INCOME | C45: =SUM(C39+C40+C41+C42+C43+C44) -> 14080583
A46: TIMBER SUMMARY
A48: REPORT SUMMARY | C48: TIMBER TYPE | E48: NUMBER OF QUANTITY
C49: INTURUSU | E49: =SUM(B9:B12) -> 35561
C50: PINUS | E50: =SUM(B6:B8) -> 83
C51: PALNCHE | E51: =SUM(B13:B14) -> 4997
C52: IBIPANDE | E52: =SUM(B17:B18) -> 540
C53: UMUSAVE | E53: =SUM(B19:B20) -> 0
C54: OTHER | E54: =B29 -> 0
C55: OTHER | E55: =B30 -> 0
C56: OTHER | E56: =B31 -> 0
C57: OTHER | E57: =B32 -> 0
C58: OTHER | E58: =B33 -> 0
C59: OTHER | E59: =B34 -> 0
C60: OTHER | E60: =B35 -> 0
C61: OTHER | E61: =B36 -> 0
C62: TOTAL TIMBER | E62: =SUM(E49:H61) -> 41181

Sheet NYARUGENGE
A1: QUANTITY REPORT
A3: MONTHS REPORT OF APRIL 2026
A5: NAME OF TIMBER | B5: No OF TIMBER | C5: PRICE OF TIMBER | E5: TOTAL COST | F5: TVA | G5: MSF | H5: TVA+MSF
A6: PINUS NINI | E6: =PRODUCT(B6*C6) -> 0 | F6: =PRODUCT(E6*18)/118 -> 0 | G6: =PRODUCT(B6*50) -> 0 | H6: =SUM(F6:G6) -> 0
A7: PINUS NTOYA | B7: 170 | C7: 7670 | E7: =PRODUCT(B7*C7) -> 1303900 | F7: =PRODUCT(E7*18)/118 -> 198900 | G7: =PRODUCT(B7*50) -> 8500 | H7: =SUM(F7:G7) -> 207400
A8: PINUS | E8: =PRODUCT(B8*C8) -> 0 | F8: =PRODUCT(E8*18)/118 -> 0 | G8: =PRODUCT(B8*50) -> 0 | H8: =SUM(F8:G8) -> 0
A9: MADIRIYE NINI | E9: =PRODUCT(B9*C9) -> 0 | F9: =PRODUCT(E9*18)/118 -> 0 | G9: =PRODUCT(B9*30) -> 0 | H9: =SUM(F9:G9) -> 0
A10: MADIRIYE NTOYA | B10: 13717 | C10: 2124 | E10: =PRODUCT(B10*C10) -> 29134908 | F10: =PRODUCT(E10*18)/118 -> 4444308 | G10: =PRODUCT(B10*30) -> 411510 | H10: =SUM(F10:G10) -> 4855818
A11: MADRIEN | E11: =PRODUCT(B11*C11) -> 0 | F11: =PRODUCT(E11*18)/118 -> 0 | G11: =PRODUCT(B11*30) -> 0 | H11: =SUM(F11:G11) -> 0
A12: MADRIEN | E12: =PRODUCT(B12*C12) -> 0 | F12: =PRODUCT(E12*18)/118 -> 0 | G12: =PRODUCT(B12*30) -> 0 | H12: =SUM(F12:G12) -> 0
A13: PLANCHE | B13: 950 | C13: 1357 | E13: =PRODUCT(B13*C13) -> 1289150 | F13: =PRODUCT(E13*18)/118 -> 196650 | G13: =PRODUCT(B13*20) -> 19000 | H13: =SUM(F13:G13) -> 215650
A14: PLANCHE | E14: =PRODUCT(B14*C14) -> 0 | F14: =PRODUCT(E14*18)/118 -> 0 | G14: =PRODUCT(B14*20) -> 0 | H14: =SUM(F14:G14) -> 0
A15: Other Timber for Difference Price
A16: NAME OF TIMBER | B16: No OF TIMBER | C16: P/U | D16: MSF | E16: TOTAL COST | F16: VAT | G16: MSF | H16: VTA+MST
A17: IBIPANDE | E17: =PRODUCT(B17*C17) -> 0 | F17: =PRODUCT(E17*18)/118 -> 0 | G17: =PRODUCT(B17*D17) -> 0 | H17: =SUM(F17:G17) -> 0
A18: IBIPANDE | E18: =PRODUCT(B18*C18) -> 0 | F18: =PRODUCT(E18*18)/118 -> 0 | G18: =PRODUCT(B18*D18) -> 0 | H18: =SUM(F18:G18) -> 0
A19: UMUSAVE | E19: =PRODUCT(B19*C19) -> 0 | F19: =PRODUCT(E19*18)/118 -> 0 | G19: =PRODUCT(B19*D19) -> 0 | H19: =SUM(F19:G19) -> 0
A20: UMUSAVE | E20: =PRODUCT(B20*C20) -> 0 | F20: =PRODUCT(E20*18)/118 -> 0 | G20: =PRODUCT(B20*D20) -> 0 | H20: =SUM(F20:G20) -> 0
A21: OTHER | E21: =PRODUCT(B21*C21) -> 0 | F21: =PRODUCT(E21*18)/118 -> 0 | G21: =PRODUCT(B21*D21) -> 0 | H21: =SUM(F21:G21) -> 0
A22: OTHER | E22: =PRODUCT(B22*C22) -> 0 | F22: =PRODUCT(E22*18)/118 -> 0 | G22: =PRODUCT(B22*D22) -> 0 | H22: =SUM(F22:G22) -> 0
A23: OTHER | E23: =PRODUCT(B23*C23) -> 0 | F23: =PRODUCT(E23*18)/118 -> 0 | G23: =PRODUCT(B23*D23) -> 0 | H23: =SUM(F23:G23) -> 0
A24: OTHER | E24: =PRODUCT(B24*C24) -> 0 | F24: =PRODUCT(E24*18)/118 -> 0 | G24: =PRODUCT(B24*D24) -> 0 | H24: =SUM(F24:G24) -> 0
A25: OTHER | E25: =PRODUCT(B25*C25) -> 0 | F25: =PRODUCT(E25*18)/118 -> 0 | G25: =PRODUCT(B25*D25) -> 0 | H25: =SUM(F25:G25) -> 0
A26: OTHER | E26: =PRODUCT(B26*C26) -> 0 | F26: =PRODUCT(E26*18)/118 -> 0 | G26: =PRODUCT(B26*D26) -> 0 | H26: =SUM(F26:G26) -> 0
A27: OTHER | E27: =PRODUCT(B27*C27) -> 0 | F27: =PRODUCT(E27*18)/118 -> 0 | G27: =PRODUCT(B27*D27) -> 0 | H27: =SUM(F27:G27) -> 0
A28: OTHER | E28: =PRODUCT(B28*C28) -> 0 | F28: =PRODUCT(E28*18)/118 -> 0 | G28: =PRODUCT(B28*D28) -> 0 | H28: =SUM(F28:G28) -> 0
... A36: OTHER | E36: =PRODUCT(B36*C36) -> 0 | F36: =PRODUCT(E36*18)/118 -> 0 | G36: =PRODUCT(B36*D36) -> 0 | H36: =SUM(F36:G36) -> 0
A37: TOTALY | E37: =SUM(E5:E36) -> 31727958 | F37: =SUM(F5:F36) -> 4839858 | G37: =SUM(G5:G36) -> 439010 | H37: =SUM(H5:H36) -> 5278868
A38: SUMMARY | C38: RWF | E38: NAME | G38: Phone | H38: RWF
A39: TOTAL RWF PAID ON MOMO PAY | C39: 5278868
A40: TOTAL RWF PAID ON CASH
A41: AMOUNT NOT INVOICED
A42: TOTAL RWF DEPPOSITED ON BANK
A43: MEMBERSHIP FEES REGISTRETION
A44: MEMBERSHIP FEES CONTRIBUTION | C44: 300000
A45: TOTAL INCOME | C45: =SUM(C39+C40+C41+C42+C43+C44) -> 5578868
A46: TIMBER SUMMARY
A48: REPORT SUMMARY | C48: TIMBER TYPE | E48: NUMBER OF QUANTITY
C49: INTURUSU | E49: =SUM(B9:B12) -> 13717
C50: PINUS | E50: =SUM(B6:B8) -> 170
C51: PALNCHE | E51: =SUM(B13:B14) -> 950
C52: IBIPANDE | E52: =SUM(B17:B18) -> 0
C53: UMUSAVE | E53: =SUM(B19:B20) -> 0
C54: OTHER | E54: =B29 -> 0
C55: OTHER | E55: =B30 -> 0
C56: OTHER | E56: =B31 -> 0
C57: OTHER | E57: =B32 -> 0
C58: OTHER | E58: =B33 -> 0
C59: OTHER | E59: =B34 -> 0
C60: OTHER | E60: =B35 -> 0
C61: OTHER | E61: =B36 -> 0
C62: TOTAL TIMBER | E62: =SUM(E49:H61) -> 14837

Sheet MUHANGA
A1: QUANTITY REPORT
A3: MONTHS REPORT OF APRIL 2026
A5: NAME OF TIMBER | B5: No OF TIMBER | C5: PRICE OF TIMBER | E5: TOTAL COST | F5: TVA | G5: MSF | H5: TVA+MSF
A6: PINUS NINI | E6: =PRODUCT(B6*C6) -> 0 | F6: =PRODUCT(E6*18)/118 -> 0 | G6: =PRODUCT(B6*50) -> 0 | H6: =SUM(F6:G6) -> 0
A7: PINUS NTOYA | E7: =PRODUCT(B7*C7) -> 0 | F7: =PRODUCT(E7*18)/118 -> 0 | G7: =PRODUCT(B7*50) -> 0 | H7: =SUM(F7:G7) -> 0
A8: IBIPANDE BYA PINUS | B8: 235 | C8: 2360 | E8: =PRODUCT(B8*C8) -> 554600 | F8: =PRODUCT(E8*18)/118 -> 84600 | G8: =PRODUCT(B8*50) -> 11750 | H8: =SUM(F8:G8) -> 96350
A9: MADIRIYE NINI | E9: =PRODUCT(B9*C9) -> 0 | F9: =PRODUCT(E9*18)/118 -> 0 | G9: =PRODUCT(B9*30) -> 0 | H9: =SUM(F9:G9) -> 0
A10: MADIRIYE NTOYA | B10: 2220 | C10: 2200 | E10: =PRODUCT(B10*C10) -> 4884000 | F10: =PRODUCT(E10*18)/118 -> 745016.95 | G10: =PRODUCT(B10*30) -> 66600 | H10: =SUM(F10:G10) -> 811616.95
A11: MADRIEN | B11: 6260 | C11: 2596 | E11: =PRODUCT(B11*C11) -> 16250960 | F11: =PRODUCT(E11*18)/118 -> 2478960 | G11: =PRODUCT(B11*30) -> 187800 | H11: =SUM(F11:G11) -> 2666760
A12: MADRIEN | B12: 1350 | C12: 2500 | E12: =PRODUCT(B12*C12) -> 3375000 | F12: =PRODUCT(E12*18)/118 -> 514830.51 | G12: =PRODUCT(B12*30) -> 40500 | H12: =SUM(F12:G12) -> 555330.51
A13: PLANCHE | E13: =PRODUCT(B13*C13) -> 0 | F13: =PRODUCT(E13*18)/118 -> 0 | G13: =PRODUCT(B13*20) -> 0 | H13: =SUM(F13:G13) -> 0
A14: PLANCHE | E14: =PRODUCT(B14*C14) -> 0 | F14: =PRODUCT(E14*18)/118 -> 0 | G14: =PRODUCT(B14*20) -> 0 | H14: =SUM(F14:G14) -> 0
A15: Other Timber for Difference Price
A16: NAME OF TIMBER | B16: No OF TIMBER | C16: P/U | D16: MSF | E16: TOTAL COST | F16: VAT | G16: MSF | H16: VTA+MST
A17: IBIPANDE | B17: 4330 | C17: 1180 | D17: 20 | E17: =PRODUCT(B17*C17) -> 5109400 | F17: =PRODUCT(E17*18)/118 -> 779400 | G17: =PRODUCT(B17*D17) -> 86600 | H17: =SUM(F17:G17) -> 866000
A18: IBIPANDE | E18: =PRODUCT(B18*C18) -> 0 | F18: =PRODUCT(E18*18)/118 -> 0 | G18: =PRODUCT(B18*D18) -> 0 | H18: =SUM(F18:G18) -> 0
A19: UMUSAVE | E19: =PRODUCT(B19*C19) -> 0 | F19: =PRODUCT(E19*18)/118 -> 0 | G19: =PRODUCT(B19*D19) -> 0 | H19: =SUM(F19:G19) -> 0
A20: UMUSAVE | E20: =PRODUCT(B20*C20) -> 0 | F20: =PRODUCT(E20*18)/118 -> 0 | G20: =PRODUCT(B20*D20) -> 0 | H20: =SUM(F20:G20) -> 0
A21: MADRIEN NINI | B21: 200 | C21: 4000 | D21: 50 | E21: =PRODUCT(B21*C21) -> 800000 | F21: =PRODUCT(E21*18)/118 -> 122033.9 | G21: =PRODUCT(B21*D21) -> 10000 | H21: =SUM(F21:G21) -> 132033.9
A22: DESCHET | C22: 10000 | D22: 2000 | E22: =PRODUCT(B22*C22) -> 0 | F22: =PRODUCT(E22*18)/118 -> 0 | G22: =PRODUCT(B22*D22) -> 0 | H22: =SUM(F22:G22) -> 0
A23: OTHER | E23: =PRODUCT(B23*C23) -> 0 | F23: =PRODUCT(E23*18)/118 -> 0 | G23: =PRODUCT(B23*D23) -> 0 | H23: =SUM(F23:G23) -> 0
A24: OTHER | E24: =PRODUCT(B24*C24) -> 0 | F24: =PRODUCT(E24*18)/118 -> 0 | G24: =PRODUCT(B24*D24) -> 0 | H24: =SUM(F24:G24) -> 0
A25: OTHER | E25: =PRODUCT(B25*C25) -> 0 | F25: =PRODUCT(E25*18)/118 -> 0 | G25: =PRODUCT(B25*D25) -> 0 | H25: =SUM(F25:G25) -> 0
A26: OTHER | E26: =PRODUCT(B26*C26) -> 0 | F26: =PRODUCT(E26*18)/118 -> 0 | G26: =PRODUCT(B26*D26) -> 0 | H26: =SUM(F26:G26) -> 0
A27: OTHER | E27: =PRODUCT(B27*C27) -> 0 | F27: =PRODUCT(E27*18)/118 -> 0 | G27: =PRODUCT(B27*D27) -> 0 | H27: =SUM(F27:G27) -> 0
A28: OTHER | E28: =PRODUCT(B28*C28) -> 0 | F28: =PRODUCT(E28*18)/118 -> 0 | G28: =PRODUCT(B28*D28) -> 0 | H28: =SUM(F28:G28) -> 0
A29: OTHER | E29: =PRODUCT(B29*C29) -> 0 | F29: =PRODUCT(E29*18)/118 -> 0 | G29: =PRODUCT(B29*D29) -> 0 | H29: =SUM(F29:G29) -> 0
A30: OTHER | E30: =PRODUCT(B30*C30) -> 0 | F30: =PRODUCT(E30*18)/118 -> 0 | G30: =PRODUCT(B30*D30) -> 0 | H30: =SUM(F30:G30) -> 0
A31: OTHER | E31: =PRODUCT(B31*C31) -> 0 | F31: =PRODUCT(E31*18)/118 -> 0 | G31: =PRODUCT(B31*D31) -> 0 | H31: =SUM(F31:G31) -> 0
A32: OTHER | E32: =PRODUCT(B32*C32) -> 0 | F32: =PRODUCT(E32*18)/118 -> 0 | G32: =PRODUCT(B32*D32) -> 0 | H32: =SUM(F32:G32) -> 0
A33: OTHER | E33: =PRODUCT(B33*C33) -> 0 | F33: =PRODUCT(E33*18)/118 -> 0 | G33: =PRODUCT(B33*D33) -> 0 | H33: =SUM(F33:G33) -> 0
A34: OTHER | E34: =PRODUCT(B34*C34) -> 0 | F34: =PRODUCT(E34*18)/118 -> 0 | G34: =PRODUCT(B34*D34) -> 0 | H34: =SUM(F34:G34) -> 0
... A36: OTHER | E36: =PRODUCT(B36*C36) -> 0 | F36: =PRODUCT(E36*18)/118 -> 0 | G36: =PRODUCT(B36*D36) -> 0 | H36: =SUM(F36:G36) -> 0
A37: TOTALY | E37: =SUM(E5:E36) -> 30973960 | F37: =SUM(F5:F36) -> 4724841.4 | G37: =SUM(G5:G36) -> 403250 | H37: =SUM(H5:H36) -> 5128091.4
A38: SUMMARY | C38: RWF | E38: NAME | G38: Phone | H38: RWF
A39: TOTAL RWF PAID ON MOMO PAY | C39: 5128091
A40: TOTAL RWF PAID ON CASH
A41: AMOUNT NOT INVOICED
A42: TOTAL RWF DEPPOSITED ON BANK
A43: MEMBERSHIP FEES REGISTRETION
A44: MEMBERSHIP FEES CONTRIBUTION
A45: TOTAL INCOME | C45: =SUM(C39+C40+C41+C42+C43+C44) -> 5128091
A46: TIMBER SUMMARY
A48: REPORT SUMMARY | C48: TIMBER TYPE | E48: NUMBER OF QUANTITY
C49: INTURUSU | E49: =SUM(B9:B12) -> 9830
C50: PINUS | E50: =SUM(B6:B8) -> 235
C51: PALNCHE | E51: =SUM(B13:B14) -> 0
C52: IBIPANDE | E52: =SUM(B17:B18) -> 4330
C53: UMUSAVE | E53: =SUM(B19:B20) -> 0
C54: OTHER | E54: =B29 -> 0
C55: OTHER | E55: =B30 -> 0
C56: OTHER | E56: =B31 -> 0
C57: OTHER | E57: =B32 -> 0
C58: OTHER | E58: =B33 -> 0
C59: OTHER | E59: =B34 -> 0
C60: OTHER | E60: =B35 -> 0
C61: OTHER | E61: =B36 -> 0
C62: TOTAL TIMBER | E62: =SUM(E49:H61) -> 14395

Sheet HUYE
A1: QUANTITY REPORT
A3: MONTHS REPORT OF APRIL 2026
A5: NAME OF TIMBER | B5: No OF TIMBER | C5: PRICE OF TIMBER | E5: TOTAL COST | F5: TVA | G5: MSF | H5: TVA+MSF
A6: PINUS NINI | C6: 9440 | E6: =PRODUCT(B6*C6) -> 0 | F6: =PRODUCT(E6*18)/118 -> 0 | G6: =PRODUCT(B6*50) -> 0 | H6: =SUM(F6:G6) -> 0
A7: PINUS NTOYA | E7: =PRODUCT(B7*C7) -> 0 | F7: =PRODUCT(E7*18)/118 -> 0 | G7: =PRODUCT(B7*50) -> 0 | H7: =SUM(F7:G7) -> 0
A8: IBIPANDE PINUS | C8: 2360 | E8: =PRODUCT(B8*C8) -> 0 | F8: =PRODUCT(E8*18)/118 -> 0 | G8: =PRODUCT(B8*50) -> 0 | H8: =SUM(F8:G8) -> 0
A9: MADIRIYE NINI | B9: 799 | C9: 4130 | E9: =PRODUCT(B9*C9) -> 3299870 | F9: =PRODUCT(E9*18)/118 -> 503370 | G9: =PRODUCT(B9*30) -> 23970 | H9: =SUM(F9:G9) -> 527340
A10: MADIRIYE NTOYA | B10: 7262 | C10: 2360 | E10: =PRODUCT(B10*C10) -> 17138320 | F10: =PRODUCT(E10*18)/118 -> 2614320 | G10: =PRODUCT(B10*30) -> 217860 | H10: =SUM(F10:G10) -> 2832180
A11: SIPURE | C11: 1180 | E11: =PRODUCT(B11*C11) -> 0 | F11: =PRODUCT(E11*18)/118 -> 0 | G11: =PRODUCT(B11*30) -> 0 | H11: =SUM(F11:G11) -> 0
A12: MADRIEN | C12: 1180 | E12: =PRODUCT(B12*C12) -> 0 | F12: =PRODUCT(E12*18)/118 -> 0 | G12: =PRODUCT(B12*30) -> 0 | H12: =SUM(F12:G12) -> 0
A13: SIPURE | B13: 2000 | C13: 1180 | E13: =PRODUCT(B13*C13) -> 2360000 | F13: =PRODUCT(E13*18)/118 -> 360000 | G13: =PRODUCT(B13*20) -> 40000 | H13: =SUM(F13:G13) -> 400000
A14: GEREVERIA | B14: 718 | C14: 1180 | E14: =PRODUCT(B14*C14) -> 847240 | F14: =PRODUCT(E14*18)/118 -> 129240 | G14: =PRODUCT(B14*20) -> 14360 | H14: =SUM(F14:G14) -> 143600
A15: Other Timber for Difference Price
A16: NAME OF TIMBER | B16: No OF TIMBER | C16: P/U | D16: MSF | E16: TOTAL COST | F16: VAT | G16: MSF | H16: VTA+MST
A17: IBIPANDE | E17: =PRODUCT(B17*C17) -> 0 | F17: =PRODUCT(E17*18)/118 -> 0 | G17: =PRODUCT(B17*D17) -> 0 | H17: =SUM(F17:G17) -> 0
A18: IBIPANDE | E18: =PRODUCT(B18*C18) -> 0 | F18: =PRODUCT(E18*18)/118 -> 0 | G18: =PRODUCT(B18*D18) -> 0 | H18: =SUM(F18:G18) -> 0
A19: UMUSAVE | E19: =PRODUCT(B19*C19) -> 0 | F19: =PRODUCT(E19*18)/118 -> 0 | G19: =PRODUCT(B19*D19) -> 0 | H19: =SUM(F19:G19) -> 0
A20: UMUSAVE | E20: =PRODUCT(B20*C20) -> 0 | F20: =PRODUCT(E20*18)/118 -> 0 | G20: =PRODUCT(B20*D20) -> 0 | H20: =SUM(F20:G20) -> 0
A21: DESCHET | B21: 31 | D21: 1000 | E21: =PRODUCT(B21*C21) -> 0 | F21: =PRODUCT(E21*18)/118 -> 0 | G21: =PRODUCT(B21*D21) -> 31000 | H21: =SUM(F21:G21) -> 31000
A22: DESCHET | B22: 60 | C22: 10000 | D22: 1500 | E22: =PRODUCT(B22*C22) -> 600000 | F22: =PRODUCT(E22*18)/118 -> 91525.424 | G22: =PRODUCT(B22*D22) -> 90000 | H22: =SUM(F22:G22) -> 181525.42
A23: OTHER | E23: =PRODUCT(B23*C23) -> 0 | F23: =PRODUCT(E23*18)/118 -> 0 | G23: =PRODUCT(B23*D23) -> 0 | H23: =SUM(F23:G23) -> 0
A24: OTHER | E24: =PRODUCT(B24*C24) -> 0 | F24: =PRODUCT(E24*18)/118 -> 0 | G24: =PRODUCT(B24*D24) -> 0 | H24: =SUM(F24:G24) -> 0
A25: OTHER | E25: =PRODUCT(B25*C25) -> 0 | F25: =PRODUCT(E25*18)/118 -> 0 | G25: =PRODUCT(B25*D25) -> 0 | H25: =SUM(F25:G25) -> 0
A26: OTHER | E26: =PRODUCT(B26*C26) -> 0 | F26: =PRODUCT(E26*18)/118 -> 0 | G26: =PRODUCT(B26*D26) -> 0 | H26: =SUM(F26:G26) -> 0
A27: OTHER | E27: =PRODUCT(B27*C27) -> 0 | F27: =PRODUCT(E27*18)/118 -> 0 | G27: =PRODUCT(B27*D27) -> 0 | H27: =SUM(F27:G27) -> 0
A28: OTHER | E28: =PRODUCT(B28*C28) -> 0 | F28: =PRODUCT(E28*18)/118 -> 0 | G28: =PRODUCT(B28*D28) -> 0 | H28: =SUM(F28:G28) -> 0
A29: OTHER | E29: =PRODUCT(B29*C29) -> 0 | F29: =PRODUCT(E29*18)/118 -> 0 | G29: =PRODUCT(B29*D29) -> 0 | H29: =SUM(F29:G29) -> 0
A30: OTHER | E30: =PRODUCT(B30*C30) -> 0 | F30: =PRODUCT(E30*18)/118 -> 0 | G30: =PRODUCT(B30*D30) -> 0 | H30: =SUM(F30:G30) -> 0
A31: OTHER | E31: =PRODUCT(B31*C31) -> 0 | F31: =PRODUCT(E31*18)/118 -> 0 | G31: =PRODUCT(B31*D31) -> 0 | H31: =SUM(F31:G31) -> 0
A32: OTHER | E32: =PRODUCT(B32*C32) -> 0 | F32: =PRODUCT(E32*18)/118 -> 0 | G32: =PRODUCT(B32*D32) -> 0 | H32: =SUM(F32:G32) -> 0
A33: OTHER | E33: =PRODUCT(B33*C33) -> 0 | F33: =PRODUCT(E33*18)/118 -> 0 | G33: =PRODUCT(B33*D33) -> 0 | H33: =SUM(F33:G33) -> 0
A34: OTHER | E34: =PRODUCT(B34*C34) -> 0 | F34: =PRODUCT(E34*18)/118 -> 0 | G34: =PRODUCT(B34*D34) -> 0 | H34: =SUM(F34:G34) -> 0
... A36: OTHER | E36: =PRODUCT(B36*C36) -> 0 | F36: =PRODUCT(E36*18)/118 -> 0 | G36: =PRODUCT(B36*D36) -> 0 | H36: =SUM(F36:G36) -> 0
A37: TOTALY | E37: =SUM(E5:E36) -> 24245430 | F37: =SUM(F5:F36) -> 3698455.4 | G37: =SUM(G5:G36) -> 417190 | H37: =SUM(H5:H36) -> 4115645.4
A38: SUMMARY | C38: RWF | E38: NAME | G38: Phone | H38: RWF
A39: TOTAL RWF PAID ON MOMO PAY | C39: 4051363
A40: TOTAL RWF PAID ON CASH | C40: 64282
A41: AMOUNT NOT INVOICED
A42: TOTAL RWF DEPPOSITED ON BANK
A43: MEMBERSHIP FEES REGISTRETION
A44: MEMBERSHIP FEES CONTRIBUTION
A45: TOTAL INCOME | C45: =SUM(C39+C40+C41+C42+C43+C44) -> 4115645
A46: TIMBER SUMMARY
A48: REPORT SUMMARY | C48: TIMBER TYPE | E48: NUMBER OF QUANTITY
C49: INTURUSU | E49: =SUM(B9:B12) -> 8061
C50: PINUS | E50: =SUM(B6:B8) -> 0
C51: PALNCHE | E51: =SUM(B13:B14) -> 2718
C52: IBIPANDE | E52: =SUM(B17:B18) -> 0
C53: UMUSAVE | E53: =SUM(B19:B20) -> 0
C54: OTHER | E54: =B29 -> 0
C55: OTHER | E55: =B30 -> 0
C56: OTHER | E56: =B31 -> 0
C57: OTHER | E57: =B32 -> 0
C58: OTHER | E58: =B33 -> 0
C59: OTHER | E59: =B34 -> 0
C60: OTHER | E60: =B35 -> 0
C61: OTHER | E61: =B36 -> 0
C62: TOTAL TIMBER | E62: =SUM(E49:H61) -> 10779

Sheet NYAMAGABE
A1: QUANTITY REPORT
A3: MONTHS REPORT OF APRIL 2026
A5: NAME OF TIMBER | B5: No OF TIMBER | C5: PRICE OF TIMBER | E5: TOTAL COST | F5: TVA | G5: MSF | H5: TVA+MSF
A6: PINUS NINI | E6: =PRODUCT(B6*C6) -> 0 | F6: =PRODUCT(E6*18)/118 -> 0 | G6: =PRODUCT(B6*50) -> 0 | H6: =SUM(F6:G6) -> 0
A7: PINUS NTOYA | E7: =PRODUCT(B7*C7) -> 0 | F7: =PRODUCT(E7*18)/118 -> 0 | G7: =PRODUCT(B7*50) -> 0 | H7: =SUM(F7:G7) -> 0
A8: IBIPANDE BYA PINUS | B8: 390 | C8: 2360 | E8: =PRODUCT(B8*C8) -> 920400 | F8: =PRODUCT(E8*18)/118 -> 140400 | G8: =PRODUCT(B8*50) -> 19500 | H8: =SUM(F8:G8) -> 159900
A9: MADIRIYE NINI | E9: =PRODUCT(B9*C9) -> 0 | F9: =PRODUCT(E9*18)/118 -> 0 | G9: =PRODUCT(B9*30) -> 0 | H9: =SUM(F9:G9) -> 0
A10: MADIRIYE NTOYA | B10: 225 | C10: 2360 | E10: =PRODUCT(B10*C10) -> 531000 | F10: =PRODUCT(E10*18)/118 -> 81000 | G10: =PRODUCT(B10*30) -> 6750 | H10: =SUM(F10:G10) -> 87750
A11: MADRIEN | E11: =PRODUCT(B11*C11) -> 0 | F11: =PRODUCT(E11*18)/118 -> 0 | G11: =PRODUCT(B11*30) -> 0 | H11: =SUM(F11:G11) -> 0
A12: MADRIEN | E12: =PRODUCT(B12*C12) -> 0 | F12: =PRODUCT(E12*18)/118 -> 0 | G12: =PRODUCT(B12*30) -> 0 | H12: =SUM(F12:G12) -> 0
A13: PLANCHE | E13: =PRODUCT(B13*C13) -> 0 | F13: =PRODUCT(E13*18)/118 -> 0 | G13: =PRODUCT(B13*20) -> 0 | H13: =SUM(F13:G13) -> 0
A14: PLANCHE | E14: =PRODUCT(B14*C14) -> 0 | F14: =PRODUCT(E14*18)/118 -> 0 | G14: =PRODUCT(B14*20) -> 0 | H14: =SUM(F14:G14) -> 0
A15: Other Timber for Difference Price
A16: NAME OF TIMBER | B16: No OF TIMBER | C16: P/U | D16: MSF | E16: TOTAL COST | F16: VAT | G16: MSF | H16: VTA+MST
A17: IBIPANDE | E17: =PRODUCT(B17*C17) -> 0 | F17: =PRODUCT(E17*18)/118 -> 0 | G17: =PRODUCT(B17*D17) -> 0 | H17: =SUM(F17:G17) -> 0
A18: IBIPANDE | E18: =PRODUCT(B18*C18) -> 0 | F18: =PRODUCT(E18*18)/118 -> 0 | G18: =PRODUCT(B18*D18) -> 0 | H18: =SUM(F18:G18) -> 0
A19: UMUSAVE | E19: =PRODUCT(B19*C19) -> 0 | F19: =PRODUCT(E19*18)/118 -> 0 | G19: =PRODUCT(B19*D19) -> 0 | H19: =SUM(F19:G19) -> 0
A20: UMUSAVE | E20: =PRODUCT(B20*C20) -> 0 | F20: =PRODUCT(E20*18)/118 -> 0 | G20: =PRODUCT(B20*D20) -> 0 | H20: =SUM(F20:G20) -> 0
A21: DESCHET | C21: 10000 | D21: 1500 | E21: =PRODUCT(B21*C21) -> 0 | F21: =PRODUCT(E21*18)/118 -> 0 | G21: =PRODUCT(B21*D21) -> 0 | H21: =SUM(F21:G21) -> 0
A22: OTHER | E22: =PRODUCT(B22*C22) -> 0 | F22: =PRODUCT(E22*18)/118 -> 0 | G22: =PRODUCT(B22*D22) -> 0 | H22: =SUM(F22:G22) -> 0
A23: OTHER | E23: =PRODUCT(B23*C23) -> 0 | F23: =PRODUCT(E23*18)/118 -> 0 | G23: =PRODUCT(B23*D23) -> 0 | H23: =SUM(F23:G23) -> 0
A24: OTHER | E24: =PRODUCT(B24*C24) -> 0 | F24: =PRODUCT(E24*18)/118 -> 0 | G24: =PRODUCT(B24*D24) -> 0 | H24: =SUM(F24:G24) -> 0
A25: OTHER | E25: =PRODUCT(B25*C25) -> 0 | F25: =PRODUCT(E25*18)/118 -> 0 | G25: =PRODUCT(B25*D25) -> 0 | H25: =SUM(F25:G25) -> 0
A26: OTHER | E26: =PRODUCT(B26*C26) -> 0 | F26: =PRODUCT(E26*18)/118 -> 0 | G26: =PRODUCT(B26*D26) -> 0 | H26: =SUM(F26:G26) -> 0
A27: OTHER | E27: =PRODUCT(B27*C27) -> 0 | F27: =PRODUCT(E27*18)/118 -> 0 | G27: =PRODUCT(B27*D27) -> 0 | H27: =SUM(F27:G27) -> 0
A28: OTHER | E28: =PRODUCT(B28*C28) -> 0 | F28: =PRODUCT(E28*18)/118 -> 0 | G28: =PRODUCT(B28*D28) -> 0 | H28: =SUM(F28:G28) -> 0
A29: OTHER | E29: =PRODUCT(B29*C29) -> 0 | F29: =PRODUCT(E29*18)/118 -> 0 | G29: =PRODUCT(B29*D29) -> 0 | H29: =SUM(F29:G29) -> 0
A30: OTHER | E30: =PRODUCT(B30*C30) -> 0 | F30: =PRODUCT(E30*18)/118 -> 0 | G30: =PRODUCT(B30*D30) -> 0 | H30: =SUM(F30:G30) -> 0
A31: OTHER | E31: =PRODUCT(B31*C31) -> 0 | F31: =PRODUCT(E31*18)/118 -> 0 | G31: =PRODUCT(B31*D31) -> 0 | H31: =SUM(F31:G31) -> 0
A32: OTHER | E32: =PRODUCT(B32*C32) -> 0 | F32: =PRODUCT(E32*18)/118 -> 0 | G32: =PRODUCT(B32*D32) -> 0 | H32: =SUM(F32:G32) -> 0
A33: OTHER | E33: =PRODUCT(B33*C33) -> 0 | F33: =PRODUCT(E33*18)/118 -> 0 | G33: =PRODUCT(B33*D33) -> 0 | H33: =SUM(F33:G33) -> 0
... A36: OTHER | E36: =PRODUCT(B36*C36) -> 0 | F36: =PRODUCT(E36*18)/118 -> 0 | G36: =PRODUCT(B36*D36) -> 0 | H36: =SUM(F36:G36) -> 0
A37: TOTALY | E37: =SUM(E5:E36) -> 1451400 | F37: =SUM(F5:F36) -> 221400 | G37: =SUM(G5:G36) -> 26250 | H37: =SUM(H5:H36) -> 247650
A38: SUMMARY | C38: RWF | E38: NAME | G38: Phone | H38: RWF
A39: TOTAL RWF PAID ON MOMO PAY | C39: 247650
A40: TOTAL RWF PAID ON CASH
A41: AMOUNT NOT INVOICED
A42: TOTAL RWF DEPPOSITED ON BANK
A43: MEMBERSHIP FEES REGISTRETION
A44: MEMBERSHIP FEES CONTRIBUTION
A45: TOTAL INCOME | C45: =SUM(C39+C40+C41+C42+C43+C44) -> 247650
A46: TIMBER SUMMARY
A48: REPORT SUMMARY | C48: TIMBER TYPE | E48: NUMBER OF QUANTITY
C49: INTURUSU | E49: =SUM(B9:B12) -> 225
C50: PINUS | E50: =SUM(B6:B8) -> 390
C51: PALNCHE | E51: =SUM(B13:B14) -> 0
C52: IBIPANDE | E52: =SUM(B17:B18) -> 0
C53: UMUSAVE | E53: =SUM(B19:B20) -> 0
C54: OTHER | E54: =B29 -> 0
C55: OTHER | E55: =B30 -> 0
C56: OTHER | E56: =B31 -> 0
C57: OTHER | E57: =B32 -> 0
C58: OTHER | E58: =B33 -> 0
C59: OTHER | E59: =B34 -> 0
C60: OTHER | E60: =B35 -> 0
C61: OTHER | E61: =B36 -> 0
C62: TOTAL TIMBER | E62: =SUM(E49:H61) -> 615

Sheet KAYONZA
A1: QUANTITY REPORT
A3: MONTHS REPORT OF APRIL 2026
A5: NAME OF TIMBER | B5: No OF TIMBER | C5: PRICE OF TIMBER | E5: TOTAL COST | F5: TVA | G5: MSF | H5: TVA+MSF
A6: PINUS NINI | E6: =PRODUCT(B6*C6) -> 0 | F6: =PRODUCT(E6*18)/118 -> 0 | G6: =PRODUCT(B6*50) -> 0 | H6: =SUM(F6:G6) -> 0
A7: PINUS NTOYA | B7: 220 | C7: 5900 | E7: =PRODUCT(B7*C7) -> 1298000 | F7: =PRODUCT(E7*18)/118 -> 198000 | G7: =PRODUCT(B7*50) -> 11000 | H7: =SUM(F7:G7) -> 209000
A8: PINUS | E8: =PRODUCT(B8*C8) -> 0 | F8: =PRODUCT(E8*18)/118 -> 0 | G8: =PRODUCT(B8*50) -> 0 | H8: =SUM(F8:G8) -> 0
A9: MADIRIYE NINI | E9: =PRODUCT(B9*C9) -> 0 | F9: =PRODUCT(E9*18)/118 -> 0 | G9: =PRODUCT(B9*30) -> 0 | H9: =SUM(F9:G9) -> 0
A10: MADIRIYE NTOYA | E10: =PRODUCT(B10*C10) -> 0 | F10: =PRODUCT(E10*18)/118 -> 0 | G10: =PRODUCT(B10*30) -> 0 | H10: =SUM(F10:G10) -> 0
A11: MADRIEN | B11: 7000 | C11: 2124 | E11: =PRODUCT(B11*C11) -> 14868000 | F11: =PRODUCT(E11*18)/118 -> 2268000 | G11: =PRODUCT(B11*30) -> 210000 | H11: =SUM(F11:G11) -> 2478000
A12: MADRIEN | E12: =PRODUCT(B12*C12) -> 0 | F12: =PRODUCT(E12*18)/118 -> 0 | G12: =PRODUCT(B12*30) -> 0 | H12: =SUM(F12:G12) -> 0
A13: PLANCHE | B13: 1370 | C13: 1357 | E13: =PRODUCT(B13*C13) -> 1859090 | F13: =PRODUCT(E13*18)/118 -> 283590 | G13: =PRODUCT(B13*20) -> 27400 | H13: =SUM(F13:G13) -> 310990
A14: PLANCHE | C14: 1354 | E14: =PRODUCT(B14*C14) -> 0 | F14: =PRODUCT(E14*18)/118 -> 0 | G14: =PRODUCT(B14*20) -> 0 | H14: =SUM(F14:G14) -> 0
A15: Other Timber for Difference Price
A16: NAME OF TIMBER | B16: No OF TIMBER | C16: P/U | D16: MSF | E16: TOTAL COST | F16: VAT | G16: MSF | H16: VTA+MST
A17: IBIPANDE | B17: 2066 | C17: 1180 | D17: 20 | E17: =PRODUCT(B17*C17) -> 2437880 | F17: =PRODUCT(E17*18)/118 -> 371880 | G17: =PRODUCT(B17*D17) -> 41320 | H17: =SUM(F17:G17) -> 413200
A18: IBIPANDE | B18: 65 | D18: 200 | E18: =PRODUCT(B18*C18) -> 0 | F18: =PRODUCT(E18*18)/118 -> 0 | G18: =PRODUCT(B18*D18) -> 13000 | H18: =SUM(F18:G18) -> 13000
A19: UMUSAVE | B19: 28 | D19: 465 | E19: =PRODUCT(B19*C19) -> 0 | F19: =PRODUCT(E19*18)/118 -> 0 | G19: =PRODUCT(B19*D19) -> 13020 | H19: =SUM(F19:G19) -> 13020
A20: IBIPANDE BYA SIPURE | D20: 354 | E20: =PRODUCT(B20*C20) -> 0 | F20: =PRODUCT(E20*18)/118 -> 0 | G20: =PRODUCT(B20*D20) -> 0 | H20: =SUM(F20:G20) -> 0
A21: OTHER | E21: =PRODUCT(B21*C21) -> 0 | F21: =PRODUCT(E21*18)/118 -> 0 | G21: =PRODUCT(B21*D21) -> 0 | H21: =SUM(F21:G21) -> 0
A22: OTHER | E22: =PRODUCT(B22*C22) -> 0 | F22: =PRODUCT(E22*18)/118 -> 0 | G22: =PRODUCT(B22*D22) -> 0 | H22: =SUM(F22:G22) -> 0
A23: OTHER | E23: =PRODUCT(B23*C23) -> 0 | F23: =PRODUCT(E23*18)/118 -> 0 | G23: =PRODUCT(B23*D23) -> 0 | H23: =SUM(F23:G23) -> 0
A24: OTHER | E24: =PRODUCT(B24*C24) -> 0 | F24: =PRODUCT(E24*18)/118 -> 0 | G24: =PRODUCT(B24*D24) -> 0 | H24: =SUM(F24:G24) -> 0
A25: OTHER | E25: =PRODUCT(B25*C25) -> 0 | F25: =PRODUCT(E25*18)/118 -> 0 | G25: =PRODUCT(B25*D25) -> 0 | H25: =SUM(F25:G25) -> 0
A26: OTHER | E26: =PRODUCT(B26*C26) -> 0 | F26: =PRODUCT(E26*18)/118 -> 0 | G26: =PRODUCT(B26*D26) -> 0 | H26: =SUM(F26:G26) -> 0
A27: OTHER | E27: =PRODUCT(B27*C27) -> 0 | F27: =PRODUCT(E27*18)/118 -> 0 | G27: =PRODUCT(B27*D27) -> 0 | H27: =SUM(F27:G27) -> 0
A28: OTHER | E28: =PRODUCT(B28*C28) -> 0 | F28: =PRODUCT(E28*18)/118 -> 0 | G28: =PRODUCT(B28*D28) -> 0 | H28: =SUM(F28:G28) -> 0
A29: OTHER | E29: =PRODUCT(B29*C29) -> 0 | F29: =PRODUCT(E29*18)/118 -> 0 | G29: =PRODUCT(B29*D29) -> 0 | H29: =SUM(F29:G29) -> 0
A30: OTHER | E30: =PRODUCT(B30*C30) -> 0 | F30: =PRODUCT(E30*18)/118 -> 0 | G30: =PRODUCT(B30*D30) -> 0 | H30: =SUM(F30:G30) -> 0
A31: OTHER | E31: =PRODUCT(B31*C31) -> 0 | F31: =PRODUCT(E31*18)/118 -> 0 | G31: =PRODUCT(B31*D31) -> 0 | H31: =SUM(F31:G31) -> 0
A32: OTHER | E32: =PRODUCT(B32*C32) -> 0 | F32: =PRODUCT(E32*18)/118 -> 0 | G32: =PRODUCT(B32*D32) -> 0 | H32: =SUM(F32:G32) -> 0
... A36: OTHER | E36: =PRODUCT(B36*C36) -> 0 | F36: =PRODUCT(E36*18)/118 -> 0 | G36: =PRODUCT(B36*D36) -> 0 | H36: =SUM(F36:G36) -> 0
A37: TOTALY | E37: =SUM(E5:E36) -> 20462970 | F37: =SUM(F5:F36) -> 3121470 | G37: =SUM(G5:G36) -> 315740 | H37: =SUM(H5:H36) -> 3437210
A38: SUMMARY | C38: RWF | E38: NAME | G38: Phone | H38: RWF
A39: TOTAL RWF PAID ON MOMO PAY | C39: 3437210
A40: TOTAL RWF PAID ON CASH
A41: AMOUNT NOT INVOICED
A42: TOTAL RWF DEPPOSITED ON BANK
A43: MEMBERSHIP FEES REGISTRETION
A44: MEMBERSHIP FEES CONTRIBUTION
A45: TOTAL INCOME | C45: =SUM(C39+C40+C41+C42+C43+C44) -> 3437210
A46: TIMBER SUMMARY
A48: REPORT SUMMARY | C48: TIMBER TYPE | E48: NUMBER OF QUANTITY
C49: INTURUSU | E49: =SUM(B9:B12) -> 7000
C50: PINUS | E50: =SUM(B6:B8) -> 220
C51: PALNCHE | E51: =SUM(B13:B14) -> 1370
C52: IBIPANDE | E52: =SUM(B17:B18) -> 2131
C53: UMUSAVE | E53: =SUM(B19:B20) -> 28
C54: OTHER | E54: =B29 -> 0
C55: OTHER | E55: =B30 -> 0
C56: OTHER | E56: =B31 -> 0
C57: OTHER | E57: =B32 -> 0
C58: OTHER | E58: =B33 -> 0
C59: OTHER | E59: =B34 -> 0
C60: OTHER | E60: =B35 -> 0
C61: OTHER | E61: =B36 -> 0
C62: TOTAL TIMBER | E62: =SUM(E49:H61) -> 10749

Sheet RUHANGO
A1: QUANTITY REPORT
A3: MONTHS REPORT OF APRIL 2026
A5: NAME OF TIMBER | B5: No OF TIMBER | C5: PRICE OF TIMBER | E5: TOTAL COST | F5: TVA | G5: MSF | H5: TVA+MSF
A6: PINUS NINI | E6: =PRODUCT(B6*C6) -> 0 | F6: =PRODUCT(E6*18)/118 -> 0 | G6: =PRODUCT(B6*50) -> 0 | H6: =SUM(F6:G6) -> 0
A7: PINUS NTOYA | E7: =PRODUCT(B7*C7) -> 0 | F7: =PRODUCT(E7*18)/118 -> 0 | G7: =PRODUCT(B7*50) -> 0 | H7: =SUM(F7:G7) -> 0
A8: PINUS | E8: =PRODUCT(B8*C8) -> 0 | F8: =PRODUCT(E8*18)/118 -> 0 | G8: =PRODUCT(B8*50) -> 0 | H8: =SUM(F8:G8) -> 0
A9: MADIRIYE NINI | E9: =PRODUCT(B9*C9) -> 0 | F9: =PRODUCT(E9*18)/118 -> 0 | G9: =PRODUCT(B9*30) -> 0 | H9: =SUM(F9:G9) -> 0
A10: MADIRIYE NTOYA | B10: 1650 | C10: 1800 | E10: =PRODUCT(B10*C10) -> 2970000 | F10: =PRODUCT(E10*18)/118 -> 453050.85 | G10: =PRODUCT(B10*30) -> 49500 | H10: =SUM(F10:G10) -> 502550.85
A11: MADRIEN | E11: =PRODUCT(B11*C11) -> 0 | F11: =PRODUCT(E11*18)/118 -> 0 | G11: =PRODUCT(B11*30) -> 0 | H11: =SUM(F11:G11) -> 0
A12: MADRIEN | E12: =PRODUCT(B12*C12) -> 0 | F12: =PRODUCT(E12*18)/118 -> 0 | G12: =PRODUCT(B12*30) -> 0 | H12: =SUM(F12:G12) -> 0
A13: PLANCHE | E13: =PRODUCT(B13*C13) -> 0 | F13: =PRODUCT(E13*18)/118 -> 0 | G13: =PRODUCT(B13*20) -> 0 | H13: =SUM(F13:G13) -> 0
A14: PLANCHE | E14: =PRODUCT(B14*C14) -> 0 | F14: =PRODUCT(E14*18)/118 -> 0 | G14: =PRODUCT(B14*20) -> 0 | H14: =SUM(F14:G14) -> 0
A15: Other Timber for Difference Price
A16: NAME OF TIMBER | B16: No OF TIMBER | C16: P/U | D16: MSF | E16: TOTAL COST | F16: VAT | G16: MSF | H16: VTA+MST
A17: IBIPANDE | B17: 400 | C17: 800 | D17: 20 | E17: =PRODUCT(B17*C17) -> 320000 | F17: =PRODUCT(E17*18)/118 -> 48813.559 | G17: =PRODUCT(B17*D17) -> 8000 | H17: =SUM(F17:G17) -> 56813.559
A18: IBIPANDE | E18: =PRODUCT(B18*C18) -> 0 | F18: =PRODUCT(E18*18)/118 -> 0 | G18: =PRODUCT(B18*D18) -> 0 | H18: =SUM(F18:G18) -> 0
A19: UMUSAVE | E19: =PRODUCT(B19*C19) -> 0 | F19: =PRODUCT(E19*18)/118 -> 0 | G19: =PRODUCT(B19*D19) -> 0 | H19: =SUM(F19:G19) -> 0
A20: UMUSAVE | E20: =PRODUCT(B20*C20) -> 0 | F20: =PRODUCT(E20*18)/118 -> 0 | G20: =PRODUCT(B20*D20) -> 0 | H20: =SUM(F20:G20) -> 0
A21: OTHER | B21: 2987 | D21: 50 | E21: =PRODUCT(B21*C21) -> 0 | F21: =PRODUCT(E21*18)/118 -> 0 | G21: =PRODUCT(B21*D21) -> 149350 | H21: =SUM(F21:G21) -> 149350
A22: OTHER | E22: =PRODUCT(B22*C22) -> 0 | F22: =PRODUCT(E22*18)/118 -> 0 | G22: =PRODUCT(B22*D22) -> 0 | H22: =SUM(F22:G22) -> 0
A23: OTHER | E23: =PRODUCT(B23*C23) -> 0 | F23: =PRODUCT(E23*18)/118 -> 0 | G23: =PRODUCT(B23*D23) -> 0 | H23: =SUM(F23:G23) -> 0
A24: OTHER | E24: =PRODUCT(B24*C24) -> 0 | F24: =PRODUCT(E24*18)/118 -> 0 | G24: =PRODUCT(B24*D24) -> 0 | H24: =SUM(F24:G24) -> 0
A25: OTHER | E25: =PRODUCT(B25*C25) -> 0 | F25: =PRODUCT(E25*18)/118 -> 0 | G25: =PRODUCT(B25*D25) -> 0 | H25: =SUM(F25:G25) -> 0
A26: OTHER | E26: =PRODUCT(B26*C26) -> 0 | F26: =PRODUCT(E26*18)/118 -> 0 | G26: =PRODUCT(B26*D26) -> 0 | H26: =SUM(F26:G26) -> 0
A27: OTHER | E27: =PRODUCT(B27*C27) -> 0 | F27: =PRODUCT(E27*18)/118 -> 0 | G27: =PRODUCT(B27*D27) -> 0 | H27: =SUM(F27:G27) -> 0
A28: OTHER | E28: =PRODUCT(B28*C28) -> 0 | F28: =PRODUCT(E28*18)/118 -> 0 | G28: =PRODUCT(B28*D28) -> 0 | H28: =SUM(F28:G28) -> 0
A29: OTHER | E29: =PRODUCT(B29*C29) -> 0 | F29: =PRODUCT(E29*18)/118 -> 0 | G29: =PRODUCT(B29*D29) -> 0 | H29: =SUM(F29:G29) -> 0
A30: OTHER | E30: =PRODUCT(B30*C30) -> 0 | F30: =PRODUCT(E30*18)/118 -> 0 | G30: =PRODUCT(B30*D30) -> 0 | H30: =SUM(F30:G30) -> 0
A31: OTHER | E31: =PRODUCT(B31*C31) -> 0 | F31: =PRODUCT(E31*18)/118 -> 0 | G31: =PRODUCT(B31*D31) -> 0 | H31: =SUM(F31:G31) -> 0
A32: OTHER | E32: =PRODUCT(B32*C32) -> 0 | F32: =PRODUCT(E32*18)/118 -> 0 | G32: =PRODUCT(B32*D32) -> 0 | H32: =SUM(F32:G32) -> 0
A33: OTHER | E33: =PRODUCT(B33*C33) -> 0 | F33: =PRODUCT(E33*18)/118 -> 0 | G33: =PRODUCT(B33*D33) -> 0 | H33: =SUM(F33:G33) -> 0
... A36: OTHER | E36: =PRODUCT(B36*C36) -> 0 | F36: =PRODUCT(E36*18)/118 -> 0 | G36: =PRODUCT(B36*D36) -> 0 | H36: =SUM(F36:G36) -> 0
A37: TOTALY | E37: =SUM(E5:E36) -> 3290000 | F37: =SUM(F5:F36) -> 501864.41 | G37: =SUM(G5:G36) -> 206850 | H37: =SUM(H5:H36) -> 708714.41
A38: SUMMARY | C38: RWF | E38: NAME | G38: Phone | H38: RWF
A39: TOTAL RWF PAID ON MOMO PAY | C39: 708714
A40: TOTAL RWF PAID ON CASH
A41: AMOUNT NOT INVOICED
A42: TOTAL RWF DEPPOSITED ON BANK
A43: MEMBERSHIP FEES REGISTRETION
A44: MEMBERSHIP FEES CONTRIBUTION
A45: TOTAL INCOME | C45: =SUM(C39+C40+C41+C42+C43+C44) -> 708714
A46: TIMBER SUMMARY
A48: REPORT SUMMARY | C48: TIMBER TYPE | E48: NUMBER OF QUANTITY
C49: INTURUSU | E49: =SUM(B9:B12) -> 1650
C50: PINUS | E50: =SUM(B6:B8) -> 0
C51: PALNCHE | E51: =SUM(B13:B14) -> 0
C52: IBIPANDE | E52: =SUM(B17:B18) -> 400
C53: UMUSAVE | E53: =SUM(B19:B20) -> 0
C54: OTHER | E54: =B29 -> 0
C55: OTHER | E55: =B30 -> 0
C56: OTHER | E56: =B31 -> 0
C57: OTHER | E57: =B32 -> 0
C58: OTHER | E58: =B33 -> 0
C59: OTHER | E59: =B34 -> 0
C60: OTHER | E60: =B35 -> 0
C61: OTHER | E61: =B36 -> 0
C62: TOTAL TIMBER | E62: =SUM(E49:H61) -> 2050

Sheet KARONGI
A1: QUANTITY REPORT
A3: MONTHS REPORT OF APRIL 2026
A5: NAME OF TIMBER | B5: No OF TIMBER | C5: PRICE OF TIMBER | E5: TOTAL COST | F5: TVA | G5: MSF | H5: TVA+MSF
A6: PINUS NINI | B6: 130 | C6: 7080 | E6: =PRODUCT(B6*C6) -> 920400 | F6: =PRODUCT(E6*18)/118 -> 140400 | G6: =PRODUCT(B6*50) -> 6500 | H6: =SUM(F6:G6) -> 146900
A7: PINUS NTOYA | B7: 45 | C7: 2000 | E7: =PRODUCT(B7*C7) -> 90000 | F7: =PRODUCT(E7*18)/118 -> 13728.814 | G7: =PRODUCT(B7*50) -> 2250 | H7: =SUM(F7:G7) -> 15978.814
A8: PINUS | B8: 1220 | C8: 1416 | E8: =PRODUCT(B8*C8) -> 1727520 | F8: =PRODUCT(E8*18)/118 -> 263520 | G8: =PRODUCT(B8*50) -> 61000 | H8: =SUM(F8:G8) -> 324520
A9: MADIRIYE NINI | C9: 3900 | E9: =PRODUCT(B9*C9) -> 0 | F9: =PRODUCT(E9*18)/118 -> 0 | G9: =PRODUCT(B9*30) -> 0 | H9: =SUM(F9:G9) -> 0
A10: MADIRIYE NTOYA | B10: 3733 | C10: 2124 | E10: =PRODUCT(B10*C10) -> 7928892 | F10: =PRODUCT(E10*18)/118 -> 1209492 | G10: =PRODUCT(B10*30) -> 111990 | H10: =SUM(F10:G10) -> 1321482
A11: MADRIEN | E11: =PRODUCT(B11*C11) -> 0 | F11: =PRODUCT(E11*18)/118 -> 0 | G11: =PRODUCT(B11*30) -> 0 | H11: =SUM(F11:G11) -> 0
A12: MADRIEN | E12: =PRODUCT(B12*C12) -> 0 | F12: =PRODUCT(E12*18)/118 -> 0 | G12: =PRODUCT(B12*30) -> 0 | H12: =SUM(F12:G12) -> 0
A13: PLANCHE | B13: 70 | C13: 1200 | E13: =PRODUCT(B13*C13) -> 84000 | F13: =PRODUCT(E13*18)/118 -> 12813.559 | G13: =PRODUCT(B13*20) -> 1400 | H13: =SUM(F13:G13) -> 14213.559
A14: PLANCHE | E14: =PRODUCT(B14*C14) -> 0 | F14: =PRODUCT(E14*18)/118 -> 0 | G14: =PRODUCT(B14*20) -> 0 | H14: =SUM(F14:G14) -> 0
A15: Other Timber for Difference Price
A16: NAME OF TIMBER | B16: No OF TIMBER | C16: P/U | D16: MSF | E16: TOTAL COST | F16: VAT | G16: MSF | H16: VTA+MST
A17: IBIPANDE | B17: 110 | D17: 266 | E17: =PRODUCT(B17*C17) -> 0 | F17: =PRODUCT(E17*18)/118 -> 0 | G17: =PRODUCT(B17*D17) -> 29260 | H17: =SUM(F17:G17) -> 29260
A18: IBIPANDE | E18: =PRODUCT(B18*C18) -> 0 | F18: =PRODUCT(E18*18)/118 -> 0 | G18: =PRODUCT(B18*D18) -> 0 | H18: =SUM(F18:G18) -> 0
A19: UMUSAVE | E19: =PRODUCT(B19*C19) -> 0 | F19: =PRODUCT(E19*18)/118 -> 0 | G19: =PRODUCT(B19*D19) -> 0 | H19: =SUM(F19:G19) -> 0
A20: UMUSAVE | E20: =PRODUCT(B20*C20) -> 0 | F20: =PRODUCT(E20*18)/118 -> 0 | G20: =PRODUCT(B20*D20) -> 0 | H20: =SUM(F20:G20) -> 0
A21: OTHER | D21: 266 | E21: =PRODUCT(B21*C21) -> 0 | F21: =PRODUCT(E21*18)/118 -> 0 | G21: =PRODUCT(B21*D21) -> 0 | H21: =SUM(F21:G21) -> 0
A22: OTHER | D22: 354 | E22: =PRODUCT(B22*C22) -> 0 | F22: =PRODUCT(E22*18)/118 -> 0 | G22: =PRODUCT(B22*D22) -> 0 | H22: =SUM(F22:G22) -> 0
A23: OTHER | C23: 2500 | D23: 50 | E23: =PRODUCT(B23*C23) -> 0 | F23: =PRODUCT(E23*18)/118 -> 0 | G23: =PRODUCT(B23*D23) -> 0 | H23: =SUM(F23:G23) -> 0
A24: OTHER | D24: 203 | E24: =PRODUCT(B24*C24) -> 0 | F24: =PRODUCT(E24*18)/118 -> 0 | G24: =PRODUCT(B24*D24) -> 0 | H24: =SUM(F24:G24) -> 0
A25: OTHER | E25: =PRODUCT(B25*C25) -> 0 | F25: =PRODUCT(E25*18)/118 -> 0 | G25: =PRODUCT(B25*D25) -> 0 | H25: =SUM(F25:G25) -> 0
A26: OTHER | E26: =PRODUCT(B26*C26) -> 0 | F26: =PRODUCT(E26*18)/118 -> 0 | G26: =PRODUCT(B26*D26) -> 0 | H26: =SUM(F26:G26) -> 0
A27: OTHER | E27: =PRODUCT(B27*C27) -> 0 | F27: =PRODUCT(E27*18)/118 -> 0 | G27: =PRODUCT(B27*D27) -> 0 | H27: =SUM(F27:G27) -> 0
A28: OTHER | E28: =PRODUCT(B28*C28) -> 0 | F28: =PRODUCT(E28*18)/118 -> 0 | G28: =PRODUCT(B28*D28) -> 0 | H28: =SUM(F28:G28) -> 0
A29: OTHER | E29: =PRODUCT(B29*C29) -> 0 | F29: =PRODUCT(E29*18)/118 -> 0 | G29: =PRODUCT(B29*D29) -> 0 | H29: =SUM(F29:G29) -> 0
A30: OTHER | E30: =PRODUCT(B30*C30) -> 0 | F30: =PRODUCT(E30*18)/118 -> 0 | G30: =PRODUCT(B30*D30) -> 0 | H30: =SUM(F30:G30) -> 0
A31: OTHER | E31: =PRODUCT(B31*C31) -> 0 | F31: =PRODUCT(E31*18)/118 -> 0 | G31: =PRODUCT(B31*D31) -> 0 | H31: =SUM(F31:G31) -> 0
A32: OTHER | E32: =PRODUCT(B32*C32) -> 0 | F32: =PRODUCT(E32*18)/118 -> 0 | G32: =PRODUCT(B32*D32) -> 0 | H32: =SUM(F32:G32) -> 0
A33: OTHER | E33: =PRODUCT(B33*C33) -> 0 | F33: =PRODUCT(E33*18)/118 -> 0 | G33: =PRODUCT(B33*D33) -> 0 | H33: =SUM(F33:G33) -> 0
A34: OTHER | E34: =PRODUCT(B34*C34) -> 0 | F34: =PRODUCT(E34*18)/118 -> 0 | G34: =PRODUCT(B34*D34) -> 0 | H34: =SUM(F34:G34) -> 0
A35: OTHER | E35: =PRODUCT(B35*C35) -> 0 | F35: =PRODUCT(E35*18)/118 -> 0 | G35: =PRODUCT(B35*D35) -> 0 | H35: =SUM(F35:G35) -> 0
A36: OTHER | E36: =PRODUCT(B36*C36) -> 0 | F36: =PRODUCT(E36*18)/118 -> 0 | G36: =PRODUCT(B36*D36) -> 0 | H36: =SUM(F36:G36) -> 0
A37: TOTALY | E37: =SUM(E5:E36) -> 10750812 | F37: =SUM(F5:F36) -> 1639954.4 | G37: =SUM(G5:G36) -> 212400 | H37: =SUM(H5:H36) -> 1852354.4
A38: SUMMARY | C38: RWF | E38: NAME | G38: Phone | H38: RWF
A39: TOTAL RWF PAID ON MOMO PAY | C39: 1852254
A40: TOTAL RWF PAID ON CASH
A41: AMOUNT NOT INVOICED
A42: TOTAL RWF DEPPOSITED ON BANK
A43: MEMBERSHIP FEES REGISTRETION
A44: MEMBERSHIP FEES CONTRIBUTION
A45: TOTAL INCOME | C45: =SUM(C39+C40+C41+C42+C43+C44) -> 1852254
A46: TIMBER SUMMARY
A48: REPORT SUMMARY | C48: TIMBER TYPE | E48: NUMBER OF QUANTITY
C49: INTURUSU | E49: =SUM(B9:B12) -> 3733
C50: PINUS | E50: =SUM(B6:B8) -> 1395
C51: PALNCHE | E51: =SUM(B13:B14) -> 70
C52: IBIPANDE | E52: =SUM(B17:B18) -> 110
C53: UMUSAVE | E53: =SUM(B19:B20) -> 0
C54: OTHER | E54: =B29 -> 0
C55: OTHER | E55: =B30 -> 0
C56: OTHER | E56: =B31 -> 0
C57: OTHER | E57: =B32 -> 0
C58: OTHER | E58: =B33 -> 0
C59: OTHER | E59: =B34 -> 0
C60: OTHER | E60: =B35 -> 0
C61: OTHER | E61: =B36 -> 0
C62: TOTAL TIMBER | E62: =SUM(E49:H61) -> 5308

Sheet RUSIZI
A1: QUANTITY REPORT
A3: MONTHS REPORT OF APRIL 2026
A5: NAME OF TIMBER | B5: No OF TIMBER | C5: PRICE OF TIMBER | E5: TOTAL COST | F5: TVA | G5: MSF | H5: TVA+MSF
A6: PINUS NINI | B6: 70 | C6: 8000 | E6: =PRODUCT(B6*C6) -> 560000 | F6: =PRODUCT(E6*18)/118 -> 85423.729 | G6: =PRODUCT(B6*50) -> 3500 | H6: =SUM(F6:G6) -> 88923.729
A7: PINUS NTOYA | E7: =PRODUCT(B7*C7) -> 0 | F7: =PRODUCT(E7*18)/118 -> 0 | G7: =PRODUCT(B7*50) -> 0 | H7: =SUM(F7:G7) -> 0
A8: PINUS | E8: =PRODUCT(B8*C8) -> 0 | F8: =PRODUCT(E8*18)/118 -> 0 | G8: =PRODUCT(B8*50) -> 0 | H8: =SUM(F8:G8) -> 0
A9: MADIRIYE NINI | E9: =PRODUCT(B9*C9) -> 0 | F9: =PRODUCT(E9*18)/118 -> 0 | G9: =PRODUCT(B9*30) -> 0 | H9: =SUM(F9:G9) -> 0
A10: MADIRIYE NTOYA | E10: =PRODUCT(B10*C10) -> 0 | F10: =PRODUCT(E10*18)/118 -> 0 | G10: =PRODUCT(B10*30) -> 0 | H10: =SUM(F10:G10) -> 0
A11: MADRIEN | E11: =PRODUCT(B11*C11) -> 0 | F11: =PRODUCT(E11*18)/118 -> 0 | G11: =PRODUCT(B11*30) -> 0 | H11: =SUM(F11:G11) -> 0
A12: MADRIEN | B12: 500 | C12: 2500 | E12: =PRODUCT(B12*C12) -> 1250000 | F12: =PRODUCT(E12*18)/118 -> 190677.97 | G12: =PRODUCT(B12*30) -> 15000 | H12: =SUM(F12:G12) -> 205677.97
A13: PLANCHE | E13: =PRODUCT(B13*C13) -> 0 | F13: =PRODUCT(E13*18)/118 -> 0 | G13: =PRODUCT(B13*20) -> 0 | H13: =SUM(F13:G13) -> 0
A14: PLANCHE | E14: =PRODUCT(B14*C14) -> 0 | F14: =PRODUCT(E14*18)/118 -> 0 | G14: =PRODUCT(B14*20) -> 0 | H14: =SUM(F14:G14) -> 0
A15: Other Timber for Difference Price
A16: NAME OF TIMBER | B16: No OF TIMBER | C16: P/U | D16: MSF | E16: TOTAL COST | F16: VAT | G16: MSF | H16: VTA+MST
A17: MADRIEN | B17: 3970 | C17: 2124 | D17: 40 | E17: =PRODUCT(B17*C17) -> 8432280 | F17: =PRODUCT(E17*18)/118 -> 1286280 | G17: =PRODUCT(B17*D17) -> 158800 | H17: =SUM(F17:G17) -> 1445080
A18: PLANCHE | B18: 2070 | C18: 1357 | D18: 30 | E18: =PRODUCT(B18*C18) -> 2808990 | F18: =PRODUCT(E18*18)/118 -> 428490 | G18: =PRODUCT(B18*D18) -> 62100 | H18: =SUM(F18:G18) -> 490590
A19: UMUSAVE | B19: 200 | C19: 1500 | D19: 40 | E19: =PRODUCT(B19*C19) -> 300000 | F19: =PRODUCT(E19*18)/118 -> 45762.712 | G19: =PRODUCT(B19*D19) -> 8000 | H19: =SUM(F19:G19) -> 53762.712
A20: MADRIEN | B20: 50 | C20: 2500 | D20: 40 | E20: =PRODUCT(B20*C20) -> 125000 | F20: =PRODUCT(E20*18)/118 -> 19067.797 | G20: =PRODUCT(B20*D20) -> 2000 | H20: =SUM(F20:G20) -> 21067.797
A21: CYPRE | B21: 285 | C21: 1000 | D21: 40 | E21: =PRODUCT(B21*C21) -> 285000 | F21: =PRODUCT(E21*18)/118 -> 43474.576 | G21: =PRODUCT(B21*D21) -> 11400 | H21: =SUM(F21:G21) -> 54874.576
A22: OTHER | B22: 2100 | D22: 100 | E22: =PRODUCT(B22*C22) -> 0 | F22: =PRODUCT(E22*18)/118 -> 0 | G22: =PRODUCT(B22*D22) -> 210000 | H22: =SUM(F22:G22) -> 210000
A23: OTHER | E23: =PRODUCT(B23*C23) -> 0 | F23: =PRODUCT(E23*18)/118 -> 0 | G23: =PRODUCT(B23*D23) -> 0 | H23: =SUM(F23:G23) -> 0
A24: OTHER | E24: =PRODUCT(B24*C24) -> 0 | F24: =PRODUCT(E24*18)/118 -> 0 | G24: =PRODUCT(B24*D24) -> 0 | H24: =SUM(F24:G24) -> 0
A25: OTHER | E25: =PRODUCT(B25*C25) -> 0 | F25: =PRODUCT(E25*18)/118 -> 0 | G25: =PRODUCT(B25*D25) -> 0 | H25: =SUM(F25:G25) -> 0
A26: OTHER | E26: =PRODUCT(B26*C26) -> 0 | F26: =PRODUCT(E26*18)/118 -> 0 | G26: =PRODUCT(B26*D26) -> 0 | H26: =SUM(F26:G26) -> 0
A27: OTHER | E27: =PRODUCT(B27*C27) -> 0 | F27: =PRODUCT(E27*18)/118 -> 0 | G27: =PRODUCT(B27*D27) -> 0 | H27: =SUM(F27:G27) -> 0
A28: OTHER | E28: =PRODUCT(B28*C28) -> 0 | F28: =PRODUCT(E28*18)/118 -> 0 | G28: =PRODUCT(B28*D28) -> 0 | H28: =SUM(F28:G28) -> 0
A29: OTHER | E29: =PRODUCT(B29*C29) -> 0 | F29: =PRODUCT(E29*18)/118 -> 0 | G29: =PRODUCT(B29*D29) -> 0 | H29: =SUM(F29:G29) -> 0
A30: OTHER | E30: =PRODUCT(B30*C30) -> 0 | F30: =PRODUCT(E30*18)/118 -> 0 | G30: =PRODUCT(B30*D30) -> 0 | H30: =SUM(F30:G30) -> 0
A31: OTHER | E31: =PRODUCT(B31*C31) -> 0 | F31: =PRODUCT(E31*18)/118 -> 0 | G31: =PRODUCT(B31*D31) -> 0 | H31: =SUM(F31:G31) -> 0
A32: OTHER | E32: =PRODUCT(B32*C32) -> 0 | F32: =PRODUCT(E32*18)/118 -> 0 | G32: =PRODUCT(B32*D32) -> 0 | H32: =SUM(F32:G32) -> 0
A33: OTHER | E33: =PRODUCT(B33*C33) -> 0 | F33: =PRODUCT(E33*18)/118 -> 0 | G33: =PRODUCT(B33*D33) -> 0 | H33: =SUM(F33:G33) -> 0
A34: OTHER | E34: =PRODUCT(B34*C34) -> 0 | F34: =PRODUCT(E34*18)/118 -> 0 | G34: =PRODUCT(B34*D34) -> 0 | H34: =SUM(F34:G34) -> 0
... A36: OTHER | E36: =PRODUCT(B36*C36) -> 0 | F36: =PRODUCT(E36*18)/118 -> 0 | G36: =PRODUCT(B36*D36) -> 0 | H36: =SUM(F36:G36) -> 0
A37: TOTALY | E37: =SUM(E5:E36) -> 13761270 | F37: =SUM(F5:F36) -> 2099176.8 | G37: =SUM(G5:G36) -> 470800 | H37: =SUM(H5:H36) -> 2569976.8
A38: SUMMARY | C38: RWF | E38: NAME | G38: Phone | H38: RWF
A39: TOTAL RWF PAID ON MOMO PAY | C39: 2569977
A40: TOTAL RWF PAID ON CASH
A41: AMOUNT NOT INVOICED
A42: TOTAL RWF DEPPOSITED ON BANK
A43: MEMBERSHIP FEES REGISTRETION
A44: MEMBERSHIP FEES CONTRIBUTION
A45: TOTAL INCOME | C45: =SUM(C39+C40+C41+C42+C43+C44) -> 2569977
A46: TIMBER SUMMARY
A48: REPORT SUMMARY | C48: TIMBER TYPE | E48: NUMBER OF QUANTITY
C49: INTURUSU | E49: =SUM(B9:B12) -> 500
C50: PINUS | E50: =SUM(B6:B8) -> 70
C51: PALNCHE | E51: =SUM(B13:B14) -> 0
C52: IBIPANDE | E52: =SUM(B17:B18) -> 6040
C53: UMUSAVE | E53: =SUM(B19:B20) -> 250
C54: OTHER | E54: =B29 -> 0
C55: OTHER | E55: =B30 -> 0
C56: OTHER | E56: =B31 -> 0
C57: OTHER | E57: =B32 -> 0
C58: OTHER | E58: =B33 -> 0
C59: OTHER | E59: =B34 -> 0
C60: OTHER | E60: =B35 -> 0
C61: OTHER | E61: =B36 -> 0
C62: TOTAL TIMBER | E62: =SUM(E49:H61) -> 6860

Sheet RUBAVU
A1: QUANTITY REPORT
A3: MONTHS REPORT OF APRIL 2026
A5: NAME OF TIMBER | B5: No OF TIMBER | C5: PRICE OF TIMBER | E5: TOTAL COST | F5: TVA | G5: MSF | H5: TVA+MSF
A6: PINUS NINI | B6: 150 | C6: 8850 | E6: =PRODUCT(B6*C6) -> 1327500 | F6: =PRODUCT(E6*18)/118 -> 202500 | G6: =PRODUCT(B6*50) -> 7500 | H6: =SUM(F6:G6) -> 210000
A7: PINUS NTOYA | E7: =PRODUCT(B7*C7) -> 0 | F7: =PRODUCT(E7*18)/118 -> 0 | G7: =PRODUCT(B7*50) -> 0 | H7: =SUM(F7:G7) -> 0
A8: IBIPANDE BYA PINUS | C8: 2360 | E8: =PRODUCT(B8*C8) -> 0 | F8: =PRODUCT(E8*18)/118 -> 0 | G8: =PRODUCT(B8*50) -> 0 | H8: =SUM(F8:G8) -> 0
A9: MADIRIYE NINI | E9: =PRODUCT(B9*C9) -> 0 | F9: =PRODUCT(E9*18)/118 -> 0 | G9: =PRODUCT(B9*30) -> 0 | H9: =SUM(F9:G9) -> 0
A10: MADIRIYE NTOYA | B10: 11095 | C10: 2360 | E10: =PRODUCT(B10*C10) -> 26184200 | F10: =PRODUCT(E10*18)/118 -> 3994200 | G10: =PRODUCT(B10*30) -> 332850 | H10: =SUM(F10:G10) -> 4327050
A11: MADRIEN | E11: =PRODUCT(B11*C11) -> 0 | F11: =PRODUCT(E11*18)/118 -> 0 | G11: =PRODUCT(B11*30) -> 0 | H11: =SUM(F11:G11) -> 0
A12: MADRIEN | E12: =PRODUCT(B12*C12) -> 0 | F12: =PRODUCT(E12*18)/118 -> 0 | G12: =PRODUCT(B12*30) -> 0 | H12: =SUM(F12:G12) -> 0
A13: PLANCHE | B13: 739 | C13: 1534 | E13: =PRODUCT(B13*C13) -> 1133626 | F13: =PRODUCT(E13*18)/118 -> 172926 | G13: =PRODUCT(B13*20) -> 14780 | H13: =SUM(F13:G13) -> 187706
A14: PLANCHE ZA PINUS | B14: 300 | C14: 1770 | E14: =PRODUCT(B14*C14) -> 531000 | F14: =PRODUCT(E14*18)/118 -> 81000 | G14: =PRODUCT(B14*20) -> 6000 | H14: =SUM(F14:G14) -> 87000
A15: Other Timber for Difference Price
A16: NAME OF TIMBER | B16: No OF TIMBER | C16: P/U | D16: MSF | E16: TOTAL COST | F16: VAT | G16: MSF | H16: VTA+MST
A17: IBIPANDE BYA PINUS | B17: 800 | C17: 2360 | D17: 50 | E17: =PRODUCT(B17*C17) -> 1888000 | F17: =PRODUCT(E17*18)/118 -> 288000 | G17: =PRODUCT(B17*D17) -> 40000 | H17: =SUM(F17:G17) -> 328000
A18: IBIPANDE BYA PINUS | B18: 350 | C18: 1770 | D18: 50 | E18: =PRODUCT(B18*C18) -> 619500 | F18: =PRODUCT(E18*18)/118 -> 94500 | G18: =PRODUCT(B18*D18) -> 17500 | H18: =SUM(F18:G18) -> 112000
A19: UMUSAVE | E19: =PRODUCT(B19*C19) -> 0 | F19: =PRODUCT(E19*18)/118 -> 0 | G19: =PRODUCT(B19*D19) -> 0 | H19: =SUM(F19:G19) -> 0
A20: UMUSAVE | E20: =PRODUCT(B20*C20) -> 0 | F20: =PRODUCT(E20*18)/118 -> 0 | G20: =PRODUCT(B20*D20) -> 0 | H20: =SUM(F20:G20) -> 0
A21: MADRIEN | B21: 150 | D21: 390 | E21: =PRODUCT(B21*C21) -> 0 | F21: =PRODUCT(E21*18)/118 -> 0 | G21: =PRODUCT(B21*D21) -> 58500 | H21: =SUM(F21:G21) -> 58500
A22: IMBABARI | B22: 10 | C22: 11800 | D22: 1000 | E22: =PRODUCT(B22*C22) -> 118000 | F22: =PRODUCT(E22*18)/118 -> 18000 | G22: =PRODUCT(B22*D22) -> 10000 | H22: =SUM(F22:G22) -> 28000
A23: OTHER | E23: =PRODUCT(B23*C23) -> 0 | F23: =PRODUCT(E23*18)/118 -> 0 | G23: =PRODUCT(B23*D23) -> 0 | H23: =SUM(F23:G23) -> 0
A24: OTHER | E24: =PRODUCT(B24*C24) -> 0 | F24: =PRODUCT(E24*18)/118 -> 0 | G24: =PRODUCT(B24*D24) -> 0 | H24: =SUM(F24:G24) -> 0
A25: OTHER | E25: =PRODUCT(B25*C25) -> 0 | F25: =PRODUCT(E25*18)/118 -> 0 | G25: =PRODUCT(B25*D25) -> 0 | H25: =SUM(F25:G25) -> 0
A26: OTHER | E26: =PRODUCT(B26*C26) -> 0 | F26: =PRODUCT(E26*18)/118 -> 0 | G26: =PRODUCT(B26*D26) -> 0 | H26: =SUM(F26:G26) -> 0
A27: OTHER | E27: =PRODUCT(B27*C27) -> 0 | F27: =PRODUCT(E27*18)/118 -> 0 | G27: =PRODUCT(B27*D27) -> 0 | H27: =SUM(F27:G27) -> 0
A28: OTHER | E28: =PRODUCT(B28*C28) -> 0 | F28: =PRODUCT(E28*18)/118 -> 0 | G28: =PRODUCT(B28*D28) -> 0 | H28: =SUM(F28:G28) -> 0
A29: OTHER | E29: =PRODUCT(B29*C29) -> 0 | F29: =PRODUCT(E29*18)/118 -> 0 | G29: =PRODUCT(B29*D29) -> 0 | H29: =SUM(F29:G29) -> 0
A30: OTHER | E30: =PRODUCT(B30*C30) -> 0 | F30: =PRODUCT(E30*18)/118 -> 0 | G30: =PRODUCT(B30*D30) -> 0 | H30: =SUM(F30:G30) -> 0
A31: OTHER | E31: =PRODUCT(B31*C31) -> 0 | F31: =PRODUCT(E31*18)/118 -> 0 | G31: =PRODUCT(B31*D31) -> 0 | H31: =SUM(F31:G31) -> 0
A32: OTHER | E32: =PRODUCT(B32*C32) -> 0 | F32: =PRODUCT(E32*18)/118 -> 0 | G32: =PRODUCT(B32*D32) -> 0 | H32: =SUM(F32:G32) -> 0
A33: OTHER | E33: =PRODUCT(B33*C33) -> 0 | F33: =PRODUCT(E33*18)/118 -> 0 | G33: =PRODUCT(B33*D33) -> 0 | H33: =SUM(F33:G33) -> 0
A34: OTHER | E34: =PRODUCT(B34*C34) -> 0 | F34: =PRODUCT(E34*18)/118 -> 0 | G34: =PRODUCT(B34*D34) -> 0 | H34: =SUM(F34:G34) -> 0
... A36: OTHER | E36: =PRODUCT(B36*C36) -> 0 | F36: =PRODUCT(E36*18)/118 -> 0 | G36: =PRODUCT(B36*D36) -> 0 | H36: =SUM(F36:G36) -> 0
A37: TOTALY | E37: =SUM(E5:E36) -> 31801826 | F37: =SUM(F5:F36) -> 4851126 | G37: =SUM(G5:G36) -> 487130 | H37: =SUM(H5:H36) -> 5338256
A38: SUMMARY | C38: RWF | E38: NAME | G38: Phone | H38: RWF
A39: TOTAL RWF PAID ON MOMO PAY | C39: 4838256
A40: TOTAL RWF PAID ON CASH
A41: AMOUNT NOT INVOICED
A42: TOTAL RWF DEPPOSITED ON BANK | C42: 500000
A43: MEMBERSHIP FEES REGISTRETION
A44: MEMBERSHIP FEES CONTRIBUTION
A45: TOTAL INCOME | C45: =SUM(C39+C40+C41+C42+C43+C44) -> 5338256
A46: TIMBER SUMMARY
A48: REPORT SUMMARY | C48: TIMBER TYPE | E48: NUMBER OF QUANTITY
C49: INTURUSU | E49: =SUM(B9:B12) -> 11095
C50: PINUS | E50: =SUM(B6:B8) -> 150
C51: PALNCHE | E51: =SUM(B13:B14) -> 1039
C52: IBIPANDE | E52: =SUM(B17:B18) -> 1150
C53: UMUSAVE | E53: =SUM(B19:B20) -> 0
C54: OTHER | E54: =B29 -> 0
C55: OTHER | E55: =B30 -> 0
C56: OTHER | E56: =B31 -> 0
C57: OTHER | E57: =B32 -> 0
C58: OTHER | E58: =B33 -> 0
C59: OTHER | E59: =B34 -> 0
C60: OTHER | E60: =B35 -> 0
C61: OTHER | E61: =B36 -> 0
C62: TOTAL TIMBER | E62: =SUM(E49:H61) -> 13434

Sheet MUSANZE
A1: QUANTITY REPORT
A3: MONTHS REPORT OF APRIL 2026
A5: NAME OF TIMBER | B5: No OF TIMBER | C5: PRICE OF TIMBER | E5: TOTAL COST | F5: TVA | G5: MSF | H5: TVA+MSF
A6: PINUS NINI | C6: 8850 | E6: =PRODUCT(B6*C6) -> 0 | F6: =PRODUCT(E6*18)/118 -> 0 | G6: =PRODUCT(B6*50) -> 0 | H6: =SUM(F6:G6) -> 0
A7: PINUS NTOYA | C7: 5950 | E7: =PRODUCT(B7*C7) -> 0 | F7: =PRODUCT(E7*18)/118 -> 0 | G7: =PRODUCT(B7*50) -> 0 | H7: =SUM(F7:G7) -> 0
A8: PINUS | E8: =PRODUCT(B8*C8) -> 0 | F8: =PRODUCT(E8*18)/118 -> 0 | G8: =PRODUCT(B8*50) -> 0 | H8: =SUM(F8:G8) -> 0
A9: MADIRIYE NINI | C9: 3000 | E9: =PRODUCT(B9*C9) -> 0 | F9: =PRODUCT(E9*18)/118 -> 0 | G9: =PRODUCT(B9*30) -> 0 | H9: =SUM(F9:G9) -> 0
A10: MADIRIYE NTOYA | B10: 6730 | C10: 2124 | E10: =PRODUCT(B10*C10) -> 14294520 | F10: =PRODUCT(E10*18)/118 -> 2180520 | G10: =PRODUCT(B10*30) -> 201900 | H10: =SUM(F10:G10) -> 2382420
A11: MADRIEN | E11: =PRODUCT(B11*C11) -> 0 | F11: =PRODUCT(E11*18)/118 -> 0 | G11: =PRODUCT(B11*30) -> 0 | H11: =SUM(F11:G11) -> 0
A12: MADRIEN | E12: =PRODUCT(B12*C12) -> 0 | F12: =PRODUCT(E12*18)/118 -> 0 | G12: =PRODUCT(B12*30) -> 0 | H12: =SUM(F12:G12) -> 0
A13: PLANCHE | B13: 700 | C13: 944 | E13: =PRODUCT(B13*C13) -> 660800 | F13: =PRODUCT(E13*18)/118 -> 100800 | G13: =PRODUCT(B13*20) -> 14000 | H13: =SUM(F13:G13) -> 114800
A14: GEREVERIA | B14: 860 | C14: 1180 | E14: =PRODUCT(B14*C14) -> 1014800 | F14: =PRODUCT(E14*18)/118 -> 154800 | G14: =PRODUCT(B14*20) -> 17200 | H14: =SUM(F14:G14) -> 172000
A15: Other Timber for Difference Price
A16: NAME OF TIMBER | B16: No OF TIMBER | C16: P/U | D16: MSF | E16: TOTAL COST | F16: VAT | G16: MSF | H16: VTA+MST
A17: IBIPANDE | C17: 2360 | D17: 25 | E17: =PRODUCT(B17*C17) -> 0 | F17: =PRODUCT(E17*18)/118 -> 0 | G17: =PRODUCT(B17*D17) -> 0 | H17: =SUM(F17:G17) -> 0
A18: IBIPANDE BITOYA | B18: 1720 | C18: 1770 | D18: 25 | E18: =PRODUCT(B18*C18) -> 3044400 | F18: =PRODUCT(E18*18)/118 -> 464400 | G18: =PRODUCT(B18*D18) -> 43000 | H18: =SUM(F18:G18) -> 507400
A19: UMUSAVE | E19: =PRODUCT(B19*C19) -> 0 | F19: =PRODUCT(E19*18)/118 -> 0 | G19: =PRODUCT(B19*D19) -> 0 | H19: =SUM(F19:G19) -> 0
A20: UMUSAVE | E20: =PRODUCT(B20*C20) -> 0 | F20: =PRODUCT(E20*18)/118 -> 0 | G20: =PRODUCT(B20*D20) -> 0 | H20: =SUM(F20:G20) -> 0
A21: OTHER | B21: 10 | C21: 2500 | D21: 20 | E21: =PRODUCT(B21*C21) -> 25000 | F21: =PRODUCT(E21*18)/118 -> 3813.5593 | G21: =PRODUCT(B21*D21) -> 200 | H21: =SUM(F21:G21) -> 4013.5593
A22: OTHER | B22: 1 | D22: 16800 | E22: =PRODUCT(B22*C22) -> 0 | F22: =PRODUCT(E22*18)/118 -> 0 | G22: =PRODUCT(B22*D22) -> 16800 | H22: =SUM(F22:G22) -> 16800
A23: OTHER | B23: 1 | D23: 44466 | E23: =PRODUCT(B23*C23) -> 0 | F23: =PRODUCT(E23*18)/118 -> 0 | G23: =PRODUCT(B23*D23) -> 44466 | H23: =SUM(F23:G23) -> 44466
A24: OTHER | D24: 354 | E24: =PRODUCT(B24*C24) -> 0 | F24: =PRODUCT(E24*18)/118 -> 0 | G24: =PRODUCT(B24*D24) -> 0 | H24: =SUM(F24:G24) -> 0
A25: OTHER | D25: 354 | E25: =PRODUCT(B25*C25) -> 0 | F25: =PRODUCT(E25*18)/118 -> 0 | G25: =PRODUCT(B25*D25) -> 0 | H25: =SUM(F25:G25) -> 0
A26: OTHER | E26: =PRODUCT(B26*C26) -> 0 | F26: =PRODUCT(E26*18)/118 -> 0 | G26: =PRODUCT(B26*D26) -> 0 | H26: =SUM(F26:G26) -> 0
A27: OTHER | E27: =PRODUCT(B27*C27) -> 0 | F27: =PRODUCT(E27*18)/118 -> 0 | G27: =PRODUCT(B27*D27) -> 0 | H27: =SUM(F27:G27) -> 0
A28: OTHER | E28: =PRODUCT(B28*C28) -> 0 | F28: =PRODUCT(E28*18)/118 -> 0 | G28: =PRODUCT(B28*D28) -> 0 | H28: =SUM(F28:G28) -> 0
A29: OTHER | E29: =PRODUCT(B29*C29) -> 0 | F29: =PRODUCT(E29*18)/118 -> 0 | G29: =PRODUCT(B29*D29) -> 0 | H29: =SUM(F29:G29) -> 0
A30: OTHER | E30: =PRODUCT(B30*C30) -> 0 | F30: =PRODUCT(E30*18)/118 -> 0 | G30: =PRODUCT(B30*D30) -> 0 | H30: =SUM(F30:G30) -> 0
A31: OTHER | E31: =PRODUCT(B31*C31) -> 0 | F31: =PRODUCT(E31*18)/118 -> 0 | G31: =PRODUCT(B31*D31) -> 0 | H31: =SUM(F31:G31) -> 0
A32: OTHER | E32: =PRODUCT(B32*C32) -> 0 | F32: =PRODUCT(E32*18)/118 -> 0 | G32: =PRODUCT(B32*D32) -> 0 | H32: =SUM(F32:G32) -> 0
A33: OTHER | E33: =PRODUCT(B33*C33) -> 0 | F33: =PRODUCT(E33*18)/118 -> 0 | G33: =PRODUCT(B33*D33) -> 0 | H33: =SUM(F33:G33) -> 0
A34: OTHER | E34: =PRODUCT(B34*C34) -> 0 | F34: =PRODUCT(E34*18)/118 -> 0 | G34: =PRODUCT(B34*D34) -> 0 | H34: =SUM(F34:G34) -> 0
A35: OTHER | E35: =PRODUCT(B35*C35) -> 0 | F35: =PRODUCT(E35*18)/118 -> 0 | G35: =PRODUCT(B35*D35) -> 0 | H35: =SUM(F35:G35) -> 0
A36: OTHER | E36: =PRODUCT(B36*C36) -> 0 | F36: =PRODUCT(E36*18)/118 -> 0 | G36: =PRODUCT(B36*D36) -> 0 | H36: =SUM(F36:G36) -> 0
A37: TOTALY | E37: =SUM(E5:E36) -> 19039520 | F37: =SUM(F5:F36) -> 2904333.6 | G37: =SUM(G5:G36) -> 337566 | H37: =SUM(H5:H36) -> 3241899.6
A38: SUMMARY | C38: RWF | E38: NAME | G38: Phone | H38: RWF
A39: TOTAL RWF PAID ON MOMO PAY | C39: 2093880
A40: TOTAL RWF PAID ON CASH | C40: 1148020
A41: AMOUNT NOT INVOICED
A42: TOTAL RWF DEPPOSITED ON BANK
A43: MEMBERSHIP FEES REGISTRETION
A44: MEMBERSHIP FEES CONTRIBUTION
A45: TOTAL INCOME | C45: =SUM(C39+C40+C41+C42+C43+C44) -> 3241900
A46: TIMBER SUMMARY
A48: REPORT SUMMARY | C48: TIMBER TYPE | E48: NUMBER OF QUANTITY
C49: INTURUSU | E49: =SUM(B9:B12) -> 6730
C50: PINUS | E50: =SUM(B6:B8) -> 0
C51: PALNCHE | E51: =SUM(B13:B14) -> 1560
C52: IBIPANDE | E52: =SUM(B17:B18) -> 1720
C53: UMUSAVE | E53: =SUM(B19:B20) -> 0
C54: OTHER | E54: =B29 -> 0
C55: OTHER | E55: =B30 -> 0
C56: OTHER | E56: =B31 -> 0
C57: OTHER | E57: =B32 -> 0
C58: OTHER | E58: =B33 -> 0
C59: OTHER | E59: =B34 -> 0
C60: OTHER | E60: =B35 -> 0
C61: OTHER | E61: =B36 -> 0
C62: TOTAL TIMBER | E62: =SUM(E49:H61) -> 10010

Sheet NYAGATARE
A1: QUANTITY REPORT
A3: MONTHS REPORT OF APRIL 2026
A5: NAME OF TIMBER | B5: No OF TIMBER | C5: PRICE OF TIMBER | E5: TOTAL COST | F5: TVA | G5: MSF | H5: TVA+MSF
A6: MADRIEN | B6: 2812 | C6: 2124 | E6: =PRODUCT(B6*C6) -> 5972688 | F6: =PRODUCT(E6*18)/118 -> 911088 | G6: =PRODUCT(B6*50) -> 140600 | H6: =SUM(F6:G6) -> 1051688
A7: MADRIEN | B7: 410 | C7: 2000 | E7: =PRODUCT(B7*C7) -> 820000 | F7: =PRODUCT(E7*18)/118 -> 125084.75 | G7: =PRODUCT(B7*50) -> 20500 | H7: =SUM(F7:G7) -> 145584.75
A8: MADRIEN | B8: 4176 | E8: =PRODUCT(B8*C8) -> 0 | F8: =PRODUCT(E8*18)/118 -> 0 | G8: =PRODUCT(B8*50) -> 208800 | H8: =SUM(F8:G8) -> 208800
A9: GEREVERIA | B9: 110 | C9: 1180 | E9: =PRODUCT(B9*C9) -> 129800 | F9: =PRODUCT(E9*18)/118 -> 19800 | G9: =PRODUCT(B9*30) -> 3300 | H9: =SUM(F9:G9) -> 23100
A10: MADIRIYE NTOYA | E10: =PRODUCT(B10*C10) -> 0 | F10: =PRODUCT(E10*18)/118 -> 0 | G10: =PRODUCT(B10*30) -> 0 | H10: =SUM(F10:G10) -> 0
A11: MADRIEN | E11: =PRODUCT(B11*C11) -> 0 | F11: =PRODUCT(E11*18)/118 -> 0 | G11: =PRODUCT(B11*30) -> 0 | H11: =SUM(F11:G11) -> 0
A12: MADRIEN | E12: =PRODUCT(B12*C12) -> 0 | F12: =PRODUCT(E12*18)/118 -> 0 | G12: =PRODUCT(B12*30) -> 0 | H12: =SUM(F12:G12) -> 0
A13: PLANCHE | E13: =PRODUCT(B13*C13) -> 0 | F13: =PRODUCT(E13*18)/118 -> 0 | G13: =PRODUCT(B13*20) -> 0 | H13: =SUM(F13:G13) -> 0
A14: PLANCHE | E14: =PRODUCT(B14*C14) -> 0 | F14: =PRODUCT(E14*18)/118 -> 0 | G14: =PRODUCT(B14*20) -> 0 | H14: =SUM(F14:G14) -> 0
A15: Other Timber for Difference Price
A16: NAME OF TIMBER | B16: No OF TIMBER | C16: P/U | D16: MSF | E16: TOTAL COST | F16: VAT | G16: MSF | H16: VTA+MST
A17: MADRIEN | C17: 2124 | D17: 50 | E17: =PRODUCT(B17*C17) -> 0 | F17: =PRODUCT(E17*18)/118 -> 0 | G17: =PRODUCT(B17*D17) -> 0 | H17: =SUM(F17:G17) -> 0
A18: INTURUSU NTOYA | C18: 2000 | D18: 50 | E18: =PRODUCT(B18*C18) -> 0 | F18: =PRODUCT(E18*18)/118 -> 0 | G18: =PRODUCT(B18*D18) -> 0 | H18: =SUM(F18:G18) -> 0
A19: GEREVERIA | C19: 1180 | D19: 30 | E19: =PRODUCT(B19*C19) -> 0 | F19: =PRODUCT(E19*18)/118 -> 0 | G19: =PRODUCT(B19*D19) -> 0 | H19: =SUM(F19:G19) -> 0
A20: UMUSAVE | E20: =PRODUCT(B20*C20) -> 0 | F20: =PRODUCT(E20*18)/118 -> 0 | G20: =PRODUCT(B20*D20) -> 0 | H20: =SUM(F20:G20) -> 0
A21: PLANCHE | B21: 489 | D21: 50 | E21: =PRODUCT(B21*C21) -> 0 | F21: =PRODUCT(E21*18)/118 -> 0 | G21: =PRODUCT(B21*D21) -> 24450 | H21: =SUM(F21:G21) -> 24450
A22: OTHER | E22: =PRODUCT(B22*C22) -> 0 | F22: =PRODUCT(E22*18)/118 -> 0 | G22: =PRODUCT(B22*D22) -> 0 | H22: =SUM(F22:G22) -> 0
A23: OTHER | E23: =PRODUCT(B23*C23) -> 0 | F23: =PRODUCT(E23*18)/118 -> 0 | G23: =PRODUCT(B23*D23) -> 0 | H23: =SUM(F23:G23) -> 0
A24: OTHER | E24: =PRODUCT(B24*C24) -> 0 | F24: =PRODUCT(E24*18)/118 -> 0 | G24: =PRODUCT(B24*D24) -> 0 | H24: =SUM(F24:G24) -> 0
A25: OTHER | E25: =PRODUCT(B25*C25) -> 0 | F25: =PRODUCT(E25*18)/118 -> 0 | G25: =PRODUCT(B25*D25) -> 0 | H25: =SUM(F25:G25) -> 0
A26: OTHER | E26: =PRODUCT(B26*C26) -> 0 | F26: =PRODUCT(E26*18)/118 -> 0 | G26: =PRODUCT(B26*D26) -> 0 | H26: =SUM(F26:G26) -> 0
A27: OTHER | E27: =PRODUCT(B27*C27) -> 0 | F27: =PRODUCT(E27*18)/118 -> 0 | G27: =PRODUCT(B27*D27) -> 0 | H27: =SUM(F27:G27) -> 0
A28: OTHER | E28: =PRODUCT(B28*C28) -> 0 | F28: =PRODUCT(E28*18)/118 -> 0 | G28: =PRODUCT(B28*D28) -> 0 | H28: =SUM(F28:G28) -> 0
A29: OTHER | E29: =PRODUCT(B29*C29) -> 0 | F29: =PRODUCT(E29*18)/118 -> 0 | G29: =PRODUCT(B29*D29) -> 0 | H29: =SUM(F29:G29) -> 0
A30: OTHER | E30: =PRODUCT(B30*C30) -> 0 | F30: =PRODUCT(E30*18)/118 -> 0 | G30: =PRODUCT(B30*D30) -> 0 | H30: =SUM(F30:G30) -> 0
A31: OTHER | E31: =PRODUCT(B31*C31) -> 0 | F31: =PRODUCT(E31*18)/118 -> 0 | G31: =PRODUCT(B31*D31) -> 0 | H31: =SUM(F31:G31) -> 0
A32: OTHER | E32: =PRODUCT(B32*C32) -> 0 | F32: =PRODUCT(E32*18)/118 -> 0 | G32: =PRODUCT(B32*D32) -> 0 | H32: =SUM(F32:G32) -> 0
A33: OTHER | E33: =PRODUCT(B33*C33) -> 0 | F33: =PRODUCT(E33*18)/118 -> 0 | G33: =PRODUCT(B33*D33) -> 0 | H33: =SUM(F33:G33) -> 0
... A36: OTHER | E36: =PRODUCT(B36*C36) -> 0 | F36: =PRODUCT(E36*18)/118 -> 0 | G36: =PRODUCT(B36*D36) -> 0 | H36: =SUM(F36:G36) -> 0
A37: TOTALY | E37: =SUM(E5:E36) -> 6922488 | F37: =SUM(F5:F36) -> 1055972.7 | G37: =SUM(G5:G36) -> 397650 | H37: =SUM(H5:H36) -> 1453622.7
A38: SUMMARY | C38: RWF | E38: NAME | G38: Phone | H38: RWF
A39: TOTAL RWF PAID ON MOMO PAY | C39: 1521032
A40: TOTAL RWF PAID ON CASH
A41: AMOUNT NOT INVOICED
A42: TOTAL RWF DEPPOSITED ON BANK
A43: MEMBERSHIP FEES REGISTRETION
A44: MEMBERSHIP FEES CONTRIBUTION
A45: TOTAL INCOME | C45: =SUM(C39+C40+C41+C42+C43+C44) -> 1521032
A46: TIMBER SUMMARY
A48: REPORT SUMMARY | C48: TIMBER TYPE | E48: NUMBER OF QUANTITY
C49: INTURUSU | E49: =SUM(B9:B12) -> 110
C50: PINUS | E50: =SUM(B6:B8) -> 7398
C51: PALNCHE | E51: =SUM(B13:B14) -> 0
C52: IBIPANDE | E52: =SUM(B17:B18) -> 0
C53: UMUSAVE | E53: =SUM(B19:B20) -> 0
C54: OTHER | E54: =B29 -> 0
C55: OTHER | E55: =B30 -> 0
C56: OTHER | E56: =B31 -> 0
C57: OTHER | E57: =B32 -> 0
C58: OTHER | E58: =B33 -> 0
C59: OTHER | E59: =B34 -> 0
C60: OTHER | E60: =B35 -> 0
C61: OTHER | E61: =B36 -> 0
C62: TOTAL TIMBER | E62: =SUM(E49:H61) -> 7508

Sheet KIREHE
A1: QUANTITY REPORT
A3: MONTHS REPORT OF APRIL 2026
A5: NAME OF TIMBER | B5: No OF TIMBER | C5: PRICE OF TIMBER | E5: TOTAL COST | F5: TVA | G5: MSF | H5: TVA+MSF
A6: PINUS NINI | E6: =PRODUCT(B6*C6) -> 0 | F6: =PRODUCT(E6*18)/118 -> 0 | G6: =PRODUCT(B6*50) -> 0 | H6: =SUM(F6:G6) -> 0
A7: PINUS NTOYA | E7: =PRODUCT(B7*C7) -> 0 | F7: =PRODUCT(E7*18)/118 -> 0 | G7: =PRODUCT(B7*50) -> 0 | H7: =SUM(F7:G7) -> 0
A8: MADRIEN | B8: 200 | C8: 2360 | E8: =PRODUCT(B8*C8) -> 472000 | F8: =PRODUCT(E8*18)/118 -> 72000 | G8: =PRODUCT(B8*50) -> 10000 | H8: =SUM(F8:G8) -> 82000
A9: MADIRIYE NINI | E9: =PRODUCT(B9*C9) -> 0 | F9: =PRODUCT(E9*18)/118 -> 0 | G9: =PRODUCT(B9*30) -> 0 | H9: =SUM(F9:G9) -> 0
A10: MADIRIYE NTOYA | B10: 4407 | C10: 2124 | E10: =PRODUCT(B10*C10) -> 9360468 | F10: =PRODUCT(E10*18)/118 -> 1427868 | G10: =PRODUCT(B10*30) -> 132210 | H10: =SUM(F10:G10) -> 1560078
A11: MADRIEN | E11: =PRODUCT(B11*C11) -> 0 | F11: =PRODUCT(E11*18)/118 -> 0 | G11: =PRODUCT(B11*30) -> 0 | H11: =SUM(F11:G11) -> 0
A12: MADRIEN | E12: =PRODUCT(B12*C12) -> 0 | F12: =PRODUCT(E12*18)/118 -> 0 | G12: =PRODUCT(B12*30) -> 0 | H12: =SUM(F12:G12) -> 0
A13: PLANCHE | E13: =PRODUCT(B13*C13) -> 0 | F13: =PRODUCT(E13*18)/118 -> 0 | G13: =PRODUCT(B13*20) -> 0 | H13: =SUM(F13:G13) -> 0
A14: PLANCHE | E14: =PRODUCT(B14*C14) -> 0 | F14: =PRODUCT(E14*18)/118 -> 0 | G14: =PRODUCT(B14*20) -> 0 | H14: =SUM(F14:G14) -> 0
A15: Other Timber for Difference Price
A16: NAME OF TIMBER | B16: No OF TIMBER | C16: P/U | D16: MSF | E16: TOTAL COST | F16: VAT | G16: MSF | H16: VTA+MST
A17: IBIPANDE | B17: 484 | C17: 1000 | D17: 30 | E17: =PRODUCT(B17*C17) -> 484000 | F17: =PRODUCT(E17*18)/118 -> 73830.508 | G17: =PRODUCT(B17*D17) -> 14520 | H17: =SUM(F17:G17) -> 88350.508
A18: IBIPANDE | B18: 930 | C18: 1180 | D18: 30 | E18: =PRODUCT(B18*C18) -> 1097400 | F18: =PRODUCT(E18*18)/118 -> 167400 | G18: =PRODUCT(B18*D18) -> 27900 | H18: =SUM(F18:G18) -> 195300
A19: GEREVERIA | C19: 1180 | D19: 30 | E19: =PRODUCT(B19*C19) -> 0 | F19: =PRODUCT(E19*18)/118 -> 0 | G19: =PRODUCT(B19*D19) -> 0 | H19: =SUM(F19:G19) -> 0
A20: PLANCHE | B20: 69 | C20: 1534 | D20: 30 | E20: =PRODUCT(B20*C20) -> 105846 | F20: =PRODUCT(E20*18)/118 -> 16146 | G20: =PRODUCT(B20*D20) -> 2070 | H20: =SUM(F20:G20) -> 18216
A21: OTHER | E21: =PRODUCT(B21*C21) -> 0 | F21: =PRODUCT(E21*18)/118 -> 0 | G21: =PRODUCT(B21*D21) -> 0 | H21: =SUM(F21:G21) -> 0
A22: OTHER | B22: 1 | C22: 1 | D22: 157584 | E22: =PRODUCT(B22*C22) -> 1 | F22: =PRODUCT(E22*18)/118 -> 0.15254237 | G22: =PRODUCT(B22*D22) -> 157584 | H22: =SUM(F22:G22) -> 157584.15
A23: OTHER | E23: =PRODUCT(B23*C23) -> 0 | F23: =PRODUCT(E23*18)/118 -> 0 | G23: =PRODUCT(B23*D23) -> 0 | H23: =SUM(F23:G23) -> 0
A24: OTHER | E24: =PRODUCT(B24*C24) -> 0 | F24: =PRODUCT(E24*18)/118 -> 0 | G24: =PRODUCT(B24*D24) -> 0 | H24: =SUM(F24:G24) -> 0
A25: OTHER | E25: =PRODUCT(B25*C25) -> 0 | F25: =PRODUCT(E25*18)/118 -> 0 | G25: =PRODUCT(B25*D25) -> 0 | H25: =SUM(F25:G25) -> 0
A26: OTHER | E26: =PRODUCT(B26*C26) -> 0 | F26: =PRODUCT(E26*18)/118 -> 0 | G26: =PRODUCT(B26*D26) -> 0 | H26: =SUM(F26:G26) -> 0
A27: OTHER | E27: =PRODUCT(B27*C27) -> 0 | F27: =PRODUCT(E27*18)/118 -> 0 | G27: =PRODUCT(B27*D27) -> 0 | H27: =SUM(F27:G27) -> 0
A28: OTHER | E28: =PRODUCT(B28*C28) -> 0 | F28: =PRODUCT(E28*18)/118 -> 0 | G28: =PRODUCT(B28*D28) -> 0 | H28: =SUM(F28:G28) -> 0
A29: OTHER | E29: =PRODUCT(B29*C29) -> 0 | F29: =PRODUCT(E29*18)/118 -> 0 | G29: =PRODUCT(B29*D29) -> 0 | H29: =SUM(F29:G29) -> 0
A30: OTHER | E30: =PRODUCT(B30*C30) -> 0 | F30: =PRODUCT(E30*18)/118 -> 0 | G30: =PRODUCT(B30*D30) -> 0 | H30: =SUM(F30:G30) -> 0
A31: OTHER | E31: =PRODUCT(B31*C31) -> 0 | F31: =PRODUCT(E31*18)/118 -> 0 | G31: =PRODUCT(B31*D31) -> 0 | H31: =SUM(F31:G31) -> 0
A32: OTHER | E32: =PRODUCT(B32*C32) -> 0 | F32: =PRODUCT(E32*18)/118 -> 0 | G32: =PRODUCT(B32*D32) -> 0 | H32: =SUM(F32:G32) -> 0
A33: OTHER | E33: =PRODUCT(B33*C33) -> 0 | F33: =PRODUCT(E33*18)/118 -> 0 | G33: =PRODUCT(B33*D33) -> 0 | H33: =SUM(F33:G33) -> 0
A34: OTHER | E34: =PRODUCT(B34*C34) -> 0 | F34: =PRODUCT(E34*18)/118 -> 0 | G34: =PRODUCT(B34*D34) -> 0 | H34: =SUM(F34:G34) -> 0
... A36: OTHER | E36: =PRODUCT(B36*C36) -> 0 | F36: =PRODUCT(E36*18)/118 -> 0 | G36: =PRODUCT(B36*D36) -> 0 | H36: =SUM(F36:G36) -> 0
A37: TOTALY | E37: =SUM(E5:E36) -> 11519715 | F37: =SUM(F5:F36) -> 1757244.7 | G37: =SUM(G5:G36) -> 344284 | H37: =SUM(H5:H36) -> 2101528.7
A38: SUMMARY | C38: RWF | E38: NAME | G38: Phone | H38: RWF
A39: TOTAL RWF PAID ON MOMO PAY | C39: 2101529
A40: TOTAL RWF PAID ON CASH
A41: AMOUNT NOT INVOICED
A42: TOTAL RWF DEPPOSITED ON BANK
A43: MEMBERSHIP FEES REGISTRETION
A44: MEMBERSHIP FEES CONTRIBUTION
A45: TOTAL INCOME | C45: =SUM(C39+C40+C41+C42+C43+C44) -> 2101529
A46: TIMBER SUMMARY
A48: REPORT SUMMARY | C48: TIMBER TYPE | E48: NUMBER OF QUANTITY
C49: INTURUSU | E49: =SUM(B9:B12) -> 4407
C50: PINUS | E50: =SUM(B6:B8) -> 200
C51: PALNCHE | E51: =SUM(B13:B14) -> 0
C52: IBIPANDE | E52: =SUM(B17:B18) -> 1414
C53: UMUSAVE | E53: =SUM(B19:B20) -> 69
C54: OTHER | E54: =B29 -> 0
C55: OTHER | E55: =B30 -> 0
C56: OTHER | E56: =B31 -> 0
C57: OTHER | E57: =B32 -> 0
C58: OTHER | E58: =B33 -> 0
C59: OTHER | E59: =B34 -> 0
C60: OTHER | E60: =B35 -> 0
C61: OTHER | E61: =B36 -> 0
C62: TOTAL TIMBER | E62: =SUM(E49:H61) -> 6090

Sheet NYANZA
A1: QUANTITY REPORT
A3: MONTHS REPORT OF APRIL 2026
A5: NAME OF TIMBER | B5: No OF TIMBER | C5: PRICE OF TIMBER | E5: TOTAL COST | F5: TVA | G5: MSF | H5: TVA+MSF
A6: PINUS NINI | E6: =PRODUCT(B6*C6) -> 0 | F6: =PRODUCT(E6*18)/118 -> 0 | G6: =PRODUCT(B6*50) -> 0 | H6: =SUM(F6:G6) -> 0
A7: PINUS NTOYA | E7: =PRODUCT(B7*C7) -> 0 | F7: =PRODUCT(E7*18)/118 -> 0 | G7: =PRODUCT(B7*50) -> 0 | H7: =SUM(F7:G7) -> 0
A8: IBIPANDE BYA PINUS | C8: 2500 | E8: =PRODUCT(B8*C8) -> 0 | F8: =PRODUCT(E8*18)/118 -> 0 | G8: =PRODUCT(B8*50) -> 0 | H8: =SUM(F8:G8) -> 0
A9: MADIRIYE NINI | E9: =PRODUCT(B9*C9) -> 0 | F9: =PRODUCT(E9*18)/118 -> 0 | G9: =PRODUCT(B9*30) -> 0 | H9: =SUM(F9:G9) -> 0
A10: MADIRIYE NTOYA | B10: 1150 | C10: 1800 | E10: =PRODUCT(B10*C10) -> 2070000 | F10: =PRODUCT(E10*18)/118 -> 315762.71 | G10: =PRODUCT(B10*30) -> 34500 | H10: =SUM(F10:G10) -> 350262.71
A11: MADRIEN | B11: 600 | C11: 2200 | E11: =PRODUCT(B11*C11) -> 1320000 | F11: =PRODUCT(E11*18)/118 -> 201355.93 | G11: =PRODUCT(B11*30) -> 18000 | H11: =SUM(F11:G11) -> 219355.93
A12: MADRIEN | E12: =PRODUCT(B12*C12) -> 0 | F12: =PRODUCT(E12*18)/118 -> 0 | G12: =PRODUCT(B12*30) -> 0 | H12: =SUM(F12:G12) -> 0
A13: PLANCHE | E13: =PRODUCT(B13*C13) -> 0 | F13: =PRODUCT(E13*18)/118 -> 0 | G13: =PRODUCT(B13*20) -> 0 | H13: =SUM(F13:G13) -> 0
A14: PLANCHE | E14: =PRODUCT(B14*C14) -> 0 | F14: =PRODUCT(E14*18)/118 -> 0 | G14: =PRODUCT(B14*20) -> 0 | H14: =SUM(F14:G14) -> 0
A15: Other Timber for Difference Price
A16: NAME OF TIMBER | B16: No OF TIMBER | C16: P/U | D16: MSF | E16: TOTAL COST | F16: VAT | G16: MSF | H16: VTA+MST
A17: IBIPANDE | C17: 800 | D17: 20 | E17: =PRODUCT(B17*C17) -> 0 | F17: =PRODUCT(E17*18)/118 -> 0 | G17: =PRODUCT(B17*D17) -> 0 | H17: =SUM(F17:G17) -> 0
A18: IBIPANDE | E18: =PRODUCT(B18*C18) -> 0 | F18: =PRODUCT(E18*18)/118 -> 0 | G18: =PRODUCT(B18*D18) -> 0 | H18: =SUM(F18:G18) -> 0
A19: UMUSAVE | E19: =PRODUCT(B19*C19) -> 0 | F19: =PRODUCT(E19*18)/118 -> 0 | G19: =PRODUCT(B19*D19) -> 0 | H19: =SUM(F19:G19) -> 0
A20: UMUSAVE | E20: =PRODUCT(B20*C20) -> 0 | F20: =PRODUCT(E20*18)/118 -> 0 | G20: =PRODUCT(B20*D20) -> 0 | H20: =SUM(F20:G20) -> 0
A21: OTHER | B21: 2987 | D21: 50 | E21: =PRODUCT(B21*C21) -> 0 | F21: =PRODUCT(E21*18)/118 -> 0 | G21: =PRODUCT(B21*D21) -> 149350 | H21: =SUM(F21:G21) -> 149350
A22: OTHER | E22: =PRODUCT(B22*C22) -> 0 | F22: =PRODUCT(E22*18)/118 -> 0 | G22: =PRODUCT(B22*D22) -> 0 | H22: =SUM(F22:G22) -> 0
A23: OTHER | E23: =PRODUCT(B23*C23) -> 0 | F23: =PRODUCT(E23*18)/118 -> 0 | G23: =PRODUCT(B23*D23) -> 0 | H23: =SUM(F23:G23) -> 0
A24: OTHER | E24: =PRODUCT(B24*C24) -> 0 | F24: =PRODUCT(E24*18)/118 -> 0 | G24: =PRODUCT(B24*D24) -> 0 | H24: =SUM(F24:G24) -> 0
A25: OTHER | E25: =PRODUCT(B25*C25) -> 0 | F25: =PRODUCT(E25*18)/118 -> 0 | G25: =PRODUCT(B25*D25) -> 0 | H25: =SUM(F25:G25) -> 0
A26: OTHER | E26: =PRODUCT(B26*C26) -> 0 | F26: =PRODUCT(E26*18)/118 -> 0 | G26: =PRODUCT(B26*D26) -> 0 | H26: =SUM(F26:G26) -> 0
A27: OTHER | E27: =PRODUCT(B27*C27) -> 0 | F27: =PRODUCT(E27*18)/118 -> 0 | G27: =PRODUCT(B27*D27) -> 0 | H27: =SUM(F27:G27) -> 0
A28: OTHER | E28: =PRODUCT(B28*C28) -> 0 | F28: =PRODUCT(E28*18)/118 -> 0 | G28: =PRODUCT(B28*D28) -> 0 | H28: =SUM(F28:G28) -> 0
A29: OTHER | E29: =PRODUCT(B29*C29) -> 0 | F29: =PRODUCT(E29*18)/118 -> 0 | G29: =PRODUCT(B29*D29) -> 0 | H29: =SUM(F29:G29) -> 0
A30: OTHER | E30: =PRODUCT(B30*C30) -> 0 | F30: =PRODUCT(E30*18)/118 -> 0 | G30: =PRODUCT(B30*D30) -> 0 | H30: =SUM(F30:G30) -> 0
A31: OTHER | E31: =PRODUCT(B31*C31) -> 0 | F31: =PRODUCT(E31*18)/118 -> 0 | G31: =PRODUCT(B31*D31) -> 0 | H31: =SUM(F31:G31) -> 0
A32: OTHER | E32: =PRODUCT(B32*C32) -> 0 | F32: =PRODUCT(E32*18)/118 -> 0 | G32: =PRODUCT(B32*D32) -> 0 | H32: =SUM(F32:G32) -> 0
A33: OTHER | E33: =PRODUCT(B33*C33) -> 0 | F33: =PRODUCT(E33*18)/118 -> 0 | G33: =PRODUCT(B33*D33) -> 0 | H33: =SUM(F33:G33) -> 0
... A36: OTHER | E36: =PRODUCT(B36*C36) -> 0 | F36: =PRODUCT(E36*18)/118 -> 0 | G36: =PRODUCT(B36*D36) -> 0 | H36: =SUM(F36:G36) -> 0
A37: TOTALY | E37: =SUM(E5:E36) -> 3390000 | F37: =SUM(F5:F36) -> 517118.64 | G37: =SUM(G5:G36) -> 201850 | H37: =SUM(H5:H36) -> 718968.64
A38: SUMMARY | C38: RWF | E38: NAME | G38: Phone | H38: RWF
A39: TOTAL RWF PAID ON MOMO PAY | C39: 718369
A40: TOTAL RWF PAID ON CASH
A41: AMOUNT NOT INVOICED
A42: TOTAL RWF DEPPOSITED ON BANK
A43: MEMBERSHIP FEES REGISTRETION
A44: MEMBERSHIP FEES CONTRIBUTION
A45: TOTAL INCOME | C45: =SUM(C39+C40+C41+C42+C43+C44) -> 718369
A46: TIMBER SUMMARY
A48: REPORT SUMMARY | C48: TIMBER TYPE | E48: NUMBER OF QUANTITY
C49: INTURUSU | E49: =SUM(B9:B12) -> 1750
C50: PINUS | E50: =SUM(B6:B8) -> 0
C51: PALNCHE | E51: =SUM(B13:B14) -> 0
C52: IBIPANDE | E52: =SUM(B17:B18) -> 0
C53: UMUSAVE | E53: =SUM(B19:B20) -> 0
C54: OTHER | E54: =B29 -> 0
C55: OTHER | E55: =B30 -> 0
C56: OTHER | E56: =B31 -> 0
C57: OTHER | E57: =B32 -> 0
C58: OTHER | E58: =B33 -> 0
C59: OTHER | E59: =B34 -> 0
C60: OTHER | E60: =B35 -> 0
C61: OTHER | E61: =B36 -> 0
C62: TOTAL TIMBER | E62: =SUM(E49:H61) -> 1750

Sheet GATSIBO
A1: QUANTITY REPORT
A3: MONTHS REPORT OF APRIL 2026
A5: NAME OF TIMBER | B5: No OF TIMBER | C5: PRICE OF TIMBER | E5: TOTAL COST | F5: TVA | G5: MSF | H5: TVA+MSF
A6: PINUS NINI | E6: =PRODUCT(B6*C6) -> 0 | F6: =PRODUCT(E6*18)/118 -> 0 | G6: =PRODUCT(B6*50) -> 0 | H6: =SUM(F6:G6) -> 0
A7: PINUS NTOYA | E7: =PRODUCT(B7*C7) -> 0 | F7: =PRODUCT(E7*18)/118 -> 0 | G7: =PRODUCT(B7*50) -> 0 | H7: =SUM(F7:G7) -> 0
A8: IBIPANDE BYA PINUS | C8: 2000 | E8: =PRODUCT(B8*C8) -> 0 | F8: =PRODUCT(E8*18)/118 -> 0 | G8: =PRODUCT(B8*50) -> 0 | H8: =SUM(F8:G8) -> 0
A9: MADIRIYE NINI | E9: =PRODUCT(B9*C9) -> 0 | F9: =PRODUCT(E9*18)/118 -> 0 | G9: =PRODUCT(B9*30) -> 0 | H9: =SUM(F9:G9) -> 0
A10: MADIRIYE NTOYA | B10: 1800 | C10: 2124 | E10: =PRODUCT(B10*C10) -> 3823200 | F10: =PRODUCT(E10*18)/118 -> 583200 | G10: =PRODUCT(B10*30) -> 54000 | H10: =SUM(F10:G10) -> 637200
A11: MADRIEN | E11: =PRODUCT(B11*C11) -> 0 | F11: =PRODUCT(E11*18)/118 -> 0 | G11: =PRODUCT(B11*30) -> 0 | H11: =SUM(F11:G11) -> 0
A12: MADRIEN | E12: =PRODUCT(B12*C12) -> 0 | F12: =PRODUCT(E12*18)/118 -> 0 | G12: =PRODUCT(B12*30) -> 0 | H12: =SUM(F12:G12) -> 0
A13: PLANCHE | B13: 50 | C13: 1357 | E13: =PRODUCT(B13*C13) -> 67850 | F13: =PRODUCT(E13*18)/118 -> 10350 | G13: =PRODUCT(B13*20) -> 1000 | H13: =SUM(F13:G13) -> 11350
A14: PLANCHE | C14: 1180 | E14: =PRODUCT(B14*C14) -> 0 | F14: =PRODUCT(E14*18)/118 -> 0 | G14: =PRODUCT(B14*20) -> 0 | H14: =SUM(F14:G14) -> 0
A15: Other Timber for Difference Price
A16: NAME OF TIMBER | B16: No OF TIMBER | C16: P/U | D16: MSF | E16: TOTAL COST | F16: VAT | G16: MSF | H16: VTA+MST
A17: IBIPANDE | E17: =PRODUCT(B17*C17) -> 0 | F17: =PRODUCT(E17*18)/118 -> 0 | G17: =PRODUCT(B17*D17) -> 0 | H17: =SUM(F17:G17) -> 0
A18: IBIPANDE | E18: =PRODUCT(B18*C18) -> 0 | F18: =PRODUCT(E18*18)/118 -> 0 | G18: =PRODUCT(B18*D18) -> 0 | H18: =SUM(F18:G18) -> 0
A19: UMUSAVE | E19: =PRODUCT(B19*C19) -> 0 | F19: =PRODUCT(E19*18)/118 -> 0 | G19: =PRODUCT(B19*D19) -> 0 | H19: =SUM(F19:G19) -> 0
A20: GEREVERIA | B20: 338 | D20: 200 | E20: =PRODUCT(B20*C20) -> 0 | F20: =PRODUCT(E20*18)/118 -> 0 | G20: =PRODUCT(B20*D20) -> 67600 | H20: =SUM(F20:G20) -> 67600
A21: MADRIEN | D21: 354 | E21: =PRODUCT(B21*C21) -> 0 | F21: =PRODUCT(E21*18)/118 -> 0 | G21: =PRODUCT(B21*D21) -> 0 | H21: =SUM(F21:G21) -> 0
A22: PLANCHE | D22: 217 | E22: =PRODUCT(B22*C22) -> 0 | F22: =PRODUCT(E22*18)/118 -> 0 | G22: =PRODUCT(B22*D22) -> 0 | H22: =SUM(F22:G22) -> 0
A23: INGIGA | B23: 198 | D23: 500 | E23: =PRODUCT(B23*C23) -> 0 | F23: =PRODUCT(E23*18)/118 -> 0 | G23: =PRODUCT(B23*D23) -> 99000 | H23: =SUM(F23:G23) -> 99000
A24: OTHER | E24: =PRODUCT(B24*C24) -> 0 | F24: =PRODUCT(E24*18)/118 -> 0 | G24: =PRODUCT(B24*D24) -> 0 | H24: =SUM(F24:G24) -> 0
A25: OTHER | E25: =PRODUCT(B25*C25) -> 0 | F25: =PRODUCT(E25*18)/118 -> 0 | G25: =PRODUCT(B25*D25) -> 0 | H25: =SUM(F25:G25) -> 0
A26: OTHER | E26: =PRODUCT(B26*C26) -> 0 | F26: =PRODUCT(E26*18)/118 -> 0 | G26: =PRODUCT(B26*D26) -> 0 | H26: =SUM(F26:G26) -> 0
A27: OTHER | E27: =PRODUCT(B27*C27) -> 0 | F27: =PRODUCT(E27*18)/118 -> 0 | G27: =PRODUCT(B27*D27) -> 0 | H27: =SUM(F27:G27) -> 0
A28: OTHER | E28: =PRODUCT(B28*C28) -> 0 | F28: =PRODUCT(E28*18)/118 -> 0 | G28: =PRODUCT(B28*D28) -> 0 | H28: =SUM(F28:G28) -> 0
A29: OTHER | E29: =PRODUCT(B29*C29) -> 0 | F29: =PRODUCT(E29*18)/118 -> 0 | G29: =PRODUCT(B29*D29) -> 0 | H29: =SUM(F29:G29) -> 0
A30: OTHER | E30: =PRODUCT(B30*C30) -> 0 | F30: =PRODUCT(E30*18)/118 -> 0 | G30: =PRODUCT(B30*D30) -> 0 | H30: =SUM(F30:G30) -> 0
A31: OTHER | E31: =PRODUCT(B31*C31) -> 0 | F31: =PRODUCT(E31*18)/118 -> 0 | G31: =PRODUCT(B31*D31) -> 0 | H31: =SUM(F31:G31) -> 0
A32: OTHER | E32: =PRODUCT(B32*C32) -> 0 | F32: =PRODUCT(E32*18)/118 -> 0 | G32: =PRODUCT(B32*D32) -> 0 | H32: =SUM(F32:G32) -> 0
A33: OTHER | E33: =PRODUCT(B33*C33) -> 0 | F33: =PRODUCT(E33*18)/118 -> 0 | G33: =PRODUCT(B33*D33) -> 0 | H33: =SUM(F33:G33) -> 0
A34: OTHER | E34: =PRODUCT(B34*C34) -> 0 | F34: =PRODUCT(E34*18)/118 -> 0 | G34: =PRODUCT(B34*D34) -> 0 | H34: =SUM(F34:G34) -> 0
A35: OTHER | E35: =PRODUCT(B35*C35) -> 0 | F35: =PRODUCT(E35*18)/118 -> 0 | G35: =PRODUCT(B35*D35) -> 0 | H35: =SUM(F35:G35) -> 0
A36: OTHER | E36: =PRODUCT(B36*C36) -> 0 | F36: =PRODUCT(E36*18)/118 -> 0 | G36: =PRODUCT(B36*D36) -> 0 | H36: =SUM(F36:G36) -> 0
A37: TOTALY | E37: =SUM(E5:E36) -> 3891050 | F37: =SUM(F5:F36) -> 593550 | G37: =SUM(G5:G36) -> 221600 | H37: =SUM(H5:H36) -> 815150
A38: SUMMARY | C38: RWF | E38: NAME | G38: Phone | H38: RWF
A39: TOTAL RWF PAID ON MOMO PAY | C39: 815150
A40: TOTAL RWF PAID ON CASH
A41: AMOUNT NOT INVOICED | C41: 53100
A42: TOTAL RWF DEPPOSITED ON BANK
A43: MEMBERSHIP FEES REGISTRETION
A44: MEMBERSHIP FEES CONTRIBUTION
A45: TOTAL INCOME | C45: =SUM(C39+C40+C41+C42+C43+C44) -> 868250
A46: TIMBER SUMMARY
A48: REPORT SUMMARY | C48: TIMBER TYPE | E48: NUMBER OF QUANTITY
C49: INTURUSU | E49: =SUM(B9:B12) -> 1800
C50: PINUS | E50: =SUM(B6:B8) -> 0
C51: PALNCHE | E51: =SUM(B13:B14) -> 50
C52: IBIPANDE | E52: =SUM(B17:B18) -> 0
C53: UMUSAVE | E53: =SUM(B19:B20) -> 338
C54: OTHER | E54: =B29 -> 0
C55: OTHER | E55: =B30 -> 0
C56: OTHER | E56: =B31 -> 0
C57: OTHER | E57: =B32 -> 0
C58: OTHER | E58: =B33 -> 0
C59: OTHER | E59: =B34 -> 0
C60: OTHER | E60: =B35 -> 0
C61: OTHER | E61: =B36 -> 0
C62: TOTAL TIMBER | E62: =SUM(E49:H61) -> 2188

Sheet GASHYUSHYA
A1: QUANTITY REPORT
A3: MONTHS REPORT OF APRIL 2026
A5: NAME OF TIMBER | B5: No OF TIMBER | C5: PRICE OF TIMBER | E5: TOTAL COST | F5: TVA | G5: MSF | H5: TVA+MSF
A6: PINUS NINI | E6: =PRODUCT(B6*C6) -> 0 | F6: =PRODUCT(E6*18)/118 -> 0 | G6: =PRODUCT(B6*50) -> 0 | H6: =SUM(F6:G6) -> 0
A7: PINUS NTOYA | E7: =PRODUCT(B7*C7) -> 0 | F7: =PRODUCT(E7*18)/118 -> 0 | G7: =PRODUCT(B7*50) -> 0 | H7: =SUM(F7:G7) -> 0
A8: PINUS | C8: 8000 | E8: =PRODUCT(B8*C8) -> 0 | F8: =PRODUCT(E8*18)/118 -> 0 | G8: =PRODUCT(B8*50) -> 0 | H8: =SUM(F8:G8) -> 0
A9: MADIRIYE NINI | E9: =PRODUCT(B9*C9) -> 0 | F9: =PRODUCT(E9*18)/118 -> 0 | G9: =PRODUCT(B9*30) -> 0 | H9: =SUM(F9:G9) -> 0
A10: MADIRIYE NTOYA | C10: 2000 | E10: =PRODUCT(B10*C10) -> 0 | F10: =PRODUCT(E10*18)/118 -> 0 | G10: =PRODUCT(B10*30) -> 0 | H10: =SUM(F10:G10) -> 0
A11: MADRIEN | B11: 9010 | C11: 2124 | E11: =PRODUCT(B11*C11) -> 19137240 | F11: =PRODUCT(E11*18)/118 -> 2919240 | G11: =PRODUCT(B11*30) -> 270300 | H11: =SUM(F11:G11) -> 3189540
A12: MADRIEN | E12: =PRODUCT(B12*C12) -> 0 | F12: =PRODUCT(E12*18)/118 -> 0 | G12: =PRODUCT(B12*30) -> 0 | H12: =SUM(F12:G12) -> 0
A13: PLANCHE | B13: 445 | C13: 1357 | E13: =PRODUCT(B13*C13) -> 603865 | F13: =PRODUCT(E13*18)/118 -> 92115 | G13: =PRODUCT(B13*20) -> 8900 | H13: =SUM(F13:G13) -> 101015
A14: PLANCHE | E14: =PRODUCT(B14*C14) -> 0 | F14: =PRODUCT(E14*18)/118 -> 0 | G14: =PRODUCT(B14*20) -> 0 | H14: =SUM(F14:G14) -> 0
A15: Other Timber for Difference Price
A16: NAME OF TIMBER | B16: No OF TIMBER | C16: P/U | D16: MSF | E16: TOTAL COST | F16: VAT | G16: MSF | H16: VTA+MST
A17: IBIPANDE BYA PINUS | B17: 1222 | C17: 2124 | D17: 50 | E17: =PRODUCT(B17*C17) -> 2595528 | F17: =PRODUCT(E17*18)/118 -> 395928 | G17: =PRODUCT(B17*D17) -> 61100 | H17: =SUM(F17:G17) -> 457028
A18: IBIPANDE | E18: =PRODUCT(B18*C18) -> 0 | F18: =PRODUCT(E18*18)/118 -> 0 | G18: =PRODUCT(B18*D18) -> 0 | H18: =SUM(F18:G18) -> 0
A19: UMUSAVE | E19: =PRODUCT(B19*C19) -> 0 | F19: =PRODUCT(E19*18)/118 -> 0 | G19: =PRODUCT(B19*D19) -> 0 | H19: =SUM(F19:G19) -> 0
A20: UMUSAVE | E20: =PRODUCT(B20*C20) -> 0 | F20: =PRODUCT(E20*18)/118 -> 0 | G20: =PRODUCT(B20*D20) -> 0 | H20: =SUM(F20:G20) -> 0
A21: OTHER | B21: 400 | D21: 100 | E21: =PRODUCT(B21*C21) -> 0 | F21: =PRODUCT(E21*18)/118 -> 0 | G21: =PRODUCT(B21*D21) -> 40000 | H21: =SUM(F21:G21) -> 40000
A22: OTHER | E22: =PRODUCT(B22*C22) -> 0 | F22: =PRODUCT(E22*18)/118 -> 0 | G22: =PRODUCT(B22*D22) -> 0 | H22: =SUM(F22:G22) -> 0
A23: OTHER | E23: =PRODUCT(B23*C23) -> 0 | F23: =PRODUCT(E23*18)/118 -> 0 | G23: =PRODUCT(B23*D23) -> 0 | H23: =SUM(F23:G23) -> 0
A24: OTHER | E24: =PRODUCT(B24*C24) -> 0 | F24: =PRODUCT(E24*18)/118 -> 0 | G24: =PRODUCT(B24*D24) -> 0 | H24: =SUM(F24:G24) -> 0
A25: OTHER | E25: =PRODUCT(B25*C25) -> 0 | F25: =PRODUCT(E25*18)/118 -> 0 | G25: =PRODUCT(B25*D25) -> 0 | H25: =SUM(F25:G25) -> 0
A26: OTHER | E26: =PRODUCT(B26*C26) -> 0 | F26: =PRODUCT(E26*18)/118 -> 0 | G26: =PRODUCT(B26*D26) -> 0 | H26: =SUM(F26:G26) -> 0
A27: OTHER | E27: =PRODUCT(B27*C27) -> 0 | F27: =PRODUCT(E27*18)/118 -> 0 | G27: =PRODUCT(B27*D27) -> 0 | H27: =SUM(F27:G27) -> 0
A28: OTHER | E28: =PRODUCT(B28*C28) -> 0 | F28: =PRODUCT(E28*18)/118 -> 0 | G28: =PRODUCT(B28*D28) -> 0 | H28: =SUM(F28:G28) -> 0
A29: OTHER | E29: =PRODUCT(B29*C29) -> 0 | F29: =PRODUCT(E29*18)/118 -> 0 | G29: =PRODUCT(B29*D29) -> 0 | H29: =SUM(F29:G29) -> 0
A30: OTHER | E30: =PRODUCT(B30*C30) -> 0 | F30: =PRODUCT(E30*18)/118 -> 0 | G30: =PRODUCT(B30*D30) -> 0 | H30: =SUM(F30:G30) -> 0
A31: OTHER | E31: =PRODUCT(B31*C31) -> 0 | F31: =PRODUCT(E31*18)/118 -> 0 | G31: =PRODUCT(B31*D31) -> 0 | H31: =SUM(F31:G31) -> 0
A32: OTHER | E32: =PRODUCT(B32*C32) -> 0 | F32: =PRODUCT(E32*18)/118 -> 0 | G32: =PRODUCT(B32*D32) -> 0 | H32: =SUM(F32:G32) -> 0
A33: OTHER | E33: =PRODUCT(B33*C33) -> 0 | F33: =PRODUCT(E33*18)/118 -> 0 | G33: =PRODUCT(B33*D33) -> 0 | H33: =SUM(F33:G33) -> 0
... A36: OTHER | E36: =PRODUCT(B36*C36) -> 0 | F36: =PRODUCT(E36*18)/118 -> 0 | G36: =PRODUCT(B36*D36) -> 0 | H36: =SUM(F36:G36) -> 0
A37: TOTALY | E37: =SUM(E5:E36) -> 22336633 | F37: =SUM(F5:F36) -> 3407283 | G37: =SUM(G5:G36) -> 380300 | H37: =SUM(H5:H36) -> 3787583
A38: SUMMARY | C38: RWF | E38: NAME | G38: Phone | H38: RWF
A39: TOTAL RWF PAID ON MOMO PAY | C39: 3787583
A40: TOTAL RWF PAID ON CASH
A41: AMOUNT NOT INVOICED
A42: TOTAL RWF DEPPOSITED ON BANK
A43: MEMBERSHIP FEES REGISTRETION
A44: MEMBERSHIP FEES CONTRIBUTION
A45: TOTAL INCOME | C45: =SUM(C39+C40+C41+C42+C43+C44) -> 3787583
A46: TIMBER SUMMARY
A48: REPORT SUMMARY | C48: TIMBER TYPE | E48: NUMBER OF QUANTITY
C49: INTURUSU | E49: =SUM(B9:B12) -> 9010
C50: PINUS | E50: =SUM(B6:B8) -> 0
C51: PALNCHE | E51: =SUM(B13:B14) -> 445
C52: IBIPANDE | E52: =SUM(B17:B18) -> 1222
C53: UMUSAVE | E53: =SUM(B19:B20) -> 0
C54: OTHER TYPE OF TIMBER | E54: =B29 -> 0
C55: OTHER TYPE OF TIMBER | E55: =B30 -> 0
C56: OTHER TYPE OF TIMBER | E56: =B31 -> 0
C57: OTHER TYPE OF TIMBER | E57: =B32 -> 0
C58: OTHER TYPE OF TIMBER | E58: =B33 -> 0
C59: OTHER TYPE OF TIMBER | E59: =B34 -> 0
C60: OTHER TYPE OF TIMBER | E60: =B35 -> 0
C61: OTHER TYPE OF TIMBER | E61: =B36 -> 0
C62: TOTAL TIMBER | E62: =SUM(E49:H61) -> 10677

Sheet RUTSIRO
A1: QUANTITY REPORT
A3: MONTHS REPORT OF NOVEMBER 2025
A5: NAME OF TIMBER | B5: No OF TIMBER | C5: PRICE OF TIMBER | E5: TOTAL COST | F5: TVA | G5: MSF | H5: TVA+MSF
A6: PINUS NINI | E6: =PRODUCT(B6*C6) -> 0 | F6: =PRODUCT(E6*18)/118 -> 0 | G6: =PRODUCT(B6*50) -> 0 | H6: =SUM(F6:G6) -> 0
A7: PINUS NTOYA | E7: =PRODUCT(B7*C7) -> 0 | F7: =PRODUCT(E7*18)/118 -> 0 | G7: =PRODUCT(B7*50) -> 0 | H7: =SUM(F7:G7) -> 0
A8: PINUS | E8: =PRODUCT(B8*C8) -> 0 | F8: =PRODUCT(E8*18)/118 -> 0 | G8: =PRODUCT(B8*50) -> 0 | H8: =SUM(F8:G8) -> 0
A9: MADIRIYE NINI | E9: =PRODUCT(B9*C9) -> 0 | F9: =PRODUCT(E9*18)/118 -> 0 | G9: =PRODUCT(B9*30) -> 0 | H9: =SUM(F9:G9) -> 0
A10: MADIRIYE NTOYA | E10: =PRODUCT(B10*C10) -> 0 | F10: =PRODUCT(E10*18)/118 -> 0 | G10: =PRODUCT(B10*30) -> 0 | H10: =SUM(F10:G10) -> 0
A11: MADRIEN | E11: =PRODUCT(B11*C11) -> 0 | F11: =PRODUCT(E11*18)/118 -> 0 | G11: =PRODUCT(B11*30) -> 0 | H11: =SUM(F11:G11) -> 0
A12: MADRIEN | C12: 2124 | E12: =PRODUCT(B12*C12) -> 0 | F12: =PRODUCT(E12*18)/118 -> 0 | G12: =PRODUCT(B12*30) -> 0 | H12: =SUM(F12:G12) -> 0
A13: PLANCHE | E13: =PRODUCT(B13*C13) -> 0 | F13: =PRODUCT(E13*18)/118 -> 0 | G13: =PRODUCT(B13*20) -> 0 | H13: =SUM(F13:G13) -> 0
A14: PLANCHE | E14: =PRODUCT(B14*C14) -> 0 | F14: =PRODUCT(E14*18)/118 -> 0 | G14: =PRODUCT(B14*20) -> 0 | H14: =SUM(F14:G14) -> 0
A15: Other Timber for Difference Price
A16: NAME OF TIMBER | B16: No OF TIMBER | C16: P/U | D16: MSF | E16: TOTAL COST | F16: VAT | G16: MSF | H16: VTA+MST
A17: IBIPANDE | E17: =PRODUCT(B17*C17) -> 0 | F17: =PRODUCT(E17*18)/118 -> 0 | G17: =PRODUCT(B17*D17) -> 0 | H17: =SUM(F17:G17) -> 0
A18: IBIPANDE | E18: =PRODUCT(B18*C18) -> 0 | F18: =PRODUCT(E18*18)/118 -> 0 | G18: =PRODUCT(B18*D18) -> 0 | H18: =SUM(F18:G18) -> 0
A19: UMUSAVE | E19: =PRODUCT(B19*C19) -> 0 | F19: =PRODUCT(E19*18)/118 -> 0 | G19: =PRODUCT(B19*D19) -> 0 | H19: =SUM(F19:G19) -> 0
A20: UMUSAVE | E20: =PRODUCT(B20*C20) -> 0 | F20: =PRODUCT(E20*18)/118 -> 0 | G20: =PRODUCT(B20*D20) -> 0 | H20: =SUM(F20:G20) -> 0
A21: OTHER | E21: =PRODUCT(B21*C21) -> 0 | F21: =PRODUCT(E21*18)/118 -> 0 | G21: =PRODUCT(B21*D21) -> 0 | H21: =SUM(F21:G21) -> 0
A22: OTHER | E22: =PRODUCT(B22*C22) -> 0 | F22: =PRODUCT(E22*18)/118 -> 0 | G22: =PRODUCT(B22*D22) -> 0 | H22: =SUM(F22:G22) -> 0
A23: OTHER | E23: =PRODUCT(B23*C23) -> 0 | F23: =PRODUCT(E23*18)/118 -> 0 | G23: =PRODUCT(B23*D23) -> 0 | H23: =SUM(F23:G23) -> 0
A24: OTHER | E24: =PRODUCT(B24*C24) -> 0 | F24: =PRODUCT(E24*18)/118 -> 0 | G24: =PRODUCT(B24*D24) -> 0 | H24: =SUM(F24:G24) -> 0
A25: OTHER | E25: =PRODUCT(B25*C25) -> 0 | F25: =PRODUCT(E25*18)/118 -> 0 | G25: =PRODUCT(B25*D25) -> 0 | H25: =SUM(F25:G25) -> 0
A26: OTHER | E26: =PRODUCT(B26*C26) -> 0 | F26: =PRODUCT(E26*18)/118 -> 0 | G26: =PRODUCT(B26*D26) -> 0 | H26: =SUM(F26:G26) -> 0
A27: OTHER | E27: =PRODUCT(B27*C27) -> 0 | F27: =PRODUCT(E27*18)/118 -> 0 | G27: =PRODUCT(B27*D27) -> 0 | H27: =SUM(F27:G27) -> 0
A28: OTHER | E28: =PRODUCT(B28*C28) -> 0 | F28: =PRODUCT(E28*18)/118 -> 0 | G28: =PRODUCT(B28*D28) -> 0 | H28: =SUM(F28:G28) -> 0
... A36: OTHER | E36: =PRODUCT(B36*C36) -> 0 | F36: =PRODUCT(E36*18)/118 -> 0 | G36: =PRODUCT(B36*D36) -> 0 | H36: =SUM(F36:G36) -> 0
A37: TOTALY | E37: =SUM(E5:E36) -> 0 | F37: =SUM(F5:F36) -> 0 | G37: =SUM(G5:G36) -> 0 | H37: =SUM(H5:H36) -> 0
A38: SUMMARY | C38: RWF | E38: NAME | G38: Phone | H38: RWF
A39: TOTAL RWF PAID ON MOMO PAY
A40: TOTAL RWF PAID ON CASH
A41: AMOUNT NOT INVOICED
A42: TOTAL RWF DEPPOSITED ON BANK
A43: MEMBERSHIP FEES REGISTRETION
A44: MEMBERSHIP FEES CONTRIBUTION
A45: TOTAL INCOME | C45: =SUM(C39+C40+C41+C42+C43+C44) -> 0
A46: TIMBER SUMMARY
A48: REPORT SUMMARY | C48: TIMBER TYPE | E48: NUMBER OF QUANTITY
C49: INTURUSU | E49: =SUM(B9:B12) -> 0
C50: PINUS | E50: =SUM(B6:B8) -> 0
C51: PALNCHE | E51: =SUM(B13:B14) -> 0
C52: IBIPANDE | E52: =SUM(B17:B18) -> 0
C53: UMUSAVE | E53: =SUM(B19:B20) -> 0
C54: OTHER TYPE OF TIMBER | E54: =B29 -> 0
C55: OTHER TYPE OF TIMBER | E55: =B30 -> 0
C56: OTHER TYPE OF TIMBER | E56: =B31 -> 0
C57: OTHER TYPE OF TIMBER | E57: =B32 -> 0
C58: OTHER TYPE OF TIMBER | E58: =B33 -> 0
C59: OTHER TYPE OF TIMBER | E59: =B34 -> 0
C60: OTHER TYPE OF TIMBER | E60: =B35 -> 0
C61: OTHER TYPE OF TIMBER | E61: =B36 -> 0
C62: TOTAL TIMBER | E62: =SUM(E49:H61) -> 0

Sheet NGORORERO
A1: QUANTITY REPORT
A3: MONTHS REPORT OF APRIL 2026
A5: NAME OF TIMBER | B5: No OF TIMBER | C5: PRICE OF TIMBER | E5: TOTAL COST | F5: TVA | G5: MSF | H5: TVA+MSF
A6: PINUS NINI | E6: =PRODUCT(B6*C6) -> 0 | F6: =PRODUCT(E6*18)/118 -> 0 | G6: =PRODUCT(B6*50) -> 0 | H6: =SUM(F6:G6) -> 0
A7: PINUS NTOYA | C7: 7670 | E7: =PRODUCT(B7*C7) -> 0 | F7: =PRODUCT(E7*18)/118 -> 0 | G7: =PRODUCT(B7*50) -> 0 | H7: =SUM(F7:G7) -> 0
A8: PINUS | E8: =PRODUCT(B8*C8) -> 0 | F8: =PRODUCT(E8*18)/118 -> 0 | G8: =PRODUCT(B8*50) -> 0 | H8: =SUM(F8:G8) -> 0
A9: MADIRIYE NINI | E9: =PRODUCT(B9*C9) -> 0 | F9: =PRODUCT(E9*18)/118 -> 0 | G9: =PRODUCT(B9*30) -> 0 | H9: =SUM(F9:G9) -> 0
A10: MADIRIYE NTOYA | C10: 1806 | E10: =PRODUCT(B10*C10) -> 0 | F10: =PRODUCT(E10*18)/118 -> 0 | G10: =PRODUCT(B10*30) -> 0 | H10: =SUM(F10:G10) -> 0
A11: MADRIEN | C11: 2124 | E11: =PRODUCT(B11*C11) -> 0 | F11: =PRODUCT(E11*18)/118 -> 0 | G11: =PRODUCT(B11*30) -> 0 | H11: =SUM(F11:G11) -> 0
A12: MADRIEN | E12: =PRODUCT(B12*C12) -> 0 | F12: =PRODUCT(E12*18)/118 -> 0 | G12: =PRODUCT(B12*30) -> 0 | H12: =SUM(F12:G12) -> 0
A13: PLANCHE | E13: =PRODUCT(B13*C13) -> 0 | F13: =PRODUCT(E13*18)/118 -> 0 | G13: =PRODUCT(B13*20) -> 0 | H13: =SUM(F13:G13) -> 0
A14: PLANCHE | E14: =PRODUCT(B14*C14) -> 0 | F14: =PRODUCT(E14*18)/118 -> 0 | G14: =PRODUCT(B14*20) -> 0 | H14: =SUM(F14:G14) -> 0
A15: Other Timber for Difference Price
A16: NAME OF TIMBER | B16: No OF TIMBER | C16: P/U | D16: MSF | E16: TOTAL COST | F16: VAT | G16: MSF | H16: VTA+MST
A17: IBIPANDE | B17: 105 | C17: 800 | D17: 20 | E17: =PRODUCT(B17*C17) -> 84000 | F17: =PRODUCT(E17*18)/118 -> 12813.559 | G17: =PRODUCT(B17*D17) -> 2100 | H17: =SUM(F17:G17) -> 14913.559
A18: IBIPANDE | E18: =PRODUCT(B18*C18) -> 0 | F18: =PRODUCT(E18*18)/118 -> 0 | G18: =PRODUCT(B18*D18) -> 0 | H18: =SUM(F18:G18) -> 0
A19: UMUSAVE | E19: =PRODUCT(B19*C19) -> 0 | F19: =PRODUCT(E19*18)/118 -> 0 | G19: =PRODUCT(B19*D19) -> 0 | H19: =SUM(F19:G19) -> 0
A20: UMUSAVE | E20: =PRODUCT(B20*C20) -> 0 | F20: =PRODUCT(E20*18)/118 -> 0 | G20: =PRODUCT(B20*D20) -> 0 | H20: =SUM(F20:G20) -> 0
A21: OTHER | E21: =PRODUCT(B21*C21) -> 0 | F21: =PRODUCT(E21*18)/118 -> 0 | G21: =PRODUCT(B21*D21) -> 0 | H21: =SUM(F21:G21) -> 0
A22: OTHER | E22: =PRODUCT(B22*C22) -> 0 | F22: =PRODUCT(E22*18)/118 -> 0 | G22: =PRODUCT(B22*D22) -> 0 | H22: =SUM(F22:G22) -> 0
A23: OTHER | E23: =PRODUCT(B23*C23) -> 0 | F23: =PRODUCT(E23*18)/118 -> 0 | G23: =PRODUCT(B23*D23) -> 0 | H23: =SUM(F23:G23) -> 0
A24: OTHER | E24: =PRODUCT(B24*C24) -> 0 | F24: =PRODUCT(E24*18)/118 -> 0 | G24: =PRODUCT(B24*D24) -> 0 | H24: =SUM(F24:G24) -> 0
A25: OTHER | E25: =PRODUCT(B25*C25) -> 0 | F25: =PRODUCT(E25*18)/118 -> 0 | G25: =PRODUCT(B25*D25) -> 0 | H25: =SUM(F25:G25) -> 0
A26: OTHER | E26: =PRODUCT(B26*C26) -> 0 | F26: =PRODUCT(E26*18)/118 -> 0 | G26: =PRODUCT(B26*D26) -> 0 | H26: =SUM(F26:G26) -> 0
A27: OTHER | E27: =PRODUCT(B27*C27) -> 0 | F27: =PRODUCT(E27*18)/118 -> 0 | G27: =PRODUCT(B27*D27) -> 0 | H27: =SUM(F27:G27) -> 0
A28: OTHER | E28: =PRODUCT(B28*C28) -> 0 | F28: =PRODUCT(E28*18)/118 -> 0 | G28: =PRODUCT(B28*D28) -> 0 | H28: =SUM(F28:G28) -> 0
A29: OTHER | E29: =PRODUCT(B29*C29) -> 0 | F29: =PRODUCT(E29*18)/118 -> 0 | G29: =PRODUCT(B29*D29) -> 0 | H29: =SUM(F29:G29) -> 0
... A36: OTHER | E36: =PRODUCT(B36*C36) -> 0 | F36: =PRODUCT(E36*18)/118 -> 0 | G36: =PRODUCT(B36*D36) -> 0 | H36: =SUM(F36:G36) -> 0
A37: TOTALY | E37: =SUM(E5:E36) -> 84000 | F37: =SUM(F5:F36) -> 12813.559 | G37: =SUM(G5:G36) -> 2100 | H37: =SUM(H5:H36) -> 14913.559
A38: SUMMARY | C38: RWF | E38: NAME | G38: Phone | H38: RWF
A39: TOTAL RWF PAID ON MOMO PAY | C39: 14914
A40: TOTAL RWF PAID ON CASH
A41: AMOUNT NOT INVOICED
A42: TOTAL RWF DEPPOSITED ON BANK
A43: MEMBERSHIP FEES REGISTRETION
A44: MEMBERSHIP FEES CONTRIBUTION
A45: TOTAL INCOME | C45: =SUM(C39+C40+C41+C42+C43+C44) -> 14914
A46: TIMBER SUMMARY
A48: REPORT SUMMARY | C48: TIMBER TYPE | E48: NUMBER OF QUANTITY
C49: INTURUSU | E49: =SUM(B9:B12) -> 0
C50: PINUS | E50: =SUM(B6:B8) -> 0
C51: PALNCHE | E51: =SUM(B13:B14) -> 0
C52: IBIPANDE | E52: =SUM(B17:B18) -> 105
C53: UMUSAVE | E53: =SUM(B19:B20) -> 0
C54: OTHER TYPE OF TIMBER | E54: =B29 -> 0
C55: OTHER TYPE OF TIMBER | E55: =B30 -> 0
C56: OTHER TYPE OF TIMBER | E56: =B31 -> 0
C57: OTHER TYPE OF TIMBER | E57: =B32 -> 0
C58: OTHER TYPE OF TIMBER | E58: =B33 -> 0
C59: OTHER TYPE OF TIMBER | E59: =B34 -> 0
C60: OTHER TYPE OF TIMBER | E60: =B35 -> 0
C61: OTHER TYPE OF TIMBER | E61: =B36 -> 0
C62: TOTAL TIMBER | E62: =SUM(E49:H61) -> 105

Sheet THIRTH
A1: QUANTITY REPORT
A3: MONTHS REPORT OF NOVEMBER 2025
A5: NAME OF TIMBER | B5: No OF TIMBER | C5: PRICE OF TIMBER | E5: TOTAL COST | F5: TVA | G5: MSF | H5: TVA+MSF
A6: PINUS NINI | E6: =PRODUCT(B6*C6) -> 0 | F6: =PRODUCT(E6*18)/118 -> 0 | G6: =PRODUCT(B6*50) -> 0 | H6: =SUM(F6:G6) -> 0
A7: PINUS NTOYA | E7: =PRODUCT(B7*C7) -> 0 | F7: =PRODUCT(E7*18)/118 -> 0 | G7: =PRODUCT(B7*50) -> 0 | H7: =SUM(F7:G7) -> 0
A8: PINUS | E8: =PRODUCT(B8*C8) -> 0 | F8: =PRODUCT(E8*18)/118 -> 0 | G8: =PRODUCT(B8*50) -> 0 | H8: =SUM(F8:G8) -> 0
A9: MADIRIYE NINI | E9: =PRODUCT(B9*C9) -> 0 | F9: =PRODUCT(E9*18)/118 -> 0 | G9: =PRODUCT(B9*30) -> 0 | H9: =SUM(F9:G9) -> 0
A10: MADIRIYE NTOYA | E10: =PRODUCT(B10*C10) -> 0 | F10: =PRODUCT(E10*18)/118 -> 0 | G10: =PRODUCT(B10*30) -> 0 | H10: =SUM(F10:G10) -> 0
A11: MADRIEN | C11: 2124 | E11: =PRODUCT(B11*C11) -> 0 | F11: =PRODUCT(E11*18)/118 -> 0 | G11: =PRODUCT(B11*30) -> 0 | H11: =SUM(F11:G11) -> 0
A12: MADRIEN | E12: =PRODUCT(B12*C12) -> 0 | F12: =PRODUCT(E12*18)/118 -> 0 | G12: =PRODUCT(B12*30) -> 0 | H12: =SUM(F12:G12) -> 0
A13: PLANCHE | E13: =PRODUCT(B13*C13) -> 0 | F13: =PRODUCT(E13*18)/118 -> 0 | G13: =PRODUCT(B13*20) -> 0 | H13: =SUM(F13:G13) -> 0
A14: PLANCHE | E14: =PRODUCT(B14*C14) -> 0 | F14: =PRODUCT(E14*18)/118 -> 0 | G14: =PRODUCT(B14*20) -> 0 | H14: =SUM(F14:G14) -> 0
A15: Other Timber for Difference Price
A16: NAME OF TIMBER | B16: No OF TIMBER | C16: P/U | D16: MSF | E16: TOTAL COST | F16: VAT | G16: MSF | H16: VTA+MST
A17: IBIPANDE | E17: =PRODUCT(B17*C17) -> 0 | F17: =PRODUCT(E17*18)/118 -> 0 | G17: =PRODUCT(B17*D17) -> 0 | H17: =SUM(F17:G17) -> 0
A18: IBIPANDE | E18: =PRODUCT(B18*C18) -> 0 | F18: =PRODUCT(E18*18)/118 -> 0 | G18: =PRODUCT(B18*D18) -> 0 | H18: =SUM(F18:G18) -> 0
A19: UMUSAVE | E19: =PRODUCT(B19*C19) -> 0 | F19: =PRODUCT(E19*18)/118 -> 0 | G19: =PRODUCT(B19*D19) -> 0 | H19: =SUM(F19:G19) -> 0
A20: UMUSAVE | E20: =PRODUCT(B20*C20) -> 0 | F20: =PRODUCT(E20*18)/118 -> 0 | G20: =PRODUCT(B20*D20) -> 0 | H20: =SUM(F20:G20) -> 0
A21: OTHER | E21: =PRODUCT(B21*C21) -> 0 | F21: =PRODUCT(E21*18)/118 -> 0 | G21: =PRODUCT(B21*D21) -> 0 | H21: =SUM(F21:G21) -> 0
A22: OTHER | E22: =PRODUCT(B22*C22) -> 0 | F22: =PRODUCT(E22*18)/118 -> 0 | G22: =PRODUCT(B22*D22) -> 0 | H22: =SUM(F22:G22) -> 0
A23: OTHER | E23: =PRODUCT(B23*C23) -> 0 | F23: =PRODUCT(E23*18)/118 -> 0 | G23: =PRODUCT(B23*D23) -> 0 | H23: =SUM(F23:G23) -> 0
A24: OTHER | E24: =PRODUCT(B24*C24) -> 0 | F24: =PRODUCT(E24*18)/118 -> 0 | G24: =PRODUCT(B24*D24) -> 0 | H24: =SUM(F24:G24) -> 0
A25: OTHER | E25: =PRODUCT(B25*C25) -> 0 | F25: =PRODUCT(E25*18)/118 -> 0 | G25: =PRODUCT(B25*D25) -> 0 | H25: =SUM(F25:G25) -> 0
A26: OTHER | E26: =PRODUCT(B26*C26) -> 0 | F26: =PRODUCT(E26*18)/118 -> 0 | G26: =PRODUCT(B26*D26) -> 0 | H26: =SUM(F26:G26) -> 0
A27: OTHER | E27: =PRODUCT(B27*C27) -> 0 | F27: =PRODUCT(E27*18)/118 -> 0 | G27: =PRODUCT(B27*D27) -> 0 | H27: =SUM(F27:G27) -> 0
A28: OTHER | E28: =PRODUCT(B28*C28) -> 0 | F28: =PRODUCT(E28*18)/118 -> 0 | G28: =PRODUCT(B28*D28) -> 0 | H28: =SUM(F28:G28) -> 0
... A36: OTHER | E36: =PRODUCT(B36*C36) -> 0 | F36: =PRODUCT(E36*18)/118 -> 0 | G36: =PRODUCT(B36*D36) -> 0 | H36: =SUM(F36:G36) -> 0
A37: TOTALY | E37: =SUM(E5:E36) -> 0 | F37: =SUM(F5:F36) -> 0 | G37: =SUM(G5:G36) -> 0 | H37: =SUM(H5:H36) -> 0
A38: SUMMARY | C38: RWF | E38: NAME | G38: Phone | H38: RWF
A39: TOTAL RWF PAID ON MOMO PAY
A40: TOTAL RWF PAID ON CASH
A41: AMOUNT NOT INVOICED
A42: TOTAL RWF DEPPOSITED ON BANK
A43: MEMBERSHIP FEES REGISTRETION
A44: MEMBERSHIP FEES CONTRIBUTION
A45: TOTAL INCOME | C45: =SUM(C39+C40+C41+C42+C43+C44) -> 0
A46: TIMBER SUMMARY
A48: REPORT SUMMARY | C48: TIMBER TYPE | E48: NUMBER OF QUANTITY
C49: INTURUSU | E49: =SUM(B9:B12) -> 0
C50: PINUS | E50: =SUM(B6:B8) -> 0
C51: PALNCHE | E51: =SUM(B13:B14) -> 0
C52: IBIPANDE | E52: =SUM(B17:B18) -> 0
C53: UMUSAVE | E53: =SUM(B19:B20) -> 0
C54: OTHER TYPE OF TIMBER | E54: =B29 -> 0
C55: OTHER TYPE OF TIMBER | E55: =B30 -> 0
C56: OTHER TYPE OF TIMBER | E56: =B31 -> 0
C57: OTHER TYPE OF TIMBER | E57: =B32 -> 0
C58: OTHER TYPE OF TIMBER | E58: =B33 -> 0
C59: OTHER TYPE OF TIMBER | E59: =B34 -> 0
C60: OTHER TYPE OF TIMBER | E60: =B35 -> 0
C61: OTHER TYPE OF TIMBER | E61: =B36 -> 0
C62: TOTAL TIMBER | E62: =SUM(E49:H61) -> 0

Sheet FOURTH
A1: QUANTITY REPORT
A3: MONTHS REPORT OF NOVEMBER 2025
A5: NAME OF TIMBER | B5: No OF TIMBER | C5: PRICE OF TIMBER | E5: TOTAL COST | F5: TVA | G5: MSF | H5: TVA+MSF
A6: PINUS NINI | E6: =PRODUCT(B6*C6) -> 0 | F6: =PRODUCT(E6*18)/118 -> 0 | G6: =PRODUCT(B6*50) -> 0 | H6: =SUM(F6:G6) -> 0
A7: PINUS NTOYA | E7: =PRODUCT(B7*C7) -> 0 | F7: =PRODUCT(E7*18)/118 -> 0 | G7: =PRODUCT(B7*50) -> 0 | H7: =SUM(F7:G7) -> 0
A8: PINUS | E8: =PRODUCT(B8*C8) -> 0 | F8: =PRODUCT(E8*18)/118 -> 0 | G8: =PRODUCT(B8*50) -> 0 | H8: =SUM(F8:G8) -> 0
A9: MADIRIYE NINI | E9: =PRODUCT(B9*C9) -> 0 | F9: =PRODUCT(E9*18)/118 -> 0 | G9: =PRODUCT(B9*30) -> 0 | H9: =SUM(F9:G9) -> 0
A10: MADIRIYE NTOYA | E10: =PRODUCT(B10*C10) -> 0 | F10: =PRODUCT(E10*18)/118 -> 0 | G10: =PRODUCT(B10*30) -> 0 | H10: =SUM(F10:G10) -> 0
A11: MADRIEN | E11: =PRODUCT(B11*C11) -> 0 | F11: =PRODUCT(E11*18)/118 -> 0 | G11: =PRODUCT(B11*30) -> 0 | H11: =SUM(F11:G11) -> 0
A12: MADRIEN | E12: =PRODUCT(B12*C12) -> 0 | F12: =PRODUCT(E12*18)/118 -> 0 | G12: =PRODUCT(B12*30) -> 0 | H12: =SUM(F12:G12) -> 0
A13: PLANCHE | E13: =PRODUCT(B13*C13) -> 0 | F13: =PRODUCT(E13*18)/118 -> 0 | G13: =PRODUCT(B13*20) -> 0 | H13: =SUM(F13:G13) -> 0
A14: PLANCHE | E14: =PRODUCT(B14*C14) -> 0 | F14: =PRODUCT(E14*18)/118 -> 0 | G14: =PRODUCT(B14*20) -> 0 | H14: =SUM(F14:G14) -> 0
A15: Other Timber for Difference Price
A16: NAME OF TIMBER | B16: No OF TIMBER | C16: P/U | D16: MSF | E16: TOTAL COST | F16: VAT | G16: MSF | H16: VTA+MST
A17: IBIPANDE | E17: =PRODUCT(B17*C17) -> 0 | F17: =PRODUCT(E17*18)/118 -> 0 | G17: =PRODUCT(B17*D17) -> 0 | H17: =SUM(F17:G17) -> 0
A18: IBIPANDE | E18: =PRODUCT(B18*C18) -> 0 | F18: =PRODUCT(E18*18)/118 -> 0 | G18: =PRODUCT(B18*D18) -> 0 | H18: =SUM(F18:G18) -> 0
A19: UMUSAVE | E19: =PRODUCT(B19*C19) -> 0 | F19: =PRODUCT(E19*18)/118 -> 0 | G19: =PRODUCT(B19*D19) -> 0 | H19: =SUM(F19:G19) -> 0
A20: UMUSAVE | E20: =PRODUCT(B20*C20) -> 0 | F20: =PRODUCT(E20*18)/118 -> 0 | G20: =PRODUCT(B20*D20) -> 0 | H20: =SUM(F20:G20) -> 0
A21: OTHER | E21: =PRODUCT(B21*C21) -> 0 | F21: =PRODUCT(E21*18)/118 -> 0 | G21: =PRODUCT(B21*D21) -> 0 | H21: =SUM(F21:G21) -> 0
A22: OTHER | E22: =PRODUCT(B22*C22) -> 0 | F22: =PRODUCT(E22*18)/118 -> 0 | G22: =PRODUCT(B22*D22) -> 0 | H22: =SUM(F22:G22) -> 0
A23: OTHER | E23: =PRODUCT(B23*C23) -> 0 | F23: =PRODUCT(E23*18)/118 -> 0 | G23: =PRODUCT(B23*D23) -> 0 | H23: =SUM(F23:G23) -> 0
A24: OTHER | E24: =PRODUCT(B24*C24) -> 0 | F24: =PRODUCT(E24*18)/118 -> 0 | G24: =PRODUCT(B24*D24) -> 0 | H24: =SUM(F24:G24) -> 0
A25: OTHER | E25: =PRODUCT(B25*C25) -> 0 | F25: =PRODUCT(E25*18)/118 -> 0 | G25: =PRODUCT(B25*D25) -> 0 | H25: =SUM(F25:G25) -> 0
A26: OTHER | E26: =PRODUCT(B26*C26) -> 0 | F26: =PRODUCT(E26*18)/118 -> 0 | G26: =PRODUCT(B26*D26) -> 0 | H26: =SUM(F26:G26) -> 0
A27: OTHER | E27: =PRODUCT(B27*C27) -> 0 | F27: =PRODUCT(E27*18)/118 -> 0 | G27: =PRODUCT(B27*D27) -> 0 | H27: =SUM(F27:G27) -> 0
A28: OTHER | E28: =PRODUCT(B28*C28) -> 0 | F28: =PRODUCT(E28*18)/118 -> 0 | G28: =PRODUCT(B28*D28) -> 0 | H28: =SUM(F28:G28) -> 0
... A36: OTHER | E36: =PRODUCT(B36*C36) -> 0 | F36: =PRODUCT(E36*18)/118 -> 0 | G36: =PRODUCT(B36*D36) -> 0 | H36: =SUM(F36:G36) -> 0
A37: TOTALY | E37: =SUM(E5:E36) -> 0 | F37: =SUM(F5:F36) -> 0 | G37: =SUM(G5:G36) -> 0 | H37: =SUM(H5:H36) -> 0
A38: SUMMARY | C38: RWF | E38: NAME | G38: Phone | H38: RWF
A39: TOTAL RWF PAID ON MOMO PAY
A40: TOTAL RWF PAID ON CASH
A41: AMOUNT NOT INVOICED
A42: TOTAL RWF DEPPOSITED ON BANK
A43: MEMBERSHIP FEES REGISTRETION
A44: MEMBERSHIP FEES CONTRIBUTION
A45: TOTAL INCOME | C45: =SUM(C39+C40+C41+C42+C43+C44) -> 0
A46: TIMBER SUMMARY
A48: REPORT SUMMARY | C48: TIMBER TYPE | E48: NUMBER OF QUANTITY
C49: INTURUSU | E49: =SUM(B9:B12) -> 0
C50: PINUS | E50: =SUM(B6:B8) -> 0
C51: PALNCHE | E51: =SUM(B13:B14) -> 0
C52: IBIPANDE | E52: =SUM(B17:B18) -> 0
C53: UMUSAVE | E53: =SUM(B19:B20) -> 0
C54: OTHER TYPE OF TIMBER | E54: =B29 -> 0
C55: OTHER TYPE OF TIMBER | E55: =B30 -> 0
C56: OTHER TYPE OF TIMBER | E56: =B31 -> 0
C57: OTHER TYPE OF TIMBER | E57: =B32 -> 0
C58: OTHER TYPE OF TIMBER | E58: =B33 -> 0
C59: OTHER TYPE OF TIMBER | E59: =B34 -> 0
C60: OTHER TYPE OF TIMBER | E60: =B35 -> 0
C61: OTHER TYPE OF TIMBER | E61: =B36 -> 0
C62: TOTAL TIMBER | E62: =SUM(E49:H61) -> 0

Sheet ALL TIMBER SUMMARY
A1: TIMBER SUMMARY
A3: TIMBER TYPE | D3: NUMBER OF QUANTITY
A4: INTURUSU | D4: =NYANZA!E49+KIREHE!E49+NYAGATARE!E49+KAYONZA!E49+MUSANZE!E49+MUSANZE!E49+RUBAVU!E49+KARONGI!E49+NYAMAGABE!E49+RUSIZI!E49+HUYE!E49+RUHANGO!E49+MUHANGA!E49+BUGESERA!E49+RWAMAGANA!E49+NYARUGENGE!E49+BISHENYI!E49+GAHANGA!E49+KIMIRONKO!E49+GISOZI!E49+GATSIBO!E49+GASHYUSHYA!E49+RUTSIRO!E49+NGORORERO!E49+THIRTH!E49+FOURTH!E49 -> 304476
A5: PINUS | D5: =NYANZA!E50+KIREHE!E50+NYAGATARE!E50+KAYONZA!E50+MUSANZE!E50+MUSANZE!E50+RUBAVU!E50+KARONGI!E50+NYAMAGABE!E50+RUSIZI!E50+HUYE!E50+RUHANGO!E50+MUHANGA!E50+BUGESERA!E50+RWAMAGANA!E50+NYARUGENGE!E50+BISHENYI!E50+GAHANGA!E50+KIMIRONKO!E50+GISOZI!E50+GATSIBO!E50+GASHYUSHYA!E50+RUTSIRO!E50+NGORORERO!E50+THIRTH!E50+FOURTH!E50 -> 17993
A6: PLANCHE | D6: =NYANZA!E51+KIREHE!E51+NYAGATARE!E51+KAYONZA!E51+MUSANZE!E51+MUSANZE!E51+RUBAVU!E51+KARONGI!E51+NYAMAGABE!E51+RUSIZI!E51+HUYE!E51+RUHANGO!E51+MUHANGA!E51+BUGESERA!E51+RWAMAGANA!E51+NYARUGENGE!E51+BISHENYI!E51+GAHANGA!E51+KIMIRONKO!E51+GISOZI!E51+GATSIBO!E51+GASHYUSHYA!E51+RUTSIRO!E51+NGORORERO!E51+THIRTH!E51+FOURTH!E51 -> 21755
A7: IBIPANDE | D7: =NYANZA!E52+KIREHE!E52+NYAGATARE!E52+KAYONZA!E52+MUSANZE!E52+MUSANZE!E52+RUBAVU!E52+KARONGI!E52+NYAMAGABE!E52+RUSIZI!E52+HUYE!E52+RUHANGO!E52+MUHANGA!E52+BUGESERA!E52+RWAMAGANA!E52+NYARUGENGE!E52+BISHENYI!E52+GAHANGA!E52+KIMIRONKO!E52+GISOZI!E52+GATSIBO!E52+GASHYUSHYA!E52+RUTSIRO!E52+NGORORERO!E52+THIRTH!E52+FOURTH!E52 -> 21263
A8: UMUSAVE | D8: =NYANZA!E53+KIREHE!E53+NYAGATARE!E53+KAYONZA!E53+MUSANZE!E53+MUSANZE!E53+RUBAVU!E53+KARONGI!E53+NYAMAGABE!E53+RUSIZI!E53+HUYE!E53+RUHANGO!E53+MUHANGA!E53+BUGESERA!E53+RWAMAGANA!E53+NYARUGENGE!E53+BISHENYI!E53+GAHANGA!E53+KIMIRONKO!E53+GISOZI!E53+GATSIBO!E53+GASHYUSHYA!E53+RUTSIRO!E53+NGORORERO!E53+THIRTH!E53+FOURTH!E53 -> 3098
A9: OTHER TYPE OF TIMBER | D9: =NYANZA!E54+KIREHE!E54+NYAGATARE!E54+KAYONZA!E54+MUSANZE!E54+MUSANZE!E54+RUBAVU!E54+KARONGI!E54+NYAMAGABE!E54+RUSIZI!E54+HUYE!E54+RUHANGO!E54+MUHANGA!E54+BUGESERA!E54+RWAMAGANA!E54+NYARUGENGE!E54+BISHENYI!E54+GAHANGA!E54+KIMIRONKO!E54+GISOZI!E54+GATSIBO!E54+GASHYUSHYA!E54+RUTSIRO!E54+NGORORERO!E54+THIRTH!E54+FOURTH!E54 -> 0
A10: OTHER TYPE OF TIMBER | D10: =NYANZA!E55+KIREHE!E55+NYAGATARE!E55+KAYONZA!E55+MUSANZE!E55+MUSANZE!E55+RUBAVU!E55+KARONGI!E55+NYAMAGABE!E55+RUSIZI!E55+HUYE!E55+RUHANGO!E55+MUHANGA!E55+BUGESERA!E55+RWAMAGANA!E55+NYARUGENGE!E55+BISHENYI!E55+GAHANGA!E55+KIMIRONKO!E55+GISOZI!E55+GATSIBO!E55+GASHYUSHYA!E55+RUTSIRO!E55+NGORORERO!E55+THIRTH!E55+FOURTH!E55 -> 0
A11: OTHER TYPE OF TIMBER | D11: =NYANZA!E56+KIREHE!E56+NYAGATARE!E56+KAYONZA!E56+MUSANZE!E56+MUSANZE!E56+RUBAVU!E56+KARONGI!E56+NYAMAGABE!E56+RUSIZI!E56+HUYE!E56+RUHANGO!E56+MUHANGA!E56+BUGESERA!E56+RWAMAGANA!E56+NYARUGENGE!E56+BISHENYI!E56+GAHANGA!E56+KIMIRONKO!E56+GISOZI!E56+GATSIBO!E56+GASHYUSHYA!E56+RUTSIRO!E56+NGORORERO!E56+THIRTH!E56+FOURTH!E56 -> 0
A12: OTHER TYPE OF TIMBER | D12: =NYANZA!E57+KIREHE!E57+NYAGATARE!E57+KAYONZA!E57+MUSANZE!E57+MUSANZE!E57+RUBAVU!E57+KARONGI!E57+NYAMAGABE!E57+RUSIZI!E57+HUYE!E57+RUHANGO!E57+MUHANGA!E57+BUGESERA!E57+RWAMAGANA!E57+NYARUGENGE!E57+BISHENYI!E57+GAHANGA!E57+KIMIRONKO!E57+GISOZI!E57+GATSIBO!E57+GASHYUSHYA!E57+RUTSIRO!E57+NGORORERO!E57+THIRTH!E57+FOURTH!E57 -> 0
A13: OTHER TYPE OF TIMBER | D13: =NYANZA!E58+KIREHE!E58+NYAGATARE!E58+KAYONZA!E58+MUSANZE!E58+MUSANZE!E58+RUBAVU!E58+KARONGI!E58+NYAMAGABE!E58+RUSIZI!E58+HUYE!E58+RUHANGO!E58+MUHANGA!E58+BUGESERA!E58+RWAMAGANA!E58+NYARUGENGE!E58+BISHENYI!E58+GAHANGA!E58+KIMIRONKO!E58+GISOZI!E58+GATSIBO!E58+GASHYUSHYA!E58+RUTSIRO!E58+NGORORERO!E58+THIRTH!E58+FOURTH!E58 -> 0
A14: OTHER TYPE OF TIMBER | D14: =NYANZA!E59+KIREHE!E59+NYAGATARE!E59+KAYONZA!E59+MUSANZE!E59+MUSANZE!E59+RUBAVU!E59+KARONGI!E59+NYAMAGABE!E59+RUSIZI!E59+HUYE!E59+RUHANGO!E59+MUHANGA!E59+BUGESERA!E59+RWAMAGANA!E59+NYARUGENGE!E59+BISHENYI!E59+GAHANGA!E59+KIMIRONKO!E59+GISOZI!E59+GATSIBO!E59+GASHYUSHYA!E59+RUTSIRO!E59+NGORORERO!E59+THIRTH!E59+FOURTH!E59 -> 0
A15: OTHER TYPE OF TIMBER | D15: =NYANZA!E60+KIREHE!E60+NYAGATARE!E60+KAYONZA!E60+MUSANZE!E60+MUSANZE!E60+RUBAVU!E60+KARONGI!E60+NYAMAGABE!E60+RUSIZI!E60+HUYE!E60+RUHANGO!E60+MUHANGA!E60+BUGESERA!E60+RWAMAGANA!E60+NYARUGENGE!E60+BISHENYI!E60+GAHANGA!E60+KIMIRONKO!E60+GISOZI!E60+GATSIBO!E60+GASHYUSHYA!E60+RUTSIRO!E60+NGORORERO!E60+THIRTH!E60+FOURTH!E60 -> 0
A16: OTHER TYPE OF TIMBER | D16: =NYANZA!E61+KIREHE!E61+NYAGATARE!E61+KAYONZA!E61+MUSANZE!E61+MUSANZE!E61+RUBAVU!E61+KARONGI!E61+NYAMAGABE!E61+RUSIZI!E61+HUYE!E61+RUHANGO!E61+MUHANGA!E61+BUGESERA!E61+RWAMAGANA!E61+NYARUGENGE!E61+BISHENYI!E61+GAHANGA!E61+KIMIRONKO!E61+GISOZI!E61+GATSIBO!E61+GASHYUSHYA!E61+RUTSIRO!E61+NGORORERO!E61+THIRTH!E61+FOURTH!E61 -> 0
A17: TOTAL TIMBER | D17: =SUM(D4:D16) -> 368585
