Workbook

Sheet FINACHIAL REPORT
A1: RWVCA REPORT DATE ….........
A2: RWANDA WOOD VALUE CHAIN ASSOCIATION
A4: ICPCs NAME | B4: TVA IN | C4: MSF IN | D4: MS REGIS | E4: MS CONTR | F4: TVA+MSF | G4: FR NOT INVOICED | H4: MOMO | I4: PAID ON BANK | J4: CASH
A5: GISOZI | B5: =GISOZI!F37 -> 0 | C5: =GISOZI!G37 -> 0 | F5: =SUM(B5:C5) -> 0 | G5: =GISOZI!C41 -> 0 | H5: =GISOZI!C39 -> 0 | I5: =GISOZI!C42 -> 0 | J5: =GISOZI!C40 -> 0
A6: GAHANGA | B6: =GAHANGA!F29 -> 0 | C6: =GAHANGA!G29 -> 0 | F6: =SUM(B6:C6) -> 0 | G6: =GAHANGA!C33 -> 0 | H6: =GAHANGA!C31 -> 0 | I6: =GAHANGA!C34 -> 0 | J6: =GAHANGA!C32 -> 0
A7: KIMIROMKO | B7: =KIMIRONKO!F37 -> 7667622 | C7: =KIMIRONKO!G37 -> 695700 | F7: =SUM(B7:C7) -> 8363322 | G7: =KIMIRONKO!C41 -> 0 | H7: =KIMIRONKO!C39 -> 8363322 | I7: =KIMIRONKO!C42 -> 0 | J7: =KIMIRONKO!C40 -> 0
A8: BISHENYI | B8: =BISHENYI!F29 -> 10441806 | C8: =BISHENYI!G29 -> 882170 | F8: =SUM(B8:C8) -> 11323976 | G8: =BISHENYI!C33 -> 0 | H8: =BISHENYI!C31 -> 11325998 | I8: =BISHENYI!C34 -> 0 | J8: =BISHENYI!C32 -> 0
A9: RWAMAGANA | B9: =RWAMAGANA!F29 -> 0 | C9: =RWAMAGANA!G29 -> 0 | F9: =SUM(B9:C9) -> 0 | G9: =RWAMAGANA!C33 -> 0 | H9: =RWAMAGANA!C31 -> 0 | I9: =RWAMAGANA!C34 -> 0 | J9: =RWAMAGANA!C32 -> 0
A10: BUGESERA | B10: =BUGESERA!F29 -> 0 | C10: =BUGESERA!G29 -> 0 | F10: =SUM(B10:C10) -> 0 | G10: =BUGESERA!C33 -> 0 | H10: =BUGESERA!C31 -> 0 | I10: =BUGESERA!C34 -> 0 | J10: =BUGESERA!C32 -> 0
A11: MUHANGA | B11: =MUHANGA!F37 -> 0 | C11: =MUHANGA!G37 -> 0 | F11: =SUM(B11:C11) -> 0 | G11: =MUHANGA!C41 -> 0 | H11: =MUHANGA!C39 -> 0 | I11: =MUHANGA!C42 -> 0 | J11: =MUHANGA!C40 -> 0
A12: RUHANGO | B12: =RUHANGO!F37 -> 0 | C12: =RUHANGO!G37 -> 0 | F12: =SUM(B12:C12) -> 0 | G12: =RUHANGO!C41 -> 0 | H12: =RUHANGO!C39 -> 0 | I12: =RUHANGO!C42 -> 0 | J12: =RUHANGO!C40 -> 0
A13: HUYE | B13: =HUYE!F37 -> 0 | C13: =HUYE!G37 -> 0 | F13: =SUM(B13:C13) -> 0 | G13: =HUYE!C41 -> 0 | H13: =HUYE!C39 -> 0 | I13: =HUYE!C42 -> 0 | J13: =HUYE!C40 -> 0
A14: RUSIZI | B14: =RUSIZI!F37 -> 0 | C14: =RUSIZI!G37 -> 0 | F14: =SUM(B14:C14) -> 0 | G14: =RUSIZI!C41 -> 0 | H14: =RUSIZI!C39 -> 0 | I14: =RUSIZI!C42 -> 0 | J14: =RUSIZI!C40 -> 0
A15: NYAMASHEKE | B15: =NYAMASHEKE!F37 -> 0 | C15: =NYAMASHEKE!G37 -> 0 | F15: =SUM(B15:C15) -> 0 | G15: =NYAMASHEKE!C41 -> 0 | H15: =NYAMASHEKE!C39 -> 0 | I15: =NYAMASHEKE!C42 -> 0 | J15: =NYAMASHEKE!C40 -> 0
A16: KARONGI | B16: =KARONGI!F37 -> 0 | C16: =KARONGI!G37 -> 0 | F16: =SUM(B16:C16) -> 0 | G16: =KARONGI!C41 -> 0 | H16: =KARONGI!C39 -> 0 | I16: =KARONGI!C42 -> 0 | J16: =KARONGI!C40 -> 0
A17: RUBAVU | B17: =RUBAVU!F29 -> 0 | C17: =RUBAVU!G29 -> 0 | F17: =SUM(B17:C17) -> 0 | G17: =RUBAVU!C33 -> 0 | H17: =RUBAVU!C31 -> 0 | I17: =RUBAVU!C34 -> 0 | J17: =RUBAVU!C32 -> 0
A18: MUSANZE | B18: =MUSANZE!F29 -> 0 | C18: =MUSANZE!G29 -> 0 | F18: =SUM(B18:C18) -> 0 | G18: =MUSANZE!C33 -> 0 | H18: =MUSANZE!C31 -> 0 | I18: =MUSANZE!C34 -> 0 | J18: =MUSANZE!C32 -> 0
A19: KAYONZA | B19: =KAYONZA!F29 -> 0 | C19: =KAYONZA!G29 -> 0 | F19: =SUM(B19:C19) -> 0 | G19: =KAYONZA!C33 -> 0 | H19: =KAYONZA!C31 -> 0 | I19: =KAYONZA!C34 -> 0 | J19: =KAYONZA!C32 -> 0
A20: NYAGATARE | B20: =NYAGATARE!F29 -> 0 | C20: =NYAGATARE!G29 -> 0 | F20: =SUM(B20:C20) -> 0 | G20: =NYAGATARE!C33 -> 0 | H20: =NYAGATARE!C31 -> 0 | I20: =NYAGATARE!C34 -> 0 | J20: =NYAGATARE!C32 -> 0
A21: KIREHE | B21: =KIREHE!F29 -> 0 | C21: =KIREHE!G29 -> 0 | F21: =SUM(B21:C21) -> 0 | G21: =KIREHE!C33 -> 0 | H21: =KIREHE!C31 -> 0 | I21: =KIREHE!C34 -> 0 | J21: =KIREHE!C32 -> 0
A22: NYANZA | B22: =NYANZA!F29 -> 0 | C22: =NYANZA!G29 -> 0 | F22: =SUM(B22:C22) -> 0 | G22: =NYANZA!C33 -> 0 | H22: =NYANZA!C31 -> 0 | I22: =NYANZA!C34 -> 0 | J22: =NYANZA!C32 -> 0
A23: NYARUGENGE | B23: =NYARUGENGE!F29 -> 0 | C23: =NYARUGENGE!G29 -> 0 | F23: =SUM(B23:C23) -> 0 | G23: =NYARUGENGE!C33 -> 0 | H23: =NYARUGENGE!C31 -> 0 | I23: =NYARUGENGE!C34 -> 0 | J23: =NYARUGENGE!C32 -> 0
A24: GATSIBO | B24: =GATSIBO!F29 -> 0 | C24: =GATSIBO!G29 -> 0 | F24: =SUM(B24:C24) -> 0 | G24: =GATSIBO!C33 -> 0 | H24: =GATSIBO!C31 -> 0 | I24: =GATSIBO!C34 -> 0 | J24: =GATSIBO!C32 -> 0
F25: =SUM(B25:C25) -> 0
F26: =SUM(B26:C26) -> 0
F27: =SUM(B27:C27) -> 0
F28: =SUM(B28:C28) -> 0
B29: =SUM(B5:B28) -> 18109428 | C29: =SUM(C5:C28) -> 1577870 | D29: =SUM(D5:D28) -> 0 | E29: =SUM(E5:E28) -> 0 | F29: =SUM(F5:F28) -> 19687298 | G29: =SUM(G5:G28) -> 0 | H29: =SUM(H5:H28) -> 19689320 | I29: =SUM(I5:I28) -> 0 | J29: =SUM(J5:J28) -> 0
E30: REPORT DESCRIPTION
A31: REPORT SUMMARY
A32: VAT+MSF | C32: =SUM(B29:C29) -> 19687298
A33: VAT+MSF+FR NOT INVOCED | C33: =SUM(F29,G29) -> 19687298
A34: MOMO+CASH+BANK | C34: =SUM(H29,J29,I29) -> 19689320
A35: MS REGIST+MS CONTRIB | C35: =SUM(D29:E29) -> 0
A36: GRAND TOTAL | C36: =SUM(C33,C35) -> 19687298 | E36: COORDINATOR NAME: Chantal NIYIGENA
A37: TOTAL INCOME | C37: =SUM(C34:C35) -> 19689320
A38: RWANDA WOOD VALUE CHAIN ASSOCIATION

Sheet GASHYUSHYA
A1: QUANTITY REPORT
A3: MONTHS REPORT OF AUGUST 2025
A5: NAME OF TIMBER | B5: No OF TIMBER | C5: PRICE OF TIMBER | E5: TOTAL COST | F5: TVA | G5: MSF | H5: TVA+MSF
A6: PINUS NINI | E6: 0 | F6: 0 | G6: 0 | H6: 0
A7: PINUS NTOYA | E7: 0 | F7: 0 | G7: 0 | H7: 0
A8: PINUS | E8: 0 | F8: 0 | G8: 0 | H8: 0
A9: MADIRIYE NINI | E9: 0 | F9: 0 | G9: 0 | H9: 0
A10: MADIRIYE NTOYA | E10: 0 | F10: 0 | G10: 0 | H10: 0
A11: MADRIEN | E11: 0 | F11: 0 | G11: 0 | H11: 0
A12: MADRIEN | E12: 0 | F12: 0 | G12: 0 | H12: 0
A13: PLANCHE | E13: 0 | F13: 0 | G13: 0 | H13: 0
A14: PLANCHE | E14: 0 | F14: 0 | G14: 0 | H14: 0
A15: Other Timber for Difference Price
A16: NAME OF TIMBER | B16: No OF TIMBER | C16: P/U | D16: MSF | E16: TOTAL COST | F16: VAT | G16: MSF | H16: VTA+MST
A17: IBIPANDE | E17: 0 | F17: 0 | G17: 0 | H17: 0
A18: IBIPANDE | E18: 0 | F18: 0 | G18: 0 | H18: 0
A19: UMUSAVE | E19: 0 | F19: 0 | G19: 0 | H19: 0
A20: UMUSAVE | E20: 0 | F20: 0 | G20: 0 | H20: 0
A21: OTHER | E21: 0 | F21: 0 | G21: 0 | H21: 0
A22: OTHER | E22: 0 | F22: 0 | G22: 0 | H22: 0
A23: OTHER | E23: 0 | F23: 0 | G23: 0 | H23: 0
A24: OTHER | E24: 0 | F24: 0 | G24: 0 | H24: 0
A25: OTHER | E25: 0 | F25: 0 | G25: 0 | H25: 0
A26: OTHER | E26: 0 | F26: 0 | G26: 0 | H26: 0
A27: OTHER | E27: 0 | F27: 0 | G27: 0 | H27: 0
A28: OTHER | E28: 0 | F28: 0 | G28: 0 | H28: 0
A29: TOTALY | E29: 0 | F29: 0 | G29: 0 | H29: 0
A30: SUMMARY | C30: RWF | E30: NAME | G30: Phone | H30: RWF
A31: TOTAL RWF PAID ON MOMO PAY
A32: TOTAL RWF PAID ON CASH
A33: AMOUNT NOT INVOICED
A34: TOTAL RWF DEPPOSITED ON BANK
A35: MEMBERSHIP FEES REGISTRETION
A36: MEMBERSHIP FEES CONTRIBUTION
A37: TOTAL INCOME | C37: 0
A38: TIMBER SUMMARY
B40: TIMBER TYPE | E40: NUMBER OF QUANTITY
B41: INTURUSU | E41: =SUM(B9:B12) -> 0
B42: PINUS | E42: =SUM(B6:B8) -> 0
B43: PALNCHE | E43: =SUM(B13:B14) -> 0
B44: IBIPANDE | E44: =SUM(B17:B18) -> 0
B45: UMUSAVE | E45: =SUM(B19:B20) -> 0
B46: OTHER | E46: =B21 -> 0
B47: OTHER | E47: =B22 -> 0
B48: OTHER | E48: =B23 -> 0
B49: OTHER | E49: =B24 -> 0
B50: OTHER | E50: =B25 -> 0
B51: OTHER | E51: =B26 -> 0
B52: OTHER | E52: =B27 -> 0
B53: OTHER | E53: =B28 -> 0
B54: TOTAL TIMBER | E54: =SUM(E41:H53) -> 0

Sheet NYAMAGABE
A1: QUANTITY REPORT
A3: MONTHS REPORT OF AUGUST 2025
A5: NAME OF TIMBER | B5: No OF TIMBER | C5: PRICE OF TIMBER | E5: TOTAL COST | F5: TVA | G5: MSF | H5: TVA+MSF
A6: PINUS NINI | E6: 0 | F6: 0 | G6: 0 | H6: 0
A7: PINUS NTOYA | E7: 0 | F7: 0 | G7: 0 | H7: 0
A8: PINUS | E8: 0 | F8: 0 | G8: 0 | H8: 0
A9: MADIRIYE NINI | E9: 0 | F9: 0 | G9: 0 | H9: 0
A10: MADIRIYE NTOYA | E10: 0 | F10: 0 | G10: 0 | H10: 0
A11: MADRIEN | E11: 0 | F11: 0 | G11: 0 | H11: 0
A12: MADRIEN | E12: 0 | F12: 0 | G12: 0 | H12: 0
A13: PLANCHE | E13: 0 | F13: 0 | G13: 0 | H13: 0
A14: PLANCHE | E14: 0 | F14: 0 | G14: 0 | H14: 0
A15: Other Timber for Difference Price
A16: NAME OF TIMBER | B16: No OF TIMBER | C16: P/U | D16: MSF | E16: TOTAL COST | F16: VAT | G16: MSF | H16: VTA+MST
A17: IBIPANDE | E17: 0 | F17: 0 | G17: 0 | H17: 0
A18: IBIPANDE | E18: 0 | F18: 0 | G18: 0 | H18: 0
A19: UMUSAVE | E19: 0 | F19: 0 | G19: 0 | H19: 0
A20: UMUSAVE | E20: 0 | F20: 0 | G20: 0 | H20: 0
A21: OTHER | E21: 0 | F21: 0 | G21: 0 | H21: 0
A22: OTHER | E22: 0 | F22: 0 | G22: 0 | H22: 0
A23: OTHER | E23: 0 | F23: 0 | G23: 0 | H23: 0
A24: OTHER | E24: 0 | F24: 0 | G24: 0 | H24: 0
A25: OTHER | E25: 0 | F25: 0 | G25: 0 | H25: 0
A26: OTHER | E26: 0 | F26: 0 | G26: 0 | H26: 0
A27: OTHER | E27: 0 | F27: 0 | G27: 0 | H27: 0
A28: OTHER | E28: 0 | F28: 0 | G28: 0 | H28: 0
A29: TOTALY | E29: 0 | F29: 0 | G29: 0 | H29: 0
A30: SUMMARY | C30: RWF | E30: NAME | G30: Phone | H30: RWF
A31: TOTAL RWF PAID ON MOMO PAY
A32: TOTAL RWF PAID ON CASH
A33: AMOUNT NOT INVOICED
A34: TOTAL RWF DEPPOSITED ON BANK
A35: MEMBERSHIP FEES REGISTRETION
A36: MEMBERSHIP FEES CONTRIBUTION
A37: TOTAL INCOME | C37: 0
A38: TIMBER SUMMARY
B40: TIMBER TYPE | E40: NUMBER OF QUANTITY
B41: INTURUSU | E41: =SUM(B9:B12) -> 0
B42: PINUS | E42: =SUM(B6:B8) -> 0
B43: PALNCHE | E43: =SUM(B13:B14) -> 0
B44: IBIPANDE | E44: =SUM(B17:B18) -> 0
B45: UMUSAVE | E45: =SUM(B19:B20) -> 0
B46: OTHER | E46: =B21 -> 0
B47: OTHER | E47: =B22 -> 0
B48: OTHER | E48: =B23 -> 0
B49: OTHER | E49: =B24 -> 0
B50: OTHER | E50: =B25 -> 0
B51: OTHER | E51: =B26 -> 0
B52: OTHER | E52: =B27 -> 0
B53: OTHER | E53: =B28 -> 0
B54: TOTAL TIMBER | E54: =SUM(E41:H53) -> 0

Sheet GISAGARA
A1: QUANTITY REPORT
A3: MONTHS REPORT OF AUGUST 2025
A5: NAME OF TIMBER | B5: No OF TIMBER | C5: PRICE OF TIMBER | E5: TOTAL COST | F5: TVA | G5: MSF | H5: TVA+MSF
A6: PINUS NINI | E6: 0 | F6: 0 | G6: 0 | H6: 0
A7: PINUS NTOYA | E7: 0 | F7: 0 | G7: 0 | H7: 0
A8: PINUS | E8: 0 | F8: 0 | G8: 0 | H8: 0
A9: MADIRIYE NINI | E9: 0 | F9: 0 | G9: 0 | H9: 0
A10: MADIRIYE NTOYA | E10: 0 | F10: 0 | G10: 0 | H10: 0
A11: MADRIEN | E11: 0 | F11: 0 | G11: 0 | H11: 0
A12: MADRIEN | E12: 0 | F12: 0 | G12: 0 | H12: 0
A13: PLANCHE | E13: 0 | F13: 0 | G13: 0 | H13: 0
A14: PLANCHE | E14: 0 | F14: 0 | G14: 0 | H14: 0
A15: Other Timber for Difference Price
A16: NAME OF TIMBER | B16: No OF TIMBER | C16: P/U | D16: MSF | E16: TOTAL COST | F16: VAT | G16: MSF | H16: VTA+MST
A17: IBIPANDE | E17: 0 | F17: 0 | G17: 0 | H17: 0
A18: IBIPANDE | E18: 0 | F18: 0 | G18: 0 | H18: 0
A19: UMUSAVE | E19: 0 | F19: 0 | G19: 0 | H19: 0
A20: UMUSAVE | E20: 0 | F20: 0 | G20: 0 | H20: 0
A21: OTHER | E21: 0 | F21: 0 | G21: 0 | H21: 0
A22: OTHER | E22: 0 | F22: 0 | G22: 0 | H22: 0
A23: OTHER | E23: 0 | F23: 0 | G23: 0 | H23: 0
A24: OTHER | E24: 0 | F24: 0 | G24: 0 | H24: 0
A25: OTHER | E25: 0 | F25: 0 | G25: 0 | H25: 0
A26: OTHER | E26: 0 | F26: 0 | G26: 0 | H26: 0
A27: OTHER | E27: 0 | F27: 0 | G27: 0 | H27: 0
A28: OTHER | E28: 0 | F28: 0 | G28: 0 | H28: 0
A29: TOTALY | E29: 0 | F29: 0 | G29: 0 | H29: 0
A30: SUMMARY | C30: RWF | E30: NAME | G30: Phone | H30: RWF
A31: TOTAL RWF PAID ON MOMO PAY
A32: TOTAL RWF PAID ON CASH
A33: AMOUNT NOT INVOICED
A34: TOTAL RWF DEPPOSITED ON BANK
A35: MEMBERSHIP FEES REGISTRETION
A36: MEMBERSHIP FEES CONTRIBUTION
A37: TOTAL INCOME | C37: 0
A38: TIMBER SUMMARY
B40: TIMBER TYPE | E40: NUMBER OF QUANTITY
B41: INTURUSU | E41: =SUM(B9:B12) -> 0
B42: PINUS | E42: =SUM(B6:B8) -> 0
B43: PALNCHE | E43: =SUM(B13:B14) -> 0
B44: IBIPANDE | E44: =SUM(B17:B18) -> 0
B45: UMUSAVE | E45: =SUM(B19:B20) -> 0
B46: OTHER | E46: =B21 -> 0
B47: OTHER | E47: =B22 -> 0
B48: OTHER | E48: =B23 -> 0
B49: OTHER | E49: =B24 -> 0
B50: OTHER | E50: =B25 -> 0
B51: OTHER | E51: =B26 -> 0
B52: OTHER | E52: =B27 -> 0
B53: OTHER | E53: =B28 -> 0
B54: TOTAL TIMBER | E54: =SUM(E41:H53) -> 0

Sheet NGORORERO
A1: QUANTITY REPORT
A3: MONTHS REPORT OF AUGUST 2025
A5: NAME OF TIMBER | B5: No OF TIMBER | C5: PRICE OF TIMBER | E5: TOTAL COST | F5: TVA | G5: MSF | H5: TVA+MSF
A6: PINUS NINI | E6: 0 | F6: 0 | G6: 0 | H6: 0
A7: PINUS NTOYA | E7: 0 | F7: 0 | G7: 0 | H7: 0
A8: PINUS | E8: 0 | F8: 0 | G8: 0 | H8: 0
A9: MADIRIYE NINI | E9: 0 | F9: 0 | G9: 0 | H9: 0
A10: MADIRIYE NTOYA | E10: 0 | F10: 0 | G10: 0 | H10: 0
A11: MADRIEN | E11: 0 | F11: 0 | G11: 0 | H11: 0
A12: MADRIEN | E12: 0 | F12: 0 | G12: 0 | H12: 0
A13: PLANCHE | E13: 0 | F13: 0 | G13: 0 | H13: 0
A14: PLANCHE | E14: 0 | F14: 0 | G14: 0 | H14: 0
A15: Other Timber for Difference Price
A16: NAME OF TIMBER | B16: No OF TIMBER | C16: P/U | D16: MSF | E16: TOTAL COST | F16: VAT | G16: MSF | H16: VTA+MST
A17: IBIPANDE | E17: 0 | F17: 0 | G17: 0 | H17: 0
A18: IBIPANDE | E18: 0 | F18: 0 | G18: 0 | H18: 0
A19: UMUSAVE | E19: 0 | F19: 0 | G19: 0 | H19: 0
A20: UMUSAVE | E20: 0 | F20: 0 | G20: 0 | H20: 0
A21: OTHER | E21: 0 | F21: 0 | G21: 0 | H21: 0
A22: OTHER | E22: 0 | F22: 0 | G22: 0 | H22: 0
A23: OTHER | E23: 0 | F23: 0 | G23: 0 | H23: 0
A24: OTHER | E24: 0 | F24: 0 | G24: 0 | H24: 0
A25: OTHER | E25: 0 | F25: 0 | G25: 0 | H25: 0
A26: OTHER | E26: 0 | F26: 0 | G26: 0 | H26: 0
A27: OTHER | E27: 0 | F27: 0 | G27: 0 | H27: 0
A28: OTHER | E28: 0 | F28: 0 | G28: 0 | H28: 0
A29: TOTALY | E29: 0 | F29: 0 | G29: 0 | H29: 0
A30: SUMMARY | C30: RWF | E30: NAME | G30: Phone | H30: RWF
A31: TOTAL RWF PAID ON MOMO PAY
A32: TOTAL RWF PAID ON CASH
A33: AMOUNT NOT INVOICED
A34: TOTAL RWF DEPPOSITED ON BANK
A35: MEMBERSHIP FEES REGISTRETION
A36: MEMBERSHIP FEES CONTRIBUTION
A37: TOTAL INCOME | C37: 0
A38: TIMBER SUMMARY
B40: TIMBER TYPE | E40: NUMBER OF QUANTITY
B41: INTURUSU | E41: =SUM(B9:B12) -> 0
B42: PINUS | E42: =SUM(B6:B8) -> 0
B43: PALNCHE | E43: =SUM(B13:B14) -> 0
B44: IBIPANDE | E44: =SUM(B17:B18) -> 0
B45: UMUSAVE | E45: =SUM(B19:B20) -> 0
B46: OTHER | E46: =B21 -> 0
B47: OTHER | E47: =B22 -> 0
B48: OTHER | E48: =B23 -> 0
B49: OTHER | E49: =B24 -> 0
B50: OTHER | E50: =B25 -> 0
B51: OTHER | E51: =B26 -> 0
B52: OTHER | E52: =B27 -> 0
B53: OTHER | E53: =B28 -> 0
B54: TOTAL TIMBER | E54: =SUM(E41:H53) -> 0

Sheet GISOZI
A1: QUANTITY REPORT
A3: MONTHS REPORT OF AUGUST 2025
A5: NAME OF TIMBER | B5: No OF TIMBER | C5: PRICE OF TIMBER | E5: TOTAL COST | F5: TVA | G5: MSF | H5: TVA+MSF
A6: PINUS NINI | E6: =PRODUCT(B6*C6) -> 0 | F6: =PRODUCT(E6*18)/118 -> 0 | G6: =PRODUCT(B6*50) -> 0 | H6: =SUM(F6:G6) -> 0
A7: PINUS NTOYA | E7: =PRODUCT(B7*C7) -> 0 | F7: =PRODUCT(E7*18)/118 -> 0 | G7: =PRODUCT(B7*50) -> 0 | H7: =SUM(F7:G7) -> 0
A8: PINUS | E8: =PRODUCT(B8*C8) -> 0 | F8: =PRODUCT(E8*18)/118 -> 0 | G8: =PRODUCT(B8*50) -> 0 | H8: =SUM(F8:G8) -> 0
A9: MADIRIYE NINI | E9: =PRODUCT(B9*C9) -> 0 | F9: =PRODUCT(E9*18)/118 -> 0 | G9: =PRODUCT(B9*30) -> 0 | H9: =SUM(F9:G9) -> 0
A10: MADIRIYE NTOYA | E10: =PRODUCT(B10*C10) -> 0 | F10: =PRODUCT(E10*18)/118 -> 0 | G10: =PRODUCT(B10*30) -> 0 | H10: =SUM(F10:G10) -> 0
A11: MADRIEN | E11: =PRODUCT(B11*C11) -> 0 | F11: =PRODUCT(E11*18)/118 -> 0 | G11: =PRODUCT(B11*30) -> 0 | H11: =SUM(F11:G11) -> 0
A12: MADRIEN | E12: =PRODUCT(B12*C12) -> 0 | F12: =PRODUCT(E12*18)/118 -> 0 | G12: =PRODUCT(B12*30) -> 0 | H12: =SUM(F12:G12) -> 0
A13: PLANCHE | E13: =PRODUCT(B13*C13) -> 0 | F13: =PRODUCT(E13*18)/118 -> 0 | G13: =PRODUCT(B13*20) -> 0 | H13: =SUM(F13:G13) -> 0
A14: PLANCHE | E14: =PRODUCT(B14*C14) -> 0 | F14: =PRODUCT(E14*18)/118 -> 0 | G14: =PRODUCT(B14*20) -> 0 | H14: =SUM(F14:G14) -> 0
A15: Other Timber for Difference Price
A16: NAME OF TIMBER | B16: No OF TIMBER | C16: P/U | D16: MSF | E16: TOTAL COST | F16: VAT | G16: MSF | H16: VTA+MST
A17: IBIPANDE | E17: 0 | F17: 0 | G17: 0 | H17: 0
A18: IBIPANDE | E18: 0 | F18: 0 | G18: 0 | H18: 0
A19: UMUSAVE | E19: 0 | F19: 0 | G19: 0 | H19: 0
A20: UMUSAVE | E20: 0 | F20: 0 | G20: 0 | H20: 0
A21: OTHER | E21: 0 | F21: 0 | G21: 0 | H21: 0
A22: OTHER | E22: 0 | F22: 0 | G22: 0 | H22: 0
A23: OTHER | E23: 0 | F23: 0 | G23: 0 | H23: 0
A24: OTHER | E24: 0 | F24: 0 | G24: 0 | H24: 0
A25: OTHER | E25: 0 | F25: 0 | G25: 0 | H25: 0
A26: OTHER | E26: 0 | F26: 0 | G26: 0 | H26: 0
A27: OTHER | E27: 0 | F27: 0 | G27: 0 | H27: 0
A28: OTHER | E28: 0 | F28: 0 | G28: 0 | H28: 0
... A36: OTHER | E36: 0 | F36: 0 | G36: 0 | H36: 0
A37: TOTALY | E37: =SUM(E5:E36) -> 0 | F37: =SUM(F5:F36) -> 0 | G37: =SUM(G5:G36) -> 0 | H37: =SUM(H5:H36) -> 0
A38: SUMMARY | C38: RWF | E38: NAME | G38: Phone | H38: RWF
A39: TOTAL RWF PAID ON MOMO PAY
A40: TOTAL RWF PAID ON CASH
A41: AMOUNT NOT INVOICED
A42: TOTAL RWF DEPPOSITED ON BANK
A43: MEMBERSHIP FEES REGISTRETION
A44: MEMBERSHIP FEES CONTRIBUTION
A45: TOTAL INCOME | C45: =SUM(C39:C44) -> 0
A46: TIMBER SUMMARY
B48: TIMBER TYPE | E48: NUMBER OF QUANTITY
B49: INTURUSU | E49: =SUM(B9:B12) -> 0
B50: PINUS | E50: =SUM(B6:B8) -> 0
B51: PALNCHE | E51: =SUM(B13:B14) -> 0
B52: IBIPANDE | E52: =SUM(B17:B18) -> 0
B53: UMUSAVE | E53: =SUM(B19:B20) -> 0
B54: OTHER | E54: =B29 -> 0
B55: OTHER | E55: =B30 -> 0
B56: OTHER | E56: =B31 -> 0
B57: OTHER | E57: =B32 -> 0
B58: OTHER | E58: =B33 -> 0
B59: OTHER | E59: =B34 -> 0
B60: OTHER | E60: =B35 -> 0
B61: OTHER | E61: =B36 -> 0
B62: TOTAL TIMBER | E62: =SUM(E49:H61) -> 0

Sheet BISHENYI
A1: QUANTITY REPORT
A3: MONTHS REPORT OF MAY 2026
A5: NAME OF TIMBER | B5: No OF TIMBER | C5: PRICE OF TIMBER | E5: TOTAL COST | F5: TVA | G5: MSF | H5: TVA+MSF
A6: PINUS NINI | E6: =PRODUCT(B6*C6) -> 0 | F6: =PRODUCT(E6*18)/118 -> 0 | G6: =PRODUCT(B6*50) -> 0 | H6: =SUM(F6:G6) -> 0
A7: PINUS NTOYA | B7: 190 | C7: 7670 | E7: =PRODUCT(B7*C7) -> 1457300 | F7: =PRODUCT(E7*18)/118 -> 222300 | G7: =PRODUCT(B7*50) -> 9500 | H7: =SUM(F7:G7) -> 231800
A8: PINUS | E8: =PRODUCT(B8*C8) -> 0 | F8: =PRODUCT(E8*18)/118 -> 0 | G8: =PRODUCT(B8*50) -> 0 | H8: =SUM(F8:G8) -> 0
A9: MADIRIYE NINI | E9: =PRODUCT(B9*C9) -> 0 | F9: =PRODUCT(E9*18)/118 -> 0 | G9: =PRODUCT(B9*30) -> 0 | H9: =SUM(F9:G9) -> 0
A10: MADIRIYE NTOYA | B10: 26839 | C10: 2360 | E10: =PRODUCT(B10*C10) -> 63340040 | F10: =PRODUCT(E10*18)/118 -> 9662040 | G10: =PRODUCT(B10*30) -> 805170 | H10: =SUM(F10:G10) -> 10467210
A11: MADRIEN | E11: =PRODUCT(B11*C11) -> 0 | F11: =PRODUCT(E11*18)/118 -> 0 | G11: =PRODUCT(B11*30) -> 0 | H11: =SUM(F11:G11) -> 0
A12: MADRIEN | E12: =PRODUCT(B12*C12) -> 0 | F12: =PRODUCT(E12*18)/118 -> 0 | G12: =PRODUCT(B12*30) -> 0 | H12: =SUM(F12:G12) -> 0
A13: PLANCHE | B13: 1750 | C13: 1534 | E13: =PRODUCT(B13*C13) -> 2684500 | F13: =PRODUCT(E13*18)/118 -> 409500 | G13: =PRODUCT(B13*20) -> 35000 | H13: =SUM(F13:G13) -> 444500
A14: PLANCHE | E14: =PRODUCT(B14*C14) -> 0 | F14: =PRODUCT(E14*18)/118 -> 0 | G14: =PRODUCT(B14*20) -> 0 | H14: =SUM(F14:G14) -> 0
A15: Other Timber for Difference Price
A16: NAME OF TIMBER | B16: No OF TIMBER | C16: P/U | D16: MSF | E16: TOTAL COST | F16: VAT | G16: MSF | H16: VTA+MST
A17: IBIPANDE BYA PINUS | B17: 450 | C17: 2000 | D17: 50 | E17: =PRODUCT(B17*C17) -> 900000 | F17: =PRODUCT(E17*18)/118 -> 137288.14 | G17: =PRODUCT(B17*D17) -> 22500 | H17: =SUM(F17:G17) -> 159788.14
A18: DECHETS | B18: 7 | C18: 10000 | E18: =PRODUCT(B18*C18) -> 70000 | F18: =PRODUCT(E18*18)/118 -> 10677.966 | G18: =PRODUCT(B18*D18) -> 0 | H18: =SUM(F18:G18) -> 10677.966
A19: DECHETS | B19: 1 | D19: 10000 | E19: =PRODUCT(B19*C19) -> 0 | F19: =PRODUCT(E19*18)/118 -> 0 | G19: =PRODUCT(B19*D19) -> 10000 | H19: =SUM(F19:G19) -> 10000
A20: UMUSAVE | E20: =PRODUCT(B20*C20) -> 0 | F20: =PRODUCT(E20*18)/118 -> 0 | G20: =PRODUCT(B20*D20) -> 0 | H20: =SUM(F20:G20) -> 0
A21: OTHER | E21: =PRODUCT(B21*C21) -> 0 | F21: =PRODUCT(E21*18)/118 -> 0 | G21: =PRODUCT(B21*D21) -> 0 | H21: =SUM(F21:G21) -> 0
A22: OTHER | E22: =PRODUCT(B22*C22) -> 0 | F22: =PRODUCT(E22*18)/118 -> 0 | G22: =PRODUCT(B22*D22) -> 0 | H22: =SUM(F22:G22) -> 0
A23: OTHER | E23: =PRODUCT(B23*C23) -> 0 | F23: =PRODUCT(E23*18)/118 -> 0 | G23: =PRODUCT(B23*D23) -> 0 | H23: =SUM(F23:G23) -> 0
A24: OTHER | E24: =PRODUCT(B24*C24) -> 0 | F24: =PRODUCT(E24*18)/118 -> 0 | G24: =PRODUCT(B24*D24) -> 0 | H24: =SUM(F24:G24) -> 0
A25: OTHER | E25: =PRODUCT(B25*C25) -> 0 | F25: =PRODUCT(E25*18)/118 -> 0 | G25: =PRODUCT(B25*D25) -> 0 | H25: =SUM(F25:G25) -> 0
A26: OTHER | E26: =PRODUCT(B26*C26) -> 0 | F26: =PRODUCT(E26*18)/118 -> 0 | G26: =PRODUCT(B26*D26) -> 0 | H26: =SUM(F26:G26) -> 0
A27: OTHER | E27: =PRODUCT(B27*C27) -> 0 | F27: =PRODUCT(E27*18)/118 -> 0 | G27: =PRODUCT(B27*D27) -> 0 | H27: =SUM(F27:G27) -> 0
A28: OTHER | E28: =PRODUCT(B28*C28) -> 0 | F28: =PRODUCT(E28*18)/118 -> 0 | G28: =PRODUCT(B28*D28) -> 0 | H28: =SUM(F28:G28) -> 0
A29: TOTALY | E29: =SUM(E6:E28) -> 68451840 | F29: =SUM(F6:F28) -> 10441806 | G29: =SUM(G6:G28) -> 882170 | H29: =SUM(F29:G29) -> 11323976
A30: SUMMARY | C30: RWF | E30: NAME | G30: Phone | H30: RWF
A31: TOTAL RWF PAID ON MOMO PAY | C31: 11325998
A32: TOTAL RWF PAID ON CASH
A33: AMOUNT NOT INVOICED
A34: TOTAL RWF DEPPOSITED ON BANK
A35: MEMBERSHIP FEES REGISTRETION
A36: MEMBERSHIP FEES CONTRIBUTION
A37: TOTAL INCOME | C37: =SUM(C31:C36) -> 11325998
A38: TIMBER SUMMARY
B40: TIMBER TYPE | E40: NUMBER OF QUANTITY
B41: INTURUSU | E41: =SUM(B9:B12) -> 26839
B42: PINUS | E42: =SUM(B6:B8) -> 190
B43: PALNCHE | E43: =SUM(B13:B14) -> 1750
B44: IBIPANDE | E44: =SUM(B17:B18) -> 457
B45: UMUSAVE | E45: =SUM(B19:B20) -> 1
B46: OTHER | E46: =B21 -> 0
B47: OTHER | E47: =B22 -> 0
B48: OTHER | E48: =B23 -> 0
B49: OTHER | E49: =B24 -> 0
B50: OTHER | E50: =B25 -> 0
B51: OTHER | E51: =B26 -> 0
B52: OTHER | E52: =B27 -> 0
B53: OTHER | E53: =B28 -> 0
B54: TOTAL TIMBER | E54: =SUM(E41:H53) -> 29237

Sheet KIMIRONKO
A1: QUANTITY REPORT
A3: QUARTER 2 KIMIRONKO REPORT
A5: NAME OF TIMBER | B5: No OF TIMBER | C5: PRICE OF TIMBER | E5: TOTAL COST | F5: TVA | G5: MSF | H5: TVA+MSF
A6: PINUS NINI | C6: 15000 | E6: =PRODUCT(B6*C6) -> 0 | F6: =PRODUCT(E6*18)/118 -> 0 | G6: =PRODUCT(B6*50) -> 0 | H6: =SUM(F6:G6) -> 0
A7: PINUS NTOYA | C7: 9000 | E7: =PRODUCT(B7*C7) -> 0 | F7: =PRODUCT(E7*18)/118 -> 0 | G7: =PRODUCT(B7*50) -> 0 | H7: =SUM(F7:G7) -> 0
A8: PINUS | B8: 250 | C8: 7670 | E8: =PRODUCT(B8*C8) -> 1917500 | F8: =PRODUCT(E8*18)/118 -> 292500 | G8: =PRODUCT(B8*50) -> 12500 | H8: =SUM(F8:G8) -> 305000
A9: MADIRIYE NINI | B9: 100 | C9: 4130 | E9: =PRODUCT(B9*C9) -> 413000 | F9: =PRODUCT(E9*18)/118 -> 63000 | G9: =PRODUCT(B9*30) -> 3000 | H9: =SUM(F9:G9) -> 66000
A10: MADIRIYE NTOYA | B10: 20152 | C10: 2124 | E10: =PRODUCT(B10*C10) -> 42802848 | F10: =PRODUCT(E10*18)/118 -> 6529248 | G10: =PRODUCT(B10*30) -> 604560 | H10: =SUM(F10:G10) -> 7133808
A11: MADRIEN | C11: 3540 | E11: =PRODUCT(B11*C11) -> 0 | F11: =PRODUCT(E11*18)/118 -> 0 | G11: =PRODUCT(B11*30) -> 0 | H11: =SUM(F11:G11) -> 0
A12: MADRIEN | C12: 2006 | E12: =PRODUCT(B12*C12) -> 0 | F12: =PRODUCT(E12*18)/118 -> 0 | G12: =PRODUCT(B12*30) -> 0 | H12: =SUM(F12:G12) -> 0
A13: PLANCHE | B13: 3782 | C13: 1357 | E13: =PRODUCT(B13*C13) -> 5132174 | F13: =PRODUCT(E13*18)/118 -> 782874 | G13: =PRODUCT(B13*20) -> 75640 | H13: =SUM(F13:G13) -> 858514
A14: PLANCHE | E14: =PRODUCT(B14*C14) -> 0 | F14: =PRODUCT(E14*18)/118 -> 0 | G14: =PRODUCT(B14*20) -> 0 | H14: =SUM(F14:G14) -> 0
A15: Other Timber for Difference Price
A16: NAME OF TIMBER | B16: No OF TIMBER | C16: P/U | D16: MSF | E16: TOTAL COST | F16: VAT | G16: MSF | H16: VTA+MST
A17: IBIPANDE | E17: 0 | F17: 0 | G17: 0 | H17: 0
A18: IBIPANDE | E18: 0 | F18: 0 | G18: 0 | H18: 0
A19: UMUSAVE | E19: 0 | F19: 0 | G19: 0 | H19: 0
A20: UMUSAVE | E20: 0 | F20: 0 | G20: 0 | H20: 0
A21: OTHER | E21: 0 | F21: 0 | G21: 0 | H21: 0
A22: OTHER | E22: 0 | F22: 0 | G22: 0 | H22: 0
A23: OTHER | E23: 0 | F23: 0 | G23: 0 | H23: 0
A24: OTHER | E24: 0 | F24: 0 | G24: 0 | H24: 0
A25: OTHER | E25: 0 | F25: 0 | G25: 0 | H25: 0
A26: OTHER | E26: 0 | F26: 0 | G26: 0 | H26: 0
A27: OTHER | E27: 0 | F27: 0 | G27: 0 | H27: 0
A28: OTHER | E28: 0 | F28: 0 | G28: 0 | H28: 0
... A36: OTHER | E36: 0 | F36: 0 | G36: 0 | H36: 0
A37: TOTALY | E37: =SUM(E5:E36) -> 50265522 | F37: =SUM(F5:F36) -> 7667622 | G37: =SUM(G5:G36) -> 695700 | H37: =SUM(H5:H36) -> 8363322
A38: SUMMARY | C38: RWF | E38: NAME | G38: Phone | H38: RWF
A39: TOTAL RWF PAID ON MOMO PAY | C39: 8363322
A40: TOTAL RWF PAID ON CASH
A41: AMOUNT NOT INVOICED
A42: TOTAL RWF DEPPOSITED ON BANK
A43: MEMBERSHIP FEES REGISTRETION
A44: MEMBERSHIP FEES CONTRIBUTION
A45: TOTAL INCOME | C45: =SUM(C39:C44) -> 8363322
A46: TIMBER SUMMARY
B48: TIMBER TYPE | E48: NUMBER OF QUANTITY
B49: INTURUSU | E49: =SUM(B9:B12) -> 20252
B50: PINUS | E50: =SUM(B6:B8) -> 250
B51: PALNCHE | E51: =SUM(B13:B14) -> 3782
B52: IBIPANDE | E52: =SUM(B17:B18) -> 0
B53: UMUSAVE | E53: =SUM(B19:B20) -> 0
B54: OTHER | E54: =B29 -> 0
B55: OTHER | E55: =B30 -> 0
B56: OTHER | E56: =B31 -> 0
B57: OTHER | E57: =B32 -> 0
B58: OTHER | E58: =B33 -> 0
B59: OTHER | E59: =B34 -> 0
B60: OTHER | E60: =B35 -> 0
B61: OTHER | E61: =B36 -> 0
B62: TOTAL TIMBER | E62: =SUM(E49:H61) -> 24284

Sheet GAHANGA
A1: QUANTITY REPORT
A3: MONTHS REPORT OF AUGUST 2025
A5: NAME OF TIMBER | B5: No OF TIMBER | C5: PRICE OF TIMBER | E5: TOTAL COST | F5: TVA | G5: MSF | H5: TVA+MSF
A6: PINUS NINI | E6: =PRODUCT(B6*C6) -> 0 | F6: =PRODUCT(E6*18)/118 -> 0 | G6: =PRODUCT(B6*50) -> 0 | H6: =SUM(F6:G6) -> 0
A7: PINUS NTOYA | E7: =PRODUCT(B7*C7) -> 0 | F7: =PRODUCT(E7*18)/118 -> 0 | G7: =PRODUCT(B7*50) -> 0 | H7: =SUM(F7:G7) -> 0
A8: PINUS | E8: =PRODUCT(B8*C8) -> 0 | F8: =PRODUCT(E8*18)/118 -> 0 | G8: =PRODUCT(B8*50) -> 0 | H8: =SUM(F8:G8) -> 0
A9: MADIRIYE NINI | E9: =PRODUCT(B9*C9) -> 0 | F9: =PRODUCT(E9*18)/118 -> 0 | G9: =PRODUCT(B9*30) -> 0 | H9: =SUM(F9:G9) -> 0
A10: MADIRIYE NTOYA | E10: =PRODUCT(B10*C10) -> 0 | F10: =PRODUCT(E10*18)/118 -> 0 | G10: =PRODUCT(B10*30) -> 0 | H10: =SUM(F10:G10) -> 0
A11: MADRIEN | E11: =PRODUCT(B11*C11) -> 0 | F11: =PRODUCT(E11*18)/118 -> 0 | G11: =PRODUCT(B11*30) -> 0 | H11: =SUM(F11:G11) -> 0
A12: MADRIEN | E12: =PRODUCT(B12*C12) -> 0 | F12: =PRODUCT(E12*18)/118 -> 0 | G12: =PRODUCT(B12*30) -> 0 | H12: =SUM(F12:G12) -> 0
A13: PLANCHE | E13: =PRODUCT(B13*C13) -> 0 | F13: =PRODUCT(E13*18)/118 -> 0 | G13: =PRODUCT(B13*20) -> 0 | H13: =SUM(F13:G13) -> 0
A14: PLANCHE | E14: =PRODUCT(B14*C14) -> 0 | F14: =PRODUCT(E14*18)/118 -> 0 | G14: =PRODUCT(B14*20) -> 0 | H14: =SUM(F14:G14) -> 0
A15: Other Timber for Difference Price
A16: NAME OF TIMBER | B16: No OF TIMBER | C16: P/U | D16: MSF | E16: TOTAL COST | F16: VAT | G16: MSF | H16: VTA+MST
A17: IBIPANDE | E17: =PRODUCT(B17*C17) -> 0 | F17: =PRODUCT(E17*18)/118 -> 0 | G17: =PRODUCT(B17*D17) -> 0 | H17: =SUM(F17:G17) -> 0
A18: IBIPANDE | E18: =PRODUCT(B18*C18) -> 0 | F18: =PRODUCT(E18*18)/118 -> 0 | G18: =PRODUCT(B18*D18) -> 0 | H18: =SUM(F18:G18) -> 0
A19: UMUSAVE | E19: =PRODUCT(B19*C19) -> 0 | F19: =PRODUCT(E19*18)/118 -> 0 | G19: =PRODUCT(B19*D19) -> 0 | H19: =SUM(F19:G19) -> 0
A20: UMUSAVE | E20: =PRODUCT(B20*C20) -> 0 | F20: =PRODUCT(E20*18)/118 -> 0 | G20: =PRODUCT(B20*D20) -> 0 | H20: =SUM(F20:G20) -> 0
A21: OTHER | E21: =PRODUCT(B21*C21) -> 0 | F21: =PRODUCT(E21*18)/118 -> 0 | G21: =PRODUCT(B21*D21) -> 0 | H21: =SUM(F21:G21) -> 0
A22: OTHER | E22: =PRODUCT(B22*C22) -> 0 | F22: =PRODUCT(E22*18)/118 -> 0 | G22: =PRODUCT(B22*D22) -> 0 | H22: =SUM(F22:G22) -> 0
A23: OTHER | E23: =PRODUCT(B23*C23) -> 0 | F23: =PRODUCT(E23*18)/118 -> 0 | G23: =PRODUCT(B23*D23) -> 0 | H23: =SUM(F23:G23) -> 0
A24: OTHER | E24: =PRODUCT(B24*C24) -> 0 | F24: =PRODUCT(E24*18)/118 -> 0 | G24: =PRODUCT(B24*D24) -> 0 | H24: =SUM(F24:G24) -> 0
A25: OTHER | E25: =PRODUCT(B25*C25) -> 0 | F25: =PRODUCT(E25*18)/118 -> 0 | G25: =PRODUCT(B25*D25) -> 0 | H25: =SUM(F25:G25) -> 0
A26: OTHER | E26: =PRODUCT(B26*C26) -> 0 | F26: =PRODUCT(E26*18)/118 -> 0 | G26: =PRODUCT(B26*D26) -> 0 | H26: =SUM(F26:G26) -> 0
A27: OTHER | E27: =PRODUCT(B27*C27) -> 0 | F27: =PRODUCT(E27*18)/118 -> 0 | G27: =PRODUCT(B27*D27) -> 0 | H27: =SUM(F27:G27) -> 0
A28: OTHER | E28: =PRODUCT(B28*C28) -> 0 | F28: =PRODUCT(E28*18)/118 -> 0 | G28: =PRODUCT(B28*D28) -> 0 | H28: =SUM(F28:G28) -> 0
A29: TOTALY | E29: =SUM(E6:E28) -> 0 | F29: =SUM(F6:F28) -> 0 | G29: =SUM(G6:G28) -> 0 | H29: =SUM(F29:G29) -> 0
A30: SUMMARY | C30: RWF | E30: NAME | G30: Phone | H30: RWF
A31: TOTAL RWF PAID ON MOMO PAY
A32: TOTAL RWF PAID ON CASH
A33: AMOUNT NOT INVOICED
A34: TOTAL RWF DEPPOSITED ON BANK
A35: MEMBERSHIP FEES REGISTRETION
A36: MEMBERSHIP FEES CONTRIBUTION
A37: TOTAL INCOME | C37: 0
A38: TIMBER SUMMARY
B40: TIMBER TYPE | E40: NUMBER OF QUANTITY
B41: INTURUSU | E41: =SUM(B9:B12) -> 0
B42: PINUS | E42: =SUM(B6:B8) -> 0
B43: PALNCHE | E43: =SUM(B13:B14) -> 0
B44: IBIPANDE | E44: =SUM(B17:B18) -> 0
B45: UMUSAVE | E45: =SUM(B19:B20) -> 0
B46: OTHER | E46: =B21 -> 0
B47: OTHER | E47: =B22 -> 0
B48: OTHER | E48: =B23 -> 0
B49: OTHER | E49: =B24 -> 0
B50: OTHER | E50: =B25 -> 0
B51: OTHER | E51: =B26 -> 0
B52: OTHER | E52: =B27 -> 0
B53: OTHER | E53: =B28 -> 0
B54: TOTAL TIMBER | E54: =SUM(E41:H53) -> 0

Sheet BUGESERA
A1: QUANTITY REPORT
A3: MONTHS REPORT OF AUGUST 2025
A5: NAME OF TIMBER | B5: No OF TIMBER | C5: PRICE OF TIMBER | E5: TOTAL COST | F5: TVA | G5: MSF | H5: TVA+MSF
A6: PINUS NINI | E6: =PRODUCT(B6*C6) -> 0 | F6: =PRODUCT(E6*18)/118 -> 0 | G6: =PRODUCT(B6*50) -> 0 | H6: =SUM(F6:G6) -> 0
A7: PINUS NTOYA | E7: =PRODUCT(B7*C7) -> 0 | F7: =PRODUCT(E7*18)/118 -> 0 | G7: =PRODUCT(B7*50) -> 0 | H7: =SUM(F7:G7) -> 0
A8: PINUS | E8: =PRODUCT(B8*C8) -> 0 | F8: =PRODUCT(E8*18)/118 -> 0 | G8: =PRODUCT(B8*50) -> 0 | H8: =SUM(F8:G8) -> 0
A9: MADIRIYE NINI | E9: =PRODUCT(B9*C9) -> 0 | F9: =PRODUCT(E9*18)/118 -> 0 | G9: =PRODUCT(B9*30) -> 0 | H9: =SUM(F9:G9) -> 0
A10: MADIRIYE NTOYA | E10: =PRODUCT(B10*C10) -> 0 | F10: =PRODUCT(E10*18)/118 -> 0 | G10: =PRODUCT(B10*30) -> 0 | H10: =SUM(F10:G10) -> 0
A11: MADRIEN | E11: =PRODUCT(B11*C11) -> 0 | F11: =PRODUCT(E11*18)/118 -> 0 | G11: =PRODUCT(B11*30) -> 0 | H11: =SUM(F11:G11) -> 0
A12: MADRIEN | E12: =PRODUCT(B12*C12) -> 0 | F12: =PRODUCT(E12*18)/118 -> 0 | G12: =PRODUCT(B12*30) -> 0 | H12: =SUM(F12:G12) -> 0
A13: PLANCHE | E13: =PRODUCT(B13*C13) -> 0 | F13: =PRODUCT(E13*18)/118 -> 0 | G13: =PRODUCT(B13*20) -> 0 | H13: =SUM(F13:G13) -> 0
A14: PLANCHE | E14: =PRODUCT(B14*C14) -> 0 | F14: =PRODUCT(E14*18)/118 -> 0 | G14: =PRODUCT(B14*20) -> 0 | H14: =SUM(F14:G14) -> 0
A15: Other Timber for Difference Price
A16: NAME OF TIMBER | B16: No OF TIMBER | C16: P/U | D16: MSF | E16: TOTAL COST | F16: VAT | G16: MSF | H16: VTA+MST
A17: IBIPANDE | E17: =PRODUCT(B17*C17) -> 0 | F17: =PRODUCT(E17*18)/118 -> 0 | G17: =PRODUCT(B17*D17) -> 0 | H17: =SUM(F17:G17) -> 0
A18: IBIPANDE | E18: =PRODUCT(B18*C18) -> 0 | F18: =PRODUCT(E18*18)/118 -> 0 | G18: =PRODUCT(B18*D18) -> 0 | H18: =SUM(F18:G18) -> 0
A19: UMUSAVE | E19: =PRODUCT(B19*C19) -> 0 | F19: =PRODUCT(E19*18)/118 -> 0 | G19: =PRODUCT(B19*D19) -> 0 | H19: =SUM(F19:G19) -> 0
A20: UMUSAVE | E20: =PRODUCT(B20*C20) -> 0 | F20: =PRODUCT(E20*18)/118 -> 0 | G20: =PRODUCT(B20*D20) -> 0 | H20: =SUM(F20:G20) -> 0
A21: OTHER | E21: =PRODUCT(B21*C21) -> 0 | F21: =PRODUCT(E21*18)/118 -> 0 | G21: =PRODUCT(B21*D21) -> 0 | H21: =SUM(F21:G21) -> 0
A22: OTHER | E22: =PRODUCT(B22*C22) -> 0 | F22: =PRODUCT(E22*18)/118 -> 0 | G22: =PRODUCT(B22*D22) -> 0 | H22: =SUM(F22:G22) -> 0
A23: OTHER | E23: =PRODUCT(B23*C23) -> 0 | F23: =PRODUCT(E23*18)/118 -> 0 | G23: =PRODUCT(B23*D23) -> 0 | H23: =SUM(F23:G23) -> 0
A24: OTHER | E24: =PRODUCT(B24*C24) -> 0 | F24: =PRODUCT(E24*18)/118 -> 0 | G24: =PRODUCT(B24*D24) -> 0 | H24: =SUM(F24:G24) -> 0
A25: OTHER | E25: =PRODUCT(B25*C25) -> 0 | F25: =PRODUCT(E25*18)/118 -> 0 | G25: =PRODUCT(B25*D25) -> 0 | H25: =SUM(F25:G25) -> 0
A26: OTHER | E26: =PRODUCT(B26*C26) -> 0 | F26: =PRODUCT(E26*18)/118 -> 0 | G26: =PRODUCT(B26*D26) -> 0 | H26: =SUM(F26:G26) -> 0
A27: OTHER | E27: =PRODUCT(B27*C27) -> 0 | F27: =PRODUCT(E27*18)/118 -> 0 | G27: =PRODUCT(B27*D27) -> 0 | H27: =SUM(F27:G27) -> 0
A28: OTHER | E28: =PRODUCT(B28*C28) -> 0 | F28: =PRODUCT(E28*18)/118 -> 0 | G28: =PRODUCT(B28*D28) -> 0 | H28: =SUM(F28:G28) -> 0
A29: TOTALY | E29: =SUM(E6:E28) -> 0 | F29: =SUM(F6:F28) -> 0 | G29: =SUM(G6:G28) -> 0 | H29: =SUM(F29:G29) -> 0
A30: SUMMARY | C30: RWF | E30: NAME | G30: Phone | H30: RWF
A31: TOTAL RWF PAID ON MOMO PAY
A32: TOTAL RWF PAID ON CASH
A33: AMOUNT NOT INVOICED
A34: TOTAL RWF DEPPOSITED ON BANK
A35: MEMBERSHIP FEES REGISTRETION
A36: MEMBERSHIP FEES CONTRIBUTION
A37: TOTAL INCOME | C37: 0
A38: TIMBER SUMMARY
B40: TIMBER TYPE | E40: NUMBER OF QUANTITY
B41: INTURUSU | E41: =SUM(B9:B12) -> 0
B42: PINUS | E42: =SUM(B6:B8) -> 0
B43: PALNCHE | E43: =SUM(B13:B14) -> 0
B44: IBIPANDE | E44: =SUM(B17:B18) -> 0
B45: UMUSAVE | E45: =SUM(B19:B20) -> 0
B46: OTHER | E46: =B21 -> 0
B47: OTHER | E47: =B22 -> 0
B48: OTHER | E48: =B23 -> 0
B49: OTHER | E49: =B24 -> 0
B50: OTHER | E50: =B25 -> 0
B51: OTHER | E51: =B26 -> 0
B52: OTHER | E52: =B27 -> 0
B53: OTHER | E53: =B28 -> 0
B54: TOTAL TIMBER | E54: =SUM(E41:H53) -> 0

Sheet NYARUGENGE
A1: QUANTITY REPORT
A3: MONTHS REPORT OF AUGUST 2025
A5: NAME OF TIMBER | B5: No OF TIMBER | C5: PRICE OF TIMBER | E5: TOTAL COST | F5: TVA | G5: MSF | H5: TVA+MSF
A6: PINUS NINI | E6: =PRODUCT(B6*C6) -> 0 | F6: =PRODUCT(E6*18)/118 -> 0 | G6: =PRODUCT(B6*50) -> 0 | H6: =SUM(F6:G6) -> 0
A7: PINUS NTOYA | E7: =PRODUCT(B7*C7) -> 0 | F7: =PRODUCT(E7*18)/118 -> 0 | G7: =PRODUCT(B7*50) -> 0 | H7: =SUM(F7:G7) -> 0
A8: PINUS | E8: =PRODUCT(B8*C8) -> 0 | F8: =PRODUCT(E8*18)/118 -> 0 | G8: =PRODUCT(B8*50) -> 0 | H8: =SUM(F8:G8) -> 0
A9: MADIRIYE NINI | E9: =PRODUCT(B9*C9) -> 0 | F9: =PRODUCT(E9*18)/118 -> 0 | G9: =PRODUCT(B9*30) -> 0 | H9: =SUM(F9:G9) -> 0
A10: MADIRIYE NTOYA | C10: 2124 | E10: =PRODUCT(B10*C10) -> 0 | F10: =PRODUCT(E10*18)/118 -> 0 | G10: =PRODUCT(B10*30) -> 0 | H10: =SUM(F10:G10) -> 0
A11: MADRIEN | E11: =PRODUCT(B11*C11) -> 0 | F11: =PRODUCT(E11*18)/118 -> 0 | G11: =PRODUCT(B11*30) -> 0 | H11: =SUM(F11:G11) -> 0
A12: MADRIEN | E12: =PRODUCT(B12*C12) -> 0 | F12: =PRODUCT(E12*18)/118 -> 0 | G12: =PRODUCT(B12*30) -> 0 | H12: =SUM(F12:G12) -> 0
A13: PLANCHE | C13: 1357 | E13: =PRODUCT(B13*C13) -> 0 | F13: =PRODUCT(E13*18)/118 -> 0 | G13: =PRODUCT(B13*20) -> 0 | H13: =SUM(F13:G13) -> 0
A14: PLANCHE | E14: =PRODUCT(B14*C14) -> 0 | F14: =PRODUCT(E14*18)/118 -> 0 | G14: =PRODUCT(B14*20) -> 0 | H14: =SUM(F14:G14) -> 0
A15: Other Timber for Difference Price
A16: NAME OF TIMBER | B16: No OF TIMBER | C16: P/U | D16: MSF | E16: TOTAL COST | F16: VAT | G16: MSF | H16: VTA+MST
A17: IBIPANDE | E17: =PRODUCT(B17*C17) -> 0 | F17: =PRODUCT(E17*18)/118 -> 0 | G17: =PRODUCT(B17*D17) -> 0 | H17: =SUM(F17:G17) -> 0
A18: IBIPANDE | E18: =PRODUCT(B18*C18) -> 0 | F18: =PRODUCT(E18*18)/118 -> 0 | G18: =PRODUCT(B18*D18) -> 0 | H18: =SUM(F18:G18) -> 0
A19: UMUSAVE | E19: =PRODUCT(B19*C19) -> 0 | F19: =PRODUCT(E19*18)/118 -> 0 | G19: =PRODUCT(B19*D19) -> 0 | H19: =SUM(F19:G19) -> 0
A20: UMUSAVE | E20: =PRODUCT(B20*C20) -> 0 | F20: =PRODUCT(E20*18)/118 -> 0 | G20: =PRODUCT(B20*D20) -> 0 | H20: =SUM(F20:G20) -> 0
A21: OTHER | E21: =PRODUCT(B21*C21) -> 0 | F21: =PRODUCT(E21*18)/118 -> 0 | G21: =PRODUCT(B21*D21) -> 0 | H21: =SUM(F21:G21) -> 0
A22: OTHER | E22: =PRODUCT(B22*C22) -> 0 | F22: =PRODUCT(E22*18)/118 -> 0 | G22: =PRODUCT(B22*D22) -> 0 | H22: =SUM(F22:G22) -> 0
A23: OTHER | E23: =PRODUCT(B23*C23) -> 0 | F23: =PRODUCT(E23*18)/118 -> 0 | G23: =PRODUCT(B23*D23) -> 0 | H23: =SUM(F23:G23) -> 0
A24: OTHER | E24: =PRODUCT(B24*C24) -> 0 | F24: =PRODUCT(E24*18)/118 -> 0 | G24: =PRODUCT(B24*D24) -> 0 | H24: =SUM(F24:G24) -> 0
A25: OTHER | E25: =PRODUCT(B25*C25) -> 0 | F25: =PRODUCT(E25*18)/118 -> 0 | G25: =PRODUCT(B25*D25) -> 0 | H25: =SUM(F25:G25) -> 0
A26: OTHER | E26: =PRODUCT(B26*C26) -> 0 | F26: =PRODUCT(E26*18)/118 -> 0 | G26: =PRODUCT(B26*D26) -> 0 | H26: =SUM(F26:G26) -> 0
A27: OTHER | E27: =PRODUCT(B27*C27) -> 0 | F27: =PRODUCT(E27*18)/118 -> 0 | G27: =PRODUCT(B27*D27) -> 0 | H27: =SUM(F27:G27) -> 0
A28: OTHER | E28: =PRODUCT(B28*C28) -> 0 | F28: =PRODUCT(E28*18)/118 -> 0 | G28: =PRODUCT(B28*D28) -> 0 | H28: =SUM(F28:G28) -> 0
A29: TOTALY | E29: =SUM(E6:E28) -> 0 | F29: =SUM(F6:F28) -> 0 | G29: =SUM(G6:G28) -> 0 | H29: =SUM(F29:G29) -> 0
A30: SUMMARY | C30: RWF | E30: NAME | G30: Phone | H30: RWF
A31: TOTAL RWF PAID ON MOMO PAY
A32: TOTAL RWF PAID ON CASH
A33: AMOUNT NOT INVOICED
A34: TOTAL RWF DEPPOSITED ON BANK
A35: MEMBERSHIP FEES REGISTRETION
A36: MEMBERSHIP FEES CONTRIBUTION
A37: TOTAL INCOME | C37: 0
A38: TIMBER SUMMARY
B40: TIMBER TYPE | E40: NUMBER OF QUANTITY
B41: INTURUSU | E41: =SUM(B9:B12) -> 0
B42: PINUS | E42: =SUM(B6:B8) -> 0
B43: PALNCHE | E43: =SUM(B13:B14) -> 0
B44: IBIPANDE | E44: =SUM(B17:B18) -> 0
B45: UMUSAVE | E45: =SUM(B19:B20) -> 0
B46: OTHER | E46: =B21 -> 0
B47: OTHER | E47: =B22 -> 0
B48: OTHER | E48: =B23 -> 0
B49: OTHER | E49: =B24 -> 0
B50: OTHER | E50: =B25 -> 0
B51: OTHER | E51: =B26 -> 0
B52: OTHER | E52: =B27 -> 0
B53: OTHER | E53: =B28 -> 0
B54: TOTAL TIMBER | E54: =SUM(E41:H53) -> 0

Sheet RWAMAGANA
A1: QUANTITY REPORT
A3: MONTHS REPORT OF AUGUST 2025
A5: NAME OF TIMBER | B5: No OF TIMBER | C5: PRICE OF TIMBER | E5: TOTAL COST | F5: TVA | G5: MSF | H5: TVA+MSF
A6: PINUS NINI | E6: =PRODUCT(B6*C6) -> 0 | F6: =PRODUCT(E6*18)/118 -> 0 | G6: =PRODUCT(B6*50) -> 0 | H6: =SUM(F6:G6) -> 0
A7: PINUS NTOYA | E7: =PRODUCT(B7*C7) -> 0 | F7: =PRODUCT(E7*18)/118 -> 0 | G7: =PRODUCT(B7*50) -> 0 | H7: =SUM(F7:G7) -> 0
A8: PINUS | E8: =PRODUCT(B8*C8) -> 0 | F8: =PRODUCT(E8*18)/118 -> 0 | G8: =PRODUCT(B8*50) -> 0 | H8: =SUM(F8:G8) -> 0
A9: MADIRIYE NINI | E9: =PRODUCT(B9*C9) -> 0 | F9: =PRODUCT(E9*18)/118 -> 0 | G9: =PRODUCT(B9*30) -> 0 | H9: =SUM(F9:G9) -> 0
A10: MADIRIYE NTOYA | C10: 2124 | E10: =PRODUCT(B10*C10) -> 0 | F10: =PRODUCT(E10*18)/118 -> 0 | G10: =PRODUCT(B10*30) -> 0 | H10: =SUM(F10:G10) -> 0
A11: MADRIEN | E11: =PRODUCT(B11*C11) -> 0 | F11: =PRODUCT(E11*18)/118 -> 0 | G11: =PRODUCT(B11*30) -> 0 | H11: =SUM(F11:G11) -> 0
A12: MADRIEN | E12: =PRODUCT(B12*C12) -> 0 | F12: =PRODUCT(E12*18)/118 -> 0 | G12: =PRODUCT(B12*30) -> 0 | H12: =SUM(F12:G12) -> 0
A13: PLANCHE | E13: =PRODUCT(B13*C13) -> 0 | F13: =PRODUCT(E13*18)/118 -> 0 | G13: =PRODUCT(B13*20) -> 0 | H13: =SUM(F13:G13) -> 0
A14: PLANCHE | E14: =PRODUCT(B14*C14) -> 0 | F14: =PRODUCT(E14*18)/118 -> 0 | G14: =PRODUCT(B14*20) -> 0 | H14: =SUM(F14:G14) -> 0
A15: Other Timber for Difference Price
A16: NAME OF TIMBER | B16: No OF TIMBER | C16: P/U | D16: MSF | E16: TOTAL COST | F16: VAT | G16: MSF | H16: VTA+MST
A17: IBIPANDE | E17: =PRODUCT(B17*C17) -> 0 | F17: =PRODUCT(E17*18)/118 -> 0 | G17: =PRODUCT(B17*D17) -> 0 | H17: =SUM(F17:G17) -> 0
A18: IBIPANDE | E18: =PRODUCT(B18*C18) -> 0 | F18: =PRODUCT(E18*18)/118 -> 0 | G18: =PRODUCT(B18*D18) -> 0 | H18: =SUM(F18:G18) -> 0
A19: UMUSAVE | E19: =PRODUCT(B19*C19) -> 0 | F19: =PRODUCT(E19*18)/118 -> 0 | G19: =PRODUCT(B19*D19) -> 0 | H19: =SUM(F19:G19) -> 0
A20: UMUSAVE | E20: =PRODUCT(B20*C20) -> 0 | F20: =PRODUCT(E20*18)/118 -> 0 | G20: =PRODUCT(B20*D20) -> 0 | H20: =SUM(F20:G20) -> 0
A21: OTHER | E21: =PRODUCT(B21*C21) -> 0 | F21: =PRODUCT(E21*18)/118 -> 0 | G21: =PRODUCT(B21*D21) -> 0 | H21: =SUM(F21:G21) -> 0
A22: OTHER | E22: =PRODUCT(B22*C22) -> 0 | F22: =PRODUCT(E22*18)/118 -> 0 | G22: =PRODUCT(B22*D22) -> 0 | H22: =SUM(F22:G22) -> 0
A23: OTHER | E23: =PRODUCT(B23*C23) -> 0 | F23: =PRODUCT(E23*18)/118 -> 0 | G23: =PRODUCT(B23*D23) -> 0 | H23: =SUM(F23:G23) -> 0
A24: OTHER | E24: =PRODUCT(B24*C24) -> 0 | F24: =PRODUCT(E24*18)/118 -> 0 | G24: =PRODUCT(B24*D24) -> 0 | H24: =SUM(F24:G24) -> 0
A25: OTHER | E25: =PRODUCT(B25*C25) -> 0 | F25: =PRODUCT(E25*18)/118 -> 0 | G25: =PRODUCT(B25*D25) -> 0 | H25: =SUM(F25:G25) -> 0
A26: OTHER | E26: =PRODUCT(B26*C26) -> 0 | F26: =PRODUCT(E26*18)/118 -> 0 | G26: =PRODUCT(B26*D26) -> 0 | H26: =SUM(F26:G26) -> 0
A27: OTHER | E27: =PRODUCT(B27*C27) -> 0 | F27: =PRODUCT(E27*18)/118 -> 0 | G27: =PRODUCT(B27*D27) -> 0 | H27: =SUM(F27:G27) -> 0
A28: OTHER | E28: =PRODUCT(B28*C28) -> 0 | F28: =PRODUCT(E28*18)/118 -> 0 | G28: =PRODUCT(B28*D28) -> 0 | H28: =SUM(F28:G28) -> 0
A29: TOTALY | E29: =SUM(E6:E28) -> 0 | F29: =SUM(F6:F28) -> 0 | G29: =SUM(G6:G28) -> 0 | H29: =SUM(F29:G29) -> 0
A30: SUMMARY | C30: RWF | E30: NAME | G30: Phone | H30: RWF
A31: TOTAL RWF PAID ON MOMO PAY
A32: TOTAL RWF PAID ON CASH
A33: AMOUNT NOT INVOICED
A34: TOTAL RWF DEPPOSITED ON BANK
A35: MEMBERSHIP FEES REGISTRETION
A36: MEMBERSHIP FEES CONTRIBUTION
A37: TOTAL INCOME | C37: 0
A38: TIMBER SUMMARY
B40: TIMBER TYPE | E40: NUMBER OF QUANTITY
B41: INTURUSU | E41: =SUM(B9:B12) -> 0
B42: PINUS | E42: =SUM(B6:B8) -> 0
B43: PALNCHE | E43: =SUM(B13:B14) -> 0
B44: IBIPANDE | E44: =SUM(B17:B18) -> 0
B45: UMUSAVE | E45: =SUM(B19:B20) -> 0
B46: OTHER | E46: =B21 -> 0
B47: OTHER | E47: =B22 -> 0
B48: OTHER | E48: =B23 -> 0
B49: OTHER | E49: =B24 -> 0
B50: OTHER | E50: =B25 -> 0
B51: OTHER | E51: =B26 -> 0
B52: OTHER | E52: =B27 -> 0
B53: OTHER | E53: =B28 -> 0
B54: TOTAL TIMBER | E54: =SUM(E41:H53) -> 0

Sheet MUHANGA
A1: QUANTITY REPORT
A3: MONTHS REPORT OF AUGUST 2025
A5: NAME OF TIMBER | B5: No OF TIMBER | C5: PRICE OF TIMBER | E5: TOTAL COST | F5: TVA | G5: MSF | H5: TVA+MSF
A6: PINUS NINI | E6: =PRODUCT(B6*C6) -> 0 | F6: =PRODUCT(E6*18)/118 -> 0 | G6: =PRODUCT(B6*50) -> 0 | H6: =SUM(F6:G6) -> 0
A7: PINUS NTOYA | E7: =PRODUCT(B7*C7) -> 0 | F7: =PRODUCT(E7*18)/118 -> 0 | G7: =PRODUCT(B7*50) -> 0 | H7: =SUM(F7:G7) -> 0
A8: PINUS | E8: =PRODUCT(B8*C8) -> 0 | F8: =PRODUCT(E8*18)/118 -> 0 | G8: =PRODUCT(B8*50) -> 0 | H8: =SUM(F8:G8) -> 0
A9: MADIRIYE NINI | E9: =PRODUCT(B9*C9) -> 0 | F9: =PRODUCT(E9*18)/118 -> 0 | G9: =PRODUCT(B9*30) -> 0 | H9: =SUM(F9:G9) -> 0
A10: MADIRIYE NTOYA | E10: =PRODUCT(B10*C10) -> 0 | F10: =PRODUCT(E10*18)/118 -> 0 | G10: =PRODUCT(B10*30) -> 0 | H10: =SUM(F10:G10) -> 0
A11: MADRIEN | E11: =PRODUCT(B11*C11) -> 0 | F11: =PRODUCT(E11*18)/118 -> 0 | G11: =PRODUCT(B11*30) -> 0 | H11: =SUM(F11:G11) -> 0
A12: MADRIEN | C12: 2124 | E12: =PRODUCT(B12*C12) -> 0 | F12: =PRODUCT(E12*18)/118 -> 0 | G12: =PRODUCT(B12*30) -> 0 | H12: =SUM(F12:G12) -> 0
A13: PLANCHE | E13: =PRODUCT(B13*C13) -> 0 | F13: =PRODUCT(E13*18)/118 -> 0 | G13: =PRODUCT(B13*20) -> 0 | H13: =SUM(F13:G13) -> 0
A14: PLANCHE | E14: =PRODUCT(B14*C14) -> 0 | F14: =PRODUCT(E14*18)/118 -> 0 | G14: =PRODUCT(B14*20) -> 0 | H14: =SUM(F14:G14) -> 0
A15: Other Timber for Difference Price
A16: NAME OF TIMBER | B16: No OF TIMBER | C16: P/U | D16: MSF | E16: TOTAL COST | F16: VAT | G16: MSF | H16: VTA+MST
A17: IBIPANDE | E17: 0 | F17: 0 | G17: 0 | H17: 0
A18: IBIPANDE | E18: 0 | F18: 0 | G18: 0 | H18: 0
A19: UMUSAVE | E19: 0 | F19: 0 | G19: 0 | H19: 0
A20: UMUSAVE | E20: 0 | F20: 0 | G20: 0 | H20: 0
A21: OTHER | E21: 0 | F21: 0 | G21: 0 | H21: 0
A22: OTHER | E22: 0 | F22: 0 | G22: 0 | H22: 0
A23: OTHER | E23: 0 | F23: 0 | G23: 0 | H23: 0
A24: OTHER | E24: 0 | F24: 0 | G24: 0 | H24: 0
A25: OTHER | E25: 0 | F25: 0 | G25: 0 | H25: 0
A26: OTHER | E26: 0 | F26: 0 | G26: 0 | H26: 0
A27: OTHER | E27: 0 | F27: 0 | G27: 0 | H27: 0
A28: OTHER | E28: 0 | F28: 0 | G28: 0 | H28: 0
... A36: OTHER | E36: 0 | F36: 0 | G36: 0 | H36: 0
A37: TOTALY | E37: =SUM(E5:E36) -> 0 | F37: =SUM(F5:F36) -> 0 | G37: =SUM(G5:G36) -> 0 | H37: =SUM(H5:H36) -> 0
A38: SUMMARY | C38: RWF | E38: NAME | G38: Phone | H38: RWF
A39: TOTAL RWF PAID ON MOMO PAY
A40: TOTAL RWF PAID ON CASH
A41: AMOUNT NOT INVOICED
A42: TOTAL RWF DEPPOSITED ON BANK
A43: MEMBERSHIP FEES REGISTRETION
A44: MEMBERSHIP FEES CONTRIBUTION
A45: TOTAL INCOME | C45: 0
A46: TIMBER SUMMARY
B48: TIMBER TYPE | E48: NUMBER OF QUANTITY
B49: INTURUSU | E49: =SUM(B9:B12) -> 0
B50: PINUS | E50: =SUM(B6:B8) -> 0
B51: PALNCHE | E51: =SUM(B13:B14) -> 0
B52: IBIPANDE | E52: =SUM(B17:B18) -> 0
B53: UMUSAVE | E53: =SUM(B19:B20) -> 0
B54: OTHER | E54: =B29 -> 0
B55: OTHER | E55: =B30 -> 0
B56: OTHER | E56: =B31 -> 0
B57: OTHER | E57: =B32 -> 0
B58: OTHER | E58: =B33 -> 0
B59: OTHER | E59: =B34 -> 0
B60: OTHER | E60: =B35 -> 0
B61: OTHER | E61: =B36 -> 0
B62: TOTAL TIMBER | E62: =SUM(E49:H61) -> 0

Sheet RUHANGO
A1: QUANTITY REPORT
A3: MONTHS REPORT OF AUGUST 2025
A5: NAME OF TIMBER | B5: No OF TIMBER | C5: PRICE OF TIMBER | E5: TOTAL COST | F5: TVA | G5: MSF | H5: TVA+MSF
A6: PINUS NINI | E6: =PRODUCT(B6*C6) -> 0 | F6: =PRODUCT(E6*18)/118 -> 0 | G6: =PRODUCT(B6*50) -> 0 | H6: =SUM(F6:G6) -> 0
A7: PINUS NTOYA | E7: =PRODUCT(B7*C7) -> 0 | F7: =PRODUCT(E7*18)/118 -> 0 | G7: =PRODUCT(B7*50) -> 0 | H7: =SUM(F7:G7) -> 0
A8: PINUS | E8: =PRODUCT(B8*C8) -> 0 | F8: =PRODUCT(E8*18)/118 -> 0 | G8: =PRODUCT(B8*50) -> 0 | H8: =SUM(F8:G8) -> 0
A9: MADIRIYE NINI | E9: =PRODUCT(B9*C9) -> 0 | F9: =PRODUCT(E9*18)/118 -> 0 | G9: =PRODUCT(B9*30) -> 0 | H9: =SUM(F9:G9) -> 0
A10: MADIRIYE NTOYA | E10: =PRODUCT(B10*C10) -> 0 | F10: =PRODUCT(E10*18)/118 -> 0 | G10: =PRODUCT(B10*30) -> 0 | H10: =SUM(F10:G10) -> 0
A11: MADRIEN | E11: =PRODUCT(B11*C11) -> 0 | F11: =PRODUCT(E11*18)/118 -> 0 | G11: =PRODUCT(B11*30) -> 0 | H11: =SUM(F11:G11) -> 0
A12: MADRIEN | E12: =PRODUCT(B12*C12) -> 0 | F12: =PRODUCT(E12*18)/118 -> 0 | G12: =PRODUCT(B12*30) -> 0 | H12: =SUM(F12:G12) -> 0
A13: PLANCHE | E13: =PRODUCT(B13*C13) -> 0 | F13: =PRODUCT(E13*18)/118 -> 0 | G13: =PRODUCT(B13*20) -> 0 | H13: =SUM(F13:G13) -> 0
A14: PLANCHE | C14: 1357 | E14: =PRODUCT(B14*C14) -> 0 | F14: =PRODUCT(E14*18)/118 -> 0 | G14: =PRODUCT(B14*20) -> 0 | H14: =SUM(F14:G14) -> 0
A15: Other Timber for Difference Price
A16: NAME OF TIMBER | B16: No OF TIMBER | C16: P/U | D16: MSF | E16: TOTAL COST | F16: VAT | G16: MSF | H16: VTA+MST
A17: IBIPANDE | E17: 0 | F17: 0 | G17: 0 | H17: 0
A18: IBIPANDE | E18: 0 | F18: 0 | G18: 0 | H18: 0
A19: UMUSAVE | E19: 0 | F19: 0 | G19: 0 | H19: 0
A20: UMUSAVE | E20: 0 | F20: 0 | G20: 0 | H20: 0
A21: OTHER | E21: 0 | F21: 0 | G21: 0 | H21: 0
A22: OTHER | E22: 0 | F22: 0 | G22: 0 | H22: 0
A23: OTHER | E23: 0 | F23: 0 | G23: 0 | H23: 0
A24: OTHER | E24: 0 | F24: 0 | G24: 0 | H24: 0
A25: OTHER | E25: 0 | F25: 0 | G25: 0 | H25: 0
A26: OTHER | E26: 0 | F26: 0 | G26: 0 | H26: 0
A27: OTHER | E27: 0 | F27: 0 | G27: 0 | H27: 0
A28: OTHER | E28: 0 | F28: 0 | G28: 0 | H28: 0
... A36: OTHER | E36: 0 | F36: 0 | G36: 0 | H36: 0
A37: TOTALY | E37: =SUM(E5:E36) -> 0 | F37: =SUM(F5:F36) -> 0 | G37: =SUM(G5:G36) -> 0 | H37: =SUM(H5:H36) -> 0
A38: SUMMARY | C38: RWF | E38: NAME | G38: Phone | H38: RWF
A39: TOTAL RWF PAID ON MOMO PAY
A40: TOTAL RWF PAID ON CASH
A41: AMOUNT NOT INVOICED
A42: TOTAL RWF DEPPOSITED ON BANK
A43: MEMBERSHIP FEES REGISTRETION
A44: MEMBERSHIP FEES CONTRIBUTION
A45: TOTAL INCOME | C45: 0
A46: TIMBER SUMMARY
B48: TIMBER TYPE | E48: NUMBER OF QUANTITY
B49: INTURUSU | E49: =SUM(B9:B12) -> 0
B50: PINUS | E50: =SUM(B6:B8) -> 0
B51: PALNCHE | E51: =SUM(B13:B14) -> 0
B52: IBIPANDE | E52: =SUM(B17:B18) -> 0
B53: UMUSAVE | E53: =SUM(B19:B20) -> 0
B54: OTHER | E54: =B29 -> 0
B55: OTHER | E55: =B30 -> 0
B56: OTHER | E56: =B31 -> 0
B57: OTHER | E57: =B32 -> 0
B58: OTHER | E58: =B33 -> 0
B59: OTHER | E59: =B34 -> 0
B60: OTHER | E60: =B35 -> 0
B61: OTHER | E61: =B36 -> 0
B62: TOTAL TIMBER | E62: =SUM(E49:H61) -> 0

Sheet HUYE
A1: QUANTITY REPORT
A3: MONTHS REPORT OF AUGUST 2025
A5: NAME OF TIMBER | B5: No OF TIMBER | C5: PRICE OF TIMBER | E5: TOTAL COST | F5: TVA | G5: MSF | H5: TVA+MSF
A6: PINUS NINI | E6: =PRODUCT(B6*C6) -> 0 | F6: =PRODUCT(E6*18)/118 -> 0 | G6: =PRODUCT(B6*50) -> 0 | H6: =SUM(F6:G6) -> 0
A7: PINUS NTOYA | E7: =PRODUCT(B7*C7) -> 0 | F7: =PRODUCT(E7*18)/118 -> 0 | G7: =PRODUCT(B7*50) -> 0 | H7: =SUM(F7:G7) -> 0
A8: PINUS | E8: =PRODUCT(B8*C8) -> 0 | F8: =PRODUCT(E8*18)/118 -> 0 | G8: =PRODUCT(B8*50) -> 0 | H8: =SUM(F8:G8) -> 0
A9: MADIRIYE NINI | E9: =PRODUCT(B9*C9) -> 0 | F9: =PRODUCT(E9*18)/118 -> 0 | G9: =PRODUCT(B9*30) -> 0 | H9: =SUM(F9:G9) -> 0
A10: MADIRIYE NTOYA | E10: =PRODUCT(B10*C10) -> 0 | F10: =PRODUCT(E10*18)/118 -> 0 | G10: =PRODUCT(B10*30) -> 0 | H10: =SUM(F10:G10) -> 0
A11: MADRIEN | E11: =PRODUCT(B11*C11) -> 0 | F11: =PRODUCT(E11*18)/118 -> 0 | G11: =PRODUCT(B11*30) -> 0 | H11: =SUM(F11:G11) -> 0
A12: MADRIEN | E12: =PRODUCT(B12*C12) -> 0 | F12: =PRODUCT(E12*18)/118 -> 0 | G12: =PRODUCT(B12*30) -> 0 | H12: =SUM(F12:G12) -> 0
A13: PLANCHE | E13: =PRODUCT(B13*C13) -> 0 | F13: =PRODUCT(E13*18)/118 -> 0 | G13: =PRODUCT(B13*20) -> 0 | H13: =SUM(F13:G13) -> 0
A14: PLANCHE | E14: =PRODUCT(B14*C14) -> 0 | F14: =PRODUCT(E14*18)/118 -> 0 | G14: =PRODUCT(B14*20) -> 0 | H14: =SUM(F14:G14) -> 0
A15: Other Timber for Difference Price
A16: NAME OF TIMBER | B16: No OF TIMBER | C16: P/U | D16: MSF | E16: TOTAL COST | F16: VAT | G16: MSF | H16: VTA+MST
A17: IBIPANDE | E17: 0 | F17: 0 | G17: 0 | H17: 0
A18: IBIPANDE | E18: 0 | F18: 0 | G18: 0 | H18: 0
A19: UMUSAVE | E19: 0 | F19: 0 | G19: 0 | H19: 0
A20: UMUSAVE | E20: 0 | F20: 0 | G20: 0 | H20: 0
A21: OTHER | E21: 0 | F21: 0 | G21: 0 | H21: 0
A22: OTHER | E22: 0 | F22: 0 | G22: 0 | H22: 0
A23: OTHER | E23: 0 | F23: 0 | G23: 0 | H23: 0
A24: OTHER | E24: 0 | F24: 0 | G24: 0 | H24: 0
A25: OTHER | E25: 0 | F25: 0 | G25: 0 | H25: 0
A26: OTHER | E26: 0 | F26: 0 | G26: 0 | H26: 0
A27: OTHER | E27: 0 | F27: 0 | G27: 0 | H27: 0
A28: OTHER | E28: 0 | F28: 0 | G28: 0 | H28: 0
... A36: OTHER | E36: 0 | F36: 0 | G36: 0 | H36: 0
A37: TOTALY | E37: =SUM(E5:E36) -> 0 | F37: =SUM(F5:F36) -> 0 | G37: =SUM(G5:G36) -> 0 | H37: =SUM(H5:H36) -> 0
A38: SUMMARY | C38: RWF | E38: NAME | G38: Phone | H38: RWF
A39: TOTAL RWF PAID ON MOMO PAY
A40: TOTAL RWF PAID ON CASH
A41: AMOUNT NOT INVOICED
A42: TOTAL RWF DEPPOSITED ON BANK
A43: MEMBERSHIP FEES REGISTRETION
A44: MEMBERSHIP FEES CONTRIBUTION
A45: TOTAL INCOME | C45: 0
A46: TIMBER SUMMARY
B48: TIMBER TYPE | E48: NUMBER OF QUANTITY
B49: INTURUSU | E49: =SUM(B9:B12) -> 0
B50: PINUS | E50: =SUM(B6:B8) -> 0
B51: PALNCHE | E51: =SUM(B13:B14) -> 0
B52: IBIPANDE | E52: =SUM(B17:B18) -> 0
B53: UMUSAVE | E53: =SUM(B19:B20) -> 0
B54: OTHER | E54: =B29 -> 0
B55: OTHER | E55: =B30 -> 0
B56: OTHER | E56: =B31 -> 0
B57: OTHER | E57: =B32 -> 0
B58: OTHER | E58: =B33 -> 0
B59: OTHER | E59: =B34 -> 0
B60: OTHER | E60: =B35 -> 0
B61: OTHER | E61: =B36 -> 0
B62: TOTAL TIMBER | E62: =SUM(E49:H61) -> 0

Sheet RUSIZI
A1: QUANTITY REPORT
A3: MONTHS REPORT OF AUGUST 2025
A5: NAME OF TIMBER | B5: No OF TIMBER | C5: PRICE OF TIMBER | E5: TOTAL COST | F5: TVA | G5: MSF | H5: TVA+MSF
A6: PINUS NINI | E6: =PRODUCT(B6*C6) -> 0 | F6: =PRODUCT(E6*18)/118 -> 0 | G6: =PRODUCT(B6*50) -> 0 | H6: =SUM(F6:G6) -> 0
A7: PINUS NTOYA | E7: =PRODUCT(B7*C7) -> 0 | F7: =PRODUCT(E7*18)/118 -> 0 | G7: =PRODUCT(B7*50) -> 0 | H7: =SUM(F7:G7) -> 0
A8: PINUS | E8: =PRODUCT(B8*C8) -> 0 | F8: =PRODUCT(E8*18)/118 -> 0 | G8: =PRODUCT(B8*50) -> 0 | H8: =SUM(F8:G8) -> 0
A9: MADIRIYE NINI | E9: =PRODUCT(B9*C9) -> 0 | F9: =PRODUCT(E9*18)/118 -> 0 | G9: =PRODUCT(B9*30) -> 0 | H9: =SUM(F9:G9) -> 0
A10: MADIRIYE NTOYA | E10: =PRODUCT(B10*C10) -> 0 | F10: =PRODUCT(E10*18)/118 -> 0 | G10: =PRODUCT(B10*30) -> 0 | H10: =SUM(F10:G10) -> 0
A11: MADRIEN | E11: =PRODUCT(B11*C11) -> 0 | F11: =PRODUCT(E11*18)/118 -> 0 | G11: =PRODUCT(B11*30) -> 0 | H11: =SUM(F11:G11) -> 0
A12: MADRIEN | E12: =PRODUCT(B12*C12) -> 0 | F12: =PRODUCT(E12*18)/118 -> 0 | G12: =PRODUCT(B12*30) -> 0 | H12: =SUM(F12:G12) -> 0
A13: PLANCHE | E13: =PRODUCT(B13*C13) -> 0 | F13: =PRODUCT(E13*18)/118 -> 0 | G13: =PRODUCT(B13*20) -> 0 | H13: =SUM(F13:G13) -> 0
A14: PLANCHE | E14: =PRODUCT(B14*C14) -> 0 | F14: =PRODUCT(E14*18)/118 -> 0 | G14: =PRODUCT(B14*20) -> 0 | H14: =SUM(F14:G14) -> 0
A15: Other Timber for Difference Price
A16: NAME OF TIMBER | B16: No OF TIMBER | C16: P/U | D16: MSF | E16: TOTAL COST | F16: VAT | G16: MSF | H16: VTA+MST
A17: IBIPANDE | E17: 0 | F17: 0 | G17: 0 | H17: 0
A18: IBIPANDE | E18: 0 | F18: 0 | G18: 0 | H18: 0
A19: UMUSAVE | E19: 0 | F19: 0 | G19: 0 | H19: 0
A20: UMUSAVE | E20: 0 | F20: 0 | G20: 0 | H20: 0
A21: OTHER | E21: 0 | F21: 0 | G21: 0 | H21: 0
A22: OTHER | E22: 0 | F22: 0 | G22: 0 | H22: 0
A23: OTHER | E23: 0 | F23: 0 | G23: 0 | H23: 0
A24: OTHER | E24: 0 | F24: 0 | G24: 0 | H24: 0
A25: OTHER | E25: 0 | F25: 0 | G25: 0 | H25: 0
A26: OTHER | E26: 0 | F26: 0 | G26: 0 | H26: 0
A27: OTHER | E27: 0 | F27: 0 | G27: 0 | H27: 0
A28: OTHER | E28: 0 | F28: 0 | G28: 0 | H28: 0
... A36: OTHER | E36: 0 | F36: 0 | G36: 0 | H36: 0
A37: TOTALY | E37: =SUM(E5:E36) -> 0 | F37: =SUM(F5:F36) -> 0 | G37: =SUM(G5:G36) -> 0 | H37: =SUM(H5:H36) -> 0
A38: SUMMARY | C38: RWF | E38: NAME | G38: Phone | H38: RWF
A39: TOTAL RWF PAID ON MOMO PAY
A40: TOTAL RWF PAID ON CASH
A41: AMOUNT NOT INVOICED
A42: TOTAL RWF DEPPOSITED ON BANK
A43: MEMBERSHIP FEES REGISTRETION
A44: MEMBERSHIP FEES CONTRIBUTION
A45: TOTAL INCOME | C45: 0
A46: TIMBER SUMMARY
B48: TIMBER TYPE | E48: NUMBER OF QUANTITY
B49: INTURUSU | E49: =SUM(B9:B12) -> 0
B50: PINUS | E50: =SUM(B6:B8) -> 0
B51: PALNCHE | E51: =SUM(B13:B14) -> 0
B52: IBIPANDE | E52: =SUM(B17:B18) -> 0
B53: UMUSAVE | E53: =SUM(B19:B20) -> 0
B54: OTHER | E54: =B29 -> 0
B55: OTHER | E55: =B30 -> 0
B56: OTHER | E56: =B31 -> 0
B57: OTHER | E57: =B32 -> 0
B58: OTHER | E58: =B33 -> 0
B59: OTHER | E59: =B34 -> 0
B60: OTHER | E60: =B35 -> 0
B61: OTHER | E61: =B36 -> 0
B62: TOTAL TIMBER | E62: =SUM(E49:H61) -> 0

Sheet NYAMASHEKE
A1: QUANTITY REPORT
A3: MONTHS REPORT OF AUGUST 2025
A5: NAME OF TIMBER | B5: No OF TIMBER | C5: PRICE OF TIMBER | E5: TOTAL COST | F5: TVA | G5: MSF | H5: TVA+MSF
A6: PINUS NINI | E6: =PRODUCT(B6*C6) -> 0 | F6: =PRODUCT(E6*18)/118 -> 0 | G6: =PRODUCT(B6*50) -> 0 | H6: =SUM(F6:G6) -> 0
A7: PINUS NTOYA | E7: =PRODUCT(B7*C7) -> 0 | F7: =PRODUCT(E7*18)/118 -> 0 | G7: =PRODUCT(B7*50) -> 0 | H7: =SUM(F7:G7) -> 0
A8: PINUS | E8: =PRODUCT(B8*C8) -> 0 | F8: =PRODUCT(E8*18)/118 -> 0 | G8: =PRODUCT(B8*50) -> 0 | H8: =SUM(F8:G8) -> 0
A9: MADIRIYE NINI | E9: =PRODUCT(B9*C9) -> 0 | F9: =PRODUCT(E9*18)/118 -> 0 | G9: =PRODUCT(B9*30) -> 0 | H9: =SUM(F9:G9) -> 0
A10: MADIRIYE NTOYA | E10: =PRODUCT(B10*C10) -> 0 | F10: =PRODUCT(E10*18)/118 -> 0 | G10: =PRODUCT(B10*30) -> 0 | H10: =SUM(F10:G10) -> 0
A11: MADRIEN | E11: =PRODUCT(B11*C11) -> 0 | F11: =PRODUCT(E11*18)/118 -> 0 | G11: =PRODUCT(B11*30) -> 0 | H11: =SUM(F11:G11) -> 0
A12: MADRIEN | E12: =PRODUCT(B12*C12) -> 0 | F12: =PRODUCT(E12*18)/118 -> 0 | G12: =PRODUCT(B12*30) -> 0 | H12: =SUM(F12:G12) -> 0
A13: PLANCHE | E13: =PRODUCT(B13*C13) -> 0 | F13: =PRODUCT(E13*18)/118 -> 0 | G13: =PRODUCT(B13*20) -> 0 | H13: =SUM(F13:G13) -> 0
A14: PLANCHE | E14: =PRODUCT(B14*C14) -> 0 | F14: =PRODUCT(E14*18)/118 -> 0 | G14: =PRODUCT(B14*20) -> 0 | H14: =SUM(F14:G14) -> 0
A15: Other Timber for Difference Price
A16: NAME OF TIMBER | B16: No OF TIMBER | C16: P/U | D16: MSF | E16: TOTAL COST | F16: VAT | G16: MSF | H16: VTA+MST
A17: IBIPANDE | E17: 0 | F17: 0 | G17: 0 | H17: 0
A18: IBIPANDE | E18: 0 | F18: 0 | G18: 0 | H18: 0
A19: UMUSAVE | E19: 0 | F19: 0 | G19: 0 | H19: 0
A20: UMUSAVE | E20: 0 | F20: 0 | G20: 0 | H20: 0
A21: OTHER | E21: 0 | F21: 0 | G21: 0 | H21: 0
A22: OTHER | E22: 0 | F22: 0 | G22: 0 | H22: 0
A23: OTHER | E23: 0 | F23: 0 | G23: 0 | H23: 0
A24: OTHER | E24: 0 | F24: 0 | G24: 0 | H24: 0
A25: OTHER | E25: 0 | F25: 0 | G25: 0 | H25: 0
A26: OTHER | E26: 0 | F26: 0 | G26: 0 | H26: 0
A27: OTHER | E27: 0 | F27: 0 | G27: 0 | H27: 0
A28: OTHER | E28: 0 | F28: 0 | G28: 0 | H28: 0
... A36: OTHER | E36: 0 | F36: 0 | G36: 0 | H36: 0
A37: TOTALY | E37: =SUM(E5:E36) -> 0 | F37: =SUM(F5:F36) -> 0 | G37: =SUM(G5:G36) -> 0 | H37: =SUM(H5:H36) -> 0
A38: SUMMARY | C38: RWF | E38: NAME | G38: Phone | H38: RWF
A39: TOTAL RWF PAID ON MOMO PAY
A40: TOTAL RWF PAID ON CASH
A41: AMOUNT NOT INVOICED
A42: TOTAL RWF DEPPOSITED ON BANK
A43: MEMBERSHIP FEES REGISTRETION
A44: MEMBERSHIP FEES CONTRIBUTION
A45: TOTAL INCOME | C45: 0
A46: TIMBER SUMMARY
B48: TIMBER TYPE | E48: NUMBER OF QUANTITY
B49: INTURUSU | E49: =SUM(B11:B14) -> 0
B50: PINUS | E50: =SUM(B8:B10) -> 0
B51: PALNCHE | E51: =SUM(B15:B16) -> 0
B52: IBIPANDE | E52: =SUM(B19:B20) -> 0
B53: UMUSAVE | E53: =SUM(B29:B30) -> 0
B54: OTHER | E54: =B31 -> 0
B55: OTHER | E55: =B32 -> 0
B56: OTHER | E56: =B33 -> 0
B57: OTHER | E57: =B34 -> 0
B58: OTHER | E58: =B35 -> 0
B59: OTHER | E59: =B36 -> 0
B60: OTHER | E60: =B37 -> 0
B61: OTHER | E61: =B45 -> 0
B62: TOTAL TIMBER | E62: =SUM(E49:H61) -> 0

Sheet KAYONZA
A1: QUANTITY REPORT
A3: MONTHS REPORT OF AUGUST 2025
A5: NAME OF TIMBER | B5: No OF TIMBER | C5: PRICE OF TIMBER | E5: TOTAL COST | F5: TVA | G5: MSF | H5: TVA+MSF
A6: PINUS NINI | E6: =PRODUCT(B6*C6) -> 0 | F6: =PRODUCT(E6*18)/118 -> 0 | G6: =PRODUCT(B6*50) -> 0 | H6: =SUM(F6:G6) -> 0
A7: PINUS NTOYA | E7: =PRODUCT(B7*C7) -> 0 | F7: =PRODUCT(E7*18)/118 -> 0 | G7: =PRODUCT(B7*50) -> 0 | H7: =SUM(F7:G7) -> 0
A8: PINUS | E8: =PRODUCT(B8*C8) -> 0 | F8: =PRODUCT(E8*18)/118 -> 0 | G8: =PRODUCT(B8*50) -> 0 | H8: =SUM(F8:G8) -> 0
A9: MADIRIYE NINI | E9: =PRODUCT(B9*C9) -> 0 | F9: =PRODUCT(E9*18)/118 -> 0 | G9: =PRODUCT(B9*30) -> 0 | H9: =SUM(F9:G9) -> 0
A10: MADIRIYE NTOYA | E10: =PRODUCT(B10*C10) -> 0 | F10: =PRODUCT(E10*18)/118 -> 0 | G10: =PRODUCT(B10*30) -> 0 | H10: =SUM(F10:G10) -> 0
A11: MADRIEN | E11: =PRODUCT(B11*C11) -> 0 | F11: =PRODUCT(E11*18)/118 -> 0 | G11: =PRODUCT(B11*30) -> 0 | H11: =SUM(F11:G11) -> 0
A12: MADRIEN | E12: =PRODUCT(B12*C12) -> 0 | F12: =PRODUCT(E12*18)/118 -> 0 | G12: =PRODUCT(B12*30) -> 0 | H12: =SUM(F12:G12) -> 0
A13: PLANCHE | E13: =PRODUCT(B13*C13) -> 0 | F13: =PRODUCT(E13*18)/118 -> 0 | G13: =PRODUCT(B13*20) -> 0 | H13: =SUM(F13:G13) -> 0
A14: PLANCHE | E14: =PRODUCT(B14*C14) -> 0 | F14: =PRODUCT(E14*18)/118 -> 0 | G14: =PRODUCT(B14*20) -> 0 | H14: =SUM(F14:G14) -> 0
A15: Other Timber for Difference Price
A16: NAME OF TIMBER | B16: No OF TIMBER | C16: P/U | D16: MSF | E16: TOTAL COST | F16: VAT | G16: MSF | H16: VTA+MST
A17: IBIPANDE | E17: =PRODUCT(B17*C17) -> 0 | F17: =PRODUCT(E17*18)/118 -> 0 | G17: =PRODUCT(B17*D17) -> 0 | H17: =SUM(F17:G17) -> 0
A18: IBIPANDE | E18: =PRODUCT(B18*C18) -> 0 | F18: =PRODUCT(E18*18)/118 -> 0 | G18: =PRODUCT(B18*D18) -> 0 | H18: =SUM(F18:G18) -> 0
A19: UMUSAVE | E19: =PRODUCT(B19*C19) -> 0 | F19: =PRODUCT(E19*18)/118 -> 0 | G19: =PRODUCT(B19*D19) -> 0 | H19: =SUM(F19:G19) -> 0
A20: UMUSAVE | E20: =PRODUCT(B20*C20) -> 0 | F20: =PRODUCT(E20*18)/118 -> 0 | G20: =PRODUCT(B20*D20) -> 0 | H20: =SUM(F20:G20) -> 0
A21: OTHER | E21: =PRODUCT(B21*C21) -> 0 | F21: =PRODUCT(E21*18)/118 -> 0 | G21: =PRODUCT(B21*D21) -> 0 | H21: =SUM(F21:G21) -> 0
A22: OTHER | E22: =PRODUCT(B22*C22) -> 0 | F22: =PRODUCT(E22*18)/118 -> 0 | G22: =PRODUCT(B22*D22) -> 0 | H22: =SUM(F22:G22) -> 0
A23: OTHER | E23: =PRODUCT(B23*C23) -> 0 | F23: =PRODUCT(E23*18)/118 -> 0 | G23: =PRODUCT(B23*D23) -> 0 | H23: =SUM(F23:G23) -> 0
A24: OTHER | E24: =PRODUCT(B24*C24) -> 0 | F24: =PRODUCT(E24*18)/118 -> 0 | G24: =PRODUCT(B24*D24) -> 0 | H24: =SUM(F24:G24) -> 0
A25: OTHER | E25: =PRODUCT(B25*C25) -> 0 | F25: =PRODUCT(E25*18)/118 -> 0 | G25: =PRODUCT(B25*D25) -> 0 | H25: =SUM(F25:G25) -> 0
A26: OTHER | E26: =PRODUCT(B26*C26) -> 0 | F26: =PRODUCT(E26*18)/118 -> 0 | G26: =PRODUCT(B26*D26) -> 0 | H26: =SUM(F26:G26) -> 0
A27: OTHER | E27: =PRODUCT(B27*C27) -> 0 | F27: =PRODUCT(E27*18)/118 -> 0 | G27: =PRODUCT(B27*D27) -> 0 | H27: =SUM(F27:G27) -> 0
A28: OTHER | E28: =PRODUCT(B28*C28) -> 0 | F28: =PRODUCT(E28*18)/118 -> 0 | G28: =PRODUCT(B28*D28) -> 0 | H28: =SUM(F28:G28) -> 0
A29: TOTALY | E29: =SUM(E6:E28) -> 0 | F29: =SUM(F6:F28) -> 0 | G29: =SUM(G6:G28) -> 0 | H29: =SUM(F29:G29) -> 0
A30: SUMMARY | C30: RWF | E30: NAME | G30: Phone | H30: RWF
A31: TOTAL RWF PAID ON MOMO PAY
A32: TOTAL RWF PAID ON CASH
A33: AMOUNT NOT INVOICED
A34: TOTAL RWF DEPPOSITED ON BANK
A35: MEMBERSHIP FEES REGISTRETION
A36: MEMBERSHIP FEES CONTRIBUTION
A37: TOTAL INCOME | C37: 0
A38: TIMBER SUMMARY
B40: TIMBER TYPE | E40: NUMBER OF QUANTITY
B41: INTURUSU | E41: =SUM(B9:B12) -> 0
B42: PINUS | E42: =SUM(B6:B8) -> 0
B43: PALNCHE | E43: =SUM(B13:B14) -> 0
B44: IBIPANDE | E44: =SUM(B17:B18) -> 0
B45: UMUSAVE | E45: =SUM(B19:B20) -> 0
B46: OTHER | E46: =B21 -> 0
B47: OTHER | E47: =B22 -> 0
B48: OTHER | E48: =B23 -> 0
B49: OTHER | E49: =B24 -> 0
B50: OTHER | E50: =B25 -> 0
B51: OTHER | E51: =B26 -> 0
B52: OTHER | E52: =B27 -> 0
B53: OTHER | E53: =B28 -> 0
B54: TOTAL TIMBER | E54: =SUM(E41:H53) -> 0

Sheet KARONGI
A1: QUANTITY REPORT
A3: MONTHS REPORT OF AUGUST 2025
A5: NAME OF TIMBER | B5: No OF TIMBER | C5: PRICE OF TIMBER | E5: TOTAL COST | F5: TVA | G5: MSF | H5: TVA+MSF
A6: PINUS NINI | E6: =PRODUCT(B6*C6) -> 0 | F6: =PRODUCT(E6*18)/118 -> 0 | G6: =PRODUCT(B6*50) -> 0 | H6: =SUM(F6:G6) -> 0
A7: PINUS NTOYA | E7: =PRODUCT(B7*C7) -> 0 | F7: =PRODUCT(E7*18)/118 -> 0 | G7: =PRODUCT(B7*50) -> 0 | H7: =SUM(F7:G7) -> 0
A8: PINUS | E8: =PRODUCT(B8*C8) -> 0 | F8: =PRODUCT(E8*18)/118 -> 0 | G8: =PRODUCT(B8*50) -> 0 | H8: =SUM(F8:G8) -> 0
A9: MADIRIYE NINI | E9: =PRODUCT(B9*C9) -> 0 | F9: =PRODUCT(E9*18)/118 -> 0 | G9: =PRODUCT(B9*30) -> 0 | H9: =SUM(F9:G9) -> 0
A10: MADIRIYE NTOYA | E10: =PRODUCT(B10*C10) -> 0 | F10: =PRODUCT(E10*18)/118 -> 0 | G10: =PRODUCT(B10*30) -> 0 | H10: =SUM(F10:G10) -> 0
A11: MADRIEN | E11: =PRODUCT(B11*C11) -> 0 | F11: =PRODUCT(E11*18)/118 -> 0 | G11: =PRODUCT(B11*30) -> 0 | H11: =SUM(F11:G11) -> 0
A12: MADRIEN | E12: =PRODUCT(B12*C12) -> 0 | F12: =PRODUCT(E12*18)/118 -> 0 | G12: =PRODUCT(B12*30) -> 0 | H12: =SUM(F12:G12) -> 0
A13: PLANCHE | E13: =PRODUCT(B13*C13) -> 0 | F13: =PRODUCT(E13*18)/118 -> 0 | G13: =PRODUCT(B13*20) -> 0 | H13: =SUM(F13:G13) -> 0
A14: PLANCHE | E14: =PRODUCT(B14*C14) -> 0 | F14: =PRODUCT(E14*18)/118 -> 0 | G14: =PRODUCT(B14*20) -> 0 | H14: =SUM(F14:G14) -> 0
A15: Other Timber for Difference Price
A16: NAME OF TIMBER | B16: No OF TIMBER | C16: P/U | D16: MSF | E16: TOTAL COST | F16: VAT | G16: MSF | H16: VTA+MST
A17: IBIPANDE | E17: 0 | F17: 0 | G17: 0 | H17: 0
A18: IBIPANDE | E18: 0 | F18: 0 | G18: 0 | H18: 0
A19: UMUSAVE | E19: 0 | F19: 0 | G19: 0 | H19: 0
A20: UMUSAVE | E20: 0 | F20: 0 | G20: 0 | H20: 0
A21: OTHER | E21: 0 | F21: 0 | G21: 0 | H21: 0
A22: OTHER | E22: 0 | F22: 0 | G22: 0 | H22: 0
A23: OTHER | E23: 0 | F23: 0 | G23: 0 | H23: 0
A24: OTHER | E24: 0 | F24: 0 | G24: 0 | H24: 0
A25: OTHER | E25: 0 | F25: 0 | G25: 0 | H25: 0
A26: OTHER | E26: 0 | F26: 0 | G26: 0 | H26: 0
A27: OTHER | E27: 0 | F27: 0 | G27: 0 | H27: 0
A28: OTHER | E28: 0 | F28: 0 | G28: 0 | H28: 0
... A36: OTHER | E36: 0 | F36: 0 | G36: 0 | H36: 0
A37: TOTALY | E37: =SUM(E5:E36) -> 0 | F37: =SUM(F5:F36) -> 0 | G37: =SUM(G5:G36) -> 0 | H37: =SUM(H5:H36) -> 0
A38: SUMMARY | C38: RWF | E38: NAME | G38: Phone | H38: RWF
A39: TOTAL RWF PAID ON MOMO PAY
A40: TOTAL RWF PAID ON CASH
A41: AMOUNT NOT INVOICED
A42: TOTAL RWF DEPPOSITED ON BANK
A43: MEMBERSHIP FEES REGISTRETION
A44: MEMBERSHIP FEES CONTRIBUTION
A45: TOTAL INCOME | C45: 0
A46: TIMBER SUMMARY
B48: TIMBER TYPE | E48: NUMBER OF QUANTITY
B49: INTURUSU | E49: =SUM(B9:B12) -> 0
B50: PINUS | E50: =SUM(B6:B8) -> 0
B51: PALNCHE | E51: =SUM(B13:B14) -> 0
B52: IBIPANDE | E52: =SUM(B17:B18) -> 0
B53: UMUSAVE | E53: =SUM(B19:B20) -> 0
B54: OTHER | E54: =B29 -> 0
B55: OTHER | E55: =B30 -> 0
B56: OTHER | E56: =B31 -> 0
B57: OTHER | E57: =B32 -> 0
B58: OTHER | E58: =B33 -> 0
B59: OTHER | E59: =B34 -> 0
B60: OTHER | E60: =B35 -> 0
B61: OTHER | E61: =B36 -> 0
B62: TOTAL TIMBER | E62: =SUM(E49:H61) -> 0

Sheet RUBAVU
A1: QUANTITY REPORT
A3: MONTHS REPORT OF AUGUST 2025
A5: NAME OF TIMBER | B5: No OF TIMBER | C5: PRICE OF TIMBER | E5: TOTAL COST | F5: TVA | G5: MSF | H5: TVA+MSF
A6: PINUS NINI | E6: =PRODUCT(B6*C6) -> 0 | F6: =PRODUCT(E6*18)/118 -> 0 | G6: =PRODUCT(B6*50) -> 0 | H6: =SUM(F6:G6) -> 0
A7: PINUS NTOYA | E7: =PRODUCT(B7*C7) -> 0 | F7: =PRODUCT(E7*18)/118 -> 0 | G7: =PRODUCT(B7*50) -> 0 | H7: =SUM(F7:G7) -> 0
A8: PINUS | E8: =PRODUCT(B8*C8) -> 0 | F8: =PRODUCT(E8*18)/118 -> 0 | G8: =PRODUCT(B8*50) -> 0 | H8: =SUM(F8:G8) -> 0
A9: MADIRIYE NINI | E9: =PRODUCT(B9*C9) -> 0 | F9: =PRODUCT(E9*18)/118 -> 0 | G9: =PRODUCT(B9*30) -> 0 | H9: =SUM(F9:G9) -> 0
A10: MADIRIYE NTOYA | E10: =PRODUCT(B10*C10) -> 0 | F10: =PRODUCT(E10*18)/118 -> 0 | G10: =PRODUCT(B10*30) -> 0 | H10: =SUM(F10:G10) -> 0
A11: MADRIEN | E11: =PRODUCT(B11*C11) -> 0 | F11: =PRODUCT(E11*18)/118 -> 0 | G11: =PRODUCT(B11*30) -> 0 | H11: =SUM(F11:G11) -> 0
A12: MADRIEN | E12: =PRODUCT(B12*C12) -> 0 | F12: =PRODUCT(E12*18)/118 -> 0 | G12: =PRODUCT(B12*30) -> 0 | H12: =SUM(F12:G12) -> 0
A13: PLANCHE | E13: =PRODUCT(B13*C13) -> 0 | F13: =PRODUCT(E13*18)/118 -> 0 | G13: =PRODUCT(B13*20) -> 0 | H13: =SUM(F13:G13) -> 0
A14: PLANCHE | E14: =PRODUCT(B14*C14) -> 0 | F14: =PRODUCT(E14*18)/118 -> 0 | G14: =PRODUCT(B14*20) -> 0 | H14: =SUM(F14:G14) -> 0
A15: Other Timber for Difference Price
A16: NAME OF TIMBER | B16: No OF TIMBER | C16: P/U | D16: MSF | E16: TOTAL COST | F16: VAT | G16: MSF | H16: VTA+MST
A17: IBIPANDE | E17: =PRODUCT(B17*C17) -> 0 | F17: =PRODUCT(E17*18)/118 -> 0 | G17: =PRODUCT(B17*D17) -> 0 | H17: =SUM(F17:G17) -> 0
A18: IBIPANDE | E18: =PRODUCT(B18*C18) -> 0 | F18: =PRODUCT(E18*18)/118 -> 0 | G18: =PRODUCT(B18*D18) -> 0 | H18: =SUM(F18:G18) -> 0
A19: UMUSAVE | E19: =PRODUCT(B19*C19) -> 0 | F19: =PRODUCT(E19*18)/118 -> 0 | G19: =PRODUCT(B19*D19) -> 0 | H19: =SUM(F19:G19) -> 0
A20: UMUSAVE | E20: =PRODUCT(B20*C20) -> 0 | F20: =PRODUCT(E20*18)/118 -> 0 | G20: =PRODUCT(B20*D20) -> 0 | H20: =SUM(F20:G20) -> 0
A21: OTHER | E21: =PRODUCT(B21*C21) -> 0 | F21: =PRODUCT(E21*18)/118 -> 0 | G21: =PRODUCT(B21*D21) -> 0 | H21: =SUM(F21:G21) -> 0
A22: OTHER | E22: =PRODUCT(B22*C22) -> 0 | F22: =PRODUCT(E22*18)/118 -> 0 | G22: =PRODUCT(B22*D22) -> 0 | H22: =SUM(F22:G22) -> 0
A23: OTHER | E23: =PRODUCT(B23*C23) -> 0 | F23: =PRODUCT(E23*18)/118 -> 0 | G23: =PRODUCT(B23*D23) -> 0 | H23: =SUM(F23:G23) -> 0
A24: OTHER | E24: =PRODUCT(B24*C24) -> 0 | F24: =PRODUCT(E24*18)/118 -> 0 | G24: =PRODUCT(B24*D24) -> 0 | H24: =SUM(F24:G24) -> 0
A25: OTHER | E25: =PRODUCT(B25*C25) -> 0 | F25: =PRODUCT(E25*18)/118 -> 0 | G25: =PRODUCT(B25*D25) -> 0 | H25: =SUM(F25:G25) -> 0
A26: OTHER | E26: =PRODUCT(B26*C26) -> 0 | F26: =PRODUCT(E26*18)/118 -> 0 | G26: =PRODUCT(B26*D26) -> 0 | H26: =SUM(F26:G26) -> 0
A27: OTHER | E27: =PRODUCT(B27*C27) -> 0 | F27: =PRODUCT(E27*18)/118 -> 0 | G27: =PRODUCT(B27*D27) -> 0 | H27: =SUM(F27:G27) -> 0
A28: OTHER | E28: =PRODUCT(B28*C28) -> 0 | F28: =PRODUCT(E28*18)/118 -> 0 | G28: =PRODUCT(B28*D28) -> 0 | H28: =SUM(F28:G28) -> 0
A29: TOTALY | E29: =SUM(E6:E28) -> 0 | F29: =SUM(F6:F28) -> 0 | G29: =SUM(G6:G28) -> 0 | H29: =SUM(F29:G29) -> 0
A30: SUMMARY | C30: RWF | E30: NAME | G30: Phone | H30: RWF
A31: TOTAL RWF PAID ON MOMO PAY
A32: TOTAL RWF PAID ON CASH
A33: AMOUNT NOT INVOICED
A34: TOTAL RWF DEPPOSITED ON BANK
A35: MEMBERSHIP FEES REGISTRETION
A36: MEMBERSHIP FEES CONTRIBUTION
A37: TOTAL INCOME | C37: 0
A38: TIMBER SUMMARY
B40: TIMBER TYPE | E40: NUMBER OF QUANTITY
B41: INTURUSU | E41: =SUM(B9:B12) -> 0
B42: PINUS | E42: =SUM(B6:B8) -> 0
B43: PALNCHE | E43: =SUM(B13:B14) -> 0
B44: IBIPANDE | E44: =SUM(B17:B18) -> 0
B45: UMUSAVE | E45: =SUM(B19:B20) -> 0
B46: OTHER | E46: =B21 -> 0
B47: OTHER | E47: =B22 -> 0
B48: OTHER | E48: =B23 -> 0
B49: OTHER | E49: =B24 -> 0
B50: OTHER | E50: =B25 -> 0
B51: OTHER | E51: =B26 -> 0
B52: OTHER | E52: =B27 -> 0
B53: OTHER | E53: =B28 -> 0
B54: TOTAL TIMBER | E54: =SUM(E41:H53) -> 0

Sheet MUSANZE
A1: QUANTITY REPORT
A3: MONTHS REPORT OF AUGUST 2025
A5: NAME OF TIMBER | B5: No OF TIMBER | C5: PRICE OF TIMBER | E5: TOTAL COST | F5: TVA | G5: MSF | H5: TVA+MSF
A6: PINUS NINI | E6: =PRODUCT(B6*C6) -> 0 | F6: =PRODUCT(E6*18)/118 -> 0 | G6: =PRODUCT(B6*50) -> 0 | H6: =SUM(F6:G6) -> 0
A7: PINUS NTOYA | E7: =PRODUCT(B7*C7) -> 0 | F7: =PRODUCT(E7*18)/118 -> 0 | G7: =PRODUCT(B7*50) -> 0 | H7: =SUM(F7:G7) -> 0
A8: PINUS | E8: =PRODUCT(B8*C8) -> 0 | F8: =PRODUCT(E8*18)/118 -> 0 | G8: =PRODUCT(B8*50) -> 0 | H8: =SUM(F8:G8) -> 0
A9: MADIRIYE NINI | E9: =PRODUCT(B9*C9) -> 0 | F9: =PRODUCT(E9*18)/118 -> 0 | G9: =PRODUCT(B9*30) -> 0 | H9: =SUM(F9:G9) -> 0
A10: MADIRIYE NTOYA | E10: =PRODUCT(B10*C10) -> 0 | F10: =PRODUCT(E10*18)/118 -> 0 | G10: =PRODUCT(B10*30) -> 0 | H10: =SUM(F10:G10) -> 0
A11: MADRIEN | E11: =PRODUCT(B11*C11) -> 0 | F11: =PRODUCT(E11*18)/118 -> 0 | G11: =PRODUCT(B11*30) -> 0 | H11: =SUM(F11:G11) -> 0
A12: MADRIEN | E12: =PRODUCT(B12*C12) -> 0 | F12: =PRODUCT(E12*18)/118 -> 0 | G12: =PRODUCT(B12*30) -> 0 | H12: =SUM(F12:G12) -> 0
A13: PLANCHE | E13: =PRODUCT(B13*C13) -> 0 | F13: =PRODUCT(E13*18)/118 -> 0 | G13: =PRODUCT(B13*20) -> 0 | H13: =SUM(F13:G13) -> 0
A14: PLANCHE | E14: =PRODUCT(B14*C14) -> 0 | F14: =PRODUCT(E14*18)/118 -> 0 | G14: =PRODUCT(B14*20) -> 0 | H14: =SUM(F14:G14) -> 0
A15: Other Timber for Difference Price
A16: NAME OF TIMBER | B16: No OF TIMBER | C16: P/U | D16: MSF | E16: TOTAL COST | F16: VAT | G16: MSF | H16: VTA+MST
A17: IBIPANDE | E17: =PRODUCT(B17*C17) -> 0 | F17: =PRODUCT(E17*18)/118 -> 0 | G17: =PRODUCT(B17*D17) -> 0 | H17: =SUM(F17:G17) -> 0
A18: IBIPANDE | E18: =PRODUCT(B18*C18) -> 0 | F18: =PRODUCT(E18*18)/118 -> 0 | G18: =PRODUCT(B18*D18) -> 0 | H18: =SUM(F18:G18) -> 0
A19: UMUSAVE | E19: =PRODUCT(B19*C19) -> 0 | F19: =PRODUCT(E19*18)/118 -> 0 | G19: =PRODUCT(B19*D19) -> 0 | H19: =SUM(F19:G19) -> 0
A20: UMUSAVE | E20: =PRODUCT(B20*C20) -> 0 | F20: =PRODUCT(E20*18)/118 -> 0 | G20: =PRODUCT(B20*D20) -> 0 | H20: =SUM(F20:G20) -> 0
A21: OTHER | E21: =PRODUCT(B21*C21) -> 0 | F21: =PRODUCT(E21*18)/118 -> 0 | G21: =PRODUCT(B21*D21) -> 0 | H21: =SUM(F21:G21) -> 0
A22: OTHER | E22: =PRODUCT(B22*C22) -> 0 | F22: =PRODUCT(E22*18)/118 -> 0 | G22: =PRODUCT(B22*D22) -> 0 | H22: =SUM(F22:G22) -> 0
A23: OTHER | E23: =PRODUCT(B23*C23) -> 0 | F23: =PRODUCT(E23*18)/118 -> 0 | G23: =PRODUCT(B23*D23) -> 0 | H23: =SUM(F23:G23) -> 0
A24: OTHER | E24: =PRODUCT(B24*C24) -> 0 | F24: =PRODUCT(E24*18)/118 -> 0 | G24: =PRODUCT(B24*D24) -> 0 | H24: =SUM(F24:G24) -> 0
A25: OTHER | E25: =PRODUCT(B25*C25) -> 0 | F25: =PRODUCT(E25*18)/118 -> 0 | G25: =PRODUCT(B25*D25) -> 0 | H25: =SUM(F25:G25) -> 0
A26: OTHER | E26: =PRODUCT(B26*C26) -> 0 | F26: =PRODUCT(E26*18)/118 -> 0 | G26: =PRODUCT(B26*D26) -> 0 | H26: =SUM(F26:G26) -> 0
A27: OTHER | E27: =PRODUCT(B27*C27) -> 0 | F27: =PRODUCT(E27*18)/118 -> 0 | G27: =PRODUCT(B27*D27) -> 0 | H27: =SUM(F27:G27) -> 0
A28: OTHER | E28: =PRODUCT(B28*C28) -> 0 | F28: =PRODUCT(E28*18)/118 -> 0 | G28: =PRODUCT(B28*D28) -> 0 | H28: =SUM(F28:G28) -> 0
A29: TOTALY | E29: =SUM(E6:E28) -> 0 | F29: =SUM(F6:F28) -> 0 | G29: =SUM(G6:G28) -> 0 | H29: =SUM(F29:G29) -> 0
A30: SUMMARY | C30: RWF | E30: NAME | G30: Phone | H30: RWF
A31: TOTAL RWF PAID ON MOMO PAY
A32: TOTAL RWF PAID ON CASH
A33: AMOUNT NOT INVOICED
A34: TOTAL RWF DEPPOSITED ON BANK
A35: MEMBERSHIP FEES REGISTRETION
A36: MEMBERSHIP FEES CONTRIBUTION
A37: TOTAL INCOME | C37: 0
A38: TIMBER SUMMARY
B40: TIMBER TYPE | E40: NUMBER OF QUANTITY
B41: INTURUSU | E41: =SUM(B9:B12) -> 0
B42: PINUS | E42: =SUM(B6:B8) -> 0
B43: PALNCHE | E43: =SUM(B13:B14) -> 0
B44: IBIPANDE | E44: =SUM(B17:B18) -> 0
B45: UMUSAVE | E45: =SUM(B19:B20) -> 0
B46: OTHER | E46: =B21 -> 0
B47: OTHER | E47: =B22 -> 0
B48: OTHER | E48: =B23 -> 0
B49: OTHER | E49: =B24 -> 0
B50: OTHER | E50: =B25 -> 0
B51: OTHER | E51: =B26 -> 0
B52: OTHER | E52: =B27 -> 0
B53: OTHER | E53: =B28 -> 0
B54: TOTAL TIMBER | E54: =SUM(E41:H53) -> 0

Sheet NYAGATARE
A1: QUANTITY REPORT
A3: MONTHS REPORT OF AUGUST 2025
A5: NAME OF TIMBER | B5: No OF TIMBER | C5: PRICE OF TIMBER | E5: TOTAL COST | F5: TVA | G5: MSF | H5: TVA+MSF
A6: PINUS NINI | E6: =PRODUCT(B6*C6) -> 0 | F6: =PRODUCT(E6*18)/118 -> 0 | G6: =PRODUCT(B6*50) -> 0 | H6: =SUM(F6:G6) -> 0
A7: PINUS NTOYA | E7: =PRODUCT(B7*C7) -> 0 | F7: =PRODUCT(E7*18)/118 -> 0 | G7: =PRODUCT(B7*50) -> 0 | H7: =SUM(F7:G7) -> 0
A8: PINUS | E8: =PRODUCT(B8*C8) -> 0 | F8: =PRODUCT(E8*18)/118 -> 0 | G8: =PRODUCT(B8*50) -> 0 | H8: =SUM(F8:G8) -> 0
A9: MADIRIYE NINI | E9: =PRODUCT(B9*C9) -> 0 | F9: =PRODUCT(E9*18)/118 -> 0 | G9: =PRODUCT(B9*30) -> 0 | H9: =SUM(F9:G9) -> 0
A10: MADIRIYE NTOYA | E10: =PRODUCT(B10*C10) -> 0 | F10: =PRODUCT(E10*18)/118 -> 0 | G10: =PRODUCT(B10*30) -> 0 | H10: =SUM(F10:G10) -> 0
A11: MADRIEN | E11: =PRODUCT(B11*C11) -> 0 | F11: =PRODUCT(E11*18)/118 -> 0 | G11: =PRODUCT(B11*30) -> 0 | H11: =SUM(F11:G11) -> 0
A12: MADRIEN | E12: =PRODUCT(B12*C12) -> 0 | F12: =PRODUCT(E12*18)/118 -> 0 | G12: =PRODUCT(B12*30) -> 0 | H12: =SUM(F12:G12) -> 0
A13: PLANCHE | E13: =PRODUCT(B13*C13) -> 0 | F13: =PRODUCT(E13*18)/118 -> 0 | G13: =PRODUCT(B13*20) -> 0 | H13: =SUM(F13:G13) -> 0
A14: PLANCHE | E14: =PRODUCT(B14*C14) -> 0 | F14: =PRODUCT(E14*18)/118 -> 0 | G14: =PRODUCT(B14*20) -> 0 | H14: =SUM(F14:G14) -> 0
A15: Other Timber for Difference Price
A16: NAME OF TIMBER | B16: No OF TIMBER | C16: P/U | D16: MSF | E16: TOTAL COST | F16: VAT | G16: MSF | H16: VTA+MST
A17: IBIPANDE | E17: =PRODUCT(B17*C17) -> 0 | F17: =PRODUCT(E17*18)/118 -> 0 | G17: =PRODUCT(B17*D17) -> 0 | H17: =SUM(F17:G17) -> 0
A18: IBIPANDE | E18: =PRODUCT(B18*C18) -> 0 | F18: =PRODUCT(E18*18)/118 -> 0 | G18: =PRODUCT(B18*D18) -> 0 | H18: =SUM(F18:G18) -> 0
A19: UMUSAVE | E19: =PRODUCT(B19*C19) -> 0 | F19: =PRODUCT(E19*18)/118 -> 0 | G19: =PRODUCT(B19*D19) -> 0 | H19: =SUM(F19:G19) -> 0
A20: UMUSAVE | E20: =PRODUCT(B20*C20) -> 0 | F20: =PRODUCT(E20*18)/118 -> 0 | G20: =PRODUCT(B20*D20) -> 0 | H20: =SUM(F20:G20) -> 0
A21: OTHER | E21: =PRODUCT(B21*C21) -> 0 | F21: =PRODUCT(E21*18)/118 -> 0 | G21: =PRODUCT(B21*D21) -> 0 | H21: =SUM(F21:G21) -> 0
A22: OTHER | E22: =PRODUCT(B22*C22) -> 0 | F22: =PRODUCT(E22*18)/118 -> 0 | G22: =PRODUCT(B22*D22) -> 0 | H22: =SUM(F22:G22) -> 0
A23: OTHER | E23: =PRODUCT(B23*C23) -> 0 | F23: =PRODUCT(E23*18)/118 -> 0 | G23: =PRODUCT(B23*D23) -> 0 | H23: =SUM(F23:G23) -> 0
A24: OTHER | E24: =PRODUCT(B24*C24) -> 0 | F24: =PRODUCT(E24*18)/118 -> 0 | G24: =PRODUCT(B24*D24) -> 0 | H24: =SUM(F24:G24) -> 0
A25: OTHER | E25: =PRODUCT(B25*C25) -> 0 | F25: =PRODUCT(E25*18)/118 -> 0 | G25: =PRODUCT(B25*D25) -> 0 | H25: =SUM(F25:G25) -> 0
A26: OTHER | E26: =PRODUCT(B26*C26) -> 0 | F26: =PRODUCT(E26*18)/118 -> 0 | G26: =PRODUCT(B26*D26) -> 0 | H26: =SUM(F26:G26) -> 0
A27: OTHER | E27: =PRODUCT(B27*C27) -> 0 | F27: =PRODUCT(E27*18)/118 -> 0 | G27: =PRODUCT(B27*D27) -> 0 | H27: =SUM(F27:G27) -> 0
A28: OTHER | E28: =PRODUCT(B28*C28) -> 0 | F28: =PRODUCT(E28*18)/118 -> 0 | G28: =PRODUCT(B28*D28) -> 0 | H28: =SUM(F28:G28) -> 0
A29: TOTALY | E29: =SUM(E6:E28) -> 0 | F29: =SUM(F6:F28) -> 0 | G29: =SUM(G6:G28) -> 0 | H29: =SUM(F29:G29) -> 0
A30: SUMMARY | C30: RWF | E30: NAME | G30: Phone | H30: RWF
A31: TOTAL RWF PAID ON MOMO PAY
A32: TOTAL RWF PAID ON CASH
A33: AMOUNT NOT INVOICED
A34: TOTAL RWF DEPPOSITED ON BANK
A35: MEMBERSHIP FEES REGISTRETION
A36: MEMBERSHIP FEES CONTRIBUTION
A37: TOTAL INCOME | C37: 0
A38: TIMBER SUMMARY
B40: TIMBER TYPE | E40: NUMBER OF QUANTITY
B41: INTURUSU | E41: =SUM(B9:B12) -> 0
B42: PINUS | E42: =SUM(B6:B8) -> 0
B43: PALNCHE | E43: =SUM(B13:B14) -> 0
B44: IBIPANDE | E44: =SUM(B17:B18) -> 0
B45: UMUSAVE | E45: =SUM(B19:B20) -> 0
B46: OTHER | E46: =B21 -> 0
B47: OTHER | E47: =B22 -> 0
B48: OTHER | E48: =B23 -> 0
B49: OTHER | E49: =B24 -> 0
B50: OTHER | E50: =B25 -> 0
B51: OTHER | E51: =B26 -> 0
B52: OTHER | E52: =B27 -> 0
B53: OTHER | E53: =B28 -> 0
B54: TOTAL TIMBER | E54: =SUM(E41:H53) -> 0

Sheet KIREHE
A1: QUANTITY REPORT
A3: MONTHS REPORT OF AUGUST 2025
A5: NAME OF TIMBER | B5: No OF TIMBER | C5: PRICE OF TIMBER | E5: TOTAL COST | F5: TVA | G5: MSF | H5: TVA+MSF
A6: PINUS NINI | E6: =PRODUCT(B6*C6) -> 0 | F6: =PRODUCT(E6*18)/118 -> 0 | G6: =PRODUCT(B6*50) -> 0 | H6: =SUM(F6:G6) -> 0
A7: PINUS NTOYA | E7: =PRODUCT(B7*C7) -> 0 | F7: =PRODUCT(E7*18)/118 -> 0 | G7: =PRODUCT(B7*50) -> 0 | H7: =SUM(F7:G7) -> 0
A8: PINUS | E8: =PRODUCT(B8*C8) -> 0 | F8: =PRODUCT(E8*18)/118 -> 0 | G8: =PRODUCT(B8*50) -> 0 | H8: =SUM(F8:G8) -> 0
A9: MADIRIYE NINI | E9: =PRODUCT(B9*C9) -> 0 | F9: =PRODUCT(E9*18)/118 -> 0 | G9: =PRODUCT(B9*30) -> 0 | H9: =SUM(F9:G9) -> 0
A10: MADIRIYE NTOYA | E10: =PRODUCT(B10*C10) -> 0 | F10: =PRODUCT(E10*18)/118 -> 0 | G10: =PRODUCT(B10*30) -> 0 | H10: =SUM(F10:G10) -> 0
A11: MADRIEN | E11: =PRODUCT(B11*C11) -> 0 | F11: =PRODUCT(E11*18)/118 -> 0 | G11: =PRODUCT(B11*30) -> 0 | H11: =SUM(F11:G11) -> 0
A12: MADRIEN | E12: =PRODUCT(B12*C12) -> 0 | F12: =PRODUCT(E12*18)/118 -> 0 | G12: =PRODUCT(B12*30) -> 0 | H12: =SUM(F12:G12) -> 0
A13: PLANCHE | E13: =PRODUCT(B13*C13) -> 0 | F13: =PRODUCT(E13*18)/118 -> 0 | G13: =PRODUCT(B13*20) -> 0 | H13: =SUM(F13:G13) -> 0
A14: PLANCHE | E14: =PRODUCT(B14*C14) -> 0 | F14: =PRODUCT(E14*18)/118 -> 0 | G14: =PRODUCT(B14*20) -> 0 | H14: =SUM(F14:G14) -> 0
A15: Other Timber for Difference Price
A16: NAME OF TIMBER | B16: No OF TIMBER | C16: P/U | D16: MSF | E16: TOTAL COST | F16: VAT | G16: MSF | H16: VTA+MST
A17: IBIPANDE | E17: =PRODUCT(B17*C17) -> 0 | F17: =PRODUCT(E17*18)/118 -> 0 | G17: =PRODUCT(B17*D17) -> 0 | H17: =SUM(F17:G17) -> 0
A18: IBIPANDE | E18: =PRODUCT(B18*C18) -> 0 | F18: =PRODUCT(E18*18)/118 -> 0 | G18: =PRODUCT(B18*D18) -> 0 | H18: =SUM(F18:G18) -> 0
A19: UMUSAVE | E19: =PRODUCT(B19*C19) -> 0 | F19: =PRODUCT(E19*18)/118 -> 0 | G19: =PRODUCT(B19*D19) -> 0 | H19: =SUM(F19:G19) -> 0
A20: UMUSAVE | E20: =PRODUCT(B20*C20) -> 0 | F20: =PRODUCT(E20*18)/118 -> 0 | G20: =PRODUCT(B20*D20) -> 0 | H20: =SUM(F20:G20) -> 0
A21: OTHER | E21: =PRODUCT(B21*C21) -> 0 | F21: =PRODUCT(E21*18)/118 -> 0 | G21: =PRODUCT(B21*D21) -> 0 | H21: =SUM(F21:G21) -> 0
A22: OTHER | E22: =PRODUCT(B22*C22) -> 0 | F22: =PRODUCT(E22*18)/118 -> 0 | G22: =PRODUCT(B22*D22) -> 0 | H22: =SUM(F22:G22) -> 0
A23: OTHER | E23: =PRODUCT(B23*C23) -> 0 | F23: =PRODUCT(E23*18)/118 -> 0 | G23: =PRODUCT(B23*D23) -> 0 | H23: =SUM(F23:G23) -> 0
A24: OTHER | E24: =PRODUCT(B24*C24) -> 0 | F24: =PRODUCT(E24*18)/118 -> 0 | G24: =PRODUCT(B24*D24) -> 0 | H24: =SUM(F24:G24) -> 0
A25: OTHER | E25: =PRODUCT(B25*C25) -> 0 | F25: =PRODUCT(E25*18)/118 -> 0 | G25: =PRODUCT(B25*D25) -> 0 | H25: =SUM(F25:G25) -> 0
A26: OTHER | E26: =PRODUCT(B26*C26) -> 0 | F26: =PRODUCT(E26*18)/118 -> 0 | G26: =PRODUCT(B26*D26) -> 0 | H26: =SUM(F26:G26) -> 0
A27: OTHER | E27: =PRODUCT(B27*C27) -> 0 | F27: =PRODUCT(E27*18)/118 -> 0 | G27: =PRODUCT(B27*D27) -> 0 | H27: =SUM(F27:G27) -> 0
A28: OTHER | E28: =PRODUCT(B28*C28) -> 0 | F28: =PRODUCT(E28*18)/118 -> 0 | G28: =PRODUCT(B28*D28) -> 0 | H28: =SUM(F28:G28) -> 0
A29: TOTALY | E29: =SUM(E6:E28) -> 0 | F29: =SUM(F6:F28) -> 0 | G29: =SUM(G6:G28) -> 0 | H29: =SUM(F29:G29) -> 0
A30: SUMMARY | C30: RWF | E30: NAME | G30: Phone | H30: RWF
A31: TOTAL RWF PAID ON MOMO PAY
A32: TOTAL RWF PAID ON CASH
A33: AMOUNT NOT INVOICED
A34: TOTAL RWF DEPPOSITED ON BANK
A35: MEMBERSHIP FEES REGISTRETION
A36: MEMBERSHIP FEES CONTRIBUTION
A37: TOTAL INCOME | C37: 0
A38: TIMBER SUMMARY
B40: TIMBER TYPE | E40: NUMBER OF QUANTITY
B41: INTURUSU | E41: =SUM(B9:B12) -> 0
B42: PINUS | E42: =SUM(B6:B8) -> 0
B43: PALNCHE | E43: =SUM(B13:B14) -> 0
B44: IBIPANDE | E44: =SUM(B17:B18) -> 0
B45: UMUSAVE | E45: =SUM(B19:B20) -> 0
B46: OTHER | E46: =B21 -> 0
B47: OTHER | E47: =B22 -> 0
B48: OTHER | E48: =B23 -> 0
B49: OTHER | E49: =B24 -> 0
B50: OTHER | E50: =B25 -> 0
B51: OTHER | E51: =B26 -> 0
B52: OTHER | E52: =B27 -> 0
B53: OTHER | E53: =B28 -> 0
B54: TOTAL TIMBER | E54: =SUM(E41:H53) -> 0

Sheet NYANZA
A1: QUANTITY REPORT
A3: MONTHS REPORT OF AUGUST 2025
A5: NAME OF TIMBER | B5: No OF TIMBER | C5: PRICE OF TIMBER | E5: TOTAL COST | F5: TVA | G5: MSF | H5: TVA+MSF
A6: PINUS NINI | E6: =PRODUCT(B6*C6) -> 0 | F6: =PRODUCT(E6*18)/118 -> 0 | G6: =PRODUCT(B6*50) -> 0 | H6: =SUM(F6:G6) -> 0
A7: PINUS NTOYA | E7: =PRODUCT(B7*C7) -> 0 | F7: =PRODUCT(E7*18)/118 -> 0 | G7: =PRODUCT(B7*50) -> 0 | H7: =SUM(F7:G7) -> 0
A8: PINUS | E8: =PRODUCT(B8*C8) -> 0 | F8: =PRODUCT(E8*18)/118 -> 0 | G8: =PRODUCT(B8*50) -> 0 | H8: =SUM(F8:G8) -> 0
A9: MADIRIYE NINI | E9: =PRODUCT(B9*C9) -> 0 | F9: =PRODUCT(E9*18)/118 -> 0 | G9: =PRODUCT(B9*30) -> 0 | H9: =SUM(F9:G9) -> 0
A10: MADIRIYE NTOYA | E10: =PRODUCT(B10*C10) -> 0 | F10: =PRODUCT(E10*18)/118 -> 0 | G10: =PRODUCT(B10*30) -> 0 | H10: =SUM(F10:G10) -> 0
A11: MADRIEN | E11: =PRODUCT(B11*C11) -> 0 | F11: =PRODUCT(E11*18)/118 -> 0 | G11: =PRODUCT(B11*30) -> 0 | H11: =SUM(F11:G11) -> 0
A12: MADRIEN | E12: =PRODUCT(B12*C12) -> 0 | F12: =PRODUCT(E12*18)/118 -> 0 | G12: =PRODUCT(B12*30) -> 0 | H12: =SUM(F12:G12) -> 0
A13: PLANCHE | E13: =PRODUCT(B13*C13) -> 0 | F13: =PRODUCT(E13*18)/118 -> 0 | G13: =PRODUCT(B13*20) -> 0 | H13: =SUM(F13:G13) -> 0
A14: PLANCHE | E14: =PRODUCT(B14*C14) -> 0 | F14: =PRODUCT(E14*18)/118 -> 0 | G14: =PRODUCT(B14*20) -> 0 | H14: =SUM(F14:G14) -> 0
A15: Other Timber for Difference Price
A16: NAME OF TIMBER | B16: No OF TIMBER | C16: P/U | D16: MSF | E16: TOTAL COST | F16: VAT | G16: MSF | H16: VTA+MST
A17: IBIPANDE | E17: =PRODUCT(B17*C17) -> 0 | F17: =PRODUCT(E17*18)/118 -> 0 | G17: =PRODUCT(B17*D17) -> 0 | H17: =SUM(F17:G17) -> 0
A18: IBIPANDE | E18: =PRODUCT(B18*C18) -> 0 | F18: =PRODUCT(E18*18)/118 -> 0 | G18: =PRODUCT(B18*D18) -> 0 | H18: =SUM(F18:G18) -> 0
A19: UMUSAVE | E19: =PRODUCT(B19*C19) -> 0 | F19: =PRODUCT(E19*18)/118 -> 0 | G19: =PRODUCT(B19*D19) -> 0 | H19: =SUM(F19:G19) -> 0
A20: UMUSAVE | E20: =PRODUCT(B20*C20) -> 0 | F20: =PRODUCT(E20*18)/118 -> 0 | G20: =PRODUCT(B20*D20) -> 0 | H20: =SUM(F20:G20) -> 0
A21: OTHER | E21: =PRODUCT(B21*C21) -> 0 | F21: =PRODUCT(E21*18)/118 -> 0 | G21: =PRODUCT(B21*D21) -> 0 | H21: =SUM(F21:G21) -> 0
A22: OTHER | E22: =PRODUCT(B22*C22) -> 0 | F22: =PRODUCT(E22*18)/118 -> 0 | G22: =PRODUCT(B22*D22) -> 0 | H22: =SUM(F22:G22) -> 0
A23: OTHER | E23: =PRODUCT(B23*C23) -> 0 | F23: =PRODUCT(E23*18)/118 -> 0 | G23: =PRODUCT(B23*D23) -> 0 | H23: =SUM(F23:G23) -> 0
A24: OTHER | E24: =PRODUCT(B24*C24) -> 0 | F24: =PRODUCT(E24*18)/118 -> 0 | G24: =PRODUCT(B24*D24) -> 0 | H24: =SUM(F24:G24) -> 0
A25: OTHER | E25: =PRODUCT(B25*C25) -> 0 | F25: =PRODUCT(E25*18)/118 -> 0 | G25: =PRODUCT(B25*D25) -> 0 | H25: =SUM(F25:G25) -> 0
A26: OTHER | E26: =PRODUCT(B26*C26) -> 0 | F26: =PRODUCT(E26*18)/118 -> 0 | G26: =PRODUCT(B26*D26) -> 0 | H26: =SUM(F26:G26) -> 0
A27: OTHER | E27: =PRODUCT(B27*C27) -> 0 | F27: =PRODUCT(E27*18)/118 -> 0 | G27: =PRODUCT(B27*D27) -> 0 | H27: =SUM(F27:G27) -> 0
A28: OTHER | E28: =PRODUCT(B28*C28) -> 0 | F28: =PRODUCT(E28*18)/118 -> 0 | G28: =PRODUCT(B28*D28) -> 0 | H28: =SUM(F28:G28) -> 0
A29: TOTALY | E29: =SUM(E6:E28) -> 0 | F29: =SUM(F6:F28) -> 0 | G29: =SUM(G6:G28) -> 0 | H29: =SUM(F29:G29) -> 0
A30: SUMMARY | C30: RWF | E30: NAME | G30: Phone | H30: RWF
A31: TOTAL RWF PAID ON MOMO PAY
A32: TOTAL RWF PAID ON CASH
A33: AMOUNT NOT INVOICED
A34: TOTAL RWF DEPPOSITED ON BANK
A35: MEMBERSHIP FEES REGISTRETION
A36: MEMBERSHIP FEES CONTRIBUTION
A37: TOTAL INCOME | C37: 0
A38: TIMBER SUMMARY
B40: TIMBER TYPE | E40: NUMBER OF QUANTITY
B41: INTURUSU | E41: =SUM(B9:B12) -> 0
B42: PINUS | E42: =SUM(B6:B8) -> 0
B43: PALNCHE | E43: =SUM(B13:B14) -> 0
B44: IBIPANDE | E44: =SUM(B17:B18) -> 0
B45: UMUSAVE | E45: =SUM(B19:B20) -> 0
B46: OTHER | E46: =B21 -> 0
B47: OTHER | E47: =B22 -> 0
B48: OTHER | E48: =B23 -> 0
B49: OTHER | E49: =B24 -> 0
B50: OTHER | E50: =B25 -> 0
B51: OTHER | E51: =B26 -> 0
B52: OTHER | E52: =B27 -> 0
B53: OTHER | E53: =B28 -> 0
B54: TOTAL TIMBER | E54: =SUM(E41:H53) -> 0

Sheet GATSIBO
A1: QUANTITY REPORT
A3: MONTHS REPORT OF AUGUST 2025
A5: NAME OF TIMBER | B5: No OF TIMBER | C5: PRICE OF TIMBER | E5: TOTAL COST | F5: TVA | G5: MSF | H5: TVA+MSF
A6: PINUS NINI | E6: 0 | F6: 0 | G6: 0 | H6: 0
A7: PINUS NTOYA | E7: 0 | F7: 0 | G7: 0 | H7: 0
A8: PINUS | E8: 0 | F8: 0 | G8: 0 | H8: 0
A9: MADIRIYE NINI | E9: 0 | F9: 0 | G9: 0 | H9: 0
A10: MADIRIYE NTOYA | E10: 0 | F10: 0 | G10: 0 | H10: 0
A11: MADRIEN | E11: 0 | F11: 0 | G11: 0 | H11: 0
A12: MADRIEN | E12: 0 | F12: 0 | G12: 0 | H12: 0
A13: PLANCHE | E13: 0 | F13: 0 | G13: 0 | H13: 0
A14: PLANCHE | E14: 0 | F14: 0 | G14: 0 | H14: 0
A15: Other Timber for Difference Price
A16: NAME OF TIMBER | B16: No OF TIMBER | C16: P/U | D16: MSF | E16: TOTAL COST | F16: VAT | G16: MSF | H16: VTA+MST
A17: IBIPANDE | E17: 0 | F17: 0 | G17: 0 | H17: 0
A18: IBIPANDE | E18: 0 | F18: 0 | G18: 0 | H18: 0
A19: UMUSAVE | E19: 0 | F19: 0 | G19: 0 | H19: 0
A20: UMUSAVE | E20: 0 | F20: 0 | G20: 0 | H20: 0
A21: OTHER | E21: 0 | F21: 0 | G21: 0 | H21: 0
A22: OTHER | E22: 0 | F22: 0 | G22: 0 | H22: 0
A23: OTHER | E23: 0 | F23: 0 | G23: 0 | H23: 0
A24: OTHER | E24: 0 | F24: 0 | G24: 0 | H24: 0
A25: OTHER | E25: 0 | F25: 0 | G25: 0 | H25: 0
A26: OTHER | E26: 0 | F26: 0 | G26: 0 | H26: 0
A27: OTHER | E27: 0 | F27: 0 | G27: 0 | H27: 0
A28: OTHER | E28: 0 | F28: 0 | G28: 0 | H28: 0
A29: TOTALY | E29: 0 | F29: 0 | G29: 0 | H29: 0
A30: SUMMARY | C30: RWF | E30: NAME | G30: Phone | H30: RWF
A31: TOTAL RWF PAID ON MOMO PAY
A32: TOTAL RWF PAID ON CASH
A33: AMOUNT NOT INVOICED
A34: TOTAL RWF DEPPOSITED ON BANK
A35: MEMBERSHIP FEES REGISTRETION
A36: MEMBERSHIP FEES CONTRIBUTION
A37: TOTAL INCOME | C37: 0
A38: TIMBER SUMMARY
B40: TIMBER TYPE | E40: NUMBER OF QUANTITY
B41: INTURUSU | E41: =SUM(B9:B12) -> 0
B42: PINUS | E42: =SUM(B6:B8) -> 0
B43: PALNCHE | E43: =SUM(B13:B14) -> 0
B44: IBIPANDE | E44: =SUM(B17:B18) -> 0
B45: UMUSAVE | E45: =SUM(B19:B20) -> 0
B46: OTHER | E46: =B21 -> 0
B47: OTHER | E47: =B22 -> 0
B48: OTHER | E48: =B23 -> 0
B49: OTHER | E49: =B24 -> 0
B50: OTHER | E50: =B25 -> 0
B51: OTHER | E51: =B26 -> 0
B52: OTHER | E52: =B27 -> 0
B53: OTHER | E53: =B28 -> 0
B54: TOTAL TIMBER | E54: =SUM(E41:H53) -> 0

Sheet ALL TIMBER SUMMARY
A1: TIMBER SUMMARY
A3: TIMBER TYPE | D3: NUMBER OF QUANTITY
A4: INTURUSU | D4: =NYANZA!E41+KIREHE!E41+NYAGATARE!E41+KAYONZA!E41+MUSANZE!E41+MUSANZE!E41+RUBAVU!E41+KARONGI!E49+NYAMASHEKE!E49+RUSIZI!E49+HUYE!E49+RUHANGO!E49+MUHANGA!E49+BUGESERA!E41+RWAMAGANA!E41+NYARUGENGE!E41+BISHENYI!E41+GAHANGA!E41+KIMIRONKO!E49+GISOZI!E49+GATSIBO!E41 -> 47091
A5: PINUS | D5: =NYANZA!E42+KIREHE!E42+NYAGATARE!E42+KAYONZA!E42+MUSANZE!E42+MUSANZE!E42+RUBAVU!E42+KARONGI!E50+NYAMASHEKE!E50+RUSIZI!E50+HUYE!E50+RUHANGO!E50+MUHANGA!E50+BUGESERA!E42+RWAMAGANA!E42+NYARUGENGE!E42+BISHENYI!E42+GAHANGA!E42+KIMIRONKO!E50+GISOZI!E50+GATSIBO!E42 -> 440
A6: PLANCHE | D6: =NYANZA!E43+KIREHE!E43+NYAGATARE!E43+KAYONZA!E43+MUSANZE!E43+MUSANZE!E43+RUBAVU!E43+KARONGI!E51+NYAMASHEKE!E51+RUSIZI!E51+HUYE!E51+RUHANGO!E51+MUHANGA!E51+BUGESERA!E43+RWAMAGANA!E43+NYARUGENGE!E43+BISHENYI!E43+GAHANGA!E43+KIMIRONKO!E51+GISOZI!E51+GATSIBO!E43 -> 5532
A7: IBIPANDE | D7: =NYANZA!E44+KIREHE!E44+NYAGATARE!E44+KAYONZA!E44+MUSANZE!E44+MUSANZE!E44+RUBAVU!E44+KARONGI!E52+NYAMASHEKE!E52+RUSIZI!E52+HUYE!E52+RUHANGO!E52+MUHANGA!E52+BUGESERA!E44+RWAMAGANA!E44+NYARUGENGE!E44+BISHENYI!E44+GAHANGA!E44+KIMIRONKO!E52+GISOZI!E52+GATSIBO!E44 -> 457
A8: UMUSAVE | D8: =NYANZA!E45+KIREHE!E45+NYAGATARE!E45+KAYONZA!E45+MUSANZE!E45+MUSANZE!E45+RUBAVU!E45+KARONGI!E53+NYAMASHEKE!E53+RUSIZI!E53+HUYE!E53+RUHANGO!E53+MUHANGA!E53+BUGESERA!E45+RWAMAGANA!E45+NYARUGENGE!E45+BISHENYI!E45+GAHANGA!E45+KIMIRONKO!E53+GISOZI!E53+GATSIBO!E45 -> 1
A9: OTHER | D9: =NYANZA!E46+KIREHE!E46+NYAGATARE!E46+KAYONZA!E46+MUSANZE!E46+MUSANZE!E46+RUBAVU!E46+KARONGI!E54+NYAMASHEKE!E54+RUSIZI!E54+HUYE!E54+RUHANGO!E54+MUHANGA!E54+BUGESERA!E46+RWAMAGANA!E46+NYARUGENGE!E46+BISHENYI!E46+GAHANGA!E46+KIMIRONKO!E54+GISOZI!E54+GATSIBO!E46 -> 0
A10: OTHER | D10: =NYANZA!E47+KIREHE!E47+NYAGATARE!E47+KAYONZA!E47+MUSANZE!E47+MUSANZE!E47+RUBAVU!E47+KARONGI!E55+NYAMASHEKE!E55+RUSIZI!E55+HUYE!E55+RUHANGO!E55+MUHANGA!E55+BUGESERA!E47+RWAMAGANA!E47+NYARUGENGE!E47+BISHENYI!E47+GAHANGA!E47+KIMIRONKO!E55+GISOZI!E55+GATSIBO!E47 -> 0
A11: OTHER | D11: =NYANZA!E48+KIREHE!E48+NYAGATARE!E48+KAYONZA!E48+MUSANZE!E48+MUSANZE!E48+RUBAVU!E48+KARONGI!E56+NYAMASHEKE!E56+RUSIZI!E56+HUYE!E56+RUHANGO!E56+MUHANGA!E56+BUGESERA!E48+RWAMAGANA!E48+NYARUGENGE!E48+BISHENYI!E48+GAHANGA!E48+KIMIRONKO!E56+GISOZI!E56+GATSIBO!E48 -> 0
A12: OTHER | D12: =NYANZA!E49+KIREHE!E49+NYAGATARE!E49+KAYONZA!E49+MUSANZE!E49+MUSANZE!E49+RUBAVU!E49+KARONGI!E57+NYAMASHEKE!E57+RUSIZI!E57+HUYE!E57+RUHANGO!E57+MUHANGA!E57+BUGESERA!E49+RWAMAGANA!E49+NYARUGENGE!E49+BISHENYI!E49+GAHANGA!E49+KIMIRONKO!E57+GISOZI!E57+GATSIBO!E49 -> 0
A13: OTHER | D13: =NYANZA!E50+KIREHE!E50+NYAGATARE!E50+KAYONZA!E50+MUSANZE!E50+MUSANZE!E50+RUBAVU!E50+KARONGI!E58+NYAMASHEKE!E58+RUSIZI!E58+HUYE!E58+RUHANGO!E58+MUHANGA!E58+BUGESERA!E50+RWAMAGANA!E50+NYARUGENGE!E50+BISHENYI!E50+GAHANGA!E50+KIMIRONKO!E58+GISOZI!E58+GATSIBO!E50 -> 0
A14: OTHER | D14: =NYANZA!E51+KIREHE!E51+NYAGATARE!E51+KAYONZA!E51+MUSANZE!E51+MUSANZE!E51+RUBAVU!E51+KARONGI!E59+NYAMASHEKE!E59+RUSIZI!E59+HUYE!E59+RUHANGO!E59+MUHANGA!E59+BUGESERA!E51+RWAMAGANA!E51+NYARUGENGE!E51+BISHENYI!E51+GAHANGA!E51+KIMIRONKO!E59+GISOZI!E59+GATSIBO!E51 -> 0
A15: OTHER | D15: =NYANZA!E52+KIREHE!E52+NYAGATARE!E52+KAYONZA!E52+MUSANZE!E52+MUSANZE!E52+RUBAVU!E52+KARONGI!E60+NYAMASHEKE!E60+RUSIZI!E60+HUYE!E60+RUHANGO!E60+MUHANGA!E60+BUGESERA!E52+RWAMAGANA!E52+NYARUGENGE!E52+BISHENYI!E52+GAHANGA!E52+KIMIRONKO!E60+GISOZI!E60+GATSIBO!E52 -> 0
A16: OTHER | D16: =NYANZA!E53+KIREHE!E53+NYAGATARE!E53+KAYONZA!E53+MUSANZE!E53+MUSANZE!E53+RUBAVU!E53+KARONGI!E61+NYAMASHEKE!E61+RUSIZI!E61+HUYE!E61+RUHANGO!E61+MUHANGA!E61+BUGESERA!E53+RWAMAGANA!E53+NYARUGENGE!E53+BISHENYI!E53+GAHANGA!E53+KIMIRONKO!E61+GISOZI!E61+GATSIBO!E53 -> 0
A17: TOTAL TIMBER | D17: =SUM(D4:D16) -> 53521
