Workbook

Sheet FINACHIAL REPORT
A1: RWVCA REPORT DATE ….........
A2: RWANDA WOOD VALUE CHAIN ASSOCIATION
A4: ICPCs NAME | B4: TVA IN | C4: MSF IN | D4: MS REGIS | E4: MS CONTR | F4: TVA+MSF | G4: FR NOT INVOICED | H4: MOMO | I4: PAID ON BANK | J4: CASH
A5: GISOZI | B5: =GISOZI!F57 -> 1.3337817e+08 | C5: =GISOZI!G57 -> 11062265 | D5: =GISOZI!C63 -> 0 | E5: =GISOZI!C64 -> 0 | F5: =SUM(B5:C5) -> 1.4444043e+08 | G5: =GISOZI!C61 -> 0 | H5: =GISOZI!C59 -> 144418433 | I5: =GISOZI!C62 -> 0 | J5: =GISOZI!C60 -> 0
A6: GAHANGA | B6: =GAHANGA!F37 -> 32429106 | C6: =GAHANGA!G37 -> 2790530 | D6: =GAHANGA!C43 -> 0 | E6: =GAHANGA!C44 -> 0 | F6: =SUM(B6:C6) -> 35219636 | G6: =GAHANGA!C41 -> 0 | H6: =GAHANGA!C39 -> 35219636 | I6: =GAHANGA!C42 -> 0 | J6: =GAHANGA!C40 -> 0
A7: KIMIROMKO | B7: =KIMIRONKO!F37 -> 43961918 | C7: =KIMIRONKO!G37 -> 3989250 | D7: =KIMIRONKO!C43 -> 0 | E7: =KIMIRONKO!C44 -> 0 | F7: =SUM(B7:C7) -> 47951168 | G7: =KIMIRONKO!C41 -> 0 | H7: =KIMIRONKO!C39 -> 0 | I7: =KIMIRONKO!C42 -> 0 | J7: =KIMIRONKO!C40 -> 0
A8: BISHENYI | B8: =BISHENYI!F37 -> 36607739 | C8: =BISHENYI!G37 -> 3043280 | D8: =BISHENYI!C43 -> 0 | E8: =BISHENYI!C44 -> 0 | F8: =SUM(B8:C8) -> 39651019 | G8: =BISHENYI!C41 -> 0 | H8: =BISHENYI!C39 -> 39653064 | I8: =BISHENYI!C42 -> 0 | J8: =BISHENYI!C40 -> 0
A9: RWAMAGANA | B9: =RWAMAGANA!F37 -> 13006128 | C9: =RWAMAGANA!G37 -> 1486781 | D9: =RWAMAGANA!C43 -> 0 | E9: =RWAMAGANA!C44 -> 800000 | F9: =SUM(B9:C9) -> 14492909 | G9: =RWAMAGANA!C41 -> 0 | H9: =RWAMAGANA!C39 -> 14492909 | I9: =RWAMAGANA!C42 -> 0 | J9: =RWAMAGANA!C40 -> 0
A10: BUGESERA | B10: =BUGESERA!F37 -> 44061174 | C10: =BUGESERA!G37 -> 4067790 | D10: =BUGESERA!C43 -> 0 | E10: =BUGESERA!C44 -> 0 | F10: =SUM(B10:C10) -> 48128964 | G10: =BUGESERA!C41 -> 0 | H10: =BUGESERA!C39 -> 45442312 | I10: =BUGESERA!C42 -> 0 | J10: =BUGESERA!C40 -> 2686652
A11: MUHANGA | B11: =MUHANGA!F37 -> 16087243 | C11: =MUHANGA!G37 -> 1381030 | D11: =MUHANGA!C43 -> 0 | E11: =MUHANGA!C44 -> 0 | F11: =SUM(B11:C11) -> 17468273 | G11: =MUHANGA!C41 -> 0 | H11: =MUHANGA!C39 -> 0 | I11: =MUHANGA!C42 -> 0 | J11: =MUHANGA!C40 -> 0
A12: RUHANGO | B12: =RUHANGO!F37 -> 1849728.8 | C12: =RUHANGO!G37 -> 594800 | D12: =RUHANGO!C43 -> 0 | E12: =RUHANGO!C44 -> 0 | F12: =SUM(B12:C12) -> 2444528.8 | G12: =RUHANGO!C41 -> 0 | H12: =RUHANGO!C39 -> 2444529 | I12: =RUHANGO!C42 -> 0 | J12: =RUHANGO!C40 -> 0
A13: HUYE | B13: =HUYE!F37 -> 14103728 | C13: =HUYE!G37 -> 1453620 | D13: =HUYE!C43 -> 0 | E13: =HUYE!C44 -> 0 | F13: =SUM(B13:C13) -> 15557348 | G13: =HUYE!C41 -> 0 | H13: =HUYE!C39 -> 0 | I13: =HUYE!C42 -> 0 | J13: =HUYE!C40 -> 0
A14: RUSIZI | B14: =RUSIZI!F37 -> 4761958.9 | C14: =RUSIZI!G37 -> 1040410 | D14: =RUSIZI!C43 -> 0 | E14: =RUSIZI!C44 -> 0 | F14: =SUM(B14:C14) -> 5802368.9 | G14: =RUSIZI!C41 -> 0 | H14: =RUSIZI!C39 -> 5802369 | I14: =RUSIZI!C42 -> 0 | J14: =RUSIZI!C40 -> 0
A15: NYAMAGABE | B15: =NYAMAGABE!F37 -> 0 | C15: =NYAMAGABE!G37 -> 0 | D15: =NYAMAGABE!C43 -> 0 | E15: =NYAMAGABE!C44 -> 0 | F15: =SUM(B15:C15) -> 0 | G15: =NYAMAGABE!C41 -> 0 | H15: =NYAMAGABE!C39 -> 316500 | I15: =NYAMAGABE!C42 -> 0 | J15: =NYAMAGABE!C40 -> 0
A16: KARONGI | B16: =KARONGI!F37 -> 5212535.8 | C16: =KARONGI!G37 -> 884978 | D16: =KARONGI!C43 -> 0 | E16: =KARONGI!C44 -> 0 | F16: =SUM(B16:C16) -> 6097513.8 | G16: =KARONGI!C41 -> 0 | H16: =KARONGI!C39 -> 6097514 | I16: =KARONGI!C42 -> 645430 | J16: =KARONGI!C40 -> 0
A17: RUBAVU | B17: =RUBAVU!F37 -> 13910148 | C17: =RUBAVU!G37 -> 1437418 | D17: =RUBAVU!C43 -> 0 | E17: =RUBAVU!C44 -> 0 | F17: =SUM(B17:C17) -> 15347566 | G17: =RUBAVU!C41 -> 0 | H17: =RUBAVU!C39 -> 14347566 | I17: =RUBAVU!C42 -> 1000000 | J17: =RUBAVU!C40 -> 0
A18: MUSANZE | B18: =MUSANZE!F37 -> 10958316 | C18: =MUSANZE!G37 -> 1300046 | D18: =MUSANZE!C43 -> 0 | E18: =MUSANZE!C44 -> 0 | F18: =SUM(B18:C18) -> 12258362 | G18: =MUSANZE!C41 -> 0 | H18: =MUSANZE!C39 -> 8700743 | I18: =MUSANZE!C42 -> 0 | J18: =MUSANZE!C40 -> 3557619
A19: KAYONZA | B19: =KAYONZA!F37 -> 7891110 | C19: =KAYONZA!G37 -> 721970 | D19: =KAYONZA!C43 -> 0 | E19: =KAYONZA!C44 -> 0 | F19: =SUM(B19:C19) -> 8613080 | G19: =KAYONZA!C41 -> 0 | H19: =KAYONZA!C39 -> 8926280 | I19: =KAYONZA!C42 -> 0 | J19: =KAYONZA!C40 -> 0
A20: NYAGATARE | B20: =NYAGATARE!F37 -> 5024402.2 | C20: =NYAGATARE!G37 -> 1076750 | D20: =NYAGATARE!C43 -> 0 | E20: =NYAGATARE!C44 -> 0 | F20: =SUM(B20:C20) -> 6101152.2 | G20: =NYAGATARE!C41 -> 0 | H20: =NYAGATARE!C39 -> 0 | I20: =NYAGATARE!C42 -> 0 | J20: =NYAGATARE!C40 -> 0
A21: KIREHE | B21: =KIREHE!F37 -> 5213268.8 | C21: =KIREHE!G37 -> 1208916 | D21: =KIREHE!C43 -> 0 | E21: =KIREHE!C44 -> 0 | F21: =SUM(B21:C21) -> 6422184.8 | G21: =KIREHE!C41 -> 0 | H21: =KIREHE!C39 -> 6422184.8 | I21: =KIREHE!C42 -> 0 | J21: =KIREHE!C40 -> 0
A22: NYANZA | B22: =NYANZA!F37 -> 1970847.5 | C22: =NYANZA!G37 -> 616200 | D22: =NYANZA!C43 -> 0 | E22: =NYANZA!C44 -> 0 | F22: =SUM(B22:C22) -> 2587047.5 | G22: =NYANZA!C41 -> 0 | H22: =NYANZA!C39 -> 2587047 | I22: =NYANZA!C42 -> 0 | J22: =NYANZA!C40 -> 0
A23: NYARUGENGE | B23: =NYARUGENGE!F37 -> 16261470 | C23: =NYARUGENGE!G37 -> 1488400 | D23: =NYARUGENGE!C43 -> 0 | E23: =NYARUGENGE!C44 -> 0 | F23: =SUM(B23:C23) -> 17749870 | G23: =NYARUGENGE!C41 -> 0 | H23: =NYARUGENGE!C39 -> 17749870 | I23: =NYARUGENGE!C42 -> 0 | J23: =NYARUGENGE!C40 -> 0
A24: GATSIBO | B24: =GATSIBO!F37 -> 2731644.9 | C24: =GATSIBO!G37 -> 657787 | D24: =GATSIBO!C43 -> 0 | E24: =GATSIBO!C44 -> 0 | F24: =SUM(B24:C24) -> 3389431.9 | G24: =GATSIBO!C41 -> 0 | H24: =GATSIBO!C39 -> 3389432 | I24: =GATSIBO!C42 -> 0 | J24: =GATSIBO!C40 -> 0
A25: GASHYUSHYA | B25: =GASHYUSHYA!F37 -> 9455958.8 | C25: =GASHYUSHYA!G37 -> 936870 | D25: =GASHYUSHYA!C43 -> 0 | E25: =GASHYUSHYA!C44 -> 0 | F25: =SUM(B25:C25) -> 10392829 | G25: =GASHYUSHYA!C41 -> 0 | H25: =GASHYUSHYA!C39 -> 10582828 | I25: =GASHYUSHYA!C42 -> 0 | J25: =GASHYUSHYA!C40 -> 0
A26: RUTSIRO | B26: =RUTSIRO!F37 -> 0 | C26: =RUTSIRO!G37 -> 0 | D26: =RUTSIRO!C43 -> 0 | E26: =RUTSIRO!C44 -> 0 | F26: =SUM(B26:C26) -> 0 | G26: =RUTSIRO!C41 -> 0 | H26: =RUTSIRO!C39 -> 0 | I26: =RUTSIRO!C42 -> 0 | J26: =RUTSIRO!C40 -> 0
A27: NGORORERO | B27: =NGORORERO!F37 -> 98420.339 | C27: =NGORORERO!G37 -> 13100 | D27: =NGORORERO!C43 -> 0 | E27: =NGORORERO!C44 -> 0 | F27: =SUM(B27:C27) -> 111520.34 | G27: =NGORORERO!C41 -> 0 | H27: =NGORORERO!C39 -> 0 | I27: =NGORORERO!C42 -> 0 | J27: =NGORORERO!C40 -> 0
A28: NYAMASHEKE | B28: =NYAMASHEKE!F37 -> 0 | C28: =NYAMASHEKE!G37 -> 0 | D28: =NYAMASHEKE!C43 -> 0 | E28: =NYAMASHEKE!C44 -> 0 | F28: =SUM(B28:C28) -> 0 | G28: =NYAMASHEKE!C41 -> 0 | H28: =NYAMASHEKE!C39 -> 0 | I28: =NYAMASHEKE!C42 -> 0 | J28: =NYAMASHEKE!C40 -> 0
B29: =SUM(B5:B28) -> 4.1897501e+08 | C29: =SUM(C5:C28) -> 41252191 | D29: =SUM(D5:D28) -> 0 | E29: =SUM(E5:E28) -> 800000 | F29: =SUM(F5:F28) -> 4.602272e+08 | G29: =SUM(G5:G28) -> 0 | H29: =SUM(H5:H28) -> 3.6659322e+08 | I29: =SUM(I5:I28) -> 1645430 | J29: =SUM(J5:J28) -> 6244271
E30: REPORT DESCRIPTION
A31: REPORT SUMMARY
A32: VAT+MSF | C32: =SUM(B29+C29) -> 4.602272e+08
A33: VAT+MSF+FR NOT INVOCED | C33: =SUM(F29,G29) -> 4.602272e+08
A34: MOMO+CASH+BANK+FR NOT INVOICED | C34: =SUM(H29,J29,I29+G29) -> 3.7448292e+08
A35: MS REGIST+MS CONTRIB | C35: =SUM(D29:E29) -> 800000
A36: TOTAL INCOME INVOICED+MSF&MS REGIST | C36: =SUM(H29+I29+J29+C35) -> 3.7528292e+08 | E36: COORDINATOR NAME: Chantal NIYIGENA
A37: TOTAL INCOME | C37: =NYANZA!C45+KIREHE!C45+NYAGATARE!C45+KAYONZA!C45+MUSANZE!C45+MUSANZE!C45+RUBAVU!C45+KARONGI!C45+NYAMAGABE!C45+RUSIZI!C45+HUYE!C45+RUHANGO!C45+MUHANGA!C45+BUGESERA!C45+RWAMAGANA!C45+NYARUGENGE!C45+BISHENYI!C45+GAHANGA!C45+KIMIRONKO!C45+GISOZI!C65+GATSIBO!C45+GASHYUSHYA!C45 -> 3.8754128e+08
A38: RWANDA WOOD VALUE CHAIN ASSOCIATION

Sheet GISOZI
A1: QUANTITY REPORT
A3: MONTHLY REPORT OF JUNE 2026
A5: NAME OF TIMBER | B5: No OF TIMBER | C5: PRICE OF TIMBER | E5: TOTAL COST | F5: TVA | G5: MSF | H5: TVA+MSF
A6: PINUS NINI | B6: 500 | C6: 12000 | E6: =PRODUCT(B6*C6) -> 6000000 | F6: =PRODUCT(E6*18)/118 -> 915254.24 | G6: =PRODUCT(B6*50) -> 25000 | H6: =SUM(F6:G6) -> 940254.24
A7: PINUS | B7: 614 | C7: 10620 | E7: =PRODUCT(B7*C7) -> 6520680 | F7: =PRODUCT(E7*18)/118 -> 994680 | G7: =PRODUCT(B7*50) -> 30700 | H7: =SUM(F7:G7) -> 1025380
A8: PINUS NTOYA | B8: 14938 | C8: 8000 | E8: =PRODUCT(B8*C8) -> 119504000 | F8: =PRODUCT(E8*18)/118 -> 18229424 | G8: =PRODUCT(B8*50) -> 746900 | H8: =SUM(F8:G8) -> 18976324
A9: MADIRIYE NINI | B9: 5038 | C9: 3776 | E9: =PRODUCT(B9*C9) -> 19023488 | F9: =PRODUCT(E9*18)/118 -> 2901888 | G9: =PRODUCT(B9*30) -> 151140 | H9: =SUM(F9:G9) -> 3053028
A10: MADIRIYE NTOYA | B10: 62831 | C10: 2000 | E10: =PRODUCT(B10*C10) -> 125662000 | F10: =PRODUCT(E10*18)/118 -> 19168780 | G10: =PRODUCT(B10*30) -> 1884930 | H10: =SUM(F10:G10) -> 21053710
A11: MADRIEN | B11: 250499 | C11: 2124 | E11: =PRODUCT(B11*C11) -> 532059876 | F11: =PRODUCT(E11*18)/118 -> 81161676 | G11: =PRODUCT(B11*30) -> 7514970 | H11: =SUM(F11:G11) -> 88676646
A12: MADRIEN | B12: 3720 | C12: 3000 | E12: =PRODUCT(B12*C12) -> 11160000 | F12: =PRODUCT(E12*18)/118 -> 1702372.9 | G12: =PRODUCT(B12*30) -> 111600 | H12: =SUM(F12:G12) -> 1813972.9
A13: PLANCHE | B13: 7300 | C13: 1357 | E13: =PRODUCT(B13*C13) -> 9906100 | F13: =PRODUCT(E13*18)/118 -> 1511100 | G13: =PRODUCT(B13*20) -> 146000 | H13: =SUM(F13:G13) -> 1657100
A14: MUNYONGORO | B14: 2971 | C14: 3000 | E14: =PRODUCT(B14*C14) -> 8913000 | F14: =PRODUCT(E14*18)/118 -> 1359610.2 | G14: =PRODUCT(B14*20) -> 59420 | H14: =SUM(F14:G14) -> 1419030.2
A15: Other Timber for Difference Price
A16: NAME OF TIMBER | B16: No OF TIMBER | C16: P/U | D16: MSF | E16: TOTAL COST | F16: VAT | G16: MSF | H16: VTA+MST
A17: INTURUSU | B17: 720 | C17: 2600 | D17: 30 | E17: =PRODUCT(B17*C17) -> 1872000 | F17: =PRODUCT(E17*18)/118 -> 285559.32 | G17: =PRODUCT(B17*D17) -> 21600 | H17: =SUM(F17:G17) -> 307159.32
A18: IBIPANDE BYA PINUS | B18: 2007 | C18: 2000 | D18: 25 | E18: =PRODUCT(B18*C18) -> 4014000 | F18: =PRODUCT(E18*18)/118 -> 612305.08 | G18: =PRODUCT(B18*D18) -> 50175 | H18: =SUM(F18:G18) -> 662480.08
A19: PINUS | B19: 1797 | C19: 5000 | D19: 50 | E19: =PRODUCT(B19*C19) -> 8985000 | F19: =PRODUCT(E19*18)/118 -> 1370593.2 | G19: =PRODUCT(B19*D19) -> 89850 | H19: =SUM(F19:G19) -> 1460443.2
A20: IBIPANDE BY'INTURUSU | B20: 840 | C20: 1500 | D20: 20 | E20: =PRODUCT(B20*C20) -> 1260000 | F20: =PRODUCT(E20*18)/118 -> 192203.39 | G20: =PRODUCT(B20*D20) -> 16800 | H20: =SUM(F20:G20) -> 209003.39
A21: SIPURI | B21: 40 | C21: 8000 | D21: 50 | E21: =PRODUCT(B21*C21) -> 320000 | F21: =PRODUCT(E21*18)/118 -> 48813.559 | G21: =PRODUCT(B21*D21) -> 2000 | H21: =SUM(F21:G21) -> 50813.559
A22: MUNYONGORO | E22: =PRODUCT(B22*C22) -> 0 | F22: =PRODUCT(E22*18)/118 -> 0 | G22: =PRODUCT(B22*D22) -> 0 | H22: =SUM(F22:G22) -> 0
A23: PINUS NINI, | E23: =PRODUCT(B23*C23) -> 0 | F23: =PRODUCT(E23*18)/118 -> 0 | G23: =PRODUCT(B23*D23) -> 0 | H23: =SUM(F23:G23) -> 0
A24: PINUS | B24: 1307 | C24: 6000 | D24: 50 | E24: =PRODUCT(B24*C24) -> 7842000 | F24: =PRODUCT(E24*18)/118 -> 1196237.3 | G24: =PRODUCT(B24*D24) -> 65350 | H24: =SUM(F24:G24) -> 1261587.3
A25: MADRIEN | B25: 400 | C25: 2500 | D25: 30 | E25: =PRODUCT(B25*C25) -> 1000000 | F25: =PRODUCT(E25*18)/118 -> 152542.37 | G25: =PRODUCT(B25*D25) -> 12000 | H25: =SUM(F25:G25) -> 164542.37
A26: PINUS NTOYA | B26: 230 | C26: 4000 | D26: 50 | E26: =PRODUCT(B26*C26) -> 920000 | F26: =PRODUCT(E26*18)/118 -> 140338.98 | G26: =PRODUCT(B26*D26) -> 11500 | H26: =SUM(F26:G26) -> 151838.98
A27: PLANCHET ZA PINUS | B27: 300 | C27: 1770 | D27: 20 | E27: =PRODUCT(B27*C27) -> 531000 | F27: =PRODUCT(E27*18)/118 -> 81000 | G27: =PRODUCT(B27*D27) -> 6000 | H27: =SUM(F27:G27) -> 87000
A28: MADRIEN | B28: 450 | C28: 2596 | D28: 30 | E28: =PRODUCT(B28*C28) -> 1168200 | F28: =PRODUCT(E28*18)/118 -> 178200 | G28: =PRODUCT(B28*D28) -> 13500 | H28: =SUM(F28:G28) -> 191700
A29: MADRIEN | B29: 616 | C29: 3500 | D29: 30 | E29: =PRODUCT(B29*C29) -> 2156000 | F29: =PRODUCT(E29*18)/118 -> 328881.36 | G29: =PRODUCT(B29*D29) -> 18480 | H29: =SUM(F29:G29) -> 347361.36
A30: INTURUSU NTOYA | E30: =PRODUCT(B30*C30) -> 0 | F30: =PRODUCT(E30*18)/118 -> 0 | G30: =PRODUCT(B30*D30) -> 0 | H30: =SUM(F30:G30) -> 0
A31: DECHET | B31: 42 | C31: 10000 | E31: =PRODUCT(B31*C31) -> 420000 | F31: =PRODUCT(E31*18)/118 -> 64067.797 | G31: =PRODUCT(B31*D31) -> 0 | H31: =SUM(F31:G31) -> 64067.797
A32: DECHET | B32: 6 | D32: 5000 | E32: =PRODUCT(B32*C32) -> 0 | F32: =PRODUCT(E32*18)/118 -> 0 | G32: =PRODUCT(B32*D32) -> 30000 | H32: =SUM(F32:G32) -> 30000
A33: MUNYONGORO | E33: =PRODUCT(B33*C33) -> 0 | F33: =PRODUCT(E33*18)/118 -> 0 | G33: =PRODUCT(B33*D33) -> 0 | H33: =SUM(F33:G33) -> 0
A34: MUNYONGORO | E34: =PRODUCT(B34*C34) -> 0 | F34: =PRODUCT(E34*18)/118 -> 0 | G34: =PRODUCT(B34*D34) -> 0 | H34: =SUM(F34:G34) -> 0
A35: OTHER | E35: =PRODUCT(B35*C35) -> 0 | F35: =PRODUCT(E35*18)/118 -> 0 | G35: =PRODUCT(B35*D35) -> 0 | H35: =SUM(F35:G35) -> 0
A36: PINUS | B36: 1087 | C36: 4720 | D36: 50 | E36: =PRODUCT(B36*C36) -> 5130640 | F36: =PRODUCT(E36*18)/118 -> 782640 | G36: =PRODUCT(B36*D36) -> 54350 | H36: =SUM(F36:G36) -> 836990
A37: MUNYONGORO | E37: =PRODUCT(B37*C37) -> 0 | F37: =PRODUCT(E37*18)/118 -> 0 | G37: =PRODUCT(B37*D37) -> 0 | H37: =SUM(F37:G37) -> 0
A38: MADRIEN | E38: =PRODUCT(B38*C38) -> 0 | F38: =PRODUCT(E38*18)/118 -> 0 | G38: =PRODUCT(B38*D38) -> 0 | H38: =SUM(F38:G38) -> 0
A39: IBIPANDE BYA PINUS | E39: =PRODUCT(B39*C39) -> 0 | F39: =PRODUCT(E39*18)/118 -> 0 | G39: =PRODUCT(B39*D39) -> 0 | H39: =SUM(F39:G39) -> 0
A40: PINUS | E40: =PRODUCT(B40*C40) -> 0 | F40: =PRODUCT(E40*18)/118 -> 0 | G40: =PRODUCT(B40*D40) -> 0 | H40: =SUM(F40:G40) -> 0
A41: SIPURE | E41: =PRODUCT(B41*C41) -> 0 | F41: =PRODUCT(E41*18)/118 -> 0 | G41: =PRODUCT(B41*D41) -> 0 | H41: =SUM(F41:G41) -> 0
A42: INTURUSU NTOYA | E42: =PRODUCT(B42*C42) -> 0 | F42: =PRODUCT(E42*18)/118 -> 0 | G42: =PRODUCT(B42*D42) -> 0 | H42: =SUM(F42:G42) -> 0
A43: DECHET | E43: =PRODUCT(B43*C43) -> 0 | F43: =PRODUCT(E43*18)/118 -> 0 | G43: =PRODUCT(B43*D43) -> 0 | H43: =SUM(F43:G43) -> 0
A44: DECHET | E44: =PRODUCT(B44*C44) -> 0 | F44: =PRODUCT(E44*18)/118 -> 0 | G44: =PRODUCT(B44*D44) -> 0 | H44: =SUM(F44:G44) -> 0
A45: MUNYONGORO | E45: =PRODUCT(B45*C45) -> 0 | F45: =PRODUCT(E45*18)/118 -> 0 | G45: =PRODUCT(B45*D45) -> 0 | H45: =SUM(F45:G45) -> 0
A46: Madrien zidasanzwe | E46: =PRODUCT(B46*C46) -> 0 | F46: =PRODUCT(E46*18)/118 -> 0 | G46: =PRODUCT(B46*D46) -> 0 | H46: =SUM(F46:G46) -> 0
A47: MADRIEN | E47: =PRODUCT(B47*C47) -> 0 | F47: =PRODUCT(E47*18)/118 -> 0 | G47: =PRODUCT(B47*D47) -> 0 | H47: =SUM(F47:G47) -> 0
A48: SIPURE | E48: =PRODUCT(B48*C48) -> 0 | F48: =PRODUCT(E48*18)/118 -> 0 | G48: =PRODUCT(B48*D48) -> 0 | H48: =SUM(F48:G48) -> 0
... A56: MADRIEN | E56: =PRODUCT(B56*C56) -> 0 | F56: =PRODUCT(E56*18)/118 -> 0 | G56: =PRODUCT(B56*D56) -> 0 | H56: =SUM(F56:G56) -> 0
A57: TOTALY | E57: =SUM(E5:E56) -> 874367984 | F57: =SUM(F5:F56) -> 1.3337817e+08 | G57: =SUM(G5:G56) -> 11062265 | H57: =SUM(F57:G57) -> 1.4444043e+08
A58: SUMMARY | C58: RWF | E58: NAME | G58: Phone | H58: RWF
A59: TOTAL RWF PAID ON MOMO PAY | C59: 144418433
A60: TOTAL RWF PAID ON CASH
A61: AMOUNT NOT INVOICED
A62: TOTAL RWF DEPPOSITED ON BANK
A63: MEMBERSHIP FEES REGISTRETION
A64: MEMBERSHIP FEES CONTRIBUTION
A65: TOTAL INCOME | C65: =SUM(C59+C60+C61+C62+C63+C64) -> 144418433
A66: TIMBER SUMMARY
A68: REPORT SUMMARY | C68: TIMBER TYPE | E68: NUMBER OF QUANTITY
C69: INTURUSU | E69: =SUM(B9:B12) -> 322088
C70: PINUS | E70: =SUM(B6:B8) -> 16052
C71: PALNCHE | E71: =SUM(B13:B14) -> 10271
C72: IBIPANDE | E72: =SUM(B37:B38) -> 0
C73: UMUSAVE | E73: =SUM(B39:B40) -> 0
C74: OTHER | E74: =SUM(B17:B49) -> 9842
C75: OTHER | E75: =B50 -> 0
C76: OTHER | E76: =B51 -> 0
C77: OTHER | E77: =B52 -> 0
C78: OTHER | E78: =B53 -> 0
C79: OTHER | E79: =B54 -> 0
C80: OTHER | E80: =B55 -> 0
C81: OTHER | E81: =B56 -> 0
C82: TOTAL TIMBER | E82: =SUM(E69:H81) -> 358253

Sheet BISHENYI
A1: QUANTITY REPORT
A3: MONTHLY REPORT OF MAY 2026
A5: NAME OF TIMBER | B5: No OF TIMBER | C5: PRICE OF TIMBER | E5: TOTAL COST | F5: TVA | G5: MSF | H5: TVA+MSF
A6: PINUS NINI | B6: 945 | C6: 7670 | E6: =PRODUCT(B6*C6) -> 7248150 | F6: =PRODUCT(E6*18)/118 -> 1105650 | G6: =PRODUCT(B6*50) -> 47250 | H6: =SUM(F6:G6) -> 1152900
A7: PINUS NTOYA | C7: 7670 | E7: =PRODUCT(B7*C7) -> 0 | F7: =PRODUCT(E7*18)/118 -> 0 | G7: =PRODUCT(B7*50) -> 0 | H7: =SUM(F7:G7) -> 0
A8: PINUS | E8: =PRODUCT(B8*C8) -> 0 | F8: =PRODUCT(E8*18)/118 -> 0 | G8: =PRODUCT(B8*50) -> 0 | H8: =SUM(F8:G8) -> 0
A9: MADIRIYE NINI | B9: 185 | C9: 3776 | E9: =PRODUCT(B9*C9) -> 698560 | F9: =PRODUCT(E9*18)/118 -> 106560 | G9: =PRODUCT(B9*30) -> 5550 | H9: =SUM(F9:G9) -> 112110
A10: MADIRIYE NTOYA | B10: 92166 | C10: 2360 | E10: =PRODUCT(B10*C10) -> 217511760 | F10: =PRODUCT(E10*18)/118 -> 33179760 | G10: =PRODUCT(B10*30) -> 2764980 | H10: =SUM(F10:G10) -> 35944740
A11: MADRIEN | E11: =PRODUCT(B11*C11) -> 0 | F11: =PRODUCT(E11*18)/118 -> 0 | G11: =PRODUCT(B11*30) -> 0 | H11: =SUM(F11:G11) -> 0
A12: MADRIEN | E12: =PRODUCT(B12*C12) -> 0 | F12: =PRODUCT(E12*18)/118 -> 0 | G12: =PRODUCT(B12*30) -> 0 | H12: =SUM(F12:G12) -> 0
A13: PLANCHE | B13: 8400 | C13: 1534 | E13: =PRODUCT(B13*C13) -> 12885600 | F13: =PRODUCT(E13*18)/118 -> 1965600 | G13: =PRODUCT(B13*20) -> 168000 | H13: =SUM(F13:G13) -> 2133600
A14: PLANCHE | E14: =PRODUCT(B14*C14) -> 0 | F14: =PRODUCT(E14*18)/118 -> 0 | G14: =PRODUCT(B14*20) -> 0 | H14: =SUM(F14:G14) -> 0
A15: Other Timber for Difference Price
A16: NAME OF TIMBER | B16: No OF TIMBER | C16: P/U | D16: MSF | E16: TOTAL COST | F16: VAT | G16: MSF | H16: VTA+MST
A17: IBIPANDE BYA PINUS | B17: 750 | C17: 2000 | D17: 50 | E17: =PRODUCT(B17*C17) -> 1500000 | F17: =PRODUCT(E17*18)/118 -> 228813.56 | G17: =PRODUCT(B17*D17) -> 37500 | H17: =SUM(F17:G17) -> 266313.56
A18: DECHET | B18: 14 | C18: 10000 | E18: =PRODUCT(B18*C18) -> 140000 | F18: =PRODUCT(E18*18)/118 -> 21355.932 | G18: =PRODUCT(B18*D18) -> 0 | H18: =SUM(F18:G18) -> 21355.932
A19: DECHET | B19: 2 | D19: 10000 | E19: =PRODUCT(B19*C19) -> 0 | F19: =PRODUCT(E19*18)/118 -> 0 | G19: =PRODUCT(B19*D19) -> 20000 | H19: =SUM(F19:G19) -> 20000
A20: UMUSAVE | E20: =PRODUCT(B20*C20) -> 0 | F20: =PRODUCT(E20*18)/118 -> 0 | G20: =PRODUCT(B20*D20) -> 0 | H20: =SUM(F20:G20) -> 0
A21: OTHER | E21: =PRODUCT(B21*C21) -> 0 | F21: =PRODUCT(E21*18)/118 -> 0 | G21: =PRODUCT(B21*D21) -> 0 | H21: =SUM(F21:G21) -> 0
A22: OTHER | E22: =PRODUCT(B22*C22) -> 0 | F22: =PRODUCT(E22*18)/118 -> 0 | G22: =PRODUCT(B22*D22) -> 0 | H22: =SUM(F22:G22) -> 0
A23: OTHER | E23: =PRODUCT(B23*C23) -> 0 | F23: =PRODUCT(E23*18)/118 -> 0 | G23: =PRODUCT(B23*D23) -> 0 | H23: =SUM(F23:G23) -> 0
A24: OTHER | E24: =PRODUCT(B24*C24) -> 0 | F24: =PRODUCT(E24*18)/118 -> 0 | G24: =PRODUCT(B24*D24) -> 0 | H24: =SUM(F24:G24) -> 0
A25: OTHER | E25: =PRODUCT(B25*C25) -> 0 | F25: =PRODUCT(E25*18)/118 -> 0 | G25: =PRODUCT(B25*D25) -> 0 | H25: =SUM(F25:G25) -> 0
A26: OTHER | E26: =PRODUCT(B26*C26) -> 0 | F26: =PRODUCT(E26*18)/118 -> 0 | G26: =PRODUCT(B26*D26) -> 0 | H26: =SUM(F26:G26) -> 0
A27: OTHER | E27: =PRODUCT(B27*C27) -> 0 | F27: =PRODUCT(E27*18)/118 -> 0 | G27: =PRODUCT(B27*D27) -> 0 | H27: =SUM(F27:G27) -> 0
A28: OTHER | E28: =PRODUCT(B28*C28) -> 0 | F28: =PRODUCT(E28*18)/118 -> 0 | G28: =PRODUCT(B28*D28) -> 0 | H28: =SUM(F28:G28) -> 0
A29: OTHER | E29: =PRODUCT(B29*C29) -> 0 | F29: =PRODUCT(E29*18)/118 -> 0 | G29: =PRODUCT(B29*D29) -> 0 | H29: =SUM(F29:G29) -> 0
A30: OTHER | E30: =PRODUCT(B30*C30) -> 0 | F30: =PRODUCT(E30*18)/118 -> 0 | G30: =PRODUCT(B30*D30) -> 0 | H30: =SUM(F30:G30) -> 0
A31: OTHER | E31: =PRODUCT(B31*C31) -> 0 | F31: =PRODUCT(E31*18)/118 -> 0 | G31: =PRODUCT(B31*D31) -> 0 | H31: =SUM(F31:G31) -> 0
... A36: OTHER | E36: =PRODUCT(B36*C36) -> 0 | F36: =PRODUCT(E36*18)/118 -> 0 | G36: =PRODUCT(B36*D36) -> 0 | H36: =SUM(F36:G36) -> 0
A37: TOTALY | E37: =SUM(E5:E36) -> 239984070 | F37: =SUM(F5:F36) -> 36607739 | G37: =SUM(G5:G36) -> 3043280 | H37: =SUM(H5:H36) -> 39651019
A38: SUMMARY | C38: RWF | E38: NAME | G38: Phone | H38: RWF
A39: TOTAL RWF PAID ON MOMO PAY | C39: 39653064
A40: TOTAL RWF PAID ON CASH
A41: AMOUNT NOT INVOICED
A42: TOTAL RWF DEPPOSITED ON BANK
A43: MEMBERSHIP FEES REGISTRETION
A44: MEMBERSHIP FEES CONTRIBUTION
A45: TOTAL INCOME | C45: =SUM(C39+C40+C41+C42+C43+C44) -> 39653064
A46: TIMBER SUMMARY
A48: REPORT SUMMARY | C48: TIMBER TYPE | E48: NUMBER OF QUANTITY
C49: INTURUSU | E49: =SUM(B9:B12) -> 92351
C50: PINUS | E50: =SUM(B6:B8) -> 945
C51: PALNCHE | E51: =SUM(B13:B14) -> 8400
C52: IBIPANDE | E52: =SUM(B17:B18) -> 764
C53: UMUSAVE | E53: =SUM(B19:B20) -> 2
C54: OTHER | E54: =B29 -> 0
C55: OTHER | E55: =B30 -> 0
C56: OTHER | E56: =B31 -> 0
C57: OTHER | E57: =B32 -> 0
C58: OTHER | E58: =B33 -> 0
C59: OTHER | E59: =B34 -> 0
C60: OTHER | E60: =B35 -> 0
C61: OTHER | E61: =B36 -> 0
C62: TOTAL TIMBER | E62: =SUM(E49:H61) -> 102462

Sheet RWAMAGANA
A1: QUANTITY REPORT
A3: MONTHLY REPORT OF MAY 2026
A5: NAME OF TIMBER | B5: No OF TIMBER | C5: PRICE OF TIMBER | E5: TOTAL COST | F5: TVA | G5: MSF | H5: TVA+MSF
A6: PINUS NINI | E6: =PRODUCT(B6*C6) -> 0 | F6: =PRODUCT(E6*18)/118 -> 0 | G6: =PRODUCT(B6*50) -> 0 | H6: =SUM(F6:G6) -> 0
A7: PINUS NTOYA | B7: 970 | C7: 5900 | E7: =PRODUCT(B7*C7) -> 5723000 | F7: =PRODUCT(E7*18)/118 -> 873000 | G7: =PRODUCT(B7*50) -> 48500 | H7: =SUM(F7:G7) -> 921500
A8: PINUS | E8: =PRODUCT(B8*C8) -> 0 | F8: =PRODUCT(E8*18)/118 -> 0 | G8: =PRODUCT(B8*50) -> 0 | H8: =SUM(F8:G8) -> 0
A9: MADIRIYE NINI | E9: =PRODUCT(B9*C9) -> 0 | F9: =PRODUCT(E9*18)/118 -> 0 | G9: =PRODUCT(B9*30) -> 0 | H9: =SUM(F9:G9) -> 0
A10: MADIRIYE NTOYA | E10: =PRODUCT(B10*C10) -> 0 | F10: =PRODUCT(E10*18)/118 -> 0 | G10: =PRODUCT(B10*30) -> 0 | H10: =SUM(F10:G10) -> 0
A11: MADRIEN | B11: 36147 | C11: 2124 | E11: =PRODUCT(B11*C11) -> 76776228 | F11: =PRODUCT(E11*18)/118 -> 11711628 | G11: =PRODUCT(B11*30) -> 1084410 | H11: =SUM(F11:G11) -> 12796038
A12: MADRIEN | E12: =PRODUCT(B12*C12) -> 0 | F12: =PRODUCT(E12*18)/118 -> 0 | G12: =PRODUCT(B12*30) -> 0 | H12: =SUM(F12:G12) -> 0
A13: PLANCHE | B13: 1838 | C13: 1357 | E13: =PRODUCT(B13*C13) -> 2494166 | F13: =PRODUCT(E13*18)/118 -> 380466 | G13: =PRODUCT(B13*20) -> 36760 | H13: =SUM(F13:G13) -> 417226
A14: PLANCHE | E14: =PRODUCT(B14*C14) -> 0 | F14: =PRODUCT(E14*18)/118 -> 0 | G14: =PRODUCT(B14*20) -> 0 | H14: =SUM(F14:G14) -> 0
A15: Other Timber for Difference Price
A16: NAME OF TIMBER | B16: No OF TIMBER | C16: P/U | D16: MSF | E16: TOTAL COST | F16: VAT | G16: MSF | H16: VTA+MST
A17: DECHETS | B17: 21 | C17: 10000 | D17: 1331 | E17: =PRODUCT(B17*C17) -> 210000 | F17: =PRODUCT(E17*18)/118 -> 32033.898 | G17: =PRODUCT(B17*D17) -> 27951 | H17: =SUM(F17:G17) -> 59984.898
A18: IBIPANDE | D18: 210 | E18: =PRODUCT(B18*C18) -> 0 | F18: =PRODUCT(E18*18)/118 -> 0 | G18: =PRODUCT(B18*D18) -> 0 | H18: =SUM(F18:G18) -> 0
A19: UMUSAVE | E19: =PRODUCT(B19*C19) -> 0 | F19: =PRODUCT(E19*18)/118 -> 0 | G19: =PRODUCT(B19*D19) -> 0 | H19: =SUM(F19:G19) -> 0
A20: UMUSAVE | E20: =PRODUCT(B20*C20) -> 0 | F20: =PRODUCT(E20*18)/118 -> 0 | G20: =PRODUCT(B20*D20) -> 0 | H20: =SUM(F20:G20) -> 0
A21: GEREVERIYA | B21: 1181 | D21: 210 | E21: =PRODUCT(B21*C21) -> 0 | F21: =PRODUCT(E21*18)/118 -> 0 | G21: =PRODUCT(B21*D21) -> 248010 | H21: =SUM(F21:G21) -> 248010
A22: GEREVERIYA | B22: 50 | C22: 1180 | D22: 30 | E22: =PRODUCT(B22*C22) -> 59000 | F22: =PRODUCT(E22*18)/118 -> 9000 | G22: =PRODUCT(B22*D22) -> 1500 | H22: =SUM(F22:G22) -> 10500
A23: PINUS | B23: 793 | D23: 50 | E23: =PRODUCT(B23*C23) -> 0 | F23: =PRODUCT(E23*18)/118 -> 0 | G23: =PRODUCT(B23*D23) -> 39650 | H23: =SUM(F23:G23) -> 39650
A24: OTHER | E24: =PRODUCT(B24*C24) -> 0 | F24: =PRODUCT(E24*18)/118 -> 0 | G24: =PRODUCT(B24*D24) -> 0 | H24: =SUM(F24:G24) -> 0
A25: OTHER | E25: =PRODUCT(B25*C25) -> 0 | F25: =PRODUCT(E25*18)/118 -> 0 | G25: =PRODUCT(B25*D25) -> 0 | H25: =SUM(F25:G25) -> 0
A26: OTHER | E26: =PRODUCT(B26*C26) -> 0 | F26: =PRODUCT(E26*18)/118 -> 0 | G26: =PRODUCT(B26*D26) -> 0 | H26: =SUM(F26:G26) -> 0
A27: OTHER | E27: =PRODUCT(B27*C27) -> 0 | F27: =PRODUCT(E27*18)/118 -> 0 | G27: =PRODUCT(B27*D27) -> 0 | H27: =SUM(F27:G27) -> 0
A28: OTHER | E28: =PRODUCT(B28*C28) -> 0 | F28: =PRODUCT(E28*18)/118 -> 0 | G28: =PRODUCT(B28*D28) -> 0 | H28: =SUM(F28:G28) -> 0
A29: OTHER | E29: =PRODUCT(B29*C29) -> 0 | F29: =PRODUCT(E29*18)/118 -> 0 | G29: =PRODUCT(B29*D29) -> 0 | H29: =SUM(F29:G29) -> 0
A30: OTHER | E30: =PRODUCT(B30*C30) -> 0 | F30: =PRODUCT(E30*18)/118 -> 0 | G30: =PRODUCT(B30*D30) -> 0 | H30: =SUM(F30:G30) -> 0
A31: OTHER | E31: =PRODUCT(B31*C31) -> 0 | F31: =PRODUCT(E31*18)/118 -> 0 | G31: =PRODUCT(B31*D31) -> 0 | H31: =SUM(F31:G31) -> 0
A32: OTHER | E32: =PRODUCT(B32*C32) -> 0 | F32: =PRODUCT(E32*18)/118 -> 0 | G32: =PRODUCT(B32*D32) -> 0 | H32: =SUM(F32:G32) -> 0
A33: OTHER | E33: =PRODUCT(B33*C33) -> 0 | F33: =PRODUCT(E33*18)/118 -> 0 | G33: =PRODUCT(B33*D33) -> 0 | H33: =SUM(F33:G33) -> 0
A34: OTHER | E34: =PRODUCT(B34*C34) -> 0 | F34: =PRODUCT(E34*18)/118 -> 0 | G34: =PRODUCT(B34*D34) -> 0 | H34: =SUM(F34:G34) -> 0
A35: OTHER | E35: =PRODUCT(B35*C35) -> 0 | F35: =PRODUCT(E35*18)/118 -> 0 | G35: =PRODUCT(B35*D35) -> 0 | H35: =SUM(F35:G35) -> 0
A36: OTHER | E36: =PRODUCT(B36*C36) -> 0 | F36: =PRODUCT(E36*18)/118 -> 0 | G36: =PRODUCT(B36*D36) -> 0 | H36: =SUM(F36:G36) -> 0
A37: TOTALY | E37: =SUM(E5:E36) -> 85262394 | F37: =SUM(F5:F36) -> 13006128 | G37: =SUM(G5:G36) -> 1486781 | H37: =SUM(H5:H36) -> 14492909
A38: SUMMARY | C38: RWF | E38: NAME | G38: Phone | H38: RWF
A39: TOTAL RWF PAID ON MOMO PAY | C39: 14492909
A40: TOTAL RWF PAID ON CASH
A41: AMOUNT NOT INVOICED
A42: TOTAL RWF DEPPOSITED ON BANK
A43: MEMBERSHIP FEES REGISTRETION
A44: MEMBERSHIP FEES CONTRIBUTION | C44: 800000
A45: TOTAL INCOME | C45: =SUM(C39+C40+C41+C42+C43+C44) -> 15292909
A46: TIMBER SUMMARY
A48: REPORT SUMMARY | C48: TIMBER TYPE | E48: NUMBER OF QUANTITY
C49: INTURUSU | E49: =SUM(B9:B12) -> 36147
C50: PINUS | E50: =SUM(B6:B8) -> 970
C51: PALNCHE | E51: =SUM(B13:B14) -> 1838
C52: IBIPANDE | E52: =SUM(B17:B18) -> 21
C53: UMUSAVE | E53: =SUM(B19:B20) -> 0
C54: OTHER | E54: =B29 -> 0
C55: OTHER | E55: =B30 -> 0
C56: OTHER | E56: =B31 -> 0
C57: OTHER | E57: =B32 -> 0
C58: OTHER | E58: =B33 -> 0
C59: OTHER | E59: =B34 -> 0
C60: OTHER | E60: =B35 -> 0
C61: OTHER | E61: =B36 -> 0
C62: TOTAL TIMBER | E62: =SUM(E49:H61) -> 38976

Sheet KIMIRONKO
A1: QUANTITY&FINACHIAL REPORT
A3: MONTHLY REPORT OF MAY 2026
A5: NAME OF TIMBER | B5: No OF TIMBER | C5: PRICE OF TIMBER | E5: TOTAL COST | F5: TVA | G5: MSF | H5: TVA+MSF
A6: PINUS NINI | B6: 150 | C6: 12500 | E6: =PRODUCT(B6*C6) -> 1875000 | F6: =PRODUCT(E6*18)/118 -> 286016.95 | G6: =PRODUCT(B6*50) -> 7500 | H6: =SUM(F6:G6) -> 293516.95
A7: PINUS NTOYA | B7: 2892 | C7: 3000 | E7: =PRODUCT(B7*C7) -> 8676000 | F7: =PRODUCT(E7*18)/118 -> 1323457.6 | G7: =PRODUCT(B7*50) -> 144600 | H7: =SUM(F7:G7) -> 1468057.6
A8: PINUS | B8: 1545 | C8: 7670 | E8: =PRODUCT(B8*C8) -> 11850150 | F8: =PRODUCT(E8*18)/118 -> 1807650 | G8: =PRODUCT(B8*50) -> 77250 | H8: =SUM(F8:G8) -> 1884900
A9: MADIRIYE NINI | E9: =PRODUCT(B9*C9) -> 0 | F9: =PRODUCT(E9*18)/118 -> 0 | G9: =PRODUCT(B9*30) -> 0 | H9: =SUM(F9:G9) -> 0
A10: MADIRIYE NTOYA | B10: 120728 | C10: 2124 | E10: =PRODUCT(B10*C10) -> 256426272 | F10: =PRODUCT(E10*18)/118 -> 39115872 | G10: =PRODUCT(B10*30) -> 3621840 | H10: =SUM(F10:G10) -> 42737712
A11: MADRIEN | E11: =PRODUCT(B11*C11) -> 0 | F11: =PRODUCT(E11*18)/118 -> 0 | G11: =PRODUCT(B11*30) -> 0 | H11: =SUM(F11:G11) -> 0
A12: MADRIEN | E12: =PRODUCT(B12*C12) -> 0 | F12: =PRODUCT(E12*18)/118 -> 0 | G12: =PRODUCT(B12*30) -> 0 | H12: =SUM(F12:G12) -> 0
A13: PLANCHE | B13: 6903 | C13: 1357 | E13: =PRODUCT(B13*C13) -> 9367371 | F13: =PRODUCT(E13*18)/118 -> 1428921 | G13: =PRODUCT(B13*20) -> 138060 | H13: =SUM(F13:G13) -> 1566981
A14: PLANCHE | E14: =PRODUCT(B14*C14) -> 0 | F14: =PRODUCT(E14*18)/118 -> 0 | G14: =PRODUCT(B14*20) -> 0 | H14: =SUM(F14:G14) -> 0
A15: Other Timber for Difference Price
A16: NAME OF TIMBER | B16: No OF TIMBER | C16: P/U | D16: MSF | E16: TOTAL COST | F16: VAT | G16: MSF | H16: VTA+MST
A17: IBIPANDE | E17: =PRODUCT(B17*C17) -> 0 | F17: =PRODUCT(E17*18)/118 -> 0 | G17: =PRODUCT(B17*D17) -> 0 | H17: =SUM(F17:G17) -> 0
A18: IBIPANDE | E18: =PRODUCT(B18*C18) -> 0 | F18: =PRODUCT(E18*18)/118 -> 0 | G18: =PRODUCT(B18*D18) -> 0 | H18: =SUM(F18:G18) -> 0
A19: UMUSAVE | E19: =PRODUCT(B19*C19) -> 0 | F19: =PRODUCT(E19*18)/118 -> 0 | G19: =PRODUCT(B19*D19) -> 0 | H19: =SUM(F19:G19) -> 0
A20: UMUSAVE | E20: =PRODUCT(B20*C20) -> 0 | F20: =PRODUCT(E20*18)/118 -> 0 | G20: =PRODUCT(B20*D20) -> 0 | H20: =SUM(F20:G20) -> 0
A21: OTHER | E21: =PRODUCT(B21*C21) -> 0 | F21: =PRODUCT(E21*18)/118 -> 0 | G21: =PRODUCT(B21*D21) -> 0 | H21: =SUM(F21:G21) -> 0
A22: OTHER | E22: =PRODUCT(B22*C22) -> 0 | F22: =PRODUCT(E22*18)/118 -> 0 | G22: =PRODUCT(B22*D22) -> 0 | H22: =SUM(F22:G22) -> 0
A23: OTHER | E23: =PRODUCT(B23*C23) -> 0 | F23: =PRODUCT(E23*18)/118 -> 0 | G23: =PRODUCT(B23*D23) -> 0 | H23: =SUM(F23:G23) -> 0
A24: OTHER | E24: =PRODUCT(B24*C24) -> 0 | F24: =PRODUCT(E24*18)/118 -> 0 | G24: =PRODUCT(B24*D24) -> 0 | H24: =SUM(F24:G24) -> 0
A25: OTHER | E25: =PRODUCT(B25*C25) -> 0 | F25: =PRODUCT(E25*18)/118 -> 0 | G25: =PRODUCT(B25*D25) -> 0 | H25: =SUM(F25:G25) -> 0
A26: OTHER | E26: =PRODUCT(B26*C26) -> 0 | F26: =PRODUCT(E26*18)/118 -> 0 | G26: =PRODUCT(B26*D26) -> 0 | H26: =SUM(F26:G26) -> 0
A27: OTHER | E27: =PRODUCT(B27*C27) -> 0 | F27: =PRODUCT(E27*18)/118 -> 0 | G27: =PRODUCT(B27*D27) -> 0 | H27: =SUM(F27:G27) -> 0
A28: OTHER | E28: =PRODUCT(B28*C28) -> 0 | F28: =PRODUCT(E28*18)/118 -> 0 | G28: =PRODUCT(B28*D28) -> 0 | H28: =SUM(F28:G28) -> 0
... A36: OTHER | E36: =PRODUCT(B36*C36) -> 0 | F36: =PRODUCT(E36*18)/118 -> 0 | G36: =PRODUCT(B36*D36) -> 0 | H36: =SUM(F36:G36) -> 0
A37: TOTALY | E37: =SUM(E5:E36) -> 288194793 | F37: =SUM(F5:F36) -> 43961918 | G37: =SUM(G5:G36) -> 3989250 | H37: =SUM(H5:H36) -> 47951168
A38: SUMMARY | C38: RWF | E38: NAME | G38: Phone | H38: RWF
A39: TOTAL RWF PAID ON MOMO PAY
A40: TOTAL RWF PAID ON CASH
A41: AMOUNT NOT INVOICED
A42: TOTAL RWF DEPPOSITED ON BANK
A43: MEMBERSHIP FEES REGISTRETION
A44: MEMBERSHIP FEES CONTRIBUTION
A45: TOTAL INCOME | C45: =SUM(C39+C40+C41+C42+C43+C44) -> 0
A46: TIMBER SUMMARY
A48: REPORT SUMMARY | C48: TIMBER TYPE | E48: NUMBER OF QUANTITY
C49: INTURUSU | E49: =SUM(B9:B12) -> 120728
C50: PINUS | E50: =SUM(B6:B8) -> 4587
C51: PALNCHE | E51: =SUM(B13:B14) -> 6903
C52: IBIPANDE | E52: =SUM(B17:B18) -> 0
C53: UMUSAVE | E53: =SUM(B19:B20) -> 0
C54: OTHER | E54: =B29 -> 0
C55: OTHER | E55: =B30 -> 0
C56: OTHER | E56: =B31 -> 0
C57: OTHER | E57: =B32 -> 0
C58: OTHER | E58: =B33 -> 0
C59: OTHER | E59: =B34 -> 0
C60: OTHER | E60: =B35 -> 0
C61: OTHER | E61: =B36 -> 0
C62: TOTAL TIMBER | E62: =SUM(E49:H61) -> 132218

Sheet GAHANGA
A1: QUANTITY REPORT
A3: MONTHLY REPORT OF MAY 2026
A5: NAME OF TIMBER | B5: No OF TIMBER | C5: PRICE OF TIMBER | E5: TOTAL COST | F5: TVA | G5: MSF | H5: TVA+MSF
A6: PINUS NINI | E6: =PRODUCT(B6*C6) -> 0 | F6: =PRODUCT(E6*18)/118 -> 0 | G6: =PRODUCT(B6*50) -> 0 | H6: =SUM(F6:G6) -> 0
A7: PINUS NTOYA | B7: 1905 | C7: 7670 | E7: =PRODUCT(B7*C7) -> 14611350 | F7: =PRODUCT(E7*18)/118 -> 2228850 | G7: =PRODUCT(B7*50) -> 95250 | H7: =SUM(F7:G7) -> 2324100
A8: PINUS | B8: 264 | C8: 8000 | E8: =PRODUCT(B8*C8) -> 2112000 | F8: =PRODUCT(E8*18)/118 -> 322169.49 | G8: =PRODUCT(B8*50) -> 13200 | H8: =SUM(F8:G8) -> 335369.49
A9: MADIRIYE NINI | E9: =PRODUCT(B9*C9) -> 0 | F9: =PRODUCT(E9*18)/118 -> 0 | G9: =PRODUCT(B9*30) -> 0 | H9: =SUM(F9:G9) -> 0
A10: MADIRIYE NTOYA | B10: 84966 | C10: 2124 | E10: =PRODUCT(B10*C10) -> 180467784 | F10: =PRODUCT(E10*18)/118 -> 27528984 | G10: =PRODUCT(B10*30) -> 2548980 | H10: =SUM(F10:G10) -> 30077964
A11: MADRIEN | B11: 200 | C11: 3500 | E11: =PRODUCT(B11*C11) -> 700000 | F11: =PRODUCT(E11*18)/118 -> 106779.66 | G11: =PRODUCT(B11*30) -> 6000 | H11: =SUM(F11:G11) -> 112779.66
A12: MADRIEN | E12: =PRODUCT(B12*C12) -> 0 | F12: =PRODUCT(E12*18)/118 -> 0 | G12: =PRODUCT(B12*30) -> 0 | H12: =SUM(F12:G12) -> 0
A13: PLANCHE | B13: 3400 | C13: 1357 | E13: =PRODUCT(B13*C13) -> 4613800 | F13: =PRODUCT(E13*18)/118 -> 703800 | G13: =PRODUCT(B13*20) -> 68000 | H13: =SUM(F13:G13) -> 771800
A14: PLANCHE | E14: =PRODUCT(B14*C14) -> 0 | F14: =PRODUCT(E14*18)/118 -> 0 | G14: =PRODUCT(B14*20) -> 0 | H14: =SUM(F14:G14) -> 0
A15: Other Timber for Difference Price
A16: NAME OF TIMBER | B16: No OF TIMBER | C16: P/U | D16: MSF | E16: TOTAL COST | F16: VAT | G16: MSF | H16: VTA+MST
A17: IBIPANDE | B17: 300 | C17: 4000 | D17: 50 | E17: =PRODUCT(B17*C17) -> 1200000 | F17: =PRODUCT(E17*18)/118 -> 183050.85 | G17: =PRODUCT(B17*D17) -> 15000 | H17: =SUM(F17:G17) -> 198050.85
A18: IBIPANDE | B18: 400 | C18: 2000 | D18: 50 | E18: =PRODUCT(B18*C18) -> 800000 | F18: =PRODUCT(E18*18)/118 -> 122033.9 | G18: =PRODUCT(B18*D18) -> 20000 | H18: =SUM(F18:G18) -> 142033.9
A19: UMUSAVE | B19: 371 | C19: 19500 | D19: 50 | E19: =PRODUCT(B19*C19) -> 7234500 | F19: =PRODUCT(E19*18)/118 -> 1103567.8 | G19: =PRODUCT(B19*D19) -> 18550 | H19: =SUM(F19:G19) -> 1122117.8
A20: UMUSAVE | B20: 111 | C20: 7670 | D20: 50 | E20: =PRODUCT(B20*C20) -> 851370 | F20: =PRODUCT(E20*18)/118 -> 129870 | G20: =PRODUCT(B20*D20) -> 5550 | H20: =SUM(F20:G20) -> 135420
A21: OTHER | E21: =PRODUCT(B21*C21) -> 0 | F21: =PRODUCT(E21*18)/118 -> 0 | G21: =PRODUCT(B21*D21) -> 0 | H21: =SUM(F21:G21) -> 0
A22: OTHER | E22: =PRODUCT(B22*C22) -> 0 | F22: =PRODUCT(E22*18)/118 -> 0 | G22: =PRODUCT(B22*D22) -> 0 | H22: =SUM(F22:G22) -> 0
A23: OTHER | E23: =PRODUCT(B23*C23) -> 0 | F23: =PRODUCT(E23*18)/118 -> 0 | G23: =PRODUCT(B23*D23) -> 0 | H23: =SUM(F23:G23) -> 0
A24: OTHER | E24: =PRODUCT(B24*C24) -> 0 | F24: =PRODUCT(E24*18)/118 -> 0 | G24: =PRODUCT(B24*D24) -> 0 | H24: =SUM(F24:G24) -> 0
A25: OTHER | E25: =PRODUCT(B25*C25) -> 0 | F25: =PRODUCT(E25*18)/118 -> 0 | G25: =PRODUCT(B25*D25) -> 0 | H25: =SUM(F25:G25) -> 0
A26: OTHER | E26: =PRODUCT(B26*C26) -> 0 | F26: =PRODUCT(E26*18)/118 -> 0 | G26: =PRODUCT(B26*D26) -> 0 | H26: =SUM(F26:G26) -> 0
A27: OTHER | E27: =PRODUCT(B27*C27) -> 0 | F27: =PRODUCT(E27*18)/118 -> 0 | G27: =PRODUCT(B27*D27) -> 0 | H27: =SUM(F27:G27) -> 0
A28: OTHER | E28: =PRODUCT(B28*C28) -> 0 | F28: =PRODUCT(E28*18)/118 -> 0 | G28: =PRODUCT(B28*D28) -> 0 | H28: =SUM(F28:G28) -> 0
A29: OTHER | E29: =PRODUCT(B29*C29) -> 0 | F29: =PRODUCT(E29*18)/118 -> 0 | G29: =PRODUCT(B29*D29) -> 0 | H29: =SUM(F29:G29) -> 0
A30: OTHER | E30: =PRODUCT(B30*C30) -> 0 | F30: =PRODUCT(E30*18)/118 -> 0 | G30: =PRODUCT(B30*D30) -> 0 | H30: =SUM(F30:G30) -> 0
A31: OTHER | E31: =PRODUCT(B31*C31) -> 0 | F31: =PRODUCT(E31*18)/118 -> 0 | G31: =PRODUCT(B31*D31) -> 0 | H31: =SUM(F31:G31) -> 0
A32: OTHER | E32: =PRODUCT(B32*C32) -> 0 | F32: =PRODUCT(E32*18)/118 -> 0 | G32: =PRODUCT(B32*D32) -> 0 | H32: =SUM(F32:G32) -> 0
... A36: OTHER | E36: =PRODUCT(B36*C36) -> 0 | F36: =PRODUCT(E36*18)/118 -> 0 | G36: =PRODUCT(B36*D36) -> 0 | H36: =SUM(F36:G36) -> 0
A37: TOTALY | E37: =SUM(E5:E36) -> 212590804 | F37: =SUM(F5:F36) -> 32429106 | G37: =SUM(G5:G36) -> 2790530 | H37: =SUM(H5:H36) -> 35219636
A38: SUMMARY | C38: RWF | E38: NAME | G38: Phone | H38: RWF
A39: TOTAL RWF PAID ON MOMO PAY | C39: 35219636
A40: TOTAL RWF PAID ON CASH
A41: AMOUNT NOT INVOICED
A42: TOTAL RWF DEPPOSITED ON BANK
A43: MEMBERSHIP FEES REGISTRETION
A44: MEMBERSHIP FEES CONTRIBUTION
A45: TOTAL INCOME | C45: =SUM(C39+C40+C41+C42+C43+C44) -> 35219636
A46: TIMBER SUMMARY
A48: REPORT SUMMARY | C48: TIMBER TYPE | E48: NUMBER OF QUANTITY
C49: INTURUSU | E49: =SUM(B9:B12) -> 85166
C50: PINUS | E50: =SUM(B6:B8) -> 2169
C51: PALNCHE | E51: =SUM(B13:B14) -> 3400
C52: IBIPANDE | E52: =SUM(B17:B18) -> 700
C53: UMUSAVE | E53: =SUM(B19:B20) -> 482
C54: OTHER | E54: =B29 -> 0
C55: OTHER | E55: =B30 -> 0
C56: OTHER | E56: =B31 -> 0
C57: OTHER | E57: =B32 -> 0
C58: OTHER | E58: =B33 -> 0
C59: OTHER | E59: =B34 -> 0
C60: OTHER | E60: =B35 -> 0
C61: OTHER | E61: =B36 -> 0
C62: TOTAL TIMBER | E62: =SUM(E49:H61) -> 91917

Sheet BUGESERA
A1: QUANTITY REPORT
A3: MONTHLY REPORT OF MAY 2026
A5: NAME OF TIMBER | B5: No OF TIMBER | C5: PRICE OF TIMBER | E5: TOTAL COST | F5: TVA | G5: MSF | H5: TVA+MSF
A6: PINUS NINI | E6: =PRODUCT(B6*C6) -> 0 | F6: =PRODUCT(E6*18)/118 -> 0 | G6: =PRODUCT(B6*50) -> 0 | H6: =SUM(F6:G6) -> 0
A7: PINUS NTOYA | B7: 1490 | C7: 4720 | E7: =PRODUCT(B7*C7) -> 7032800 | F7: =PRODUCT(E7*18)/118 -> 1072800 | G7: =PRODUCT(B7*50) -> 74500 | H7: =SUM(F7:G7) -> 1147300
A8: PINUS | E8: =PRODUCT(B8*C8) -> 0 | F8: =PRODUCT(E8*18)/118 -> 0 | G8: =PRODUCT(B8*50) -> 0 | H8: =SUM(F8:G8) -> 0
A9: MADIRIYE NINI | E9: =PRODUCT(B9*C9) -> 0 | F9: =PRODUCT(E9*18)/118 -> 0 | G9: =PRODUCT(B9*30) -> 0 | H9: =SUM(F9:G9) -> 0
A10: MADIRIYE NTOYA | B10: 115795 | C10: 2124 | E10: =PRODUCT(B10*C10) -> 245948580 | F10: =PRODUCT(E10*18)/118 -> 37517580 | G10: =PRODUCT(B10*30) -> 3473850 | H10: =SUM(F10:G10) -> 40991430
A11: MADRIEN | E11: =PRODUCT(B11*C11) -> 0 | F11: =PRODUCT(E11*18)/118 -> 0 | G11: =PRODUCT(B11*30) -> 0 | H11: =SUM(F11:G11) -> 0
A12: MADRIEN | E12: =PRODUCT(B12*C12) -> 0 | F12: =PRODUCT(E12*18)/118 -> 0 | G12: =PRODUCT(B12*30) -> 0 | H12: =SUM(F12:G12) -> 0
A13: PLANCHE | B13: 23254 | C13: 1357 | E13: =PRODUCT(B13*C13) -> 31555678 | F13: =PRODUCT(E13*18)/118 -> 4813578 | G13: =PRODUCT(B13*20) -> 465080 | H13: =SUM(F13:G13) -> 5278658
A14: PLANCHE | E14: =PRODUCT(B14*C14) -> 0 | F14: =PRODUCT(E14*18)/118 -> 0 | G14: =PRODUCT(B14*20) -> 0 | H14: =SUM(F14:G14) -> 0
A15: Other Timber for Difference Price
A16: NAME OF TIMBER | B16: No OF TIMBER | C16: P/U | D16: MSF | E16: TOTAL COST | F16: VAT | G16: MSF | H16: VTA+MST
A17: IBIPANDE BYA PINUS | B17: 90 | C17: 2006 | D17: 30 | E17: =PRODUCT(B17*C17) -> 180540 | F17: =PRODUCT(E17*18)/118 -> 27540 | G17: =PRODUCT(B17*D17) -> 2700 | H17: =SUM(F17:G17) -> 30240
A18: IBIPANDE BYA CEDERERA | B18: 118 | C18: 1298 | D18: 30 | E18: =PRODUCT(B18*C18) -> 153164 | F18: =PRODUCT(E18*18)/118 -> 23364 | G18: =PRODUCT(B18*D18) -> 3540 | H18: =SUM(F18:G18) -> 26904
A19: INTURUSU NINI | B19: 1203 | C19: 3304 | D19: 40 | E19: =PRODUCT(B19*C19) -> 3974712 | F19: =PRODUCT(E19*18)/118 -> 606312 | G19: =PRODUCT(B19*D19) -> 48120 | H19: =SUM(F19:G19) -> 654432
A20: UMUSAVE | E20: =PRODUCT(B20*C20) -> 0 | F20: =PRODUCT(E20*18)/118 -> 0 | G20: =PRODUCT(B20*D20) -> 0 | H20: =SUM(F20:G20) -> 0
A21: OTHER | D21: 10000 | E21: =PRODUCT(B21*C21) -> 0 | F21: =PRODUCT(E21*18)/118 -> 0 | G21: =PRODUCT(B21*D21) -> 0 | H21: =SUM(F21:G21) -> 0
A22: OTHER | E22: =PRODUCT(B22*C22) -> 0 | F22: =PRODUCT(E22*18)/118 -> 0 | G22: =PRODUCT(B22*D22) -> 0 | H22: =SUM(F22:G22) -> 0
A23: OTHER | E23: =PRODUCT(B23*C23) -> 0 | F23: =PRODUCT(E23*18)/118 -> 0 | G23: =PRODUCT(B23*D23) -> 0 | H23: =SUM(F23:G23) -> 0
A24: OTHER | E24: =PRODUCT(B24*C24) -> 0 | F24: =PRODUCT(E24*18)/118 -> 0 | G24: =PRODUCT(B24*D24) -> 0 | H24: =SUM(F24:G24) -> 0
A25: OTHER | E25: =PRODUCT(B25*C25) -> 0 | F25: =PRODUCT(E25*18)/118 -> 0 | G25: =PRODUCT(B25*D25) -> 0 | H25: =SUM(F25:G25) -> 0
A26: OTHER | E26: =PRODUCT(B26*C26) -> 0 | F26: =PRODUCT(E26*18)/118 -> 0 | G26: =PRODUCT(B26*D26) -> 0 | H26: =SUM(F26:G26) -> 0
A27: OTHER | E27: =PRODUCT(B27*C27) -> 0 | F27: =PRODUCT(E27*18)/118 -> 0 | G27: =PRODUCT(B27*D27) -> 0 | H27: =SUM(F27:G27) -> 0
A28: OTHER | E28: =PRODUCT(B28*C28) -> 0 | F28: =PRODUCT(E28*18)/118 -> 0 | G28: =PRODUCT(B28*D28) -> 0 | H28: =SUM(F28:G28) -> 0
A29: OTHER | E29: =PRODUCT(B29*C29) -> 0 | F29: =PRODUCT(E29*18)/118 -> 0 | G29: =PRODUCT(B29*D29) -> 0 | H29: =SUM(F29:G29) -> 0
A30: OTHER | E30: =PRODUCT(B30*C30) -> 0 | F30: =PRODUCT(E30*18)/118 -> 0 | G30: =PRODUCT(B30*D30) -> 0 | H30: =SUM(F30:G30) -> 0
A31: OTHER | E31: =PRODUCT(B31*C31) -> 0 | F31: =PRODUCT(E31*18)/118 -> 0 | G31: =PRODUCT(B31*D31) -> 0 | H31: =SUM(F31:G31) -> 0
A32: OTHER | E32: =PRODUCT(B32*C32) -> 0 | F32: =PRODUCT(E32*18)/118 -> 0 | G32: =PRODUCT(B32*D32) -> 0 | H32: =SUM(F32:G32) -> 0
A33: OTHER | E33: =PRODUCT(B33*C33) -> 0 | F33: =PRODUCT(E33*18)/118 -> 0 | G33: =PRODUCT(B33*D33) -> 0 | H33: =SUM(F33:G33) -> 0
... A36: OTHER | E36: =PRODUCT(B36*C36) -> 0 | F36: =PRODUCT(E36*18)/118 -> 0 | G36: =PRODUCT(B36*D36) -> 0 | H36: =SUM(F36:G36) -> 0
A37: TOTALY | E37: =SUM(E5:E36) -> 288845474 | F37: =SUM(F5:F36) -> 44061174 | G37: =SUM(G5:G36) -> 4067790 | H37: =SUM(H5:H36) -> 48128964
A38: SUMMARY | C38: RWF | E38: NAME | G38: Phone | H38: RWF
A39: TOTAL RWF PAID ON MOMO PAY | C39: 45442312
A40: TOTAL RWF PAID ON CASH | C40: 2686652
A41: AMOUNT NOT INVOICED
A42: TOTAL RWF DEPPOSITED ON BANK
A43: MEMBERSHIP FEES REGISTRETION
A44: MEMBERSHIP FEES CONTRIBUTION
A45: TOTAL INCOME | C45: =SUM(C39+C40+C41+C42+C43+C44) -> 48128964
A46: TIMBER SUMMARY
A48: REPORT SUMMARY | C48: TIMBER TYPE | E48: NUMBER OF QUANTITY
C49: INTURUSU | E49: =SUM(B9:B12) -> 115795
C50: PINUS | E50: =SUM(B6:B8) -> 1490
C51: PALNCHE | E51: =SUM(B13:B14) -> 23254
C52: IBIPANDE | E52: =SUM(B17:B18) -> 208
C53: UMUSAVE | E53: =SUM(B19:B20) -> 1203
C54: OTHER | E54: =B29 -> 0
C55: OTHER | E55: =B30 -> 0
C56: OTHER | E56: =B31 -> 0
C57: OTHER | E57: =B32 -> 0
C58: OTHER | E58: =B33 -> 0
C59: OTHER | E59: =B34 -> 0
C60: OTHER | E60: =B35 -> 0
C61: OTHER | E61: =B36 -> 0
C62: TOTAL TIMBER | E62: =SUM(E49:H61) -> 141950

Sheet NYARUGENGE
A1: QUANTITY REPORT
A3: MONTHLY REPORT OF JUNE 2026
A5: NAME OF TIMBER | B5: No OF TIMBER | C5: PRICE OF TIMBER | E5: TOTAL COST | F5: TVA | G5: MSF | H5: TVA+MSF
A6: PINUS NINI | E6: =PRODUCT(B6*C6) -> 0 | F6: =PRODUCT(E6*18)/118 -> 0 | G6: =PRODUCT(B6*50) -> 0 | H6: =SUM(F6:G6) -> 0
A7: PINUS NTOYA | E7: =PRODUCT(B7*C7) -> 0 | F7: =PRODUCT(E7*18)/118 -> 0 | G7: =PRODUCT(B7*50) -> 0 | H7: =SUM(F7:G7) -> 0
A8: PINUS | B8: 350 | C8: 7670 | E8: =PRODUCT(B8*C8) -> 2684500 | F8: =PRODUCT(E8*18)/118 -> 409500 | G8: =PRODUCT(B8*50) -> 17500 | H8: =SUM(F8:G8) -> 427000
A9: MADIRIYE NINI | E9: =PRODUCT(B9*C9) -> 0 | F9: =PRODUCT(E9*18)/118 -> 0 | G9: =PRODUCT(B9*30) -> 0 | H9: =SUM(F9:G9) -> 0
A10: MADIRIYE NTOYA | B10: 46530 | C10: 2124 | E10: =PRODUCT(B10*C10) -> 98829720 | F10: =PRODUCT(E10*18)/118 -> 15075720 | G10: =PRODUCT(B10*30) -> 1395900 | H10: =SUM(F10:G10) -> 16471620
A11: MADRIEN | E11: =PRODUCT(B11*C11) -> 0 | F11: =PRODUCT(E11*18)/118 -> 0 | G11: =PRODUCT(B11*30) -> 0 | H11: =SUM(F11:G11) -> 0
A12: MADRIEN | E12: =PRODUCT(B12*C12) -> 0 | F12: =PRODUCT(E12*18)/118 -> 0 | G12: =PRODUCT(B12*30) -> 0 | H12: =SUM(F12:G12) -> 0
A13: PLANCHE | B13: 3750 | C13: 1357 | E13: =PRODUCT(B13*C13) -> 5088750 | F13: =PRODUCT(E13*18)/118 -> 776250 | G13: =PRODUCT(B13*20) -> 75000 | H13: =SUM(F13:G13) -> 851250
A14: PLANCHE | E14: =PRODUCT(B14*C14) -> 0 | F14: =PRODUCT(E14*18)/118 -> 0 | G14: =PRODUCT(B14*20) -> 0 | H14: =SUM(F14:G14) -> 0
A15: Other Timber for Difference Price
A16: NAME OF TIMBER | B16: No OF TIMBER | C16: P/U | D16: MSF | E16: TOTAL COST | F16: VAT | G16: MSF | H16: VTA+MST
A17: IBIPANDE | E17: =PRODUCT(B17*C17) -> 0 | F17: =PRODUCT(E17*18)/118 -> 0 | G17: =PRODUCT(B17*D17) -> 0 | H17: =SUM(F17:G17) -> 0
A18: IBIPANDE | E18: =PRODUCT(B18*C18) -> 0 | F18: =PRODUCT(E18*18)/118 -> 0 | G18: =PRODUCT(B18*D18) -> 0 | H18: =SUM(F18:G18) -> 0
A19: UMUSAVE | E19: =PRODUCT(B19*C19) -> 0 | F19: =PRODUCT(E19*18)/118 -> 0 | G19: =PRODUCT(B19*D19) -> 0 | H19: =SUM(F19:G19) -> 0
A20: UMUSAVE | E20: =PRODUCT(B20*C20) -> 0 | F20: =PRODUCT(E20*18)/118 -> 0 | G20: =PRODUCT(B20*D20) -> 0 | H20: =SUM(F20:G20) -> 0
A21: OTHER | E21: =PRODUCT(B21*C21) -> 0 | F21: =PRODUCT(E21*18)/118 -> 0 | G21: =PRODUCT(B21*D21) -> 0 | H21: =SUM(F21:G21) -> 0
A22: OTHER | E22: =PRODUCT(B22*C22) -> 0 | F22: =PRODUCT(E22*18)/118 -> 0 | G22: =PRODUCT(B22*D22) -> 0 | H22: =SUM(F22:G22) -> 0
A23: OTHER | E23: =PRODUCT(B23*C23) -> 0 | F23: =PRODUCT(E23*18)/118 -> 0 | G23: =PRODUCT(B23*D23) -> 0 | H23: =SUM(F23:G23) -> 0
A24: OTHER | E24: =PRODUCT(B24*C24) -> 0 | F24: =PRODUCT(E24*18)/118 -> 0 | G24: =PRODUCT(B24*D24) -> 0 | H24: =SUM(F24:G24) -> 0
A25: OTHER | E25: =PRODUCT(B25*C25) -> 0 | F25: =PRODUCT(E25*18)/118 -> 0 | G25: =PRODUCT(B25*D25) -> 0 | H25: =SUM(F25:G25) -> 0
A26: OTHER | E26: =PRODUCT(B26*C26) -> 0 | F26: =PRODUCT(E26*18)/118 -> 0 | G26: =PRODUCT(B26*D26) -> 0 | H26: =SUM(F26:G26) -> 0
A27: OTHER | E27: =PRODUCT(B27*C27) -> 0 | F27: =PRODUCT(E27*18)/118 -> 0 | G27: =PRODUCT(B27*D27) -> 0 | H27: =SUM(F27:G27) -> 0
A28: OTHER | E28: =PRODUCT(B28*C28) -> 0 | F28: =PRODUCT(E28*18)/118 -> 0 | G28: =PRODUCT(B28*D28) -> 0 | H28: =SUM(F28:G28) -> 0
... A36: OTHER | E36: =PRODUCT(B36*C36) -> 0 | F36: =PRODUCT(E36*18)/118 -> 0 | G36: =PRODUCT(B36*D36) -> 0 | H36: =SUM(F36:G36) -> 0
A37: TOTALY | E37: =SUM(E5:E36) -> 106602970 | F37: =SUM(F5:F36) -> 16261470 | G37: =SUM(G5:G36) -> 1488400 | H37: =SUM(H5:H36) -> 17749870
A38: SUMMARY | C38: RWF | E38: NAME | G38: Phone | H38: RWF
A39: TOTAL RWF PAID ON MOMO PAY | C39: 17749870
A40: TOTAL RWF PAID ON CASH
A41: AMOUNT NOT INVOICED
A42: TOTAL RWF DEPPOSITED ON BANK
A43: MEMBERSHIP FEES REGISTRETION
A44: MEMBERSHIP FEES CONTRIBUTION
A45: TOTAL INCOME | C45: =SUM(C39+C40+C41+C42+C43+C44) -> 17749870
A46: TIMBER SUMMARY
A48: REPORT SUMMARY | C48: TIMBER TYPE | E48: NUMBER OF QUANTITY
C49: INTURUSU | E49: =SUM(B9:B12) -> 46530
C50: PINUS | E50: =SUM(B6:B8) -> 350
C51: PALNCHE | E51: =SUM(B13:B14) -> 3750
C52: IBIPANDE | E52: =SUM(B17:B18) -> 0
C53: UMUSAVE | E53: =SUM(B19:B20) -> 0
C54: OTHER | E54: =B29 -> 0
C55: OTHER | E55: =B30 -> 0
C56: OTHER | E56: =B31 -> 0
C57: OTHER | E57: =B32 -> 0
C58: OTHER | E58: =B33 -> 0
C59: OTHER | E59: =B34 -> 0
C60: OTHER | E60: =B35 -> 0
C61: OTHER | E61: =B36 -> 0
C62: TOTAL TIMBER | E62: =SUM(E49:H61) -> 50630

Sheet MUHANGA
A1: QUANTITY REPORT
A3: MONTHLY REPORT OF MAY 2026
A5: NAME OF TIMBER | B5: No OF TIMBER | C5: PRICE OF TIMBER | E5: TOTAL COST | F5: TVA | G5: MSF | H5: TVA+MSF
A6: PINUS NINI | E6: =PRODUCT(B6*C6) -> 0 | F6: =PRODUCT(E6*18)/118 -> 0 | G6: =PRODUCT(B6*50) -> 0 | H6: =SUM(F6:G6) -> 0
A7: PINUS NTOYA | B7: 253 | C7: 7670 | E7: =PRODUCT(B7*C7) -> 1940510 | F7: =PRODUCT(E7*18)/118 -> 296010 | G7: =PRODUCT(B7*50) -> 12650 | H7: =SUM(F7:G7) -> 308660
A8: PINUS | E8: =PRODUCT(B8*C8) -> 0 | F8: =PRODUCT(E8*18)/118 -> 0 | G8: =PRODUCT(B8*50) -> 0 | H8: =SUM(F8:G8) -> 0
A9: MADIRIYE NINI | E9: =PRODUCT(B9*C9) -> 0 | F9: =PRODUCT(E9*18)/118 -> 0 | G9: =PRODUCT(B9*30) -> 0 | H9: =SUM(F9:G9) -> 0
A10: MADIRIYE NTOYA | B10: 6067 | C10: 2200 | E10: =PRODUCT(B10*C10) -> 13347400 | F10: =PRODUCT(E10*18)/118 -> 2036044.1 | G10: =PRODUCT(B10*30) -> 182010 | H10: =SUM(F10:G10) -> 2218054.1
A11: MADRIEN | B11: 22736 | C11: 2596 | E11: =PRODUCT(B11*C11) -> 59022656 | F11: =PRODUCT(E11*18)/118 -> 9003456 | G11: =PRODUCT(B11*30) -> 682080 | H11: =SUM(F11:G11) -> 9685536
A12: MADRIEN | B12: 1350 | C12: 2500 | E12: =PRODUCT(B12*C12) -> 3375000 | F12: =PRODUCT(E12*18)/118 -> 514830.51 | G12: =PRODUCT(B12*30) -> 40500 | H12: =SUM(F12:G12) -> 555330.51
A13: PLANCHE | B13: 1608 | C13: 1416 | E13: =PRODUCT(B13*C13) -> 2276928 | F13: =PRODUCT(E13*18)/118 -> 347328 | G13: =PRODUCT(B13*20) -> 32160 | H13: =SUM(F13:G13) -> 379488
A14: PLANCHE | B14: 400 | C14: 1200 | E14: =PRODUCT(B14*C14) -> 480000 | F14: =PRODUCT(E14*18)/118 -> 73220.339 | G14: =PRODUCT(B14*20) -> 8000 | H14: =SUM(F14:G14) -> 81220.339
A15: Other Timber for Difference Price
A16: NAME OF TIMBER | B16: No OF TIMBER | C16: P/U | D16: MSF | E16: TOTAL COST | F16: VAT | G16: MSF | H16: VTA+MST
A17: IBIPANDE | B17: 19894 | C17: 1180 | D17: 20 | E17: =PRODUCT(B17*C17) -> 23474920 | F17: =PRODUCT(E17*18)/118 -> 3580920 | G17: =PRODUCT(B17*D17) -> 397880 | H17: =SUM(F17:G17) -> 3978800
A18: MADRIEN NINI | B18: 200 | C18: 4000 | D18: 50 | E18: =PRODUCT(B18*C18) -> 800000 | F18: =PRODUCT(E18*18)/118 -> 122033.9 | G18: =PRODUCT(B18*D18) -> 10000 | H18: =SUM(F18:G18) -> 132033.9
A19: IBIPANDE BYA PINUS | B19: 315 | C19: 2360 | D19: 50 | E19: =PRODUCT(B19*C19) -> 743400 | F19: =PRODUCT(E19*18)/118 -> 113400 | G19: =PRODUCT(B19*D19) -> 15750 | H19: =SUM(F19:G19) -> 129150
A20: UMUSAVE | E20: =PRODUCT(B20*C20) -> 0 | F20: =PRODUCT(E20*18)/118 -> 0 | G20: =PRODUCT(B20*D20) -> 0 | H20: =SUM(F20:G20) -> 0
A21: OTHER | E21: =PRODUCT(B21*C21) -> 0 | F21: =PRODUCT(E21*18)/118 -> 0 | G21: =PRODUCT(B21*D21) -> 0 | H21: =SUM(F21:G21) -> 0
A22: OTHER | E22: =PRODUCT(B22*C22) -> 0 | F22: =PRODUCT(E22*18)/118 -> 0 | G22: =PRODUCT(B22*D22) -> 0 | H22: =SUM(F22:G22) -> 0
A23: OTHER | E23: =PRODUCT(B23*C23) -> 0 | F23: =PRODUCT(E23*18)/118 -> 0 | G23: =PRODUCT(B23*D23) -> 0 | H23: =SUM(F23:G23) -> 0
A24: OTHER | E24: =PRODUCT(B24*C24) -> 0 | F24: =PRODUCT(E24*18)/118 -> 0 | G24: =PRODUCT(B24*D24) -> 0 | H24: =SUM(F24:G24) -> 0
A25: OTHER | E25: =PRODUCT(B25*C25) -> 0 | F25: =PRODUCT(E25*18)/118 -> 0 | G25: =PRODUCT(B25*D25) -> 0 | H25: =SUM(F25:G25) -> 0
A26: OTHER | E26: =PRODUCT(B26*C26) -> 0 | F26: =PRODUCT(E26*18)/118 -> 0 | G26: =PRODUCT(B26*D26) -> 0 | H26: =SUM(F26:G26) -> 0
A27: OTHER | E27: =PRODUCT(B27*C27) -> 0 | F27: =PRODUCT(E27*18)/118 -> 0 | G27: =PRODUCT(B27*D27) -> 0 | H27: =SUM(F27:G27) -> 0
A28: OTHER | E28: =PRODUCT(B28*C28) -> 0 | F28: =PRODUCT(E28*18)/118 -> 0 | G28: =PRODUCT(B28*D28) -> 0 | H28: =SUM(F28:G28) -> 0
A29: OTHER | E29: =PRODUCT(B29*C29) -> 0 | F29: =PRODUCT(E29*18)/118 -> 0 | G29: =PRODUCT(B29*D29) -> 0 | H29: =SUM(F29:G29) -> 0
A30: OTHER | E30: =PRODUCT(B30*C30) -> 0 | F30: =PRODUCT(E30*18)/118 -> 0 | G30: =PRODUCT(B30*D30) -> 0 | H30: =SUM(F30:G30) -> 0
A31: OTHER | E31: =PRODUCT(B31*C31) -> 0 | F31: =PRODUCT(E31*18)/118 -> 0 | G31: =PRODUCT(B31*D31) -> 0 | H31: =SUM(F31:G31) -> 0
... A36: OTHER | E36: =PRODUCT(B36*C36) -> 0 | F36: =PRODUCT(E36*18)/118 -> 0 | G36: =PRODUCT(B36*D36) -> 0 | H36: =SUM(F36:G36) -> 0
A37: TOTALY | E37: =SUM(E5:E36) -> 105460814 | F37: =SUM(F5:F36) -> 16087243 | G37: =SUM(G5:G36) -> 1381030 | H37: =SUM(H5:H36) -> 17468273
A38: SUMMARY | C38: RWF | E38: NAME | G38: Phone | H38: RWF
A39: TOTAL RWF PAID ON MOMO PAY
A40: TOTAL RWF PAID ON CASH
A41: AMOUNT NOT INVOICED
A42: TOTAL RWF DEPPOSITED ON BANK
A43: MEMBERSHIP FEES REGISTRETION
A44: MEMBERSHIP FEES CONTRIBUTION
A45: TOTAL INCOME | C45: =SUM(C39+C40+C41+C42+C43+C44) -> 0
A46: TIMBER SUMMARY
A48: REPORT SUMMARY | C48: TIMBER TYPE | E48: NUMBER OF QUANTITY
C49: INTURUSU | E49: =SUM(B9:B12) -> 30153
C50: PINUS | E50: =SUM(B6:B8) -> 253
C51: PALNCHE | E51: =SUM(B13:B14) -> 2008
C52: IBIPANDE | E52: =SUM(B17:B18) -> 20094
C53: UMUSAVE | E53: =SUM(B19:B20) -> 315
C54: OTHER | E54: =B29 -> 0
C55: OTHER | E55: =B30 -> 0
C56: OTHER | E56: =B31 -> 0
C57: OTHER | E57: =B32 -> 0
C58: OTHER | E58: =B33 -> 0
C59: OTHER | E59: =B34 -> 0
C60: OTHER | E60: =B35 -> 0
C61: OTHER | E61: =B36 -> 0
C62: TOTAL TIMBER | E62: =SUM(E49:H61) -> 52823

Sheet HUYE
A1: QUANTITY REPORT
A3: MONTHLY REPORT OF MAY 2026
A5: NAME OF TIMBER | B5: No OF TIMBER | C5: PRICE OF TIMBER | E5: TOTAL COST | F5: TVA | G5: MSF | H5: TVA+MSF
A6: PINUS NINI | B6: 232 | C6: 8260 | E6: =PRODUCT(B6*C6) -> 1916320 | F6: =PRODUCT(E6*18)/118 -> 292320 | G6: =PRODUCT(B6*50) -> 11600 | H6: =SUM(F6:G6) -> 303920
A7: Pinus | B7: 572 | C7: 9440 | E7: =PRODUCT(B7*C7) -> 5399680 | F7: =PRODUCT(E7*18)/118 -> 823680 | G7: =PRODUCT(B7*50) -> 28600 | H7: =SUM(F7:G7) -> 852280
A8: PINUS | B8: 175 | C8: 7000 | E8: =PRODUCT(B8*C8) -> 1225000 | F8: =PRODUCT(E8*18)/118 -> 186864.41 | G8: =PRODUCT(B8*50) -> 8750 | H8: =SUM(F8:G8) -> 195614.41
A9: MADIRIYE NINI | B9: 53 | C9: 3540 | E9: =PRODUCT(B9*C9) -> 187620 | F9: =PRODUCT(E9*18)/118 -> 28620 | G9: =PRODUCT(B9*30) -> 1590 | H9: =SUM(F9:G9) -> 30210
A10: MADIRIYE NTOYA | B10: 22285 | C10: 2360 | E10: =PRODUCT(B10*C10) -> 52592600 | F10: =PRODUCT(E10*18)/118 -> 8022600 | G10: =PRODUCT(B10*30) -> 668550 | H10: =SUM(F10:G10) -> 8691150
A11: GEREVERIYA | C11: 1180 | E11: =PRODUCT(B11*C11) -> 0 | F11: =PRODUCT(E11*18)/118 -> 0 | G11: =PRODUCT(B11*30) -> 0 | H11: =SUM(F11:G11) -> 0
A12: MADRIEN | B12: 2782 | C12: 4130 | E12: =PRODUCT(B12*C12) -> 11489660 | F12: =PRODUCT(E12*18)/118 -> 1752660 | G12: =PRODUCT(B12*30) -> 83460 | H12: =SUM(F12:G12) -> 1836120
A13: PLANCHE | B13: 3381 | C13: 1180 | E13: =PRODUCT(B13*C13) -> 3989580 | F13: =PRODUCT(E13*18)/118 -> 608580 | G13: =PRODUCT(B13*20) -> 67620 | H13: =SUM(F13:G13) -> 676200
A14: GEREVERIYA | C14: 1180 | E14: =PRODUCT(B14*C14) -> 0 | F14: =PRODUCT(E14*18)/118 -> 0 | G14: =PRODUCT(B14*20) -> 0 | H14: =SUM(F14:G14) -> 0
A15: Other Timber for Difference Price
A16: NAME OF TIMBER | B16: No OF TIMBER | C16: P/U | D16: MSF | E16: TOTAL COST | F16: VAT | G16: MSF | H16: VTA+MST
A17: IBIPANDE | B17: 1681 | C17: 2950 | D17: 50 | E17: =PRODUCT(B17*C17) -> 4958950 | F17: =PRODUCT(E17*18)/118 -> 756450 | G17: =PRODUCT(B17*D17) -> 84050 | H17: =SUM(F17:G17) -> 840500
A18: IBIPANDE BYA PINUS | B18: 2536 | C18: 2360 | D18: 50 | E18: =PRODUCT(B18*C18) -> 5984960 | F18: =PRODUCT(E18*18)/118 -> 912960 | G18: =PRODUCT(B18*D18) -> 126800 | H18: =SUM(F18:G18) -> 1039760
A19: SIPURE | B19: 2000 | C19: 1180 | D19: 20 | E19: =PRODUCT(B19*C19) -> 2360000 | F19: =PRODUCT(E19*18)/118 -> 360000 | G19: =PRODUCT(B19*D19) -> 40000 | H19: =SUM(F19:G19) -> 400000
A20: SEDERERA | B20: 130 | C20: 1180 | D20: 20 | E20: =PRODUCT(B20*C20) -> 153400 | F20: =PRODUCT(E20*18)/118 -> 23400 | G20: =PRODUCT(B20*D20) -> 2600 | H20: =SUM(F20:G20) -> 26000
A21: DECHETS | B21: 220 | C21: 10000 | D21: 1500 | E21: =PRODUCT(B21*C21) -> 2200000 | F21: =PRODUCT(E21*18)/118 -> 335593.22 | G21: =PRODUCT(B21*D21) -> 330000 | H21: =SUM(F21:G21) -> 665593.22
A22: DECHETS | E22: =PRODUCT(B22*C22) -> 0 | F22: =PRODUCT(E22*18)/118 -> 0 | G22: =PRODUCT(B22*D22) -> 0 | H22: =SUM(F22:G22) -> 0
A23: OTHER | E23: =PRODUCT(B23*C23) -> 0 | F23: =PRODUCT(E23*18)/118 -> 0 | G23: =PRODUCT(B23*D23) -> 0 | H23: =SUM(F23:G23) -> 0
A24: OTHER | E24: =PRODUCT(B24*C24) -> 0 | F24: =PRODUCT(E24*18)/118 -> 0 | G24: =PRODUCT(B24*D24) -> 0 | H24: =SUM(F24:G24) -> 0
A25: OTHER | E25: =PRODUCT(B25*C25) -> 0 | F25: =PRODUCT(E25*18)/118 -> 0 | G25: =PRODUCT(B25*D25) -> 0 | H25: =SUM(F25:G25) -> 0
A26: OTHER | E26: =PRODUCT(B26*C26) -> 0 | F26: =PRODUCT(E26*18)/118 -> 0 | G26: =PRODUCT(B26*D26) -> 0 | H26: =SUM(F26:G26) -> 0
A27: OTHER | E27: =PRODUCT(B27*C27) -> 0 | F27: =PRODUCT(E27*18)/118 -> 0 | G27: =PRODUCT(B27*D27) -> 0 | H27: =SUM(F27:G27) -> 0
A28: OTHER | E28: =PRODUCT(B28*C28) -> 0 | F28: =PRODUCT(E28*18)/118 -> 0 | G28: =PRODUCT(B28*D28) -> 0 | H28: =SUM(F28:G28) -> 0
A29: OTHER | E29: =PRODUCT(B29*C29) -> 0 | F29: =PRODUCT(E29*18)/118 -> 0 | G29: =PRODUCT(B29*D29) -> 0 | H29: =SUM(F29:G29) -> 0
A30: OTHER | E30: =PRODUCT(B30*C30) -> 0 | F30: =PRODUCT(E30*18)/118 -> 0 | G30: =PRODUCT(B30*D30) -> 0 | H30: =SUM(F30:G30) -> 0
A31: OTHER | E31: =PRODUCT(B31*C31) -> 0 | F31: =PRODUCT(E31*18)/118 -> 0 | G31: =PRODUCT(B31*D31) -> 0 | H31: =SUM(F31:G31) -> 0
A32: OTHER | E32: =PRODUCT(B32*C32) -> 0 | F32: =PRODUCT(E32*18)/118 -> 0 | G32: =PRODUCT(B32*D32) -> 0 | H32: =SUM(F32:G32) -> 0
A33: OTHER | E33: =PRODUCT(B33*C33) -> 0 | F33: =PRODUCT(E33*18)/118 -> 0 | G33: =PRODUCT(B33*D33) -> 0 | H33: =SUM(F33:G33) -> 0
... A36: OTHER | E36: =PRODUCT(B36*C36) -> 0 | F36: =PRODUCT(E36*18)/118 -> 0 | G36: =PRODUCT(B36*D36) -> 0 | H36: =SUM(F36:G36) -> 0
A37: TOTALY | E37: =SUM(E5:E36) -> 92457770 | F37: =SUM(F5:F36) -> 14103728 | G37: =SUM(G5:G36) -> 1453620 | H37: =SUM(H5:H36) -> 15557348
A38: SUMMARY | C38: RWF | E38: NAME | G38: Phone | H38: RWF
A39: TOTAL RWF PAID ON MOMO PAY
A40: TOTAL RWF PAID ON CASH
A41: AMOUNT NOT INVOICED
A42: TOTAL RWF DEPPOSITED ON BANK
A43: MEMBERSHIP FEES REGISTRETION
A44: MEMBERSHIP FEES CONTRIBUTION
A45: TOTAL INCOME | C45: =SUM(C39+C40+C41+C42+C43+C44) -> 0
A46: TIMBER SUMMARY
A48: REPORT SUMMARY | C48: TIMBER TYPE | E48: NUMBER OF QUANTITY
C49: INTURUSU | E49: =SUM(B9:B12) -> 25120
C50: PINUS | E50: =SUM(B6:B8) -> 979
C51: PALNCHE | E51: =SUM(B13:B14) -> 3381
C52: IBIPANDE | E52: =SUM(B17:B18) -> 4217
C53: UMUSAVE | E53: =SUM(B19:B20) -> 2130
C54: OTHER | E54: =B29 -> 0
C55: OTHER | E55: =B30 -> 0
C56: OTHER | E56: =B31 -> 0
C57: OTHER | E57: =B32 -> 0
C58: OTHER | E58: =B33 -> 0
C59: OTHER | E59: =B34 -> 0
C60: OTHER | E60: =B35 -> 0
C61: OTHER | E61: =B36 -> 0
C62: TOTAL TIMBER | E62: =SUM(E49:H61) -> 35827

Sheet NYAMAGABE
A1: QUANTITY REPORT
A3: MONTHLY REPORT OF MAY 2026
A5: NAME OF TIMBER | B5: No OF TIMBER | C5: PRICE OF TIMBER | E5: TOTAL COST | F5: TVA | G5: MSF | H5: TVA+MSF
A6: PINUS NINI | E6: =PRODUCT(B6*C6) -> 0 | F6: =PRODUCT(E6*18)/118 -> 0 | G6: =PRODUCT(B6*50) -> 0 | H6: =SUM(F6:G6) -> 0
A7: PINUS NTOYA | C7: 7000 | E7: =PRODUCT(B7*C7) -> 0 | F7: =PRODUCT(E7*18)/118 -> 0 | G7: =PRODUCT(B7*50) -> 0 | H7: =SUM(F7:G7) -> 0
A8: PINUS | C8: 8260 | E8: =PRODUCT(B8*C8) -> 0 | F8: =PRODUCT(E8*18)/118 -> 0 | G8: =PRODUCT(B8*50) -> 0 | H8: =SUM(F8:G8) -> 0
A9: MADIRIYE NINI | E9: =PRODUCT(B9*C9) -> 0 | F9: =PRODUCT(E9*18)/118 -> 0 | G9: =PRODUCT(B9*30) -> 0 | H9: =SUM(F9:G9) -> 0
A10: MADIRIYE NTOYA | C10: 2360 | E10: =PRODUCT(B10*C10) -> 0 | F10: =PRODUCT(E10*18)/118 -> 0 | G10: =PRODUCT(B10*30) -> 0 | H10: =SUM(F10:G10) -> 0
A11: MADRIEN | E11: =PRODUCT(B11*C11) -> 0 | F11: =PRODUCT(E11*18)/118 -> 0 | G11: =PRODUCT(B11*30) -> 0 | H11: =SUM(F11:G11) -> 0
A12: MADRIEN | E12: =PRODUCT(B12*C12) -> 0 | F12: =PRODUCT(E12*18)/118 -> 0 | G12: =PRODUCT(B12*30) -> 0 | H12: =SUM(F12:G12) -> 0
A13: PLANCHE | C13: 1180 | E13: =PRODUCT(B13*C13) -> 0 | F13: =PRODUCT(E13*18)/118 -> 0 | G13: =PRODUCT(B13*20) -> 0 | H13: =SUM(F13:G13) -> 0
A14: PLANCHE | E14: =PRODUCT(B14*C14) -> 0 | F14: =PRODUCT(E14*18)/118 -> 0 | G14: =PRODUCT(B14*20) -> 0 | H14: =SUM(F14:G14) -> 0
A15: Other Timber for Difference Price
A16: NAME OF TIMBER | B16: No OF TIMBER | C16: P/U | D16: MSF | E16: TOTAL COST | F16: VAT | G16: MSF | H16: VTA+MST
A17: IBIPANDE BYA PINUS | D17: 50 | E17: =PRODUCT(B17*C17) -> 0 | F17: =PRODUCT(E17*18)/118 -> 0 | G17: =PRODUCT(B17*D17) -> 0 | H17: =SUM(F17:G17) -> 0
A18: IBIPANDE BYA PINUS | D18: 50 | E18: =PRODUCT(B18*C18) -> 0 | F18: =PRODUCT(E18*18)/118 -> 0 | G18: =PRODUCT(B18*D18) -> 0 | H18: =SUM(F18:G18) -> 0
A19: UMUSAVE | E19: =PRODUCT(B19*C19) -> 0 | F19: =PRODUCT(E19*18)/118 -> 0 | G19: =PRODUCT(B19*D19) -> 0 | H19: =SUM(F19:G19) -> 0
A20: UMUSAVE | E20: =PRODUCT(B20*C20) -> 0 | F20: =PRODUCT(E20*18)/118 -> 0 | G20: =PRODUCT(B20*D20) -> 0 | H20: =SUM(F20:G20) -> 0
A21: OTHER | E21: =PRODUCT(B21*C21) -> 0 | F21: =PRODUCT(E21*18)/118 -> 0 | G21: =PRODUCT(B21*D21) -> 0 | H21: =SUM(F21:G21) -> 0
A22: OTHER | E22: =PRODUCT(B22*C22) -> 0 | F22: =PRODUCT(E22*18)/118 -> 0 | G22: =PRODUCT(B22*D22) -> 0 | H22: =SUM(F22:G22) -> 0
A23: OTHER | E23: =PRODUCT(B23*C23) -> 0 | F23: =PRODUCT(E23*18)/118 -> 0 | G23: =PRODUCT(B23*D23) -> 0 | H23: =SUM(F23:G23) -> 0
A24: OTHER | E24: =PRODUCT(B24*C24) -> 0 | F24: =PRODUCT(E24*18)/118 -> 0 | G24: =PRODUCT(B24*D24) -> 0 | H24: =SUM(F24:G24) -> 0
A25: OTHER | E25: =PRODUCT(B25*C25) -> 0 | F25: =PRODUCT(E25*18)/118 -> 0 | G25: =PRODUCT(B25*D25) -> 0 | H25: =SUM(F25:G25) -> 0
A26: OTHER | E26: =PRODUCT(B26*C26) -> 0 | F26: =PRODUCT(E26*18)/118 -> 0 | G26: =PRODUCT(B26*D26) -> 0 | H26: =SUM(F26:G26) -> 0
A27: OTHER | E27: =PRODUCT(B27*C27) -> 0 | F27: =PRODUCT(E27*18)/118 -> 0 | G27: =PRODUCT(B27*D27) -> 0 | H27: =SUM(F27:G27) -> 0
A28: OTHER | E28: =PRODUCT(B28*C28) -> 0 | F28: =PRODUCT(E28*18)/118 -> 0 | G28: =PRODUCT(B28*D28) -> 0 | H28: =SUM(F28:G28) -> 0
A29: OTHER | E29: =PRODUCT(B29*C29) -> 0 | F29: =PRODUCT(E29*18)/118 -> 0 | G29: =PRODUCT(B29*D29) -> 0 | H29: =SUM(F29:G29) -> 0
A30: OTHER | E30: =PRODUCT(B30*C30) -> 0 | F30: =PRODUCT(E30*18)/118 -> 0 | G30: =PRODUCT(B30*D30) -> 0 | H30: =SUM(F30:G30) -> 0
... A36: OTHER | E36: =PRODUCT(B36*C36) -> 0 | F36: =PRODUCT(E36*18)/118 -> 0 | G36: =PRODUCT(B36*D36) -> 0 | H36: =SUM(F36:G36) -> 0
A37: TOTALY | E37: =SUM(E5:E36) -> 0 | F37: =SUM(F5:F36) -> 0 | G37: =SUM(G5:G36) -> 0 | H37: =SUM(H5:H36) -> 0
A38: SUMMARY | C38: RWF | E38: NAME | G38: Phone | H38: RWF
A39: TOTAL RWF PAID ON MOMO PAY | C39: 316500
A40: TOTAL RWF PAID ON CASH
A41: AMOUNT NOT INVOICED
A42: TOTAL RWF DEPPOSITED ON BANK
A43: MEMBERSHIP FEES REGISTRETION
A44: MEMBERSHIP FEES CONTRIBUTION
A45: TOTAL INCOME | C45: =SUM(C39+C40+C41+C42+C43+C44) -> 316500
A46: TIMBER SUMMARY
A48: REPORT SUMMARY | C48: TIMBER TYPE | E48: NUMBER OF QUANTITY
C49: INTURUSU | E49: =SUM(B9:B12) -> 0
C50: PINUS | E50: =SUM(B6:B8) -> 0
C51: PALNCHE | E51: =SUM(B13:B14) -> 0
C52: IBIPANDE | E52: =SUM(B17:B18) -> 0
C53: UMUSAVE | E53: =SUM(B19:B20) -> 0
C54: OTHER | E54: =B29 -> 0
C55: OTHER | E55: =B30 -> 0
C56: OTHER | E56: =B31 -> 0
C57: OTHER | E57: =B32 -> 0
C58: OTHER | E58: =B33 -> 0
C59: OTHER | E59: =B34 -> 0
C60: OTHER | E60: =B35 -> 0
C61: OTHER | E61: =B36 -> 0
C62: TOTAL TIMBER | E62: =SUM(E49:H61) -> 0

Sheet KAYONZA
A1: QUANTITY REPORT
A3: MONTHLY REPORT OF MAY 2026
A5: NAME OF TIMBER | B5: No OF TIMBER | C5: PRICE OF TIMBER | E5: TOTAL COST | F5: TVA | G5: MSF | H5: TVA+MSF
A6: PINUS NINI | E6: =PRODUCT(B6*C6) -> 0 | F6: =PRODUCT(E6*18)/118 -> 0 | G6: =PRODUCT(B6*50) -> 0 | H6: =SUM(F6:G6) -> 0
A7: PINUS NTOYA | B7: 580 | C7: 5900 | E7: =PRODUCT(B7*C7) -> 3422000 | F7: =PRODUCT(E7*18)/118 -> 522000 | G7: =PRODUCT(B7*50) -> 29000 | H7: =SUM(F7:G7) -> 551000
A8: PINUS | E8: =PRODUCT(B8*C8) -> 0 | F8: =PRODUCT(E8*18)/118 -> 0 | G8: =PRODUCT(B8*50) -> 0 | H8: =SUM(F8:G8) -> 0
A9: MADIRIYE NINI | E9: =PRODUCT(B9*C9) -> 0 | F9: =PRODUCT(E9*18)/118 -> 0 | G9: =PRODUCT(B9*30) -> 0 | H9: =SUM(F9:G9) -> 0
A10: MADIRIYE NTOYA | E10: =PRODUCT(B10*C10) -> 0 | F10: =PRODUCT(E10*18)/118 -> 0 | G10: =PRODUCT(B10*30) -> 0 | H10: =SUM(F10:G10) -> 0
A11: MADRIEN | B11: 19315 | C11: 2124 | E11: =PRODUCT(B11*C11) -> 41025060 | F11: =PRODUCT(E11*18)/118 -> 6258060 | G11: =PRODUCT(B11*30) -> 579450 | H11: =SUM(F11:G11) -> 6837510
A12: MADRIEN | E12: =PRODUCT(B12*C12) -> 0 | F12: =PRODUCT(E12*18)/118 -> 0 | G12: =PRODUCT(B12*30) -> 0 | H12: =SUM(F12:G12) -> 0
A13: PLANCHE | B13: 3310 | C13: 1357 | E13: =PRODUCT(B13*C13) -> 4491670 | F13: =PRODUCT(E13*18)/118 -> 685170 | G13: =PRODUCT(B13*20) -> 66200 | H13: =SUM(F13:G13) -> 751370
A14: PLANCHE | E14: =PRODUCT(B14*C14) -> 0 | F14: =PRODUCT(E14*18)/118 -> 0 | G14: =PRODUCT(B14*20) -> 0 | H14: =SUM(F14:G14) -> 0
A15: Other Timber for Difference Price
A16: NAME OF TIMBER | B16: No OF TIMBER | C16: P/U | D16: MSF | E16: TOTAL COST | F16: VAT | G16: MSF | H16: VTA+MST
A17: IBIPANDE | B17: 2366 | C17: 1180 | D17: 20 | E17: =PRODUCT(B17*C17) -> 2791880 | F17: =PRODUCT(E17*18)/118 -> 425880 | G17: =PRODUCT(B17*D17) -> 47320 | H17: =SUM(F17:G17) -> 473200
A18: GEREVERIYA | D18: 20 | E18: =PRODUCT(B18*C18) -> 0 | F18: =PRODUCT(E18*18)/118 -> 0 | G18: =PRODUCT(B18*D18) -> 0 | H18: =SUM(F18:G18) -> 0
A19: UMUSAVE | D19: 200 | E19: =PRODUCT(B19*C19) -> 0 | F19: =PRODUCT(E19*18)/118 -> 0 | G19: =PRODUCT(B19*D19) -> 0 | H19: =SUM(F19:G19) -> 0
A20: IBIPANDE BYA SIPURE | D20: 354 | E20: =PRODUCT(B20*C20) -> 0 | F20: =PRODUCT(E20*18)/118 -> 0 | G20: =PRODUCT(B20*D20) -> 0 | H20: =SUM(F20:G20) -> 0
A21: OTHER | D21: 354 | E21: =PRODUCT(B21*C21) -> 0 | F21: =PRODUCT(E21*18)/118 -> 0 | G21: =PRODUCT(B21*D21) -> 0 | H21: =SUM(F21:G21) -> 0
A22: OTHER | D22: 30 | E22: =PRODUCT(B22*C22) -> 0 | F22: =PRODUCT(E22*18)/118 -> 0 | G22: =PRODUCT(B22*D22) -> 0 | H22: =SUM(F22:G22) -> 0
A23: OTHER | E23: =PRODUCT(B23*C23) -> 0 | F23: =PRODUCT(E23*18)/118 -> 0 | G23: =PRODUCT(B23*D23) -> 0 | H23: =SUM(F23:G23) -> 0
A24: OTHER | E24: =PRODUCT(B24*C24) -> 0 | F24: =PRODUCT(E24*18)/118 -> 0 | G24: =PRODUCT(B24*D24) -> 0 | H24: =SUM(F24:G24) -> 0
A25: OTHER | E25: =PRODUCT(B25*C25) -> 0 | F25: =PRODUCT(E25*18)/118 -> 0 | G25: =PRODUCT(B25*D25) -> 0 | H25: =SUM(F25:G25) -> 0
A26: OTHER | E26: =PRODUCT(B26*C26) -> 0 | F26: =PRODUCT(E26*18)/118 -> 0 | G26: =PRODUCT(B26*D26) -> 0 | H26: =SUM(F26:G26) -> 0
A27: OTHER | E27: =PRODUCT(B27*C27) -> 0 | F27: =PRODUCT(E27*18)/118 -> 0 | G27: =PRODUCT(B27*D27) -> 0 | H27: =SUM(F27:G27) -> 0
A28: OTHER | E28: =PRODUCT(B28*C28) -> 0 | F28: =PRODUCT(E28*18)/118 -> 0 | G28: =PRODUCT(B28*D28) -> 0 | H28: =SUM(F28:G28) -> 0
A29: OTHER | E29: =PRODUCT(B29*C29) -> 0 | F29: =PRODUCT(E29*18)/118 -> 0 | G29: =PRODUCT(B29*D29) -> 0 | H29: =SUM(F29:G29) -> 0
A30: OTHER | E30: =PRODUCT(B30*C30) -> 0 | F30: =PRODUCT(E30*18)/118 -> 0 | G30: =PRODUCT(B30*D30) -> 0 | H30: =SUM(F30:G30) -> 0
A31: OTHER | E31: =PRODUCT(B31*C31) -> 0 | F31: =PRODUCT(E31*18)/118 -> 0 | G31: =PRODUCT(B31*D31) -> 0 | H31: =SUM(F31:G31) -> 0
A32: OTHER | E32: =PRODUCT(B32*C32) -> 0 | F32: =PRODUCT(E32*18)/118 -> 0 | G32: =PRODUCT(B32*D32) -> 0 | H32: =SUM(F32:G32) -> 0
A33: OTHER | E33: =PRODUCT(B33*C33) -> 0 | F33: =PRODUCT(E33*18)/118 -> 0 | G33: =PRODUCT(B33*D33) -> 0 | H33: =SUM(F33:G33) -> 0
A34: OTHER | E34: =PRODUCT(B34*C34) -> 0 | F34: =PRODUCT(E34*18)/118 -> 0 | G34: =PRODUCT(B34*D34) -> 0 | H34: =SUM(F34:G34) -> 0
... A36: OTHER | E36: =PRODUCT(B36*C36) -> 0 | F36: =PRODUCT(E36*18)/118 -> 0 | G36: =PRODUCT(B36*D36) -> 0 | H36: =SUM(F36:G36) -> 0
A37: TOTALY | E37: =SUM(E5:E36) -> 51730610 | F37: =SUM(F5:F36) -> 7891110 | G37: =SUM(G5:G36) -> 721970 | H37: =SUM(H5:H36) -> 8613080
A38: SUMMARY | C38: RWF | E38: NAME | G38: Phone | H38: RWF
A39: TOTAL RWF PAID ON MOMO PAY | C39: 8926280
A40: TOTAL RWF PAID ON CASH
A41: AMOUNT NOT INVOICED
A42: TOTAL RWF DEPPOSITED ON BANK
A43: MEMBERSHIP FEES REGISTRETION
A44: MEMBERSHIP FEES CONTRIBUTION
A45: TOTAL INCOME | C45: =SUM(C39+C40+C41+C42+C43+C44) -> 8926280
A46: TIMBER SUMMARY
A48: REPORT SUMMARY | C48: TIMBER TYPE | E48: NUMBER OF QUANTITY
C49: INTURUSU | E49: =SUM(B9:B12) -> 19315
C50: PINUS | E50: =SUM(B6:B8) -> 580
C51: PALNCHE | E51: =SUM(B13:B14) -> 3310
C52: IBIPANDE | E52: =SUM(B17:B18) -> 2366
C53: UMUSAVE | E53: =SUM(B19:B20) -> 0
C54: OTHER | E54: =B29 -> 0
C55: OTHER | E55: =B30 -> 0
C56: OTHER | E56: =B31 -> 0
C57: OTHER | E57: =B32 -> 0
C58: OTHER | E58: =B33 -> 0
C59: OTHER | E59: =B34 -> 0
C60: OTHER | E60: =B35 -> 0
C61: OTHER | E61: =B36 -> 0
C62: TOTAL TIMBER | E62: =SUM(E49:H61) -> 25571

Sheet RUHANGO
A1: QUANTITY REPORT
A3: MONTHLY REPORT OF MAY 2026
A5: NAME OF TIMBER | B5: No OF TIMBER | C5: PRICE OF TIMBER | E5: TOTAL COST | F5: TVA | G5: MSF | H5: TVA+MSF
A6: PINUS NINI | E6: =PRODUCT(B6*C6) -> 0 | F6: =PRODUCT(E6*18)/118 -> 0 | G6: =PRODUCT(B6*50) -> 0 | H6: =SUM(F6:G6) -> 0
A7: PINUS NTOYA | E7: =PRODUCT(B7*C7) -> 0 | F7: =PRODUCT(E7*18)/118 -> 0 | G7: =PRODUCT(B7*50) -> 0 | H7: =SUM(F7:G7) -> 0
A8: PINUS | E8: =PRODUCT(B8*C8) -> 0 | F8: =PRODUCT(E8*18)/118 -> 0 | G8: =PRODUCT(B8*50) -> 0 | H8: =SUM(F8:G8) -> 0
A9: MADIRIYE NINI | B9: 700 | C9: 2300 | E9: =PRODUCT(B9*C9) -> 1610000 | F9: =PRODUCT(E9*18)/118 -> 245593.22 | G9: =PRODUCT(B9*30) -> 21000 | H9: =SUM(F9:G9) -> 266593.22
A10: MADIRIYE NTOYA | B10: 5320 | C10: 1800 | E10: =PRODUCT(B10*C10) -> 9576000 | F10: =PRODUCT(E10*18)/118 -> 1460745.8 | G10: =PRODUCT(B10*30) -> 159600 | H10: =SUM(F10:G10) -> 1620345.8
A11: MADRIEN | B11: 200 | C11: 2500 | E11: =PRODUCT(B11*C11) -> 500000 | F11: =PRODUCT(E11*18)/118 -> 76271.186 | G11: =PRODUCT(B11*30) -> 6000 | H11: =SUM(F11:G11) -> 82271.186
A12: MADRIEN | E12: =PRODUCT(B12*C12) -> 0 | F12: =PRODUCT(E12*18)/118 -> 0 | G12: =PRODUCT(B12*30) -> 0 | H12: =SUM(F12:G12) -> 0
A13: PLANCHE | B13: 100 | C13: 1200 | E13: =PRODUCT(B13*C13) -> 120000 | F13: =PRODUCT(E13*18)/118 -> 18305.085 | G13: =PRODUCT(B13*20) -> 2000 | H13: =SUM(F13:G13) -> 20305.085
A14: PLANCHE | E14: =PRODUCT(B14*C14) -> 0 | F14: =PRODUCT(E14*18)/118 -> 0 | G14: =PRODUCT(B14*20) -> 0 | H14: =SUM(F14:G14) -> 0
A15: Other Timber for Difference Price
A16: NAME OF TIMBER | B16: No OF TIMBER | C16: P/U | D16: MSF | E16: TOTAL COST | F16: VAT | G16: MSF | H16: VTA+MST
A17: IBIPANDE | B17: 400 | C17: 800 | D17: 20 | E17: =PRODUCT(B17*C17) -> 320000 | F17: =PRODUCT(E17*18)/118 -> 48813.559 | G17: =PRODUCT(B17*D17) -> 8000 | H17: =SUM(F17:G17) -> 56813.559
A18: IBIPANDE | E18: =PRODUCT(B18*C18) -> 0 | F18: =PRODUCT(E18*18)/118 -> 0 | G18: =PRODUCT(B18*D18) -> 0 | H18: =SUM(F18:G18) -> 0
A19: UMUSAVE | E19: =PRODUCT(B19*C19) -> 0 | F19: =PRODUCT(E19*18)/118 -> 0 | G19: =PRODUCT(B19*D19) -> 0 | H19: =SUM(F19:G19) -> 0
A20: UMUSAVE | E20: =PRODUCT(B20*C20) -> 0 | F20: =PRODUCT(E20*18)/118 -> 0 | G20: =PRODUCT(B20*D20) -> 0 | H20: =SUM(F20:G20) -> 0
A21: OTHER | B21: 7964 | D21: 50 | E21: =PRODUCT(B21*C21) -> 0 | F21: =PRODUCT(E21*18)/118 -> 0 | G21: =PRODUCT(B21*D21) -> 398200 | H21: =SUM(F21:G21) -> 398200
A22: OTHER | E22: =PRODUCT(B22*C22) -> 0 | F22: =PRODUCT(E22*18)/118 -> 0 | G22: =PRODUCT(B22*D22) -> 0 | H22: =SUM(F22:G22) -> 0
A23: OTHER | E23: =PRODUCT(B23*C23) -> 0 | F23: =PRODUCT(E23*18)/118 -> 0 | G23: =PRODUCT(B23*D23) -> 0 | H23: =SUM(F23:G23) -> 0
A24: OTHER | E24: =PRODUCT(B24*C24) -> 0 | F24: =PRODUCT(E24*18)/118 -> 0 | G24: =PRODUCT(B24*D24) -> 0 | H24: =SUM(F24:G24) -> 0
A25: OTHER | E25: =PRODUCT(B25*C25) -> 0 | F25: =PRODUCT(E25*18)/118 -> 0 | G25: =PRODUCT(B25*D25) -> 0 | H25: =SUM(F25:G25) -> 0
A26: OTHER | E26: =PRODUCT(B26*C26) -> 0 | F26: =PRODUCT(E26*18)/118 -> 0 | G26: =PRODUCT(B26*D26) -> 0 | H26: =SUM(F26:G26) -> 0
A27: OTHER | E27: =PRODUCT(B27*C27) -> 0 | F27: =PRODUCT(E27*18)/118 -> 0 | G27: =PRODUCT(B27*D27) -> 0 | H27: =SUM(F27:G27) -> 0
A28: OTHER | E28: =PRODUCT(B28*C28) -> 0 | F28: =PRODUCT(E28*18)/118 -> 0 | G28: =PRODUCT(B28*D28) -> 0 | H28: =SUM(F28:G28) -> 0
A29: OTHER | E29: =PRODUCT(B29*C29) -> 0 | F29: =PRODUCT(E29*18)/118 -> 0 | G29: =PRODUCT(B29*D29) -> 0 | H29: =SUM(F29:G29) -> 0
A30: OTHER | E30: =PRODUCT(B30*C30) -> 0 | F30: =PRODUCT(E30*18)/118 -> 0 | G30: =PRODUCT(B30*D30) -> 0 | H30: =SUM(F30:G30) -> 0
A31: OTHER | E31: =PRODUCT(B31*C31) -> 0 | F31: =PRODUCT(E31*18)/118 -> 0 | G31: =PRODUCT(B31*D31) -> 0 | H31: =SUM(F31:G31) -> 0
A32: OTHER | E32: =PRODUCT(B32*C32) -> 0 | F32: =PRODUCT(E32*18)/118 -> 0 | G32: =PRODUCT(B32*D32) -> 0 | H32: =SUM(F32:G32) -> 0
A33: OTHER | E33: =PRODUCT(B33*C33) -> 0 | F33: =PRODUCT(E33*18)/118 -> 0 | G33: =PRODUCT(B33*D33) -> 0 | H33: =SUM(F33:G33) -> 0
... A36: OTHER | E36: =PRODUCT(B36*C36) -> 0 | F36: =PRODUCT(E36*18)/118 -> 0 | G36: =PRODUCT(B36*D36) -> 0 | H36: =SUM(F36:G36) -> 0
A37: TOTALY | E37: =SUM(E5:E36) -> 12126000 | F37: =SUM(F5:F36) -> 1849728.8 | G37: =SUM(G5:G36) -> 594800 | H37: =SUM(H5:H36) -> 2444528.8
A38: SUMMARY | C38: RWF | E38: NAME | G38: Phone | H38: RWF
A39: TOTAL RWF PAID ON MOMO PAY | C39: 2444529
A40: TOTAL RWF PAID ON CASH
A41: AMOUNT NOT INVOICED
A42: TOTAL RWF DEPPOSITED ON BANK
A43: MEMBERSHIP FEES REGISTRETION
A44: MEMBERSHIP FEES CONTRIBUTION
A45: TOTAL INCOME | C45: =SUM(C39+C40+C41+C42+C43+C44) -> 2444529
A46: TIMBER SUMMARY
A48: REPORT SUMMARY | C48: TIMBER TYPE | E48: NUMBER OF QUANTITY
C49: INTURUSU | E49: =SUM(B9:B12) -> 6220
C50: PINUS | E50: =SUM(B6:B8) -> 0
C51: PALNCHE | E51: =SUM(B13:B14) -> 100
C52: IBIPANDE | E52: =SUM(B17:B18) -> 400
C53: UMUSAVE | E53: =SUM(B19:B20) -> 0
C54: OTHER | E54: =B29 -> 0
C55: OTHER | E55: =B30 -> 0
C56: OTHER | E56: =B31 -> 0
C57: OTHER | E57: =B32 -> 0
C58: OTHER | E58: =B33 -> 0
C59: OTHER | E59: =B34 -> 0
C60: OTHER | E60: =B35 -> 0
C61: OTHER | E61: =B36 -> 0
C62: TOTAL TIMBER | E62: =SUM(E49:H61) -> 6720

Sheet KARONGI
A1: QUANTITY REPORT
A3: MONTHLY REPORT OF MAY 2026
A5: NAME OF TIMBER | B5: No OF TIMBER | C5: PRICE OF TIMBER | E5: TOTAL COST | F5: TVA | G5: MSF | H5: TVA+MSF
A6: PINUS NINI | B6: 130 | C6: 7080 | E6: =PRODUCT(B6*C6) -> 920400 | F6: =PRODUCT(E6*18)/118 -> 140400 | G6: =PRODUCT(B6*50) -> 6500 | H6: =SUM(F6:G6) -> 146900
A7: PINUS NTOYA | B7: 250 | C7: 7000 | E7: =PRODUCT(B7*C7) -> 1750000 | F7: =PRODUCT(E7*18)/118 -> 266949.15 | G7: =PRODUCT(B7*50) -> 12500 | H7: =SUM(F7:G7) -> 279449.15
A8: PINUS | B8: 300 | C8: 6000 | E8: =PRODUCT(B8*C8) -> 1800000 | F8: =PRODUCT(E8*18)/118 -> 274576.27 | G8: =PRODUCT(B8*50) -> 15000 | H8: =SUM(F8:G8) -> 289576.27
A9: MADIRIYE NINI | E9: =PRODUCT(B9*C9) -> 0 | F9: =PRODUCT(E9*18)/118 -> 0 | G9: =PRODUCT(B9*30) -> 0 | H9: =SUM(F9:G9) -> 0
A10: MADIRIYE NTOYA | B10: 8057 | C10: 2124 | E10: =PRODUCT(B10*C10) -> 17113068 | F10: =PRODUCT(E10*18)/118 -> 2610468 | G10: =PRODUCT(B10*30) -> 241710 | H10: =SUM(F10:G10) -> 2852178
A11: MADRIEN | E11: =PRODUCT(B11*C11) -> 0 | F11: =PRODUCT(E11*18)/118 -> 0 | G11: =PRODUCT(B11*30) -> 0 | H11: =SUM(F11:G11) -> 0
A12: MADRIEN | E12: =PRODUCT(B12*C12) -> 0 | F12: =PRODUCT(E12*18)/118 -> 0 | G12: =PRODUCT(B12*30) -> 0 | H12: =SUM(F12:G12) -> 0
A13: PLANCHE | B13: 595 | C13: 1200 | E13: =PRODUCT(B13*C13) -> 714000 | F13: =PRODUCT(E13*18)/118 -> 108915.25 | G13: =PRODUCT(B13*20) -> 11900 | H13: =SUM(F13:G13) -> 120815.25
A14: PLANCHE | E14: =PRODUCT(B14*C14) -> 0 | F14: =PRODUCT(E14*18)/118 -> 0 | G14: =PRODUCT(B14*20) -> 0 | H14: =SUM(F14:G14) -> 0
A15: Other Timber for Difference Price
A16: NAME OF TIMBER | B16: No OF TIMBER | C16: P/U | D16: MSF | E16: TOTAL COST | F16: VAT | G16: MSF | H16: VTA+MST
A17: PINUS | D17: 50 | E17: =PRODUCT(B17*C17) -> 0 | F17: =PRODUCT(E17*18)/118 -> 0 | G17: =PRODUCT(B17*D17) -> 0 | H17: =SUM(F17:G17) -> 0
A18: UMUSAVE | D18: 50 | E18: =PRODUCT(B18*C18) -> 0 | F18: =PRODUCT(E18*18)/118 -> 0 | G18: =PRODUCT(B18*D18) -> 0 | H18: =SUM(F18:G18) -> 0
A19: PLANCHE ZA GEREVERIYA | D19: 20 | E19: =PRODUCT(B19*C19) -> 0 | F19: =PRODUCT(E19*18)/118 -> 0 | G19: =PRODUCT(B19*D19) -> 0 | H19: =SUM(F19:G19) -> 0
A20: PALCNHE ZA PINUS | D20: 266 | E20: =PRODUCT(B20*C20) -> 0 | F20: =PRODUCT(E20*18)/118 -> 0 | G20: =PRODUCT(B20*D20) -> 0 | H20: =SUM(F20:G20) -> 0
A21: MADRIEN | D21: 354 | E21: =PRODUCT(B21*C21) -> 0 | F21: =PRODUCT(E21*18)/118 -> 0 | G21: =PRODUCT(B21*D21) -> 0 | H21: =SUM(F21:G21) -> 0
A22: OTHER | B22: 145 | C22: 2000 | D22: 50 | E22: =PRODUCT(B22*C22) -> 290000 | F22: =PRODUCT(E22*18)/118 -> 44237.288 | G22: =PRODUCT(B22*D22) -> 7250 | H22: =SUM(F22:G22) -> 51487.288
A23: OTHER | B23: 150 | C23: 2500 | D23: 50 | E23: =PRODUCT(B23*C23) -> 375000 | F23: =PRODUCT(E23*18)/118 -> 57203.39 | G23: =PRODUCT(B23*D23) -> 7500 | H23: =SUM(F23:G23) -> 64703.39
A24: OTHER | B24: 300 | C24: 900 | D24: 50 | E24: =PRODUCT(B24*C24) -> 270000 | F24: =PRODUCT(E24*18)/118 -> 41186.441 | G24: =PRODUCT(B24*D24) -> 15000 | H24: =SUM(F24:G24) -> 56186.441
A25: OTHER | B25: 456 | D25: 266 | E25: =PRODUCT(B25*C25) -> 0 | F25: =PRODUCT(E25*18)/118 -> 0 | G25: =PRODUCT(B25*D25) -> 121296 | H25: =SUM(F25:G25) -> 121296
A26: OTHER | B26: 3 | D26: 200 | E26: =PRODUCT(B26*C26) -> 0 | F26: =PRODUCT(E26*18)/118 -> 0 | G26: =PRODUCT(B26*D26) -> 600 | H26: =SUM(F26:G26) -> 600
A27: OTHER | B27: 168 | D27: 354 | E27: =PRODUCT(B27*C27) -> 0 | F27: =PRODUCT(E27*18)/118 -> 0 | G27: =PRODUCT(B27*D27) -> 59472 | H27: =SUM(F27:G27) -> 59472
A28: OTHER | B28: 7725 | C28: 1416 | D28: 50 | E28: =PRODUCT(B28*C28) -> 10938600 | F28: =PRODUCT(E28*18)/118 -> 1668600 | G28: =PRODUCT(B28*D28) -> 386250 | H28: =SUM(F28:G28) -> 2054850
A29: OTHER | E29: =PRODUCT(B29*C29) -> 0 | F29: =PRODUCT(E29*18)/118 -> 0 | G29: =PRODUCT(B29*D29) -> 0 | H29: =SUM(F29:G29) -> 0
A30: OTHER | E30: =PRODUCT(B30*C30) -> 0 | F30: =PRODUCT(E30*18)/118 -> 0 | G30: =PRODUCT(B30*D30) -> 0 | H30: =SUM(F30:G30) -> 0
A31: OTHER | E31: =PRODUCT(B31*C31) -> 0 | F31: =PRODUCT(E31*18)/118 -> 0 | G31: =PRODUCT(B31*D31) -> 0 | H31: =SUM(F31:G31) -> 0
A32: OTHER | E32: =PRODUCT(B32*C32) -> 0 | F32: =PRODUCT(E32*18)/118 -> 0 | G32: =PRODUCT(B32*D32) -> 0 | H32: =SUM(F32:G32) -> 0
A33: OTHER | E33: =PRODUCT(B33*C33) -> 0 | F33: =PRODUCT(E33*18)/118 -> 0 | G33: =PRODUCT(B33*D33) -> 0 | H33: =SUM(F33:G33) -> 0
A34: OTHER | E34: =PRODUCT(B34*C34) -> 0 | F34: =PRODUCT(E34*18)/118 -> 0 | G34: =PRODUCT(B34*D34) -> 0 | H34: =SUM(F34:G34) -> 0
A35: OTHER | E35: =PRODUCT(B35*C35) -> 0 | F35: =PRODUCT(E35*18)/118 -> 0 | G35: =PRODUCT(B35*D35) -> 0 | H35: =SUM(F35:G35) -> 0
A36: OTHER | E36: =PRODUCT(B36*C36) -> 0 | F36: =PRODUCT(E36*18)/118 -> 0 | G36: =PRODUCT(B36*D36) -> 0 | H36: =SUM(F36:G36) -> 0
A37: TOTALY | E37: =SUM(E5:E36) -> 34171068 | F37: =SUM(F5:F36) -> 5212535.8 | G37: =SUM(G5:G36) -> 884978 | H37: =SUM(H5:H36) -> 6097513.8
A38: SUMMARY | C38: RWF | E38: NAME | G38: Phone | H38: RWF
A39: TOTAL RWF PAID ON MOMO PAY | C39: 6097514
A40: TOTAL RWF PAID ON CASH
A41: AMOUNT NOT INVOICED
A42: TOTAL RWF DEPPOSITED ON BANK | C42: 645430
A43: MEMBERSHIP FEES REGISTRETION
A44: MEMBERSHIP FEES CONTRIBUTION
A45: TOTAL INCOME | C45: =SUM(C39+C40+C41+C42+C43+C44) -> 6742944
A46: TIMBER SUMMARY
A48: REPORT SUMMARY | C48: TIMBER TYPE | E48: NUMBER OF QUANTITY
C49: INTURUSU | E49: =SUM(B9:B12) -> 8057
C50: PINUS | E50: =SUM(B6:B8) -> 680
C51: PALNCHE | E51: =SUM(B13:B14) -> 595
C52: IBIPANDE | E52: =SUM(B17:B18) -> 0
C53: UMUSAVE | E53: =SUM(B19:B20) -> 0
C54: OTHER | E54: =B29 -> 0
C55: OTHER | E55: =B30 -> 0
C56: OTHER | E56: =B31 -> 0
C57: OTHER | E57: =B32 -> 0
C58: OTHER | E58: =B33 -> 0
C59: OTHER | E59: =B34 -> 0
C60: OTHER | E60: =B35 -> 0
C61: OTHER | E61: =B36 -> 0
C62: TOTAL TIMBER | E62: =SUM(E49:H61) -> 9332

Sheet RUSIZI
A1: QUANTITY REPORT
A3: MONTHLY REPORT OF MAY 2026
A5: NAME OF TIMBER | B5: No OF TIMBER | C5: PRICE OF TIMBER | E5: TOTAL COST | F5: TVA | G5: MSF | H5: TVA+MSF
A6: PINUS NINI | B6: 70 | C6: 8000 | E6: =PRODUCT(B6*C6) -> 560000 | F6: =PRODUCT(E6*18)/118 -> 85423.729 | G6: =PRODUCT(B6*50) -> 3500 | H6: =SUM(F6:G6) -> 88923.729
A7: IBIPANDE BYA PINUS | E7: =PRODUCT(B7*C7) -> 0 | F7: =PRODUCT(E7*18)/118 -> 0 | G7: =PRODUCT(B7*50) -> 0 | H7: =SUM(F7:G7) -> 0
A8: PINUS | E8: =PRODUCT(B8*C8) -> 0 | F8: =PRODUCT(E8*18)/118 -> 0 | G8: =PRODUCT(B8*50) -> 0 | H8: =SUM(F8:G8) -> 0
A9: MADIRIYE NINI | E9: =PRODUCT(B9*C9) -> 0 | F9: =PRODUCT(E9*18)/118 -> 0 | G9: =PRODUCT(B9*30) -> 0 | H9: =SUM(F9:G9) -> 0
A10: MADIRIYE NTOYA | E10: =PRODUCT(B10*C10) -> 0 | F10: =PRODUCT(E10*18)/118 -> 0 | G10: =PRODUCT(B10*30) -> 0 | H10: =SUM(F10:G10) -> 0
A11: MADRIEN | B11: 500 | C11: 2500 | E11: =PRODUCT(B11*C11) -> 1250000 | F11: =PRODUCT(E11*18)/118 -> 190677.97 | G11: =PRODUCT(B11*30) -> 15000 | H11: =SUM(F11:G11) -> 205677.97
A12: MADRIEN | E12: =PRODUCT(B12*C12) -> 0 | F12: =PRODUCT(E12*18)/118 -> 0 | G12: =PRODUCT(B12*30) -> 0 | H12: =SUM(F12:G12) -> 0
A13: PLANCHE | E13: =PRODUCT(B13*C13) -> 0 | F13: =PRODUCT(E13*18)/118 -> 0 | G13: =PRODUCT(B13*20) -> 0 | H13: =SUM(F13:G13) -> 0
A14: PLANCHE | E14: =PRODUCT(B14*C14) -> 0 | F14: =PRODUCT(E14*18)/118 -> 0 | G14: =PRODUCT(B14*20) -> 0 | H14: =SUM(F14:G14) -> 0
A15: Other Timber for Difference Price
A16: NAME OF TIMBER | B16: No OF TIMBER | C16: P/U | D16: MSF | E16: TOTAL COST | F16: VAT | G16: MSF | H16: VTA+MST
A17: PINUS | C17: 8000 | D17: 50 | E17: =PRODUCT(B17*C17) -> 0 | F17: =PRODUCT(E17*18)/118 -> 0 | G17: =PRODUCT(B17*D17) -> 0 | H17: =SUM(F17:G17) -> 0
A18: PINUS | B18: 90 | C18: 2300 | D18: 30 | E18: =PRODUCT(B18*C18) -> 207000 | F18: =PRODUCT(E18*18)/118 -> 31576.271 | G18: =PRODUCT(B18*D18) -> 2700 | H18: =SUM(F18:G18) -> 34276.271
A19: INTURUSU | C19: 2124 | D19: 30 | E19: =PRODUCT(B19*C19) -> 0 | F19: =PRODUCT(E19*18)/118 -> 0 | G19: =PRODUCT(B19*D19) -> 0 | H19: =SUM(F19:G19) -> 0
A20: MADRIEN | B20: 9579 | C20: 2124 | D20: 40 | E20: =PRODUCT(B20*C20) -> 20345796 | F20: =PRODUCT(E20*18)/118 -> 3103596 | G20: =PRODUCT(B20*D20) -> 383160 | H20: =SUM(F20:G20) -> 3486756
A21: PLANCHE NINI | B21: 2795 | C21: 1357 | D21: 30 | E21: =PRODUCT(B21*C21) -> 3792815 | F21: =PRODUCT(E21*18)/118 -> 578565 | G21: =PRODUCT(B21*D21) -> 83850 | H21: =SUM(F21:G21) -> 662415
A22: PLANCHE | B22: 2775 | C22: 1357 | D22: 20 | E22: =PRODUCT(B22*C22) -> 3765675 | F22: =PRODUCT(E22*18)/118 -> 574425 | G22: =PRODUCT(B22*D22) -> 55500 | H22: =SUM(F22:G22) -> 629925
A23: SIPURE | B23: 285 | C23: 1000 | D23: 40 | E23: =PRODUCT(B23*C23) -> 285000 | F23: =PRODUCT(E23*18)/118 -> 43474.576 | G23: =PRODUCT(B23*D23) -> 11400 | H23: =SUM(F23:G23) -> 54874.576
A24: CADELAMA | B24: 80 | C24: 2500 | D24: 40 | E24: =PRODUCT(B24*C24) -> 200000 | F24: =PRODUCT(E24*18)/118 -> 30508.475 | G24: =PRODUCT(B24*D24) -> 3200 | H24: =SUM(F24:G24) -> 33708.475
A25: PLANCHE | B25: 80 | C25: 1700 | D25: 30 | E25: =PRODUCT(B25*C25) -> 136000 | F25: =PRODUCT(E25*18)/118 -> 20745.763 | G25: =PRODUCT(B25*D25) -> 2400 | H25: =SUM(F25:G25) -> 23145.763
A26: UMUSAVE | B26: 450 | C26: 1500 | D26: 40 | E26: =PRODUCT(B26*C26) -> 675000 | F26: =PRODUCT(E26*18)/118 -> 102966.1 | G26: =PRODUCT(B26*D26) -> 18000 | H26: =SUM(F26:G26) -> 120966.1
A27: OTHER | B27: 4617 | D27: 100 | E27: =PRODUCT(B27*C27) -> 0 | F27: =PRODUCT(E27*18)/118 -> 0 | G27: =PRODUCT(B27*D27) -> 461700 | H27: =SUM(F27:G27) -> 461700
A28: OTHER | E28: =PRODUCT(B28*C28) -> 0 | F28: =PRODUCT(E28*18)/118 -> 0 | G28: =PRODUCT(B28*D28) -> 0 | H28: =SUM(F28:G28) -> 0
A29: OTHER | E29: =PRODUCT(B29*C29) -> 0 | F29: =PRODUCT(E29*18)/118 -> 0 | G29: =PRODUCT(B29*D29) -> 0 | H29: =SUM(F29:G29) -> 0
A30: OTHER | E30: =PRODUCT(B30*C30) -> 0 | F30: =PRODUCT(E30*18)/118 -> 0 | G30: =PRODUCT(B30*D30) -> 0 | H30: =SUM(F30:G30) -> 0
A31: OTHER | E31: =PRODUCT(B31*C31) -> 0 | F31: =PRODUCT(E31*18)/118 -> 0 | G31: =PRODUCT(B31*D31) -> 0 | H31: =SUM(F31:G31) -> 0
A32: OTHER | E32: =PRODUCT(B32*C32) -> 0 | F32: =PRODUCT(E32*18)/118 -> 0 | G32: =PRODUCT(B32*D32) -> 0 | H32: =SUM(F32:G32) -> 0
A33: OTHER | E33: =PRODUCT(B33*C33) -> 0 | F33: =PRODUCT(E33*18)/118 -> 0 | G33: =PRODUCT(B33*D33) -> 0 | H33: =SUM(F33:G33) -> 0
A34: OTHER | E34: =PRODUCT(B34*C34) -> 0 | F34: =PRODUCT(E34*18)/118 -> 0 | G34: =PRODUCT(B34*D34) -> 0 | H34: =SUM(F34:G34) -> 0
A35: OTHER | E35: =PRODUCT(B35*C35) -> 0 | F35: =PRODUCT(E35*18)/118 -> 0 | G35: =PRODUCT(B35*D35) -> 0 | H35: =SUM(F35:G35) -> 0
A36: OTHER | E36: =PRODUCT(B36*C36) -> 0 | F36: =PRODUCT(E36*18)/118 -> 0 | G36: =PRODUCT(B36*D36) -> 0 | H36: =SUM(F36:G36) -> 0
A37: TOTALY | E37: =SUM(E5:E36) -> 31217286 | F37: =SUM(F5:F36) -> 4761958.9 | G37: =SUM(G5:G36) -> 1040410 | H37: =SUM(H5:H36) -> 5802368.9
A38: SUMMARY | C38: RWF | E38: NAME | G38: Phone | H38: RWF
A39: TOTAL RWF PAID ON MOMO PAY | C39: 5802369
A40: TOTAL RWF PAID ON CASH
A41: AMOUNT NOT INVOICED
A42: TOTAL RWF DEPPOSITED ON BANK
A43: MEMBERSHIP FEES REGISTRETION
A44: MEMBERSHIP FEES CONTRIBUTION
A45: TOTAL INCOME | C45: =SUM(C39+C40+C41+C42+C43+C44) -> 5802369
A46: TIMBER SUMMARY
A48: REPORT SUMMARY | C48: TIMBER TYPE | E48: NUMBER OF QUANTITY
C49: INTURUSU | E49: =SUM(B9:B12) -> 500
C50: PINUS | E50: =SUM(B6:B8) -> 70
C51: PALNCHE | E51: =SUM(B13:B14) -> 0
C52: IBIPANDE | E52: =SUM(B17:B18) -> 90
C53: UMUSAVE | E53: =SUM(B19:B20) -> 9579
C54: OTHER | E54: =B29 -> 0
C55: OTHER | E55: =B30 -> 0
C56: OTHER | E56: =B31 -> 0
C57: OTHER | E57: =B32 -> 0
C58: OTHER | E58: =B33 -> 0
C59: OTHER | E59: =B34 -> 0
C60: OTHER | E60: =B35 -> 0
C61: OTHER | E61: =B36 -> 0
C62: TOTAL TIMBER | E62: =SUM(E49:H61) -> 10239

Sheet RUBAVU
A1: QUANTITY REPORT
A3: MONTHLY REPORT OF MAY 2026
A5: NAME OF TIMBER | B5: No OF TIMBER | C5: PRICE OF TIMBER | E5: TOTAL COST | F5: TVA | G5: MSF | H5: TVA+MSF
A6: PINUS NINI | B6: 1002 | C6: 8850 | E6: =PRODUCT(B6*C6) -> 8867700 | F6: =PRODUCT(E6*18)/118 -> 1352700 | G6: =PRODUCT(B6*50) -> 50100 | H6: =SUM(F6:G6) -> 1402800
A7: PINUS | C7: 2360 | E7: =PRODUCT(B7*C7) -> 0 | F7: =PRODUCT(E7*18)/118 -> 0 | G7: =PRODUCT(B7*50) -> 0 | H7: =SUM(F7:G7) -> 0
A8: PINUS | E8: =PRODUCT(B8*C8) -> 0 | F8: =PRODUCT(E8*18)/118 -> 0 | G8: =PRODUCT(B8*50) -> 0 | H8: =SUM(F8:G8) -> 0
A9: MADIRIYE NINI | E9: =PRODUCT(B9*C9) -> 0 | F9: =PRODUCT(E9*18)/118 -> 0 | G9: =PRODUCT(B9*30) -> 0 | H9: =SUM(F9:G9) -> 0
A10: MADIRIYE NTOYA | B10: 29357 | C10: 2360 | E10: =PRODUCT(B10*C10) -> 69282520 | F10: =PRODUCT(E10*18)/118 -> 10568520 | G10: =PRODUCT(B10*30) -> 880710 | H10: =SUM(F10:G10) -> 11449230
A11: MADRIEN | E11: =PRODUCT(B11*C11) -> 0 | F11: =PRODUCT(E11*18)/118 -> 0 | G11: =PRODUCT(B11*30) -> 0 | H11: =SUM(F11:G11) -> 0
A12: MADRIEN | E12: =PRODUCT(B12*C12) -> 0 | F12: =PRODUCT(E12*18)/118 -> 0 | G12: =PRODUCT(B12*30) -> 0 | H12: =SUM(F12:G12) -> 0
A13: PLANCHE | B13: 3257 | C13: 1534 | E13: =PRODUCT(B13*C13) -> 4996238 | F13: =PRODUCT(E13*18)/118 -> 762138 | G13: =PRODUCT(B13*20) -> 65140 | H13: =SUM(F13:G13) -> 827278
A14: PLANCHE ZA PINUS | B14: 300 | C14: 1770 | E14: =PRODUCT(B14*C14) -> 531000 | F14: =PRODUCT(E14*18)/118 -> 81000 | G14: =PRODUCT(B14*20) -> 6000 | H14: =SUM(F14:G14) -> 87000
A15: Other Timber for Difference Price
A16: NAME OF TIMBER | B16: No OF TIMBER | C16: P/U | D16: MSF | E16: TOTAL COST | F16: VAT | G16: MSF | H16: VTA+MST
A17: IBIPANDE BYA PINUS | B17: 1877 | C17: 1770 | D17: 50 | E17: =PRODUCT(B17*C17) -> 3322290 | F17: =PRODUCT(E17*18)/118 -> 506790 | G17: =PRODUCT(B17*D17) -> 93850 | H17: =SUM(F17:G17) -> 600640
A18: MADRIEN | B18: 513 | D18: 390 | E18: =PRODUCT(B18*C18) -> 0 | F18: =PRODUCT(E18*18)/118 -> 0 | G18: =PRODUCT(B18*D18) -> 200070 | H18: =SUM(F18:G18) -> 200070
A19: IBIPANDE BYA PINUS | B19: 1500 | C19: 2360 | D19: 50 | E19: =PRODUCT(B19*C19) -> 3540000 | F19: =PRODUCT(E19*18)/118 -> 540000 | G19: =PRODUCT(B19*D19) -> 75000 | H19: =SUM(F19:G19) -> 615000
A20: PLANCHE Z'IBIPANDE | B20: 450 | C20: 1180 | D20: 20 | E20: =PRODUCT(B20*C20) -> 531000 | F20: =PRODUCT(E20*18)/118 -> 81000 | G20: =PRODUCT(B20*D20) -> 9000 | H20: =SUM(F20:G20) -> 90000
A21: PLANCHE | B21: 2 | D21: 254 | E21: =PRODUCT(B21*C21) -> 0 | F21: =PRODUCT(E21*18)/118 -> 0 | G21: =PRODUCT(B21*D21) -> 508 | H21: =SUM(F21:G21) -> 508
A22: IMBABARI | B22: 10 | C22: 11800 | D22: 1000 | E22: =PRODUCT(B22*C22) -> 118000 | F22: =PRODUCT(E22*18)/118 -> 18000 | G22: =PRODUCT(B22*D22) -> 10000 | H22: =SUM(F22:G22) -> 28000
A23: IBIPANDE BYA PINUS | B23: 147 | D23: 320 | E23: =PRODUCT(B23*C23) -> 0 | F23: =PRODUCT(E23*18)/118 -> 0 | G23: =PRODUCT(B23*D23) -> 47040 | H23: =SUM(F23:G23) -> 47040
A24: OTHER | E24: =PRODUCT(B24*C24) -> 0 | F24: =PRODUCT(E24*18)/118 -> 0 | G24: =PRODUCT(B24*D24) -> 0 | H24: =SUM(F24:G24) -> 0
A25: OTHER | E25: =PRODUCT(B25*C25) -> 0 | F25: =PRODUCT(E25*18)/118 -> 0 | G25: =PRODUCT(B25*D25) -> 0 | H25: =SUM(F25:G25) -> 0
A26: OTHER | E26: =PRODUCT(B26*C26) -> 0 | F26: =PRODUCT(E26*18)/118 -> 0 | G26: =PRODUCT(B26*D26) -> 0 | H26: =SUM(F26:G26) -> 0
A27: OTHER | E27: =PRODUCT(B27*C27) -> 0 | F27: =PRODUCT(E27*18)/118 -> 0 | G27: =PRODUCT(B27*D27) -> 0 | H27: =SUM(F27:G27) -> 0
A28: OTHER | E28: =PRODUCT(B28*C28) -> 0 | F28: =PRODUCT(E28*18)/118 -> 0 | G28: =PRODUCT(B28*D28) -> 0 | H28: =SUM(F28:G28) -> 0
A29: OTHER | E29: =PRODUCT(B29*C29) -> 0 | F29: =PRODUCT(E29*18)/118 -> 0 | G29: =PRODUCT(B29*D29) -> 0 | H29: =SUM(F29:G29) -> 0
A30: OTHER | E30: =PRODUCT(B30*C30) -> 0 | F30: =PRODUCT(E30*18)/118 -> 0 | G30: =PRODUCT(B30*D30) -> 0 | H30: =SUM(F30:G30) -> 0
A31: OTHER | E31: =PRODUCT(B31*C31) -> 0 | F31: =PRODUCT(E31*18)/118 -> 0 | G31: =PRODUCT(B31*D31) -> 0 | H31: =SUM(F31:G31) -> 0
A32: OTHER | E32: =PRODUCT(B32*C32) -> 0 | F32: =PRODUCT(E32*18)/118 -> 0 | G32: =PRODUCT(B32*D32) -> 0 | H32: =SUM(F32:G32) -> 0
A33: OTHER | E33: =PRODUCT(B33*C33) -> 0 | F33: =PRODUCT(E33*18)/118 -> 0 | G33: =PRODUCT(B33*D33) -> 0 | H33: =SUM(F33:G33) -> 0
A34: OTHER | E34: =PRODUCT(B34*C34) -> 0 | F34: =PRODUCT(E34*18)/118 -> 0 | G34: =PRODUCT(B34*D34) -> 0 | H34: =SUM(F34:G34) -> 0
A35: OTHER | E35: =PRODUCT(B35*C35) -> 0 | F35: =PRODUCT(E35*18)/118 -> 0 | G35: =PRODUCT(B35*D35) -> 0 | H35: =SUM(F35:G35) -> 0
A36: OTHER | E36: =PRODUCT(B36*C36) -> 0 | F36: =PRODUCT(E36*18)/118 -> 0 | G36: =PRODUCT(B36*D36) -> 0 | H36: =SUM(F36:G36) -> 0
A37: TOTALY | E37: =SUM(E5:E36) -> 91188748 | F37: =SUM(F5:F36) -> 13910148 | G37: =SUM(G5:G36) -> 1437418 | H37: =SUM(H5:H36) -> 15347566
A38: SUMMARY | C38: RWF | E38: NAME | G38: Phone | H38: RWF
A39: TOTAL RWF PAID ON MOMO PAY | C39: 14347566
A40: TOTAL RWF PAID ON CASH
A41: AMOUNT NOT INVOICED
A42: TOTAL RWF DEPPOSITED ON BANK | C42: 1000000
A43: MEMBERSHIP FEES REGISTRETION
A44: MEMBERSHIP FEES CONTRIBUTION
A45: TOTAL INCOME | C45: =SUM(C39+C40+C41+C42+C43+C44) -> 15347566
A46: TIMBER SUMMARY
A48: REPORT SUMMARY | C48: TIMBER TYPE | E48: NUMBER OF QUANTITY
C49: INTURUSU | E49: =SUM(B9:B12) -> 29357
C50: PINUS | E50: =SUM(B6:B8) -> 1002
C51: PALNCHE | E51: =SUM(B13:B14) -> 3557
C52: IBIPANDE | E52: =SUM(B17:B18) -> 2390
C53: UMUSAVE | E53: =SUM(B19:B20) -> 1950
C54: OTHER | E54: =B29 -> 0
C55: OTHER | E55: =B30 -> 0
C56: OTHER | E56: =B31 -> 0
C57: OTHER | E57: =B32 -> 0
C58: OTHER | E58: =B33 -> 0
C59: OTHER | E59: =B34 -> 0
C60: OTHER | E60: =B35 -> 0
C61: OTHER | E61: =B36 -> 0
C62: TOTAL TIMBER | E62: =SUM(E49:H61) -> 38256

Sheet MUSANZE
A1: QUANTITY REPORT
A3: MONTHLY REPORT OF MAY 2026
A5: NAME OF TIMBER | B5: No OF TIMBER | C5: PRICE OF TIMBER | E5: TOTAL COST | F5: TVA | G5: MSF | H5: TVA+MSF
A6: PINUS NINI | B6: 815 | C6: 8850 | E6: =PRODUCT(B6*C6) -> 7212750 | F6: =PRODUCT(E6*18)/118 -> 1100250 | G6: =PRODUCT(B6*50) -> 40750 | H6: =SUM(F6:G6) -> 1141000
A7: PINUS NTOYA | B7: 6000 | C7: 1300 | E7: =PRODUCT(B7*C7) -> 7800000 | F7: =PRODUCT(E7*18)/118 -> 1189830.5 | G7: =PRODUCT(B7*50) -> 300000 | H7: =SUM(F7:G7) -> 1489830.5
A8: IBIPANDE BYA PINUS | B8: 6 | C8: 60000 | E8: =PRODUCT(B8*C8) -> 360000 | F8: =PRODUCT(E8*18)/118 -> 54915.254 | G8: =PRODUCT(B8*50) -> 300 | H8: =SUM(F8:G8) -> 55215.254
A9: MADIRIYE NINI | B9: 40 | C9: 4700 | E9: =PRODUCT(B9*C9) -> 188000 | F9: =PRODUCT(E9*18)/118 -> 28677.966 | G9: =PRODUCT(B9*30) -> 1200 | H9: =SUM(F9:G9) -> 29877.966
A10: MADIRIYE NTOYA | B10: 18130 | C10: 2124 | E10: =PRODUCT(B10*C10) -> 38508120 | F10: =PRODUCT(E10*18)/118 -> 5874120 | G10: =PRODUCT(B10*30) -> 543900 | H10: =SUM(F10:G10) -> 6418020
A11: MADRIEN | B11: 20 | C11: 4500 | E11: =PRODUCT(B11*C11) -> 90000 | F11: =PRODUCT(E11*18)/118 -> 13728.814 | G11: =PRODUCT(B11*30) -> 600 | H11: =SUM(F11:G11) -> 14328.814
A12: MADRIEN | E12: =PRODUCT(B12*C12) -> 0 | F12: =PRODUCT(E12*18)/118 -> 0 | G12: =PRODUCT(B12*30) -> 0 | H12: =SUM(F12:G12) -> 0
A13: PLANCHE | B13: 3090 | C13: 944 | E13: =PRODUCT(B13*C13) -> 2916960 | F13: =PRODUCT(E13*18)/118 -> 444960 | G13: =PRODUCT(B13*20) -> 61800 | H13: =SUM(F13:G13) -> 506760
A14: GEREVERIYA | B14: 3114 | C14: 1180 | E14: =PRODUCT(B14*C14) -> 3674520 | F14: =PRODUCT(E14*18)/118 -> 560520 | G14: =PRODUCT(B14*20) -> 62280 | H14: =SUM(F14:G14) -> 622800
A15: Other Timber for Difference Price
A16: NAME OF TIMBER | B16: No OF TIMBER | C16: P/U | D16: MSF | E16: TOTAL COST | F16: VAT | G16: MSF | H16: VTA+MST
A17: IBIPANDE | B17: 1120 | C17: 2360 | D17: 25 | E17: =PRODUCT(B17*C17) -> 2643200 | F17: =PRODUCT(E17*18)/118 -> 403200 | G17: =PRODUCT(B17*D17) -> 28000 | H17: =SUM(F17:G17) -> 431200
A18: IBIPANDE BITOYA | B18: 2510 | C18: 1770 | D18: 25 | E18: =PRODUCT(B18*C18) -> 4442700 | F18: =PRODUCT(E18*18)/118 -> 677700 | G18: =PRODUCT(B18*D18) -> 62750 | H18: =SUM(F18:G18) -> 740450
A19: PLANCHE | B19: 10 | C19: 2500 | D19: 20 | E19: =PRODUCT(B19*C19) -> 25000 | F19: =PRODUCT(E19*18)/118 -> 3813.5593 | G19: =PRODUCT(B19*D19) -> 200 | H19: =SUM(F19:G19) -> 4013.5593
A20: UMUSAVE | C20: 60000 | D20: 50 | E20: =PRODUCT(B20*C20) -> 0 | F20: =PRODUCT(E20*18)/118 -> 0 | G20: =PRODUCT(B20*D20) -> 0 | H20: =SUM(F20:G20) -> 0
A21: GEREVERIYA | C21: 1180 | D21: 20 | E21: =PRODUCT(B21*C21) -> 0 | F21: =PRODUCT(E21*18)/118 -> 0 | G21: =PRODUCT(B21*D21) -> 0 | H21: =SUM(F21:G21) -> 0
A22: MADRIEN NTOYA | B22: 230 | C22: 1180 | D22: 20 | E22: =PRODUCT(B22*C22) -> 271400 | F22: =PRODUCT(E22*18)/118 -> 41400 | G22: =PRODUCT(B22*D22) -> 4600 | H22: =SUM(F22:G22) -> 46000
A23: IBIPANDE | B23: 2360 | C23: 1000 | D23: 25 | E23: =PRODUCT(B23*C23) -> 2360000 | F23: =PRODUCT(E23*18)/118 -> 360000 | G23: =PRODUCT(B23*D23) -> 59000 | H23: =SUM(F23:G23) -> 419000
A24: IBIPANDE | B24: 2360 | C24: 570 | D24: 25 | E24: =PRODUCT(B24*C24) -> 1345200 | F24: =PRODUCT(E24*18)/118 -> 205200 | G24: =PRODUCT(B24*D24) -> 59000 | H24: =SUM(F24:G24) -> 264200
A25: OTHER | B25: 1 | D25: 16800 | E25: =PRODUCT(B25*C25) -> 0 | F25: =PRODUCT(E25*18)/118 -> 0 | G25: =PRODUCT(B25*D25) -> 16800 | H25: =SUM(F25:G25) -> 16800
A26: OTHER | B26: 1 | D26: 44466 | E26: =PRODUCT(B26*C26) -> 0 | F26: =PRODUCT(E26*18)/118 -> 0 | G26: =PRODUCT(B26*D26) -> 44466 | H26: =SUM(F26:G26) -> 44466
A27: OTHER | B27: 1 | D27: 14400 | E27: =PRODUCT(B27*C27) -> 0 | F27: =PRODUCT(E27*18)/118 -> 0 | G27: =PRODUCT(B27*D27) -> 14400 | H27: =SUM(F27:G27) -> 14400
A28: OTHER | E28: =PRODUCT(B28*C28) -> 0 | F28: =PRODUCT(E28*18)/118 -> 0 | G28: =PRODUCT(B28*D28) -> 0 | H28: =SUM(F28:G28) -> 0
A29: OTHER | E29: =PRODUCT(B29*C29) -> 0 | F29: =PRODUCT(E29*18)/118 -> 0 | G29: =PRODUCT(B29*D29) -> 0 | H29: =SUM(F29:G29) -> 0
A30: OTHER | E30: =PRODUCT(B30*C30) -> 0 | F30: =PRODUCT(E30*18)/118 -> 0 | G30: =PRODUCT(B30*D30) -> 0 | H30: =SUM(F30:G30) -> 0
A31: OTHER | E31: =PRODUCT(B31*C31) -> 0 | F31: =PRODUCT(E31*18)/118 -> 0 | G31: =PRODUCT(B31*D31) -> 0 | H31: =SUM(F31:G31) -> 0
A32: OTHER | E32: =PRODUCT(B32*C32) -> 0 | F32: =PRODUCT(E32*18)/118 -> 0 | G32: =PRODUCT(B32*D32) -> 0 | H32: =SUM(F32:G32) -> 0
A33: OTHER | E33: =PRODUCT(B33*C33) -> 0 | F33: =PRODUCT(E33*18)/118 -> 0 | G33: =PRODUCT(B33*D33) -> 0 | H33: =SUM(F33:G33) -> 0
A34: OTHER | E34: =PRODUCT(B34*C34) -> 0 | F34: =PRODUCT(E34*18)/118 -> 0 | G34: =PRODUCT(B34*D34) -> 0 | H34: =SUM(F34:G34) -> 0
A35: OTHER | E35: =PRODUCT(B35*C35) -> 0 | F35: =PRODUCT(E35*18)/118 -> 0 | G35: =PRODUCT(B35*D35) -> 0 | H35: =SUM(F35:G35) -> 0
A36: OTHER | E36: =PRODUCT(B36*C36) -> 0 | F36: =PRODUCT(E36*18)/118 -> 0 | G36: =PRODUCT(B36*D36) -> 0 | H36: =SUM(F36:G36) -> 0
A37: TOTALY | E37: =SUM(E5:E36) -> 71837850 | F37: =SUM(F5:F36) -> 10958316 | G37: =SUM(G5:G36) -> 1300046 | H37: =SUM(H5:H36) -> 12258362
A38: SUMMARY | C38: RWF | E38: NAME | G38: Phone | H38: RWF
A39: TOTAL RWF PAID ON MOMO PAY | C39: 8700743
A40: TOTAL RWF PAID ON CASH | C40: 3557619
A41: AMOUNT NOT INVOICED
A42: TOTAL RWF DEPPOSITED ON BANK
A43: MEMBERSHIP FEES REGISTRETION
A44: MEMBERSHIP FEES CONTRIBUTION
A45: TOTAL INCOME | C45: =SUM(C39+C40+C41+C42+C43+C44) -> 12258362
A46: TIMBER SUMMARY
A48: REPORT SUMMARY | C48: TIMBER TYPE | E48: NUMBER OF QUANTITY
C49: INTURUSU | E49: =SUM(B9:B12) -> 18190
C50: PINUS | E50: =SUM(B6:B8) -> 6821
C51: PALNCHE | E51: =SUM(B13:B14) -> 6204
C52: IBIPANDE | E52: =SUM(B17:B18) -> 3630
C53: UMUSAVE | E53: =SUM(B19:B20) -> 10
C54: OTHER | E54: =B29 -> 0
C55: OTHER | E55: =B30 -> 0
C56: OTHER | E56: =B31 -> 0
C57: OTHER | E57: =B32 -> 0
C58: OTHER | E58: =B33 -> 0
C59: OTHER | E59: =B34 -> 0
C60: OTHER | E60: =B35 -> 0
C61: OTHER | E61: =B36 -> 0
C62: TOTAL TIMBER | E62: =SUM(E49:H61) -> 34855

Sheet NYAGATARE
A1: QUANTITY REPORT
A3: MONTHLY REPORT OF MAY 2026
A5: NAME OF TIMBER | B5: No OF TIMBER | C5: PRICE OF TIMBER | E5: TOTAL COST | F5: TVA | G5: MSF | H5: TVA+MSF
A6: PINUS NINI | E6: =PRODUCT(B6*C6) -> 0 | F6: =PRODUCT(E6*18)/118 -> 0 | G6: =PRODUCT(B6*50) -> 0 | H6: =SUM(F6:G6) -> 0
A7: PINUS NTOYA | E7: =PRODUCT(B7*C7) -> 0 | F7: =PRODUCT(E7*18)/118 -> 0 | G7: =PRODUCT(B7*50) -> 0 | H7: =SUM(F7:G7) -> 0
A8: PINUS | E8: =PRODUCT(B8*C8) -> 0 | F8: =PRODUCT(E8*18)/118 -> 0 | G8: =PRODUCT(B8*50) -> 0 | H8: =SUM(F8:G8) -> 0
A9: MADIRIYE NINI | E9: =PRODUCT(B9*C9) -> 0 | F9: =PRODUCT(E9*18)/118 -> 0 | G9: =PRODUCT(B9*30) -> 0 | H9: =SUM(F9:G9) -> 0
A10: MADIRIYE NTOYA | E10: =PRODUCT(B10*C10) -> 0 | F10: =PRODUCT(E10*18)/118 -> 0 | G10: =PRODUCT(B10*30) -> 0 | H10: =SUM(F10:G10) -> 0
A11: MADRIEN | E11: =PRODUCT(B11*C11) -> 0 | F11: =PRODUCT(E11*18)/118 -> 0 | G11: =PRODUCT(B11*30) -> 0 | H11: =SUM(F11:G11) -> 0
A12: MADRIEN | E12: =PRODUCT(B12*C12) -> 0 | F12: =PRODUCT(E12*18)/118 -> 0 | G12: =PRODUCT(B12*30) -> 0 | H12: =SUM(F12:G12) -> 0
A13: PLANCHE | E13: =PRODUCT(B13*C13) -> 0 | F13: =PRODUCT(E13*18)/118 -> 0 | G13: =PRODUCT(B13*20) -> 0 | H13: =SUM(F13:G13) -> 0
A14: PLANCHE | E14: =PRODUCT(B14*C14) -> 0 | F14: =PRODUCT(E14*18)/118 -> 0 | G14: =PRODUCT(B14*20) -> 0 | H14: =SUM(F14:G14) -> 0
A15: Other Timber for Difference Price
A16: NAME OF TIMBER | B16: No OF TIMBER | C16: P/U | D16: MSF | E16: TOTAL COST | F16: VAT | G16: MSF | H16: VTA+MST
A17: MADRIEN | B17: 500 | C17: 4800 | D17: 50 | E17: =PRODUCT(B17*C17) -> 2400000 | F17: =PRODUCT(E17*18)/118 -> 366101.69 | G17: =PRODUCT(B17*D17) -> 25000 | H17: =SUM(F17:G17) -> 391101.69
A18: MADRIEN | B18: 850 | C18: 4000 | D18: 50 | E18: =PRODUCT(B18*C18) -> 3400000 | F18: =PRODUCT(E18*18)/118 -> 518644.07 | G18: =PRODUCT(B18*D18) -> 42500 | H18: =SUM(F18:G18) -> 561144.07
A19: MADRIEN | B19: 2990 | C19: 3000 | D19: 50 | E19: =PRODUCT(B19*C19) -> 8970000 | F19: =PRODUCT(E19*18)/118 -> 1368305.1 | G19: =PRODUCT(B19*D19) -> 149500 | H19: =SUM(F19:G19) -> 1517805.1
A20: MADRIEN | B20: 1350 | C20: 2500 | D20: 50 | E20: =PRODUCT(B20*C20) -> 3375000 | F20: =PRODUCT(E20*18)/118 -> 514830.51 | G20: =PRODUCT(B20*D20) -> 67500 | H20: =SUM(F20:G20) -> 582330.51
A21: MADRIEN | B21: 5502 | C21: 2124 | D21: 50 | E21: =PRODUCT(B21*C21) -> 11686248 | F21: =PRODUCT(E21*18)/118 -> 1782648 | G21: =PRODUCT(B21*D21) -> 275100 | H21: =SUM(F21:G21) -> 2057748
A22: MADRIEN | B22: 410 | C22: 2000 | D22: 50 | E22: =PRODUCT(B22*C22) -> 820000 | F22: =PRODUCT(E22*18)/118 -> 125084.75 | G22: =PRODUCT(B22*D22) -> 20500 | H22: =SUM(F22:G22) -> 145584.75
A23: MADRIEN | B23: 180 | C23: 2200 | D23: 50 | E23: =PRODUCT(B23*C23) -> 396000 | F23: =PRODUCT(E23*18)/118 -> 60406.78 | G23: =PRODUCT(B23*D23) -> 9000 | H23: =SUM(F23:G23) -> 69406.78
A24: PLANCHE | B24: 300 | C24: 1357 | D24: 50 | E24: =PRODUCT(B24*C24) -> 407100 | F24: =PRODUCT(E24*18)/118 -> 62100 | G24: =PRODUCT(B24*D24) -> 15000 | H24: =SUM(F24:G24) -> 77100
A25: GEREVERIYA | B25: 510 | C25: 1180 | D25: 50 | E25: =PRODUCT(B25*C25) -> 601800 | F25: =PRODUCT(E25*18)/118 -> 91800 | G25: =PRODUCT(B25*D25) -> 25500 | H25: =SUM(F25:G25) -> 117300
A26: IBIPANDE BYA PINUS | B26: 120 | C26: 4500 | D26: 50 | E26: =PRODUCT(B26*C26) -> 540000 | F26: =PRODUCT(E26*18)/118 -> 82372.881 | G26: =PRODUCT(B26*D26) -> 6000 | H26: =SUM(F26:G26) -> 88372.881
A27: PLANCHE | B27: 70 | C27: 1180 | D27: 50 | E27: =PRODUCT(B27*C27) -> 82600 | F27: =PRODUCT(E27*18)/118 -> 12600 | G27: =PRODUCT(B27*D27) -> 3500 | H27: =SUM(F27:G27) -> 16100
A28: PLANCHE | B28: 21 | C28: 1000 | D28: 50 | E28: =PRODUCT(B28*C28) -> 21000 | F28: =PRODUCT(E28*18)/118 -> 3203.3898 | G28: =PRODUCT(B28*D28) -> 1050 | H28: =SUM(F28:G28) -> 4253.3898
... A30: IBIPANDE | B30: 100 | C30: 1180 | D30: 50 | E30: =PRODUCT(B30*C30) -> 118000 | F30: =PRODUCT(E30*18)/118 -> 18000 | G30: =PRODUCT(B30*D30) -> 5000 | H30: =SUM(F30:G30) -> 23000
A31: MADRIEN | B31: 8592 | D31: 50 | E31: =PRODUCT(B31*C31) -> 0 | F31: =PRODUCT(E31*18)/118 -> 0 | G31: =PRODUCT(B31*D31) -> 429600 | H31: =SUM(F31:G31) -> 429600
A32: OTHER | E32: =PRODUCT(B32*C32) -> 0 | F32: =PRODUCT(E32*18)/118 -> 0 | G32: =PRODUCT(B32*D32) -> 0 | H32: =SUM(F32:G32) -> 0
A33: OTHER | E33: =PRODUCT(B33*C33) -> 0 | F33: =PRODUCT(E33*18)/118 -> 0 | G33: =PRODUCT(B33*D33) -> 0 | H33: =SUM(F33:G33) -> 0
A34: OTHER | E34: =PRODUCT(B34*C34) -> 0 | F34: =PRODUCT(E34*18)/118 -> 0 | G34: =PRODUCT(B34*D34) -> 0 | H34: =SUM(F34:G34) -> 0
A35: OTHER | E35: =PRODUCT(B35*C35) -> 0 | F35: =PRODUCT(E35*18)/118 -> 0 | G35: =PRODUCT(B35*D35) -> 0 | H35: =SUM(F35:G35) -> 0
A36: OTHER | E36: =PRODUCT(B36*C36) -> 0 | F36: =PRODUCT(E36*18)/118 -> 0 | G36: =PRODUCT(B36*D36) -> 0 | H36: =SUM(F36:G36) -> 0
A37: TOTALY | E37: =SUM(E5:E36) -> 32937748 | F37: =SUM(F5:F36) -> 5024402.2 | G37: =SUM(G5:G36) -> 1076750 | H37: =SUM(H5:H36) -> 6101152.2
A38: SUMMARY | C38: RWF | E38: NAME | G38: Phone | H38: RWF
A39: TOTAL RWF PAID ON MOMO PAY
A40: TOTAL RWF PAID ON CASH
A41: AMOUNT NOT INVOICED
A42: TOTAL RWF DEPPOSITED ON BANK
A43: MEMBERSHIP FEES REGISTRETION
A44: MEMBERSHIP FEES CONTRIBUTION
A45: TOTAL INCOME | C45: =SUM(C39+C40+C41+C42+C43+C44) -> 0
A46: TIMBER SUMMARY
A48: REPORT SUMMARY | C48: TIMBER TYPE | E48: NUMBER OF QUANTITY
C49: INTURUSU | E49: =SUM(B9:B12) -> 0
C50: PINUS | E50: =SUM(B6:B8) -> 0
C51: PALNCHE | E51: =SUM(B13:B14) -> 0
C52: IBIPANDE | E52: =SUM(B17:B18) -> 1350
C53: UMUSAVE | E53: =SUM(B19:B20) -> 4340
C54: OTHER | E54: =B29 -> 40
C55: OTHER | E55: =B30 -> 100
C56: OTHER | E56: =B31 -> 8592
C57: OTHER | E57: =B32 -> 0
C58: OTHER | E58: =B33 -> 0
C59: OTHER | E59: =B34 -> 0
C60: OTHER | E60: =B35 -> 0
C61: OTHER | E61: =B36 -> 0
C62: TOTAL TIMBER | E62: =SUM(E49:H61) -> 14422

Sheet KIREHE
A1: QUANTITY REPORT
A3: MONTHLY REPORT OF MAY 2026
A5: NAME OF TIMBER | B5: No OF TIMBER | C5: PRICE OF TIMBER | E5: TOTAL COST | F5: TVA | G5: MSF | H5: TVA+MSF
A6: PINUS NINI | C6: 2600 | E6: =PRODUCT(B6*C6) -> 0 | F6: =PRODUCT(E6*18)/118 -> 0 | G6: =PRODUCT(B6*50) -> 0 | H6: =SUM(F6:G6) -> 0
A7: PINUS | C7: 3500 | E7: =PRODUCT(B7*C7) -> 0 | F7: =PRODUCT(E7*18)/118 -> 0 | G7: =PRODUCT(B7*50) -> 0 | H7: =SUM(F7:G7) -> 0
A8: PINUS | B8: 235 | C8: 7670 | E8: =PRODUCT(B8*C8) -> 1802450 | F8: =PRODUCT(E8*18)/118 -> 274950 | G8: =PRODUCT(B8*50) -> 11750 | H8: =SUM(F8:G8) -> 286700
A9: MADIRIYE NINI | E9: =PRODUCT(B9*C9) -> 0 | F9: =PRODUCT(E9*18)/118 -> 0 | G9: =PRODUCT(B9*30) -> 0 | H9: =SUM(F9:G9) -> 0
A10: MADIRIYE NTOYA | B10: 9470 | C10: 2124 | E10: =PRODUCT(B10*C10) -> 20114280 | F10: =PRODUCT(E10*18)/118 -> 3068280 | G10: =PRODUCT(B10*30) -> 284100 | H10: =SUM(F10:G10) -> 3352380
A11: MADRIEN | E11: =PRODUCT(B11*C11) -> 0 | F11: =PRODUCT(E11*18)/118 -> 0 | G11: =PRODUCT(B11*30) -> 0 | H11: =SUM(F11:G11) -> 0
A12: MADRIEN | E12: =PRODUCT(B12*C12) -> 0 | F12: =PRODUCT(E12*18)/118 -> 0 | G12: =PRODUCT(B12*30) -> 0 | H12: =SUM(F12:G12) -> 0
A13: PLANCHE | E13: =PRODUCT(B13*C13) -> 0 | F13: =PRODUCT(E13*18)/118 -> 0 | G13: =PRODUCT(B13*20) -> 0 | H13: =SUM(F13:G13) -> 0
A14: PLANCHE | E14: =PRODUCT(B14*C14) -> 0 | F14: =PRODUCT(E14*18)/118 -> 0 | G14: =PRODUCT(B14*20) -> 0 | H14: =SUM(F14:G14) -> 0
A15: Other Timber for Difference Price
A16: NAME OF TIMBER | B16: No OF TIMBER | C16: P/U | D16: MSF | E16: TOTAL COST | F16: VAT | G16: MSF | H16: VTA+MST
A17: IBIPANDE | B17: 1890 | C17: 1000 | D17: 30 | E17: =PRODUCT(B17*C17) -> 1890000 | F17: =PRODUCT(E17*18)/118 -> 288305.08 | G17: =PRODUCT(B17*D17) -> 56700 | H17: =SUM(F17:G17) -> 345005.08
A18: IBIPANDE | B18: 789 | C18: 3500 | D18: 30 | E18: =PRODUCT(B18*C18) -> 2761500 | F18: =PRODUCT(E18*18)/118 -> 421245.76 | G18: =PRODUCT(B18*D18) -> 23670 | H18: =SUM(F18:G18) -> 444915.76
A19: PLANCHE | B19: 1983 | C19: 1534 | D19: 30 | E19: =PRODUCT(B19*C19) -> 3041922 | F19: =PRODUCT(E19*18)/118 -> 464022 | G19: =PRODUCT(B19*D19) -> 59490 | H19: =SUM(F19:G19) -> 523512
A20: UMUSAVE | B20: 10 | C20: 1200 | D20: 30 | E20: =PRODUCT(B20*C20) -> 12000 | F20: =PRODUCT(E20*18)/118 -> 1830.5085 | G20: =PRODUCT(B20*D20) -> 300 | H20: =SUM(F20:G20) -> 2130.5085
A21: DECHET Z'INTURUSU | B21: 200 | C21: 1800 | D21: 30 | E21: =PRODUCT(B21*C21) -> 360000 | F21: =PRODUCT(E21*18)/118 -> 54915.254 | G21: =PRODUCT(B21*D21) -> 6000 | H21: =SUM(F21:G21) -> 60915.254
A22: IBIPANDE | B22: 1854 | C22: 1180 | D22: 30 | E22: =PRODUCT(B22*C22) -> 2187720 | F22: =PRODUCT(E22*18)/118 -> 333720 | G22: =PRODUCT(B22*D22) -> 55620 | H22: =SUM(F22:G22) -> 389340
A23: UMUSAVE | B23: 104 | C23: 1500 | D23: 30 | E23: =PRODUCT(B23*C23) -> 156000 | F23: =PRODUCT(E23*18)/118 -> 23796.61 | G23: =PRODUCT(B23*D23) -> 3120 | H23: =SUM(F23:G23) -> 26916.61
A24: IBIPANDE | B24: 530 | C24: 2600 | D24: 50 | E24: =PRODUCT(B24*C24) -> 1378000 | F24: =PRODUCT(E24*18)/118 -> 210203.39 | G24: =PRODUCT(B24*D24) -> 26500 | H24: =SUM(F24:G24) -> 236703.39
A25: MADRIEN | B25: 200 | C25: 2360 | D25: 30 | E25: =PRODUCT(B25*C25) -> 472000 | F25: =PRODUCT(E25*18)/118 -> 72000 | G25: =PRODUCT(B25*D25) -> 6000 | H25: =SUM(F25:G25) -> 78000
A26: OTHER | B26: 1 | C26: 1 | D26: 675666 | E26: =PRODUCT(B26*C26) -> 1 | F26: =PRODUCT(E26*18)/118 -> 0.15254237 | G26: =PRODUCT(B26*D26) -> 675666 | H26: =SUM(F26:G26) -> 675666.15
A27: OTHER | E27: =PRODUCT(B27*C27) -> 0 | F27: =PRODUCT(E27*18)/118 -> 0 | G27: =PRODUCT(B27*D27) -> 0 | H27: =SUM(F27:G27) -> 0
A28: OTHER | E28: =PRODUCT(B28*C28) -> 0 | F28: =PRODUCT(E28*18)/118 -> 0 | G28: =PRODUCT(B28*D28) -> 0 | H28: =SUM(F28:G28) -> 0
A29: OTHER | E29: =PRODUCT(B29*C29) -> 0 | F29: =PRODUCT(E29*18)/118 -> 0 | G29: =PRODUCT(B29*D29) -> 0 | H29: =SUM(F29:G29) -> 0
A30: OTHER | E30: =PRODUCT(B30*C30) -> 0 | F30: =PRODUCT(E30*18)/118 -> 0 | G30: =PRODUCT(B30*D30) -> 0 | H30: =SUM(F30:G30) -> 0
A31: OTHER | E31: =PRODUCT(B31*C31) -> 0 | F31: =PRODUCT(E31*18)/118 -> 0 | G31: =PRODUCT(B31*D31) -> 0 | H31: =SUM(F31:G31) -> 0
A32: OTHER | E32: =PRODUCT(B32*C32) -> 0 | F32: =PRODUCT(E32*18)/118 -> 0 | G32: =PRODUCT(B32*D32) -> 0 | H32: =SUM(F32:G32) -> 0
A33: OTHER | E33: =PRODUCT(B33*C33) -> 0 | F33: =PRODUCT(E33*18)/118 -> 0 | G33: =PRODUCT(B33*D33) -> 0 | H33: =SUM(F33:G33) -> 0
A34: OTHER | E34: =PRODUCT(B34*C34) -> 0 | F34: =PRODUCT(E34*18)/118 -> 0 | G34: =PRODUCT(B34*D34) -> 0 | H34: =SUM(F34:G34) -> 0
A35: OTHER | E35: =PRODUCT(B35*C35) -> 0 | F35: =PRODUCT(E35*18)/118 -> 0 | G35: =PRODUCT(B35*D35) -> 0 | H35: =SUM(F35:G35) -> 0
A36: OTHER | E36: =PRODUCT(B36*C36) -> 0 | F36: =PRODUCT(E36*18)/118 -> 0 | G36: =PRODUCT(B36*D36) -> 0 | H36: =SUM(F36:G36) -> 0
A37: TOTALY | E37: =SUM(E5:E36) -> 34175873 | F37: =SUM(F5:F36) -> 5213268.8 | G37: =SUM(G5:G36) -> 1208916 | H37: =SUM(H5:H36) -> 6422184.8
A38: SUMMARY | C38: RWF | E38: NAME | G38: Phone | H38: RWF
A39: TOTAL RWF PAID ON MOMO PAY | C39: 6422184.8
A40: TOTAL RWF PAID ON CASH
A41: AMOUNT NOT INVOICED
A42: TOTAL RWF DEPPOSITED ON BANK
A43: MEMBERSHIP FEES REGISTRETION
A44: MEMBERSHIP FEES CONTRIBUTION
A45: TOTAL INCOME | C45: =SUM(C39+C40+C41+C42+C43+C44) -> 6422184.8
A46: TIMBER SUMMARY
A48: REPORT SUMMARY | C48: TIMBER TYPE | E48: NUMBER OF QUANTITY
C49: INTURUSU | E49: =SUM(B9:B12) -> 9470
C50: PINUS | E50: =SUM(B6:B8) -> 235
C51: PALNCHE | E51: =SUM(B13:B14) -> 0
C52: IBIPANDE | E52: =SUM(B17:B18) -> 2679
C53: UMUSAVE | E53: =SUM(B19:B20) -> 1993
C54: OTHER | E54: =B29 -> 0
C55: OTHER | E55: =B30 -> 0
C56: OTHER | E56: =B31 -> 0
C57: OTHER | E57: =B32 -> 0
C58: OTHER | E58: =B33 -> 0
C59: OTHER | E59: =B34 -> 0
C60: OTHER | E60: =B35 -> 0
C61: OTHER | E61: =B36 -> 0
C62: TOTAL TIMBER | E62: =SUM(E49:H61) -> 14377

Sheet NYANZA
A1: QUANTITY REPORT
A3: MONTHLY REPORT OF MAY 2026
A5: NAME OF TIMBER | B5: No OF TIMBER | C5: PRICE OF TIMBER | E5: TOTAL COST | F5: TVA | G5: MSF | H5: TVA+MSF
A6: PINUS NINI | E6: =PRODUCT(B6*C6) -> 0 | F6: =PRODUCT(E6*18)/118 -> 0 | G6: =PRODUCT(B6*50) -> 0 | H6: =SUM(F6:G6) -> 0
A7: PINUS NTOYA | B7: 400 | C7: 2000 | E7: =PRODUCT(B7*C7) -> 800000 | F7: =PRODUCT(E7*18)/118 -> 122033.9 | G7: =PRODUCT(B7*50) -> 20000 | H7: =SUM(F7:G7) -> 142033.9
A8: IBIPANDE | C8: 2000 | E8: =PRODUCT(B8*C8) -> 0 | F8: =PRODUCT(E8*18)/118 -> 0 | G8: =PRODUCT(B8*50) -> 0 | H8: =SUM(F8:G8) -> 0
A9: MADIRIYE NINI | B9: 600 | C9: 2200 | E9: =PRODUCT(B9*C9) -> 1320000 | F9: =PRODUCT(E9*18)/118 -> 201355.93 | G9: =PRODUCT(B9*30) -> 18000 | H9: =SUM(F9:G9) -> 219355.93
A10: MADIRIYE NTOYA | B10: 5800 | C10: 1800 | E10: =PRODUCT(B10*C10) -> 10440000 | F10: =PRODUCT(E10*18)/118 -> 1592542.4 | G10: =PRODUCT(B10*30) -> 174000 | H10: =SUM(F10:G10) -> 1766542.4
A11: MADRIEN | E11: =PRODUCT(B11*C11) -> 0 | F11: =PRODUCT(E11*18)/118 -> 0 | G11: =PRODUCT(B11*30) -> 0 | H11: =SUM(F11:G11) -> 0
A12: MADRIEN | E12: =PRODUCT(B12*C12) -> 0 | F12: =PRODUCT(E12*18)/118 -> 0 | G12: =PRODUCT(B12*30) -> 0 | H12: =SUM(F12:G12) -> 0
A13: PLANCHE | B13: 300 | C13: 1200 | E13: =PRODUCT(B13*C13) -> 360000 | F13: =PRODUCT(E13*18)/118 -> 54915.254 | G13: =PRODUCT(B13*20) -> 6000 | H13: =SUM(F13:G13) -> 60915.254
A14: PLANCHE | E14: =PRODUCT(B14*C14) -> 0 | F14: =PRODUCT(E14*18)/118 -> 0 | G14: =PRODUCT(B14*20) -> 0 | H14: =SUM(F14:G14) -> 0
A15: Other Timber for Difference Price
A16: NAME OF TIMBER | B16: No OF TIMBER | C16: P/U | D16: MSF | E16: TOTAL COST | F16: VAT | G16: MSF | H16: VTA+MST
A17: IBIPANDE | E17: =PRODUCT(B17*C17) -> 0 | F17: =PRODUCT(E17*18)/118 -> 0 | G17: =PRODUCT(B17*D17) -> 0 | H17: =SUM(F17:G17) -> 0
A18: IBIPANDE | E18: =PRODUCT(B18*C18) -> 0 | F18: =PRODUCT(E18*18)/118 -> 0 | G18: =PRODUCT(B18*D18) -> 0 | H18: =SUM(F18:G18) -> 0
A19: UMUSAVE | E19: =PRODUCT(B19*C19) -> 0 | F19: =PRODUCT(E19*18)/118 -> 0 | G19: =PRODUCT(B19*D19) -> 0 | H19: =SUM(F19:G19) -> 0
A20: UMUSAVE | E20: =PRODUCT(B20*C20) -> 0 | F20: =PRODUCT(E20*18)/118 -> 0 | G20: =PRODUCT(B20*D20) -> 0 | H20: =SUM(F20:G20) -> 0
A21: OTHER | B21: 7964 | D21: 50 | E21: =PRODUCT(B21*C21) -> 0 | F21: =PRODUCT(E21*18)/118 -> 0 | G21: =PRODUCT(B21*D21) -> 398200 | H21: =SUM(F21:G21) -> 398200
A22: OTHER | E22: =PRODUCT(B22*C22) -> 0 | F22: =PRODUCT(E22*18)/118 -> 0 | G22: =PRODUCT(B22*D22) -> 0 | H22: =SUM(F22:G22) -> 0
A23: OTHER | E23: =PRODUCT(B23*C23) -> 0 | F23: =PRODUCT(E23*18)/118 -> 0 | G23: =PRODUCT(B23*D23) -> 0 | H23: =SUM(F23:G23) -> 0
A24: OTHER | E24: =PRODUCT(B24*C24) -> 0 | F24: =PRODUCT(E24*18)/118 -> 0 | G24: =PRODUCT(B24*D24) -> 0 | H24: =SUM(F24:G24) -> 0
A25: OTHER | E25: =PRODUCT(B25*C25) -> 0 | F25: =PRODUCT(E25*18)/118 -> 0 | G25: =PRODUCT(B25*D25) -> 0 | H25: =SUM(F25:G25) -> 0
A26: OTHER | E26: =PRODUCT(B26*C26) -> 0 | F26: =PRODUCT(E26*18)/118 -> 0 | G26: =PRODUCT(B26*D26) -> 0 | H26: =SUM(F26:G26) -> 0
A27: OTHER | E27: =PRODUCT(B27*C27) -> 0 | F27: =PRODUCT(E27*18)/118 -> 0 | G27: =PRODUCT(B27*D27) -> 0 | H27: =SUM(F27:G27) -> 0
A28: OTHER | E28: =PRODUCT(B28*C28) -> 0 | F28: =PRODUCT(E28*18)/118 -> 0 | G28: =PRODUCT(B28*D28) -> 0 | H28: =SUM(F28:G28) -> 0
A29: OTHER | E29: =PRODUCT(B29*C29) -> 0 | F29: =PRODUCT(E29*18)/118 -> 0 | G29: =PRODUCT(B29*D29) -> 0 | H29: =SUM(F29:G29) -> 0
A30: OTHER | E30: =PRODUCT(B30*C30) -> 0 | F30: =PRODUCT(E30*18)/118 -> 0 | G30: =PRODUCT(B30*D30) -> 0 | H30: =SUM(F30:G30) -> 0
A31: OTHER | E31: =PRODUCT(B31*C31) -> 0 | F31: =PRODUCT(E31*18)/118 -> 0 | G31: =PRODUCT(B31*D31) -> 0 | H31: =SUM(F31:G31) -> 0
A32: OTHER | E32: =PRODUCT(B32*C32) -> 0 | F32: =PRODUCT(E32*18)/118 -> 0 | G32: =PRODUCT(B32*D32) -> 0 | H32: =SUM(F32:G32) -> 0
A33: OTHER | E33: =PRODUCT(B33*C33) -> 0 | F33: =PRODUCT(E33*18)/118 -> 0 | G33: =PRODUCT(B33*D33) -> 0 | H33: =SUM(F33:G33) -> 0
... A36: OTHER | E36: =PRODUCT(B36*C36) -> 0 | F36: =PRODUCT(E36*18)/118 -> 0 | G36: =PRODUCT(B36*D36) -> 0 | H36: =SUM(F36:G36) -> 0
A37: TOTALY | E37: =SUM(E5:E36) -> 12920000 | F37: =SUM(F5:F36) -> 1970847.5 | G37: =SUM(G5:G36) -> 616200 | H37: =SUM(H5:H36) -> 2587047.5
A38: SUMMARY | C38: RWF | E38: NAME | G38: Phone | H38: RWF
A39: TOTAL RWF PAID ON MOMO PAY | C39: 2587047
A40: TOTAL RWF PAID ON CASH
A41: AMOUNT NOT INVOICED
A42: TOTAL RWF DEPPOSITED ON BANK
A43: MEMBERSHIP FEES REGISTRETION
A44: MEMBERSHIP FEES CONTRIBUTION
A45: TOTAL INCOME | C45: =SUM(C39+C40+C41+C42+C43+C44) -> 2587047
A46: TIMBER SUMMARY
A48: REPORT SUMMARY | C48: TIMBER TYPE | E48: NUMBER OF QUANTITY
C49: INTURUSU | E49: =SUM(B9:B12) -> 6400
C50: PINUS | E50: =SUM(B6:B8) -> 400
C51: PALNCHE | E51: =SUM(B13:B14) -> 300
C52: IBIPANDE | E52: =SUM(B17:B18) -> 0
C53: UMUSAVE | E53: =SUM(B19:B20) -> 0
C54: OTHER | E54: =B29 -> 0
C55: OTHER | E55: =B30 -> 0
C56: OTHER | E56: =B31 -> 0
C57: OTHER | E57: =B32 -> 0
C58: OTHER | E58: =B33 -> 0
C59: OTHER | E59: =B34 -> 0
C60: OTHER | E60: =B35 -> 0
C61: OTHER | E61: =B36 -> 0
C62: TOTAL TIMBER | E62: =SUM(E49:H61) -> 7100

Sheet GATSIBO
A1: QUANTITY REPORT
A3: MONTHLY REPORT OF MAY 2026
A5: NAME OF TIMBER | B5: No OF TIMBER | C5: PRICE OF TIMBER | E5: TOTAL COST | F5: TVA | G5: MSF | H5: TVA+MSF
A6: PINUS NINI | C6: 5900 | E6: =PRODUCT(B6*C6) -> 0 | F6: =PRODUCT(E6*18)/118 -> 0 | G6: =PRODUCT(B6*50) -> 0 | H6: =SUM(F6:G6) -> 0
A7: PINUS NTOYA | B7: 665 | C7: 5900 | E7: =PRODUCT(B7*C7) -> 3923500 | F7: =PRODUCT(E7*18)/118 -> 598500 | G7: =PRODUCT(B7*50) -> 33250 | H7: =SUM(F7:G7) -> 631750
A8: PINUS | E8: =PRODUCT(B8*C8) -> 0 | F8: =PRODUCT(E8*18)/118 -> 0 | G8: =PRODUCT(B8*50) -> 0 | H8: =SUM(F8:G8) -> 0
A9: MADIRIYE NINI | E9: =PRODUCT(B9*C9) -> 0 | F9: =PRODUCT(E9*18)/118 -> 0 | G9: =PRODUCT(B9*30) -> 0 | H9: =SUM(F9:G9) -> 0
A10: MADIRIYE NTOYA | B10: 6350 | C10: 2124 | E10: =PRODUCT(B10*C10) -> 13487400 | F10: =PRODUCT(E10*18)/118 -> 2057400 | G10: =PRODUCT(B10*30) -> 190500 | H10: =SUM(F10:G10) -> 2247900
A11: MADRIEN | E11: =PRODUCT(B11*C11) -> 0 | F11: =PRODUCT(E11*18)/118 -> 0 | G11: =PRODUCT(B11*30) -> 0 | H11: =SUM(F11:G11) -> 0
A12: PINUS | B12: 35 | C12: 5000 | E12: =PRODUCT(B12*C12) -> 175000 | F12: =PRODUCT(E12*18)/118 -> 26694.915 | G12: =PRODUCT(B12*30) -> 1050 | H12: =SUM(F12:G12) -> 27744.915
A13: PLANCHE | B13: 150 | C13: 1357 | E13: =PRODUCT(B13*C13) -> 203550 | F13: =PRODUCT(E13*18)/118 -> 31050 | G13: =PRODUCT(B13*20) -> 3000 | H13: =SUM(F13:G13) -> 34050
A14: GEREVERIYA | B14: 100 | C14: 1180 | E14: =PRODUCT(B14*C14) -> 118000 | F14: =PRODUCT(E14*18)/118 -> 18000 | G14: =PRODUCT(B14*20) -> 2000 | H14: =SUM(F14:G14) -> 20000
A15: Other Timber for Difference Price
A16: NAME OF TIMBER | B16: No OF TIMBER | C16: P/U | D16: MSF | E16: TOTAL COST | F16: VAT | G16: MSF | H16: VTA+MST
A17: MADRIEN NTOYA | B17: 100 | D17: 354 | E17: =PRODUCT(B17*C17) -> 0 | F17: =PRODUCT(E17*18)/118 -> 0 | G17: =PRODUCT(B17*D17) -> 35400 | H17: =SUM(F17:G17) -> 35400
A18: PINUS | C18: 5000 | D18: 50 | E18: =PRODUCT(B18*C18) -> 0 | F18: =PRODUCT(E18*18)/118 -> 0 | G18: =PRODUCT(B18*D18) -> 0 | H18: =SUM(F18:G18) -> 0
A19: GEREVERIYA | B19: 906 | D19: 200 | E19: =PRODUCT(B19*C19) -> 0 | F19: =PRODUCT(E19*18)/118 -> 0 | G19: =PRODUCT(B19*D19) -> 181200 | H19: =SUM(F19:G19) -> 181200
A20: INGIGA | B20: 418 | D20: 500 | E20: =PRODUCT(B20*C20) -> 0 | F20: =PRODUCT(E20*18)/118 -> 0 | G20: =PRODUCT(B20*D20) -> 209000 | H20: =SUM(F20:G20) -> 209000
A21: PLANCHE | B21: 11 | D21: 217 | E21: =PRODUCT(B21*C21) -> 0 | F21: =PRODUCT(E21*18)/118 -> 0 | G21: =PRODUCT(B21*D21) -> 2387 | H21: =SUM(F21:G21) -> 2387
A22: OTHER | E22: =PRODUCT(B22*C22) -> 0 | F22: =PRODUCT(E22*18)/118 -> 0 | G22: =PRODUCT(B22*D22) -> 0 | H22: =SUM(F22:G22) -> 0
A23: OTHER | E23: =PRODUCT(B23*C23) -> 0 | F23: =PRODUCT(E23*18)/118 -> 0 | G23: =PRODUCT(B23*D23) -> 0 | H23: =SUM(F23:G23) -> 0
A24: OTHER | E24: =PRODUCT(B24*C24) -> 0 | F24: =PRODUCT(E24*18)/118 -> 0 | G24: =PRODUCT(B24*D24) -> 0 | H24: =SUM(F24:G24) -> 0
A25: OTHER | E25: =PRODUCT(B25*C25) -> 0 | F25: =PRODUCT(E25*18)/118 -> 0 | G25: =PRODUCT(B25*D25) -> 0 | H25: =SUM(F25:G25) -> 0
A26: OTHER | E26: =PRODUCT(B26*C26) -> 0 | F26: =PRODUCT(E26*18)/118 -> 0 | G26: =PRODUCT(B26*D26) -> 0 | H26: =SUM(F26:G26) -> 0
A27: OTHER | E27: =PRODUCT(B27*C27) -> 0 | F27: =PRODUCT(E27*18)/118 -> 0 | G27: =PRODUCT(B27*D27) -> 0 | H27: =SUM(F27:G27) -> 0
A28: OTHER | E28: =PRODUCT(B28*C28) -> 0 | F28: =PRODUCT(E28*18)/118 -> 0 | G28: =PRODUCT(B28*D28) -> 0 | H28: =SUM(F28:G28) -> 0
A29: OTHER | E29: =PRODUCT(B29*C29) -> 0 | F29: =PRODUCT(E29*18)/118 -> 0 | G29: =PRODUCT(B29*D29) -> 0 | H29: =SUM(F29:G29) -> 0
A30: OTHER | E30: =PRODUCT(B30*C30) -> 0 | F30: =PRODUCT(E30*18)/118 -> 0 | G30: =PRODUCT(B30*D30) -> 0 | H30: =SUM(F30:G30) -> 0
A31: OTHER | E31: =PRODUCT(B31*C31) -> 0 | F31: =PRODUCT(E31*18)/118 -> 0 | G31: =PRODUCT(B31*D31) -> 0 | H31: =SUM(F31:G31) -> 0
A32: OTHER | E32: =PRODUCT(B32*C32) -> 0 | F32: =PRODUCT(E32*18)/118 -> 0 | G32: =PRODUCT(B32*D32) -> 0 | H32: =SUM(F32:G32) -> 0
A33: OTHER | E33: =PRODUCT(B33*C33) -> 0 | F33: =PRODUCT(E33*18)/118 -> 0 | G33: =PRODUCT(B33*D33) -> 0 | H33: =SUM(F33:G33) -> 0
... A36: OTHER | E36: =PRODUCT(B36*C36) -> 0 | F36: =PRODUCT(E36*18)/118 -> 0 | G36: =PRODUCT(B36*D36) -> 0 | H36: =SUM(F36:G36) -> 0
A37: TOTALY | E37: =SUM(E5:E36) -> 17907450 | F37: =SUM(F5:F36) -> 2731644.9 | G37: =SUM(G5:G36) -> 657787 | H37: =SUM(H5:H36) -> 3389431.9
A38: SUMMARY | C38: RWF | E38: NAME | G38: Phone | H38: RWF
A39: TOTAL RWF PAID ON MOMO PAY | C39: 3389432
A40: TOTAL RWF PAID ON CASH
A41: AMOUNT NOT INVOICED
A42: TOTAL RWF DEPPOSITED ON BANK
A43: MEMBERSHIP FEES REGISTRETION
A44: MEMBERSHIP FEES CONTRIBUTION
A45: TOTAL INCOME | C45: =SUM(C39+C40+C41+C42+C43+C44) -> 3389432
A46: TIMBER SUMMARY
A48: REPORT SUMMARY | C48: TIMBER TYPE | E48: NUMBER OF QUANTITY
C49: INTURUSU | E49: =SUM(B9:B12) -> 6385
C50: PINUS | E50: =SUM(B6:B8) -> 665
C51: PALNCHE | E51: =SUM(B13:B14) -> 250
C52: IBIPANDE | E52: =SUM(B17:B18) -> 100
C53: UMUSAVE | E53: =SUM(B19:B20) -> 1324
C54: OTHER | E54: =B29 -> 0
C55: OTHER | E55: =B30 -> 0
C56: OTHER | E56: =B31 -> 0
C57: OTHER | E57: =B32 -> 0
C58: OTHER | E58: =B33 -> 0
C59: OTHER | E59: =B34 -> 0
C60: OTHER | E60: =B35 -> 0
C61: OTHER | E61: =B36 -> 0
C62: TOTAL TIMBER | E62: =SUM(E49:H61) -> 8724

Sheet GASHYUSHYA
A1: QUANTITY REPORT
A3: MONTHLY REPORT OF MAY 2026
A5: NAME OF TIMBER | B5: No OF TIMBER | C5: PRICE OF TIMBER | E5: TOTAL COST | F5: TVA | G5: MSF | H5: TVA+MSF
A6: PINUS NINI | E6: =PRODUCT(B6*C6) -> 0 | F6: =PRODUCT(E6*18)/118 -> 0 | G6: =PRODUCT(B6*50) -> 0 | H6: =SUM(F6:G6) -> 0
A7: PINUS NTOYA | E7: =PRODUCT(B7*C7) -> 0 | F7: =PRODUCT(E7*18)/118 -> 0 | G7: =PRODUCT(B7*50) -> 0 | H7: =SUM(F7:G7) -> 0
A8: PINUS | E8: =PRODUCT(B8*C8) -> 0 | F8: =PRODUCT(E8*18)/118 -> 0 | G8: =PRODUCT(B8*50) -> 0 | H8: =SUM(F8:G8) -> 0
A9: MADIRIYE NINI | E9: =PRODUCT(B9*C9) -> 0 | F9: =PRODUCT(E9*18)/118 -> 0 | G9: =PRODUCT(B9*30) -> 0 | H9: =SUM(F9:G9) -> 0
A10: MADIRIYE NTOYA | B10: 24334 | C10: 2124 | E10: =PRODUCT(B10*C10) -> 51685416 | F10: =PRODUCT(E10*18)/118 -> 7884216 | G10: =PRODUCT(B10*30) -> 730020 | H10: =SUM(F10:G10) -> 8614236
A11: MADRIEN | B11: 835 | C11: 2000 | E11: =PRODUCT(B11*C11) -> 1670000 | F11: =PRODUCT(E11*18)/118 -> 254745.76 | G11: =PRODUCT(B11*30) -> 25050 | H11: =SUM(F11:G11) -> 279795.76
A12: MADRIEN | E12: =PRODUCT(B12*C12) -> 0 | F12: =PRODUCT(E12*18)/118 -> 0 | G12: =PRODUCT(B12*30) -> 0 | H12: =SUM(F12:G12) -> 0
A13: PLANCHE | B13: 1795 | C13: 1357 | E13: =PRODUCT(B13*C13) -> 2435815 | F13: =PRODUCT(E13*18)/118 -> 371565 | G13: =PRODUCT(B13*20) -> 35900 | H13: =SUM(F13:G13) -> 407465
A14: PLANCHE | E14: =PRODUCT(B14*C14) -> 0 | F14: =PRODUCT(E14*18)/118 -> 0 | G14: =PRODUCT(B14*20) -> 0 | H14: =SUM(F14:G14) -> 0
A15: Other Timber for Difference Price
A16: NAME OF TIMBER | B16: No OF TIMBER | C16: P/U | D16: MSF | E16: TOTAL COST | F16: VAT | G16: MSF | H16: VTA+MST
A17: IBIPANDE BYA PINUS | B17: 2918 | C17: 2124 | D17: 50 | E17: =PRODUCT(B17*C17) -> 6197832 | F17: =PRODUCT(E17*18)/118 -> 945432 | G17: =PRODUCT(B17*D17) -> 145900 | H17: =SUM(F17:G17) -> 1091332
A18: IBIPANDE | E18: =PRODUCT(B18*C18) -> 0 | F18: =PRODUCT(E18*18)/118 -> 0 | G18: =PRODUCT(B18*D18) -> 0 | H18: =SUM(F18:G18) -> 0
A19: UMUSAVE | E19: =PRODUCT(B19*C19) -> 0 | F19: =PRODUCT(E19*18)/118 -> 0 | G19: =PRODUCT(B19*D19) -> 0 | H19: =SUM(F19:G19) -> 0
A20: UMUSAVE | E20: =PRODUCT(B20*C20) -> 0 | F20: =PRODUCT(E20*18)/118 -> 0 | G20: =PRODUCT(B20*D20) -> 0 | H20: =SUM(F20:G20) -> 0
A21: OTHER | D21: 100 | E21: =PRODUCT(B21*C21) -> 0 | F21: =PRODUCT(E21*18)/118 -> 0 | G21: =PRODUCT(B21*D21) -> 0 | H21: =SUM(F21:G21) -> 0
A22: OTHER | E22: =PRODUCT(B22*C22) -> 0 | F22: =PRODUCT(E22*18)/118 -> 0 | G22: =PRODUCT(B22*D22) -> 0 | H22: =SUM(F22:G22) -> 0
A23: OTHER | E23: =PRODUCT(B23*C23) -> 0 | F23: =PRODUCT(E23*18)/118 -> 0 | G23: =PRODUCT(B23*D23) -> 0 | H23: =SUM(F23:G23) -> 0
A24: OTHER | E24: =PRODUCT(B24*C24) -> 0 | F24: =PRODUCT(E24*18)/118 -> 0 | G24: =PRODUCT(B24*D24) -> 0 | H24: =SUM(F24:G24) -> 0
A25: OTHER | E25: =PRODUCT(B25*C25) -> 0 | F25: =PRODUCT(E25*18)/118 -> 0 | G25: =PRODUCT(B25*D25) -> 0 | H25: =SUM(F25:G25) -> 0
A26: OTHER | E26: =PRODUCT(B26*C26) -> 0 | F26: =PRODUCT(E26*18)/118 -> 0 | G26: =PRODUCT(B26*D26) -> 0 | H26: =SUM(F26:G26) -> 0
A27: OTHER | E27: =PRODUCT(B27*C27) -> 0 | F27: =PRODUCT(E27*18)/118 -> 0 | G27: =PRODUCT(B27*D27) -> 0 | H27: =SUM(F27:G27) -> 0
A28: OTHER | E28: =PRODUCT(B28*C28) -> 0 | F28: =PRODUCT(E28*18)/118 -> 0 | G28: =PRODUCT(B28*D28) -> 0 | H28: =SUM(F28:G28) -> 0
A29: OTHER | E29: =PRODUCT(B29*C29) -> 0 | F29: =PRODUCT(E29*18)/118 -> 0 | G29: =PRODUCT(B29*D29) -> 0 | H29: =SUM(F29:G29) -> 0
A30: OTHER | E30: =PRODUCT(B30*C30) -> 0 | F30: =PRODUCT(E30*18)/118 -> 0 | G30: =PRODUCT(B30*D30) -> 0 | H30: =SUM(F30:G30) -> 0
A31: OTHER | E31: =PRODUCT(B31*C31) -> 0 | F31: =PRODUCT(E31*18)/118 -> 0 | G31: =PRODUCT(B31*D31) -> 0 | H31: =SUM(F31:G31) -> 0
A32: OTHER | E32: =PRODUCT(B32*C32) -> 0 | F32: =PRODUCT(E32*18)/118 -> 0 | G32: =PRODUCT(B32*D32) -> 0 | H32: =SUM(F32:G32) -> 0
A33: OTHER | E33: =PRODUCT(B33*C33) -> 0 | F33: =PRODUCT(E33*18)/118 -> 0 | G33: =PRODUCT(B33*D33) -> 0 | H33: =SUM(F33:G33) -> 0
... A36: OTHER | E36: =PRODUCT(B36*C36) -> 0 | F36: =PRODUCT(E36*18)/118 -> 0 | G36: =PRODUCT(B36*D36) -> 0 | H36: =SUM(F36:G36) -> 0
A37: TOTALY | E37: =SUM(E5:E36) -> 61989063 | F37: =SUM(F5:F36) -> 9455958.8 | G37: =SUM(G5:G36) -> 936870 | H37: =SUM(H5:H36) -> 10392829
A38: SUMMARY | C38: RWF | E38: NAME | G38: Phone | H38: RWF
A39: TOTAL RWF PAID ON MOMO PAY | C39: 10582828
A40: TOTAL RWF PAID ON CASH
A41: AMOUNT NOT INVOICED
A42: TOTAL RWF DEPPOSITED ON BANK
A43: MEMBERSHIP FEES REGISTRETION
A44: MEMBERSHIP FEES CONTRIBUTION
A45: TOTAL INCOME | C45: =SUM(C39+C40+C41+C42+C43+C44) -> 10582828
A46: TIMBER SUMMARY
A48: REPORT SUMMARY | C48: TIMBER TYPE | E48: NUMBER OF QUANTITY
C49: INTURUSU | E49: =SUM(B9:B12) -> 25169
C50: PINUS | E50: =SUM(B6:B8) -> 0
C51: PALNCHE | E51: =SUM(B13:B14) -> 1795
C52: IBIPANDE | E52: =SUM(B17:B18) -> 2918
C53: UMUSAVE | E53: =SUM(B19:B20) -> 0
C54: OTHER TYPE OF TIMBER | E54: =B29 -> 0
C55: OTHER TYPE OF TIMBER | E55: =B30 -> 0
C56: OTHER TYPE OF TIMBER | E56: =B31 -> 0
C57: OTHER TYPE OF TIMBER | E57: =B32 -> 0
C58: OTHER TYPE OF TIMBER | E58: =B33 -> 0
C59: OTHER TYPE OF TIMBER | E59: =B34 -> 0
C60: OTHER TYPE OF TIMBER | E60: =B35 -> 0
C61: OTHER TYPE OF TIMBER | E61: =B36 -> 0
C62: TOTAL TIMBER | E62: =SUM(E49:H61) -> 29882

Sheet RUTSIRO
A1: QUANTITY REPORT
A3: MONTHLY REPORT OF MAY 2026
A5: NAME OF TIMBER | B5: No OF TIMBER | C5: PRICE OF TIMBER | E5: TOTAL COST | F5: TVA | G5: MSF | H5: TVA+MSF
A6: PINUS NINI | E6: =PRODUCT(B6*C6) -> 0 | F6: =PRODUCT(E6*18)/118 -> 0 | G6: =PRODUCT(B6*50) -> 0 | H6: =SUM(F6:G6) -> 0
A7: PINUS NTOYA | E7: =PRODUCT(B7*C7) -> 0 | F7: =PRODUCT(E7*18)/118 -> 0 | G7: =PRODUCT(B7*50) -> 0 | H7: =SUM(F7:G7) -> 0
A8: PINUS | E8: =PRODUCT(B8*C8) -> 0 | F8: =PRODUCT(E8*18)/118 -> 0 | G8: =PRODUCT(B8*50) -> 0 | H8: =SUM(F8:G8) -> 0
A9: MADIRIYE NINI | E9: =PRODUCT(B9*C9) -> 0 | F9: =PRODUCT(E9*18)/118 -> 0 | G9: =PRODUCT(B9*30) -> 0 | H9: =SUM(F9:G9) -> 0
A10: MADIRIYE NTOYA | E10: =PRODUCT(B10*C10) -> 0 | F10: =PRODUCT(E10*18)/118 -> 0 | G10: =PRODUCT(B10*30) -> 0 | H10: =SUM(F10:G10) -> 0
A11: MADRIEN | E11: =PRODUCT(B11*C11) -> 0 | F11: =PRODUCT(E11*18)/118 -> 0 | G11: =PRODUCT(B11*30) -> 0 | H11: =SUM(F11:G11) -> 0
A12: MADRIEN | C12: 2124 | E12: =PRODUCT(B12*C12) -> 0 | F12: =PRODUCT(E12*18)/118 -> 0 | G12: =PRODUCT(B12*30) -> 0 | H12: =SUM(F12:G12) -> 0
A13: PLANCHE | E13: =PRODUCT(B13*C13) -> 0 | F13: =PRODUCT(E13*18)/118 -> 0 | G13: =PRODUCT(B13*20) -> 0 | H13: =SUM(F13:G13) -> 0
A14: PLANCHE | E14: =PRODUCT(B14*C14) -> 0 | F14: =PRODUCT(E14*18)/118 -> 0 | G14: =PRODUCT(B14*20) -> 0 | H14: =SUM(F14:G14) -> 0
A15: Other Timber for Difference Price
A16: NAME OF TIMBER | B16: No OF TIMBER | C16: P/U | D16: MSF | E16: TOTAL COST | F16: VAT | G16: MSF | H16: VTA+MST
A17: IBIPANDE | E17: =PRODUCT(B17*C17) -> 0 | F17: =PRODUCT(E17*18)/118 -> 0 | G17: =PRODUCT(B17*D17) -> 0 | H17: =SUM(F17:G17) -> 0
A18: IBIPANDE | E18: =PRODUCT(B18*C18) -> 0 | F18: =PRODUCT(E18*18)/118 -> 0 | G18: =PRODUCT(B18*D18) -> 0 | H18: =SUM(F18:G18) -> 0
A19: UMUSAVE | E19: =PRODUCT(B19*C19) -> 0 | F19: =PRODUCT(E19*18)/118 -> 0 | G19: =PRODUCT(B19*D19) -> 0 | H19: =SUM(F19:G19) -> 0
A20: UMUSAVE | E20: =PRODUCT(B20*C20) -> 0 | F20: =PRODUCT(E20*18)/118 -> 0 | G20: =PRODUCT(B20*D20) -> 0 | H20: =SUM(F20:G20) -> 0
A21: OTHER | E21: =PRODUCT(B21*C21) -> 0 | F21: =PRODUCT(E21*18)/118 -> 0 | G21: =PRODUCT(B21*D21) -> 0 | H21: =SUM(F21:G21) -> 0
A22: OTHER | E22: =PRODUCT(B22*C22) -> 0 | F22: =PRODUCT(E22*18)/118 -> 0 | G22: =PRODUCT(B22*D22) -> 0 | H22: =SUM(F22:G22) -> 0
A23: OTHER | E23: =PRODUCT(B23*C23) -> 0 | F23: =PRODUCT(E23*18)/118 -> 0 | G23: =PRODUCT(B23*D23) -> 0 | H23: =SUM(F23:G23) -> 0
A24: OTHER | E24: =PRODUCT(B24*C24) -> 0 | F24: =PRODUCT(E24*18)/118 -> 0 | G24: =PRODUCT(B24*D24) -> 0 | H24: =SUM(F24:G24) -> 0
A25: OTHER | E25: =PRODUCT(B25*C25) -> 0 | F25: =PRODUCT(E25*18)/118 -> 0 | G25: =PRODUCT(B25*D25) -> 0 | H25: =SUM(F25:G25) -> 0
A26: OTHER | E26: =PRODUCT(B26*C26) -> 0 | F26: =PRODUCT(E26*18)/118 -> 0 | G26: =PRODUCT(B26*D26) -> 0 | H26: =SUM(F26:G26) -> 0
A27: OTHER | E27: =PRODUCT(B27*C27) -> 0 | F27: =PRODUCT(E27*18)/118 -> 0 | G27: =PRODUCT(B27*D27) -> 0 | H27: =SUM(F27:G27) -> 0
A28: OTHER | E28: =PRODUCT(B28*C28) -> 0 | F28: =PRODUCT(E28*18)/118 -> 0 | G28: =PRODUCT(B28*D28) -> 0 | H28: =SUM(F28:G28) -> 0
... A36: OTHER | E36: =PRODUCT(B36*C36) -> 0 | F36: =PRODUCT(E36*18)/118 -> 0 | G36: =PRODUCT(B36*D36) -> 0 | H36: =SUM(F36:G36) -> 0
A37: TOTALY | E37: =SUM(E5:E36) -> 0 | F37: =SUM(F5:F36) -> 0 | G37: =SUM(G5:G36) -> 0 | H37: =SUM(H5:H36) -> 0
A38: SUMMARY | C38: RWF | E38: NAME | G38: Phone | H38: RWF
A39: TOTAL RWF PAID ON MOMO PAY
A40: TOTAL RWF PAID ON CASH
A41: AMOUNT NOT INVOICED
A42: TOTAL RWF DEPPOSITED ON BANK
A43: MEMBERSHIP FEES REGISTRETION
A44: MEMBERSHIP FEES CONTRIBUTION
A45: TOTAL INCOME | C45: =SUM(C39+C40+C41+C42+C43+C44) -> 0
A46: TIMBER SUMMARY
A48: REPORT SUMMARY | C48: TIMBER TYPE | E48: NUMBER OF QUANTITY
C49: INTURUSU | E49: =SUM(B9:B12) -> 0
C50: PINUS | E50: =SUM(B6:B8) -> 0
C51: PALNCHE | E51: =SUM(B13:B14) -> 0
C52: IBIPANDE | E52: =SUM(B17:B18) -> 0
C53: UMUSAVE | E53: =SUM(B19:B20) -> 0
C54: OTHER TYPE OF TIMBER | E54: =B29 -> 0
C55: OTHER TYPE OF TIMBER | E55: =B30 -> 0
C56: OTHER TYPE OF TIMBER | E56: =B31 -> 0
C57: OTHER TYPE OF TIMBER | E57: =B32 -> 0
C58: OTHER TYPE OF TIMBER | E58: =B33 -> 0
C59: OTHER TYPE OF TIMBER | E59: =B34 -> 0
C60: OTHER TYPE OF TIMBER | E60: =B35 -> 0
C61: OTHER TYPE OF TIMBER | E61: =B36 -> 0
C62: TOTAL TIMBER | E62: =SUM(E49:H61) -> 0

Sheet NGORORERO
A1: QUANTITY REPORT
A3: MONTHLY REPORT OF MAY 2026
A5: NAME OF TIMBER | B5: No OF TIMBER | C5: PRICE OF TIMBER | E5: TOTAL COST | F5: TVA | G5: MSF | H5: TVA+MSF
A6: PINUS NINI | E6: =PRODUCT(B6*C6) -> 0 | F6: =PRODUCT(E6*18)/118 -> 0 | G6: =PRODUCT(B6*50) -> 0 | H6: =SUM(F6:G6) -> 0
A7: PINUS NTOYA | E7: =PRODUCT(B7*C7) -> 0 | F7: =PRODUCT(E7*18)/118 -> 0 | G7: =PRODUCT(B7*50) -> 0 | H7: =SUM(F7:G7) -> 0
A8: PINUS | E8: =PRODUCT(B8*C8) -> 0 | F8: =PRODUCT(E8*18)/118 -> 0 | G8: =PRODUCT(B8*50) -> 0 | H8: =SUM(F8:G8) -> 0
A9: MADIRIYE NINI | E9: =PRODUCT(B9*C9) -> 0 | F9: =PRODUCT(E9*18)/118 -> 0 | G9: =PRODUCT(B9*30) -> 0 | H9: =SUM(F9:G9) -> 0
A10: MADIRIYE NTOYA | B10: 200 | C10: 1806 | E10: =PRODUCT(B10*C10) -> 361200 | F10: =PRODUCT(E10*18)/118 -> 55098.305 | G10: =PRODUCT(B10*30) -> 6000 | H10: =SUM(F10:G10) -> 61098.305
A11: MADRIEN | C11: 2124 | E11: =PRODUCT(B11*C11) -> 0 | F11: =PRODUCT(E11*18)/118 -> 0 | G11: =PRODUCT(B11*30) -> 0 | H11: =SUM(F11:G11) -> 0
A12: MADRIEN | E12: =PRODUCT(B12*C12) -> 0 | F12: =PRODUCT(E12*18)/118 -> 0 | G12: =PRODUCT(B12*30) -> 0 | H12: =SUM(F12:G12) -> 0
A13: PLANCHE | E13: =PRODUCT(B13*C13) -> 0 | F13: =PRODUCT(E13*18)/118 -> 0 | G13: =PRODUCT(B13*20) -> 0 | H13: =SUM(F13:G13) -> 0
A14: PLANCHE | E14: =PRODUCT(B14*C14) -> 0 | F14: =PRODUCT(E14*18)/118 -> 0 | G14: =PRODUCT(B14*20) -> 0 | H14: =SUM(F14:G14) -> 0
A15: Other Timber for Difference Price
A16: NAME OF TIMBER | B16: No OF TIMBER | C16: P/U | D16: MSF | E16: TOTAL COST | F16: VAT | G16: MSF | H16: VTA+MST
A17: IBIPANDE | E17: =PRODUCT(B17*C17) -> 0 | F17: =PRODUCT(E17*18)/118 -> 0 | G17: =PRODUCT(B17*D17) -> 0 | H17: =SUM(F17:G17) -> 0
A18: IBIPANDE | B18: 355 | C18: 800 | D18: 20 | E18: =PRODUCT(B18*C18) -> 284000 | F18: =PRODUCT(E18*18)/118 -> 43322.034 | G18: =PRODUCT(B18*D18) -> 7100 | H18: =SUM(F18:G18) -> 50422.034
A19: UMUSAVE | E19: =PRODUCT(B19*C19) -> 0 | F19: =PRODUCT(E19*18)/118 -> 0 | G19: =PRODUCT(B19*D19) -> 0 | H19: =SUM(F19:G19) -> 0
A20: UMUSAVE | E20: =PRODUCT(B20*C20) -> 0 | F20: =PRODUCT(E20*18)/118 -> 0 | G20: =PRODUCT(B20*D20) -> 0 | H20: =SUM(F20:G20) -> 0
A21: MADRIEN | C21: 1806 | D21: 30 | E21: =PRODUCT(B21*C21) -> 0 | F21: =PRODUCT(E21*18)/118 -> 0 | G21: =PRODUCT(B21*D21) -> 0 | H21: =SUM(F21:G21) -> 0
A22: OTHER | E22: =PRODUCT(B22*C22) -> 0 | F22: =PRODUCT(E22*18)/118 -> 0 | G22: =PRODUCT(B22*D22) -> 0 | H22: =SUM(F22:G22) -> 0
A23: OTHER | E23: =PRODUCT(B23*C23) -> 0 | F23: =PRODUCT(E23*18)/118 -> 0 | G23: =PRODUCT(B23*D23) -> 0 | H23: =SUM(F23:G23) -> 0
A24: OTHER | E24: =PRODUCT(B24*C24) -> 0 | F24: =PRODUCT(E24*18)/118 -> 0 | G24: =PRODUCT(B24*D24) -> 0 | H24: =SUM(F24:G24) -> 0
A25: OTHER | E25: =PRODUCT(B25*C25) -> 0 | F25: =PRODUCT(E25*18)/118 -> 0 | G25: =PRODUCT(B25*D25) -> 0 | H25: =SUM(F25:G25) -> 0
A26: OTHER | E26: =PRODUCT(B26*C26) -> 0 | F26: =PRODUCT(E26*18)/118 -> 0 | G26: =PRODUCT(B26*D26) -> 0 | H26: =SUM(F26:G26) -> 0
A27: OTHER | E27: =PRODUCT(B27*C27) -> 0 | F27: =PRODUCT(E27*18)/118 -> 0 | G27: =PRODUCT(B27*D27) -> 0 | H27: =SUM(F27:G27) -> 0
A28: OTHER | E28: =PRODUCT(B28*C28) -> 0 | F28: =PRODUCT(E28*18)/118 -> 0 | G28: =PRODUCT(B28*D28) -> 0 | H28: =SUM(F28:G28) -> 0
A29: OTHER | E29: =PRODUCT(B29*C29) -> 0 | F29: =PRODUCT(E29*18)/118 -> 0 | G29: =PRODUCT(B29*D29) -> 0 | H29: =SUM(F29:G29) -> 0
A30: OTHER | E30: =PRODUCT(B30*C30) -> 0 | F30: =PRODUCT(E30*18)/118 -> 0 | G30: =PRODUCT(B30*D30) -> 0 | H30: =SUM(F30:G30) -> 0
A31: OTHER | E31: =PRODUCT(B31*C31) -> 0 | F31: =PRODUCT(E31*18)/118 -> 0 | G31: =PRODUCT(B31*D31) -> 0 | H31: =SUM(F31:G31) -> 0
A32: OTHER | E32: =PRODUCT(B32*C32) -> 0 | F32: =PRODUCT(E32*18)/118 -> 0 | G32: =PRODUCT(B32*D32) -> 0 | H32: =SUM(F32:G32) -> 0
A33: OTHER | E33: =PRODUCT(B33*C33) -> 0 | F33: =PRODUCT(E33*18)/118 -> 0 | G33: =PRODUCT(B33*D33) -> 0 | H33: =SUM(F33:G33) -> 0
... A36: OTHER | E36: =PRODUCT(B36*C36) -> 0 | F36: =PRODUCT(E36*18)/118 -> 0 | G36: =PRODUCT(B36*D36) -> 0 | H36: =SUM(F36:G36) -> 0
A37: TOTALY | E37: =SUM(E5:E36) -> 645200 | F37: =SUM(F5:F36) -> 98420.339 | G37: =SUM(G5:G36) -> 13100 | H37: =SUM(H5:H36) -> 111520.34
A38: SUMMARY | C38: RWF | E38: NAME | G38: Phone | H38: RWF
A39: TOTAL RWF PAID ON MOMO PAY
A40: TOTAL RWF PAID ON CASH
A41: AMOUNT NOT INVOICED
A42: TOTAL RWF DEPPOSITED ON BANK
A43: MEMBERSHIP FEES REGISTRETION
A44: MEMBERSHIP FEES CONTRIBUTION
A45: TOTAL INCOME | C45: =SUM(C39+C40+C41+C42+C43+C44) -> 0
A46: TIMBER SUMMARY
A48: REPORT SUMMARY | C48: TIMBER TYPE | E48: NUMBER OF QUANTITY
C49: INTURUSU | E49: =SUM(B9:B12) -> 200
C50: PINUS | E50: =SUM(B6:B8) -> 0
C51: PALNCHE | E51: =SUM(B13:B14) -> 0
C52: IBIPANDE | E52: =SUM(B17:B18) -> 355
C53: UMUSAVE | E53: =SUM(B19:B20) -> 0
C54: OTHER TYPE OF TIMBER | E54: =B29 -> 0
C55: OTHER TYPE OF TIMBER | E55: =B30 -> 0
C56: OTHER TYPE OF TIMBER | E56: =B31 -> 0
C57: OTHER TYPE OF TIMBER | E57: =B32 -> 0
C58: OTHER TYPE OF TIMBER | E58: =B33 -> 0
C59: OTHER TYPE OF TIMBER | E59: =B34 -> 0
C60: OTHER TYPE OF TIMBER | E60: =B35 -> 0
C61: OTHER TYPE OF TIMBER | E61: =B36 -> 0
C62: TOTAL TIMBER | E62: =SUM(E49:H61) -> 555

Sheet NYAMASHEKE
A1: QUANTITY REPORT
A3: MONTHLY REPORT OF MAY 2026
A5: NAME OF TIMBER | B5: No OF TIMBER | C5: PRICE OF TIMBER | E5: TOTAL COST | F5: TVA | G5: MSF | H5: TVA+MSF
A6: PINUS NINI | E6: =PRODUCT(B6*C6) -> 0 | F6: =PRODUCT(E6*18)/118 -> 0 | G6: =PRODUCT(B6*50) -> 0 | H6: =SUM(F6:G6) -> 0
A7: PINUS NTOYA | E7: =PRODUCT(B7*C7) -> 0 | F7: =PRODUCT(E7*18)/118 -> 0 | G7: =PRODUCT(B7*50) -> 0 | H7: =SUM(F7:G7) -> 0
A8: PINUS | E8: =PRODUCT(B8*C8) -> 0 | F8: =PRODUCT(E8*18)/118 -> 0 | G8: =PRODUCT(B8*50) -> 0 | H8: =SUM(F8:G8) -> 0
A9: MADIRIYE NINI | E9: =PRODUCT(B9*C9) -> 0 | F9: =PRODUCT(E9*18)/118 -> 0 | G9: =PRODUCT(B9*30) -> 0 | H9: =SUM(F9:G9) -> 0
A10: MADIRIYE NTOYA | E10: =PRODUCT(B10*C10) -> 0 | F10: =PRODUCT(E10*18)/118 -> 0 | G10: =PRODUCT(B10*30) -> 0 | H10: =SUM(F10:G10) -> 0
A11: MADRIEN | C11: 2124 | E11: =PRODUCT(B11*C11) -> 0 | F11: =PRODUCT(E11*18)/118 -> 0 | G11: =PRODUCT(B11*30) -> 0 | H11: =SUM(F11:G11) -> 0
A12: MADRIEN | E12: =PRODUCT(B12*C12) -> 0 | F12: =PRODUCT(E12*18)/118 -> 0 | G12: =PRODUCT(B12*30) -> 0 | H12: =SUM(F12:G12) -> 0
A13: PLANCHE | E13: =PRODUCT(B13*C13) -> 0 | F13: =PRODUCT(E13*18)/118 -> 0 | G13: =PRODUCT(B13*20) -> 0 | H13: =SUM(F13:G13) -> 0
A14: PLANCHE | E14: =PRODUCT(B14*C14) -> 0 | F14: =PRODUCT(E14*18)/118 -> 0 | G14: =PRODUCT(B14*20) -> 0 | H14: =SUM(F14:G14) -> 0
A15: Other Timber for Difference Price
A16: NAME OF TIMBER | B16: No OF TIMBER | C16: P/U | D16: MSF | E16: TOTAL COST | F16: VAT | G16: MSF | H16: VTA+MST
A17: IBIPANDE | E17: =PRODUCT(B17*C17) -> 0 | F17: =PRODUCT(E17*18)/118 -> 0 | G17: =PRODUCT(B17*D17) -> 0 | H17: =SUM(F17:G17) -> 0
A18: PLANCHE | C18: 2360 | D18: 30 | E18: =PRODUCT(B18*C18) -> 0 | F18: =PRODUCT(E18*18)/118 -> 0 | G18: =PRODUCT(B18*D18) -> 0 | H18: =SUM(F18:G18) -> 0
A19: UMUSAVE | E19: =PRODUCT(B19*C19) -> 0 | F19: =PRODUCT(E19*18)/118 -> 0 | G19: =PRODUCT(B19*D19) -> 0 | H19: =SUM(F19:G19) -> 0
A20: UMUSAVE | E20: =PRODUCT(B20*C20) -> 0 | F20: =PRODUCT(E20*18)/118 -> 0 | G20: =PRODUCT(B20*D20) -> 0 | H20: =SUM(F20:G20) -> 0
A21: OTHER | E21: =PRODUCT(B21*C21) -> 0 | F21: =PRODUCT(E21*18)/118 -> 0 | G21: =PRODUCT(B21*D21) -> 0 | H21: =SUM(F21:G21) -> 0
A22: OTHER | E22: =PRODUCT(B22*C22) -> 0 | F22: =PRODUCT(E22*18)/118 -> 0 | G22: =PRODUCT(B22*D22) -> 0 | H22: =SUM(F22:G22) -> 0
A23: OTHER | E23: =PRODUCT(B23*C23) -> 0 | F23: =PRODUCT(E23*18)/118 -> 0 | G23: =PRODUCT(B23*D23) -> 0 | H23: =SUM(F23:G23) -> 0
A24: OTHER | E24: =PRODUCT(B24*C24) -> 0 | F24: =PRODUCT(E24*18)/118 -> 0 | G24: =PRODUCT(B24*D24) -> 0 | H24: =SUM(F24:G24) -> 0
A25: OTHER | E25: =PRODUCT(B25*C25) -> 0 | F25: =PRODUCT(E25*18)/118 -> 0 | G25: =PRODUCT(B25*D25) -> 0 | H25: =SUM(F25:G25) -> 0
A26: OTHER | E26: =PRODUCT(B26*C26) -> 0 | F26: =PRODUCT(E26*18)/118 -> 0 | G26: =PRODUCT(B26*D26) -> 0 | H26: =SUM(F26:G26) -> 0
A27: OTHER | E27: =PRODUCT(B27*C27) -> 0 | F27: =PRODUCT(E27*18)/118 -> 0 | G27: =PRODUCT(B27*D27) -> 0 | H27: =SUM(F27:G27) -> 0
A28: OTHER | E28: =PRODUCT(B28*C28) -> 0 | F28: =PRODUCT(E28*18)/118 -> 0 | G28: =PRODUCT(B28*D28) -> 0 | H28: =SUM(F28:G28) -> 0
A29: OTHER | E29: =PRODUCT(B29*C29) -> 0 | F29: =PRODUCT(E29*18)/118 -> 0 | G29: =PRODUCT(B29*D29) -> 0 | H29: =SUM(F29:G29) -> 0
A30: OTHER | E30: =PRODUCT(B30*C30) -> 0 | F30: =PRODUCT(E30*18)/118 -> 0 | G30: =PRODUCT(B30*D30) -> 0 | H30: =SUM(F30:G30) -> 0
... A36: OTHER | E36: =PRODUCT(B36*C36) -> 0 | F36: =PRODUCT(E36*18)/118 -> 0 | G36: =PRODUCT(B36*D36) -> 0 | H36: =SUM(F36:G36) -> 0
A37: TOTALY | E37: =SUM(E5:E36) -> 0 | F37: =SUM(F5:F36) -> 0 | G37: =SUM(G5:G36) -> 0 | H37: =SUM(H5:H36) -> 0
A38: SUMMARY | C38: RWF | E38: NAME | G38: Phone | H38: RWF
A39: TOTAL RWF PAID ON MOMO PAY
A40: TOTAL RWF PAID ON CASH
A41: AMOUNT NOT INVOICED
A42: TOTAL RWF DEPPOSITED ON BANK
A43: MEMBERSHIP FEES REGISTRETION
A44: MEMBERSHIP FEES CONTRIBUTION
A45: TOTAL INCOME | C45: =SUM(C39+C40+C41+C42+C43+C44) -> 0
A46: TIMBER SUMMARY
A48: REPORT SUMMARY | C48: TIMBER TYPE | E48: NUMBER OF QUANTITY
C49: INTURUSU | E49: =SUM(B9:B12) -> 0
C50: PINUS | E50: =SUM(B6:B8) -> 0
C51: PALNCHE | E51: =SUM(B13:B14) -> 0
C52: IBIPANDE | E52: =SUM(B17:B18) -> 0
C53: UMUSAVE | E53: =SUM(B19:B20) -> 0
C54: OTHER TYPE OF TIMBER | E54: =B29 -> 0
C55: OTHER TYPE OF TIMBER | E55: =B30 -> 0
C56: OTHER TYPE OF TIMBER | E56: =B31 -> 0
C57: OTHER TYPE OF TIMBER | E57: =B32 -> 0
C58: OTHER TYPE OF TIMBER | E58: =B33 -> 0
C59: OTHER TYPE OF TIMBER | E59: =B34 -> 0
C60: OTHER TYPE OF TIMBER | E60: =B35 -> 0
C61: OTHER TYPE OF TIMBER | E61: =B36 -> 0
C62: TOTAL TIMBER | E62: =SUM(E49:H61) -> 0

Sheet FOURTH
A1: QUANTITY REPORT
A3: MONTHS REPORT OF NOVEMBER 2025
A5: NAME OF TIMBER | B5: No OF TIMBER | C5: PRICE OF TIMBER | E5: TOTAL COST | F5: TVA | G5: MSF | H5: TVA+MSF
A6: PINUS NINI | E6: =PRODUCT(B6*C6) -> 0 | F6: =PRODUCT(E6*18)/118 -> 0 | G6: =PRODUCT(B6*50) -> 0 | H6: =SUM(F6:G6) -> 0
A7: PINUS NTOYA | E7: =PRODUCT(B7*C7) -> 0 | F7: =PRODUCT(E7*18)/118 -> 0 | G7: =PRODUCT(B7*50) -> 0 | H7: =SUM(F7:G7) -> 0
A8: PINUS | E8: =PRODUCT(B8*C8) -> 0 | F8: =PRODUCT(E8*18)/118 -> 0 | G8: =PRODUCT(B8*50) -> 0 | H8: =SUM(F8:G8) -> 0
A9: MADIRIYE NINI | E9: =PRODUCT(B9*C9) -> 0 | F9: =PRODUCT(E9*18)/118 -> 0 | G9: =PRODUCT(B9*30) -> 0 | H9: =SUM(F9:G9) -> 0
A10: MADIRIYE NTOYA | E10: =PRODUCT(B10*C10) -> 0 | F10: =PRODUCT(E10*18)/118 -> 0 | G10: =PRODUCT(B10*30) -> 0 | H10: =SUM(F10:G10) -> 0
A11: MADRIEN | E11: =PRODUCT(B11*C11) -> 0 | F11: =PRODUCT(E11*18)/118 -> 0 | G11: =PRODUCT(B11*30) -> 0 | H11: =SUM(F11:G11) -> 0
A12: MADRIEN | E12: =PRODUCT(B12*C12) -> 0 | F12: =PRODUCT(E12*18)/118 -> 0 | G12: =PRODUCT(B12*30) -> 0 | H12: =SUM(F12:G12) -> 0
A13: PLANCHE | E13: =PRODUCT(B13*C13) -> 0 | F13: =PRODUCT(E13*18)/118 -> 0 | G13: =PRODUCT(B13*20) -> 0 | H13: =SUM(F13:G13) -> 0
A14: PLANCHE | E14: =PRODUCT(B14*C14) -> 0 | F14: =PRODUCT(E14*18)/118 -> 0 | G14: =PRODUCT(B14*20) -> 0 | H14: =SUM(F14:G14) -> 0
A15: Other Timber for Difference Price
A16: NAME OF TIMBER | B16: No OF TIMBER | C16: P/U | D16: MSF | E16: TOTAL COST | F16: VAT | G16: MSF | H16: VTA+MST
A17: IBIPANDE | E17: =PRODUCT(B17*C17) -> 0 | F17: =PRODUCT(E17*18)/118 -> 0 | G17: =PRODUCT(B17*D17) -> 0 | H17: =SUM(F17:G17) -> 0
A18: IBIPANDE | E18: =PRODUCT(B18*C18) -> 0 | F18: =PRODUCT(E18*18)/118 -> 0 | G18: =PRODUCT(B18*D18) -> 0 | H18: =SUM(F18:G18) -> 0
A19: UMUSAVE | E19: =PRODUCT(B19*C19) -> 0 | F19: =PRODUCT(E19*18)/118 -> 0 | G19: =PRODUCT(B19*D19) -> 0 | H19: =SUM(F19:G19) -> 0
A20: UMUSAVE | E20: =PRODUCT(B20*C20) -> 0 | F20: =PRODUCT(E20*18)/118 -> 0 | G20: =PRODUCT(B20*D20) -> 0 | H20: =SUM(F20:G20) -> 0
A21: OTHER | E21: =PRODUCT(B21*C21) -> 0 | F21: =PRODUCT(E21*18)/118 -> 0 | G21: =PRODUCT(B21*D21) -> 0 | H21: =SUM(F21:G21) -> 0
A22: OTHER | E22: =PRODUCT(B22*C22) -> 0 | F22: =PRODUCT(E22*18)/118 -> 0 | G22: =PRODUCT(B22*D22) -> 0 | H22: =SUM(F22:G22) -> 0
A23: OTHER | E23: =PRODUCT(B23*C23) -> 0 | F23: =PRODUCT(E23*18)/118 -> 0 | G23: =PRODUCT(B23*D23) -> 0 | H23: =SUM(F23:G23) -> 0
A24: OTHER | E24: =PRODUCT(B24*C24) -> 0 | F24: =PRODUCT(E24*18)/118 -> 0 | G24: =PRODUCT(B24*D24) -> 0 | H24: =SUM(F24:G24) -> 0
A25: OTHER | E25: =PRODUCT(B25*C25) -> 0 | F25: =PRODUCT(E25*18)/118 -> 0 | G25: =PRODUCT(B25*D25) -> 0 | H25: =SUM(F25:G25) -> 0
A26: OTHER | E26: =PRODUCT(B26*C26) -> 0 | F26: =PRODUCT(E26*18)/118 -> 0 | G26: =PRODUCT(B26*D26) -> 0 | H26: =SUM(F26:G26) -> 0
A27: OTHER | E27: =PRODUCT(B27*C27) -> 0 | F27: =PRODUCT(E27*18)/118 -> 0 | G27: =PRODUCT(B27*D27) -> 0 | H27: =SUM(F27:G27) -> 0
A28: OTHER | E28: =PRODUCT(B28*C28) -> 0 | F28: =PRODUCT(E28*18)/118 -> 0 | G28: =PRODUCT(B28*D28) -> 0 | H28: =SUM(F28:G28) -> 0
... A36: OTHER | E36: =PRODUCT(B36*C36) -> 0 | F36: =PRODUCT(E36*18)/118 -> 0 | G36: =PRODUCT(B36*D36) -> 0 | H36: =SUM(F36:G36) -> 0
A37: TOTALY | E37: =SUM(E5:E36) -> 0 | F37: =SUM(F5:F36) -> 0 | G37: =SUM(G5:G36) -> 0 | H37: =SUM(H5:H36) -> 0
A38: SUMMARY | C38: RWF | E38: NAME | G38: Phone | H38: RWF
A39: TOTAL RWF PAID ON MOMO PAY
A40: TOTAL RWF PAID ON CASH
A41: AMOUNT NOT INVOICED
A42: TOTAL RWF DEPPOSITED ON BANK
A43: MEMBERSHIP FEES REGISTRETION
A44: MEMBERSHIP FEES CONTRIBUTION
A45: TOTAL INCOME | C45: =SUM(C39+C40+C41+C42+C43+C44) -> 0
A46: TIMBER SUMMARY
A48: REPORT SUMMARY | C48: TIMBER TYPE | E48: NUMBER OF QUANTITY
C49: INTURUSU | E49: =SUM(B9:B12) -> 0
C50: PINUS | E50: =SUM(B6:B8) -> 0
C51: PALNCHE | E51: =SUM(B13:B14) -> 0
C52: IBIPANDE | E52: =SUM(B17:B18) -> 0
C53: UMUSAVE | E53: =SUM(B19:B20) -> 0
C54: OTHER TYPE OF TIMBER | E54: =B29 -> 0
C55: OTHER TYPE OF TIMBER | E55: =B30 -> 0
C56: OTHER TYPE OF TIMBER | E56: =B31 -> 0
C57: OTHER TYPE OF TIMBER | E57: =B32 -> 0
C58: OTHER TYPE OF TIMBER | E58: =B33 -> 0
C59: OTHER TYPE OF TIMBER | E59: =B34 -> 0
C60: OTHER TYPE OF TIMBER | E60: =B35 -> 0
C61: OTHER TYPE OF TIMBER | E61: =B36 -> 0
C62: TOTAL TIMBER | E62: =SUM(E49:H61) -> 0

Sheet ALL TIMBER SUMMARY
A1: TIMBER SUMMARY
A3: TIMBER TYPE | D3: NUMBER OF QUANTITY
A4: INTURUSU | D4: =NYANZA!E49+KIREHE!E49+NYAGATARE!E49+KAYONZA!E49+MUSANZE!E49+MUSANZE!E49+RUBAVU!E49+KARONGI!E49+NYAMAGABE!E49+RUSIZI!E49+HUYE!E49+RUHANGO!E49+MUHANGA!E49+BUGESERA!E49+RWAMAGANA!E49+NYARUGENGE!E49+BISHENYI!E49+GAHANGA!E49+KIMIRONKO!E49+GISOZI!E69+GATSIBO!E49+GASHYUSHYA!E49+RUTSIRO!E49+NGORORERO!E49+NYAMASHEKE!E49+FOURTH!E49 -> 1021531
A5: PINUS | D5: =NYANZA!E50+KIREHE!E50+NYAGATARE!E50+KAYONZA!E50+MUSANZE!E50+MUSANZE!E50+RUBAVU!E50+KARONGI!E50+NYAMAGABE!E50+RUSIZI!E50+HUYE!E50+RUHANGO!E50+MUHANGA!E50+BUGESERA!E50+RWAMAGANA!E50+NYARUGENGE!E50+BISHENYI!E50+GAHANGA!E50+KIMIRONKO!E50+GISOZI!E70+GATSIBO!E50+GASHYUSHYA!E50+RUTSIRO!E50+NGORORERO!E50+NYAMASHEKE!E50+FOURTH!E50 -> 45069
A6: PLANCHE | D6: =NYANZA!E51+KIREHE!E51+NYAGATARE!E51+KAYONZA!E51+MUSANZE!E51+MUSANZE!E51+RUBAVU!E51+KARONGI!E51+NYAMAGABE!E51+RUSIZI!E51+HUYE!E51+RUHANGO!E51+MUHANGA!E51+BUGESERA!E51+RWAMAGANA!E51+NYARUGENGE!E51+BISHENYI!E51+GAHANGA!E51+KIMIRONKO!E51+GISOZI!E71+GATSIBO!E51+GASHYUSHYA!E51+RUTSIRO!E51+NGORORERO!E51+NYAMASHEKE!E51+FOURTH!E51 -> 85520
A7: IBIPANDE | D7: =NYANZA!E52+KIREHE!E52+NYAGATARE!E52+KAYONZA!E52+MUSANZE!E52+MUSANZE!E52+RUBAVU!E52+KARONGI!E52+NYAMAGABE!E52+RUSIZI!E52+HUYE!E52+RUHANGO!E52+MUHANGA!E52+BUGESERA!E52+RWAMAGANA!E52+NYARUGENGE!E52+BISHENYI!E52+GAHANGA!E52+KIMIRONKO!E52+GISOZI!E72+GATSIBO!E52+GASHYUSHYA!E52+RUTSIRO!E52+NGORORERO!E52+NYAMASHEKE!E52+FOURTH!E52 -> 45912
A8: UMUSAVE | D8: =NYANZA!E53+KIREHE!E53+NYAGATARE!E53+KAYONZA!E53+MUSANZE!E53+MUSANZE!E53+RUBAVU!E53+KARONGI!E53+NYAMAGABE!E53+RUSIZI!E53+HUYE!E53+RUHANGO!E53+MUHANGA!E53+BUGESERA!E53+RWAMAGANA!E53+NYARUGENGE!E53+BISHENYI!E53+GAHANGA!E53+KIMIRONKO!E53+GISOZI!E73+GATSIBO!E53+GASHYUSHYA!E53+RUTSIRO!E53+NGORORERO!E53+NYAMASHEKE!E53+FOURTH!E53 -> 23338
A9: OTHER TYPE OF TIMBER | D9: =NYANZA!E54+KIREHE!E54+NYAGATARE!E54+KAYONZA!E54+MUSANZE!E54+MUSANZE!E54+RUBAVU!E54+KARONGI!E54+NYAMAGABE!E54+RUSIZI!E54+HUYE!E54+RUHANGO!E54+MUHANGA!E54+BUGESERA!E54+RWAMAGANA!E54+NYARUGENGE!E54+BISHENYI!E54+GAHANGA!E54+KIMIRONKO!E54+GISOZI!E74+GATSIBO!E54+GASHYUSHYA!E54+RUTSIRO!E54+NGORORERO!E54+NYAMASHEKE!E54+FOURTH!E54 -> 9882
A10: OTHER TYPE OF TIMBER | D10: =NYANZA!E55+KIREHE!E55+NYAGATARE!E55+KAYONZA!E55+MUSANZE!E55+MUSANZE!E55+RUBAVU!E55+KARONGI!E55+NYAMAGABE!E55+RUSIZI!E55+HUYE!E55+RUHANGO!E55+MUHANGA!E55+BUGESERA!E55+RWAMAGANA!E55+NYARUGENGE!E55+BISHENYI!E55+GAHANGA!E55+KIMIRONKO!E55+GISOZI!E75+GATSIBO!E55+GASHYUSHYA!E55+RUTSIRO!E55+NGORORERO!E55+NYAMASHEKE!E55+FOURTH!E55 -> 100
A11: OTHER TYPE OF TIMBER | D11: =NYANZA!E56+KIREHE!E56+NYAGATARE!E56+KAYONZA!E56+MUSANZE!E56+MUSANZE!E56+RUBAVU!E56+KARONGI!E56+NYAMAGABE!E56+RUSIZI!E56+HUYE!E56+RUHANGO!E56+MUHANGA!E56+BUGESERA!E56+RWAMAGANA!E56+NYARUGENGE!E56+BISHENYI!E56+GAHANGA!E56+KIMIRONKO!E56+GISOZI!E76+GATSIBO!E56+GASHYUSHYA!E56+RUTSIRO!E56+NGORORERO!E56+NYAMASHEKE!E56+FOURTH!E56 -> 8592
A12: OTHER TYPE OF TIMBER | D12: =NYANZA!E57+KIREHE!E57+NYAGATARE!E57+KAYONZA!E57+MUSANZE!E57+MUSANZE!E57+RUBAVU!E57+KARONGI!E57+NYAMAGABE!E57+RUSIZI!E57+HUYE!E57+RUHANGO!E57+MUHANGA!E57+BUGESERA!E57+RWAMAGANA!E57+NYARUGENGE!E57+BISHENYI!E57+GAHANGA!E57+KIMIRONKO!E57+GISOZI!E77+GATSIBO!E57+GASHYUSHYA!E57+RUTSIRO!E57+NGORORERO!E57+NYAMASHEKE!E57+FOURTH!E57 -> 0
A13: OTHER TYPE OF TIMBER | D13: =NYANZA!E58+KIREHE!E58+NYAGATARE!E58+KAYONZA!E58+MUSANZE!E58+MUSANZE!E58+RUBAVU!E58+KARONGI!E58+NYAMAGABE!E58+RUSIZI!E58+HUYE!E58+RUHANGO!E58+MUHANGA!E58+BUGESERA!E58+RWAMAGANA!E58+NYARUGENGE!E58+BISHENYI!E58+GAHANGA!E58+KIMIRONKO!E58+GISOZI!E78+GATSIBO!E58+GASHYUSHYA!E58+RUTSIRO!E58+NGORORERO!E58+NYAMASHEKE!E58+FOURTH!E58 -> 0
A14: OTHER TYPE OF TIMBER | D14: =NYANZA!E59+KIREHE!E59+NYAGATARE!E59+KAYONZA!E59+MUSANZE!E59+MUSANZE!E59+RUBAVU!E59+KARONGI!E59+NYAMAGABE!E59+RUSIZI!E59+HUYE!E59+RUHANGO!E59+MUHANGA!E59+BUGESERA!E59+RWAMAGANA!E59+NYARUGENGE!E59+BISHENYI!E59+GAHANGA!E59+KIMIRONKO!E59+GISOZI!E79+GATSIBO!E59+GASHYUSHYA!E59+RUTSIRO!E59+NGORORERO!E59+NYAMASHEKE!E59+FOURTH!E59 -> 0
A15: OTHER TYPE OF TIMBER | D15: =NYANZA!E60+KIREHE!E60+NYAGATARE!E60+KAYONZA!E60+MUSANZE!E60+MUSANZE!E60+RUBAVU!E60+KARONGI!E60+NYAMAGABE!E60+RUSIZI!E60+HUYE!E60+RUHANGO!E60+MUHANGA!E60+BUGESERA!E60+RWAMAGANA!E60+NYARUGENGE!E60+BISHENYI!E60+GAHANGA!E60+KIMIRONKO!E60+GISOZI!E80+GATSIBO!E60+GASHYUSHYA!E60+RUTSIRO!E60+NGORORERO!E60+NYAMASHEKE!E60+FOURTH!E60 -> 0
A16: OTHER TYPE OF TIMBER | D16: =NYANZA!E61+KIREHE!E61+NYAGATARE!E61+KAYONZA!E61+MUSANZE!E61+MUSANZE!E61+RUBAVU!E61+KARONGI!E61+NYAMAGABE!E61+RUSIZI!E61+HUYE!E61+RUHANGO!E61+MUHANGA!E61+BUGESERA!E61+RWAMAGANA!E61+NYARUGENGE!E61+BISHENYI!E61+GAHANGA!E61+KIMIRONKO!E61+GISOZI!E81+GATSIBO!E61+GASHYUSHYA!E61+RUTSIRO!E61+NGORORERO!E61+NYAMASHEKE!E61+FOURTH!E61 -> 0
A17: TOTAL TIMBER | D17: =SUM(D4:D16) -> 1239944
